Workbook

Sheet Cover
B2: PROJECT ZENITH — SALES WORKSTREAM | INITIATIVE MODELS & WAVE TEMPLATES
B4: Workstream | C4: Sales — 2 priority initiatives: (1) Underwriting & Pricing for front book, (2) SMB Long Tail — Partner. ELT sponsor: Susan | WSL: Selwyn. LE and MM initiatives follow the Track 2 timeline.
B5: Purpose | C5: One file per workstream: each initiative has a Model sheet (all logic and inputs) formula-linked into its own copy of the standard WAVE business-case template. S2 submission: Sep 4; S3: Sep 18.
B6: Version / status | C6: v1 — structure complete; impact-driver rates seeded from Aug 13 / Board decks (midpoints), revenue/seller baselines to be populated from received + pending datasets (models compute $0 until baselines are entered).
B7: Prepared | C7: Prepared by AAO model build, 31 Aug 2026. Sources: Project Zenith workplan vS_1; Zenith Business Case Template by Lever (WAVE); Aug 13 deck pp. 6, 14–15; Board deck pp. 9, 20, 52.
B8: Sources | C8: Workplan Sales tab (initiative-specific data POV); Sales Data Requests tab (4 of 6 received); WAVE standard template (reference copy at the end of this file).
B10: HOW THIS FILE IS ORGANIZED
B12: Cover | C12: This sheet — orientation, legend, deviations, open items.
B13: Instructions | C13: The WAVE template's own instruction sheet (as uploaded; dead broken-reference drop-down cells cleared).
B14: Rate Card | C14: Shared people-cost engine: rate basis, role table + blended rate, contingency reference, capitalization policy.
B15: Summary | C15: Portfolio roll-up of both initiatives (links to WAVE sheets).
B16: SALES-1 Model / SALES-1 WAVE | C16: Underwriting & Pricing front book — model + linked WAVE template.
B17: SALES-2 Model / SALES-2 WAVE | C17: SMB Long Tail — Partner — model + linked WAVE template.
B18: Standard Template | C18: Reference copy of the standard WAVE template (only error-guard fixes applied — see deviations).
B20: COLOR LEGEND
B22: Input — change freely
B23: Formula — do not overwrite
B24: Link to another sheet
B25: Section band
B27: MODEL -> WAVE LINKING
B29: • Each initiative has a '<code> Model' sheet (all logic and inputs) and a '<code> WAVE' sheet (the standard template). The WAVE sheet contains NO hardcoded numbers for this initiative — its benefit/cost rows link (green) to the Model sheet's feed rows in $M.
B30: • Model sheets use the same time grid as WAVE: columns L:P = FY2026–2030 annual, columns T:CA = Jan-2026..Dec-2030 monthly. Annual cells are SUMIFS of the monthly grid, so the WAVE monthly-vs-annual checks (CI1:CM1) pass by construction.
B31: • The 'Ann. Run Rate' (K) on feed rows is defined as the 2030 value, matching the WAVE rule 'Annualized Run Rate (K) = 2030 Value (P)'. Keep ramps reaching 100% before 2030.
B32: • Benefits ramp linearly from the go-live date over 'months to full run rate' — same convention as the Servicing S2 model. One-time costs spread evenly over each milestone's billing months.
B33: • People costs: milestone labor = Team size x Billing months x blended monthly rate (Rate Card) x (1 + contingency). Capitalization: each milestone carries a Cap % (default from Rate Card policy) that splits labor into WAVE CapEx vs OTC rows. Same for non-labor one-time items.
B35: DEVIATIONS FROM THE STANDARD WAVE TEMPLATE (documented fixes)
... B52: • Rate Card role rates are placeholders; capitalization defaults need Finance sign-off.

Sheet Instructions
L1: 1 | M1: 2 | N1: 3 | O1: 4 | P1: 5 | R1: =COUNTIFS($R$78:$R$128, "Error") -> 0 | T1: 2026 | U1: 2026 | V1: 2026 | W1: 2026 | X1: 2026 | Y1: 2026 | Z1: 2026 | AA1: 2026 | AB1: 2026 | AC1: 2026 | AD1: 2026 | AE1: 2026 | AF1: 2027 | AG1: 2027 | AH1: 2027 | AI1: 2027 | AJ1: 2027 | AK1: 2027 | AL1: 2027 | AM1: 2027 | AN1: 2027 | AO1: 2027 | AP1: 2027 | AQ1: 2027 | AR1: 2028 | AS1: 2028 | AT1: 2028 | AU1: 2028 | AV1: 2028 | AW1: 2028 | AX1: 2028 | AY1: 2028 | AZ1: 2028 | BA1: 2028 | BB1: 2028 | BC1: 2028 | BD1: 2029 | BE1: 2029 | BF1: 2029 | BG1: 2029 | BH1: 2029 | BI1: 2029 | BJ1: 2029 | BK1: 2029 | BL1: 2029 | BM1: 2029 | BN1: 2029 | BO1: 2029 | BP1: 2030 | BQ1: 2030 | BR1: 2030 | BS1: 2030 | BT1: 2030 | BU1: 2030 | BV1: 2030 | BW1: 2030 | BX1: 2030 | BY1: 2030 | BZ1: 2030 | CA1: 2030 | CI1: =COUNTIFS(CI$78:CI$159, "FALSE") -> 0 | CJ1: =COUNTIFS(CJ$78:CJ$159, "FALSE") -> 4 | CK1: =COUNTIFS(CK$78:CK$159, "FALSE") -> 4 | CL1: =COUNTIFS(CL$78:CL$159, "FALSE") -> 0 | CM1: =COUNTIFS(CM$78:CM$159, "FALSE") -> 0
C9: ="#"&$F$13&" Initiative Business Case" -> #123456 Initiative Business Case
C11: INPUTS & ASSUMPTIONS
D13: Initiative # | F13: 123456
D14: Initiative Owner | F14: John Smith
D15: Initiative Name | F15: Leverage agentic AI for customer service and care centers, reducing number of calls handled by live customer care agents and increasing productivity | I15: Names - 5-7 words
I16: Descriptions - 10-20 words
D18: Estimated L4 date | F18: 46736
D19: Net Recurring Benefit ($M) | F19: =$K$128 -> 7.2
C21: SECTION I - PRIMARY VALUE DRIVER (ILLUSTRATIVE) | L21: CHECKS
D23: Illustrative example of value driver explanation - please edit fields to reflect value drivers for your Initiative | L23: Criteria (Column Reference) | P23: Check | Q23: Troubleshoot:
D24: Baseline | H24: Period | I24: KPI | J24: Inputs | L24: (A) Annualized Run Rate (K) = 2030 Value (P) | P24: =IF($R$1=0, "PASS", "ERROR") -> PASS | Q24: =IF(P24="Error", "Check column R for errors", "")
E25: # of calls handled by live agents | G25: [A] | H25: FY2025 | I25: # of calls | J25: 6000 | L25: (B) 2026 Value (L) = Sum of Monthly 2026 Values (CC) | P25: =IF($CI$1=0, "PASS", "ERROR") -> PASS | Q25: =IF(P25="Error", "Check column CI for errors", "")
E26: AHT | G26: [B] | H26: FY 2026 | I26: Seconds | J26: 150 | L26: (C) 2027 Value (M) = Sum of Monthly 2027 Values (CD) | P26: =IF($CJ$1=0, "PASS", "ERROR") -> ERROR | Q26: =IF(P26="Error", "Check column CJ for errors", "") -> Check column CJ for errors
E27: # of live agents handling calls | G27: [C] | H27: FY 2025 | I27: # of live agents | J27: 500 | L27: (D) 2028 Value (N) = Sum of Monthly 2028 Values (CE) | P27: =IF($CK$1=0, "PASS", "ERROR") -> ERROR | Q27: =IF(P27="Error", "Check column CK for errors", "") -> Check column CK for errors
E28: Average cost per agent | H28: FY 2026 | I28: $ / agent | J28: 50000 | L28: (E) 2029 Value (O) = Sum of Monthly 2029 Values (CF) | P28: =IF($CL$1=0, "PASS", "ERROR") -> PASS | Q28: =IF(P28="Error", "Check column CL for errors", "")
E29: Total spend on contact center for queue X | G29: [D] | H29: FY2025 | I29: $USD M | J29: =(J27*J28)/1000000 -> 25 | L29: (F) 2030 Value (P) = Sum of Monthly 2030 Values (CG) | P29: =IF($CM$1=0, "PASS", "ERROR") -> PASS | Q29: =IF(P29="Error", "Check column CM for errors", "")
D31: Goal | Y31: D
E32: # of calls handled by live agents | G32: [E] | I32: # of calls | J32: 4000
E33: AHT | G33: [F] | I33: Seconds | J33: 120
E34: # of live agents handling calls | G34: [G] | I34: # of live agents | J34: 260
E35: Average cost per agent | I35: $ / agent | J35: =J28 -> 50000
E36: Total spend on contact center for queue X | G36: [H] | H36: FY2026 | I36: $USD M | J36: =(J34*J35)/1000000 -> 13
D38: Incremental Improvement
E39: # of calls handled by live agents | G39: [A]-[E] | I39: # of calls | J39: =J25-J32 -> 2000
E40: AHT | G40: [B]-[F] | I40: Seconds | J40: =J26-J33 -> 30
E41: # of live agents handling calls | G41: [C]-[G] | I41: # of live agents | J41: =J27-J34 -> 240
E42: Total spend on contact center queue X | G42: [D]-[H] | I42: USD M | J42: =J29-J36 -> 12
D43: Baseline | H43: Period | I43: $USD M | J43: Inputs
E44: # xxxx | H44: FY2025 | I44: # xxxx | J44: 12000000
E45: xxxx unit cost | G45: [A] | H45: FY2025 | I45: $ xxxx | J45: 0.14
E46: xxxx total spend | G46: [B] | H46: FY2025 | I46: $USD K | J46: =(J44*J45)/1000 -> 1680
D48: Goal
E49: # xxxx | H49: FY2025 | I49: # xxxx | J49: =$J$25 -> 6000
E50: xxxx unit cost | G50: [C] | H50: FY2026 | I50: $ xxxx | J50: 0.1
E51: xxxx total spend | G51: [D] | H51: FY2026 | I51: $USD K | J51: =(J49*J50)/1000 -> 0.6
D53: Incremental Improvement
E54: =E50 -> xxxx unit cost | G54: [A]-[C] | I54: $ / xxxx | J54: =J45-J50 -> 0.04
E55: =E51 -> xxxx total spend | G55: [B]-[D] | I55: $USD K | J55: =J46-J51 -> 1679.4
D58: Baseline | H58: Period | I58: KPI | J58: Inputs
E59: # xxxx | H59: FY2025 | I59: # xxxx | J59: 12000000
E60: xxxx unit cost | G60: [A] | H60: FY2025 | I60: $ xxxx | J60: 0.14
E61: xxxx total spend | G61: [B] | H61: FY2025 | I61: $USD K | J61: =(J59*J60)/1000 -> 1680
D63: Goal
E64: # xxxx | H64: FY2025 | I64: # xxxx | J64: =$J$25 -> 6000
E65: xxxx unit cost | G65: [C] | H65: FY2026 | I65: $ xxxx | J65: 0.1
E66: xxxx total spend | G66: [D] | H66: FY2026 | I66: $USD K | J66: =(J64*J65)/1000 -> 0.6
D68: Incremental Improvement
E69: =E65 -> xxxx unit cost | G69: [A]-[C] | I69: $ / xxxx | J69: =J60-J65 -> 0.04
E70: =E66 -> xxxx total spend | G70: [B]-[D] | I70: $USD K | J70: =J61-J66 -> 1679.4
C73: SECTION II - NET RECURRING BENEFITS | CC73: ANNUAL SUMMARY | CI73: CHECK CELLS
D75: RECURRING BENEFITS | H75: Comment | I75: Baseline | J75: Goal | K75: Ann. Run Rate | L75: 2026 | M75: =L75+1 -> 2027 | N75: =M75+1 -> 2028 | O75: =N75+1 -> 2029 | P75: =O75+1 -> 2030 | Q75: Impacted BU | R75: Check | T75: 46023 | U75: =EOMONTH(T75, 1) -> 46081 | V75: =EOMONTH(U75, 1) -> 46112 | W75: =EOMONTH(V75, 1) -> 46142 | X75: =EOMONTH(W75, 1) -> 46173 | Y75: =EOMONTH(X75, 1) -> 46203 | Z75: =EOMONTH(Y75, 1) -> 46234 | AA75: =EOMONTH(Z75, 1) -> 46265 | AB75: =EOMONTH(AA75, 1) -> 46295 | ... CA75: =EOMONTH(BZ75, 1) -> 47848 | CC75: 2026 | CD75: =CC75+1 -> 2027 | CE75: =CD75+1 -> 2028 | CF75: =CE75+1 -> 2029 | CG75: =CF75+1 -> 2030 | CI75: 2026 | CJ75: =CI75+1 -> 2027 | CK75: =CJ75+1 -> 2028 | CL75: =CK75+1 -> 2029 | CM75: =CL75+1 -> 2030
E76: $USD M | I76: FY25 Hist. | J76: Future State | K76: Increment
E77: Revenue
I78: 0 | J78: 0 | K78: =J78-I78 -> 0 | R78: =IF(K78=P78, "", "Error") | CC78: =SUMIFS($T78:$CA78, $T$1:$CA$1, CC$75) -> 0 | CD78: =SUMIFS($T78:$CA78, $T$1:$CA$1, CD$75) -> 0 | CE78: =SUMIFS($T78:$CA78, $T$1:$CA$1, CE$75) -> 0 | CF78: =SUMIFS($T78:$CA78, $T$1:$CA$1, CF$75) -> 0 | CG78: =SUMIFS($T78:$CA78, $T$1:$CA$1, CG$75) -> 0 | CI78: =CC78=L78 -> 1 | CJ78: =CD78=M78 -> 1 | CK78: =CE78=N78 -> 1 | CL78: =CF78=O78 -> 1 | CM78: =CG78=P78 -> 1
I79: 0 | J79: 0 | K79: =J79-I79 -> 0 | R79: =IF(K79=P79, "", "Error") | CC79: =SUMIFS($T79:$CA79, $T$1:$CA$1, CC$75) -> 0 | CD79: =SUMIFS($T79:$CA79, $T$1:$CA$1, CD$75) -> 0 | CE79: =SUMIFS($T79:$CA79, $T$1:$CA$1, CE$75) -> 0 | CF79: =SUMIFS($T79:$CA79, $T$1:$CA$1, CF$75) -> 0 | CG79: =SUMIFS($T79:$CA79, $T$1:$CA$1, CG$75) -> 0 | CI79: =CC79=L79 -> 1 | CJ79: =CD79=M79 -> 1 | CK79: =CE79=N79 -> 1 | CL79: =CF79=O79 -> 1 | CM79: =CG79=P79 -> 1
E80: Revenue Subtotal | I80: =SUM(I78:I79) -> 0 | J80: =SUM(J78:J79) -> 0 | K80: =SUM(K78:K79) -> 0 | L80: =SUM(L78:L79) -> 0 | M80: =SUM(M78:M79) -> 0 | N80: =SUM(N78:N79) -> 0 | O80: =SUM(O78:O79) -> 0 | P80: =SUM(P78:P79) -> 0 | T80: =SUM(T78:T79) -> 0 | U80: =SUM(U78:U79) -> 0 | V80: =SUM(V78:V79) -> 0 | W80: =SUM(W78:W79) -> 0 | X80: =SUM(X78:X79) -> 0 | Y80: =SUM(Y78:Y79) -> 0 | Z80: =SUM(Z78:Z79) -> 0 | AA80: =SUM(AA78:AA79) -> 0 | ... CA80: =SUM(CA78:CA79) -> 0 | CC80: =SUM(CC78:CC79) -> 0 | CD80: =SUM(CD78:CD79) -> 0 | CE80: =SUM(CE78:CE79) -> 0 | CF80: =SUM(CF78:CF79) -> 0 | CG80: =SUM(CG78:CG79) -> 0 | CI80: =CC80=L80 -> 1 | CJ80: =CD80=M80 -> 1 | CK80: =CE80=N80 -> 1 | CL80: =CF80=O80 -> 1 | CM80: =CG80=P80 -> 1
E82: Cost of Sales
K83: =I83-J83 -> 0 | R83: =IF(K83=P83, "", "Error") | CC83: =SUMIFS($T83:$CA83, $T$1:$CA$1, CC$75) -> 0 | CD83: =SUMIFS($T83:$CA83, $T$1:$CA$1, CD$75) -> 0 | CE83: =SUMIFS($T83:$CA83, $T$1:$CA$1, CE$75) -> 0 | CF83: =SUMIFS($T83:$CA83, $T$1:$CA$1, CF$75) -> 0 | CG83: =SUMIFS($T83:$CA83, $T$1:$CA$1, CG$75) -> 0 | CI83: =CC83=L83 -> 1 | CJ83: =CD83=M83 -> 1 | CK83: =CE83=N83 -> 1 | CL83: =CF83=O83 -> 1 | CM83: =CG83=P83 -> 1
I84: 0 | J84: 0 | K84: =I84-J84 -> 0 | R84: =IF(K84=P84, "", "Error") | CC84: =SUMIFS($T84:$CA84, $T$1:$CA$1, CC$75) -> 0 | CD84: =SUMIFS($T84:$CA84, $T$1:$CA$1, CD$75) -> 0 | CE84: =SUMIFS($T84:$CA84, $T$1:$CA$1, CE$75) -> 0 | CF84: =SUMIFS($T84:$CA84, $T$1:$CA$1, CF$75) -> 0 | CG84: =SUMIFS($T84:$CA84, $T$1:$CA$1, CG$75) -> 0 | CI84: =CC84=L84 -> 1 | CJ84: =CD84=M84 -> 1 | CK84: =CE84=N84 -> 1 | CL84: =CF84=O84 -> 1 | CM84: =CG84=P84 -> 1
I85: 0 | J85: 0 | K85: =I85-J85 -> 0 | R85: =IF(K85=P85, "", "Error") | CC85: =SUMIFS($T85:$CA85, $T$1:$CA$1, CC$75) -> 0 | CD85: =SUMIFS($T85:$CA85, $T$1:$CA$1, CD$75) -> 0 | CE85: =SUMIFS($T85:$CA85, $T$1:$CA$1, CE$75) -> 0 | CF85: =SUMIFS($T85:$CA85, $T$1:$CA$1, CF$75) -> 0 | CG85: =SUMIFS($T85:$CA85, $T$1:$CA$1, CG$75) -> 0 | CI85: =CC85=L85 -> 1 | CJ85: =CD85=M85 -> 1 | CK85: =CE85=N85 -> 1 | CL85: =CF85=O85 -> 1 | CM85: =CG85=P85 -> 1
I86: 0 | J86: 0 | K86: =I86-J86 -> 0 | R86: =IF(K86=P86, "", "Error") | CC86: =SUMIFS($T86:$CA86, $T$1:$CA$1, CC$75) -> 0 | CD86: =SUMIFS($T86:$CA86, $T$1:$CA$1, CD$75) -> 0 | CE86: =SUMIFS($T86:$CA86, $T$1:$CA$1, CE$75) -> 0 | CF86: =SUMIFS($T86:$CA86, $T$1:$CA$1, CF$75) -> 0 | CG86: =SUMIFS($T86:$CA86, $T$1:$CA$1, CG$75) -> 0 | CI86: =CC86=L86 -> 1 | CJ86: =CD86=M86 -> 1 | CK86: =CE86=N86 -> 1 | CL86: =CF86=O86 -> 1 | CM86: =CG86=P86 -> 1
K87: =I87-J87 -> 0 | R87: =IF(K87=P87, "", "Error") | CC87: =SUMIFS($T87:$CA87, $T$1:$CA$1, CC$75) -> 0 | CD87: =SUMIFS($T87:$CA87, $T$1:$CA$1, CD$75) -> 0 | CE87: =SUMIFS($T87:$CA87, $T$1:$CA$1, CE$75) -> 0 | CF87: =SUMIFS($T87:$CA87, $T$1:$CA$1, CF$75) -> 0 | CG87: =SUMIFS($T87:$CA87, $T$1:$CA$1, CG$75) -> 0 | CI87: =CC87=L87 -> 1 | CJ87: =CD87=M87 -> 1 | CK87: =CE87=N87 -> 1 | CL87: =CF87=O87 -> 1 | CM87: =CG87=P87 -> 1
E88: Cost of Sales Subtotal | I88: =SUM(I83:I87) -> 0 | J88: =SUM(J83:J87) -> 0 | K88: =SUM(K83:K87) -> 0 | L88: =SUM(L83:L87) -> 0 | M88: =SUM(M83:M87) -> 0 | N88: =SUM(N83:N87) -> 0 | O88: =SUM(O83:O87) -> 0 | P88: =SUM(P83:P87) -> 0 | T88: =SUM(T83:T87) -> 0 | U88: =SUM(U83:U87) -> 0 | V88: =SUM(V83:V87) -> 0 | W88: =SUM(W83:W87) -> 0 | X88: =SUM(X83:X87) -> 0 | Y88: =SUM(Y83:Y87) -> 0 | Z88: =SUM(Z83:Z87) -> 0 | AA88: =SUM(AA83:AA87) -> 0 | ... CA88: =SUM(CA83:CA87) -> 0 | CC88: =SUM(CC83:CC87) -> 0 | CD88: =SUM(CD83:CD87) -> 0 | CE88: =SUM(CE83:CE87) -> 0 | CF88: =SUM(CF83:CF87) -> 0 | CG88: =SUM(CG83:CG87) -> 0 | CI88: =CC88=L88 -> 1 | CJ88: =CD88=M88 -> 1 | CK88: =CE88=N88 -> 1 | CL88: =CF88=O88 -> 1 | CM88: =CG88=P88 -> 1
E90: OPEX
E91: OPEX - Temporary Workers | I91: =J29 -> 25 | J91: =J36 -> 13 | K91: =I91-J91 -> 12 | N91: =K91 -> 12 | O91: =N91 -> 12 | P91: =O91 -> 12 | Q91: Global Risk | R91: =IF(K91=P91, "", "Error") | AR91: =$P$91/12 -> 1 | AS91: =$P$91/12 -> 1 | AT91: =$P$91/12 -> 1 | AU91: =$P$91/12 -> 1 | AV91: =$P$91/12 -> 1 | AW91: =$P$91/12 -> 1 | AX91: =$P$91/12 -> 1 | AY91: =$P$91/12 -> 1 | ... CA91: =$P$91/12 -> 1 | CB91: =20/12 -> 1.6666667 | CC91: =SUMIFS($T91:$CA91, $T$1:$CA$1, CC$75) -> 0 | CE91: =SUMIFS($T91:$CA91, $T$1:$CA$1, CE$75) -> 12 | CF91: =SUMIFS($T91:$CA91, $T$1:$CA$1, CF$75) -> 12 | CG91: =SUMIFS($T91:$CA91, $T$1:$CA$1, CG$75) -> 12 | CI91: =CC91=L91 -> 1 | CJ91: =CD91=M91 -> 1 | CK91: =CE91=N91 -> 1 | CL91: =CF91=O91 -> 1 | CM91: =CG91=P91 -> 1
I92: 0 | J92: 0 | K92: =I92-J92 -> 0 | R92: =IF(K92=P92, "", "Error") | CC92: =SUMIFS($T92:$CA92, $T$1:$CA$1, CC$75) -> 0 | CD92: =SUMIFS($T92:$CA92, $T$1:$CA$1, CD$75) -> 0 | CE92: =SUMIFS($T92:$CA92, $T$1:$CA$1, CE$75) -> 0 | CF92: =SUMIFS($T92:$CA92, $T$1:$CA$1, CF$75) -> 0 | CG92: =SUMIFS($T92:$CA92, $T$1:$CA$1, CG$75) -> 0 | CI92: =CC92=L92 -> 1 | CJ92: =CD92=M92 -> 1 | CK92: =CE92=N92 -> 1 | CL92: =CF92=O92 -> 1 | CM92: =CG92=P92 -> 1
I93: 0 | J93: 0 | K93: =I93-J93 -> 0 | R93: =IF(K93=P93, "", "Error") | CC93: =SUMIFS($T93:$CA93, $T$1:$CA$1, CC$75) -> 0 | CD93: =SUMIFS($T93:$CA93, $T$1:$CA$1, CD$75) -> 0 | CE93: =SUMIFS($T93:$CA93, $T$1:$CA$1, CE$75) -> 0 | CF93: =SUMIFS($T93:$CA93, $T$1:$CA$1, CF$75) -> 0 | CG93: =SUMIFS($T93:$CA93, $T$1:$CA$1, CG$75) -> 0 | CI93: =CC93=L93 -> 1 | CJ93: =CD93=M93 -> 1 | CK93: =CE93=N93 -> 1 | CL93: =CF93=O93 -> 1 | CM93: =CG93=P93 -> 1
I94: 0 | J94: 0 | K94: =I94-J94 -> 0 | R94: =IF(K94=P94, "", "Error") | CC94: =SUMIFS($T94:$CA94, $T$1:$CA$1, CC$75) -> 0 | CD94: =SUMIFS($T94:$CA94, $T$1:$CA$1, CD$75) -> 0 | CE94: =SUMIFS($T94:$CA94, $T$1:$CA$1, CE$75) -> 0 | CF94: =SUMIFS($T94:$CA94, $T$1:$CA$1, CF$75) -> 0 | CG94: =SUMIFS($T94:$CA94, $T$1:$CA$1, CG$75) -> 0 | CI94: =CC94=L94 -> 1 | CJ94: =CD94=M94 -> 1 | CK94: =CE94=N94 -> 1 | CL94: =CF94=O94 -> 1 | CM94: =CG94=P94 -> 1
I95: 0 | J95: 0 | K95: =I95-J95 -> 0 | R95: =IF(K95=P95, "", "Error") | CC95: =SUMIFS($T95:$CA95, $T$1:$CA$1, CC$75) -> 0 | CD95: =SUMIFS($T95:$CA95, $T$1:$CA$1, CD$75) -> 0 | CE95: =SUMIFS($T95:$CA95, $T$1:$CA$1, CE$75) -> 0 | CF95: =SUMIFS($T95:$CA95, $T$1:$CA$1, CF$75) -> 0 | CG95: =SUMIFS($T95:$CA95, $T$1:$CA$1, CG$75) -> 0 | CI95: =CC95=L95 -> 1 | CJ95: =CD95=M95 -> 1 | CK95: =CE95=N95 -> 1 | CL95: =CF95=O95 -> 1 | CM95: =CG95=P95 -> 1
E96: OpEx subtotal | I96: =SUM(I91:I95) -> 25 | J96: =SUM(J91:J95) -> 13 | K96: =SUM(K91:K95) -> 12 | L96: =SUM(L91:L95) -> 0 | M96: =SUM(M91:M95) -> 0 | N96: =SUM(N91:N95) -> 12 | O96: =SUM(O91:O95) -> 12 | P96: =SUM(P91:P95) -> 12 | T96: =SUM(T91:T95) -> 0 | U96: =SUM(U91:U95) -> 0 | V96: =SUM(V91:V95) -> 0 | W96: =SUM(W91:W95) -> 0 | X96: =SUM(X91:X95) -> 0 | Y96: =SUM(Y91:Y95) -> 0 | Z96: =SUM(Z91:Z95) -> 0 | AA96: =SUM(AA91:AA95) -> 0 | ... CA96: =SUM(CA91:CA95) -> 1 | CC96: =SUM(CC91:CC95) -> 0 | CD96: =SUM(CD91:CD95) -> 0 | CE96: =SUM(CE91:CE95) -> 12 | CF96: =SUM(CF91:CF95) -> 12 | CG96: =SUM(CG91:CG95) -> 12 | CI96: =CC96=L96 -> 1 | CJ96: =CD96=M96 -> 1 | CK96: =CE96=N96 -> 1 | CL96: =CF96=O96 -> 1 | CM96: =CG96=P96 -> 1
E100: Recurring Benefits Total | I100: =SUM(I80, I88, I96) -> 25 | J100: =SUM(J80, J88, J96) -> 13 | K100: =SUM(-K80, K88, K96) -> 12 | L100: =SUM(L80, L88, L96) -> 0 | M100: =SUM(M80, M88, M96) -> 0 | N100: =SUM(N80, N88, N96) -> 12 | O100: =SUM(O80, O88, O96) -> 12 | P100: =SUM(P80, P88, P96) -> 12 | T100: =SUM(T80, T88, T96) -> 0 | U100: =SUM(U80, U88, U96) -> 0 | V100: =SUM(V80, V88, V96) -> 0 | W100: =SUM(W80, W88, W96) -> 0 | X100: =SUM(X80, X88, X96) -> 0 | Y100: =SUM(Y80, Y88, Y96) -> 0 | Z100: =SUM(Z80, Z88, Z96) -> 0 | AA100: =SUM(AA80, AA88, AA96) -> 0 | ... CA100: =SUM(CA80, CA88, CA96) -> 1 | CC100: =SUM(CC80, CC88, CC96) -> 0 | CD100: =SUM(CD80, CD88, CD96) -> 0 | CE100: =SUM(CE80, CE88, CE96) -> 12 | CF100: =SUM(CF80, CF88, CF96) -> 12 | CG100: =SUM(CG80, CG88, CG96) -> 12 | CH100: =SUM(CH80, CH88, CH96) -> 0 | CI100: =CC100=L100 -> 1 | CJ100: =CD100=M100 -> 1 | CK100: =CE100=N100 -> 1 | CL100: =CF100=O100 -> 1 | CM100: =CG100=P100 -> 1
D102: RECURRING COSTS TO ACHIEVE IMPACT | H102: Comment | I102: Baseline | J102: Goal | K102: Ann. Run Rate | L102: 2026 | M102: =L102+1 -> 2027 | N102: =M102+1 -> 2028 | O102: =N102+1 -> 2029 | P102: =O102+1 -> 2030 | Q102: Impacted BU | R102: Check | T102: 46023 | U102: =EOMONTH(T102, 1) -> 46081 | V102: =EOMONTH(U102, 1) -> 46112 | W102: =EOMONTH(V102, 1) -> 46142 | X102: =EOMONTH(W102, 1) -> 46173 | Y102: =EOMONTH(X102, 1) -> 46203 | Z102: =EOMONTH(Y102, 1) -> 46234 | AA102: =EOMONTH(Z102, 1) -> 46265 | AB102: =EOMONTH(AA102, 1) -> 46295 | ... CA102: =EOMONTH(BZ102, 1) -> 47848 | CC102: 2026 | CD102: =CC102+1 -> 2027 | CE102: =CD102+1 -> 2028 | CF102: =CE102+1 -> 2029 | CG102: =CF102+1 -> 2030 | CI102: 2026 | CJ102: =CI102+1 -> 2027 | CK102: =CJ102+1 -> 2028 | CL102: =CK102+1 -> 2029 | CM102: =CL102+1 -> 2030
E103: $USD M | I103: FY25 Hist. | J103: Future State | K103: Increment
E104: Revenue
I105: 0 | J105: 0 | K105: =J105-I105 -> 0 | R105: =IF(K105=P105, "", "Error") | CC105: =SUMIFS($T105:$CA105, $T$1:$CA$1, CC$75) -> 0 | CD105: =SUMIFS($T105:$CA105, $T$1:$CA$1, CD$75) -> 0 | CE105: =SUMIFS($T105:$CA105, $T$1:$CA$1, CE$75) -> 0 | CF105: =SUMIFS($T105:$CA105, $T$1:$CA$1, CF$75) -> 0 | CG105: =SUMIFS($T105:$CA105, $T$1:$CA$1, CG$75) -> 0 | CI105: =CC105=L105 -> 1 | CJ105: =CD105=M105 -> 1 | CK105: =CE105=N105 -> 1 | CL105: =CF105=O105 -> 1 | CM105: =CG105=P105 -> 1
I106: 0 | J106: 0 | K106: =J106-I106 -> 0 | R106: =IF(K106=P106, "", "Error") | CC106: =SUMIFS($T106:$CA106, $T$1:$CA$1, CC$75) -> 0 | CD106: =SUMIFS($T106:$CA106, $T$1:$CA$1, CD$75) -> 0 | CE106: =SUMIFS($T106:$CA106, $T$1:$CA$1, CE$75) -> 0 | CF106: =SUMIFS($T106:$CA106, $T$1:$CA$1, CF$75) -> 0 | CG106: =SUMIFS($T106:$CA106, $T$1:$CA$1, CG$75) -> 0 | CI106: =CC106=L106 -> 1 | CJ106: =CD106=M106 -> 1 | CK106: =CE106=N106 -> 1 | CL106: =CF106=O106 -> 1 | CM106: =CG106=P106 -> 1
E107: Revenue Subtotal | I107: =SUM(I105:I106) -> 0 | J107: =SUM(J105:J106) -> 0 | K107: =SUM(K105:K106) -> 0 | L107: =SUM(L105:L106) -> 0 | M107: =SUM(M105:M106) -> 0 | N107: =SUM(N105:N106) -> 0 | O107: =SUM(O105:O106) -> 0 | P107: =SUM(P105:P106) -> 0 | T107: =SUM(T105:T106) -> 0 | U107: =SUM(U105:U106) -> 0 | V107: =SUM(V105:V106) -> 0 | W107: =SUM(W105:W106) -> 0 | X107: =SUM(X105:X106) -> 0 | Y107: =SUM(Y105:Y106) -> 0 | Z107: =SUM(Z105:Z106) -> 0 | AA107: =SUM(AA105:AA106) -> 0 | ... CA107: =SUM(CA105:CA106) -> 0 | CC107: =SUM(CC105:CC106) -> 0 | CD107: =SUM(CD105:CD106) -> 0 | CE107: =SUM(CE105:CE106) -> 0 | CF107: =SUM(CF105:CF106) -> 0 | CG107: =SUM(CG105:CG106) -> 0 | CI107: =CC107=L107 -> 1 | CJ107: =CD107=M107 -> 1 | CK107: =CE107=N107 -> 1 | CL107: =CF107=O107 -> 1 | CM107: =CG107=P107 -> 1
E109: Cost of Sales
I110: 0 | J110: 0 | K110: =J110-I110 -> 0 | R110: =IF(K110=P110, "", "Error") | CC110: =SUMIFS($T110:$CA110, $T$1:$CA$1, CC$75) -> 0 | CD110: =SUMIFS($T110:$CA110, $T$1:$CA$1, CD$75) -> 0 | CE110: =SUMIFS($T110:$CA110, $T$1:$CA$1, CE$75) -> 0 | CF110: =SUMIFS($T110:$CA110, $T$1:$CA$1, CF$75) -> 0 | CG110: =SUMIFS($T110:$CA110, $T$1:$CA$1, CG$75) -> 0 | CI110: =CC110=L110 -> 1 | CJ110: =CD110=M110 -> 1 | CK110: =CE110=N110 -> 1 | CL110: =CF110=O110 -> 1 | CM110: =CG110=P110 -> 1
I111: 0 | J111: 0 | K111: =J111-I111 -> 0 | R111: =IF(K111=P111, "", "Error") | CC111: =SUMIFS($T111:$CA111, $T$1:$CA$1, CC$75) -> 0 | CD111: =SUMIFS($T111:$CA111, $T$1:$CA$1, CD$75) -> 0 | CE111: =SUMIFS($T111:$CA111, $T$1:$CA$1, CE$75) -> 0 | CF111: =SUMIFS($T111:$CA111, $T$1:$CA$1, CF$75) -> 0 | CG111: =SUMIFS($T111:$CA111, $T$1:$CA$1, CG$75) -> 0 | CI111: =CC111=L111 -> 1 | CJ111: =CD111=M111 -> 1 | CK111: =CE111=N111 -> 1 | CL111: =CF111=O111 -> 1 | CM111: =CG111=P111 -> 1
I112: 0 | J112: 0 | K112: =J112-I112 -> 0 | R112: =IF(K112=P112, "", "Error") | CC112: =SUMIFS($T112:$CA112, $T$1:$CA$1, CC$75) -> 0 | CD112: =SUMIFS($T112:$CA112, $T$1:$CA$1, CD$75) -> 0 | CE112: =SUMIFS($T112:$CA112, $T$1:$CA$1, CE$75) -> 0 | CF112: =SUMIFS($T112:$CA112, $T$1:$CA$1, CF$75) -> 0 | CG112: =SUMIFS($T112:$CA112, $T$1:$CA$1, CG$75) -> 0 | CI112: =CC112=L112 -> 1 | CJ112: =CD112=M112 -> 1 | CK112: =CE112=N112 -> 1 | CL112: =CF112=O112 -> 1 | CM112: =CG112=P112 -> 1
I113: 0 | J113: 0 | K113: =J113-I113 -> 0 | R113: =IF(K113=P113, "", "Error") | CC113: =SUMIFS($T113:$CA113, $T$1:$CA$1, CC$75) -> 0 | CD113: =SUMIFS($T113:$CA113, $T$1:$CA$1, CD$75) -> 0 | CE113: =SUMIFS($T113:$CA113, $T$1:$CA$1, CE$75) -> 0 | CF113: =SUMIFS($T113:$CA113, $T$1:$CA$1, CF$75) -> 0 | CG113: =SUMIFS($T113:$CA113, $T$1:$CA$1, CG$75) -> 0 | CI113: =CC113=L113 -> 1 | CJ113: =CD113=M113 -> 1 | CK113: =CE113=N113 -> 1 | CL113: =CF113=O113 -> 1 | CM113: =CG113=P113 -> 1
E115: Cost of Sales Subtotal | I115: =SUM(I110:I114) -> 0 | J115: =SUM(J110:J114) -> 0 | K115: =SUM(K110:K114) -> 0 | L115: =SUM(L110:L114) -> 0 | M115: =SUM(M110:M114) -> 0 | N115: =SUM(N110:N114) -> 0 | O115: =SUM(O110:O114) -> 0 | P115: =SUM(P110:P114) -> 0 | T115: =SUM(T110:T114) -> 0 | U115: =SUM(U110:U114) -> 0 | V115: =SUM(V110:V114) -> 0 | W115: =SUM(W110:W114) -> 0 | X115: =SUM(X110:X114) -> 0 | Y115: =SUM(Y110:Y114) -> 0 | Z115: =SUM(Z110:Z114) -> 0 | AA115: =SUM(AA110:AA114) -> 0 | ... CA115: =SUM(CA110:CA114) -> 0 | CC115: =SUM(CC110:CC114) -> 0 | CD115: =SUM(CD110:CD114) -> 0 | CE115: =SUM(CE110:CE114) -> 0 | CF115: =SUM(CF110:CF114) -> 0 | CG115: =SUM(CG110:CG114) -> 0 | CI115: =CC115=L115 -> 1 | CJ115: =CD115=M115 -> 1 | CK115: =CE115=N115 -> 1 | CL115: =CF115=O115 -> 1 | CM115: =CG115=P115 -> 1
E117: OPEX
E118: OPEX - SaaS SW | H118: Platform licencing & LLM inference | I118: 0 | J118: 3.6 | K118: =J118-I118 -> 3.6 | N118: 3.6 | O118: 3.6 | P118: 3.6 | R118: =IF(K118=P118, "", "Error") | AR118: =3.6/12 -> 0.3 | AS118: =3.6/12 -> 0.3 | AT118: =3.6/12 -> 0.3 | AU118: =3.6/12 -> 0.3 | AV118: =3.6/12 -> 0.3 | AW118: =3.6/12 -> 0.3 | AX118: =3.6/12 -> 0.3 | AY118: =3.6/12 -> 0.3 | ... CA118: =3.6/12 -> 0.3 | CC118: =SUMIFS($T118:$CA118, $T$1:$CA$1, CC$75) -> 0 | CD118: =SUMIFS($T118:$CA118, $T$1:$CA$1, CD$75) -> 0 | CE118: =SUMIFS($T118:$CA118, $T$1:$CA$1, CE$75) -> 3.6 | CF118: =SUMIFS($T118:$CA118, $T$1:$CA$1, CF$75) -> 3.6 | CG118: =SUMIFS($T118:$CA118, $T$1:$CA$1, CG$75) -> 3.6 | CI118: =CC118=L118 -> 1 | CJ118: =CD118=M118 -> 1 | CK118: =CE118=N118 -> 1 | CL118: =CF118=O118 -> 1 | CM118: =CG118=P118 -> 1
E119: OPEX - Cloud Services | H119: Cloud infra | I119: 0 | J119: 1.2 | K119: =J119-I119 -> 1.2 | M119: 1.2 | N119: 1.2 | O119: 1.2 | P119: 1.2 | R119: =IF(K119=P119, "", "Error") | AF119: =1.2/12 -> 0.1 | AG119: =1.2/12 -> 0.1 | AH119: =1.2/12 -> 0.1 | AI119: =1.2/12 -> 0.1 | AJ119: =1.2/12 -> 0.1 | AK119: =1.2/12 -> 0.1 | AL119: =1.2/12 -> 0.1 | AM119: =1.2/12 -> 0.1 | ... CA119: =1.2/12 -> 0.1 | CC119: =SUMIFS($T119:$CA119, $T$1:$CA$1, CC$75) -> 0 | CD119: =SUMIFS($T119:$CA119, $T$1:$CA$1, CD$75) -> 1.2 | CE119: =SUMIFS($T119:$CA119, $T$1:$CA$1, CE$75) -> 1.2 | CF119: =SUMIFS($T119:$CA119, $T$1:$CA$1, CF$75) -> 1.2 | CG119: =SUMIFS($T119:$CA119, $T$1:$CA$1, CG$75) -> 1.2 | CI119: =CC119=L119 -> 1 | CJ119: =CD119=M119 -> 1 | CK119: =CE119=N119 -> 1 | CL119: =CF119=O119 -> 1 | CM119: =CG119=P119 -> 1
CC120: =SUMIFS($T120:$CA120, $T$1:$CA$1, CC$75) -> 0 | CD120: =SUMIFS($T120:$CA120, $T$1:$CA$1, CD$75) -> 0 | CE120: =SUMIFS($T120:$CA120, $T$1:$CA$1, CE$75) -> 0 | CF120: =SUMIFS($T120:$CA120, $T$1:$CA$1, CF$75) -> 0 | CG120: =SUMIFS($T120:$CA120, $T$1:$CA$1, CG$75) -> 0 | CI120: =CC120=L120 -> 1 | CJ120: =CD120=M120 -> 1 | CK120: =CE120=N120 -> 1 | CL120: =CF120=O120 -> 1 | CM120: =CG120=P120 -> 1
J121: 0 | K121: =J121-I121 -> 0 | R121: =IF(K121=P121, "", "Error") | CC121: =SUMIFS($T121:$CA121, $T$1:$CA$1, CC$75) -> 0 | CD121: =SUMIFS($T121:$CA121, $T$1:$CA$1, CD$75) -> 0 | CE121: =SUMIFS($T121:$CA121, $T$1:$CA$1, CE$75) -> 0 | CF121: =SUMIFS($T121:$CA121, $T$1:$CA$1, CF$75) -> 0 | CG121: =SUMIFS($T121:$CA121, $T$1:$CA$1, CG$75) -> 0 | CI121: =CC121=L121 -> 1 | CJ121: =CD121=M121 -> 1 | CK121: =CE121=N121 -> 1 | CL121: =CF121=O121 -> 1 | CM121: =CG121=P121 -> 1
I122: 0 | J122: 0 | K122: =J122-I122 -> 0 | R122: =IF(K122=P122, "", "Error") | CC122: =SUMIFS($T122:$CA122, $T$1:$CA$1, CC$75) -> 0 | CD122: =SUMIFS($T122:$CA122, $T$1:$CA$1, CD$75) -> 0 | CE122: =SUMIFS($T122:$CA122, $T$1:$CA$1, CE$75) -> 0 | CF122: =SUMIFS($T122:$CA122, $T$1:$CA$1, CF$75) -> 0 | CG122: =SUMIFS($T122:$CA122, $T$1:$CA$1, CG$75) -> 0 | CI122: =CC122=L122 -> 1 | CJ122: =CD122=M122 -> 1 | CK122: =CE122=N122 -> 1 | CL122: =CF122=O122 -> 1 | CM122: =CG122=P122 -> 1
E123: OpEx subtotal | I123: =SUM(I118:I122) -> 0 | J123: =SUM(J118:J122) -> 4.8 | K123: =SUM(K118:K122) -> 4.8 | L123: =SUM(L118:L122) -> 0 | M123: =SUM(M118:M122) -> 1.2 | N123: =SUM(N118:N122) -> 4.8 | O123: =SUM(O118:O122) -> 4.8 | P123: =SUM(P118:P122) -> 4.8 | T123: =SUM(T118:T122) -> 0 | U123: =SUM(U118:U122) -> 0 | V123: =SUM(V118:V122) -> 0 | W123: =SUM(W118:W122) -> 0 | X123: =SUM(X118:X122) -> 0 | Y123: =SUM(Y118:Y122) -> 0 | Z123: =SUM(Z118:Z122) -> 0 | AA123: =SUM(AA118:AA122) -> 0 | ... CA123: =SUM(CA118:CA122) -> 0.4 | CC123: =SUM(CC118:CC122) -> 0 | CD123: =SUM(CD118:CD122) -> 1.2 | CE123: =SUM(CE118:CE122) -> 4.8 | CF123: =SUM(CF118:CF122) -> 4.8 | CG123: =SUM(CG118:CG122) -> 4.8 | CI123: =CC123=L123 -> 1 | CJ123: =CD123=M123 -> 1 | CK123: =CE123=N123 -> 1 | CL123: =CF123=O123 -> 1 | CM123: =CG123=P123 -> 1
E126: Recurring Costs Total | I126: =SUM(-I107, I115, I123) -> 0 | J126: =SUM(-J107, J115, J123) -> 4.8 | K126: =SUM(-K107, K115, K123) -> 4.8 | L126: =SUM(-L107, L115, L123) -> 0 | M126: =SUM(-M107, M115, M123) -> 1.2 | N126: =SUM(-N107, N115, N123) -> 4.8 | O126: =SUM(-O107, O115, O123) -> 4.8 | P126: =SUM(-P107, P115, P123) -> 4.8 | T126: =SUM(-T107, T115, T123) -> 0 | U126: =SUM(-U107, U115, U123) -> 0 | V126: =SUM(-V107, V115, V123) -> 0 | W126: =SUM(-W107, W115, W123) -> 0 | X126: =SUM(-X107, X115, X123) -> 0 | Y126: =SUM(-Y107, Y115, Y123) -> 0 | Z126: =SUM(-Z107, Z115, Z123) -> 0 | AA126: =SUM(-AA107, AA115, AA123) -> 0 | ... CA126: =SUM(-CA107, CA115, CA123) -> 0.4 | CC126: =SUM(-CC107, CC115, CC123) -> 0 | CD126: =SUM(-CD107, CD115, CD123) -> 1.2 | CE126: =SUM(-CE107, CE115, CE123) -> 4.8 | CF126: =SUM(-CF107, CF115, CF123) -> 4.8 | CG126: =SUM(-CG107, CG115, CG123) -> 4.8 | CI126: =CC126=L126 -> 1 | CJ126: =CD126=M126 -> 1 | CK126: =CE126=N126 -> 1 | CL126: =CF126=O126 -> 1 | CM126: =CG126=P126 -> 1
E128: Net Recurring Benefit | I128: =SUM(I100, -I126) -> 25 | J128: =SUM(J100, -J126) -> 8.2 | K128: =SUM(K100, -K126) -> 7.2 | L128: =SUM(L100, -L126) -> 0 | M128: =SUM(M100, -M126) -> -1.2 | N128: =SUM(N100, -N126) -> 7.2 | O128: =SUM(O100, -O126) -> 7.2 | P128: =SUM(P100, -P126) -> 7.2 | R128: =IF(K128=P128, "", "Error") | T128: =SUM(T100, -T126) -> 0 | U128: =SUM(U100, -U126) -> 0 | V128: =SUM(V100, -V126) -> 0 | W128: =SUM(W100, -W126) -> 0 | X128: =SUM(X100, -X126) -> 0 | Y128: =SUM(Y100, -Y126) -> 0 | Z128: =SUM(Z100, -Z126) -> 0 | AA128: =SUM(AA100, -AA126) -> 0 | ... CA128: =SUM(CA100, -CA126) -> 0.6 | CC128: =SUM(CC100, -CC126) -> 0 | CD128: =SUM(CD100, -CD126) -> -1.2 | CE128: =SUM(CE100, -CE126) -> 7.2 | CF128: =SUM(CF100, -CF126) -> 7.2 | CG128: =SUM(CG100, -CG126) -> 7.2 | CI128: =CC128=L128 -> 1 | CJ128: =CD128=M128 -> 1 | CK128: =CE128=N128 -> 1 | CL128: =CF128=O128 -> 1 | CM128: =CG128=P128 -> 1
C131: SECTION III - ONE-TIME IMPLEMENTATION | CC131: ANNUAL SUMMARY | CI131: CHECK CELLS
T133: 2026 | AF133: 2027 | AR133: 2028 | BD133: 2029 | BP133: 2030
D134: ONE-TIME BENEFITS | K134: Comment | L134: 2026 | M134: =L134+1 -> 2027 | N134: =M134+1 -> 2028 | O134: =N134+1 -> 2029 | P134: =O134+1 -> 2030 | Q134: Impacted BU | T134: 46023 | U134: =EOMONTH(T134, 1) -> 46081 | V134: =EOMONTH(U134, 1) -> 46112 | W134: =EOMONTH(V134, 1) -> 46142 | X134: =EOMONTH(W134, 1) -> 46173 | Y134: =EOMONTH(X134, 1) -> 46203 | Z134: =EOMONTH(Y134, 1) -> 46234 | AA134: =EOMONTH(Z134, 1) -> 46265 | AB134: =EOMONTH(AA134, 1) -> 46295 | ... CA134: =EOMONTH(BZ134, 1) -> 47848 | CC134: 2026 | CD134: =CC134+1 -> 2027 | CE134: =CD134+1 -> 2028 | CF134: =CE134+1 -> 2029 | CG134: =CF134+1 -> 2030 | CI134: 2026 | CJ134: =CI134+1 -> 2027 | CK134: =CJ134+1 -> 2028 | CL134: =CK134+1 -> 2029 | CM134: =CL134+1 -> 2030
E136: Working Capital
CC137: =SUMIFS($T137:$CA137, $T$1:$CA$1, CC$75) -> 0 | CD137: =SUMIFS($T137:$CA137, $T$1:$CA$1, CD$75) -> 0 | CE137: =SUMIFS($T137:$CA137, $T$1:$CA$1, CE$75) -> 0 | CF137: =SUMIFS($T137:$CA137, $T$1:$CA$1, CF$75) -> 0 | CG137: =SUMIFS($T137:$CA137, $T$1:$CA$1, CG$75) -> 0 | CI137: =CC137=L137 -> 1 | CJ137: =CD137=M137 -> 1 | CK137: =CE137=N137 -> 1 | CL137: =CF137=O137 -> 1 | CM137: =CG137=P137 -> 1
CC138: =SUMIFS($T138:$CA138, $T$1:$CA$1, CC$75) -> 0 | CD138: =SUMIFS($T138:$CA138, $T$1:$CA$1, CD$75) -> 0 | CE138: =SUMIFS($T138:$CA138, $T$1:$CA$1, CE$75) -> 0 | CF138: =SUMIFS($T138:$CA138, $T$1:$CA$1, CF$75) -> 0 | CG138: =SUMIFS($T138:$CA138, $T$1:$CA$1, CG$75) -> 0 | CI138: =CC138=L138 -> 1 | CJ138: =CD138=M138 -> 1 | CK138: =CE138=N138 -> 1 | CL138: =CF138=O138 -> 1 | CM138: =CG138=P138 -> 1
E139: Working Capital Subtotal | L139: =SUM(L137:L138) -> 0 | M139: =SUM(M137:M138) -> 0 | N139: =SUM(N137:N138) -> 0 | O139: =SUM(O137:O138) -> 0 | P139: =SUM(P137:P138) -> 0 | T139: =SUM(T137:T138) -> 0 | U139: =SUM(U137:U138) -> 0 | V139: =SUM(V137:V138) -> 0 | W139: =SUM(W137:W138) -> 0 | X139: =SUM(X137:X138) -> 0 | Y139: =SUM(Y137:Y138) -> 0 | Z139: =SUM(Z137:Z138) -> 0 | AA139: =SUM(AA137:AA138) -> 0 | ... CA139: =SUM(CA137:CA138) -> 0 | CC139: =SUM(CC137:CC138) -> 0 | CD139: =SUM(CD137:CD138) -> 0 | CE139: =SUM(CE137:CE138) -> 0 | CF139: =SUM(CF137:CF138) -> 0 | CG139: =SUM(CG137:CG138) -> 0 | CI139: =CC139=L139 -> 1 | CJ139: =CD139=M139 -> 1 | CK139: =CE139=N139 -> 1 | CL139: =CF139=O139 -> 1 | CM139: =CG139=P139 -> 1
...

Sheet Rate Card
B2: RATE CARD — people-cost engine (shared by all initiative models)
B4: Blue cells with yellow fill = inputs you can change. Black = formulas. All initiative models pull the blended rate and policy tables from this sheet.
B6: 1. RATE BASIS
B8: Rate basis for people costs | D8: Yearly | F8: Choose how role rates are quoted, then TYPE YOUR RATES in the matching column of the role table below (Yearly->col D, Monthly->col E, Hourly->col F). The other columns show derived equivalents until you overwrite them. Hourly => monthly = $/hr x hours/day x days/month.
B10: Working hours per day | D10: 8 | F10: Used only when rate basis = Hourly.
B11: Billable days per month | D11: 21
B12: Months per year (for yearly basis) | D12: 12
B14: 2. STANDARD TEAM COMPOSITION & BLENDED RATE
B16: Role | C16: # in std team | D16: Yearly rate ($/yr) | E16: Monthly rate ($/mo) | F16: Hourly rate ($/hr) | G16: Monthly used ($/mo) | H16: Team cost ($/mo) | I16: Source / notes
B17: Engineer | C17: 3 | D17: 180000 | E17: =IF(D17="",0,D17/$D$12) -> 15000 | F17: =IF(D17="",0,E17/($D$10*$D$11)) -> 89.285714 | G17: =IF($D$8="Hourly",F17*$D$10*$D$11,IF($D$8="Monthly",E17,IF(D17="",0,D17/$D$12))) -> 15000 | H17: =IF(C17="",0,C17*G17) -> 45000
B18: QA Engineer | C18: 2 | D18: 140000 | E18: =IF(D18="",0,D18/$D$12) -> 11666.667 | F18: =IF(D18="",0,E18/($D$10*$D$11)) -> 69.444444 | G18: =IF($D$8="Hourly",F18*$D$10*$D$11,IF($D$8="Monthly",E18,IF(D18="",0,D18/$D$12))) -> 11666.667 | H18: =IF(C18="",0,C18*G18) -> 23333.333
B19: Solution Architect | C19: 1 | D19: 220000 | E19: =IF(D19="",0,D19/$D$12) -> 18333.333 | F19: =IF(D19="",0,E19/($D$10*$D$11)) -> 109.12698 | G19: =IF($D$8="Hourly",F19*$D$10*$D$11,IF($D$8="Monthly",E19,IF(D19="",0,D19/$D$12))) -> 18333.333 | H19: =IF(C19="",0,C19*G19) -> 18333.333
B20: Product Manager | C20: 1 | D20: 190000 | E20: =IF(D20="",0,D20/$D$12) -> 15833.333 | F20: =IF(D20="",0,E20/($D$10*$D$11)) -> 94.246032 | G20: =IF($D$8="Hourly",F20*$D$10*$D$11,IF($D$8="Monthly",E20,IF(D20="",0,D20/$D$12))) -> 15833.333 | H20: =IF(C20="",0,C20*G20) -> 15833.333
B21: Data Engineer | C21: 1 | D21: 185000 | E21: =IF(D21="",0,D21/$D$12) -> 15416.667 | F21: =IF(D21="",0,E21/($D$10*$D$11)) -> 91.765873 | G21: =IF($D$8="Hourly",F21*$D$10*$D$11,IF($D$8="Monthly",E21,IF(D21="",0,D21/$D$12))) -> 15416.667 | H21: =IF(C21="",0,C21*G21) -> 15416.667
B22: ML Engineer | C22: 1 | D22: 210000 | E22: =IF(D22="",0,D22/$D$12) -> 17500 | F22: =IF(D22="",0,E22/($D$10*$D$11)) -> 104.16667 | G22: =IF($D$8="Hourly",F22*$D$10*$D$11,IF($D$8="Monthly",E22,IF(D22="",0,D22/$D$12))) -> 17500 | H22: =IF(C22="",0,C22*G22) -> 17500
B23: Program Manager | C23: 1 | D23: 170000 | E23: =IF(D23="",0,D23/$D$12) -> 14166.667 | F23: =IF(D23="",0,E23/($D$10*$D$11)) -> 84.325397 | G23: =IF($D$8="Hourly",F23*$D$10*$D$11,IF($D$8="Monthly",E23,IF(D23="",0,D23/$D$12))) -> 14166.667 | H23: =IF(C23="",0,C23*G23) -> 14166.667
E24: =IF(D24="",0,D24/$D$12) -> 0 | F24: =IF(D24="",0,E24/($D$10*$D$11)) -> 0 | G24: =IF($D$8="Hourly",F24*$D$10*$D$11,IF($D$8="Monthly",E24,IF(D24="",0,D24/$D$12))) -> 0 | H24: =IF(C24="",0,C24*G24) -> 0 | I24: spare row — add roles as team shape is refined
E25: =IF(D25="",0,D25/$D$12) -> 0 | F25: =IF(D25="",0,E25/($D$10*$D$11)) -> 0 | G25: =IF($D$8="Hourly",F25*$D$10*$D$11,IF($D$8="Monthly",E25,IF(D25="",0,D25/$D$12))) -> 0 | H25: =IF(C25="",0,C25*G25) -> 0 | I25: spare row — add roles as team shape is refined
E26: =IF(D26="",0,D26/$D$12) -> 0 | F26: =IF(D26="",0,E26/($D$10*$D$11)) -> 0 | G26: =IF($D$8="Hourly",F26*$D$10*$D$11,IF($D$8="Monthly",E26,IF(D26="",0,D26/$D$12))) -> 0 | H26: =IF(C26="",0,C26*G26) -> 0 | I26: spare row — add roles as team shape is refined
B27: Total standard team | C27: =SUM(C17:C26) -> 10 | H27: =SUM(H17:H26) -> 149583.33
B29: BLENDED RATE — per team member | G29: =IF(C27=0,0,H27/C27) -> 14958.333 | H29: $/person/month | I29: Weighted average monthly cost of one member of the standard team. Initiative milestone tables use this unless a rate override is entered.
G30: =G29*$D$12 -> 179500 | H30: $/person/year
G31: =G29/($D$10*$D$11) -> 89.037698 | H31: $/person/hour
B33: 3. CONTINGENCY FACTOR REFERENCE
B35: Complexity / risk level | C35: Factor | F35: Based on the complexity and risks to deliver the milestone.
B36: Low | C36: 0.1
B37: Medium | C37: 0.15
B38: High | C38: 0.2
B39: Very high | C39: 0.5
B42: 4. CAPITALIZATION POLICY (labor) — default % of milestone labor capitalizable
B44: Milestone | C44: Cap % | F44: Share of labor cost treated as CapEx (feeds WAVE 'Capital Expenditures'); remainder is expensed one-time cost (WAVE 'OTC'). Defaults follow a typical internal-use software policy (ASC 350-40): application development/build stage capitalizable, planning and post-launch expensed. CONFIRM WITH FINANCE — initiative models reference these cells, override there if needed.
B45: Plan / Design | C45: 0
B46: Build / Test | C46: 0.8
B47: Pilot / Change Mgmt. | C47: 0
B48: Scale / Run | C48: 0
B49: Non-labor one-time (default) | C49: 0
B51: 5. NOTES
B52: • Role rates are PLACEHOLDERS — replace with the PayPal/FP&A rate card. Servicing S2 reference: $200,000/yr blended loaded delivery FTE (+10% delivery risk), $180,000/yr run-team FTE.
B53: • Team composition mirrors the standard AAO delivery-pod thinking; adjust for vendor-heavy builds (PRM/orchestration) where internal pod may be smaller.
B54: • Build/Test capitalization default of 80% follows a typical internal-use software policy — CONFIRM WITH FINANCE, especially for vendor/SaaS-heavy builds where treatment differs.

Sheet Summary
B2: SALES WORKSTREAM — PORTFOLIO SUMMARY ($M)
B3: All figures link to the initiative WAVE sheets. Payback/NPV per WAVE Section IV.
B5: Initiative | C5: NRB run rate | D5: NRB 2026 | E5: NRB 2027 | F5: NRB 2028 | G5: NRB 2029 | H5: NRB 2030 | I5: One-time cost (5yr) | J5: Run cost 2030 | K5: NPV (5yr) | L5: Payback (yrs)
B6: SALES-1 — Underwriting & Pricing — Front Book | C6: ='SALES-1 WAVE'!$K$117 -> 0 | D6: ='SALES-1 WAVE'!$L$117 -> 0 | E6: ='SALES-1 WAVE'!$M$117 -> 0 | F6: ='SALES-1 WAVE'!$N$117 -> 0 | G6: ='SALES-1 WAVE'!$O$117 -> 0 | H6: ='SALES-1 WAVE'!$P$117 -> 0 | I6: =SUM('SALES-1 WAVE'!$L$147:$P$147) -> 1.5247089 | J6: ='SALES-1 WAVE'!$P$115 -> 0 | K6: ='SALES-1 WAVE'!$G$168 -> -1.2988552 | L6: ='SALES-1 WAVE'!$G$165 -> >5
B7: SALES-2 — SMB Long Tail — Partner | C7: ='SALES-2 WAVE'!$K$117 -> 0 | D7: ='SALES-2 WAVE'!$L$117 -> 0 | E7: ='SALES-2 WAVE'!$M$117 -> 0 | F7: ='SALES-2 WAVE'!$N$117 -> 0 | G7: ='SALES-2 WAVE'!$O$117 -> 0 | H7: ='SALES-2 WAVE'!$P$117 -> 0 | I7: =SUM('SALES-2 WAVE'!$L$147:$P$147) -> 1.5247089 | J7: ='SALES-2 WAVE'!$P$115 -> 0 | K7: ='SALES-2 WAVE'!$G$168 -> -1.2988552 | L7: ='SALES-2 WAVE'!$G$165 -> >5
B8: TOTAL — SALES WORKSTREAM | C8: =SUM(C6:C7) -> 0 | D8: =SUM(D6:D7) -> 0 | E8: =SUM(E6:E7) -> 0 | F8: =SUM(F6:F7) -> 0 | G8: =SUM(G6:G7) -> 0 | H8: =SUM(H6:H7) -> 0 | I8: =SUM(I6:I7) -> 3.0494178 | J8: =SUM(J6:J7) -> 0
B10: Note: NPV and payback are not additive across initiatives; totals shown for benefit/cost columns only.
B11: Capitalization policy note: this file defaults Build/Test labor to 80% capitalizable (Rate Card) pending Finance sign-off; the Servicing file defaults to 0% to mirror the S2 model's all-cash treatment. Align the policy across workstreams with Finance before the S2 gate.

Sheet SALES-1 Model
B2: SALES-1 — Underwriting & Pricing — Front Book | INITIATIVE MODEL
B3: Workstream: Sales (ELT sponsor: Susan | WSL: Selwyn) • Model status: Structure ready; NSR/seller baselines to populate from received datasets — see open items
T5: 2026 | U5: 2026 | V5: 2026 | W5: 2026 | X5: 2026 | Y5: 2026 | Z5: 2026 | AA5: 2026 | AB5: 2026 | AC5: 2026 | AD5: 2026 | AE5: 2026 | AF5: 2027 | AG5: 2027 | AH5: 2027 | AI5: 2027 | AJ5: 2027 | AK5: 2027 | AL5: 2027 | AM5: 2027 | AN5: 2027 | AO5: 2027 | AP5: 2027 | AQ5: 2027 | AR5: 2028 | AS5: 2028 | AT5: 2028 | AU5: 2028 | AV5: 2028 | AW5: 2028 | AX5: 2028 | AY5: 2028 | AZ5: 2028 | BA5: 2028 | BB5: 2028 | BC5: 2028 | BD5: 2029 | BE5: 2029 | BF5: 2029 | BG5: 2029 | BH5: 2029 | BI5: 2029 | BJ5: 2029 | BK5: 2029 | BL5: 2029 | BM5: 2029 | BN5: 2029 | BO5: 2029 | BP5: 2030 | BQ5: 2030 | BR5: 2030 | BS5: 2030 | BT5: 2030 | BU5: 2030 | BV5: 2030 | BW5: 2030 | BX5: 2030 | BY5: 2030 | BZ5: 2030 | CA5: 2030
B6: Monthly grid (Jan-26 → Dec-30) → | K6: Run rate | L6: 2026 | M6: 2027 | N6: 2028 | O6: 2029 | P6: 2030 | T6: =DATE(2026,1,31) -> 46053 | U6: =EOMONTH(T6,1) -> 46081 | V6: =EOMONTH(U6,1) -> 46112 | W6: =EOMONTH(V6,1) -> 46142 | X6: =EOMONTH(W6,1) -> 46173 | Y6: =EOMONTH(X6,1) -> 46203 | Z6: =EOMONTH(Y6,1) -> 46234 | AA6: =EOMONTH(Z6,1) -> 46265 | AB6: =EOMONTH(AA6,1) -> 46295 | ... CA6: =EOMONTH(BZ6,1) -> 47848
B8: 0. INITIATIVE & STATUS
B10: Initiative name | D10: Agentic underwriting and pricing for the front book — faster cycle times, freed seller capacity, RoS uplift
B11: Initiative owner | D11: Sales initiative owner — TBC | I11: confirm with workstream lead
B12: Impacted BU | D12: Global Sales
B13: Go-live / Estimated L4 date | D13: =DATE(2027,4,1) -> 46478 | I13: Benefit ramp is gated on this date.
B15: Source: Workplan: 'Project Zenith Automation workplan and data requests vS_1.xlsx', Sales tab + Sales Data Requests tab
B16: Source: Impact ranges: Aug 13 deck pp. 6, 14–15; Board deck pp. 9, 20, 52 (preliminary — Finance to validate)
B17: Open items to refine with initiative owner:
B18: – Baselines to populate: front-book NSR by segment (pending), TM% by BU/region (received 8/20 — reflects CEO ask on revenue-quality differences), FLC by region (received 8/21), seller counts & time-on-UW split (pending).
B19: – Revenue-acceleration conversion factor (cycle time -> incremental NSR) must be defined with Finance — incremental vs pull-forward treatment per the Finance approval package requirements.
B20: – Sales/Risk attribution and Risk & Compliance dependency (underwriting, credit decisioning, risk-based pricing) to be resolved.
B21: – Interviews in flight (Pricing 8/27, Underwriting 8/27, Tech 8/26); build shape below is the standard AAO pod PLACEHOLDER — refine after tech workshop (W6).
B23: 1. SIZING ASSUMPTIONS (blue = inputs — refine with initiative owner)
B25: Baseline / denominator (populate from received datasets + pending requests)
B26: Front-book NSR in scope (annual) | D26: 0 | E26: $/yr | F26: PENDING — placeholder, not data. NSR by segment — pending
B27: Transaction margin (TM % of NSR) — blended in scope | D27: 0 | E27: % | F27: Received 8/20 by BU/region — populate blended in-scope value
B28: # sellers in scope (UW/pricing-involved) | D28: 0 | E28: # FTE | F28: PENDING — placeholder, not data. Seller counts by segment — pending
B29: Avg fully loaded cost per seller | D29: 0 | E29: $/yr | F29: FLC by region received 8/21 — populate blended value
B30: % of seller time on UW, pricing & related activities | D30: 0 | E30: % | F30: PENDING — placeholder, not data. Seller time-allocation — pending
B31: Impact drivers (Aug 13 deck pp. 6, 14 — preliminary ranges, midpoints seeded)
B32: UW cycle-time reduction | D32: 0.7 | E32: % | F32: Source: 70%
B33: Pricing cycle-time reduction | D33: 0.25 | E33: % | F33: Source: 20–30% — midpoint
B34: Revenue-acceleration conversion (% incremental NSR from faster cycles) | D34: 0 | E34: % | F34: PENDING — placeholder, not data. Define with Finance: converts cycle-time reduction into incremental NSR; keep incremental vs pull-forward split explicit
B35: Capture rate — revenue acceleration | D35: 0.75 | E35: % | F35: Source: 75%
B36: RoS / margin uplift | D36: 0.025 | E36: % | F36: Source: 2–3% — midpoint
B37: Capture rate — RoS uplift | D37: 0.75 | E37: % | F37: Assumed same as pricing capture — confirm
B38: Seller capacity freed — UW | D38: 0.35 | E38: % | F38: Source: 30–40% — midpoint
B39: Seller capacity freed — pricing | D39: 0.3 | E39: % | F39: Source: 25–35% — midpoint
B40: Capture rate — seller capacity to cost | D40: 0.65 | E40: % | F40: Source: 65%
B41: Investment uplifts (consistent with Servicing S2 standard)
B42: Programme management, % of build | D42: 0.08 | E42: %
B43: Contingency, % of build incl. PM | D43: 0.1 | E43: %
B44: (spare assumption row)
B45: (spare assumption row)
B47: 2. BENEFIT CALCULATION (steady-state annual run-rate)
B49: In-scope margin base (NSR x TM%) | D49: =$D$26*$D$27 -> 0 | E49: $/yr
B50: Revenue acceleration — UW + pricing cycle time | D50: =$D$26*$D$27*$D$34*$D$35 -> 0 | E50: $/yr | F50: Margin base x acceleration conversion x capture. Cycle-time reductions (70% UW / 25% pricing) inform the conversion factor — keep the factor honest about incremental vs pull-forward
B51: RoS / pricing uplift benefit | D51: =$D$26*$D$27*$D$36*$D$37 -> 0 | E51: $/yr | F51: Margin base x RoS uplift x capture — confirm whether uplift applies to NSR or TM base
B52: Seller capacity freed (bankable) | D52: =$D$28*$D$29*$D$30*(($D$38+$D$39)/2)*$D$40 -> 0 | E52: $/yr | F52: Sellers x FLC x % time on UW/pricing x avg capacity freed x capture
B54: 3. RAMP & PHASING
B56: Months to full run rate after go-live (linear ramp) | D56: 9 | F56: Benefit starts at go-live and ramps linearly to steady state over this many months.
B57: Monthly ramp % (run-rate captured in month) | T57: =MIN(1,MAX(0,((YEAR(T$6)-YEAR($D$13))*12+MONTH(T$6)-MONTH($D$13)+0.5)/MAX($D$56,0.5))) -> 0 | U57: =MIN(1,MAX(0,((YEAR(U$6)-YEAR($D$13))*12+MONTH(U$6)-MONTH($D$13)+0.5)/MAX($D$56,0.5))) -> 0 | V57: =MIN(1,MAX(0,((YEAR(V$6)-YEAR($D$13))*12+MONTH(V$6)-MONTH($D$13)+0.5)/MAX($D$56,0.5))) -> 0 | W57: =MIN(1,MAX(0,((YEAR(W$6)-YEAR($D$13))*12+MONTH(W$6)-MONTH($D$13)+0.5)/MAX($D$56,0.5))) -> 0 | X57: =MIN(1,MAX(0,((YEAR(X$6)-YEAR($D$13))*12+MONTH(X$6)-MONTH($D$13)+0.5)/MAX($D$56,0.5))) -> 0 | Y57: =MIN(1,MAX(0,((YEAR(Y$6)-YEAR($D$13))*12+MONTH(Y$6)-MONTH($D$13)+0.5)/MAX($D$56,0.5))) -> 0 | Z57: =MIN(1,MAX(0,((YEAR(Z$6)-YEAR($D$13))*12+MONTH(Z$6)-MONTH($D$13)+0.5)/MAX($D$56,0.5))) -> 0 | AA57: =MIN(1,MAX(0,((YEAR(AA$6)-YEAR($D$13))*12+MONTH(AA$6)-MONTH($D$13)+0.5)/MAX($D$56,0.5))) -> 0 | ... CA57: =MIN(1,MAX(0,((YEAR(CA$6)-YEAR($D$13))*12+MONTH(CA$6)-MONTH($D$13)+0.5)/MAX($D$56,0.5))) -> 1
B58: Resulting average ramp % by year (info) | L58: =SUMIFS($T57:$CA57,$T$5:$CA$5,2026)/12 -> 0 | M58: =SUMIFS($T57:$CA57,$T$5:$CA$5,2027)/12 -> 0.375 | N58: =SUMIFS($T57:$CA57,$T$5:$CA$5,2028)/12 -> 1 | O58: =SUMIFS($T57:$CA57,$T$5:$CA$5,2029)/12 -> 1 | P58: =SUMIFS($T57:$CA57,$T$5:$CA$5,2030)/12 -> 1
B60: 4. RECURRING BENEFIT LINES ($M — these rows feed the WAVE sheet)
B62: Line (WAVE category) | D62: Baseline $M | K62: Run rate
B63: Revenue - Acceleration from UW & pricing cycle time [REV] | D63: =$D$49/1000000 -> 0 | K63: =SUMIFS($T63:$CA63,$T$5:$CA$5,2030) -> 0 | L63: =SUMIFS($T63:$CA63,$T$5:$CA$5,2026) -> 0 | M63: =SUMIFS($T63:$CA63,$T$5:$CA$5,2027) -> 0 | N63: =SUMIFS($T63:$CA63,$T$5:$CA$5,2028) -> 0 | O63: =SUMIFS($T63:$CA63,$T$5:$CA$5,2029) -> 0 | P63: =SUMIFS($T63:$CA63,$T$5:$CA$5,2030) -> 0 | T63: =($D$50)/1000000/12*T$57 -> 0 | U63: =($D$50)/1000000/12*U$57 -> 0 | V63: =($D$50)/1000000/12*V$57 -> 0 | W63: =($D$50)/1000000/12*W$57 -> 0 | X63: =($D$50)/1000000/12*X$57 -> 0 | Y63: =($D$50)/1000000/12*Y$57 -> 0 | Z63: =($D$50)/1000000/12*Z$57 -> 0 | AA63: =($D$50)/1000000/12*AA$57 -> 0 | ... CA63: =($D$50)/1000000/12*CA$57 -> 0
B64: Revenue - RoS / pricing uplift [REV] | D64: =$D$49/1000000 -> 0 | K64: =SUMIFS($T64:$CA64,$T$5:$CA$5,2030) -> 0 | L64: =SUMIFS($T64:$CA64,$T$5:$CA$5,2026) -> 0 | M64: =SUMIFS($T64:$CA64,$T$5:$CA$5,2027) -> 0 | N64: =SUMIFS($T64:$CA64,$T$5:$CA$5,2028) -> 0 | O64: =SUMIFS($T64:$CA64,$T$5:$CA$5,2029) -> 0 | P64: =SUMIFS($T64:$CA64,$T$5:$CA$5,2030) -> 0 | T64: =($D$51)/1000000/12*T$57 -> 0 | U64: =($D$51)/1000000/12*U$57 -> 0 | V64: =($D$51)/1000000/12*V$57 -> 0 | W64: =($D$51)/1000000/12*W$57 -> 0 | X64: =($D$51)/1000000/12*X$57 -> 0 | Y64: =($D$51)/1000000/12*Y$57 -> 0 | Z64: =($D$51)/1000000/12*Z$57 -> 0 | AA64: =($D$51)/1000000/12*AA$57 -> 0 | ... CA64: =($D$51)/1000000/12*CA$57 -> 0
B65: OPEX - Seller capacity freed (UW & pricing) [OPEX] | D65: =$D$28*$D$29/1000000 -> 0 | K65: =SUMIFS($T65:$CA65,$T$5:$CA$5,2030) -> 0 | L65: =SUMIFS($T65:$CA65,$T$5:$CA$5,2026) -> 0 | M65: =SUMIFS($T65:$CA65,$T$5:$CA$5,2027) -> 0 | N65: =SUMIFS($T65:$CA65,$T$5:$CA$5,2028) -> 0 | O65: =SUMIFS($T65:$CA65,$T$5:$CA$5,2029) -> 0 | P65: =SUMIFS($T65:$CA65,$T$5:$CA$5,2030) -> 0 | T65: =($D$52)/1000000/12*T$57 -> 0 | U65: =($D$52)/1000000/12*U$57 -> 0 | V65: =($D$52)/1000000/12*V$57 -> 0 | W65: =($D$52)/1000000/12*W$57 -> 0 | X65: =($D$52)/1000000/12*X$57 -> 0 | Y65: =($D$52)/1000000/12*Y$57 -> 0 | Z65: =($D$52)/1000000/12*Z$57 -> 0 | AA65: =($D$52)/1000000/12*AA$57 -> 0 | ... CA65: =($D$52)/1000000/12*CA$57 -> 0
B66: Total recurring benefit ($M) | K66: =SUM(K63:K65) -> 0 | L66: =SUM(L63:L65) -> 0 | M66: =SUM(M63:M65) -> 0 | N66: =SUM(N63:N65) -> 0 | O66: =SUM(O63:O65) -> 0 | P66: =SUM(P63:P65) -> 0
B68: 5. ONE-TIME INVESTMENT — people cost by milestone (standard approach)
B70: Milestone | C70: Assumptions | D70: Team size | E70: Billing months | F70: Contingency Factor | G70: Labor Costs | H70: Start month | I70: Cap % (labor) | K70: Rate override ($/mo)
C71: Capture any assumptions on cost drivers, timelines, contingency factor etc. | E71: Months the team works at full utilization | F71: Low=10% Medium=15% High=20% Very high=50% | G71: Total labor costs for milestone | I71: Default links to Rate Card policy — type a % to override
B72: Plan / Design | C72: PLACEHOLDER — standard AAO pod shape; refine after W6 tech workshop and vendor RFP decisions. | D72: 4 | E72: 2 | F72: 0.1 | G72: =D72*E72*IF(K72="",'Rate Card'!$G$29,K72)*(1+F72) -> 131633.33 | H72: =DATE(2026,10,1) -> 46296 | I72: ='Rate Card'!$C$45 -> 0
B73: Build / Test | C73: PLACEHOLDER — one 8-FTE pod; vendor build (incl. integrations/data, API) carried in non-labor lines below. | D73: 8 | E73: 5 | F73: 0.1 | G73: =D73*E73*IF(K73="",'Rate Card'!$G$29,K73)*(1+F73) -> 658166.67 | H73: =DATE(2026,12,1) -> 46357 | I73: ='Rate Card'!$C$46 -> 0.8
B74: Pilot / Change Mgmt. | C74: PLACEHOLDER — scale-up team of 5 through segment rollout; change management cost in non-labor below. | D74: 5 | E74: 6 | F74: 0.1 | G74: =D74*E74*IF(K74="",'Rate Card'!$G$29,K74)*(1+F74) -> 493625 | H74: =DATE(2027,4,1) -> 46478 | I74: ='Rate Card'!$C$47 -> 0
B75: Scale / Run | C75: Run-phase support carried as recurring run cost (Section 6). | D75: 0 | E75: 0 | F75: 0.1 | G75: =D75*E75*IF(K75="",'Rate Card'!$G$29,K75)*(1+F75) -> 0 | H75: =DATE(2027,10,1) -> 46661 | I75: ='Rate Card'!$C$48 -> 0
B77: Milestone labor phasing ($/month, spread evenly over billing months)
B78: Plan / Design | T78: =IF(AND(T$6>=EOMONTH($H$72,0),T$6<=EOMONTH(EDATE($H$72,$E$72-1),0)),$G$72/MAX($E$72,1),0) -> 0 | U78: =IF(AND(U$6>=EOMONTH($H$72,0),U$6<=EOMONTH(EDATE($H$72,$E$72-1),0)),$G$72/MAX($E$72,1),0) -> 0 | V78: =IF(AND(V$6>=EOMONTH($H$72,0),V$6<=EOMONTH(EDATE($H$72,$E$72-1),0)),$G$72/MAX($E$72,1),0) -> 0 | W78: =IF(AND(W$6>=EOMONTH($H$72,0),W$6<=EOMONTH(EDATE($H$72,$E$72-1),0)),$G$72/MAX($E$72,1),0) -> 0 | X78: =IF(AND(X$6>=EOMONTH($H$72,0),X$6<=EOMONTH(EDATE($H$72,$E$72-1),0)),$G$72/MAX($E$72,1),0) -> 0 | Y78: =IF(AND(Y$6>=EOMONTH($H$72,0),Y$6<=EOMONTH(EDATE($H$72,$E$72-1),0)),$G$72/MAX($E$72,1),0) -> 0 | Z78: =IF(AND(Z$6>=EOMONTH($H$72,0),Z$6<=EOMONTH(EDATE($H$72,$E$72-1),0)),$G$72/MAX($E$72,1),0) -> 0 | AA78: =IF(AND(AA$6>=EOMONTH($H$72,0),AA$6<=EOMONTH(EDATE($H$72,$E$72-1),0)),$G$72/MAX($E$72,1),0) -> 0 | ... CA78: =IF(AND(CA$6>=EOMONTH($H$72,0),CA$6<=EOMONTH(EDATE($H$72,$E$72-1),0)),$G$72/MAX($E$72,1),0) -> 0
B79: Build / Test | T79: =IF(AND(T$6>=EOMONTH($H$73,0),T$6<=EOMONTH(EDATE($H$73,$E$73-1),0)),$G$73/MAX($E$73,1),0) -> 0 | U79: =IF(AND(U$6>=EOMONTH($H$73,0),U$6<=EOMONTH(EDATE($H$73,$E$73-1),0)),$G$73/MAX($E$73,1),0) -> 0 | V79: =IF(AND(V$6>=EOMONTH($H$73,0),V$6<=EOMONTH(EDATE($H$73,$E$73-1),0)),$G$73/MAX($E$73,1),0) -> 0 | W79: =IF(AND(W$6>=EOMONTH($H$73,0),W$6<=EOMONTH(EDATE($H$73,$E$73-1),0)),$G$73/MAX($E$73,1),0) -> 0 | X79: =IF(AND(X$6>=EOMONTH($H$73,0),X$6<=EOMONTH(EDATE($H$73,$E$73-1),0)),$G$73/MAX($E$73,1),0) -> 0 | Y79: =IF(AND(Y$6>=EOMONTH($H$73,0),Y$6<=EOMONTH(EDATE($H$73,$E$73-1),0)),$G$73/MAX($E$73,1),0) -> 0 | Z79: =IF(AND(Z$6>=EOMONTH($H$73,0),Z$6<=EOMONTH(EDATE($H$73,$E$73-1),0)),$G$73/MAX($E$73,1),0) -> 0 | AA79: =IF(AND(AA$6>=EOMONTH($H$73,0),AA$6<=EOMONTH(EDATE($H$73,$E$73-1),0)),$G$73/MAX($E$73,1),0) -> 0 | ... CA79: =IF(AND(CA$6>=EOMONTH($H$73,0),CA$6<=EOMONTH(EDATE($H$73,$E$73-1),0)),$G$73/MAX($E$73,1),0) -> 0
B80: Pilot / Change Mgmt. | T80: =IF(AND(T$6>=EOMONTH($H$74,0),T$6<=EOMONTH(EDATE($H$74,$E$74-1),0)),$G$74/MAX($E$74,1),0) -> 0 | U80: =IF(AND(U$6>=EOMONTH($H$74,0),U$6<=EOMONTH(EDATE($H$74,$E$74-1),0)),$G$74/MAX($E$74,1),0) -> 0 | V80: =IF(AND(V$6>=EOMONTH($H$74,0),V$6<=EOMONTH(EDATE($H$74,$E$74-1),0)),$G$74/MAX($E$74,1),0) -> 0 | W80: =IF(AND(W$6>=EOMONTH($H$74,0),W$6<=EOMONTH(EDATE($H$74,$E$74-1),0)),$G$74/MAX($E$74,1),0) -> 0 | X80: =IF(AND(X$6>=EOMONTH($H$74,0),X$6<=EOMONTH(EDATE($H$74,$E$74-1),0)),$G$74/MAX($E$74,1),0) -> 0 | Y80: =IF(AND(Y$6>=EOMONTH($H$74,0),Y$6<=EOMONTH(EDATE($H$74,$E$74-1),0)),$G$74/MAX($E$74,1),0) -> 0 | Z80: =IF(AND(Z$6>=EOMONTH($H$74,0),Z$6<=EOMONTH(EDATE($H$74,$E$74-1),0)),$G$74/MAX($E$74,1),0) -> 0 | AA80: =IF(AND(AA$6>=EOMONTH($H$74,0),AA$6<=EOMONTH(EDATE($H$74,$E$74-1),0)),$G$74/MAX($E$74,1),0) -> 0 | ... CA80: =IF(AND(CA$6>=EOMONTH($H$74,0),CA$6<=EOMONTH(EDATE($H$74,$E$74-1),0)),$G$74/MAX($E$74,1),0) -> 0
B81: Scale / Run | T81: =IF(AND(T$6>=EOMONTH($H$75,0),T$6<=EOMONTH(EDATE($H$75,$E$75-1),0)),$G$75/MAX($E$75,1),0) -> 0 | U81: =IF(AND(U$6>=EOMONTH($H$75,0),U$6<=EOMONTH(EDATE($H$75,$E$75-1),0)),$G$75/MAX($E$75,1),0) -> 0 | V81: =IF(AND(V$6>=EOMONTH($H$75,0),V$6<=EOMONTH(EDATE($H$75,$E$75-1),0)),$G$75/MAX($E$75,1),0) -> 0 | W81: =IF(AND(W$6>=EOMONTH($H$75,0),W$6<=EOMONTH(EDATE($H$75,$E$75-1),0)),$G$75/MAX($E$75,1),0) -> 0 | X81: =IF(AND(X$6>=EOMONTH($H$75,0),X$6<=EOMONTH(EDATE($H$75,$E$75-1),0)),$G$75/MAX($E$75,1),0) -> 0 | Y81: =IF(AND(Y$6>=EOMONTH($H$75,0),Y$6<=EOMONTH(EDATE($H$75,$E$75-1),0)),$G$75/MAX($E$75,1),0) -> 0 | Z81: =IF(AND(Z$6>=EOMONTH($H$75,0),Z$6<=EOMONTH(EDATE($H$75,$E$75-1),0)),$G$75/MAX($E$75,1),0) -> 0 | AA81: =IF(AND(AA$6>=EOMONTH($H$75,0),AA$6<=EOMONTH(EDATE($H$75,$E$75-1),0)),$G$75/MAX($E$75,1),0) -> 0 | ... CA81: =IF(AND(CA$6>=EOMONTH($H$75,0),CA$6<=EOMONTH(EDATE($H$75,$E$75-1),0)),$G$75/MAX($E$75,1),0) -> 0
B82: Total milestone labor (all blocks) | G82: =SUM(G72:G75) -> 1283425
B84: One-time non-labor costs (vendor, integration, licences, change mgmt., etc.)
B85: Item | C85: Assumptions / notes | D85: Total $ | E85: Spread months | H85: Start month | I85: Cap %
B86: Vendor build (incl. integrations / data / API) | C86: PENDING — placeholder, not data. Build cost incl. vendor — RFP W8 | D86: 0 | E86: 5 | H86: =DATE(2026,12,1) -> 46357 | I86: 0
B87: Change management | C87: PENDING — placeholder, not data. Change management cost | D87: 0 | E87: 6 | H87: =DATE(2027,4,1) -> 46478 | I87: 0
B88: Programme management (8% of build) | C88: 8% x (milestone labor + vendor + change mgmt) — Servicing S2 standard | D88: =$D$42*($G$82+$D$86+$D$87) -> 102674 | E88: 9 | H88: =DATE(2026,10,1) -> 46296 | I88: 0
B89: Contingency (10% of build incl. PM) | C89: 10% x (build subtotal incl. PM) — Servicing S2 standard | D89: =$D$43*($G$82+$D$86+$D$87+$D$88) -> 138609.9 | E89: 9 | H89: =DATE(2026,10,1) -> 46296 | I89: 0
B90: (spare) | D90: 0 | E90: 1 | H90: =DATE(2027,4,1) -> 46478 | I90: 0
B92: Non-labor phasing ($/month)
B93: phasing — item 1 | T93: =IF(AND(T$6>=EOMONTH($H$86,0),T$6<=EOMONTH(EDATE($H$86,$E$86-1),0)),$D$86/MAX($E$86,1),0) -> 0 | U93: =IF(AND(U$6>=EOMONTH($H$86,0),U$6<=EOMONTH(EDATE($H$86,$E$86-1),0)),$D$86/MAX($E$86,1),0) -> 0 | V93: =IF(AND(V$6>=EOMONTH($H$86,0),V$6<=EOMONTH(EDATE($H$86,$E$86-1),0)),$D$86/MAX($E$86,1),0) -> 0 | W93: =IF(AND(W$6>=EOMONTH($H$86,0),W$6<=EOMONTH(EDATE($H$86,$E$86-1),0)),$D$86/MAX($E$86,1),0) -> 0 | X93: =IF(AND(X$6>=EOMONTH($H$86,0),X$6<=EOMONTH(EDATE($H$86,$E$86-1),0)),$D$86/MAX($E$86,1),0) -> 0 | Y93: =IF(AND(Y$6>=EOMONTH($H$86,0),Y$6<=EOMONTH(EDATE($H$86,$E$86-1),0)),$D$86/MAX($E$86,1),0) -> 0 | Z93: =IF(AND(Z$6>=EOMONTH($H$86,0),Z$6<=EOMONTH(EDATE($H$86,$E$86-1),0)),$D$86/MAX($E$86,1),0) -> 0 | AA93: =IF(AND(AA$6>=EOMONTH($H$86,0),AA$6<=EOMONTH(EDATE($H$86,$E$86-1),0)),$D$86/MAX($E$86,1),0) -> 0 | ... CA93: =IF(AND(CA$6>=EOMONTH($H$86,0),CA$6<=EOMONTH(EDATE($H$86,$E$86-1),0)),$D$86/MAX($E$86,1),0) -> 0
B94: phasing — item 2 | T94: =IF(AND(T$6>=EOMONTH($H$87,0),T$6<=EOMONTH(EDATE($H$87,$E$87-1),0)),$D$87/MAX($E$87,1),0) -> 0 | U94: =IF(AND(U$6>=EOMONTH($H$87,0),U$6<=EOMONTH(EDATE($H$87,$E$87-1),0)),$D$87/MAX($E$87,1),0) -> 0 | V94: =IF(AND(V$6>=EOMONTH($H$87,0),V$6<=EOMONTH(EDATE($H$87,$E$87-1),0)),$D$87/MAX($E$87,1),0) -> 0 | W94: =IF(AND(W$6>=EOMONTH($H$87,0),W$6<=EOMONTH(EDATE($H$87,$E$87-1),0)),$D$87/MAX($E$87,1),0) -> 0 | X94: =IF(AND(X$6>=EOMONTH($H$87,0),X$6<=EOMONTH(EDATE($H$87,$E$87-1),0)),$D$87/MAX($E$87,1),0) -> 0 | Y94: =IF(AND(Y$6>=EOMONTH($H$87,0),Y$6<=EOMONTH(EDATE($H$87,$E$87-1),0)),$D$87/MAX($E$87,1),0) -> 0 | Z94: =IF(AND(Z$6>=EOMONTH($H$87,0),Z$6<=EOMONTH(EDATE($H$87,$E$87-1),0)),$D$87/MAX($E$87,1),0) -> 0 | AA94: =IF(AND(AA$6>=EOMONTH($H$87,0),AA$6<=EOMONTH(EDATE($H$87,$E$87-1),0)),$D$87/MAX($E$87,1),0) -> 0 | ... CA94: =IF(AND(CA$6>=EOMONTH($H$87,0),CA$6<=EOMONTH(EDATE($H$87,$E$87-1),0)),$D$87/MAX($E$87,1),0) -> 0
B95: phasing — item 3 | T95: =IF(AND(T$6>=EOMONTH($H$88,0),T$6<=EOMONTH(EDATE($H$88,$E$88-1),0)),$D$88/MAX($E$88,1),0) -> 0 | U95: =IF(AND(U$6>=EOMONTH($H$88,0),U$6<=EOMONTH(EDATE($H$88,$E$88-1),0)),$D$88/MAX($E$88,1),0) -> 0 | V95: =IF(AND(V$6>=EOMONTH($H$88,0),V$6<=EOMONTH(EDATE($H$88,$E$88-1),0)),$D$88/MAX($E$88,1),0) -> 0 | W95: =IF(AND(W$6>=EOMONTH($H$88,0),W$6<=EOMONTH(EDATE($H$88,$E$88-1),0)),$D$88/MAX($E$88,1),0) -> 0 | X95: =IF(AND(X$6>=EOMONTH($H$88,0),X$6<=EOMONTH(EDATE($H$88,$E$88-1),0)),$D$88/MAX($E$88,1),0) -> 0 | Y95: =IF(AND(Y$6>=EOMONTH($H$88,0),Y$6<=EOMONTH(EDATE($H$88,$E$88-1),0)),$D$88/MAX($E$88,1),0) -> 0 | Z95: =IF(AND(Z$6>=EOMONTH($H$88,0),Z$6<=EOMONTH(EDATE($H$88,$E$88-1),0)),$D$88/MAX($E$88,1),0) -> 0 | AA95: =IF(AND(AA$6>=EOMONTH($H$88,0),AA$6<=EOMONTH(EDATE($H$88,$E$88-1),0)),$D$88/MAX($E$88,1),0) -> 0 | ... CA95: =IF(AND(CA$6>=EOMONTH($H$88,0),CA$6<=EOMONTH(EDATE($H$88,$E$88-1),0)),$D$88/MAX($E$88,1),0) -> 0
B96: phasing — item 4 | T96: =IF(AND(T$6>=EOMONTH($H$89,0),T$6<=EOMONTH(EDATE($H$89,$E$89-1),0)),$D$89/MAX($E$89,1),0) -> 0 | U96: =IF(AND(U$6>=EOMONTH($H$89,0),U$6<=EOMONTH(EDATE($H$89,$E$89-1),0)),$D$89/MAX($E$89,1),0) -> 0 | V96: =IF(AND(V$6>=EOMONTH($H$89,0),V$6<=EOMONTH(EDATE($H$89,$E$89-1),0)),$D$89/MAX($E$89,1),0) -> 0 | W96: =IF(AND(W$6>=EOMONTH($H$89,0),W$6<=EOMONTH(EDATE($H$89,$E$89-1),0)),$D$89/MAX($E$89,1),0) -> 0 | X96: =IF(AND(X$6>=EOMONTH($H$89,0),X$6<=EOMONTH(EDATE($H$89,$E$89-1),0)),$D$89/MAX($E$89,1),0) -> 0 | Y96: =IF(AND(Y$6>=EOMONTH($H$89,0),Y$6<=EOMONTH(EDATE($H$89,$E$89-1),0)),$D$89/MAX($E$89,1),0) -> 0 | Z96: =IF(AND(Z$6>=EOMONTH($H$89,0),Z$6<=EOMONTH(EDATE($H$89,$E$89-1),0)),$D$89/MAX($E$89,1),0) -> 0 | AA96: =IF(AND(AA$6>=EOMONTH($H$89,0),AA$6<=EOMONTH(EDATE($H$89,$E$89-1),0)),$D$89/MAX($E$89,1),0) -> 0 | ... CA96: =IF(AND(CA$6>=EOMONTH($H$89,0),CA$6<=EOMONTH(EDATE($H$89,$E$89-1),0)),$D$89/MAX($E$89,1),0) -> 0
B97: phasing — item 5 | T97: =IF(AND(T$6>=EOMONTH($H$90,0),T$6<=EOMONTH(EDATE($H$90,$E$90-1),0)),$D$90/MAX($E$90,1),0) -> 0 | U97: =IF(AND(U$6>=EOMONTH($H$90,0),U$6<=EOMONTH(EDATE($H$90,$E$90-1),0)),$D$90/MAX($E$90,1),0) -> 0 | V97: =IF(AND(V$6>=EOMONTH($H$90,0),V$6<=EOMONTH(EDATE($H$90,$E$90-1),0)),$D$90/MAX($E$90,1),0) -> 0 | W97: =IF(AND(W$6>=EOMONTH($H$90,0),W$6<=EOMONTH(EDATE($H$90,$E$90-1),0)),$D$90/MAX($E$90,1),0) -> 0 | X97: =IF(AND(X$6>=EOMONTH($H$90,0),X$6<=EOMONTH(EDATE($H$90,$E$90-1),0)),$D$90/MAX($E$90,1),0) -> 0 | Y97: =IF(AND(Y$6>=EOMONTH($H$90,0),Y$6<=EOMONTH(EDATE($H$90,$E$90-1),0)),$D$90/MAX($E$90,1),0) -> 0 | Z97: =IF(AND(Z$6>=EOMONTH($H$90,0),Z$6<=EOMONTH(EDATE($H$90,$E$90-1),0)),$D$90/MAX($E$90,1),0) -> 0 | AA97: =IF(AND(AA$6>=EOMONTH($H$90,0),AA$6<=EOMONTH(EDATE($H$90,$E$90-1),0)),$D$90/MAX($E$90,1),0) -> 0 | ... CA97: =IF(AND(CA$6>=EOMONTH($H$90,0),CA$6<=EOMONTH(EDATE($H$90,$E$90-1),0)),$D$90/MAX($E$90,1),0) -> 0
B99: One-time investment feed rows ($M — these feed the WAVE sheet)
B100: CAPEX — capitalized build labor | L100: =SUMIFS($T100:$CA100,$T$5:$CA$5,2026) -> 0.10530667 | M100: =SUMIFS($T100:$CA100,$T$5:$CA$5,2027) -> 0.42122667 | N100: =SUMIFS($T100:$CA100,$T$5:$CA$5,2028) -> 0 | O100: =SUMIFS($T100:$CA100,$T$5:$CA$5,2029) -> 0 | P100: =SUMIFS($T100:$CA100,$T$5:$CA$5,2030) -> 0 | T100: =(SUMPRODUCT(T78:T81,$I$72:$I$75))/1000000 -> 0 | U100: =(SUMPRODUCT(U78:U81,$I$72:$I$75))/1000000 -> 0 | V100: =(SUMPRODUCT(V78:V81,$I$72:$I$75))/1000000 -> 0 | W100: =(SUMPRODUCT(W78:W81,$I$72:$I$75))/1000000 -> 0 | X100: =(SUMPRODUCT(X78:X81,$I$72:$I$75))/1000000 -> 0 | Y100: =(SUMPRODUCT(Y78:Y81,$I$72:$I$75))/1000000 -> 0 | Z100: =(SUMPRODUCT(Z78:Z81,$I$72:$I$75))/1000000 -> 0 | AA100: =(SUMPRODUCT(AA78:AA81,$I$72:$I$75))/1000000 -> 0 | ... CA100: =(SUMPRODUCT(CA78:CA81,$I$72:$I$75))/1000000 -> 0
B101: CAPEX — capitalized non-labor | L101: =SUMIFS($T101:$CA101,$T$5:$CA$5,2026) -> 0 | M101: =SUMIFS($T101:$CA101,$T$5:$CA$5,2027) -> 0 | N101: =SUMIFS($T101:$CA101,$T$5:$CA$5,2028) -> 0 | O101: =SUMIFS($T101:$CA101,$T$5:$CA$5,2029) -> 0 | P101: =SUMIFS($T101:$CA101,$T$5:$CA$5,2030) -> 0 | T101: =SUMPRODUCT(T93:T97,$I$86:$I$90)/1000000 -> 0 | U101: =SUMPRODUCT(U93:U97,$I$86:$I$90)/1000000 -> 0 | V101: =SUMPRODUCT(V93:V97,$I$86:$I$90)/1000000 -> 0 | W101: =SUMPRODUCT(W93:W97,$I$86:$I$90)/1000000 -> 0 | X101: =SUMPRODUCT(X93:X97,$I$86:$I$90)/1000000 -> 0 | Y101: =SUMPRODUCT(Y93:Y97,$I$86:$I$90)/1000000 -> 0 | Z101: =SUMPRODUCT(Z93:Z97,$I$86:$I$90)/1000000 -> 0 | AA101: =SUMPRODUCT(AA93:AA97,$I$86:$I$90)/1000000 -> 0 | ... CA101: =SUMPRODUCT(CA93:CA97,$I$86:$I$90)/1000000 -> 0
B102: OTC — build labor (expensed) | L102: =SUMIFS($T102:$CA102,$T$5:$CA$5,2026) -> 0.15796 | M102: =SUMIFS($T102:$CA102,$T$5:$CA$5,2027) -> 0.59893167 | N102: =SUMIFS($T102:$CA102,$T$5:$CA$5,2028) -> 0 | O102: =SUMIFS($T102:$CA102,$T$5:$CA$5,2029) -> 0 | P102: =SUMIFS($T102:$CA102,$T$5:$CA$5,2030) -> 0 | T102: =(SUMPRODUCT(T78:T81,1-$I$72:$I$75))/1000000 -> 0 | U102: =(SUMPRODUCT(U78:U81,1-$I$72:$I$75))/1000000 -> 0 | V102: =(SUMPRODUCT(V78:V81,1-$I$72:$I$75))/1000000 -> 0 | W102: =(SUMPRODUCT(W78:W81,1-$I$72:$I$75))/1000000 -> 0 | X102: =(SUMPRODUCT(X78:X81,1-$I$72:$I$75))/1000000 -> 0 | Y102: =(SUMPRODUCT(Y78:Y81,1-$I$72:$I$75))/1000000 -> 0 | Z102: =(SUMPRODUCT(Z78:Z81,1-$I$72:$I$75))/1000000 -> 0 | AA102: =(SUMPRODUCT(AA78:AA81,1-$I$72:$I$75))/1000000 -> 0 | ... CA102: =(SUMPRODUCT(CA78:CA81,1-$I$72:$I$75))/1000000 -> 0
B103: OTC — non-labor (expensed) | L103: =SUMIFS($T103:$CA103,$T$5:$CA$5,2026) -> 0.080427967 | M103: =SUMIFS($T103:$CA103,$T$5:$CA$5,2027) -> 0.16085593 | N103: =SUMIFS($T103:$CA103,$T$5:$CA$5,2028) -> 0 | O103: =SUMIFS($T103:$CA103,$T$5:$CA$5,2029) -> 0 | P103: =SUMIFS($T103:$CA103,$T$5:$CA$5,2030) -> 0 | T103: =SUMPRODUCT(T93:T97,1-$I$86:$I$90)/1000000 -> 0 | U103: =SUMPRODUCT(U93:U97,1-$I$86:$I$90)/1000000 -> 0 | V103: =SUMPRODUCT(V93:V97,1-$I$86:$I$90)/1000000 -> 0 | W103: =SUMPRODUCT(W93:W97,1-$I$86:$I$90)/1000000 -> 0 | X103: =SUMPRODUCT(X93:X97,1-$I$86:$I$90)/1000000 -> 0 | Y103: =SUMPRODUCT(Y93:Y97,1-$I$86:$I$90)/1000000 -> 0 | Z103: =SUMPRODUCT(Z93:Z97,1-$I$86:$I$90)/1000000 -> 0 | AA103: =SUMPRODUCT(AA93:AA97,1-$I$86:$I$90)/1000000 -> 0 | ... CA103: =SUMPRODUCT(CA93:CA97,1-$I$86:$I$90)/1000000 -> 0
B104: Total one-time investment ($M) | L104: =SUM(L100:L103) -> 0.34369463 | M104: =SUM(M100:M103) -> 1.1810143 | N104: =SUM(N100:N103) -> 0 | O104: =SUM(O100:O103) -> 0 | P104: =SUM(P100:P103) -> 0
B106: 6. RECURRING RUN COSTS to achieve impact
B108: Line | C108: Assumptions / notes | D108: Annual $ (steady state) | H108: Start month | I108: Scales with ramp? (Y/N)
B109: OPEX - Token cost for agents | C109: PENDING — placeholder, not data. Agent token consumption — scales with adoption/ramp | D109: 0 | H109: =DATE(2027,4,1) -> 46478 | I109: Y
B110: OPEX - Vendor / SaaS recurring | C110: PENDING — placeholder, not data. Recurring vendor/licence opex | D110: 0 | H110: =DATE(2027,4,1) -> 46478 | I110: N
B111: OPEX - Support & maintenance | C111: PENDING — placeholder, not data. Ongoing support/maintenance | D111: 0 | H111: =DATE(2027,4,1) -> 46478 | I111: N
B113: Run-cost feed rows ($M)
B114: OPEX - Token cost for agents [RUN] | K114: =SUMIFS($T114:$CA114,$T$5:$CA$5,2030) -> 0 | L114: =SUMIFS($T114:$CA114,$T$5:$CA$5,2026) -> 0 | M114: =SUMIFS($T114:$CA114,$T$5:$CA$5,2027) -> 0 | N114: =SUMIFS($T114:$CA114,$T$5:$CA$5,2028) -> 0 | O114: =SUMIFS($T114:$CA114,$T$5:$CA$5,2029) -> 0 | P114: =SUMIFS($T114:$CA114,$T$5:$CA$5,2030) -> 0 | T114: =$D$109/1000000/12*IF($I$109="Y",T$57,IF(T$6>=EOMONTH($H$109,0),1,0)) -> 0 | U114: =$D$109/1000000/12*IF($I$109="Y",U$57,IF(U$6>=EOMONTH($H$109,0),1,0)) -> 0 | V114: =$D$109/1000000/12*IF($I$109="Y",V$57,IF(V$6>=EOMONTH($H$109,0),1,0)) -> 0 | W114: =$D$109/1000000/12*IF($I$109="Y",W$57,IF(W$6>=EOMONTH($H$109,0),1,0)) -> 0 | X114: =$D$109/1000000/12*IF($I$109="Y",X$57,IF(X$6>=EOMONTH($H$109,0),1,0)) -> 0 | Y114: =$D$109/1000000/12*IF($I$109="Y",Y$57,IF(Y$6>=EOMONTH($H$109,0),1,0)) -> 0 | Z114: =$D$109/1000000/12*IF($I$109="Y",Z$57,IF(Z$6>=EOMONTH($H$109,0),1,0)) -> 0 | AA114: =$D$109/1000000/12*IF($I$109="Y",AA$57,IF(AA$6>=EOMONTH($H$109,0),1,0)) -> 0 | ... CA114: =$D$109/1000000/12*IF($I$109="Y",CA$57,IF(CA$6>=EOMONTH($H$109,0),1,0)) -> 0
B115: OPEX - Vendor / SaaS recurring [RUN] | K115: =SUMIFS($T115:$CA115,$T$5:$CA$5,2030) -> 0 | L115: =SUMIFS($T115:$CA115,$T$5:$CA$5,2026) -> 0 | M115: =SUMIFS($T115:$CA115,$T$5:$CA$5,2027) -> 0 | N115: =SUMIFS($T115:$CA115,$T$5:$CA$5,2028) -> 0 | O115: =SUMIFS($T115:$CA115,$T$5:$CA$5,2029) -> 0 | P115: =SUMIFS($T115:$CA115,$T$5:$CA$5,2030) -> 0 | T115: =$D$110/1000000/12*IF($I$110="Y",T$57,IF(T$6>=EOMONTH($H$110,0),1,0)) -> 0 | U115: =$D$110/1000000/12*IF($I$110="Y",U$57,IF(U$6>=EOMONTH($H$110,0),1,0)) -> 0 | V115: =$D$110/1000000/12*IF($I$110="Y",V$57,IF(V$6>=EOMONTH($H$110,0),1,0)) -> 0 | W115: =$D$110/1000000/12*IF($I$110="Y",W$57,IF(W$6>=EOMONTH($H$110,0),1,0)) -> 0 | X115: =$D$110/1000000/12*IF($I$110="Y",X$57,IF(X$6>=EOMONTH($H$110,0),1,0)) -> 0 | Y115: =$D$110/1000000/12*IF($I$110="Y",Y$57,IF(Y$6>=EOMONTH($H$110,0),1,0)) -> 0 | Z115: =$D$110/1000000/12*IF($I$110="Y",Z$57,IF(Z$6>=EOMONTH($H$110,0),1,0)) -> 0 | AA115: =$D$110/1000000/12*IF($I$110="Y",AA$57,IF(AA$6>=EOMONTH($H$110,0),1,0)) -> 0 | ... CA115: =$D$110/1000000/12*IF($I$110="Y",CA$57,IF(CA$6>=EOMONTH($H$110,0),1,0)) -> 0
B116: OPEX - Support & maintenance [RUN] | K116: =SUMIFS($T116:$CA116,$T$5:$CA$5,2030) -> 0 | L116: =SUMIFS($T116:$CA116,$T$5:$CA$5,2026) -> 0 | M116: =SUMIFS($T116:$CA116,$T$5:$CA$5,2027) -> 0 | N116: =SUMIFS($T116:$CA116,$T$5:$CA$5,2028) -> 0 | O116: =SUMIFS($T116:$CA116,$T$5:$CA$5,2029) -> 0 | P116: =SUMIFS($T116:$CA116,$T$5:$CA$5,2030) -> 0 | T116: =$D$111/1000000/12*IF($I$111="Y",T$57,IF(T$6>=EOMONTH($H$111,0),1,0)) -> 0 | U116: =$D$111/1000000/12*IF($I$111="Y",U$57,IF(U$6>=EOMONTH($H$111,0),1,0)) -> 0 | V116: =$D$111/1000000/12*IF($I$111="Y",V$57,IF(V$6>=EOMONTH($H$111,0),1,0)) -> 0 | W116: =$D$111/1000000/12*IF($I$111="Y",W$57,IF(W$6>=EOMONTH($H$111,0),1,0)) -> 0 | X116: =$D$111/1000000/12*IF($I$111="Y",X$57,IF(X$6>=EOMONTH($H$111,0),1,0)) -> 0 | Y116: =$D$111/1000000/12*IF($I$111="Y",Y$57,IF(Y$6>=EOMONTH($H$111,0),1,0)) -> 0 | Z116: =$D$111/1000000/12*IF($I$111="Y",Z$57,IF(Z$6>=EOMONTH($H$111,0),1,0)) -> 0 | AA116: =$D$111/1000000/12*IF($I$111="Y",AA$57,IF(AA$6>=EOMONTH($H$111,0),1,0)) -> 0 | ... CA116: =$D$111/1000000/12*IF($I$111="Y",CA$57,IF(CA$6>=EOMONTH($H$111,0),1,0)) -> 0
B117: Total run cost ($M) | K117: =SUM(K114:K116) -> 0 | L117: =SUM(L114:L116) -> 0 | M117: =SUM(M114:M116) -> 0 | N117: =SUM(N114:N116) -> 0 | O117: =SUM(O114:O116) -> 0 | P117: =SUM(P114:P116) -> 0
B119: 7. WAVE MAPPING (reference)
B121: Model row 63 — Revenue - Acceleration from UW & pricing cycle time | F121: → WAVE row 66 (Section II — Recurring Benefits)
B122: Model row 64 — Revenue - RoS / pricing uplift | F122: → WAVE row 67 (Section II — Recurring Benefits)
B123: Model row 65 — OPEX - Seller capacity freed (UW & pricing) | F123: → WAVE row 79 (Section II — Recurring Benefits)
B124: Model row 114 — OPEX - Token cost for agents | F124: → WAVE row 107 (Section II — Recurring Costs)
...

Sheet SALES-1 WAVE
L1: 1 | M1: 2 | N1: 3 | O1: 4 | P1: 5 | R1: =COUNTIFS($R$66:$R$117, "Error") -> 0 | T1: 2026 | U1: 2026 | V1: 2026 | W1: 2026 | X1: 2026 | Y1: 2026 | Z1: 2026 | AA1: 2026 | AB1: 2026 | AC1: 2026 | AD1: 2026 | AE1: 2026 | AF1: 2027 | AG1: 2027 | AH1: 2027 | AI1: 2027 | AJ1: 2027 | AK1: 2027 | AL1: 2027 | AM1: 2027 | AN1: 2027 | AO1: 2027 | AP1: 2027 | AQ1: 2027 | AR1: 2028 | AS1: 2028 | AT1: 2028 | AU1: 2028 | AV1: 2028 | AW1: 2028 | AX1: 2028 | AY1: 2028 | AZ1: 2028 | BA1: 2028 | BB1: 2028 | BC1: 2028 | BD1: 2029 | BE1: 2029 | BF1: 2029 | BG1: 2029 | BH1: 2029 | BI1: 2029 | BJ1: 2029 | BK1: 2029 | BL1: 2029 | BM1: 2029 | BN1: 2029 | BO1: 2029 | BP1: 2030 | BQ1: 2030 | BR1: 2030 | BS1: 2030 | BT1: 2030 | BU1: 2030 | BV1: 2030 | BW1: 2030 | BX1: 2030 | BY1: 2030 | BZ1: 2030 | CA1: 2030 | CI1: =COUNTIFS(CI$66:CI$149, "FALSE") -> 0 | CJ1: =COUNTIFS(CJ$66:CJ$149, "FALSE") -> 0 | CK1: =COUNTIFS(CK$66:CK$149, "FALSE") -> 0 | CL1: =COUNTIFS(CL$66:CL$149, "FALSE") -> 0 | CM1: =COUNTIFS(CM$66:CM$149, "FALSE") -> 0
C2: ="#"&$F$6&" Initiative Business Case" -> #TBD Initiative Business Case
C4: INPUTS & ASSUMPTIONS
D6: Initiative # | F6: TBD
D7: Initiative Owner | F7: Sales initiative owner — TBC
D8: Initiative Name | F8: Agentic underwriting and pricing for the front book — faster cycle times, freed seller capacity, RoS uplift
D11: Estimated L4 date | F11: ='SALES-1 Model'!$D$13 -> 46478
D12: Net Recurring Benefit ($M) | F12: =$K$117 -> 0
C14: SECTION I - PRIMARY VALUE DRIVER (ILLUSTRATIVE)
D16: Primary value driver — linked to the Model sheet; refine with the initiative owner
D17: Baseline | H17: Period | I17: KPI | J17: Inputs
E18: Front-book NSR in scope | H18: TTM 6/1/26 | I18: $USD M | J18: ='SALES-1 Model'!$D$26/1000000 -> 0
E19: Transaction margin (TM % of NSR) | H19: TTM 6/1/26 | I19: % | J19: ='SALES-1 Model'!$D$27 -> 0
E20: In-scope margin base | H20: TTM 6/1/26 | I20: $USD M | J20: ='SALES-1 Model'!$D$49/1000000 -> 0
E21: Sellers in scope x FLC | H21: TTM 6/1/26 | I21: $USD M | J21: ='SALES-1 Model'!$D$28*'SALES-1 Model'!$D$29/1000000 -> 0
D23: Goal
E24: UW / pricing cycle-time reduction | H24: Steady state | I24: % (UW) | J24: ='SALES-1 Model'!$D$32 -> 0.7
E25: Seller capacity freed x capture | H25: Steady state | I25: % | J25: =(('SALES-1 Model'!$D$38+'SALES-1 Model'!$D$39)/2)*'SALES-1 Model'!$D$40 -> 0.21125
D28: Incremental Improvement
E29: Total annual benefit (run rate) | I29: $USD M | J29: =('SALES-1 Model'!$D$50+'SALES-1 Model'!$D$51+'SALES-1 Model'!$D$52)/1000000 -> 0
C60: SECTION II - NET RECURRING BENEFITS | CC60: ANNUAL SUMMARY | CI60: CHECK CELLS
T62: 2026 | AF62: 2027 | AR62: 2028 | BD62: 2029 | BP62: 2030 | CI62: CHECK
D63: RECURRING BENEFITS | H63: Comment | I63: Baseline | J63: Goal | K63: Ann. Run Rate | L63: 2026 | M63: =L63+1 -> 2027 | N63: =M63+1 -> 2028 | O63: =N63+1 -> 2029 | P63: =O63+1 -> 2030 | Q63: Impacted BU | R63: Check | T63: 46023 | U63: =EOMONTH(T63, 1) -> 46081 | V63: =EOMONTH(U63, 1) -> 46112 | W63: =EOMONTH(V63, 1) -> 46142 | X63: =EOMONTH(W63, 1) -> 46173 | Y63: =EOMONTH(X63, 1) -> 46203 | Z63: =EOMONTH(Y63, 1) -> 46234 | AA63: =EOMONTH(Z63, 1) -> 46265 | AB63: =EOMONTH(AA63, 1) -> 46295 | ... CA63: =EOMONTH(BZ63, 1) -> 47848 | CC63: 2026 | CD63: =CC63+1 -> 2027 | CE63: =CD63+1 -> 2028 | CF63: =CE63+1 -> 2029 | CG63: =CF63+1 -> 2030 | CI63: 2026 | CJ63: =CI63+1 -> 2027 | CK63: =CJ63+1 -> 2028 | CL63: =CK63+1 -> 2029 | CM63: =CL63+1 -> 2030
E64: $USD M | I64: =$H$18 -> TTM 6/1/26 | J64: Future State | K64: Increment
E65: Revenue
E66: Revenue - Acceleration from UW & pricing cycle time | H66: Margin base uplift from faster cycle times (incremental share only) | I66: ='SALES-1 Model'!$D$63 -> 0 | J66: =I66+'SALES-1 Model'!$K$63 -> 0 | K66: ='SALES-1 Model'!$K$63 -> 0 | L66: ='SALES-1 Model'!L63 -> 0 | M66: ='SALES-1 Model'!M63 -> 0 | N66: ='SALES-1 Model'!N63 -> 0 | O66: ='SALES-1 Model'!O63 -> 0 | P66: ='SALES-1 Model'!P63 -> 0 | Q66: Global Sales | R66: =IF(K66=P66, "", "Error") | T66: ='SALES-1 Model'!T63 -> 0 | U66: ='SALES-1 Model'!U63 -> 0 | V66: ='SALES-1 Model'!V63 -> 0 | W66: ='SALES-1 Model'!W63 -> 0 | X66: ='SALES-1 Model'!X63 -> 0 | Y66: ='SALES-1 Model'!Y63 -> 0 | Z66: ='SALES-1 Model'!Z63 -> 0 | AA66: ='SALES-1 Model'!AA63 -> 0 | ... CA66: ='SALES-1 Model'!CA63 -> 0 | CC66: =SUMIFS($T66:$CA66, $T$1:$CA$1, CC$63) -> 0 | CD66: =SUMIFS($T66:$CA66, $T$1:$CA$1, CD$63) -> 0 | CE66: =SUMIFS($T66:$CA66, $T$1:$CA$1, CE$63) -> 0 | CF66: =SUMIFS($T66:$CA66, $T$1:$CA$1, CF$63) -> 0 | CG66: =SUMIFS($T66:$CA66, $T$1:$CA$1, CG$63) -> 0 | CI66: =CC66=L66 -> 1 | CJ66: =CD66=M66 -> 1 | CK66: =CE66=N66 -> 1 | CL66: =CF66=O66 -> 1 | CM66: =CG66=P66 -> 1
E67: Revenue - RoS / pricing uplift | H67: 2–3% RoS uplift at 75% capture (midpoint seeded) | I67: ='SALES-1 Model'!$D$64 -> 0 | J67: =I67+'SALES-1 Model'!$K$64 -> 0 | K67: ='SALES-1 Model'!$K$64 -> 0 | L67: ='SALES-1 Model'!L64 -> 0 | M67: ='SALES-1 Model'!M64 -> 0 | N67: ='SALES-1 Model'!N64 -> 0 | O67: ='SALES-1 Model'!O64 -> 0 | P67: ='SALES-1 Model'!P64 -> 0 | Q67: Global Sales | R67: =IF(K67=P67, "", "Error") | T67: ='SALES-1 Model'!T64 -> 0 | U67: ='SALES-1 Model'!U64 -> 0 | V67: ='SALES-1 Model'!V64 -> 0 | W67: ='SALES-1 Model'!W64 -> 0 | X67: ='SALES-1 Model'!X64 -> 0 | Y67: ='SALES-1 Model'!Y64 -> 0 | Z67: ='SALES-1 Model'!Z64 -> 0 | AA67: ='SALES-1 Model'!AA64 -> 0 | ... CA67: ='SALES-1 Model'!CA64 -> 0 | CC67: =SUMIFS($T67:$CA67, $T$1:$CA$1, CC$63) -> 0 | CD67: =SUMIFS($T67:$CA67, $T$1:$CA$1, CD$63) -> 0 | CE67: =SUMIFS($T67:$CA67, $T$1:$CA$1, CE$63) -> 0 | CF67: =SUMIFS($T67:$CA67, $T$1:$CA$1, CF$63) -> 0 | CG67: =SUMIFS($T67:$CA67, $T$1:$CA$1, CG$63) -> 0 | CI67: =CC67=L67 -> 1 | CJ67: =CD67=M67 -> 1 | CK67: =CE67=N67 -> 1 | CL67: =CF67=O67 -> 1 | CM67: =CG67=P67 -> 1
E68: Revenue Subtotal | I68: =SUM(I66:I67) -> 0 | J68: =SUM(J66:J67) -> 0 | K68: =SUM(K66:K67) -> 0 | L68: =SUM(L66:L67) -> 0 | M68: =SUM(M66:M67) -> 0 | N68: =SUM(N66:N67) -> 0 | O68: =SUM(O66:O67) -> 0 | P68: =SUM(P66:P67) -> 0 | T68: =SUM(T66:T67) -> 0 | U68: =SUM(U66:U67) -> 0 | V68: =SUM(V66:V67) -> 0 | W68: =SUM(W66:W67) -> 0 | X68: =SUM(X66:X67) -> 0 | Y68: =SUM(Y66:Y67) -> 0 | Z68: =SUM(Z66:Z67) -> 0 | AA68: =SUM(AA66:AA67) -> 0 | ... CA68: =SUM(CA66:CA67) -> 0 | CC68: =SUM(CC66:CC67) -> 0 | CD68: =SUM(CD66:CD67) -> 0 | CE68: =SUM(CE66:CE67) -> 0 | CF68: =SUM(CF66:CF67) -> 0 | CG68: =SUM(CG66:CG67) -> 0 | CI68: =CC68=L68 -> 1 | CJ68: =CD68=M68 -> 1 | CK68: =CE68=N68 -> 1 | CL68: =CF68=O68 -> 1 | CM68: =CG68=P68 -> 1
E70: Cost of Sales
K71: =I71-J71 -> 0 | R71: =IF(K71=P71, "", "Error") | CC71: =SUMIFS($T71:$CA71, $T$1:$CA$1, CC$63) -> 0 | CD71: =SUMIFS($T71:$CA71, $T$1:$CA$1, CD$63) -> 0 | CE71: =SUMIFS($T71:$CA71, $T$1:$CA$1, CE$63) -> 0 | CF71: =SUMIFS($T71:$CA71, $T$1:$CA$1, CF$63) -> 0 | CG71: =SUMIFS($T71:$CA71, $T$1:$CA$1, CG$63) -> 0 | CI71: =CC71=L71 -> 1 | CJ71: =CD71=M71 -> 1 | CK71: =CE71=N71 -> 1 | CL71: =CF71=O71 -> 1 | CM71: =CG71=P71 -> 1
I72: 0 | J72: 0 | K72: =I72-J72 -> 0 | R72: =IF(K72=P72, "", "Error") | CC72: =SUMIFS($T72:$CA72, $T$1:$CA$1, CC$63) -> 0 | CD72: =SUMIFS($T72:$CA72, $T$1:$CA$1, CD$63) -> 0 | CE72: =SUMIFS($T72:$CA72, $T$1:$CA$1, CE$63) -> 0 | CF72: =SUMIFS($T72:$CA72, $T$1:$CA$1, CF$63) -> 0 | CG72: =SUMIFS($T72:$CA72, $T$1:$CA$1, CG$63) -> 0 | CI72: =CC72=L72 -> 1 | CJ72: =CD72=M72 -> 1 | CK72: =CE72=N72 -> 1 | CL72: =CF72=O72 -> 1 | CM72: =CG72=P72 -> 1
I73: 0 | J73: 0 | K73: =I73-J73 -> 0 | R73: =IF(K73=P73, "", "Error") | CC73: =SUMIFS($T73:$CA73, $T$1:$CA$1, CC$63) -> 0 | CD73: =SUMIFS($T73:$CA73, $T$1:$CA$1, CD$63) -> 0 | CE73: =SUMIFS($T73:$CA73, $T$1:$CA$1, CE$63) -> 0 | CF73: =SUMIFS($T73:$CA73, $T$1:$CA$1, CF$63) -> 0 | CG73: =SUMIFS($T73:$CA73, $T$1:$CA$1, CG$63) -> 0 | CI73: =CC73=L73 -> 1 | CJ73: =CD73=M73 -> 1 | CK73: =CE73=N73 -> 1 | CL73: =CF73=O73 -> 1 | CM73: =CG73=P73 -> 1
I74: 0 | J74: 0 | K74: =I74-J74 -> 0 | R74: =IF(K74=P74, "", "Error") | CC74: =SUMIFS($T74:$CA74, $T$1:$CA$1, CC$63) -> 0 | CD74: =SUMIFS($T74:$CA74, $T$1:$CA$1, CD$63) -> 0 | CE74: =SUMIFS($T74:$CA74, $T$1:$CA$1, CE$63) -> 0 | CF74: =SUMIFS($T74:$CA74, $T$1:$CA$1, CF$63) -> 0 | CG74: =SUMIFS($T74:$CA74, $T$1:$CA$1, CG$63) -> 0 | CI74: =CC74=L74 -> 1 | CJ74: =CD74=M74 -> 1 | CK74: =CE74=N74 -> 1 | CL74: =CF74=O74 -> 1 | CM74: =CG74=P74 -> 1
K75: =I75-J75 -> 0 | R75: =IF(K75=P75, "", "Error") | CC75: =SUMIFS($T75:$CA75, $T$1:$CA$1, CC$63) -> 0 | CD75: =SUMIFS($T75:$CA75, $T$1:$CA$1, CD$63) -> 0 | CE75: =SUMIFS($T75:$CA75, $T$1:$CA$1, CE$63) -> 0 | CF75: =SUMIFS($T75:$CA75, $T$1:$CA$1, CF$63) -> 0 | CG75: =SUMIFS($T75:$CA75, $T$1:$CA$1, CG$63) -> 0 | CI75: =CC75=L75 -> 1 | CJ75: =CD75=M75 -> 1 | CK75: =CE75=N75 -> 1 | CL75: =CF75=O75 -> 1 | CM75: =CG75=P75 -> 1
E76: Cost of Sales Subtotal | I76: =SUM(I71:I75) -> 0 | J76: =SUM(J71:J75) -> 0 | K76: =SUM(K71:K75) -> 0 | L76: =SUM(L71:L75) -> 0 | M76: =SUM(M71:M75) -> 0 | N76: =SUM(N71:N75) -> 0 | O76: =SUM(O71:O75) -> 0 | P76: =SUM(P71:P75) -> 0 | T76: =SUM(T71:T75) -> 0 | U76: =SUM(U71:U75) -> 0 | V76: =SUM(V71:V75) -> 0 | W76: =SUM(W71:W75) -> 0 | X76: =SUM(X71:X75) -> 0 | Y76: =SUM(Y71:Y75) -> 0 | Z76: =SUM(Z71:Z75) -> 0 | AA76: =SUM(AA71:AA75) -> 0 | ... CA76: =SUM(CA71:CA75) -> 0 | CC76: =SUM(CC71:CC75) -> 0 | CD76: =SUM(CD71:CD75) -> 0 | CE76: =SUM(CE71:CE75) -> 0 | CF76: =SUM(CF71:CF75) -> 0 | CG76: =SUM(CG71:CG75) -> 0 | CI76: =CC76=L76 -> 1 | CJ76: =CD76=M76 -> 1 | CK76: =CE76=N76 -> 1 | CL76: =CF76=O76 -> 1 | CM76: =CG76=P76 -> 1
E78: OPEX
E79: OPEX - Seller capacity freed (UW & pricing) | H79: 30–40% (UW) / 25–35% (pricing) seller capacity freed at 65% capture | I79: ='SALES-1 Model'!$D$65 -> 0 | J79: =I79-'SALES-1 Model'!$K$65 -> 0 | K79: ='SALES-1 Model'!$K$65 -> 0 | L79: ='SALES-1 Model'!L65 -> 0 | M79: ='SALES-1 Model'!M65 -> 0 | N79: ='SALES-1 Model'!N65 -> 0 | O79: ='SALES-1 Model'!O65 -> 0 | P79: ='SALES-1 Model'!P65 -> 0 | Q79: Global Sales | R79: =IF(K79=P79, "", "Error") | T79: ='SALES-1 Model'!T65 -> 0 | U79: ='SALES-1 Model'!U65 -> 0 | V79: ='SALES-1 Model'!V65 -> 0 | W79: ='SALES-1 Model'!W65 -> 0 | X79: ='SALES-1 Model'!X65 -> 0 | Y79: ='SALES-1 Model'!Y65 -> 0 | Z79: ='SALES-1 Model'!Z65 -> 0 | AA79: ='SALES-1 Model'!AA65 -> 0 | ... CA79: ='SALES-1 Model'!CA65 -> 0 | CC79: =SUMIFS($T79:$CA79, $T$1:$CA$1, CC$63) -> 0 | CD79: =SUMIFS($T79:$CA79, $T$1:$CA$1, CD$63) -> 0 | CE79: =SUMIFS($T79:$CA79, $T$1:$CA$1, CE$63) -> 0 | CF79: =SUMIFS($T79:$CA79, $T$1:$CA$1, CF$63) -> 0 | CG79: =SUMIFS($T79:$CA79, $T$1:$CA$1, CG$63) -> 0 | CI79: =CC79=L79 -> 1 | CJ79: =CD79=M79 -> 1 | CK79: =CE79=N79 -> 1 | CL79: =CF79=O79 -> 1 | CM79: =CG79=P79 -> 1
I80: 0 | J80: 0 | K80: =I80-J80 -> 0 | R80: =IF(K80=P80, "", "Error") | CC80: =SUMIFS($T80:$CA80, $T$1:$CA$1, CC$63) -> 0 | CD80: =SUMIFS($T80:$CA80, $T$1:$CA$1, CD$63) -> 0 | CE80: =SUMIFS($T80:$CA80, $T$1:$CA$1, CE$63) -> 0 | CF80: =SUMIFS($T80:$CA80, $T$1:$CA$1, CF$63) -> 0 | CG80: =SUMIFS($T80:$CA80, $T$1:$CA$1, CG$63) -> 0 | CI80: =CC80=L80 -> 1 | CJ80: =CD80=M80 -> 1 | CK80: =CE80=N80 -> 1 | CL80: =CF80=O80 -> 1 | CM80: =CG80=P80 -> 1
I81: 0 | J81: 0 | K81: =I81-J81 -> 0 | R81: =IF(K81=P81, "", "Error") | CC81: =SUMIFS($T81:$CA81, $T$1:$CA$1, CC$63) -> 0 | CD81: =SUMIFS($T81:$CA81, $T$1:$CA$1, CD$63) -> 0 | CE81: =SUMIFS($T81:$CA81, $T$1:$CA$1, CE$63) -> 0 | CF81: =SUMIFS($T81:$CA81, $T$1:$CA$1, CF$63) -> 0 | CG81: =SUMIFS($T81:$CA81, $T$1:$CA$1, CG$63) -> 0 | CI81: =CC81=L81 -> 1 | CJ81: =CD81=M81 -> 1 | CK81: =CE81=N81 -> 1 | CL81: =CF81=O81 -> 1 | CM81: =CG81=P81 -> 1
I82: 0 | J82: 0 | K82: =I82-J82 -> 0 | R82: =IF(K82=P82, "", "Error") | CC82: =SUMIFS($T82:$CA82, $T$1:$CA$1, CC$63) -> 0 | CD82: =SUMIFS($T82:$CA82, $T$1:$CA$1, CD$63) -> 0 | CE82: =SUMIFS($T82:$CA82, $T$1:$CA$1, CE$63) -> 0 | CF82: =SUMIFS($T82:$CA82, $T$1:$CA$1, CF$63) -> 0 | CG82: =SUMIFS($T82:$CA82, $T$1:$CA$1, CG$63) -> 0 | CI82: =CC82=L82 -> 1 | CJ82: =CD82=M82 -> 1 | CK82: =CE82=N82 -> 1 | CL82: =CF82=O82 -> 1 | CM82: =CG82=P82 -> 1
I83: 0 | J83: 0 | K83: =I83-J83 -> 0 | R83: =IF(K83=P83, "", "Error") | CC83: =SUMIFS($T83:$CA83, $T$1:$CA$1, CC$63) -> 0 | CD83: =SUMIFS($T83:$CA83, $T$1:$CA$1, CD$63) -> 0 | CE83: =SUMIFS($T83:$CA83, $T$1:$CA$1, CE$63) -> 0 | CF83: =SUMIFS($T83:$CA83, $T$1:$CA$1, CF$63) -> 0 | CG83: =SUMIFS($T83:$CA83, $T$1:$CA$1, CG$63) -> 0 | CI83: =CC83=L83 -> 1 | CJ83: =CD83=M83 -> 1 | CK83: =CE83=N83 -> 1 | CL83: =CF83=O83 -> 1 | CM83: =CG83=P83 -> 1
E84: OpEx subtotal | I84: =SUM(I79:I83) -> 0 | J84: =SUM(J79:J83) -> 0 | K84: =SUM(K79:K83) -> 0 | L84: =SUM(L79:L83) -> 0 | M84: =SUM(M79:M83) -> 0 | N84: =SUM(N79:N83) -> 0 | O84: =SUM(O79:O83) -> 0 | P84: =SUM(P79:P83) -> 0 | T84: =SUM(T79:T83) -> 0 | U84: =SUM(U79:U83) -> 0 | V84: =SUM(V79:V83) -> 0 | W84: =SUM(W79:W83) -> 0 | X84: =SUM(X79:X83) -> 0 | Y84: =SUM(Y79:Y83) -> 0 | Z84: =SUM(Z79:Z83) -> 0 | AA84: =SUM(AA79:AA83) -> 0 | ... CA84: =SUM(CA79:CA83) -> 0 | CC84: =SUM(CC79:CC83) -> 0 | CD84: =SUM(CD79:CD83) -> 0 | CE84: =SUM(CE79:CE83) -> 0 | CF84: =SUM(CF79:CF83) -> 0 | CG84: =SUM(CG79:CG83) -> 0 | CI84: =CC84=L84 -> 1 | CJ84: =CD84=M84 -> 1 | CK84: =CE84=N84 -> 1 | CL84: =CF84=O84 -> 1 | CM84: =CG84=P84 -> 1
E88: Recurring Benefits Total | I88: =SUM(I68, I76, I84) -> 0 | J88: =SUM(J68, J76, J84) -> 0 | K88: =SUM(K68, K76, K84) -> 0 | L88: =SUM(L68, L76, L84) -> 0 | M88: =SUM(M68, M76, M84) -> 0 | N88: =SUM(N68, N76, N84) -> 0 | O88: =SUM(O68, O76, O84) -> 0 | P88: =SUM(P68, P76, P84) -> 0 | T88: =SUM(T68, T76, T84) -> 0 | U88: =SUM(U68, U76, U84) -> 0 | V88: =SUM(V68, V76, V84) -> 0 | W88: =SUM(W68, W76, W84) -> 0 | X88: =SUM(X68, X76, X84) -> 0 | Y88: =SUM(Y68, Y76, Y84) -> 0 | Z88: =SUM(Z68, Z76, Z84) -> 0 | AA88: =SUM(AA68, AA76, AA84) -> 0 | ... CA88: =SUM(CA68, CA76, CA84) -> 0 | CC88: =SUM(CC68, CC76, CC84) -> 0 | CD88: =SUM(CD68, CD76, CD84) -> 0 | CE88: =SUM(CE68, CE76, CE84) -> 0 | CF88: =SUM(CF68, CF76, CF84) -> 0 | CG88: =SUM(CG68, CG76, CG84) -> 0 | CH88: =SUM(CH68, CH76, CH84) -> 0 | CI88: =CC88=L88 -> 1 | CJ88: =CD88=M88 -> 1 | CK88: =CE88=N88 -> 1 | CL88: =CF88=O88 -> 1 | CM88: =CG88=P88 -> 1
T90: 2026 | AF90: 2027 | AR90: 2028 | BD90: 2029 | BP90: 2030 | CI90: CHECK
D91: RECURRING COSTS TO ACHIEVE IMPACT | H91: Comment | I91: Baseline | J91: Goal | K91: Ann. Run Rate | L91: 2026 | M91: =L91+1 -> 2027 | N91: =M91+1 -> 2028 | O91: =N91+1 -> 2029 | P91: =O91+1 -> 2030 | Q91: Impacted BU | R91: Check | T91: 46023 | U91: =EOMONTH(T91, 1) -> 46081 | V91: =EOMONTH(U91, 1) -> 46112 | W91: =EOMONTH(V91, 1) -> 46142 | X91: =EOMONTH(W91, 1) -> 46173 | Y91: =EOMONTH(X91, 1) -> 46203 | Z91: =EOMONTH(Y91, 1) -> 46234 | AA91: =EOMONTH(Z91, 1) -> 46265 | AB91: =EOMONTH(AA91, 1) -> 46295 | ... CA91: =EOMONTH(BZ91, 1) -> 47848 | CC91: 2026 | CD91: =CC91+1 -> 2027 | CE91: =CD91+1 -> 2028 | CF91: =CE91+1 -> 2029 | CG91: =CF91+1 -> 2030 | CI91: 2026 | CJ91: =CI91+1 -> 2027 | CK91: =CJ91+1 -> 2028 | CL91: =CK91+1 -> 2029 | CM91: =CL91+1 -> 2030
E92: $USD M | I92: =$H$18 -> TTM 6/1/26 | J92: Future State | K92: Increment
E93: Revenue
I94: 0 | J94: 0 | K94: =J94-I94 -> 0 | R94: =IF(K94=P94, "", "Error") | CC94: =SUMIFS($T94:$CA94, $T$1:$CA$1, CC$63) -> 0 | CD94: =SUMIFS($T94:$CA94, $T$1:$CA$1, CD$63) -> 0 | CE94: =SUMIFS($T94:$CA94, $T$1:$CA$1, CE$63) -> 0 | CF94: =SUMIFS($T94:$CA94, $T$1:$CA$1, CF$63) -> 0 | CG94: =SUMIFS($T94:$CA94, $T$1:$CA$1, CG$63) -> 0 | CI94: =CC94=L94 -> 1 | CJ94: =CD94=M94 -> 1 | CK94: =CE94=N94 -> 1 | CL94: =CF94=O94 -> 1 | CM94: =CG94=P94 -> 1
I95: 0 | J95: 0 | K95: =J95-I95 -> 0 | R95: =IF(K95=P95, "", "Error") | CC95: =SUMIFS($T95:$CA95, $T$1:$CA$1, CC$63) -> 0 | CD95: =SUMIFS($T95:$CA95, $T$1:$CA$1, CD$63) -> 0 | CE95: =SUMIFS($T95:$CA95, $T$1:$CA$1, CE$63) -> 0 | CF95: =SUMIFS($T95:$CA95, $T$1:$CA$1, CF$63) -> 0 | CG95: =SUMIFS($T95:$CA95, $T$1:$CA$1, CG$63) -> 0 | CI95: =CC95=L95 -> 1 | CJ95: =CD95=M95 -> 1 | CK95: =CE95=N95 -> 1 | CL95: =CF95=O95 -> 1 | CM95: =CG95=P95 -> 1
E96: Revenue Subtotal | I96: =SUM(I94:I95) -> 0 | J96: =SUM(J94:J95) -> 0 | K96: =SUM(K94:K95) -> 0 | L96: =SUM(L94:L95) -> 0 | M96: =SUM(M94:M95) -> 0 | N96: =SUM(N94:N95) -> 0 | O96: =SUM(O94:O95) -> 0 | P96: =SUM(P94:P95) -> 0 | T96: =SUM(T94:T95) -> 0 | U96: =SUM(U94:U95) -> 0 | V96: =SUM(V94:V95) -> 0 | W96: =SUM(W94:W95) -> 0 | X96: =SUM(X94:X95) -> 0 | Y96: =SUM(Y94:Y95) -> 0 | Z96: =SUM(Z94:Z95) -> 0 | AA96: =SUM(AA94:AA95) -> 0 | ... CA96: =SUM(CA94:CA95) -> 0 | CC96: =SUM(CC94:CC95) -> 0 | CD96: =SUM(CD94:CD95) -> 0 | CE96: =SUM(CE94:CE95) -> 0 | CF96: =SUM(CF94:CF95) -> 0 | CG96: =SUM(CG94:CG95) -> 0 | CI96: =CC96=L96 -> 1 | CJ96: =CD96=M96 -> 1 | CK96: =CE96=N96 -> 1 | CL96: =CF96=O96 -> 1 | CM96: =CG96=P96 -> 1
E98: Cost of Sales
I99: 0 | J99: 0 | K99: =J99-I99 -> 0 | L99: 0 | M99: 0 | N99: 0 | O99: 0 | P99: 0 | R99: =IF(K99=P99, "", "Error") | CC99: =SUMIFS($T99:$CA99, $T$1:$CA$1, CC$63) -> 0 | CD99: =SUMIFS($T99:$CA99, $T$1:$CA$1, CD$63) -> 0 | CE99: =SUMIFS($T99:$CA99, $T$1:$CA$1, CE$63) -> 0 | CF99: =SUMIFS($T99:$CA99, $T$1:$CA$1, CF$63) -> 0 | CG99: =SUMIFS($T99:$CA99, $T$1:$CA$1, CG$63) -> 0 | CI99: =CC99=L99 -> 1 | CJ99: =CD99=M99 -> 1 | CK99: =CE99=N99 -> 1 | CL99: =CF99=O99 -> 1 | CM99: =CG99=P99 -> 1
I100: 0 | J100: 0 | K100: =J100-I100 -> 0 | L100: 0 | M100: 0 | N100: 0 | O100: 0 | P100: 0 | R100: =IF(K100=P100, "", "Error") | CC100: =SUMIFS($T100:$CA100, $T$1:$CA$1, CC$63) -> 0 | CD100: =SUMIFS($T100:$CA100, $T$1:$CA$1, CD$63) -> 0 | CE100: =SUMIFS($T100:$CA100, $T$1:$CA$1, CE$63) -> 0 | CF100: =SUMIFS($T100:$CA100, $T$1:$CA$1, CF$63) -> 0 | CG100: =SUMIFS($T100:$CA100, $T$1:$CA$1, CG$63) -> 0 | CI100: =CC100=L100 -> 1 | CJ100: =CD100=M100 -> 1 | CK100: =CE100=N100 -> 1 | CL100: =CF100=O100 -> 1 | CM100: =CG100=P100 -> 1
I101: 0 | J101: 0 | K101: =J101-I101 -> 0 | L101: 0 | M101: 0 | N101: 0 | O101: 0 | P101: 0 | R101: =IF(K101=P101, "", "Error") | CC101: =SUMIFS($T101:$CA101, $T$1:$CA$1, CC$63) -> 0 | CD101: =SUMIFS($T101:$CA101, $T$1:$CA$1, CD$63) -> 0 | CE101: =SUMIFS($T101:$CA101, $T$1:$CA$1, CE$63) -> 0 | CF101: =SUMIFS($T101:$CA101, $T$1:$CA$1, CF$63) -> 0 | CG101: =SUMIFS($T101:$CA101, $T$1:$CA$1, CG$63) -> 0 | CI101: =CC101=L101 -> 1 | CJ101: =CD101=M101 -> 1 | CK101: =CE101=N101 -> 1 | CL101: =CF101=O101 -> 1 | CM101: =CG101=P101 -> 1
I102: 0 | J102: 0 | K102: =J102-I102 -> 0 | L102: 0 | M102: 0 | N102: 0 | O102: 0 | P102: 0 | R102: =IF(K102=P102, "", "Error") | CC102: =SUMIFS($T102:$CA102, $T$1:$CA$1, CC$63) -> 0 | CD102: =SUMIFS($T102:$CA102, $T$1:$CA$1, CD$63) -> 0 | CE102: =SUMIFS($T102:$CA102, $T$1:$CA$1, CE$63) -> 0 | CF102: =SUMIFS($T102:$CA102, $T$1:$CA$1, CF$63) -> 0 | CG102: =SUMIFS($T102:$CA102, $T$1:$CA$1, CG$63) -> 0 | CI102: =CC102=L102 -> 1 | CJ102: =CD102=M102 -> 1 | CK102: =CE102=N102 -> 1 | CL102: =CF102=O102 -> 1 | CM102: =CG102=P102 -> 1
K103: =J103-I103 -> 0 | L103: 0 | M103: 0 | N103: 0 | O103: 0 | P103: 0
E104: Cost of Sales Subtotal | I104: =SUM(I99:I103) -> 0 | J104: =SUM(J99:J103) -> 0 | K104: =SUM(K99:K103) -> 0 | L104: =SUM(L99:L103) -> 0 | M104: =SUM(M99:M103) -> 0 | N104: =SUM(N99:N103) -> 0 | O104: =SUM(O99:O103) -> 0 | P104: =SUM(P99:P103) -> 0 | T104: =SUM(T99:T103) -> 0 | U104: =SUM(U99:U103) -> 0 | V104: =SUM(V99:V103) -> 0 | W104: =SUM(W99:W103) -> 0 | X104: =SUM(X99:X103) -> 0 | Y104: =SUM(Y99:Y103) -> 0 | Z104: =SUM(Z99:Z103) -> 0 | AA104: =SUM(AA99:AA103) -> 0 | ... CA104: =SUM(CA99:CA103) -> 0 | CC104: =SUM(CC99:CC103) -> 0 | CD104: =SUM(CD99:CD103) -> 0 | CE104: =SUM(CE99:CE103) -> 0 | CF104: =SUM(CF99:CF103) -> 0 | CG104: =SUM(CG99:CG103) -> 0 | CI104: =CC104=L104 -> 1 | CJ104: =CD104=M104 -> 1 | CK104: =CE104=N104 -> 1 | CL104: =CF104=O104 -> 1 | CM104: =CG104=P104 -> 1
E106: OPEX
E107: OPEX - Token cost for agents | H107: PENDING — placeholder, not data. Agent token consumption — scales with adoption/ramp | I107: 0 | J107: =I107+'SALES-1 Model'!$K$114 -> 0 | K107: ='SALES-1 Model'!$K$114 -> 0 | L107: ='SALES-1 Model'!L114 -> 0 | M107: ='SALES-1 Model'!M114 -> 0 | N107: ='SALES-1 Model'!N114 -> 0 | O107: ='SALES-1 Model'!O114 -> 0 | P107: ='SALES-1 Model'!P114 -> 0 | Q107: Global Sales | R107: =IF(K107=P107, "", "Error") | T107: ='SALES-1 Model'!T114 -> 0 | U107: ='SALES-1 Model'!U114 -> 0 | V107: ='SALES-1 Model'!V114 -> 0 | W107: ='SALES-1 Model'!W114 -> 0 | X107: ='SALES-1 Model'!X114 -> 0 | Y107: ='SALES-1 Model'!Y114 -> 0 | Z107: ='SALES-1 Model'!Z114 -> 0 | AA107: ='SALES-1 Model'!AA114 -> 0 | ... CA107: ='SALES-1 Model'!CA114 -> 0 | CC107: =SUMIFS($T107:$CA107, $T$1:$CA$1, CC$63) -> 0 | CD107: =SUMIFS($T107:$CA107, $T$1:$CA$1, CD$63) -> 0 | CE107: =SUMIFS($T107:$CA107, $T$1:$CA$1, CE$63) -> 0 | CF107: =SUMIFS($T107:$CA107, $T$1:$CA$1, CF$63) -> 0 | CG107: =SUMIFS($T107:$CA107, $T$1:$CA$1, CG$63) -> 0 | CI107: =CC107=L107 -> 1 | CJ107: =CD107=M107 -> 1 | CK107: =CE107=N107 -> 1 | CL107: =CF107=O107 -> 1 | CM107: =CG107=P107 -> 1
E108: OPEX - Vendor / SaaS recurring | H108: PENDING — placeholder, not data. Recurring vendor/licence opex | I108: 0 | J108: =I108+'SALES-1 Model'!$K$115 -> 0 | K108: ='SALES-1 Model'!$K$115 -> 0 | L108: ='SALES-1 Model'!L115 -> 0 | M108: ='SALES-1 Model'!M115 -> 0 | N108: ='SALES-1 Model'!N115 -> 0 | O108: ='SALES-1 Model'!O115 -> 0 | P108: ='SALES-1 Model'!P115 -> 0 | Q108: Global Sales | R108: =IF(K108=P108, "", "Error") | T108: ='SALES-1 Model'!T115 -> 0 | U108: ='SALES-1 Model'!U115 -> 0 | V108: ='SALES-1 Model'!V115 -> 0 | W108: ='SALES-1 Model'!W115 -> 0 | X108: ='SALES-1 Model'!X115 -> 0 | Y108: ='SALES-1 Model'!Y115 -> 0 | Z108: ='SALES-1 Model'!Z115 -> 0 | AA108: ='SALES-1 Model'!AA115 -> 0 | ... CA108: ='SALES-1 Model'!CA115 -> 0 | CC108: =SUMIFS($T108:$CA108, $T$1:$CA$1, CC$63) -> 0 | CD108: =SUMIFS($T108:$CA108, $T$1:$CA$1, CD$63) -> 0 | CE108: =SUMIFS($T108:$CA108, $T$1:$CA$1, CE$63) -> 0 | CF108: =SUMIFS($T108:$CA108, $T$1:$CA$1, CF$63) -> 0 | CG108: =SUMIFS($T108:$CA108, $T$1:$CA$1, CG$63) -> 0 | CI108: =CC108=L108 -> 1 | CJ108: =CD108=M108 -> 1 | CK108: =CE108=N108 -> 1 | CL108: =CF108=O108 -> 1 | CM108: =CG108=P108 -> 1
E109: OPEX - Support & maintenance | H109: PENDING — placeholder, not data. Ongoing support/maintenance | I109: 0 | J109: =I109+'SALES-1 Model'!$K$116 -> 0 | K109: ='SALES-1 Model'!$K$116 -> 0 | L109: ='SALES-1 Model'!L116 -> 0 | M109: ='SALES-1 Model'!M116 -> 0 | N109: ='SALES-1 Model'!N116 -> 0 | O109: ='SALES-1 Model'!O116 -> 0 | P109: ='SALES-1 Model'!P116 -> 0 | Q109: Global Sales | R109: =IF(K109=P109, "", "Error") | T109: ='SALES-1 Model'!T116 -> 0 | U109: ='SALES-1 Model'!U116 -> 0 | V109: ='SALES-1 Model'!V116 -> 0 | W109: ='SALES-1 Model'!W116 -> 0 | X109: ='SALES-1 Model'!X116 -> 0 | Y109: ='SALES-1 Model'!Y116 -> 0 | Z109: ='SALES-1 Model'!Z116 -> 0 | AA109: ='SALES-1 Model'!AA116 -> 0 | ... CA109: ='SALES-1 Model'!CA116 -> 0 | CC109: =SUMIFS($T109:$CA109, $T$1:$CA$1, CC$63) -> 0 | CD109: =SUMIFS($T109:$CA109, $T$1:$CA$1, CD$63) -> 0 | CE109: =SUMIFS($T109:$CA109, $T$1:$CA$1, CE$63) -> 0 | CF109: =SUMIFS($T109:$CA109, $T$1:$CA$1, CF$63) -> 0 | CG109: =SUMIFS($T109:$CA109, $T$1:$CA$1, CG$63) -> 0 | CI109: =CC109=L109 -> 1 | CJ109: =CD109=M109 -> 1 | CK109: =CE109=N109 -> 1 | CL109: =CF109=O109 -> 1 | CM109: =CG109=P109 -> 1
I110: 0 | J110: 0 | K110: =J110-I110 -> 0 | L110: 0 | M110: 0 | N110: 0 | O110: 0 | P110: 0 | R110: =IF(K110=P110, "", "Error") | CC110: =SUMIFS($T110:$CA110, $T$1:$CA$1, CC$63) -> 0 | CD110: =SUMIFS($T110:$CA110, $T$1:$CA$1, CD$63) -> 0 | CE110: =SUMIFS($T110:$CA110, $T$1:$CA$1, CE$63) -> 0 | CF110: =SUMIFS($T110:$CA110, $T$1:$CA$1, CF$63) -> 0 | CG110: =SUMIFS($T110:$CA110, $T$1:$CA$1, CG$63) -> 0 | CI110: =CC110=L110 -> 1 | CJ110: =CD110=M110 -> 1 | CK110: =CE110=N110 -> 1 | CL110: =CF110=O110 -> 1 | CM110: =CG110=P110 -> 1
I111: 0 | J111: 0 | K111: =J111-I111 -> 0 | L111: 0 | M111: 0 | N111: 0 | O111: 0 | P111: 0 | R111: =IF(K111=P111, "", "Error") | CC111: =SUMIFS($T111:$CA111, $T$1:$CA$1, CC$63) -> 0 | CD111: =SUMIFS($T111:$CA111, $T$1:$CA$1, CD$63) -> 0 | CE111: =SUMIFS($T111:$CA111, $T$1:$CA$1, CE$63) -> 0 | CF111: =SUMIFS($T111:$CA111, $T$1:$CA$1, CF$63) -> 0 | CG111: =SUMIFS($T111:$CA111, $T$1:$CA$1, CG$63) -> 0 | CI111: =CC111=L111 -> 1 | CJ111: =CD111=M111 -> 1 | CK111: =CE111=N111 -> 1 | CL111: =CF111=O111 -> 1 | CM111: =CG111=P111 -> 1
E112: OpEx subtotal | I112: =SUM(I107:I111) -> 0 | J112: =SUM(J107:J111) -> 0 | K112: =SUM(K107:K111) -> 0 | L112: =SUM(L107:L111) -> 0 | M112: =SUM(M107:M111) -> 0 | N112: =SUM(N107:N111) -> 0 | O112: =SUM(O107:O111) -> 0 | P112: =SUM(P107:P111) -> 0 | T112: =SUM(T107:T111) -> 0 | U112: =SUM(U107:U111) -> 0 | V112: =SUM(V107:V111) -> 0 | W112: =SUM(W107:W111) -> 0 | X112: =SUM(X107:X111) -> 0 | Y112: =SUM(Y107:Y111) -> 0 | Z112: =SUM(Z107:Z111) -> 0 | AA112: =SUM(AA107:AA111) -> 0 | ... CA112: =SUM(CA107:CA111) -> 0 | CC112: =SUM(CC107:CC111) -> 0 | CD112: =SUM(CD107:CD111) -> 0 | CE112: =SUM(CE107:CE111) -> 0 | CF112: =SUM(CF107:CF111) -> 0 | CG112: =SUM(CG107:CG111) -> 0 | CI112: =CC112=L112 -> 1 | CJ112: =CD112=M112 -> 1 | CK112: =CE112=N112 -> 1 | CL112: =CF112=O112 -> 1 | CM112: =CG112=P112 -> 1
E115: Recurring Costs Total | I115: =SUM(-I96, I104, I112) -> 0 | J115: =SUM(-J96, J104, J112) -> 0 | K115: =SUM(-K96, K104, K112) -> 0 | L115: =SUM(-L96, L104, L112) -> 0 | M115: =SUM(-M96, M104, M112) -> 0 | N115: =SUM(-N96, N104, N112) -> 0 | O115: =SUM(-O96, O104, O112) -> 0 | P115: =SUM(-P96, P104, P112) -> 0 | T115: =SUM(-T96, T104, T112) -> 0 | U115: =SUM(-U96, U104, U112) -> 0 | V115: =SUM(-V96, V104, V112) -> 0 | W115: =SUM(-W96, W104, W112) -> 0 | X115: =SUM(-X96, X104, X112) -> 0 | Y115: =SUM(-Y96, Y104, Y112) -> 0 | Z115: =SUM(-Z96, Z104, Z112) -> 0 | AA115: =SUM(-AA96, AA104, AA112) -> 0 | ... CA115: =SUM(-CA96, CA104, CA112) -> 0 | CC115: =SUM(-CC96, CC104, CC112) -> 0 | CD115: =SUM(-CD96, CD104, CD112) -> 0 | CE115: =SUM(-CE96, CE104, CE112) -> 0 | CF115: =SUM(-CF96, CF104, CF112) -> 0 | CG115: =SUM(-CG96, CG104, CG112) -> 0 | CI115: =CC115=L115 -> 1 | CJ115: =CD115=M115 -> 1 | CK115: =CE115=N115 -> 1 | CL115: =CF115=O115 -> 1 | CM115: =CG115=P115 -> 1
E117: Net Recurring Benefit | I117: =SUM(I88, -I115) -> 0 | J117: =SUM(J88, -J115) -> 0 | K117: =SUM(K88, -K115) -> 0 | L117: =SUM(L88, -L115) -> 0 | M117: =SUM(M88, -M115) -> 0 | N117: =SUM(N88, -N115) -> 0 | O117: =SUM(O88, -O115) -> 0 | P117: =SUM(P88, -P115) -> 0 | R117: =IF(K117=P117, "", "Error") | T117: =SUM(T88, -T115) -> 0 | U117: =SUM(U88, -U115) -> 0 | V117: =SUM(V88, -V115) -> 0 | W117: =SUM(W88, -W115) -> 0 | X117: =SUM(X88, -X115) -> 0 | Y117: =SUM(Y88, -Y115) -> 0 | Z117: =SUM(Z88, -Z115) -> 0 | AA117: =SUM(AA88, -AA115) -> 0 | ... CA117: =SUM(CA88, -CA115) -> 0 | CC117: =SUM(CC88, -CC115) -> 0 | CD117: =SUM(CD88, -CD115) -> 0 | CE117: =SUM(CE88, -CE115) -> 0 | CF117: =SUM(CF88, -CF115) -> 0 | CG117: =SUM(CG88, -CG115) -> 0 | CI117: =CC117=L117 -> 1 | CJ117: =CD117=M117 -> 1 | CK117: =CE117=N117 -> 1 | CL117: =CF117=O117 -> 1 | CM117: =CG117=P117 -> 1
C120: SECTION III - ONE-TIME IMPLEMENTATION | CC120: ANNUAL SUMMARY | CI120: CHECK CELLS
T122: 2026 | AF122: 2027 | AR122: 2028 | BD122: 2029 | BP122: 2030
D123: ONE-TIME BENEFITS | K123: Comment | L123: 2026 | M123: =L123+1 -> 2027 | N123: =M123+1 -> 2028 | O123: =N123+1 -> 2029 | P123: =O123+1 -> 2030 | Q123: Impacted BU | T123: 46023 | U123: =EOMONTH(T123, 1) -> 46081 | V123: =EOMONTH(U123, 1) -> 46112 | W123: =EOMONTH(V123, 1) -> 46142 | X123: =EOMONTH(W123, 1) -> 46173 | Y123: =EOMONTH(X123, 1) -> 46203 | Z123: =EOMONTH(Y123, 1) -> 46234 | AA123: =EOMONTH(Z123, 1) -> 46265 | AB123: =EOMONTH(AA123, 1) -> 46295 | ... CA123: =EOMONTH(BZ123, 1) -> 47848 | CC123: 2026 | CD123: =CC123+1 -> 2027 | CE123: =CD123+1 -> 2028 | CF123: =CE123+1 -> 2029 | CG123: =CF123+1 -> 2030 | CI123: 2026 | CJ123: =CI123+1 -> 2027 | CK123: =CJ123+1 -> 2028 | CL123: =CK123+1 -> 2029 | CM123: =CL123+1 -> 2030
E125: Working Capital
CC126: =SUMIFS($T126:$CA126, $T$1:$CA$1, CC$63) -> 0 | CD126: =SUMIFS($T126:$CA126, $T$1:$CA$1, CD$63) -> 0 | CE126: =SUMIFS($T126:$CA126, $T$1:$CA$1, CE$63) -> 0 | CF126: =SUMIFS($T126:$CA126, $T$1:$CA$1, CF$63) -> 0 | CG126: =SUMIFS($T126:$CA126, $T$1:$CA$1, CG$63) -> 0 | CI126: =CC126=L126 -> 1 | CJ126: =CD126=M126 -> 1 | CK126: =CE126=N126 -> 1 | CL126: =CF126=O126 -> 1 | CM126: =CG126=P126 -> 1
CC127: =SUMIFS($T127:$CA127, $T$1:$CA$1, CC$63) -> 0 | CD127: =SUMIFS($T127:$CA127, $T$1:$CA$1, CD$63) -> 0 | CE127: =SUMIFS($T127:$CA127, $T$1:$CA$1, CE$63) -> 0 | CF127: =SUMIFS($T127:$CA127, $T$1:$CA$1, CF$63) -> 0 | CG127: =SUMIFS($T127:$CA127, $T$1:$CA$1, CG$63) -> 0 | CI127: =CC127=L127 -> 1 | CJ127: =CD127=M127 -> 1 | CK127: =CE127=N127 -> 1 | CL127: =CF127=O127 -> 1 | CM127: =CG127=P127 -> 1
E128: Working Capital Subtotal | L128: =SUM(L126:L127) -> 0 | M128: =SUM(M126:M127) -> 0 | N128: =SUM(N126:N127) -> 0 | O128: =SUM(O126:O127) -> 0 | P128: =SUM(P126:P127) -> 0 | T128: =SUM(T126:T127) -> 0 | U128: =SUM(U126:U127) -> 0 | V128: =SUM(V126:V127) -> 0 | W128: =SUM(W126:W127) -> 0 | X128: =SUM(X126:X127) -> 0 | Y128: =SUM(Y126:Y127) -> 0 | Z128: =SUM(Z126:Z127) -> 0 | AA128: =SUM(AA126:AA127) -> 0 | ... CA128: =SUM(CA126:CA127) -> 0 | CC128: =SUM(CC126:CC127) -> 0 | CD128: =SUM(CD126:CD127) -> 0 | CE128: =SUM(CE126:CE127) -> 0 | CF128: =SUM(CF126:CF127) -> 0 | CG128: =SUM(CG126:CG127) -> 0 | CI128: =CC128=L128 -> 1 | CJ128: =CD128=M128 -> 1 | CK128: =CE128=N128 -> 1 | CL128: =CF128=O128 -> 1 | CM128: =CG128=P128 -> 1
E130: One-Time Benefits Total | L130: =L128 -> 0 | M130: =M128 -> 0 | N130: =N128 -> 0 | O130: =O128 -> 0 | P130: =P128 -> 0 | T130: =T128 -> 0 | U130: =U128 -> 0 | V130: =V128 -> 0 | W130: =W128 -> 0 | X130: =X128 -> 0 | Y130: =Y128 -> 0 | Z130: =Z128 -> 0 | AA130: =AA128 -> 0 | ... CA130: =CA128 -> 0 | CC130: =CC128 -> 0 | CD130: =CD128 -> 0 | CE130: =CE128 -> 0 | CF130: =CF128 -> 0 | CG130: =CG128 -> 0 | CI130: =CI128 -> 1 | CJ130: =CJ128 -> 1 | CK130: =CK128 -> 1 | CL130: =CL128 -> 1 | CM130: =CM128 -> 1
T132: 2026 | AF132: 2027 | AR132: 2028 | BD132: 2029 | BP132: 2030
D133: CAPEX AND ONE-TIME COSTS | K133: Comment | L133: 2026 | M133: =L133+1 -> 2027 | N133: =M133+1 -> 2028 | O133: =N133+1 -> 2029 | P133: =O133+1 -> 2030 | T133: 46023 | U133: =EOMONTH(T133, 1) -> 46081 | V133: =EOMONTH(U133, 1) -> 46112 | W133: =EOMONTH(V133, 1) -> 46142 | X133: =EOMONTH(W133, 1) -> 46173 | Y133: =EOMONTH(X133, 1) -> 46203 | Z133: =EOMONTH(Y133, 1) -> 46234 | AA133: =EOMONTH(Z133, 1) -> 46265 | AB133: =EOMONTH(AA133, 1) -> 46295 | ... CA133: =EOMONTH(BZ133, 1) -> 47848 | CC133: 2026 | CD133: =CC133+1 -> 2027 | CE133: =CD133+1 -> 2028 | CF133: =CE133+1 -> 2029 | CG133: =CF133+1 -> 2030 | CI133: 2026 | CJ133: =CI133+1 -> 2027 | CK133: =CJ133+1 -> 2028 | CL133: =CK133+1 -> 2029 | CM133: =CL133+1 -> 2030
E135: Capital Expenditures
E136: CAPEX — capitalized build labor | L136: ='SALES-1 Model'!L100 -> 0.10530667 | M136: ='SALES-1 Model'!M100 -> 0.42122667 | N136: ='SALES-1 Model'!N100 -> 0 | O136: ='SALES-1 Model'!O100 -> 0 | P136: ='SALES-1 Model'!P100 -> 0 | Q136: Global Sales | T136: ='SALES-1 Model'!T100 -> 0 | U136: ='SALES-1 Model'!U100 -> 0 | V136: ='SALES-1 Model'!V100 -> 0 | W136: ='SALES-1 Model'!W100 -> 0 | X136: ='SALES-1 Model'!X100 -> 0 | Y136: ='SALES-1 Model'!Y100 -> 0 | Z136: ='SALES-1 Model'!Z100 -> 0 | AA136: ='SALES-1 Model'!AA100 -> 0 | ... CA136: ='SALES-1 Model'!CA100 -> 0 | CC136: =SUMIFS($T136:$CA136, $T$1:$CA$1, CC$63) -> 0.10530667 | CD136: =SUMIFS($T136:$CA136, $T$1:$CA$1, CD$63) -> 0.42122667 | CE136: =SUMIFS($T136:$CA136, $T$1:$CA$1, CE$63) -> 0 | CF136: =SUMIFS($T136:$CA136, $T$1:$CA$1, CF$63) -> 0 | CG136: =SUMIFS($T136:$CA136, $T$1:$CA$1, CG$63) -> 0 | CI136: =CC136=L136 -> 1 | CJ136: =CD136=M136 -> 1 | CK136: =CE136=N136 -> 1 | CL136: =CF136=O136 -> 1 | CM136: =CG136=P136 -> 1
E137: CAPEX — capitalized non-labor | L137: ='SALES-1 Model'!L101 -> 0 | M137: ='SALES-1 Model'!M101 -> 0 | N137: ='SALES-1 Model'!N101 -> 0 | O137: ='SALES-1 Model'!O101 -> 0 | P137: ='SALES-1 Model'!P101 -> 0 | Q137: Global Sales | T137: ='SALES-1 Model'!T101 -> 0 | U137: ='SALES-1 Model'!U101 -> 0 | V137: ='SALES-1 Model'!V101 -> 0 | W137: ='SALES-1 Model'!W101 -> 0 | X137: ='SALES-1 Model'!X101 -> 0 | Y137: ='SALES-1 Model'!Y101 -> 0 | Z137: ='SALES-1 Model'!Z101 -> 0 | AA137: ='SALES-1 Model'!AA101 -> 0 | ... CA137: ='SALES-1 Model'!CA101 -> 0 | CC137: =SUMIFS($T137:$CA137, $T$1:$CA$1, CC$63) -> 0 | CD137: =SUMIFS($T137:$CA137, $T$1:$CA$1, CD$63) -> 0 | CE137: =SUMIFS($T137:$CA137, $T$1:$CA$1, CE$63) -> 0 | CF137: =SUMIFS($T137:$CA137, $T$1:$CA$1, CF$63) -> 0 | CG137: =SUMIFS($T137:$CA137, $T$1:$CA$1, CG$63) -> 0 | CI137: =CC137=L137 -> 1 | CJ137: =CD137=M137 -> 1 | CK137: =CE137=N137 -> 1 | CL137: =CF137=O137 -> 1 | CM137: =CG137=P137 -> 1
E138: Capital Expenditures Subtotal | L138: =SUM(L136:L137) -> 0.10530667 | M138: =SUM(M136:M137) -> 0.42122667 | N138: =SUM(N136:N137) -> 0 | O138: =SUM(O136:O137) -> 0 | P138: =SUM(P136:P137) -> 0 | T138: =SUM(T136:T137) -> 0 | U138: =SUM(U136:U137) -> 0 | V138: =SUM(V136:V137) -> 0 | W138: =SUM(W136:W137) -> 0 | X138: =SUM(X136:X137) -> 0 | Y138: =SUM(Y136:Y137) -> 0 | Z138: =SUM(Z136:Z137) -> 0 | AA138: =SUM(AA136:AA137) -> 0 | ... CA138: =SUM(CA136:CA137) -> 0 | CC138: =SUM(CC136:CC137) -> 0.10530667 | CD138: =SUM(CD136:CD137) -> 0.42122667 | CE138: =SUM(CE136:CE137) -> 0 | CF138: =SUM(CF136:CF137) -> 0 | CG138: =SUM(CG136:CG137) -> 0 | CI138: =CC138=L138 -> 1 | CJ138: =CD138=M138 -> 1 | CK138: =CE138=N138 -> 1 | CL138: =CF138=O138 -> 1 | CM138: =CG138=P138 -> 1
E140: OTC
E141: OTC — build labor (expensed) | L141: ='SALES-1 Model'!L102 -> 0.15796 | M141: ='SALES-1 Model'!M102 -> 0.59893167 | N141: ='SALES-1 Model'!N102 -> 0 | O141: ='SALES-1 Model'!O102 -> 0 | P141: ='SALES-1 Model'!P102 -> 0 | Q141: Global Sales | T141: ='SALES-1 Model'!T102 -> 0 | U141: ='SALES-1 Model'!U102 -> 0 | V141: ='SALES-1 Model'!V102 -> 0 | W141: ='SALES-1 Model'!W102 -> 0 | X141: ='SALES-1 Model'!X102 -> 0 | Y141: ='SALES-1 Model'!Y102 -> 0 | Z141: ='SALES-1 Model'!Z102 -> 0 | AA141: ='SALES-1 Model'!AA102 -> 0 | ... CA141: ='SALES-1 Model'!CA102 -> 0 | CC141: =SUMIFS($T141:$CA141, $T$1:$CA$1, CC$63) -> 0.15796 | CD141: =SUMIFS($T141:$CA141, $T$1:$CA$1, CD$63) -> 0.59893167 | CE141: =SUMIFS($T141:$CA141, $T$1:$CA$1, CE$63) -> 0 | CF141: =SUMIFS($T141:$CA141, $T$1:$CA$1, CF$63) -> 0 | CG141: =SUMIFS($T141:$CA141, $T$1:$CA$1, CG$63) -> 0 | CI141: =CC141=L141 -> 1 | CJ141: =CD141=M141 -> 1 | CK141: =CE141=N141 -> 1 | CL141: =CF141=O141 -> 1 | CM141: =CG141=P141 -> 1
E142: OTC — non-labor (expensed) | L142: ='SALES-1 Model'!L103 -> 0.080427967 | M142: ='SALES-1 Model'!M103 -> 0.16085593 | N142: ='SALES-1 Model'!N103 -> 0 | O142: ='SALES-1 Model'!O103 -> 0 | P142: ='SALES-1 Model'!P103 -> 0 | Q142: Global Sales | T142: ='SALES-1 Model'!T103 -> 0 | U142: ='SALES-1 Model'!U103 -> 0 | V142: ='SALES-1 Model'!V103 -> 0 | W142: ='SALES-1 Model'!W103 -> 0 | X142: ='SALES-1 Model'!X103 -> 0 | Y142: ='SALES-1 Model'!Y103 -> 0 | Z142: ='SALES-1 Model'!Z103 -> 0 | AA142: ='SALES-1 Model'!AA103 -> 0 | ... CA142: ='SALES-1 Model'!CA103 -> 0 | CC142: =SUMIFS($T142:$CA142, $T$1:$CA$1, CC$63) -> 0.080427967 | CD142: =SUMIFS($T142:$CA142, $T$1:$CA$1, CD$63) -> 0.16085593 | CE142: =SUMIFS($T142:$CA142, $T$1:$CA$1, CE$63) -> 0 | CF142: =SUMIFS($T142:$CA142, $T$1:$CA$1, CF$63) -> 0 | CG142: =SUMIFS($T142:$CA142, $T$1:$CA$1, CG$63) -> 0 | CI142: =CC142=L142 -> 1 | CJ142: =CD142=M142 -> 1 | CK142: =CE142=N142 -> 1 | CL142: =CF142=O142 -> 1 | CM142: =CG142=P142 -> 1
CC143: =SUMIFS($T143:$CA143, $T$1:$CA$1, CC$63) -> 0 | CD143: =SUMIFS($T143:$CA143, $T$1:$CA$1, CD$63) -> 0 | CE143: =SUMIFS($T143:$CA143, $T$1:$CA$1, CE$63) -> 0 | CF143: =SUMIFS($T143:$CA143, $T$1:$CA$1, CF$63) -> 0 | CG143: =SUMIFS($T143:$CA143, $T$1:$CA$1, CG$63) -> 0 | CI143: =CC143=L143 -> 1 | CJ143: =CD143=M143 -> 1 | CK143: =CE143=N143 -> 1 | CL143: =CF143=O143 -> 1 | CM143: =CG143=P143 -> 1
E144: OTC Subtotal | L144: =SUM(L141:L143) -> 0.23838797 | M144: =SUM(M141:M143) -> 0.7597876 | N144: =SUM(N141:N143) -> 0 | O144: =SUM(O141:O143) -> 0 | P144: =SUM(P141:P143) -> 0 | T144: =SUM(T141:T143) -> 0 | U144: =SUM(U141:U143) -> 0 | V144: =SUM(V141:V143) -> 0 | W144: =SUM(W141:W143) -> 0 | X144: =SUM(X141:X143) -> 0 | Y144: =SUM(Y141:Y143) -> 0 | Z144: =SUM(Z141:Z143) -> 0 | AA144: =SUM(AA141:AA143) -> 0 | ... CA144: =SUM(CA141:CA143) -> 0 | CC144: =SUM(CC141:CC143) -> 0.23838797 | CD144: =SUM(CD141:CD143) -> 0.7597876 | CE144: =SUM(CE141:CE143) -> 0 | CF144: =SUM(CF141:CF143) -> 0 | CG144: =SUM(CG141:CG143) -> 0 | CI144: =CC144=L144 -> 1 | CJ144: =CD144=M144 -> 1 | CK144: =CE144=N144 -> 1 | CL144: =CF144=O144 -> 1 | CM144: =CG144=P144 -> 1
E147: One-Time Costs Total | L147: =SUM(L138, L144) -> 0.34369463 | M147: =SUM(M138, M144) -> 1.1810143 | N147: =SUM(N138, N144) -> 0 | O147: =SUM(O138, O144) -> 0 | P147: =SUM(P138, P144) -> 0 | T147: =SUM(T138, T144) -> 0 | U147: =SUM(U138, U144) -> 0 | V147: =SUM(V138, V144) -> 0 | W147: =SUM(W138, W144) -> 0 | X147: =SUM(X138, X144) -> 0 | Y147: =SUM(Y138, Y144) -> 0 | Z147: =SUM(Z138, Z144) -> 0 | AA147: =SUM(AA138, AA144) -> 0 | ... CA147: =SUM(CA138, CA144) -> 0 | CC147: =SUM(CC138, CC144) -> 0.34369463 | CD147: =SUM(CD138, CD144) -> 1.1810143 | CE147: =SUM(CE138, CE144) -> 0 | CF147: =SUM(CF138, CF144) -> 0 | CG147: =SUM(CG138, CG144) -> 0 | CI147: =CC147=L147 -> 1 | CJ147: =CD147=M147 -> 1 | CK147: =CE147=N147 -> 1 | CL147: =CF147=O147 -> 1 | CM147: =CG147=P147 -> 1
E149: Total One-Time Implementation Cost | L149: =SUM(L130, -L147) -> -0.34369463 | M149: =SUM(M130, -M147) -> -1.1810143 | N149: =SUM(N130, -N147) -> 0 | O149: =SUM(O130, -O147) -> 0 | P149: =SUM(P130, -P147) -> 0 | T149: =SUM(T130, -T147) -> 0 | U149: =SUM(U130, -U147) -> 0 | V149: =SUM(V130, -V147) -> 0 | W149: =SUM(W130, -W147) -> 0 | X149: =SUM(X130, -X147) -> 0 | Y149: =SUM(Y130, -Y147) -> 0 | Z149: =SUM(Z130, -Z147) -> 0 | AA149: =SUM(AA130, -AA147) -> 0 | ... CA149: =SUM(CA130, -CA147) -> 0 | CC149: =SUM(CC130, -CC147) -> -0.34369463 | CD149: =SUM(CD130, -CD147) -> -1.1810143 | CE149: =SUM(CE130, -CE147) -> 0 | CF149: =SUM(CF130, -CF147) -> 0 | CG149: =SUM(CG130, -CG147) -> 0 | CI149: =CC149=L149 -> 1 | CJ149: =CD149=M149 -> 1 | CK149: =CE149=N149 -> 1 | CL149: =CF149=O149 -> 1 | CM149: =CG149=P149 -> 1
C152: SECTION IV - FINANCIAL METRICS | CC152: ANNUAL SUMMARY | CI152: CHECK CELLS
E155: Cash Flow | L155: 2026 | M155: =L155+1 -> 2027 | N155: =M155+1 -> 2028 | O155: =N155+1 -> 2029 | P155: =O155+1 -> 2030 | Q155: Total
E156: Operating Income | L156: =L117 -> 0 | M156: =M117 -> 0 | N156: =N117 -> 0 | O156: =O117 -> 0 | P156: =P117 -> 0 | Q156: =SUM(L156:P156) -> 0
E157: (+) One-Time Benefits | L157: =L130 -> 0 | M157: =M130 -> 0 | N157: =N130 -> 0 | O157: =O130 -> 0 | P157: =P130 -> 0 | Q157: =SUM(L157:P157) -> 0
E158: (-) One-Time Cash Costs | L158: =-L147 -> -0.34369463 | M158: =-M147 -> -1.1810143 | N158: =-N147 -> 0 | O158: =-O147 -> 0 | P158: =-P147 -> 0 | Q158: =SUM(L158:P158) -> -1.5247089
E159: Cash Flow | L159: =SUM(L156:L158) -> -0.34369463 | M159: =SUM(M156:M158) -> -1.1810143 | N159: =SUM(N156:N158) -> 0 | O159: =SUM(O156:O158) -> 0 | P159: =SUM(P156:P158) -> 0 | Q159: =SUM(L159:P159) -> -1.5247089
E160: Cumulative Cash Flow | L160: =L159 -> -0.34369463 | M160: =L160+M159 -> -1.5247089 | N160: =M160+N159 -> -1.5247089 | O160: =N160+O159 -> -1.5247089 | P160: =O160+P159 -> -1.5247089 | Q160: =P160 -> -1.5247089
E161: Payback timeline | L161: =IF(L160<0,1,0) -> 1 | M161: =IF(M160<0,1,IF(AND(L160<0,M159>0),-L160/M159,0)) -> 1 | N161: =IF(N160<0,1,IF(AND(M160<0,N159>0),-M160/N159,0)) -> 1 | O161: =IF(O160<0,1,IF(AND(N160<0,O159>0),-N160/O159,0)) -> 1 | P161: =IF(P160<0,1,IF(AND(O160<0,P159>0),-O160/P159,0)) -> 1
E163: Return on Investment | F163: NRB/OTC | G163: =IFERROR(K117/-SUM(L149:P149),"n/a") -> 0
E164: Internal Rate of Return | F164: 5-yr IRR | G164: =IFERROR(IRR($L$159:$P$159, 0.2),"n/a") -> n/a
E165: Breakeven timeline | F165: # yrs | G165: =IF(SUM(L161:P161)=5,">5",SUM(L161:P161)) -> >5
E167: WACC | G167: 0.095
E168: NPV | F168: $ | G168: =SUM(L168:P168) -> -1.2988552 | L168: =L159/(1+$G$167)^L$1 -> -0.31387638 | M168: =M159/(1+$G$167)^M$1 -> -0.98497885 | N168: =N159/(1+$G$167)^N$1 -> 0 | O168: =O159/(1+$G$167)^O$1 -> 0 | P168: =P159/(1+$G$167)^P$1 -> 0 | Q168: =SUM(L168:P168) -> -1.2988552
...

Sheet SALES-2 Model
B2: SALES-2 — SMB Long Tail — Partner | INITIATIVE MODEL
B3: Workstream: Sales (ELT sponsor: Susan | WSL: Selwyn) • Model status: Structure ready; partner/SDR baselines to populate — see open items
T5: 2026 | U5: 2026 | V5: 2026 | W5: 2026 | X5: 2026 | Y5: 2026 | Z5: 2026 | AA5: 2026 | AB5: 2026 | AC5: 2026 | AD5: 2026 | AE5: 2026 | AF5: 2027 | AG5: 2027 | AH5: 2027 | AI5: 2027 | AJ5: 2027 | AK5: 2027 | AL5: 2027 | AM5: 2027 | AN5: 2027 | AO5: 2027 | AP5: 2027 | AQ5: 2027 | AR5: 2028 | AS5: 2028 | AT5: 2028 | AU5: 2028 | AV5: 2028 | AW5: 2028 | AX5: 2028 | AY5: 2028 | AZ5: 2028 | BA5: 2028 | BB5: 2028 | BC5: 2028 | BD5: 2029 | BE5: 2029 | BF5: 2029 | BG5: 2029 | BH5: 2029 | BI5: 2029 | BJ5: 2029 | BK5: 2029 | BL5: 2029 | BM5: 2029 | BN5: 2029 | BO5: 2029 | BP5: 2030 | BQ5: 2030 | BR5: 2030 | BS5: 2030 | BT5: 2030 | BU5: 2030 | BV5: 2030 | BW5: 2030 | BX5: 2030 | BY5: 2030 | BZ5: 2030 | CA5: 2030
B6: Monthly grid (Jan-26 → Dec-30) → | K6: Run rate | L6: 2026 | M6: 2027 | N6: 2028 | O6: 2029 | P6: 2030 | T6: =DATE(2026,1,31) -> 46053 | U6: =EOMONTH(T6,1) -> 46081 | V6: =EOMONTH(U6,1) -> 46112 | W6: =EOMONTH(V6,1) -> 46142 | X6: =EOMONTH(W6,1) -> 46173 | Y6: =EOMONTH(X6,1) -> 46203 | Z6: =EOMONTH(Y6,1) -> 46234 | AA6: =EOMONTH(Z6,1) -> 46265 | AB6: =EOMONTH(AA6,1) -> 46295 | ... CA6: =EOMONTH(BZ6,1) -> 47848
B8: 0. INITIATIVE & STATUS
B10: Initiative name | D10: SMB long-tail growth through partner-channel scaling and autonomous SDR outreach
B11: Initiative owner | D11: Sales initiative owner — TBC | I11: confirm with workstream lead
B12: Impacted BU | D12: Global Sales
B13: Go-live / Estimated L4 date | D13: =DATE(2027,4,1) -> 46478 | I13: Benefit ramp is gated on this date.
B15: Source: Workplan: 'Project Zenith Automation workplan and data requests vS_1.xlsx', Sales tab + Sales Data Requests tab
B16: Source: Impact ranges: Aug 13 deck pp. 6, 14–15; Board deck pp. 9, 20, 52 (preliminary — Finance to validate)
B17: Open items to refine with initiative owner:
B18: – Partner-channel revenue % received 8/24 — populate the $ base. Attach-rate quartile distribution and partner SME interview still pending (requests #5–#6).
B19: – Incrementality / cannibalization logic must be defined with Finance before S2 sign-off.
B20: – SDR conversion & cycle-time baselines pending; seller time on lead mgmt pending.
B21: – Cross-functional dependency: partner/channel org + PRM platform; watch overlap with broader SMB front-book growth (workplan flag).
B22: – Seller time saved on lead mgmt is flagged as an ENABLER in source materials — confirm bankability before counting it in the S2 number.
B24: 1. SIZING ASSUMPTIONS (blue = inputs — refine with initiative owner)
B26: Baseline / denominator (populate from received datasets + pending requests)
B27: Partner/referral-channel revenue (annual NSR) | D27: 0 | E27: $/yr | F27: % revenue via partner received 8/24 — populate $ base
B28: Transaction margin (TM % of NSR) — SMB blended | D28: 0 | E28: % | F28: From TM% dataset received 8/20
B29: SDR-influenced revenue base (annual NSR) | D29: 0 | E29: $/yr | F29: PENDING — placeholder, not data. SDR conversion & funnel data — pending
B30: # SMB sellers on lead management | D30: 0 | E30: # FTE | F30: PENDING — placeholder, not data.
B31: Avg fully loaded cost per SMB seller | D31: 0 | E31: $/yr | F31: From FLC by region (received 8/21)
B32: % of seller time on lead mgmt & related | D32: 0 | E32: % | F32: PENDING — placeholder, not data.
B33: Impact drivers (Aug 13 deck pp. 6, 14–15 — preliminary ranges, midpoints seeded)
B34: Partner-channel share uplift | D34: 1 | E34: % | F34: Source: ~100% partner-channel share uplift
B35: Incrementality factor (net of cannibalization) | D35: 0 | E35: % | F35: PENDING — placeholder, not data. Define with Finance — cannibalization treatment required for approval package
B36: SDR autonomous-outreach conversion uplift | D36: 0.15 | E36: % | F36: Source: ~15%
B37: Capture rate — SDR uplift | D37: 0.72 | E37: % | F37: Source: 72%
B38: Cycle-time pull-forward | D38: 12 | E38: days | F38: Source: ~12 days revenue acceleration — treat as timing unless Finance agrees incremental; fold agreed value into the SDR line
B39: Seller time saved on lead management | D39: 0.375 | E39: % | F39: Source: 35–40% — midpoint. ENABLER — confirm bankability
B40: Capture rate — seller time saved | D40: 0.65 | E40: % | F40: Assumed consistent with U&P seller capture — confirm
B41: Investment uplifts (consistent with Servicing S2 standard)
B42: Programme management, % of build | D42: 0.08 | E42: %
B43: Contingency, % of build incl. PM | D43: 0.1 | E43: %
B44: (spare assumption row)
B45: (spare assumption row)
B47: 2. BENEFIT CALCULATION (steady-state annual run-rate)
B49: Partner-channel share uplift benefit (margin) | D49: =$D$27*$D$28*$D$34*$D$35 -> 0 | E49: $/yr | F49: Partner margin base x share uplift x incrementality (net of cannibalization)
B50: SDR agent uplift benefit (margin) | D50: =$D$29*$D$28*$D$36*$D$37 -> 0 | E50: $/yr | F50: SDR-influenced margin base x conversion uplift x capture; add agreed pull-forward value here
B51: Seller time saved — lead management (enabler) | D51: =$D$30*$D$31*$D$32*$D$39*$D$40 -> 0 | E51: $/yr | F51: Sellers x FLC x % time on leads x time saved x capture — ENABLER, confirm bankability
B53: 3. RAMP & PHASING
B55: Months to full run rate after go-live (linear ramp) | D55: 9 | F55: Benefit starts at go-live and ramps linearly to steady state over this many months.
B56: Monthly ramp % (run-rate captured in month) | T56: =MIN(1,MAX(0,((YEAR(T$6)-YEAR($D$13))*12+MONTH(T$6)-MONTH($D$13)+0.5)/MAX($D$55,0.5))) -> 0 | U56: =MIN(1,MAX(0,((YEAR(U$6)-YEAR($D$13))*12+MONTH(U$6)-MONTH($D$13)+0.5)/MAX($D$55,0.5))) -> 0 | V56: =MIN(1,MAX(0,((YEAR(V$6)-YEAR($D$13))*12+MONTH(V$6)-MONTH($D$13)+0.5)/MAX($D$55,0.5))) -> 0 | W56: =MIN(1,MAX(0,((YEAR(W$6)-YEAR($D$13))*12+MONTH(W$6)-MONTH($D$13)+0.5)/MAX($D$55,0.5))) -> 0 | X56: =MIN(1,MAX(0,((YEAR(X$6)-YEAR($D$13))*12+MONTH(X$6)-MONTH($D$13)+0.5)/MAX($D$55,0.5))) -> 0 | Y56: =MIN(1,MAX(0,((YEAR(Y$6)-YEAR($D$13))*12+MONTH(Y$6)-MONTH($D$13)+0.5)/MAX($D$55,0.5))) -> 0 | Z56: =MIN(1,MAX(0,((YEAR(Z$6)-YEAR($D$13))*12+MONTH(Z$6)-MONTH($D$13)+0.5)/MAX($D$55,0.5))) -> 0 | AA56: =MIN(1,MAX(0,((YEAR(AA$6)-YEAR($D$13))*12+MONTH(AA$6)-MONTH($D$13)+0.5)/MAX($D$55,0.5))) -> 0 | ... CA56: =MIN(1,MAX(0,((YEAR(CA$6)-YEAR($D$13))*12+MONTH(CA$6)-MONTH($D$13)+0.5)/MAX($D$55,0.5))) -> 1
B57: Resulting average ramp % by year (info) | L57: =SUMIFS($T56:$CA56,$T$5:$CA$5,2026)/12 -> 0 | M57: =SUMIFS($T56:$CA56,$T$5:$CA$5,2027)/12 -> 0.375 | N57: =SUMIFS($T56:$CA56,$T$5:$CA$5,2028)/12 -> 1 | O57: =SUMIFS($T56:$CA56,$T$5:$CA$5,2029)/12 -> 1 | P57: =SUMIFS($T56:$CA56,$T$5:$CA$5,2030)/12 -> 1
B59: 4. RECURRING BENEFIT LINES ($M — these rows feed the WAVE sheet)
B61: Line (WAVE category) | D61: Baseline $M | K61: Run rate
B62: Revenue - Partner-channel share uplift [REV] | D62: =$D$27*$D$28/1000000 -> 0 | K62: =SUMIFS($T62:$CA62,$T$5:$CA$5,2030) -> 0 | L62: =SUMIFS($T62:$CA62,$T$5:$CA$5,2026) -> 0 | M62: =SUMIFS($T62:$CA62,$T$5:$CA$5,2027) -> 0 | N62: =SUMIFS($T62:$CA62,$T$5:$CA$5,2028) -> 0 | O62: =SUMIFS($T62:$CA62,$T$5:$CA$5,2029) -> 0 | P62: =SUMIFS($T62:$CA62,$T$5:$CA$5,2030) -> 0 | T62: =($D$49)/1000000/12*T$56 -> 0 | U62: =($D$49)/1000000/12*U$56 -> 0 | V62: =($D$49)/1000000/12*V$56 -> 0 | W62: =($D$49)/1000000/12*W$56 -> 0 | X62: =($D$49)/1000000/12*X$56 -> 0 | Y62: =($D$49)/1000000/12*Y$56 -> 0 | Z62: =($D$49)/1000000/12*Z$56 -> 0 | AA62: =($D$49)/1000000/12*AA$56 -> 0 | ... CA62: =($D$49)/1000000/12*CA$56 -> 0
B63: Revenue - SDR agent uplift (conversion + acceleration) [REV] | D63: =$D$29*$D$28/1000000 -> 0 | K63: =SUMIFS($T63:$CA63,$T$5:$CA$5,2030) -> 0 | L63: =SUMIFS($T63:$CA63,$T$5:$CA$5,2026) -> 0 | M63: =SUMIFS($T63:$CA63,$T$5:$CA$5,2027) -> 0 | N63: =SUMIFS($T63:$CA63,$T$5:$CA$5,2028) -> 0 | O63: =SUMIFS($T63:$CA63,$T$5:$CA$5,2029) -> 0 | P63: =SUMIFS($T63:$CA63,$T$5:$CA$5,2030) -> 0 | T63: =($D$50)/1000000/12*T$56 -> 0 | U63: =($D$50)/1000000/12*U$56 -> 0 | V63: =($D$50)/1000000/12*V$56 -> 0 | W63: =($D$50)/1000000/12*W$56 -> 0 | X63: =($D$50)/1000000/12*X$56 -> 0 | Y63: =($D$50)/1000000/12*Y$56 -> 0 | Z63: =($D$50)/1000000/12*Z$56 -> 0 | AA63: =($D$50)/1000000/12*AA$56 -> 0 | ... CA63: =($D$50)/1000000/12*CA$56 -> 0
B64: OPEX - Seller time saved on lead management (enabler) [OPEX] | D64: =$D$30*$D$31/1000000 -> 0 | K64: =SUMIFS($T64:$CA64,$T$5:$CA$5,2030) -> 0 | L64: =SUMIFS($T64:$CA64,$T$5:$CA$5,2026) -> 0 | M64: =SUMIFS($T64:$CA64,$T$5:$CA$5,2027) -> 0 | N64: =SUMIFS($T64:$CA64,$T$5:$CA$5,2028) -> 0 | O64: =SUMIFS($T64:$CA64,$T$5:$CA$5,2029) -> 0 | P64: =SUMIFS($T64:$CA64,$T$5:$CA$5,2030) -> 0 | T64: =($D$51)/1000000/12*T$56 -> 0 | U64: =($D$51)/1000000/12*U$56 -> 0 | V64: =($D$51)/1000000/12*V$56 -> 0 | W64: =($D$51)/1000000/12*W$56 -> 0 | X64: =($D$51)/1000000/12*X$56 -> 0 | Y64: =($D$51)/1000000/12*Y$56 -> 0 | Z64: =($D$51)/1000000/12*Z$56 -> 0 | AA64: =($D$51)/1000000/12*AA$56 -> 0 | ... CA64: =($D$51)/1000000/12*CA$56 -> 0
B65: Total recurring benefit ($M) | K65: =SUM(K62:K64) -> 0 | L65: =SUM(L62:L64) -> 0 | M65: =SUM(M62:M64) -> 0 | N65: =SUM(N62:N64) -> 0 | O65: =SUM(O62:O64) -> 0 | P65: =SUM(P62:P64) -> 0
B67: 5. ONE-TIME INVESTMENT — people cost by milestone (standard approach)
B69: Milestone | C69: Assumptions | D69: Team size | E69: Billing months | F69: Contingency Factor | G69: Labor Costs | H69: Start month | I69: Cap % (labor) | K69: Rate override ($/mo)
C70: Capture any assumptions on cost drivers, timelines, contingency factor etc. | E70: Months the team works at full utilization | F70: Low=10% Medium=15% High=20% Very high=50% | G70: Total labor costs for milestone | I70: Default links to Rate Card policy — type a % to override
B71: Plan / Design | C71: PLACEHOLDER — standard AAO pod shape; refine after tech workshop and PRM build/buy decision. | D71: 4 | E71: 2 | F71: 0.1 | G71: =D71*E71*IF(K71="",'Rate Card'!$G$29,K71)*(1+F71) -> 131633.33 | H71: =DATE(2026,10,1) -> 46296 | I71: ='Rate Card'!$C$45 -> 0
B72: Build / Test | C72: PLACEHOLDER — one 8-FTE pod; PRM/orchestration vendor build in non-labor lines. | D72: 8 | E72: 5 | F72: 0.1 | G72: =D72*E72*IF(K72="",'Rate Card'!$G$29,K72)*(1+F72) -> 658166.67 | H72: =DATE(2026,12,1) -> 46357 | I72: ='Rate Card'!$C$46 -> 0.8
B73: Pilot / Change Mgmt. | C73: PLACEHOLDER — scale-up team of 5 through partner rollout; partner enablement in non-labor below. | D73: 5 | E73: 6 | F73: 0.1 | G73: =D73*E73*IF(K73="",'Rate Card'!$G$29,K73)*(1+F73) -> 493625 | H73: =DATE(2027,4,1) -> 46478 | I73: ='Rate Card'!$C$47 -> 0
B74: Scale / Run | C74: Run-phase support carried as recurring run cost (Section 6). | D74: 0 | E74: 0 | F74: 0.1 | G74: =D74*E74*IF(K74="",'Rate Card'!$G$29,K74)*(1+F74) -> 0 | H74: =DATE(2027,10,1) -> 46661 | I74: ='Rate Card'!$C$48 -> 0
B76: Milestone labor phasing ($/month, spread evenly over billing months)
B77: Plan / Design | T77: =IF(AND(T$6>=EOMONTH($H$71,0),T$6<=EOMONTH(EDATE($H$71,$E$71-1),0)),$G$71/MAX($E$71,1),0) -> 0 | U77: =IF(AND(U$6>=EOMONTH($H$71,0),U$6<=EOMONTH(EDATE($H$71,$E$71-1),0)),$G$71/MAX($E$71,1),0) -> 0 | V77: =IF(AND(V$6>=EOMONTH($H$71,0),V$6<=EOMONTH(EDATE($H$71,$E$71-1),0)),$G$71/MAX($E$71,1),0) -> 0 | W77: =IF(AND(W$6>=EOMONTH($H$71,0),W$6<=EOMONTH(EDATE($H$71,$E$71-1),0)),$G$71/MAX($E$71,1),0) -> 0 | X77: =IF(AND(X$6>=EOMONTH($H$71,0),X$6<=EOMONTH(EDATE($H$71,$E$71-1),0)),$G$71/MAX($E$71,1),0) -> 0 | Y77: =IF(AND(Y$6>=EOMONTH($H$71,0),Y$6<=EOMONTH(EDATE($H$71,$E$71-1),0)),$G$71/MAX($E$71,1),0) -> 0 | Z77: =IF(AND(Z$6>=EOMONTH($H$71,0),Z$6<=EOMONTH(EDATE($H$71,$E$71-1),0)),$G$71/MAX($E$71,1),0) -> 0 | AA77: =IF(AND(AA$6>=EOMONTH($H$71,0),AA$6<=EOMONTH(EDATE($H$71,$E$71-1),0)),$G$71/MAX($E$71,1),0) -> 0 | ... CA77: =IF(AND(CA$6>=EOMONTH($H$71,0),CA$6<=EOMONTH(EDATE($H$71,$E$71-1),0)),$G$71/MAX($E$71,1),0) -> 0
B78: Build / Test | T78: =IF(AND(T$6>=EOMONTH($H$72,0),T$6<=EOMONTH(EDATE($H$72,$E$72-1),0)),$G$72/MAX($E$72,1),0) -> 0 | U78: =IF(AND(U$6>=EOMONTH($H$72,0),U$6<=EOMONTH(EDATE($H$72,$E$72-1),0)),$G$72/MAX($E$72,1),0) -> 0 | V78: =IF(AND(V$6>=EOMONTH($H$72,0),V$6<=EOMONTH(EDATE($H$72,$E$72-1),0)),$G$72/MAX($E$72,1),0) -> 0 | W78: =IF(AND(W$6>=EOMONTH($H$72,0),W$6<=EOMONTH(EDATE($H$72,$E$72-1),0)),$G$72/MAX($E$72,1),0) -> 0 | X78: =IF(AND(X$6>=EOMONTH($H$72,0),X$6<=EOMONTH(EDATE($H$72,$E$72-1),0)),$G$72/MAX($E$72,1),0) -> 0 | Y78: =IF(AND(Y$6>=EOMONTH($H$72,0),Y$6<=EOMONTH(EDATE($H$72,$E$72-1),0)),$G$72/MAX($E$72,1),0) -> 0 | Z78: =IF(AND(Z$6>=EOMONTH($H$72,0),Z$6<=EOMONTH(EDATE($H$72,$E$72-1),0)),$G$72/MAX($E$72,1),0) -> 0 | AA78: =IF(AND(AA$6>=EOMONTH($H$72,0),AA$6<=EOMONTH(EDATE($H$72,$E$72-1),0)),$G$72/MAX($E$72,1),0) -> 0 | ... CA78: =IF(AND(CA$6>=EOMONTH($H$72,0),CA$6<=EOMONTH(EDATE($H$72,$E$72-1),0)),$G$72/MAX($E$72,1),0) -> 0
B79: Pilot / Change Mgmt. | T79: =IF(AND(T$6>=EOMONTH($H$73,0),T$6<=EOMONTH(EDATE($H$73,$E$73-1),0)),$G$73/MAX($E$73,1),0) -> 0 | U79: =IF(AND(U$6>=EOMONTH($H$73,0),U$6<=EOMONTH(EDATE($H$73,$E$73-1),0)),$G$73/MAX($E$73,1),0) -> 0 | V79: =IF(AND(V$6>=EOMONTH($H$73,0),V$6<=EOMONTH(EDATE($H$73,$E$73-1),0)),$G$73/MAX($E$73,1),0) -> 0 | W79: =IF(AND(W$6>=EOMONTH($H$73,0),W$6<=EOMONTH(EDATE($H$73,$E$73-1),0)),$G$73/MAX($E$73,1),0) -> 0 | X79: =IF(AND(X$6>=EOMONTH($H$73,0),X$6<=EOMONTH(EDATE($H$73,$E$73-1),0)),$G$73/MAX($E$73,1),0) -> 0 | Y79: =IF(AND(Y$6>=EOMONTH($H$73,0),Y$6<=EOMONTH(EDATE($H$73,$E$73-1),0)),$G$73/MAX($E$73,1),0) -> 0 | Z79: =IF(AND(Z$6>=EOMONTH($H$73,0),Z$6<=EOMONTH(EDATE($H$73,$E$73-1),0)),$G$73/MAX($E$73,1),0) -> 0 | AA79: =IF(AND(AA$6>=EOMONTH($H$73,0),AA$6<=EOMONTH(EDATE($H$73,$E$73-1),0)),$G$73/MAX($E$73,1),0) -> 0 | ... CA79: =IF(AND(CA$6>=EOMONTH($H$73,0),CA$6<=EOMONTH(EDATE($H$73,$E$73-1),0)),$G$73/MAX($E$73,1),0) -> 0
B80: Scale / Run | T80: =IF(AND(T$6>=EOMONTH($H$74,0),T$6<=EOMONTH(EDATE($H$74,$E$74-1),0)),$G$74/MAX($E$74,1),0) -> 0 | U80: =IF(AND(U$6>=EOMONTH($H$74,0),U$6<=EOMONTH(EDATE($H$74,$E$74-1),0)),$G$74/MAX($E$74,1),0) -> 0 | V80: =IF(AND(V$6>=EOMONTH($H$74,0),V$6<=EOMONTH(EDATE($H$74,$E$74-1),0)),$G$74/MAX($E$74,1),0) -> 0 | W80: =IF(AND(W$6>=EOMONTH($H$74,0),W$6<=EOMONTH(EDATE($H$74,$E$74-1),0)),$G$74/MAX($E$74,1),0) -> 0 | X80: =IF(AND(X$6>=EOMONTH($H$74,0),X$6<=EOMONTH(EDATE($H$74,$E$74-1),0)),$G$74/MAX($E$74,1),0) -> 0 | Y80: =IF(AND(Y$6>=EOMONTH($H$74,0),Y$6<=EOMONTH(EDATE($H$74,$E$74-1),0)),$G$74/MAX($E$74,1),0) -> 0 | Z80: =IF(AND(Z$6>=EOMONTH($H$74,0),Z$6<=EOMONTH(EDATE($H$74,$E$74-1),0)),$G$74/MAX($E$74,1),0) -> 0 | AA80: =IF(AND(AA$6>=EOMONTH($H$74,0),AA$6<=EOMONTH(EDATE($H$74,$E$74-1),0)),$G$74/MAX($E$74,1),0) -> 0 | ... CA80: =IF(AND(CA$6>=EOMONTH($H$74,0),CA$6<=EOMONTH(EDATE($H$74,$E$74-1),0)),$G$74/MAX($E$74,1),0) -> 0
B81: Total milestone labor (all blocks) | G81: =SUM(G71:G74) -> 1283425
B83: One-time non-labor costs (vendor, integration, licences, change mgmt., etc.)
B84: Item | C84: Assumptions / notes | D84: Total $ | E84: Spread months | H84: Start month | I84: Cap %
B85: PRM / orchestration build (vendor) | C85: PENDING — placeholder, not data. Vendor RFP W8 | D85: 0 | E85: 5 | H85: =DATE(2026,12,1) -> 46357 | I85: 0
B86: Partner enablement & change management | C86: PENDING — placeholder, not data. | D86: 0 | E86: 6 | H86: =DATE(2027,4,1) -> 46478 | I86: 0
B87: Programme management (8% of build) | C87: 8% x (milestone labor + vendor + enablement) — Servicing S2 standard | D87: =$D$42*($G$81+$D$85+$D$86) -> 102674 | E87: 9 | H87: =DATE(2026,10,1) -> 46296 | I87: 0
B88: Contingency (10% of build incl. PM) | C88: 10% x (build subtotal incl. PM) — Servicing S2 standard | D88: =$D$43*($G$81+$D$85+$D$86+$D$87) -> 138609.9 | E88: 9 | H88: =DATE(2026,10,1) -> 46296 | I88: 0
B89: (spare) | D89: 0 | E89: 1 | H89: =DATE(2027,4,1) -> 46478 | I89: 0
B91: Non-labor phasing ($/month)
B92: phasing — item 1 | T92: =IF(AND(T$6>=EOMONTH($H$85,0),T$6<=EOMONTH(EDATE($H$85,$E$85-1),0)),$D$85/MAX($E$85,1),0) -> 0 | U92: =IF(AND(U$6>=EOMONTH($H$85,0),U$6<=EOMONTH(EDATE($H$85,$E$85-1),0)),$D$85/MAX($E$85,1),0) -> 0 | V92: =IF(AND(V$6>=EOMONTH($H$85,0),V$6<=EOMONTH(EDATE($H$85,$E$85-1),0)),$D$85/MAX($E$85,1),0) -> 0 | W92: =IF(AND(W$6>=EOMONTH($H$85,0),W$6<=EOMONTH(EDATE($H$85,$E$85-1),0)),$D$85/MAX($E$85,1),0) -> 0 | X92: =IF(AND(X$6>=EOMONTH($H$85,0),X$6<=EOMONTH(EDATE($H$85,$E$85-1),0)),$D$85/MAX($E$85,1),0) -> 0 | Y92: =IF(AND(Y$6>=EOMONTH($H$85,0),Y$6<=EOMONTH(EDATE($H$85,$E$85-1),0)),$D$85/MAX($E$85,1),0) -> 0 | Z92: =IF(AND(Z$6>=EOMONTH($H$85,0),Z$6<=EOMONTH(EDATE($H$85,$E$85-1),0)),$D$85/MAX($E$85,1),0) -> 0 | AA92: =IF(AND(AA$6>=EOMONTH($H$85,0),AA$6<=EOMONTH(EDATE($H$85,$E$85-1),0)),$D$85/MAX($E$85,1),0) -> 0 | ... CA92: =IF(AND(CA$6>=EOMONTH($H$85,0),CA$6<=EOMONTH(EDATE($H$85,$E$85-1),0)),$D$85/MAX($E$85,1),0) -> 0
B93: phasing — item 2 | T93: =IF(AND(T$6>=EOMONTH($H$86,0),T$6<=EOMONTH(EDATE($H$86,$E$86-1),0)),$D$86/MAX($E$86,1),0) -> 0 | U93: =IF(AND(U$6>=EOMONTH($H$86,0),U$6<=EOMONTH(EDATE($H$86,$E$86-1),0)),$D$86/MAX($E$86,1),0) -> 0 | V93: =IF(AND(V$6>=EOMONTH($H$86,0),V$6<=EOMONTH(EDATE($H$86,$E$86-1),0)),$D$86/MAX($E$86,1),0) -> 0 | W93: =IF(AND(W$6>=EOMONTH($H$86,0),W$6<=EOMONTH(EDATE($H$86,$E$86-1),0)),$D$86/MAX($E$86,1),0) -> 0 | X93: =IF(AND(X$6>=EOMONTH($H$86,0),X$6<=EOMONTH(EDATE($H$86,$E$86-1),0)),$D$86/MAX($E$86,1),0) -> 0 | Y93: =IF(AND(Y$6>=EOMONTH($H$86,0),Y$6<=EOMONTH(EDATE($H$86,$E$86-1),0)),$D$86/MAX($E$86,1),0) -> 0 | Z93: =IF(AND(Z$6>=EOMONTH($H$86,0),Z$6<=EOMONTH(EDATE($H$86,$E$86-1),0)),$D$86/MAX($E$86,1),0) -> 0 | AA93: =IF(AND(AA$6>=EOMONTH($H$86,0),AA$6<=EOMONTH(EDATE($H$86,$E$86-1),0)),$D$86/MAX($E$86,1),0) -> 0 | ... CA93: =IF(AND(CA$6>=EOMONTH($H$86,0),CA$6<=EOMONTH(EDATE($H$86,$E$86-1),0)),$D$86/MAX($E$86,1),0) -> 0
B94: phasing — item 3 | T94: =IF(AND(T$6>=EOMONTH($H$87,0),T$6<=EOMONTH(EDATE($H$87,$E$87-1),0)),$D$87/MAX($E$87,1),0) -> 0 | U94: =IF(AND(U$6>=EOMONTH($H$87,0),U$6<=EOMONTH(EDATE($H$87,$E$87-1),0)),$D$87/MAX($E$87,1),0) -> 0 | V94: =IF(AND(V$6>=EOMONTH($H$87,0),V$6<=EOMONTH(EDATE($H$87,$E$87-1),0)),$D$87/MAX($E$87,1),0) -> 0 | W94: =IF(AND(W$6>=EOMONTH($H$87,0),W$6<=EOMONTH(EDATE($H$87,$E$87-1),0)),$D$87/MAX($E$87,1),0) -> 0 | X94: =IF(AND(X$6>=EOMONTH($H$87,0),X$6<=EOMONTH(EDATE($H$87,$E$87-1),0)),$D$87/MAX($E$87,1),0) -> 0 | Y94: =IF(AND(Y$6>=EOMONTH($H$87,0),Y$6<=EOMONTH(EDATE($H$87,$E$87-1),0)),$D$87/MAX($E$87,1),0) -> 0 | Z94: =IF(AND(Z$6>=EOMONTH($H$87,0),Z$6<=EOMONTH(EDATE($H$87,$E$87-1),0)),$D$87/MAX($E$87,1),0) -> 0 | AA94: =IF(AND(AA$6>=EOMONTH($H$87,0),AA$6<=EOMONTH(EDATE($H$87,$E$87-1),0)),$D$87/MAX($E$87,1),0) -> 0 | ... CA94: =IF(AND(CA$6>=EOMONTH($H$87,0),CA$6<=EOMONTH(EDATE($H$87,$E$87-1),0)),$D$87/MAX($E$87,1),0) -> 0
B95: phasing — item 4 | T95: =IF(AND(T$6>=EOMONTH($H$88,0),T$6<=EOMONTH(EDATE($H$88,$E$88-1),0)),$D$88/MAX($E$88,1),0) -> 0 | U95: =IF(AND(U$6>=EOMONTH($H$88,0),U$6<=EOMONTH(EDATE($H$88,$E$88-1),0)),$D$88/MAX($E$88,1),0) -> 0 | V95: =IF(AND(V$6>=EOMONTH($H$88,0),V$6<=EOMONTH(EDATE($H$88,$E$88-1),0)),$D$88/MAX($E$88,1),0) -> 0 | W95: =IF(AND(W$6>=EOMONTH($H$88,0),W$6<=EOMONTH(EDATE($H$88,$E$88-1),0)),$D$88/MAX($E$88,1),0) -> 0 | X95: =IF(AND(X$6>=EOMONTH($H$88,0),X$6<=EOMONTH(EDATE($H$88,$E$88-1),0)),$D$88/MAX($E$88,1),0) -> 0 | Y95: =IF(AND(Y$6>=EOMONTH($H$88,0),Y$6<=EOMONTH(EDATE($H$88,$E$88-1),0)),$D$88/MAX($E$88,1),0) -> 0 | Z95: =IF(AND(Z$6>=EOMONTH($H$88,0),Z$6<=EOMONTH(EDATE($H$88,$E$88-1),0)),$D$88/MAX($E$88,1),0) -> 0 | AA95: =IF(AND(AA$6>=EOMONTH($H$88,0),AA$6<=EOMONTH(EDATE($H$88,$E$88-1),0)),$D$88/MAX($E$88,1),0) -> 0 | ... CA95: =IF(AND(CA$6>=EOMONTH($H$88,0),CA$6<=EOMONTH(EDATE($H$88,$E$88-1),0)),$D$88/MAX($E$88,1),0) -> 0
B96: phasing — item 5 | T96: =IF(AND(T$6>=EOMONTH($H$89,0),T$6<=EOMONTH(EDATE($H$89,$E$89-1),0)),$D$89/MAX($E$89,1),0) -> 0 | U96: =IF(AND(U$6>=EOMONTH($H$89,0),U$6<=EOMONTH(EDATE($H$89,$E$89-1),0)),$D$89/MAX($E$89,1),0) -> 0 | V96: =IF(AND(V$6>=EOMONTH($H$89,0),V$6<=EOMONTH(EDATE($H$89,$E$89-1),0)),$D$89/MAX($E$89,1),0) -> 0 | W96: =IF(AND(W$6>=EOMONTH($H$89,0),W$6<=EOMONTH(EDATE($H$89,$E$89-1),0)),$D$89/MAX($E$89,1),0) -> 0 | X96: =IF(AND(X$6>=EOMONTH($H$89,0),X$6<=EOMONTH(EDATE($H$89,$E$89-1),0)),$D$89/MAX($E$89,1),0) -> 0 | Y96: =IF(AND(Y$6>=EOMONTH($H$89,0),Y$6<=EOMONTH(EDATE($H$89,$E$89-1),0)),$D$89/MAX($E$89,1),0) -> 0 | Z96: =IF(AND(Z$6>=EOMONTH($H$89,0),Z$6<=EOMONTH(EDATE($H$89,$E$89-1),0)),$D$89/MAX($E$89,1),0) -> 0 | AA96: =IF(AND(AA$6>=EOMONTH($H$89,0),AA$6<=EOMONTH(EDATE($H$89,$E$89-1),0)),$D$89/MAX($E$89,1),0) -> 0 | ... CA96: =IF(AND(CA$6>=EOMONTH($H$89,0),CA$6<=EOMONTH(EDATE($H$89,$E$89-1),0)),$D$89/MAX($E$89,1),0) -> 0
B98: One-time investment feed rows ($M — these feed the WAVE sheet)
B99: CAPEX — capitalized build labor | L99: =SUMIFS($T99:$CA99,$T$5:$CA$5,2026) -> 0.10530667 | M99: =SUMIFS($T99:$CA99,$T$5:$CA$5,2027) -> 0.42122667 | N99: =SUMIFS($T99:$CA99,$T$5:$CA$5,2028) -> 0 | O99: =SUMIFS($T99:$CA99,$T$5:$CA$5,2029) -> 0 | P99: =SUMIFS($T99:$CA99,$T$5:$CA$5,2030) -> 0 | T99: =(SUMPRODUCT(T77:T80,$I$71:$I$74))/1000000 -> 0 | U99: =(SUMPRODUCT(U77:U80,$I$71:$I$74))/1000000 -> 0 | V99: =(SUMPRODUCT(V77:V80,$I$71:$I$74))/1000000 -> 0 | W99: =(SUMPRODUCT(W77:W80,$I$71:$I$74))/1000000 -> 0 | X99: =(SUMPRODUCT(X77:X80,$I$71:$I$74))/1000000 -> 0 | Y99: =(SUMPRODUCT(Y77:Y80,$I$71:$I$74))/1000000 -> 0 | Z99: =(SUMPRODUCT(Z77:Z80,$I$71:$I$74))/1000000 -> 0 | AA99: =(SUMPRODUCT(AA77:AA80,$I$71:$I$74))/1000000 -> 0 | ... CA99: =(SUMPRODUCT(CA77:CA80,$I$71:$I$74))/1000000 -> 0
B100: CAPEX — capitalized non-labor | L100: =SUMIFS($T100:$CA100,$T$5:$CA$5,2026) -> 0 | M100: =SUMIFS($T100:$CA100,$T$5:$CA$5,2027) -> 0 | N100: =SUMIFS($T100:$CA100,$T$5:$CA$5,2028) -> 0 | O100: =SUMIFS($T100:$CA100,$T$5:$CA$5,2029) -> 0 | P100: =SUMIFS($T100:$CA100,$T$5:$CA$5,2030) -> 0 | T100: =SUMPRODUCT(T92:T96,$I$85:$I$89)/1000000 -> 0 | U100: =SUMPRODUCT(U92:U96,$I$85:$I$89)/1000000 -> 0 | V100: =SUMPRODUCT(V92:V96,$I$85:$I$89)/1000000 -> 0 | W100: =SUMPRODUCT(W92:W96,$I$85:$I$89)/1000000 -> 0 | X100: =SUMPRODUCT(X92:X96,$I$85:$I$89)/1000000 -> 0 | Y100: =SUMPRODUCT(Y92:Y96,$I$85:$I$89)/1000000 -> 0 | Z100: =SUMPRODUCT(Z92:Z96,$I$85:$I$89)/1000000 -> 0 | AA100: =SUMPRODUCT(AA92:AA96,$I$85:$I$89)/1000000 -> 0 | ... CA100: =SUMPRODUCT(CA92:CA96,$I$85:$I$89)/1000000 -> 0
B101: OTC — build labor (expensed) | L101: =SUMIFS($T101:$CA101,$T$5:$CA$5,2026) -> 0.15796 | M101: =SUMIFS($T101:$CA101,$T$5:$CA$5,2027) -> 0.59893167 | N101: =SUMIFS($T101:$CA101,$T$5:$CA$5,2028) -> 0 | O101: =SUMIFS($T101:$CA101,$T$5:$CA$5,2029) -> 0 | P101: =SUMIFS($T101:$CA101,$T$5:$CA$5,2030) -> 0 | T101: =(SUMPRODUCT(T77:T80,1-$I$71:$I$74))/1000000 -> 0 | U101: =(SUMPRODUCT(U77:U80,1-$I$71:$I$74))/1000000 -> 0 | V101: =(SUMPRODUCT(V77:V80,1-$I$71:$I$74))/1000000 -> 0 | W101: =(SUMPRODUCT(W77:W80,1-$I$71:$I$74))/1000000 -> 0 | X101: =(SUMPRODUCT(X77:X80,1-$I$71:$I$74))/1000000 -> 0 | Y101: =(SUMPRODUCT(Y77:Y80,1-$I$71:$I$74))/1000000 -> 0 | Z101: =(SUMPRODUCT(Z77:Z80,1-$I$71:$I$74))/1000000 -> 0 | AA101: =(SUMPRODUCT(AA77:AA80,1-$I$71:$I$74))/1000000 -> 0 | ... CA101: =(SUMPRODUCT(CA77:CA80,1-$I$71:$I$74))/1000000 -> 0
B102: OTC — non-labor (expensed) | L102: =SUMIFS($T102:$CA102,$T$5:$CA$5,2026) -> 0.080427967 | M102: =SUMIFS($T102:$CA102,$T$5:$CA$5,2027) -> 0.16085593 | N102: =SUMIFS($T102:$CA102,$T$5:$CA$5,2028) -> 0 | O102: =SUMIFS($T102:$CA102,$T$5:$CA$5,2029) -> 0 | P102: =SUMIFS($T102:$CA102,$T$5:$CA$5,2030) -> 0 | T102: =SUMPRODUCT(T92:T96,1-$I$85:$I$89)/1000000 -> 0 | U102: =SUMPRODUCT(U92:U96,1-$I$85:$I$89)/1000000 -> 0 | V102: =SUMPRODUCT(V92:V96,1-$I$85:$I$89)/1000000 -> 0 | W102: =SUMPRODUCT(W92:W96,1-$I$85:$I$89)/1000000 -> 0 | X102: =SUMPRODUCT(X92:X96,1-$I$85:$I$89)/1000000 -> 0 | Y102: =SUMPRODUCT(Y92:Y96,1-$I$85:$I$89)/1000000 -> 0 | Z102: =SUMPRODUCT(Z92:Z96,1-$I$85:$I$89)/1000000 -> 0 | AA102: =SUMPRODUCT(AA92:AA96,1-$I$85:$I$89)/1000000 -> 0 | ... CA102: =SUMPRODUCT(CA92:CA96,1-$I$85:$I$89)/1000000 -> 0
B103: Total one-time investment ($M) | L103: =SUM(L99:L102) -> 0.34369463 | M103: =SUM(M99:M102) -> 1.1810143 | N103: =SUM(N99:N102) -> 0 | O103: =SUM(O99:O102) -> 0 | P103: =SUM(P99:P102) -> 0
B105: 6. RECURRING RUN COSTS to achieve impact
B107: Line | C107: Assumptions / notes | D107: Annual $ (steady state) | H107: Start month | I107: Scales with ramp? (Y/N)
B108: OPEX - Token cost for SDR agents | C108: PENDING — placeholder, not data. SDR agent token consumption — scales with ramp | D108: 0 | H108: =DATE(2027,4,1) -> 46478 | I108: Y
B109: OPEX - PRM / orchestration platform run | C109: PENDING — placeholder, not data. Recurring platform opex | D109: 0 | H109: =DATE(2027,4,1) -> 46478 | I109: N
B110: OPEX - Support & maintenance | C110: PENDING — placeholder, not data. Ongoing support/maintenance | D110: 0 | H110: =DATE(2027,4,1) -> 46478 | I110: N
B112: Run-cost feed rows ($M)
B113: OPEX - Token cost for SDR agents [RUN] | K113: =SUMIFS($T113:$CA113,$T$5:$CA$5,2030) -> 0 | L113: =SUMIFS($T113:$CA113,$T$5:$CA$5,2026) -> 0 | M113: =SUMIFS($T113:$CA113,$T$5:$CA$5,2027) -> 0 | N113: =SUMIFS($T113:$CA113,$T$5:$CA$5,2028) -> 0 | O113: =SUMIFS($T113:$CA113,$T$5:$CA$5,2029) -> 0 | P113: =SUMIFS($T113:$CA113,$T$5:$CA$5,2030) -> 0 | T113: =$D$108/1000000/12*IF($I$108="Y",T$56,IF(T$6>=EOMONTH($H$108,0),1,0)) -> 0 | U113: =$D$108/1000000/12*IF($I$108="Y",U$56,IF(U$6>=EOMONTH($H$108,0),1,0)) -> 0 | V113: =$D$108/1000000/12*IF($I$108="Y",V$56,IF(V$6>=EOMONTH($H$108,0),1,0)) -> 0 | W113: =$D$108/1000000/12*IF($I$108="Y",W$56,IF(W$6>=EOMONTH($H$108,0),1,0)) -> 0 | X113: =$D$108/1000000/12*IF($I$108="Y",X$56,IF(X$6>=EOMONTH($H$108,0),1,0)) -> 0 | Y113: =$D$108/1000000/12*IF($I$108="Y",Y$56,IF(Y$6>=EOMONTH($H$108,0),1,0)) -> 0 | Z113: =$D$108/1000000/12*IF($I$108="Y",Z$56,IF(Z$6>=EOMONTH($H$108,0),1,0)) -> 0 | AA113: =$D$108/1000000/12*IF($I$108="Y",AA$56,IF(AA$6>=EOMONTH($H$108,0),1,0)) -> 0 | ... CA113: =$D$108/1000000/12*IF($I$108="Y",CA$56,IF(CA$6>=EOMONTH($H$108,0),1,0)) -> 0
B114: OPEX - PRM / orchestration platform run [RUN] | K114: =SUMIFS($T114:$CA114,$T$5:$CA$5,2030) -> 0 | L114: =SUMIFS($T114:$CA114,$T$5:$CA$5,2026) -> 0 | M114: =SUMIFS($T114:$CA114,$T$5:$CA$5,2027) -> 0 | N114: =SUMIFS($T114:$CA114,$T$5:$CA$5,2028) -> 0 | O114: =SUMIFS($T114:$CA114,$T$5:$CA$5,2029) -> 0 | P114: =SUMIFS($T114:$CA114,$T$5:$CA$5,2030) -> 0 | T114: =$D$109/1000000/12*IF($I$109="Y",T$56,IF(T$6>=EOMONTH($H$109,0),1,0)) -> 0 | U114: =$D$109/1000000/12*IF($I$109="Y",U$56,IF(U$6>=EOMONTH($H$109,0),1,0)) -> 0 | V114: =$D$109/1000000/12*IF($I$109="Y",V$56,IF(V$6>=EOMONTH($H$109,0),1,0)) -> 0 | W114: =$D$109/1000000/12*IF($I$109="Y",W$56,IF(W$6>=EOMONTH($H$109,0),1,0)) -> 0 | X114: =$D$109/1000000/12*IF($I$109="Y",X$56,IF(X$6>=EOMONTH($H$109,0),1,0)) -> 0 | Y114: =$D$109/1000000/12*IF($I$109="Y",Y$56,IF(Y$6>=EOMONTH($H$109,0),1,0)) -> 0 | Z114: =$D$109/1000000/12*IF($I$109="Y",Z$56,IF(Z$6>=EOMONTH($H$109,0),1,0)) -> 0 | AA114: =$D$109/1000000/12*IF($I$109="Y",AA$56,IF(AA$6>=EOMONTH($H$109,0),1,0)) -> 0 | ... CA114: =$D$109/1000000/12*IF($I$109="Y",CA$56,IF(CA$6>=EOMONTH($H$109,0),1,0)) -> 0
B115: OPEX - Support & maintenance [RUN] | K115: =SUMIFS($T115:$CA115,$T$5:$CA$5,2030) -> 0 | L115: =SUMIFS($T115:$CA115,$T$5:$CA$5,2026) -> 0 | M115: =SUMIFS($T115:$CA115,$T$5:$CA$5,2027) -> 0 | N115: =SUMIFS($T115:$CA115,$T$5:$CA$5,2028) -> 0 | O115: =SUMIFS($T115:$CA115,$T$5:$CA$5,2029) -> 0 | P115: =SUMIFS($T115:$CA115,$T$5:$CA$5,2030) -> 0 | T115: =$D$110/1000000/12*IF($I$110="Y",T$56,IF(T$6>=EOMONTH($H$110,0),1,0)) -> 0 | U115: =$D$110/1000000/12*IF($I$110="Y",U$56,IF(U$6>=EOMONTH($H$110,0),1,0)) -> 0 | V115: =$D$110/1000000/12*IF($I$110="Y",V$56,IF(V$6>=EOMONTH($H$110,0),1,0)) -> 0 | W115: =$D$110/1000000/12*IF($I$110="Y",W$56,IF(W$6>=EOMONTH($H$110,0),1,0)) -> 0 | X115: =$D$110/1000000/12*IF($I$110="Y",X$56,IF(X$6>=EOMONTH($H$110,0),1,0)) -> 0 | Y115: =$D$110/1000000/12*IF($I$110="Y",Y$56,IF(Y$6>=EOMONTH($H$110,0),1,0)) -> 0 | Z115: =$D$110/1000000/12*IF($I$110="Y",Z$56,IF(Z$6>=EOMONTH($H$110,0),1,0)) -> 0 | AA115: =$D$110/1000000/12*IF($I$110="Y",AA$56,IF(AA$6>=EOMONTH($H$110,0),1,0)) -> 0 | ... CA115: =$D$110/1000000/12*IF($I$110="Y",CA$56,IF(CA$6>=EOMONTH($H$110,0),1,0)) -> 0
B116: Total run cost ($M) | K116: =SUM(K113:K115) -> 0 | L116: =SUM(L113:L115) -> 0 | M116: =SUM(M113:M115) -> 0 | N116: =SUM(N113:N115) -> 0 | O116: =SUM(O113:O115) -> 0 | P116: =SUM(P113:P115) -> 0
B118: 7. WAVE MAPPING (reference)
B120: Model row 62 — Revenue - Partner-channel share uplift | F120: → WAVE row 66 (Section II — Recurring Benefits)
B121: Model row 63 — Revenue - SDR agent uplift (conversion + acceleration) | F121: → WAVE row 67 (Section II — Recurring Benefits)
B122: Model row 64 — OPEX - Seller time saved on lead management (enabler) | F122: → WAVE row 79 (Section II — Recurring Benefits)
B123: Model row 113 — OPEX - Token cost for SDR agents | F123: → WAVE row 107 (Section II — Recurring Costs)
B124: Model row 114 — OPEX - PRM / orchestration platform run | F124: → WAVE row 108 (Section II — Recurring Costs)
...

Sheet SALES-2 WAVE
L1: 1 | M1: 2 | N1: 3 | O1: 4 | P1: 5 | R1: =COUNTIFS($R$66:$R$117, "Error") -> 0 | T1: 2026 | U1: 2026 | V1: 2026 | W1: 2026 | X1: 2026 | Y1: 2026 | Z1: 2026 | AA1: 2026 | AB1: 2026 | AC1: 2026 | AD1: 2026 | AE1: 2026 | AF1: 2027 | AG1: 2027 | AH1: 2027 | AI1: 2027 | AJ1: 2027 | AK1: 2027 | AL1: 2027 | AM1: 2027 | AN1: 2027 | AO1: 2027 | AP1: 2027 | AQ1: 2027 | AR1: 2028 | AS1: 2028 | AT1: 2028 | AU1: 2028 | AV1: 2028 | AW1: 2028 | AX1: 2028 | AY1: 2028 | AZ1: 2028 | BA1: 2028 | BB1: 2028 | BC1: 2028 | BD1: 2029 | BE1: 2029 | BF1: 2029 | BG1: 2029 | BH1: 2029 | BI1: 2029 | BJ1: 2029 | BK1: 2029 | BL1: 2029 | BM1: 2029 | BN1: 2029 | BO1: 2029 | BP1: 2030 | BQ1: 2030 | BR1: 2030 | BS1: 2030 | BT1: 2030 | BU1: 2030 | BV1: 2030 | BW1: 2030 | BX1: 2030 | BY1: 2030 | BZ1: 2030 | CA1: 2030 | CI1: =COUNTIFS(CI$66:CI$149, "FALSE") -> 0 | CJ1: =COUNTIFS(CJ$66:CJ$149, "FALSE") -> 0 | CK1: =COUNTIFS(CK$66:CK$149, "FALSE") -> 0 | CL1: =COUNTIFS(CL$66:CL$149, "FALSE") -> 0 | CM1: =COUNTIFS(CM$66:CM$149, "FALSE") -> 0
C2: ="#"&$F$6&" Initiative Business Case" -> #TBD Initiative Business Case
C4: INPUTS & ASSUMPTIONS
D6: Initiative # | F6: TBD
D7: Initiative Owner | F7: Sales initiative owner — TBC
D8: Initiative Name | F8: SMB long-tail growth through partner-channel scaling and autonomous SDR outreach
D11: Estimated L4 date | F11: ='SALES-2 Model'!$D$13 -> 46478
D12: Net Recurring Benefit ($M) | F12: =$K$117 -> 0
C14: SECTION I - PRIMARY VALUE DRIVER (ILLUSTRATIVE)
D16: Primary value driver — linked to the Model sheet; refine with the initiative owner
D17: Baseline | H17: Period | I17: KPI | J17: Inputs
E18: Partner/referral-channel NSR | H18: TTM 6/1/26 | I18: $USD M | J18: ='SALES-2 Model'!$D$27/1000000 -> 0
E19: SDR-influenced NSR base | H19: TTM 6/1/26 | I19: $USD M | J19: ='SALES-2 Model'!$D$29/1000000 -> 0
E20: TM % of NSR (SMB blended) | H20: TTM 6/1/26 | I20: % | J20: ='SALES-2 Model'!$D$28 -> 0
D23: Goal
E24: Partner share uplift x incrementality | H24: Steady state | I24: % | J24: ='SALES-2 Model'!$D$34*'SALES-2 Model'!$D$35 -> 0
E25: SDR conversion uplift x capture | H25: Steady state | I25: % | J25: ='SALES-2 Model'!$D$36*'SALES-2 Model'!$D$37 -> 0.108
D28: Incremental Improvement
E29: Total annual benefit (run rate) | I29: $USD M | J29: =('SALES-2 Model'!$D$49+'SALES-2 Model'!$D$50+'SALES-2 Model'!$D$51)/1000000 -> 0
C60: SECTION II - NET RECURRING BENEFITS | CC60: ANNUAL SUMMARY | CI60: CHECK CELLS
T62: 2026 | AF62: 2027 | AR62: 2028 | BD62: 2029 | BP62: 2030 | CI62: CHECK
D63: RECURRING BENEFITS | H63: Comment | I63: Baseline | J63: Goal | K63: Ann. Run Rate | L63: 2026 | M63: =L63+1 -> 2027 | N63: =M63+1 -> 2028 | O63: =N63+1 -> 2029 | P63: =O63+1 -> 2030 | Q63: Impacted BU | R63: Check | T63: 46023 | U63: =EOMONTH(T63, 1) -> 46081 | V63: =EOMONTH(U63, 1) -> 46112 | W63: =EOMONTH(V63, 1) -> 46142 | X63: =EOMONTH(W63, 1) -> 46173 | Y63: =EOMONTH(X63, 1) -> 46203 | Z63: =EOMONTH(Y63, 1) -> 46234 | AA63: =EOMONTH(Z63, 1) -> 46265 | AB63: =EOMONTH(AA63, 1) -> 46295 | ... CA63: =EOMONTH(BZ63, 1) -> 47848 | CC63: 2026 | CD63: =CC63+1 -> 2027 | CE63: =CD63+1 -> 2028 | CF63: =CE63+1 -> 2029 | CG63: =CF63+1 -> 2030 | CI63: 2026 | CJ63: =CI63+1 -> 2027 | CK63: =CJ63+1 -> 2028 | CL63: =CK63+1 -> 2029 | CM63: =CL63+1 -> 2030
E64: $USD M | I64: =$H$18 -> TTM 6/1/26 | J64: Future State | K64: Increment
E65: Revenue
E66: Revenue - Partner-channel share uplift | H66: ~100% share uplift x incrementality (net of cannibalization — Finance to agree) | I66: ='SALES-2 Model'!$D$62 -> 0 | J66: =I66+'SALES-2 Model'!$K$62 -> 0 | K66: ='SALES-2 Model'!$K$62 -> 0 | L66: ='SALES-2 Model'!L62 -> 0 | M66: ='SALES-2 Model'!M62 -> 0 | N66: ='SALES-2 Model'!N62 -> 0 | O66: ='SALES-2 Model'!O62 -> 0 | P66: ='SALES-2 Model'!P62 -> 0 | Q66: Global Sales | R66: =IF(K66=P66, "", "Error") | T66: ='SALES-2 Model'!T62 -> 0 | U66: ='SALES-2 Model'!U62 -> 0 | V66: ='SALES-2 Model'!V62 -> 0 | W66: ='SALES-2 Model'!W62 -> 0 | X66: ='SALES-2 Model'!X62 -> 0 | Y66: ='SALES-2 Model'!Y62 -> 0 | Z66: ='SALES-2 Model'!Z62 -> 0 | AA66: ='SALES-2 Model'!AA62 -> 0 | ... CA66: ='SALES-2 Model'!CA62 -> 0 | CC66: =SUMIFS($T66:$CA66, $T$1:$CA$1, CC$63) -> 0 | CD66: =SUMIFS($T66:$CA66, $T$1:$CA$1, CD$63) -> 0 | CE66: =SUMIFS($T66:$CA66, $T$1:$CA$1, CE$63) -> 0 | CF66: =SUMIFS($T66:$CA66, $T$1:$CA$1, CF$63) -> 0 | CG66: =SUMIFS($T66:$CA66, $T$1:$CA$1, CG$63) -> 0 | CI66: =CC66=L66 -> 1 | CJ66: =CD66=M66 -> 1 | CK66: =CE66=N66 -> 1 | CL66: =CF66=O66 -> 1 | CM66: =CG66=P66 -> 1
E67: Revenue - SDR agent uplift (conversion + acceleration) | H67: ~15% conversion uplift at 72% capture; ~12-day pull-forward folded in once agreed | I67: ='SALES-2 Model'!$D$63 -> 0 | J67: =I67+'SALES-2 Model'!$K$63 -> 0 | K67: ='SALES-2 Model'!$K$63 -> 0 | L67: ='SALES-2 Model'!L63 -> 0 | M67: ='SALES-2 Model'!M63 -> 0 | N67: ='SALES-2 Model'!N63 -> 0 | O67: ='SALES-2 Model'!O63 -> 0 | P67: ='SALES-2 Model'!P63 -> 0 | Q67: Global Sales | R67: =IF(K67=P67, "", "Error") | T67: ='SALES-2 Model'!T63 -> 0 | U67: ='SALES-2 Model'!U63 -> 0 | V67: ='SALES-2 Model'!V63 -> 0 | W67: ='SALES-2 Model'!W63 -> 0 | X67: ='SALES-2 Model'!X63 -> 0 | Y67: ='SALES-2 Model'!Y63 -> 0 | Z67: ='SALES-2 Model'!Z63 -> 0 | AA67: ='SALES-2 Model'!AA63 -> 0 | ... CA67: ='SALES-2 Model'!CA63 -> 0 | CC67: =SUMIFS($T67:$CA67, $T$1:$CA$1, CC$63) -> 0 | CD67: =SUMIFS($T67:$CA67, $T$1:$CA$1, CD$63) -> 0 | CE67: =SUMIFS($T67:$CA67, $T$1:$CA$1, CE$63) -> 0 | CF67: =SUMIFS($T67:$CA67, $T$1:$CA$1, CF$63) -> 0 | CG67: =SUMIFS($T67:$CA67, $T$1:$CA$1, CG$63) -> 0 | CI67: =CC67=L67 -> 1 | CJ67: =CD67=M67 -> 1 | CK67: =CE67=N67 -> 1 | CL67: =CF67=O67 -> 1 | CM67: =CG67=P67 -> 1
E68: Revenue Subtotal | I68: =SUM(I66:I67) -> 0 | J68: =SUM(J66:J67) -> 0 | K68: =SUM(K66:K67) -> 0 | L68: =SUM(L66:L67) -> 0 | M68: =SUM(M66:M67) -> 0 | N68: =SUM(N66:N67) -> 0 | O68: =SUM(O66:O67) -> 0 | P68: =SUM(P66:P67) -> 0 | T68: =SUM(T66:T67) -> 0 | U68: =SUM(U66:U67) -> 0 | V68: =SUM(V66:V67) -> 0 | W68: =SUM(W66:W67) -> 0 | X68: =SUM(X66:X67) -> 0 | Y68: =SUM(Y66:Y67) -> 0 | Z68: =SUM(Z66:Z67) -> 0 | AA68: =SUM(AA66:AA67) -> 0 | ... CA68: =SUM(CA66:CA67) -> 0 | CC68: =SUM(CC66:CC67) -> 0 | CD68: =SUM(CD66:CD67) -> 0 | CE68: =SUM(CE66:CE67) -> 0 | CF68: =SUM(CF66:CF67) -> 0 | CG68: =SUM(CG66:CG67) -> 0 | CI68: =CC68=L68 -> 1 | CJ68: =CD68=M68 -> 1 | CK68: =CE68=N68 -> 1 | CL68: =CF68=O68 -> 1 | CM68: =CG68=P68 -> 1
E70: Cost of Sales
K71: =I71-J71 -> 0 | R71: =IF(K71=P71, "", "Error") | CC71: =SUMIFS($T71:$CA71, $T$1:$CA$1, CC$63) -> 0 | CD71: =SUMIFS($T71:$CA71, $T$1:$CA$1, CD$63) -> 0 | CE71: =SUMIFS($T71:$CA71, $T$1:$CA$1, CE$63) -> 0 | CF71: =SUMIFS($T71:$CA71, $T$1:$CA$1, CF$63) -> 0 | CG71: =SUMIFS($T71:$CA71, $T$1:$CA$1, CG$63) -> 0 | CI71: =CC71=L71 -> 1 | CJ71: =CD71=M71 -> 1 | CK71: =CE71=N71 -> 1 | CL71: =CF71=O71 -> 1 | CM71: =CG71=P71 -> 1
I72: 0 | J72: 0 | K72: =I72-J72 -> 0 | R72: =IF(K72=P72, "", "Error") | CC72: =SUMIFS($T72:$CA72, $T$1:$CA$1, CC$63) -> 0 | CD72: =SUMIFS($T72:$CA72, $T$1:$CA$1, CD$63) -> 0 | CE72: =SUMIFS($T72:$CA72, $T$1:$CA$1, CE$63) -> 0 | CF72: =SUMIFS($T72:$CA72, $T$1:$CA$1, CF$63) -> 0 | CG72: =SUMIFS($T72:$CA72, $T$1:$CA$1, CG$63) -> 0 | CI72: =CC72=L72 -> 1 | CJ72: =CD72=M72 -> 1 | CK72: =CE72=N72 -> 1 | CL72: =CF72=O72 -> 1 | CM72: =CG72=P72 -> 1
I73: 0 | J73: 0 | K73: =I73-J73 -> 0 | R73: =IF(K73=P73, "", "Error") | CC73: =SUMIFS($T73:$CA73, $T$1:$CA$1, CC$63) -> 0 | CD73: =SUMIFS($T73:$CA73, $T$1:$CA$1, CD$63) -> 0 | CE73: =SUMIFS($T73:$CA73, $T$1:$CA$1, CE$63) -> 0 | CF73: =SUMIFS($T73:$CA73, $T$1:$CA$1, CF$63) -> 0 | CG73: =SUMIFS($T73:$CA73, $T$1:$CA$1, CG$63) -> 0 | CI73: =CC73=L73 -> 1 | CJ73: =CD73=M73 -> 1 | CK73: =CE73=N73 -> 1 | CL73: =CF73=O73 -> 1 | CM73: =CG73=P73 -> 1
I74: 0 | J74: 0 | K74: =I74-J74 -> 0 | R74: =IF(K74=P74, "", "Error") | CC74: =SUMIFS($T74:$CA74, $T$1:$CA$1, CC$63) -> 0 | CD74: =SUMIFS($T74:$CA74, $T$1:$CA$1, CD$63) -> 0 | CE74: =SUMIFS($T74:$CA74, $T$1:$CA$1, CE$63) -> 0 | CF74: =SUMIFS($T74:$CA74, $T$1:$CA$1, CF$63) -> 0 | CG74: =SUMIFS($T74:$CA74, $T$1:$CA$1, CG$63) -> 0 | CI74: =CC74=L74 -> 1 | CJ74: =CD74=M74 -> 1 | CK74: =CE74=N74 -> 1 | CL74: =CF74=O74 -> 1 | CM74: =CG74=P74 -> 1
K75: =I75-J75 -> 0 | R75: =IF(K75=P75, "", "Error") | CC75: =SUMIFS($T75:$CA75, $T$1:$CA$1, CC$63) -> 0 | CD75: =SUMIFS($T75:$CA75, $T$1:$CA$1, CD$63) -> 0 | CE75: =SUMIFS($T75:$CA75, $T$1:$CA$1, CE$63) -> 0 | CF75: =SUMIFS($T75:$CA75, $T$1:$CA$1, CF$63) -> 0 | CG75: =SUMIFS($T75:$CA75, $T$1:$CA$1, CG$63) -> 0 | CI75: =CC75=L75 -> 1 | CJ75: =CD75=M75 -> 1 | CK75: =CE75=N75 -> 1 | CL75: =CF75=O75 -> 1 | CM75: =CG75=P75 -> 1
E76: Cost of Sales Subtotal | I76: =SUM(I71:I75) -> 0 | J76: =SUM(J71:J75) -> 0 | K76: =SUM(K71:K75) -> 0 | L76: =SUM(L71:L75) -> 0 | M76: =SUM(M71:M75) -> 0 | N76: =SUM(N71:N75) -> 0 | O76: =SUM(O71:O75) -> 0 | P76: =SUM(P71:P75) -> 0 | T76: =SUM(T71:T75) -> 0 | U76: =SUM(U71:U75) -> 0 | V76: =SUM(V71:V75) -> 0 | W76: =SUM(W71:W75) -> 0 | X76: =SUM(X71:X75) -> 0 | Y76: =SUM(Y71:Y75) -> 0 | Z76: =SUM(Z71:Z75) -> 0 | AA76: =SUM(AA71:AA75) -> 0 | ... CA76: =SUM(CA71:CA75) -> 0 | CC76: =SUM(CC71:CC75) -> 0 | CD76: =SUM(CD71:CD75) -> 0 | CE76: =SUM(CE71:CE75) -> 0 | CF76: =SUM(CF71:CF75) -> 0 | CG76: =SUM(CG71:CG75) -> 0 | CI76: =CC76=L76 -> 1 | CJ76: =CD76=M76 -> 1 | CK76: =CE76=N76 -> 1 | CL76: =CF76=O76 -> 1 | CM76: =CG76=P76 -> 1
E78: OPEX
E79: OPEX - Seller time saved on lead management (enabler) | H79: 35–40% time saved at 65% capture — enabler; confirm bankability | I79: ='SALES-2 Model'!$D$64 -> 0 | J79: =I79-'SALES-2 Model'!$K$64 -> 0 | K79: ='SALES-2 Model'!$K$64 -> 0 | L79: ='SALES-2 Model'!L64 -> 0 | M79: ='SALES-2 Model'!M64 -> 0 | N79: ='SALES-2 Model'!N64 -> 0 | O79: ='SALES-2 Model'!O64 -> 0 | P79: ='SALES-2 Model'!P64 -> 0 | Q79: Global Sales | R79: =IF(K79=P79, "", "Error") | T79: ='SALES-2 Model'!T64 -> 0 | U79: ='SALES-2 Model'!U64 -> 0 | V79: ='SALES-2 Model'!V64 -> 0 | W79: ='SALES-2 Model'!W64 -> 0 | X79: ='SALES-2 Model'!X64 -> 0 | Y79: ='SALES-2 Model'!Y64 -> 0 | Z79: ='SALES-2 Model'!Z64 -> 0 | AA79: ='SALES-2 Model'!AA64 -> 0 | ... CA79: ='SALES-2 Model'!CA64 -> 0 | CC79: =SUMIFS($T79:$CA79, $T$1:$CA$1, CC$63) -> 0 | CD79: =SUMIFS($T79:$CA79, $T$1:$CA$1, CD$63) -> 0 | CE79: =SUMIFS($T79:$CA79, $T$1:$CA$1, CE$63) -> 0 | CF79: =SUMIFS($T79:$CA79, $T$1:$CA$1, CF$63) -> 0 | CG79: =SUMIFS($T79:$CA79, $T$1:$CA$1, CG$63) -> 0 | CI79: =CC79=L79 -> 1 | CJ79: =CD79=M79 -> 1 | CK79: =CE79=N79 -> 1 | CL79: =CF79=O79 -> 1 | CM79: =CG79=P79 -> 1
I80: 0 | J80: 0 | K80: =I80-J80 -> 0 | R80: =IF(K80=P80, "", "Error") | CC80: =SUMIFS($T80:$CA80, $T$1:$CA$1, CC$63) -> 0 | CD80: =SUMIFS($T80:$CA80, $T$1:$CA$1, CD$63) -> 0 | CE80: =SUMIFS($T80:$CA80, $T$1:$CA$1, CE$63) -> 0 | CF80: =SUMIFS($T80:$CA80, $T$1:$CA$1, CF$63) -> 0 | CG80: =SUMIFS($T80:$CA80, $T$1:$CA$1, CG$63) -> 0 | CI80: =CC80=L80 -> 1 | CJ80: =CD80=M80 -> 1 | CK80: =CE80=N80 -> 1 | CL80: =CF80=O80 -> 1 | CM80: =CG80=P80 -> 1
I81: 0 | J81: 0 | K81: =I81-J81 -> 0 | R81: =IF(K81=P81, "", "Error") | CC81: =SUMIFS($T81:$CA81, $T$1:$CA$1, CC$63) -> 0 | CD81: =SUMIFS($T81:$CA81, $T$1:$CA$1, CD$63) -> 0 | CE81: =SUMIFS($T81:$CA81, $T$1:$CA$1, CE$63) -> 0 | CF81: =SUMIFS($T81:$CA81, $T$1:$CA$1, CF$63) -> 0 | CG81: =SUMIFS($T81:$CA81, $T$1:$CA$1, CG$63) -> 0 | CI81: =CC81=L81 -> 1 | CJ81: =CD81=M81 -> 1 | CK81: =CE81=N81 -> 1 | CL81: =CF81=O81 -> 1 | CM81: =CG81=P81 -> 1
I82: 0 | J82: 0 | K82: =I82-J82 -> 0 | R82: =IF(K82=P82, "", "Error") | CC82: =SUMIFS($T82:$CA82, $T$1:$CA$1, CC$63) -> 0 | CD82: =SUMIFS($T82:$CA82, $T$1:$CA$1, CD$63) -> 0 | CE82: =SUMIFS($T82:$CA82, $T$1:$CA$1, CE$63) -> 0 | CF82: =SUMIFS($T82:$CA82, $T$1:$CA$1, CF$63) -> 0 | CG82: =SUMIFS($T82:$CA82, $T$1:$CA$1, CG$63) -> 0 | CI82: =CC82=L82 -> 1 | CJ82: =CD82=M82 -> 1 | CK82: =CE82=N82 -> 1 | CL82: =CF82=O82 -> 1 | CM82: =CG82=P82 -> 1
I83: 0 | J83: 0 | K83: =I83-J83 -> 0 | R83: =IF(K83=P83, "", "Error") | CC83: =SUMIFS($T83:$CA83, $T$1:$CA$1, CC$63) -> 0 | CD83: =SUMIFS($T83:$CA83, $T$1:$CA$1, CD$63) -> 0 | CE83: =SUMIFS($T83:$CA83, $T$1:$CA$1, CE$63) -> 0 | CF83: =SUMIFS($T83:$CA83, $T$1:$CA$1, CF$63) -> 0 | CG83: =SUMIFS($T83:$CA83, $T$1:$CA$1, CG$63) -> 0 | CI83: =CC83=L83 -> 1 | CJ83: =CD83=M83 -> 1 | CK83: =CE83=N83 -> 1 | CL83: =CF83=O83 -> 1 | CM83: =CG83=P83 -> 1
E84: OpEx subtotal | I84: =SUM(I79:I83) -> 0 | J84: =SUM(J79:J83) -> 0 | K84: =SUM(K79:K83) -> 0 | L84: =SUM(L79:L83) -> 0 | M84: =SUM(M79:M83) -> 0 | N84: =SUM(N79:N83) -> 0 | O84: =SUM(O79:O83) -> 0 | P84: =SUM(P79:P83) -> 0 | T84: =SUM(T79:T83) -> 0 | U84: =SUM(U79:U83) -> 0 | V84: =SUM(V79:V83) -> 0 | W84: =SUM(W79:W83) -> 0 | X84: =SUM(X79:X83) -> 0 | Y84: =SUM(Y79:Y83) -> 0 | Z84: =SUM(Z79:Z83) -> 0 | AA84: =SUM(AA79:AA83) -> 0 | ... CA84: =SUM(CA79:CA83) -> 0 | CC84: =SUM(CC79:CC83) -> 0 | CD84: =SUM(CD79:CD83) -> 0 | CE84: =SUM(CE79:CE83) -> 0 | CF84: =SUM(CF79:CF83) -> 0 | CG84: =SUM(CG79:CG83) -> 0 | CI84: =CC84=L84 -> 1 | CJ84: =CD84=M84 -> 1 | CK84: =CE84=N84 -> 1 | CL84: =CF84=O84 -> 1 | CM84: =CG84=P84 -> 1
E88: Recurring Benefits Total | I88: =SUM(I68, I76, I84) -> 0 | J88: =SUM(J68, J76, J84) -> 0 | K88: =SUM(K68, K76, K84) -> 0 | L88: =SUM(L68, L76, L84) -> 0 | M88: =SUM(M68, M76, M84) -> 0 | N88: =SUM(N68, N76, N84) -> 0 | O88: =SUM(O68, O76, O84) -> 0 | P88: =SUM(P68, P76, P84) -> 0 | T88: =SUM(T68, T76, T84) -> 0 | U88: =SUM(U68, U76, U84) -> 0 | V88: =SUM(V68, V76, V84) -> 0 | W88: =SUM(W68, W76, W84) -> 0 | X88: =SUM(X68, X76, X84) -> 0 | Y88: =SUM(Y68, Y76, Y84) -> 0 | Z88: =SUM(Z68, Z76, Z84) -> 0 | AA88: =SUM(AA68, AA76, AA84) -> 0 | ... CA88: =SUM(CA68, CA76, CA84) -> 0 | CC88: =SUM(CC68, CC76, CC84) -> 0 | CD88: =SUM(CD68, CD76, CD84) -> 0 | CE88: =SUM(CE68, CE76, CE84) -> 0 | CF88: =SUM(CF68, CF76, CF84) -> 0 | CG88: =SUM(CG68, CG76, CG84) -> 0 | CH88: =SUM(CH68, CH76, CH84) -> 0 | CI88: =CC88=L88 -> 1 | CJ88: =CD88=M88 -> 1 | CK88: =CE88=N88 -> 1 | CL88: =CF88=O88 -> 1 | CM88: =CG88=P88 -> 1
T90: 2026 | AF90: 2027 | AR90: 2028 | BD90: 2029 | BP90: 2030 | CI90: CHECK
D91: RECURRING COSTS TO ACHIEVE IMPACT | H91: Comment | I91: Baseline | J91: Goal | K91: Ann. Run Rate | L91: 2026 | M91: =L91+1 -> 2027 | N91: =M91+1 -> 2028 | O91: =N91+1 -> 2029 | P91: =O91+1 -> 2030 | Q91: Impacted BU | R91: Check | T91: 46023 | U91: =EOMONTH(T91, 1) -> 46081 | V91: =EOMONTH(U91, 1) -> 46112 | W91: =EOMONTH(V91, 1) -> 46142 | X91: =EOMONTH(W91, 1) -> 46173 | Y91: =EOMONTH(X91, 1) -> 46203 | Z91: =EOMONTH(Y91, 1) -> 46234 | AA91: =EOMONTH(Z91, 1) -> 46265 | AB91: =EOMONTH(AA91, 1) -> 46295 | ... CA91: =EOMONTH(BZ91, 1) -> 47848 | CC91: 2026 | CD91: =CC91+1 -> 2027 | CE91: =CD91+1 -> 2028 | CF91: =CE91+1 -> 2029 | CG91: =CF91+1 -> 2030 | CI91: 2026 | CJ91: =CI91+1 -> 2027 | CK91: =CJ91+1 -> 2028 | CL91: =CK91+1 -> 2029 | CM91: =CL91+1 -> 2030
E92: $USD M | I92: =$H$18 -> TTM 6/1/26 | J92: Future State | K92: Increment
E93: Revenue
I94: 0 | J94: 0 | K94: =J94-I94 -> 0 | R94: =IF(K94=P94, "", "Error") | CC94: =SUMIFS($T94:$CA94, $T$1:$CA$1, CC$63) -> 0 | CD94: =SUMIFS($T94:$CA94, $T$1:$CA$1, CD$63) -> 0 | CE94: =SUMIFS($T94:$CA94, $T$1:$CA$1, CE$63) -> 0 | CF94: =SUMIFS($T94:$CA94, $T$1:$CA$1, CF$63) -> 0 | CG94: =SUMIFS($T94:$CA94, $T$1:$CA$1, CG$63) -> 0 | CI94: =CC94=L94 -> 1 | CJ94: =CD94=M94 -> 1 | CK94: =CE94=N94 -> 1 | CL94: =CF94=O94 -> 1 | CM94: =CG94=P94 -> 1
I95: 0 | J95: 0 | K95: =J95-I95 -> 0 | R95: =IF(K95=P95, "", "Error") | CC95: =SUMIFS($T95:$CA95, $T$1:$CA$1, CC$63) -> 0 | CD95: =SUMIFS($T95:$CA95, $T$1:$CA$1, CD$63) -> 0 | CE95: =SUMIFS($T95:$CA95, $T$1:$CA$1, CE$63) -> 0 | CF95: =SUMIFS($T95:$CA95, $T$1:$CA$1, CF$63) -> 0 | CG95: =SUMIFS($T95:$CA95, $T$1:$CA$1, CG$63) -> 0 | CI95: =CC95=L95 -> 1 | CJ95: =CD95=M95 -> 1 | CK95: =CE95=N95 -> 1 | CL95: =CF95=O95 -> 1 | CM95: =CG95=P95 -> 1
E96: Revenue Subtotal | I96: =SUM(I94:I95) -> 0 | J96: =SUM(J94:J95) -> 0 | K96: =SUM(K94:K95) -> 0 | L96: =SUM(L94:L95) -> 0 | M96: =SUM(M94:M95) -> 0 | N96: =SUM(N94:N95) -> 0 | O96: =SUM(O94:O95) -> 0 | P96: =SUM(P94:P95) -> 0 | T96: =SUM(T94:T95) -> 0 | U96: =SUM(U94:U95) -> 0 | V96: =SUM(V94:V95) -> 0 | W96: =SUM(W94:W95) -> 0 | X96: =SUM(X94:X95) -> 0 | Y96: =SUM(Y94:Y95) -> 0 | Z96: =SUM(Z94:Z95) -> 0 | AA96: =SUM(AA94:AA95) -> 0 | ... CA96: =SUM(CA94:CA95) -> 0 | CC96: =SUM(CC94:CC95) -> 0 | CD96: =SUM(CD94:CD95) -> 0 | CE96: =SUM(CE94:CE95) -> 0 | CF96: =SUM(CF94:CF95) -> 0 | CG96: =SUM(CG94:CG95) -> 0 | CI96: =CC96=L96 -> 1 | CJ96: =CD96=M96 -> 1 | CK96: =CE96=N96 -> 1 | CL96: =CF96=O96 -> 1 | CM96: =CG96=P96 -> 1
E98: Cost of Sales
I99: 0 | J99: 0 | K99: =J99-I99 -> 0 | L99: 0 | M99: 0 | N99: 0 | O99: 0 | P99: 0 | R99: =IF(K99=P99, "", "Error") | CC99: =SUMIFS($T99:$CA99, $T$1:$CA$1, CC$63) -> 0 | CD99: =SUMIFS($T99:$CA99, $T$1:$CA$1, CD$63) -> 0 | CE99: =SUMIFS($T99:$CA99, $T$1:$CA$1, CE$63) -> 0 | CF99: =SUMIFS($T99:$CA99, $T$1:$CA$1, CF$63) -> 0 | CG99: =SUMIFS($T99:$CA99, $T$1:$CA$1, CG$63) -> 0 | CI99: =CC99=L99 -> 1 | CJ99: =CD99=M99 -> 1 | CK99: =CE99=N99 -> 1 | CL99: =CF99=O99 -> 1 | CM99: =CG99=P99 -> 1
I100: 0 | J100: 0 | K100: =J100-I100 -> 0 | L100: 0 | M100: 0 | N100: 0 | O100: 0 | P100: 0 | R100: =IF(K100=P100, "", "Error") | CC100: =SUMIFS($T100:$CA100, $T$1:$CA$1, CC$63) -> 0 | CD100: =SUMIFS($T100:$CA100, $T$1:$CA$1, CD$63) -> 0 | CE100: =SUMIFS($T100:$CA100, $T$1:$CA$1, CE$63) -> 0 | CF100: =SUMIFS($T100:$CA100, $T$1:$CA$1, CF$63) -> 0 | CG100: =SUMIFS($T100:$CA100, $T$1:$CA$1, CG$63) -> 0 | CI100: =CC100=L100 -> 1 | CJ100: =CD100=M100 -> 1 | CK100: =CE100=N100 -> 1 | CL100: =CF100=O100 -> 1 | CM100: =CG100=P100 -> 1
I101: 0 | J101: 0 | K101: =J101-I101 -> 0 | L101: 0 | M101: 0 | N101: 0 | O101: 0 | P101: 0 | R101: =IF(K101=P101, "", "Error") | CC101: =SUMIFS($T101:$CA101, $T$1:$CA$1, CC$63) -> 0 | CD101: =SUMIFS($T101:$CA101, $T$1:$CA$1, CD$63) -> 0 | CE101: =SUMIFS($T101:$CA101, $T$1:$CA$1, CE$63) -> 0 | CF101: =SUMIFS($T101:$CA101, $T$1:$CA$1, CF$63) -> 0 | CG101: =SUMIFS($T101:$CA101, $T$1:$CA$1, CG$63) -> 0 | CI101: =CC101=L101 -> 1 | CJ101: =CD101=M101 -> 1 | CK101: =CE101=N101 -> 1 | CL101: =CF101=O101 -> 1 | CM101: =CG101=P101 -> 1
I102: 0 | J102: 0 | K102: =J102-I102 -> 0 | L102: 0 | M102: 0 | N102: 0 | O102: 0 | P102: 0 | R102: =IF(K102=P102, "", "Error") | CC102: =SUMIFS($T102:$CA102, $T$1:$CA$1, CC$63) -> 0 | CD102: =SUMIFS($T102:$CA102, $T$1:$CA$1, CD$63) -> 0 | CE102: =SUMIFS($T102:$CA102, $T$1:$CA$1, CE$63) -> 0 | CF102: =SUMIFS($T102:$CA102, $T$1:$CA$1, CF$63) -> 0 | CG102: =SUMIFS($T102:$CA102, $T$1:$CA$1, CG$63) -> 0 | CI102: =CC102=L102 -> 1 | CJ102: =CD102=M102 -> 1 | CK102: =CE102=N102 -> 1 | CL102: =CF102=O102 -> 1 | CM102: =CG102=P102 -> 1
K103: =J103-I103 -> 0 | L103: 0 | M103: 0 | N103: 0 | O103: 0 | P103: 0
E104: Cost of Sales Subtotal | I104: =SUM(I99:I103) -> 0 | J104: =SUM(J99:J103) -> 0 | K104: =SUM(K99:K103) -> 0 | L104: =SUM(L99:L103) -> 0 | M104: =SUM(M99:M103) -> 0 | N104: =SUM(N99:N103) -> 0 | O104: =SUM(O99:O103) -> 0 | P104: =SUM(P99:P103) -> 0 | T104: =SUM(T99:T103) -> 0 | U104: =SUM(U99:U103) -> 0 | V104: =SUM(V99:V103) -> 0 | W104: =SUM(W99:W103) -> 0 | X104: =SUM(X99:X103) -> 0 | Y104: =SUM(Y99:Y103) -> 0 | Z104: =SUM(Z99:Z103) -> 0 | AA104: =SUM(AA99:AA103) -> 0 | ... CA104: =SUM(CA99:CA103) -> 0 | CC104: =SUM(CC99:CC103) -> 0 | CD104: =SUM(CD99:CD103) -> 0 | CE104: =SUM(CE99:CE103) -> 0 | CF104: =SUM(CF99:CF103) -> 0 | CG104: =SUM(CG99:CG103) -> 0 | CI104: =CC104=L104 -> 1 | CJ104: =CD104=M104 -> 1 | CK104: =CE104=N104 -> 1 | CL104: =CF104=O104 -> 1 | CM104: =CG104=P104 -> 1
E106: OPEX
E107: OPEX - Token cost for SDR agents | H107: PENDING — placeholder, not data. SDR agent token consumption — scales with ramp | I107: 0 | J107: =I107+'SALES-2 Model'!$K$113 -> 0 | K107: ='SALES-2 Model'!$K$113 -> 0 | L107: ='SALES-2 Model'!L113 -> 0 | M107: ='SALES-2 Model'!M113 -> 0 | N107: ='SALES-2 Model'!N113 -> 0 | O107: ='SALES-2 Model'!O113 -> 0 | P107: ='SALES-2 Model'!P113 -> 0 | Q107: Global Sales | R107: =IF(K107=P107, "", "Error") | T107: ='SALES-2 Model'!T113 -> 0 | U107: ='SALES-2 Model'!U113 -> 0 | V107: ='SALES-2 Model'!V113 -> 0 | W107: ='SALES-2 Model'!W113 -> 0 | X107: ='SALES-2 Model'!X113 -> 0 | Y107: ='SALES-2 Model'!Y113 -> 0 | Z107: ='SALES-2 Model'!Z113 -> 0 | AA107: ='SALES-2 Model'!AA113 -> 0 | ... CA107: ='SALES-2 Model'!CA113 -> 0 | CC107: =SUMIFS($T107:$CA107, $T$1:$CA$1, CC$63) -> 0 | CD107: =SUMIFS($T107:$CA107, $T$1:$CA$1, CD$63) -> 0 | CE107: =SUMIFS($T107:$CA107, $T$1:$CA$1, CE$63) -> 0 | CF107: =SUMIFS($T107:$CA107, $T$1:$CA$1, CF$63) -> 0 | CG107: =SUMIFS($T107:$CA107, $T$1:$CA$1, CG$63) -> 0 | CI107: =CC107=L107 -> 1 | CJ107: =CD107=M107 -> 1 | CK107: =CE107=N107 -> 1 | CL107: =CF107=O107 -> 1 | CM107: =CG107=P107 -> 1
E108: OPEX - PRM / orchestration platform run | H108: PENDING — placeholder, not data. Recurring platform opex | I108: 0 | J108: =I108+'SALES-2 Model'!$K$114 -> 0 | K108: ='SALES-2 Model'!$K$114 -> 0 | L108: ='SALES-2 Model'!L114 -> 0 | M108: ='SALES-2 Model'!M114 -> 0 | N108: ='SALES-2 Model'!N114 -> 0 | O108: ='SALES-2 Model'!O114 -> 0 | P108: ='SALES-2 Model'!P114 -> 0 | Q108: Global Sales | R108: =IF(K108=P108, "", "Error") | T108: ='SALES-2 Model'!T114 -> 0 | U108: ='SALES-2 Model'!U114 -> 0 | V108: ='SALES-2 Model'!V114 -> 0 | W108: ='SALES-2 Model'!W114 -> 0 | X108: ='SALES-2 Model'!X114 -> 0 | Y108: ='SALES-2 Model'!Y114 -> 0 | Z108: ='SALES-2 Model'!Z114 -> 0 | AA108: ='SALES-2 Model'!AA114 -> 0 | ... CA108: ='SALES-2 Model'!CA114 -> 0 | CC108: =SUMIFS($T108:$CA108, $T$1:$CA$1, CC$63) -> 0 | CD108: =SUMIFS($T108:$CA108, $T$1:$CA$1, CD$63) -> 0 | CE108: =SUMIFS($T108:$CA108, $T$1:$CA$1, CE$63) -> 0 | CF108: =SUMIFS($T108:$CA108, $T$1:$CA$1, CF$63) -> 0 | CG108: =SUMIFS($T108:$CA108, $T$1:$CA$1, CG$63) -> 0 | CI108: =CC108=L108 -> 1 | CJ108: =CD108=M108 -> 1 | CK108: =CE108=N108 -> 1 | CL108: =CF108=O108 -> 1 | CM108: =CG108=P108 -> 1
E109: OPEX - Support & maintenance | H109: PENDING — placeholder, not data. Ongoing support/maintenance | I109: 0 | J109: =I109+'SALES-2 Model'!$K$115 -> 0 | K109: ='SALES-2 Model'!$K$115 -> 0 | L109: ='SALES-2 Model'!L115 -> 0 | M109: ='SALES-2 Model'!M115 -> 0 | N109: ='SALES-2 Model'!N115 -> 0 | O109: ='SALES-2 Model'!O115 -> 0 | P109: ='SALES-2 Model'!P115 -> 0 | Q109: Global Sales | R109: =IF(K109=P109, "", "Error") | T109: ='SALES-2 Model'!T115 -> 0 | U109: ='SALES-2 Model'!U115 -> 0 | V109: ='SALES-2 Model'!V115 -> 0 | W109: ='SALES-2 Model'!W115 -> 0 | X109: ='SALES-2 Model'!X115 -> 0 | Y109: ='SALES-2 Model'!Y115 -> 0 | Z109: ='SALES-2 Model'!Z115 -> 0 | AA109: ='SALES-2 Model'!AA115 -> 0 | ... CA109: ='SALES-2 Model'!CA115 -> 0 | CC109: =SUMIFS($T109:$CA109, $T$1:$CA$1, CC$63) -> 0 | CD109: =SUMIFS($T109:$CA109, $T$1:$CA$1, CD$63) -> 0 | CE109: =SUMIFS($T109:$CA109, $T$1:$CA$1, CE$63) -> 0 | CF109: =SUMIFS($T109:$CA109, $T$1:$CA$1, CF$63) -> 0 | CG109: =SUMIFS($T109:$CA109, $T$1:$CA$1, CG$63) -> 0 | CI109: =CC109=L109 -> 1 | CJ109: =CD109=M109 -> 1 | CK109: =CE109=N109 -> 1 | CL109: =CF109=O109 -> 1 | CM109: =CG109=P109 -> 1
I110: 0 | J110: 0 | K110: =J110-I110 -> 0 | L110: 0 | M110: 0 | N110: 0 | O110: 0 | P110: 0 | R110: =IF(K110=P110, "", "Error") | CC110: =SUMIFS($T110:$CA110, $T$1:$CA$1, CC$63) -> 0 | CD110: =SUMIFS($T110:$CA110, $T$1:$CA$1, CD$63) -> 0 | CE110: =SUMIFS($T110:$CA110, $T$1:$CA$1, CE$63) -> 0 | CF110: =SUMIFS($T110:$CA110, $T$1:$CA$1, CF$63) -> 0 | CG110: =SUMIFS($T110:$CA110, $T$1:$CA$1, CG$63) -> 0 | CI110: =CC110=L110 -> 1 | CJ110: =CD110=M110 -> 1 | CK110: =CE110=N110 -> 1 | CL110: =CF110=O110 -> 1 | CM110: =CG110=P110 -> 1
I111: 0 | J111: 0 | K111: =J111-I111 -> 0 | L111: 0 | M111: 0 | N111: 0 | O111: 0 | P111: 0 | R111: =IF(K111=P111, "", "Error") | CC111: =SUMIFS($T111:$CA111, $T$1:$CA$1, CC$63) -> 0 | CD111: =SUMIFS($T111:$CA111, $T$1:$CA$1, CD$63) -> 0 | CE111: =SUMIFS($T111:$CA111, $T$1:$CA$1, CE$63) -> 0 | CF111: =SUMIFS($T111:$CA111, $T$1:$CA$1, CF$63) -> 0 | CG111: =SUMIFS($T111:$CA111, $T$1:$CA$1, CG$63) -> 0 | CI111: =CC111=L111 -> 1 | CJ111: =CD111=M111 -> 1 | CK111: =CE111=N111 -> 1 | CL111: =CF111=O111 -> 1 | CM111: =CG111=P111 -> 1
E112: OpEx subtotal | I112: =SUM(I107:I111) -> 0 | J112: =SUM(J107:J111) -> 0 | K112: =SUM(K107:K111) -> 0 | L112: =SUM(L107:L111) -> 0 | M112: =SUM(M107:M111) -> 0 | N112: =SUM(N107:N111) -> 0 | O112: =SUM(O107:O111) -> 0 | P112: =SUM(P107:P111) -> 0 | T112: =SUM(T107:T111) -> 0 | U112: =SUM(U107:U111) -> 0 | V112: =SUM(V107:V111) -> 0 | W112: =SUM(W107:W111) -> 0 | X112: =SUM(X107:X111) -> 0 | Y112: =SUM(Y107:Y111) -> 0 | Z112: =SUM(Z107:Z111) -> 0 | AA112: =SUM(AA107:AA111) -> 0 | ... CA112: =SUM(CA107:CA111) -> 0 | CC112: =SUM(CC107:CC111) -> 0 | CD112: =SUM(CD107:CD111) -> 0 | CE112: =SUM(CE107:CE111) -> 0 | CF112: =SUM(CF107:CF111) -> 0 | CG112: =SUM(CG107:CG111) -> 0 | CI112: =CC112=L112 -> 1 | CJ112: =CD112=M112 -> 1 | CK112: =CE112=N112 -> 1 | CL112: =CF112=O112 -> 1 | CM112: =CG112=P112 -> 1
E115: Recurring Costs Total | I115: =SUM(-I96, I104, I112) -> 0 | J115: =SUM(-J96, J104, J112) -> 0 | K115: =SUM(-K96, K104, K112) -> 0 | L115: =SUM(-L96, L104, L112) -> 0 | M115: =SUM(-M96, M104, M112) -> 0 | N115: =SUM(-N96, N104, N112) -> 0 | O115: =SUM(-O96, O104, O112) -> 0 | P115: =SUM(-P96, P104, P112) -> 0 | T115: =SUM(-T96, T104, T112) -> 0 | U115: =SUM(-U96, U104, U112) -> 0 | V115: =SUM(-V96, V104, V112) -> 0 | W115: =SUM(-W96, W104, W112) -> 0 | X115: =SUM(-X96, X104, X112) -> 0 | Y115: =SUM(-Y96, Y104, Y112) -> 0 | Z115: =SUM(-Z96, Z104, Z112) -> 0 | AA115: =SUM(-AA96, AA104, AA112) -> 0 | ... CA115: =SUM(-CA96, CA104, CA112) -> 0 | CC115: =SUM(-CC96, CC104, CC112) -> 0 | CD115: =SUM(-CD96, CD104, CD112) -> 0 | CE115: =SUM(-CE96, CE104, CE112) -> 0 | CF115: =SUM(-CF96, CF104, CF112) -> 0 | CG115: =SUM(-CG96, CG104, CG112) -> 0 | CI115: =CC115=L115 -> 1 | CJ115: =CD115=M115 -> 1 | CK115: =CE115=N115 -> 1 | CL115: =CF115=O115 -> 1 | CM115: =CG115=P115 -> 1
E117: Net Recurring Benefit | I117: =SUM(I88, -I115) -> 0 | J117: =SUM(J88, -J115) -> 0 | K117: =SUM(K88, -K115) -> 0 | L117: =SUM(L88, -L115) -> 0 | M117: =SUM(M88, -M115) -> 0 | N117: =SUM(N88, -N115) -> 0 | O117: =SUM(O88, -O115) -> 0 | P117: =SUM(P88, -P115) -> 0 | R117: =IF(K117=P117, "", "Error") | T117: =SUM(T88, -T115) -> 0 | U117: =SUM(U88, -U115) -> 0 | V117: =SUM(V88, -V115) -> 0 | W117: =SUM(W88, -W115) -> 0 | X117: =SUM(X88, -X115) -> 0 | Y117: =SUM(Y88, -Y115) -> 0 | Z117: =SUM(Z88, -Z115) -> 0 | AA117: =SUM(AA88, -AA115) -> 0 | ... CA117: =SUM(CA88, -CA115) -> 0 | CC117: =SUM(CC88, -CC115) -> 0 | CD117: =SUM(CD88, -CD115) -> 0 | CE117: =SUM(CE88, -CE115) -> 0 | CF117: =SUM(CF88, -CF115) -> 0 | CG117: =SUM(CG88, -CG115) -> 0 | CI117: =CC117=L117 -> 1 | CJ117: =CD117=M117 -> 1 | CK117: =CE117=N117 -> 1 | CL117: =CF117=O117 -> 1 | CM117: =CG117=P117 -> 1
C120: SECTION III - ONE-TIME IMPLEMENTATION | CC120: ANNUAL SUMMARY | CI120: CHECK CELLS
T122: 2026 | AF122: 2027 | AR122: 2028 | BD122: 2029 | BP122: 2030
D123: ONE-TIME BENEFITS | K123: Comment | L123: 2026 | M123: =L123+1 -> 2027 | N123: =M123+1 -> 2028 | O123: =N123+1 -> 2029 | P123: =O123+1 -> 2030 | Q123: Impacted BU | T123: 46023 | U123: =EOMONTH(T123, 1) -> 46081 | V123: =EOMONTH(U123, 1) -> 46112 | W123: =EOMONTH(V123, 1) -> 46142 | X123: =EOMONTH(W123, 1) -> 46173 | Y123: =EOMONTH(X123, 1) -> 46203 | Z123: =EOMONTH(Y123, 1) -> 46234 | AA123: =EOMONTH(Z123, 1) -> 46265 | AB123: =EOMONTH(AA123, 1) -> 46295 | ... CA123: =EOMONTH(BZ123, 1) -> 47848 | CC123: 2026 | CD123: =CC123+1 -> 2027 | CE123: =CD123+1 -> 2028 | CF123: =CE123+1 -> 2029 | CG123: =CF123+1 -> 2030 | CI123: 2026 | CJ123: =CI123+1 -> 2027 | CK123: =CJ123+1 -> 2028 | CL123: =CK123+1 -> 2029 | CM123: =CL123+1 -> 2030
E125: Working Capital
CC126: =SUMIFS($T126:$CA126, $T$1:$CA$1, CC$63) -> 0 | CD126: =SUMIFS($T126:$CA126, $T$1:$CA$1, CD$63) -> 0 | CE126: =SUMIFS($T126:$CA126, $T$1:$CA$1, CE$63) -> 0 | CF126: =SUMIFS($T126:$CA126, $T$1:$CA$1, CF$63) -> 0 | CG126: =SUMIFS($T126:$CA126, $T$1:$CA$1, CG$63) -> 0 | CI126: =CC126=L126 -> 1 | CJ126: =CD126=M126 -> 1 | CK126: =CE126=N126 -> 1 | CL126: =CF126=O126 -> 1 | CM126: =CG126=P126 -> 1
CC127: =SUMIFS($T127:$CA127, $T$1:$CA$1, CC$63) -> 0 | CD127: =SUMIFS($T127:$CA127, $T$1:$CA$1, CD$63) -> 0 | CE127: =SUMIFS($T127:$CA127, $T$1:$CA$1, CE$63) -> 0 | CF127: =SUMIFS($T127:$CA127, $T$1:$CA$1, CF$63) -> 0 | CG127: =SUMIFS($T127:$CA127, $T$1:$CA$1, CG$63) -> 0 | CI127: =CC127=L127 -> 1 | CJ127: =CD127=M127 -> 1 | CK127: =CE127=N127 -> 1 | CL127: =CF127=O127 -> 1 | CM127: =CG127=P127 -> 1
E128: Working Capital Subtotal | L128: =SUM(L126:L127) -> 0 | M128: =SUM(M126:M127) -> 0 | N128: =SUM(N126:N127) -> 0 | O128: =SUM(O126:O127) -> 0 | P128: =SUM(P126:P127) -> 0 | T128: =SUM(T126:T127) -> 0 | U128: =SUM(U126:U127) -> 0 | V128: =SUM(V126:V127) -> 0 | W128: =SUM(W126:W127) -> 0 | X128: =SUM(X126:X127) -> 0 | Y128: =SUM(Y126:Y127) -> 0 | Z128: =SUM(Z126:Z127) -> 0 | AA128: =SUM(AA126:AA127) -> 0 | ... CA128: =SUM(CA126:CA127) -> 0 | CC128: =SUM(CC126:CC127) -> 0 | CD128: =SUM(CD126:CD127) -> 0 | CE128: =SUM(CE126:CE127) -> 0 | CF128: =SUM(CF126:CF127) -> 0 | CG128: =SUM(CG126:CG127) -> 0 | CI128: =CC128=L128 -> 1 | CJ128: =CD128=M128 -> 1 | CK128: =CE128=N128 -> 1 | CL128: =CF128=O128 -> 1 | CM128: =CG128=P128 -> 1
E130: One-Time Benefits Total | L130: =L128 -> 0 | M130: =M128 -> 0 | N130: =N128 -> 0 | O130: =O128 -> 0 | P130: =P128 -> 0 | T130: =T128 -> 0 | U130: =U128 -> 0 | V130: =V128 -> 0 | W130: =W128 -> 0 | X130: =X128 -> 0 | Y130: =Y128 -> 0 | Z130: =Z128 -> 0 | AA130: =AA128 -> 0 | ... CA130: =CA128 -> 0 | CC130: =CC128 -> 0 | CD130: =CD128 -> 0 | CE130: =CE128 -> 0 | CF130: =CF128 -> 0 | CG130: =CG128 -> 0 | CI130: =CI128 -> 1 | CJ130: =CJ128 -> 1 | CK130: =CK128 -> 1 | CL130: =CL128 -> 1 | CM130: =CM128 -> 1
T132: 2026 | AF132: 2027 | AR132: 2028 | BD132: 2029 | BP132: 2030
D133: CAPEX AND ONE-TIME COSTS | K133: Comment | L133: 2026 | M133: =L133+1 -> 2027 | N133: =M133+1 -> 2028 | O133: =N133+1 -> 2029 | P133: =O133+1 -> 2030 | T133: 46023 | U133: =EOMONTH(T133, 1) -> 46081 | V133: =EOMONTH(U133, 1) -> 46112 | W133: =EOMONTH(V133, 1) -> 46142 | X133: =EOMONTH(W133, 1) -> 46173 | Y133: =EOMONTH(X133, 1) -> 46203 | Z133: =EOMONTH(Y133, 1) -> 46234 | AA133: =EOMONTH(Z133, 1) -> 46265 | AB133: =EOMONTH(AA133, 1) -> 46295 | ... CA133: =EOMONTH(BZ133, 1) -> 47848 | CC133: 2026 | CD133: =CC133+1 -> 2027 | CE133: =CD133+1 -> 2028 | CF133: =CE133+1 -> 2029 | CG133: =CF133+1 -> 2030 | CI133: 2026 | CJ133: =CI133+1 -> 2027 | CK133: =CJ133+1 -> 2028 | CL133: =CK133+1 -> 2029 | CM133: =CL133+1 -> 2030
E135: Capital Expenditures
E136: CAPEX — capitalized build labor | L136: ='SALES-2 Model'!L99 -> 0.10530667 | M136: ='SALES-2 Model'!M99 -> 0.42122667 | N136: ='SALES-2 Model'!N99 -> 0 | O136: ='SALES-2 Model'!O99 -> 0 | P136: ='SALES-2 Model'!P99 -> 0 | Q136: Global Sales | T136: ='SALES-2 Model'!T99 -> 0 | U136: ='SALES-2 Model'!U99 -> 0 | V136: ='SALES-2 Model'!V99 -> 0 | W136: ='SALES-2 Model'!W99 -> 0 | X136: ='SALES-2 Model'!X99 -> 0 | Y136: ='SALES-2 Model'!Y99 -> 0 | Z136: ='SALES-2 Model'!Z99 -> 0 | AA136: ='SALES-2 Model'!AA99 -> 0 | ... CA136: ='SALES-2 Model'!CA99 -> 0 | CC136: =SUMIFS($T136:$CA136, $T$1:$CA$1, CC$63) -> 0.10530667 | CD136: =SUMIFS($T136:$CA136, $T$1:$CA$1, CD$63) -> 0.42122667 | CE136: =SUMIFS($T136:$CA136, $T$1:$CA$1, CE$63) -> 0 | CF136: =SUMIFS($T136:$CA136, $T$1:$CA$1, CF$63) -> 0 | CG136: =SUMIFS($T136:$CA136, $T$1:$CA$1, CG$63) -> 0 | CI136: =CC136=L136 -> 1 | CJ136: =CD136=M136 -> 1 | CK136: =CE136=N136 -> 1 | CL136: =CF136=O136 -> 1 | CM136: =CG136=P136 -> 1
E137: CAPEX — capitalized non-labor | L137: ='SALES-2 Model'!L100 -> 0 | M137: ='SALES-2 Model'!M100 -> 0 | N137: ='SALES-2 Model'!N100 -> 0 | O137: ='SALES-2 Model'!O100 -> 0 | P137: ='SALES-2 Model'!P100 -> 0 | Q137: Global Sales | T137: ='SALES-2 Model'!T100 -> 0 | U137: ='SALES-2 Model'!U100 -> 0 | V137: ='SALES-2 Model'!V100 -> 0 | W137: ='SALES-2 Model'!W100 -> 0 | X137: ='SALES-2 Model'!X100 -> 0 | Y137: ='SALES-2 Model'!Y100 -> 0 | Z137: ='SALES-2 Model'!Z100 -> 0 | AA137: ='SALES-2 Model'!AA100 -> 0 | ... CA137: ='SALES-2 Model'!CA100 -> 0 | CC137: =SUMIFS($T137:$CA137, $T$1:$CA$1, CC$63) -> 0 | CD137: =SUMIFS($T137:$CA137, $T$1:$CA$1, CD$63) -> 0 | CE137: =SUMIFS($T137:$CA137, $T$1:$CA$1, CE$63) -> 0 | CF137: =SUMIFS($T137:$CA137, $T$1:$CA$1, CF$63) -> 0 | CG137: =SUMIFS($T137:$CA137, $T$1:$CA$1, CG$63) -> 0 | CI137: =CC137=L137 -> 1 | CJ137: =CD137=M137 -> 1 | CK137: =CE137=N137 -> 1 | CL137: =CF137=O137 -> 1 | CM137: =CG137=P137 -> 1
E138: Capital Expenditures Subtotal | L138: =SUM(L136:L137) -> 0.10530667 | M138: =SUM(M136:M137) -> 0.42122667 | N138: =SUM(N136:N137) -> 0 | O138: =SUM(O136:O137) -> 0 | P138: =SUM(P136:P137) -> 0 | T138: =SUM(T136:T137) -> 0 | U138: =SUM(U136:U137) -> 0 | V138: =SUM(V136:V137) -> 0 | W138: =SUM(W136:W137) -> 0 | X138: =SUM(X136:X137) -> 0 | Y138: =SUM(Y136:Y137) -> 0 | Z138: =SUM(Z136:Z137) -> 0 | AA138: =SUM(AA136:AA137) -> 0 | ... CA138: =SUM(CA136:CA137) -> 0 | CC138: =SUM(CC136:CC137) -> 0.10530667 | CD138: =SUM(CD136:CD137) -> 0.42122667 | CE138: =SUM(CE136:CE137) -> 0 | CF138: =SUM(CF136:CF137) -> 0 | CG138: =SUM(CG136:CG137) -> 0 | CI138: =CC138=L138 -> 1 | CJ138: =CD138=M138 -> 1 | CK138: =CE138=N138 -> 1 | CL138: =CF138=O138 -> 1 | CM138: =CG138=P138 -> 1
E140: OTC
E141: OTC — build labor (expensed) | L141: ='SALES-2 Model'!L101 -> 0.15796 | M141: ='SALES-2 Model'!M101 -> 0.59893167 | N141: ='SALES-2 Model'!N101 -> 0 | O141: ='SALES-2 Model'!O101 -> 0 | P141: ='SALES-2 Model'!P101 -> 0 | Q141: Global Sales | T141: ='SALES-2 Model'!T101 -> 0 | U141: ='SALES-2 Model'!U101 -> 0 | V141: ='SALES-2 Model'!V101 -> 0 | W141: ='SALES-2 Model'!W101 -> 0 | X141: ='SALES-2 Model'!X101 -> 0 | Y141: ='SALES-2 Model'!Y101 -> 0 | Z141: ='SALES-2 Model'!Z101 -> 0 | AA141: ='SALES-2 Model'!AA101 -> 0 | ... CA141: ='SALES-2 Model'!CA101 -> 0 | CC141: =SUMIFS($T141:$CA141, $T$1:$CA$1, CC$63) -> 0.15796 | CD141: =SUMIFS($T141:$CA141, $T$1:$CA$1, CD$63) -> 0.59893167 | CE141: =SUMIFS($T141:$CA141, $T$1:$CA$1, CE$63) -> 0 | CF141: =SUMIFS($T141:$CA141, $T$1:$CA$1, CF$63) -> 0 | CG141: =SUMIFS($T141:$CA141, $T$1:$CA$1, CG$63) -> 0 | CI141: =CC141=L141 -> 1 | CJ141: =CD141=M141 -> 1 | CK141: =CE141=N141 -> 1 | CL141: =CF141=O141 -> 1 | CM141: =CG141=P141 -> 1
E142: OTC — non-labor (expensed) | L142: ='SALES-2 Model'!L102 -> 0.080427967 | M142: ='SALES-2 Model'!M102 -> 0.16085593 | N142: ='SALES-2 Model'!N102 -> 0 | O142: ='SALES-2 Model'!O102 -> 0 | P142: ='SALES-2 Model'!P102 -> 0 | Q142: Global Sales | T142: ='SALES-2 Model'!T102 -> 0 | U142: ='SALES-2 Model'!U102 -> 0 | V142: ='SALES-2 Model'!V102 -> 0 | W142: ='SALES-2 Model'!W102 -> 0 | X142: ='SALES-2 Model'!X102 -> 0 | Y142: ='SALES-2 Model'!Y102 -> 0 | Z142: ='SALES-2 Model'!Z102 -> 0 | AA142: ='SALES-2 Model'!AA102 -> 0 | ... CA142: ='SALES-2 Model'!CA102 -> 0 | CC142: =SUMIFS($T142:$CA142, $T$1:$CA$1, CC$63) -> 0.080427967 | CD142: =SUMIFS($T142:$CA142, $T$1:$CA$1, CD$63) -> 0.16085593 | CE142: =SUMIFS($T142:$CA142, $T$1:$CA$1, CE$63) -> 0 | CF142: =SUMIFS($T142:$CA142, $T$1:$CA$1, CF$63) -> 0 | CG142: =SUMIFS($T142:$CA142, $T$1:$CA$1, CG$63) -> 0 | CI142: =CC142=L142 -> 1 | CJ142: =CD142=M142 -> 1 | CK142: =CE142=N142 -> 1 | CL142: =CF142=O142 -> 1 | CM142: =CG142=P142 -> 1
CC143: =SUMIFS($T143:$CA143, $T$1:$CA$1, CC$63) -> 0 | CD143: =SUMIFS($T143:$CA143, $T$1:$CA$1, CD$63) -> 0 | CE143: =SUMIFS($T143:$CA143, $T$1:$CA$1, CE$63) -> 0 | CF143: =SUMIFS($T143:$CA143, $T$1:$CA$1, CF$63) -> 0 | CG143: =SUMIFS($T143:$CA143, $T$1:$CA$1, CG$63) -> 0 | CI143: =CC143=L143 -> 1 | CJ143: =CD143=M143 -> 1 | CK143: =CE143=N143 -> 1 | CL143: =CF143=O143 -> 1 | CM143: =CG143=P143 -> 1
E144: OTC Subtotal | L144: =SUM(L141:L143) -> 0.23838797 | M144: =SUM(M141:M143) -> 0.7597876 | N144: =SUM(N141:N143) -> 0 | O144: =SUM(O141:O143) -> 0 | P144: =SUM(P141:P143) -> 0 | T144: =SUM(T141:T143) -> 0 | U144: =SUM(U141:U143) -> 0 | V144: =SUM(V141:V143) -> 0 | W144: =SUM(W141:W143) -> 0 | X144: =SUM(X141:X143) -> 0 | Y144: =SUM(Y141:Y143) -> 0 | Z144: =SUM(Z141:Z143) -> 0 | AA144: =SUM(AA141:AA143) -> 0 | ... CA144: =SUM(CA141:CA143) -> 0 | CC144: =SUM(CC141:CC143) -> 0.23838797 | CD144: =SUM(CD141:CD143) -> 0.7597876 | CE144: =SUM(CE141:CE143) -> 0 | CF144: =SUM(CF141:CF143) -> 0 | CG144: =SUM(CG141:CG143) -> 0 | CI144: =CC144=L144 -> 1 | CJ144: =CD144=M144 -> 1 | CK144: =CE144=N144 -> 1 | CL144: =CF144=O144 -> 1 | CM144: =CG144=P144 -> 1
E147: One-Time Costs Total | L147: =SUM(L138, L144) -> 0.34369463 | M147: =SUM(M138, M144) -> 1.1810143 | N147: =SUM(N138, N144) -> 0 | O147: =SUM(O138, O144) -> 0 | P147: =SUM(P138, P144) -> 0 | T147: =SUM(T138, T144) -> 0 | U147: =SUM(U138, U144) -> 0 | V147: =SUM(V138, V144) -> 0 | W147: =SUM(W138, W144) -> 0 | X147: =SUM(X138, X144) -> 0 | Y147: =SUM(Y138, Y144) -> 0 | Z147: =SUM(Z138, Z144) -> 0 | AA147: =SUM(AA138, AA144) -> 0 | ... CA147: =SUM(CA138, CA144) -> 0 | CC147: =SUM(CC138, CC144) -> 0.34369463 | CD147: =SUM(CD138, CD144) -> 1.1810143 | CE147: =SUM(CE138, CE144) -> 0 | CF147: =SUM(CF138, CF144) -> 0 | CG147: =SUM(CG138, CG144) -> 0 | CI147: =CC147=L147 -> 1 | CJ147: =CD147=M147 -> 1 | CK147: =CE147=N147 -> 1 | CL147: =CF147=O147 -> 1 | CM147: =CG147=P147 -> 1
E149: Total One-Time Implementation Cost | L149: =SUM(L130, -L147) -> -0.34369463 | M149: =SUM(M130, -M147) -> -1.1810143 | N149: =SUM(N130, -N147) -> 0 | O149: =SUM(O130, -O147) -> 0 | P149: =SUM(P130, -P147) -> 0 | T149: =SUM(T130, -T147) -> 0 | U149: =SUM(U130, -U147) -> 0 | V149: =SUM(V130, -V147) -> 0 | W149: =SUM(W130, -W147) -> 0 | X149: =SUM(X130, -X147) -> 0 | Y149: =SUM(Y130, -Y147) -> 0 | Z149: =SUM(Z130, -Z147) -> 0 | AA149: =SUM(AA130, -AA147) -> 0 | ... CA149: =SUM(CA130, -CA147) -> 0 | CC149: =SUM(CC130, -CC147) -> -0.34369463 | CD149: =SUM(CD130, -CD147) -> -1.1810143 | CE149: =SUM(CE130, -CE147) -> 0 | CF149: =SUM(CF130, -CF147) -> 0 | CG149: =SUM(CG130, -CG147) -> 0 | CI149: =CC149=L149 -> 1 | CJ149: =CD149=M149 -> 1 | CK149: =CE149=N149 -> 1 | CL149: =CF149=O149 -> 1 | CM149: =CG149=P149 -> 1
C152: SECTION IV - FINANCIAL METRICS | CC152: ANNUAL SUMMARY | CI152: CHECK CELLS
E155: Cash Flow | L155: 2026 | M155: =L155+1 -> 2027 | N155: =M155+1 -> 2028 | O155: =N155+1 -> 2029 | P155: =O155+1 -> 2030 | Q155: Total
E156: Operating Income | L156: =L117 -> 0 | M156: =M117 -> 0 | N156: =N117 -> 0 | O156: =O117 -> 0 | P156: =P117 -> 0 | Q156: =SUM(L156:P156) -> 0
E157: (+) One-Time Benefits | L157: =L130 -> 0 | M157: =M130 -> 0 | N157: =N130 -> 0 | O157: =O130 -> 0 | P157: =P130 -> 0 | Q157: =SUM(L157:P157) -> 0
E158: (-) One-Time Cash Costs | L158: =-L147 -> -0.34369463 | M158: =-M147 -> -1.1810143 | N158: =-N147 -> 0 | O158: =-O147 -> 0 | P158: =-P147 -> 0 | Q158: =SUM(L158:P158) -> -1.5247089
E159: Cash Flow | L159: =SUM(L156:L158) -> -0.34369463 | M159: =SUM(M156:M158) -> -1.1810143 | N159: =SUM(N156:N158) -> 0 | O159: =SUM(O156:O158) -> 0 | P159: =SUM(P156:P158) -> 0 | Q159: =SUM(L159:P159) -> -1.5247089
E160: Cumulative Cash Flow | L160: =L159 -> -0.34369463 | M160: =L160+M159 -> -1.5247089 | N160: =M160+N159 -> -1.5247089 | O160: =N160+O159 -> -1.5247089 | P160: =O160+P159 -> -1.5247089 | Q160: =P160 -> -1.5247089
E161: Payback timeline | L161: =IF(L160<0,1,0) -> 1 | M161: =IF(M160<0,1,IF(AND(L160<0,M159>0),-L160/M159,0)) -> 1 | N161: =IF(N160<0,1,IF(AND(M160<0,N159>0),-M160/N159,0)) -> 1 | O161: =IF(O160<0,1,IF(AND(N160<0,O159>0),-N160/O159,0)) -> 1 | P161: =IF(P160<0,1,IF(AND(O160<0,P159>0),-O160/P159,0)) -> 1
E163: Return on Investment | F163: NRB/OTC | G163: =IFERROR(K117/-SUM(L149:P149),"n/a") -> 0
E164: Internal Rate of Return | F164: 5-yr IRR | G164: =IFERROR(IRR($L$159:$P$159, 0.2),"n/a") -> n/a
E165: Breakeven timeline | F165: # yrs | G165: =IF(SUM(L161:P161)=5,">5",SUM(L161:P161)) -> >5
E167: WACC | G167: 0.095
E168: NPV | F168: $ | G168: =SUM(L168:P168) -> -1.2988552 | L168: =L159/(1+$G$167)^L$1 -> -0.31387638 | M168: =M159/(1+$G$167)^M$1 -> -0.98497885 | N168: =N159/(1+$G$167)^N$1 -> 0 | O168: =O159/(1+$G$167)^O$1 -> 0 | P168: =P159/(1+$G$167)^P$1 -> 0 | Q168: =SUM(L168:P168) -> -1.2988552
C171: END

Sheet Standard Template
L1: 1 | M1: 2 | N1: 3 | O1: 4 | P1: 5 | R1: =COUNTIFS($R$66:$R$117, "Error") -> 0 | T1: 2026 | U1: 2026 | V1: 2026 | W1: 2026 | X1: 2026 | Y1: 2026 | Z1: 2026 | AA1: 2026 | AB1: 2026 | AC1: 2026 | AD1: 2026 | AE1: 2026 | AF1: 2027 | AG1: 2027 | AH1: 2027 | AI1: 2027 | AJ1: 2027 | AK1: 2027 | AL1: 2027 | AM1: 2027 | AN1: 2027 | AO1: 2027 | AP1: 2027 | AQ1: 2027 | AR1: 2028 | AS1: 2028 | AT1: 2028 | AU1: 2028 | AV1: 2028 | AW1: 2028 | AX1: 2028 | AY1: 2028 | AZ1: 2028 | BA1: 2028 | BB1: 2028 | BC1: 2028 | BD1: 2029 | BE1: 2029 | BF1: 2029 | BG1: 2029 | BH1: 2029 | BI1: 2029 | BJ1: 2029 | BK1: 2029 | BL1: 2029 | BM1: 2029 | BN1: 2029 | BO1: 2029 | BP1: 2030 | BQ1: 2030 | BR1: 2030 | BS1: 2030 | BT1: 2030 | BU1: 2030 | BV1: 2030 | BW1: 2030 | BX1: 2030 | BY1: 2030 | BZ1: 2030 | CA1: 2030 | CI1: =COUNTIFS(CI$66:CI$149, "FALSE") -> 0 | CJ1: =COUNTIFS(CJ$66:CJ$149, "FALSE") -> 0 | CK1: =COUNTIFS(CK$66:CK$149, "FALSE") -> 0 | CL1: =COUNTIFS(CL$66:CL$149, "FALSE") -> 0 | CM1: =COUNTIFS(CM$66:CM$149, "FALSE") -> 0
C2: ="#"&$F$6&" Initiative Business Case" -> # Initiative Business Case
C4: INPUTS & ASSUMPTIONS
D6: Initiative #
D7: Initiative Owner
D8: Initiative Name
D11: Estimated L4 date
D12: Net Recurring Benefit ($M) | F12: =$K$117 -> 0
C14: SECTION I - PRIMARY VALUE DRIVER (ILLUSTRATIVE)
D16: Illustrative example of value driver explanation - please edit fields to reflect value drivers for your Initiative
D17: Baseline | H17: Period | I17: KPI | J17: Inputs
E18: # CW headcount | H18: TTM 6/1/26 | I18: # CW
E19: Average hourly cost for CW | H19: =$H$18 -> TTM 6/1/26 | I19: $USD / # hr
E20: Average utliization hours for CW - annual | H20: =$H$18 -> TTM 6/1/26 | I20: # hr
E21: Total CW spend | H21: =$H$18 -> TTM 6/1/26 | I21: $USD M | J21: =(J18*J19*J20)/1000000 -> 0
D23: Goal
E24: # FTE headcount - lower cost location | H24: FY2026 | I24: # FTE's
E25: Average fully loaded annual cost per FTE - lower cost location | H25: FY2026 | I25: $ / FTE
E26: Total personnel spend for BU | H26: FY2026 | I26: $USD | J26: =(J24*J25)/1000000 -> 0
D28: Incremental Improvement
E29: Total personnel spend for X business unit | I29: $USD | J29: =J21-J26 -> 0
D31: Baseline | H31: Period | I31: $USD M | J31: Inputs
E32: # xxxx | H32: =$H$18 -> TTM 6/1/26 | I32: # xxxx | J32: 0
E33: xxxx unit cost | G33: [A] | H33: FY2025 | I33: $ xxxx | J33: 0
E34: xxxx total spend | G34: [B] | H34: FY2025 | I34: $USD K | J34: =(J32*J33)/1000 -> 0
D36: Goal
E37: # xxxx | H37: FY2025 | I37: # xxxx | J37: =$J$18 -> 0
E38: xxxx unit cost | G38: [C] | H38: FY2026 | I38: $ xxxx | J38: 0
E39: xxxx total spend | G39: [D] | H39: FY2026 | I39: $USD K | J39: =(J37*J38)/1000 -> 0
D41: Incremental Improvement
E42: =E38 -> xxxx unit cost | G42: [A]-[C] | I42: $ / xxxx | J42: =J33-J38 -> 0
E43: =E39 -> xxxx total spend | G43: [B]-[D] | I43: $USD K | J43: =J34-J39 -> 0
D45: Baseline | H45: Period | I45: KPI | J45: Inputs
E46: # xxxx | H46: FY2025 | I46: # xxxx | J46: 0
E47: xxxx unit cost | G47: [A] | H47: FY2025 | I47: $ xxxx | J47: 0
E48: xxxx total spend | G48: [B] | H48: FY2025 | I48: $USD K | J48: =(J46*J47)/1000 -> 0
D50: Goal
E51: # xxxx | H51: FY2025 | I51: # xxxx | J51: =$J$18 -> 0
E52: xxxx unit cost | G52: [C] | H52: FY2026 | I52: $ xxxx | J52: 0
E53: xxxx total spend | G53: [D] | H53: FY2026 | I53: $USD K | J53: =(J51*J52)/1000 -> 0
D55: Incremental Improvement
E56: =E52 -> xxxx unit cost | G56: [A]-[C] | I56: $ / xxxx | J56: =J47-J52 -> 0
E57: =E53 -> xxxx total spend | G57: [B]-[D] | I57: $USD K | J57: =J48-J53 -> 0
C60: SECTION II - NET RECURRING BENEFITS | CC60: ANNUAL SUMMARY | CI60: CHECK CELLS
T62: 2026 | AF62: 2027 | AR62: 2028 | BD62: 2029 | BP62: 2030 | CI62: CHECK
D63: RECURRING BENEFITS | H63: Comment | I63: Baseline | J63: Goal | K63: Ann. Run Rate | L63: 2026 | M63: =L63+1 -> 2027 | N63: =M63+1 -> 2028 | O63: =N63+1 -> 2029 | P63: =O63+1 -> 2030 | Q63: Impacted BU | R63: Check | T63: 46023 | U63: =EOMONTH(T63, 1) -> 46081 | V63: =EOMONTH(U63, 1) -> 46112 | W63: =EOMONTH(V63, 1) -> 46142 | X63: =EOMONTH(W63, 1) -> 46173 | Y63: =EOMONTH(X63, 1) -> 46203 | Z63: =EOMONTH(Y63, 1) -> 46234 | AA63: =EOMONTH(Z63, 1) -> 46265 | AB63: =EOMONTH(AA63, 1) -> 46295 | ... CA63: =EOMONTH(BZ63, 1) -> 47848 | CC63: 2026 | CD63: =CC63+1 -> 2027 | CE63: =CD63+1 -> 2028 | CF63: =CE63+1 -> 2029 | CG63: =CF63+1 -> 2030 | CI63: 2026 | CJ63: =CI63+1 -> 2027 | CK63: =CJ63+1 -> 2028 | CL63: =CK63+1 -> 2029 | CM63: =CL63+1 -> 2030
E64: $USD M | I64: ="TTM "&TEXT($H$18,"m/d/yy") -> TTM TTM 6/1/26 | J64: Future State | K64: Increment
E65: Revenue
I66: 0 | J66: 0 | K66: =J66-I66 -> 0 | R66: =IF(K66=P66, "", "Error") | CC66: =SUMIFS($T66:$CA66, $T$1:$CA$1, CC$63) -> 0 | CD66: =SUMIFS($T66:$CA66, $T$1:$CA$1, CD$63) -> 0 | CE66: =SUMIFS($T66:$CA66, $T$1:$CA$1, CE$63) -> 0 | CF66: =SUMIFS($T66:$CA66, $T$1:$CA$1, CF$63) -> 0 | CG66: =SUMIFS($T66:$CA66, $T$1:$CA$1, CG$63) -> 0 | CI66: =CC66=L66 -> 1 | CJ66: =CD66=M66 -> 1 | CK66: =CE66=N66 -> 1 | CL66: =CF66=O66 -> 1 | CM66: =CG66=P66 -> 1
I67: 0 | J67: 0 | K67: =J67-I67 -> 0 | R67: =IF(K67=P67, "", "Error") | CC67: =SUMIFS($T67:$CA67, $T$1:$CA$1, CC$63) -> 0 | CD67: =SUMIFS($T67:$CA67, $T$1:$CA$1, CD$63) -> 0 | CE67: =SUMIFS($T67:$CA67, $T$1:$CA$1, CE$63) -> 0 | CF67: =SUMIFS($T67:$CA67, $T$1:$CA$1, CF$63) -> 0 | CG67: =SUMIFS($T67:$CA67, $T$1:$CA$1, CG$63) -> 0 | CI67: =CC67=L67 -> 1 | CJ67: =CD67=M67 -> 1 | CK67: =CE67=N67 -> 1 | CL67: =CF67=O67 -> 1 | CM67: =CG67=P67 -> 1
E68: Revenue Subtotal | I68: =SUM(I66:I67) -> 0 | J68: =SUM(J66:J67) -> 0 | K68: =SUM(K66:K67) -> 0 | L68: =SUM(L66:L67) -> 0 | M68: =SUM(M66:M67) -> 0 | N68: =SUM(N66:N67) -> 0 | O68: =SUM(O66:O67) -> 0 | P68: =SUM(P66:P67) -> 0 | T68: =SUM(T66:T67) -> 0 | U68: =SUM(U66:U67) -> 0 | V68: =SUM(V66:V67) -> 0 | W68: =SUM(W66:W67) -> 0 | X68: =SUM(X66:X67) -> 0 | Y68: =SUM(Y66:Y67) -> 0 | Z68: =SUM(Z66:Z67) -> 0 | AA68: =SUM(AA66:AA67) -> 0 | ... CA68: =SUM(CA66:CA67) -> 0 | CC68: =SUM(CC66:CC67) -> 0 | CD68: =SUM(CD66:CD67) -> 0 | CE68: =SUM(CE66:CE67) -> 0 | CF68: =SUM(CF66:CF67) -> 0 | CG68: =SUM(CG66:CG67) -> 0 | CI68: =CC68=L68 -> 1 | CJ68: =CD68=M68 -> 1 | CK68: =CE68=N68 -> 1 | CL68: =CF68=O68 -> 1 | CM68: =CG68=P68 -> 1
E70: Cost of Sales
K71: =I71-J71 -> 0 | R71: =IF(K71=P71, "", "Error") | CC71: =SUMIFS($T71:$CA71, $T$1:$CA$1, CC$63) -> 0 | CD71: =SUMIFS($T71:$CA71, $T$1:$CA$1, CD$63) -> 0 | CE71: =SUMIFS($T71:$CA71, $T$1:$CA$1, CE$63) -> 0 | CF71: =SUMIFS($T71:$CA71, $T$1:$CA$1, CF$63) -> 0 | CG71: =SUMIFS($T71:$CA71, $T$1:$CA$1, CG$63) -> 0 | CI71: =CC71=L71 -> 1 | CJ71: =CD71=M71 -> 1 | CK71: =CE71=N71 -> 1 | CL71: =CF71=O71 -> 1 | CM71: =CG71=P71 -> 1
I72: 0 | J72: 0 | K72: =I72-J72 -> 0 | R72: =IF(K72=P72, "", "Error") | CC72: =SUMIFS($T72:$CA72, $T$1:$CA$1, CC$63) -> 0 | CD72: =SUMIFS($T72:$CA72, $T$1:$CA$1, CD$63) -> 0 | CE72: =SUMIFS($T72:$CA72, $T$1:$CA$1, CE$63) -> 0 | CF72: =SUMIFS($T72:$CA72, $T$1:$CA$1, CF$63) -> 0 | CG72: =SUMIFS($T72:$CA72, $T$1:$CA$1, CG$63) -> 0 | CI72: =CC72=L72 -> 1 | CJ72: =CD72=M72 -> 1 | CK72: =CE72=N72 -> 1 | CL72: =CF72=O72 -> 1 | CM72: =CG72=P72 -> 1
I73: 0 | J73: 0 | K73: =I73-J73 -> 0 | R73: =IF(K73=P73, "", "Error") | CC73: =SUMIFS($T73:$CA73, $T$1:$CA$1, CC$63) -> 0 | CD73: =SUMIFS($T73:$CA73, $T$1:$CA$1, CD$63) -> 0 | CE73: =SUMIFS($T73:$CA73, $T$1:$CA$1, CE$63) -> 0 | CF73: =SUMIFS($T73:$CA73, $T$1:$CA$1, CF$63) -> 0 | CG73: =SUMIFS($T73:$CA73, $T$1:$CA$1, CG$63) -> 0 | CI73: =CC73=L73 -> 1 | CJ73: =CD73=M73 -> 1 | CK73: =CE73=N73 -> 1 | CL73: =CF73=O73 -> 1 | CM73: =CG73=P73 -> 1
I74: 0 | J74: 0 | K74: =I74-J74 -> 0 | R74: =IF(K74=P74, "", "Error") | CC74: =SUMIFS($T74:$CA74, $T$1:$CA$1, CC$63) -> 0 | CD74: =SUMIFS($T74:$CA74, $T$1:$CA$1, CD$63) -> 0 | CE74: =SUMIFS($T74:$CA74, $T$1:$CA$1, CE$63) -> 0 | CF74: =SUMIFS($T74:$CA74, $T$1:$CA$1, CF$63) -> 0 | CG74: =SUMIFS($T74:$CA74, $T$1:$CA$1, CG$63) -> 0 | CI74: =CC74=L74 -> 1 | CJ74: =CD74=M74 -> 1 | CK74: =CE74=N74 -> 1 | CL74: =CF74=O74 -> 1 | CM74: =CG74=P74 -> 1
K75: =I75-J75 -> 0 | R75: =IF(K75=P75, "", "Error") | CC75: =SUMIFS($T75:$CA75, $T$1:$CA$1, CC$63) -> 0 | CD75: =SUMIFS($T75:$CA75, $T$1:$CA$1, CD$63) -> 0 | CE75: =SUMIFS($T75:$CA75, $T$1:$CA$1, CE$63) -> 0 | CF75: =SUMIFS($T75:$CA75, $T$1:$CA$1, CF$63) -> 0 | CG75: =SUMIFS($T75:$CA75, $T$1:$CA$1, CG$63) -> 0 | CI75: =CC75=L75 -> 1 | CJ75: =CD75=M75 -> 1 | CK75: =CE75=N75 -> 1 | CL75: =CF75=O75 -> 1 | CM75: =CG75=P75 -> 1
E76: Cost of Sales Subtotal | I76: =SUM(I71:I75) -> 0 | J76: =SUM(J71:J75) -> 0 | K76: =SUM(K71:K75) -> 0 | L76: =SUM(L71:L75) -> 0 | M76: =SUM(M71:M75) -> 0 | N76: =SUM(N71:N75) -> 0 | O76: =SUM(O71:O75) -> 0 | P76: =SUM(P71:P75) -> 0 | T76: =SUM(T71:T75) -> 0 | U76: =SUM(U71:U75) -> 0 | V76: =SUM(V71:V75) -> 0 | W76: =SUM(W71:W75) -> 0 | X76: =SUM(X71:X75) -> 0 | Y76: =SUM(Y71:Y75) -> 0 | Z76: =SUM(Z71:Z75) -> 0 | AA76: =SUM(AA71:AA75) -> 0 | ... CA76: =SUM(CA71:CA75) -> 0 | CC76: =SUM(CC71:CC75) -> 0 | CD76: =SUM(CD71:CD75) -> 0 | CE76: =SUM(CE71:CE75) -> 0 | CF76: =SUM(CF71:CF75) -> 0 | CG76: =SUM(CG71:CG75) -> 0 | CI76: =CC76=L76 -> 1 | CJ76: =CD76=M76 -> 1 | CK76: =CE76=N76 -> 1 | CL76: =CF76=O76 -> 1 | CM76: =CG76=P76 -> 1
E78: OPEX
I79: =J21 -> 0 | J79: 0 | K79: =I79-J79 -> 0 | L79: 0 | M79: =$K79 -> 0 | N79: =$K79 -> 0 | O79: =$K79 -> 0 | P79: =$K79 -> 0 | R79: =IF(K79=P79, "", "Error") | T79: 0 | U79: 0 | V79: 0 | W79: 0 | X79: 0 | Y79: 0 | Z79: 0 | AA79: 0 | AB79: 0 | AC79: 0 | AD79: 0 | AE79: 0 | AF79: =$K$79/12 -> 0 | AG79: =$K$79/12 -> 0 | AH79: =$K$79/12 -> 0 | AI79: =$K$79/12 -> 0 | AJ79: =$K$79/12 -> 0 | AK79: =$K$79/12 -> 0 | AL79: =$K$79/12 -> 0 | AM79: =$K$79/12 -> 0 | ... BO79: =$K$79/12 -> 0 | CC79: =SUMIFS($T79:$CA79, $T$1:$CA$1, CC$63) -> 0 | CD79: =SUMIFS($T79:$CA79, $T$1:$CA$1, CD$63) -> 0 | CE79: =SUMIFS($T79:$CA79, $T$1:$CA$1, CE$63) -> 0 | CF79: =SUMIFS($T79:$CA79, $T$1:$CA$1, CF$63) -> 0 | CG79: =SUMIFS($T79:$CA79, $T$1:$CA$1, CG$63) -> 0 | CI79: =CC79=L79 -> 1 | CJ79: =CD79=M79 -> 1 | CK79: =CE79=N79 -> 1 | CL79: =CF79=O79 -> 1 | CM79: =CG79=P79 -> 1
I80: 0 | J80: 0 | K80: =I80-J80 -> 0 | R80: =IF(K80=P80, "", "Error") | CC80: =SUMIFS($T80:$CA80, $T$1:$CA$1, CC$63) -> 0 | CD80: =SUMIFS($T80:$CA80, $T$1:$CA$1, CD$63) -> 0 | CE80: =SUMIFS($T80:$CA80, $T$1:$CA$1, CE$63) -> 0 | CF80: =SUMIFS($T80:$CA80, $T$1:$CA$1, CF$63) -> 0 | CG80: =SUMIFS($T80:$CA80, $T$1:$CA$1, CG$63) -> 0 | CI80: =CC80=L80 -> 1 | CJ80: =CD80=M80 -> 1 | CK80: =CE80=N80 -> 1 | CL80: =CF80=O80 -> 1 | CM80: =CG80=P80 -> 1
I81: 0 | J81: 0 | K81: =I81-J81 -> 0 | R81: =IF(K81=P81, "", "Error") | CC81: =SUMIFS($T81:$CA81, $T$1:$CA$1, CC$63) -> 0 | CD81: =SUMIFS($T81:$CA81, $T$1:$CA$1, CD$63) -> 0 | CE81: =SUMIFS($T81:$CA81, $T$1:$CA$1, CE$63) -> 0 | CF81: =SUMIFS($T81:$CA81, $T$1:$CA$1, CF$63) -> 0 | CG81: =SUMIFS($T81:$CA81, $T$1:$CA$1, CG$63) -> 0 | CI81: =CC81=L81 -> 1 | CJ81: =CD81=M81 -> 1 | CK81: =CE81=N81 -> 1 | CL81: =CF81=O81 -> 1 | CM81: =CG81=P81 -> 1
I82: 0 | J82: 0 | K82: =I82-J82 -> 0 | R82: =IF(K82=P82, "", "Error") | CC82: =SUMIFS($T82:$CA82, $T$1:$CA$1, CC$63) -> 0 | CD82: =SUMIFS($T82:$CA82, $T$1:$CA$1, CD$63) -> 0 | CE82: =SUMIFS($T82:$CA82, $T$1:$CA$1, CE$63) -> 0 | CF82: =SUMIFS($T82:$CA82, $T$1:$CA$1, CF$63) -> 0 | CG82: =SUMIFS($T82:$CA82, $T$1:$CA$1, CG$63) -> 0 | CI82: =CC82=L82 -> 1 | CJ82: =CD82=M82 -> 1 | CK82: =CE82=N82 -> 1 | CL82: =CF82=O82 -> 1 | CM82: =CG82=P82 -> 1
I83: 0 | J83: 0 | K83: =I83-J83 -> 0 | R83: =IF(K83=P83, "", "Error") | CC83: =SUMIFS($T83:$CA83, $T$1:$CA$1, CC$63) -> 0 | CD83: =SUMIFS($T83:$CA83, $T$1:$CA$1, CD$63) -> 0 | CE83: =SUMIFS($T83:$CA83, $T$1:$CA$1, CE$63) -> 0 | CF83: =SUMIFS($T83:$CA83, $T$1:$CA$1, CF$63) -> 0 | CG83: =SUMIFS($T83:$CA83, $T$1:$CA$1, CG$63) -> 0 | CI83: =CC83=L83 -> 1 | CJ83: =CD83=M83 -> 1 | CK83: =CE83=N83 -> 1 | CL83: =CF83=O83 -> 1 | CM83: =CG83=P83 -> 1
E84: OpEx subtotal | I84: =SUM(I79:I83) -> 0 | J84: =SUM(J79:J83) -> 0 | K84: =SUM(K79:K83) -> 0 | L84: =SUM(L79:L83) -> 0 | M84: =SUM(M79:M83) -> 0 | N84: =SUM(N79:N83) -> 0 | O84: =SUM(O79:O83) -> 0 | P84: =SUM(P79:P83) -> 0 | T84: =SUM(T79:T83) -> 0 | U84: =SUM(U79:U83) -> 0 | V84: =SUM(V79:V83) -> 0 | W84: =SUM(W79:W83) -> 0 | X84: =SUM(X79:X83) -> 0 | Y84: =SUM(Y79:Y83) -> 0 | Z84: =SUM(Z79:Z83) -> 0 | AA84: =SUM(AA79:AA83) -> 0 | ... CA84: =SUM(CA79:CA83) -> 0 | CC84: =SUM(CC79:CC83) -> 0 | CD84: =SUM(CD79:CD83) -> 0 | CE84: =SUM(CE79:CE83) -> 0 | CF84: =SUM(CF79:CF83) -> 0 | CG84: =SUM(CG79:CG83) -> 0 | CI84: =CC84=L84 -> 1 | CJ84: =CD84=M84 -> 1 | CK84: =CE84=N84 -> 1 | CL84: =CF84=O84 -> 1 | CM84: =CG84=P84 -> 1
E88: Recurring Benefits Total | I88: =SUM(I68, I76, I84) -> 0 | J88: =SUM(J68, J76, J84) -> 0 | K88: =SUM(-K68, K76, K84) -> 0 | L88: =SUM(L68, L76, L84) -> 0 | M88: =SUM(M68, M76, M84) -> 0 | N88: =SUM(N68, N76, N84) -> 0 | O88: =SUM(O68, O76, O84) -> 0 | P88: =SUM(P68, P76, P84) -> 0 | T88: =SUM(T68, T76, T84) -> 0 | U88: =SUM(U68, U76, U84) -> 0 | V88: =SUM(V68, V76, V84) -> 0 | W88: =SUM(W68, W76, W84) -> 0 | X88: =SUM(X68, X76, X84) -> 0 | Y88: =SUM(Y68, Y76, Y84) -> 0 | Z88: =SUM(Z68, Z76, Z84) -> 0 | AA88: =SUM(AA68, AA76, AA84) -> 0 | ... CA88: =SUM(CA68, CA76, CA84) -> 0 | CC88: =SUM(CC68, CC76, CC84) -> 0 | CD88: =SUM(CD68, CD76, CD84) -> 0 | CE88: =SUM(CE68, CE76, CE84) -> 0 | CF88: =SUM(CF68, CF76, CF84) -> 0 | CG88: =SUM(CG68, CG76, CG84) -> 0 | CH88: =SUM(CH68, CH76, CH84) -> 0 | CI88: =CC88=L88 -> 1 | CJ88: =CD88=M88 -> 1 | CK88: =CE88=N88 -> 1 | CL88: =CF88=O88 -> 1 | CM88: =CG88=P88 -> 1
T90: 2026 | AF90: 2027 | AR90: 2028 | BD90: 2029 | BP90: 2030 | CI90: CHECK
D91: RECURRING COSTS TO ACHIEVE IMPACT | H91: Comment | I91: Baseline | J91: Goal | K91: Ann. Run Rate | L91: 2026 | M91: =L91+1 -> 2027 | N91: =M91+1 -> 2028 | O91: =N91+1 -> 2029 | P91: =O91+1 -> 2030 | Q91: Impacted BU | R91: Check | T91: 46023 | U91: =EOMONTH(T91, 1) -> 46081 | V91: =EOMONTH(U91, 1) -> 46112 | W91: =EOMONTH(V91, 1) -> 46142 | X91: =EOMONTH(W91, 1) -> 46173 | Y91: =EOMONTH(X91, 1) -> 46203 | Z91: =EOMONTH(Y91, 1) -> 46234 | AA91: =EOMONTH(Z91, 1) -> 46265 | AB91: =EOMONTH(AA91, 1) -> 46295 | ... CA91: =EOMONTH(BZ91, 1) -> 47848 | CC91: 2026 | CD91: =CC91+1 -> 2027 | CE91: =CD91+1 -> 2028 | CF91: =CE91+1 -> 2029 | CG91: =CF91+1 -> 2030 | CI91: 2026 | CJ91: =CI91+1 -> 2027 | CK91: =CJ91+1 -> 2028 | CL91: =CK91+1 -> 2029 | CM91: =CL91+1 -> 2030
E92: $USD M | I92: ="TTM "&TEXT($H$18,"m/d/yy") -> TTM TTM 6/1/26 | J92: Future State | K92: Increment
E93: Revenue
I94: 0 | J94: 0 | K94: =J94-I94 -> 0 | R94: =IF(K94=P94, "", "Error") | CC94: =SUMIFS($T94:$CA94, $T$1:$CA$1, CC$63) -> 0 | CD94: =SUMIFS($T94:$CA94, $T$1:$CA$1, CD$63) -> 0 | CE94: =SUMIFS($T94:$CA94, $T$1:$CA$1, CE$63) -> 0 | CF94: =SUMIFS($T94:$CA94, $T$1:$CA$1, CF$63) -> 0 | CG94: =SUMIFS($T94:$CA94, $T$1:$CA$1, CG$63) -> 0 | CI94: =CC94=L94 -> 1 | CJ94: =CD94=M94 -> 1 | CK94: =CE94=N94 -> 1 | CL94: =CF94=O94 -> 1 | CM94: =CG94=P94 -> 1
I95: 0 | J95: 0 | K95: =J95-I95 -> 0 | R95: =IF(K95=P95, "", "Error") | CC95: =SUMIFS($T95:$CA95, $T$1:$CA$1, CC$63) -> 0 | CD95: =SUMIFS($T95:$CA95, $T$1:$CA$1, CD$63) -> 0 | CE95: =SUMIFS($T95:$CA95, $T$1:$CA$1, CE$63) -> 0 | CF95: =SUMIFS($T95:$CA95, $T$1:$CA$1, CF$63) -> 0 | CG95: =SUMIFS($T95:$CA95, $T$1:$CA$1, CG$63) -> 0 | CI95: =CC95=L95 -> 1 | CJ95: =CD95=M95 -> 1 | CK95: =CE95=N95 -> 1 | CL95: =CF95=O95 -> 1 | CM95: =CG95=P95 -> 1
E96: Revenue Subtotal | I96: =SUM(I94:I95) -> 0 | J96: =SUM(J94:J95) -> 0 | K96: =SUM(K94:K95) -> 0 | L96: =SUM(L94:L95) -> 0 | M96: =SUM(M94:M95) -> 0 | N96: =SUM(N94:N95) -> 0 | O96: =SUM(O94:O95) -> 0 | P96: =SUM(P94:P95) -> 0 | T96: =SUM(T94:T95) -> 0 | U96: =SUM(U94:U95) -> 0 | V96: =SUM(V94:V95) -> 0 | W96: =SUM(W94:W95) -> 0 | X96: =SUM(X94:X95) -> 0 | Y96: =SUM(Y94:Y95) -> 0 | Z96: =SUM(Z94:Z95) -> 0 | AA96: =SUM(AA94:AA95) -> 0 | ... CA96: =SUM(CA94:CA95) -> 0 | CC96: =SUM(CC94:CC95) -> 0 | CD96: =SUM(CD94:CD95) -> 0 | CE96: =SUM(CE94:CE95) -> 0 | CF96: =SUM(CF94:CF95) -> 0 | CG96: =SUM(CG94:CG95) -> 0 | CI96: =CC96=L96 -> 1 | CJ96: =CD96=M96 -> 1 | CK96: =CE96=N96 -> 1 | CL96: =CF96=O96 -> 1 | CM96: =CG96=P96 -> 1
E98: Cost of Sales
I99: 0 | J99: 0 | K99: =J99-I99 -> 0 | L99: 0 | M99: 0 | N99: 0 | O99: 0 | P99: 0 | R99: =IF(K99=P99, "", "Error") | CC99: =SUMIFS($T99:$CA99, $T$1:$CA$1, CC$63) -> 0 | CD99: =SUMIFS($T99:$CA99, $T$1:$CA$1, CD$63) -> 0 | CE99: =SUMIFS($T99:$CA99, $T$1:$CA$1, CE$63) -> 0 | CF99: =SUMIFS($T99:$CA99, $T$1:$CA$1, CF$63) -> 0 | CG99: =SUMIFS($T99:$CA99, $T$1:$CA$1, CG$63) -> 0 | CI99: =CC99=L99 -> 1 | CJ99: =CD99=M99 -> 1 | CK99: =CE99=N99 -> 1 | CL99: =CF99=O99 -> 1 | CM99: =CG99=P99 -> 1
I100: 0 | J100: 0 | K100: =J100-I100 -> 0 | L100: 0 | M100: 0 | N100: 0 | O100: 0 | P100: 0 | R100: =IF(K100=P100, "", "Error") | CC100: =SUMIFS($T100:$CA100, $T$1:$CA$1, CC$63) -> 0 | CD100: =SUMIFS($T100:$CA100, $T$1:$CA$1, CD$63) -> 0 | CE100: =SUMIFS($T100:$CA100, $T$1:$CA$1, CE$63) -> 0 | CF100: =SUMIFS($T100:$CA100, $T$1:$CA$1, CF$63) -> 0 | CG100: =SUMIFS($T100:$CA100, $T$1:$CA$1, CG$63) -> 0 | CI100: =CC100=L100 -> 1 | CJ100: =CD100=M100 -> 1 | CK100: =CE100=N100 -> 1 | CL100: =CF100=O100 -> 1 | CM100: =CG100=P100 -> 1
I101: 0 | J101: 0 | K101: =J101-I101 -> 0 | L101: 0 | M101: 0 | N101: 0 | O101: 0 | P101: 0 | R101: =IF(K101=P101, "", "Error") | CC101: =SUMIFS($T101:$CA101, $T$1:$CA$1, CC$63) -> 0 | CD101: =SUMIFS($T101:$CA101, $T$1:$CA$1, CD$63) -> 0 | CE101: =SUMIFS($T101:$CA101, $T$1:$CA$1, CE$63) -> 0 | CF101: =SUMIFS($T101:$CA101, $T$1:$CA$1, CF$63) -> 0 | CG101: =SUMIFS($T101:$CA101, $T$1:$CA$1, CG$63) -> 0 | CI101: =CC101=L101 -> 1 | CJ101: =CD101=M101 -> 1 | CK101: =CE101=N101 -> 1 | CL101: =CF101=O101 -> 1 | CM101: =CG101=P101 -> 1
I102: 0 | J102: 0 | K102: =J102-I102 -> 0 | L102: 0 | M102: 0 | N102: 0 | O102: 0 | P102: 0 | R102: =IF(K102=P102, "", "Error") | CC102: =SUMIFS($T102:$CA102, $T$1:$CA$1, CC$63) -> 0 | CD102: =SUMIFS($T102:$CA102, $T$1:$CA$1, CD$63) -> 0 | CE102: =SUMIFS($T102:$CA102, $T$1:$CA$1, CE$63) -> 0 | CF102: =SUMIFS($T102:$CA102, $T$1:$CA$1, CF$63) -> 0 | CG102: =SUMIFS($T102:$CA102, $T$1:$CA$1, CG$63) -> 0 | CI102: =CC102=L102 -> 1 | CJ102: =CD102=M102 -> 1 | CK102: =CE102=N102 -> 1 | CL102: =CF102=O102 -> 1 | CM102: =CG102=P102 -> 1
K103: =J103-I103 -> 0 | L103: 0 | M103: 0 | N103: 0 | O103: 0 | P103: 0
E104: Cost of Sales Subtotal | I104: =SUM(I99:I103) -> 0 | J104: =SUM(J99:J103) -> 0 | K104: =SUM(K99:K103) -> 0 | L104: =SUM(L99:L103) -> 0 | M104: =SUM(M99:M103) -> 0 | N104: =SUM(N99:N103) -> 0 | O104: =SUM(O99:O103) -> 0 | P104: =SUM(P99:P103) -> 0 | T104: =SUM(T99:T103) -> 0 | U104: =SUM(U99:U103) -> 0 | V104: =SUM(V99:V103) -> 0 | W104: =SUM(W99:W103) -> 0 | X104: =SUM(X99:X103) -> 0 | Y104: =SUM(Y99:Y103) -> 0 | Z104: =SUM(Z99:Z103) -> 0 | AA104: =SUM(AA99:AA103) -> 0 | ... CA104: =SUM(CA99:CA103) -> 0 | CC104: =SUM(CC99:CC103) -> 0 | CD104: =SUM(CD99:CD103) -> 0 | CE104: =SUM(CE99:CE103) -> 0 | CF104: =SUM(CF99:CF103) -> 0 | CG104: =SUM(CG99:CG103) -> 0 | CI104: =CC104=L104 -> 1 | CJ104: =CD104=M104 -> 1 | CK104: =CE104=N104 -> 1 | CL104: =CF104=O104 -> 1 | CM104: =CG104=P104 -> 1
E106: OPEX
I107: 0 | J107: =J26 -> 0 | K107: =J107-I107 -> 0 | L107: 0 | M107: =$K107 -> 0 | N107: =$K107 -> 0 | O107: =$K107 -> 0 | P107: =$K107 -> 0 | R107: =IF(K107=P107, "", "Error") | AF107: =$K$107/12 -> 0 | AG107: =$K$107/12 -> 0 | AH107: =$K$107/12 -> 0 | AI107: =$K$107/12 -> 0 | AJ107: =$K$107/12 -> 0 | AK107: =$K$107/12 -> 0 | AL107: =$K$107/12 -> 0 | AM107: =$K$107/12 -> 0 | ... CA107: =$K$107/12 -> 0 | CC107: =SUMIFS($T107:$CA107, $T$1:$CA$1, CC$63) -> 0 | CD107: =SUMIFS($T107:$CA107, $T$1:$CA$1, CD$63) -> 0 | CE107: =SUMIFS($T107:$CA107, $T$1:$CA$1, CE$63) -> 0 | CF107: =SUMIFS($T107:$CA107, $T$1:$CA$1, CF$63) -> 0 | CG107: =SUMIFS($T107:$CA107, $T$1:$CA$1, CG$63) -> 0 | CI107: =CC107=L107 -> 1 | CJ107: =CD107=M107 -> 1 | CK107: =CE107=N107 -> 1 | CL107: =CF107=O107 -> 1 | CM107: =CG107=P107 -> 1
I108: 0 | J108: 0 | K108: =J108-I108 -> 0 | L108: 0 | M108: 0 | N108: 0 | O108: 0 | P108: 0 | R108: =IF(K108=P108, "", "Error") | CC108: =SUMIFS($T108:$CA108, $T$1:$CA$1, CC$63) -> 0 | CD108: =SUMIFS($T108:$CA108, $T$1:$CA$1, CD$63) -> 0 | CE108: =SUMIFS($T108:$CA108, $T$1:$CA$1, CE$63) -> 0 | CF108: =SUMIFS($T108:$CA108, $T$1:$CA$1, CF$63) -> 0 | CG108: =SUMIFS($T108:$CA108, $T$1:$CA$1, CG$63) -> 0 | CI108: =CC108=L108 -> 1 | CJ108: =CD108=M108 -> 1 | CK108: =CE108=N108 -> 1 | CL108: =CF108=O108 -> 1 | CM108: =CG108=P108 -> 1
I109: 0 | J109: 0 | K109: =J109-I109 -> 0 | L109: 0 | M109: 0 | N109: 0 | O109: 0 | P109: 0 | R109: =IF(K109=P109, "", "Error") | CC109: =SUMIFS($T109:$CA109, $T$1:$CA$1, CC$63) -> 0 | CD109: =SUMIFS($T109:$CA109, $T$1:$CA$1, CD$63) -> 0 | CE109: =SUMIFS($T109:$CA109, $T$1:$CA$1, CE$63) -> 0 | CF109: =SUMIFS($T109:$CA109, $T$1:$CA$1, CF$63) -> 0 | CG109: =SUMIFS($T109:$CA109, $T$1:$CA$1, CG$63) -> 0 | CI109: =CC109=L109 -> 1 | CJ109: =CD109=M109 -> 1 | CK109: =CE109=N109 -> 1 | CL109: =CF109=O109 -> 1 | CM109: =CG109=P109 -> 1
I110: 0 | J110: 0 | K110: =J110-I110 -> 0 | L110: 0 | M110: 0 | N110: 0 | O110: 0 | P110: 0 | R110: =IF(K110=P110, "", "Error") | CC110: =SUMIFS($T110:$CA110, $T$1:$CA$1, CC$63) -> 0 | CD110: =SUMIFS($T110:$CA110, $T$1:$CA$1, CD$63) -> 0 | CE110: =SUMIFS($T110:$CA110, $T$1:$CA$1, CE$63) -> 0 | CF110: =SUMIFS($T110:$CA110, $T$1:$CA$1, CF$63) -> 0 | CG110: =SUMIFS($T110:$CA110, $T$1:$CA$1, CG$63) -> 0 | CI110: =CC110=L110 -> 1 | CJ110: =CD110=M110 -> 1 | CK110: =CE110=N110 -> 1 | CL110: =CF110=O110 -> 1 | CM110: =CG110=P110 -> 1
