Workbook

Sheet Cover
B2: PROJECT ZENITH — SDLC WORKSTREAM | INITIATIVE MODELS & WAVE TEMPLATES
B4: Workstream | C4: SDLC — Raise engineering throughput and reimagine PDLC through agentic loop engineering. ELT sponsor: Srini | WSL: Pooja | IOs: Pooja, Aruna.
B5: Purpose | C5: One file per workstream: each initiative has a Model sheet (all logic and inputs) formula-linked into its own copy of the standard WAVE business-case template. S2 gate: Sep 3/4; S3: Sep 18.
B6: Version / status | C6: v1 — structure complete; SDLC baselines pending data requests (models compute $0 until baseline inputs are populated; impact-driver rates are seeded from the Aug 13 / Board decks).
B7: Prepared | C7: Prepared by AAO model build, 31 Aug 2026. Sources: Project Zenith workplan vS_1; Zenith Business Case Template by Lever (WAVE); Aug 13 deck pp. 9, 19–21; Board deck pp. 12, 22.
B8: Sources | C8: Workplan SDLC tab (initiatives, data POV); SDLC Data Requests tab (12 requests, 4 shared by Pooja); WAVE standard template (reference copy at the end of this file).
B10: HOW THIS FILE IS ORGANIZED
B12: Cover | C12: This sheet — orientation, legend, deviations, open items.
B13: Instructions | C13: The WAVE template's own instruction sheet (as uploaded; dead broken-reference drop-down cells cleared).
B14: Rate Card | C14: Shared people-cost engine: rate basis (yearly/monthly/hourly), role table + blended rate, contingency reference, capitalization policy.
B15: Summary | C15: Portfolio roll-up of both initiatives (links to WAVE sheets).
B16: SDLC-1 Model / SDLC-1 WAVE | C16: Agentic loop engineering — model + linked WAVE template.
B17: SDLC-2 Model / SDLC-2 WAVE | C17: PDLC re-imagination — model + linked WAVE template.
B18: Standard Template | C18: Reference copy of the standard WAVE template (only error-guard fixes applied — see deviations).
B20: COLOR LEGEND
B22: Input — change freely
B23: Formula — do not overwrite
B24: Link to another sheet
B25: Section band
B27: MODEL -> WAVE LINKING
B29: • Each initiative has a '<code> Model' sheet (all logic and inputs) and a '<code> WAVE' sheet (the standard template). The WAVE sheet contains NO hardcoded numbers for this initiative — its benefit/cost rows link (green) to the Model sheet's feed rows in $M.
B30: • Model sheets use the same time grid as WAVE: columns L:P = FY2026–2030 annual, columns T:CA = Jan-2026..Dec-2030 monthly. Annual cells are SUMIFS of the monthly grid, so the WAVE monthly-vs-annual checks (CI1:CM1) pass by construction.
B31: • The 'Ann. Run Rate' (K) on feed rows is defined as the 2030 value, matching the WAVE rule 'Annualized Run Rate (K) = 2030 Value (P)'. Keep ramps reaching 100% before 2030.
B32: • Benefits ramp linearly from the go-live date over 'months to full run rate' — same convention as the Servicing S2 model. One-time costs spread evenly over each milestone's billing months.
B33: • People costs: milestone labor = Team size x Billing months x blended monthly rate (Rate Card) x (1 + contingency). Capitalization: each milestone carries a Cap % (default from Rate Card policy) that splits labor into WAVE CapEx vs OTC rows. Same for non-labor one-time items.
B35: DEVIATIONS FROM THE STANDARD WAVE TEMPLATE (documented fixes)
... B51: • Capitalization %s (Build/Test 80% default) need Finance sign-off (ASC 350-40).

Sheet Instructions
L1: 1 | M1: 2 | N1: 3 | O1: 4 | P1: 5 | R1: =COUNTIFS($R$78:$R$128, "Error") -> 0 | T1: 2026 | U1: 2026 | V1: 2026 | W1: 2026 | X1: 2026 | Y1: 2026 | Z1: 2026 | AA1: 2026 | AB1: 2026 | AC1: 2026 | AD1: 2026 | AE1: 2026 | AF1: 2027 | AG1: 2027 | AH1: 2027 | AI1: 2027 | AJ1: 2027 | AK1: 2027 | AL1: 2027 | AM1: 2027 | AN1: 2027 | AO1: 2027 | AP1: 2027 | AQ1: 2027 | AR1: 2028 | AS1: 2028 | AT1: 2028 | AU1: 2028 | AV1: 2028 | AW1: 2028 | AX1: 2028 | AY1: 2028 | AZ1: 2028 | BA1: 2028 | BB1: 2028 | BC1: 2028 | BD1: 2029 | BE1: 2029 | BF1: 2029 | BG1: 2029 | BH1: 2029 | BI1: 2029 | BJ1: 2029 | BK1: 2029 | BL1: 2029 | BM1: 2029 | BN1: 2029 | BO1: 2029 | BP1: 2030 | BQ1: 2030 | BR1: 2030 | BS1: 2030 | BT1: 2030 | BU1: 2030 | BV1: 2030 | BW1: 2030 | BX1: 2030 | BY1: 2030 | BZ1: 2030 | CA1: 2030 | CI1: =COUNTIFS(CI$78:CI$159, "FALSE") -> 0 | CJ1: =COUNTIFS(CJ$78:CJ$159, "FALSE") -> 4 | CK1: =COUNTIFS(CK$78:CK$159, "FALSE") -> 4 | CL1: =COUNTIFS(CL$78:CL$159, "FALSE") -> 0 | CM1: =COUNTIFS(CM$78:CM$159, "FALSE") -> 0
C9: ="#"&$F$13&" Initiative Business Case" -> #123456 Initiative Business Case
C11: INPUTS & ASSUMPTIONS
D13: Initiative # | F13: 123456
D14: Initiative Owner | F14: John Smith
D15: Initiative Name | F15: Leverage agentic AI for customer service and care centers, reducing number of calls handled by live customer care agents and increasing productivity | I15: Names - 5-7 words
I16: Descriptions - 10-20 words
D18: Estimated L4 date | F18: 46736
D19: Net Recurring Benefit ($M) | F19: =$K$128 -> 7.2
C21: SECTION I - PRIMARY VALUE DRIVER (ILLUSTRATIVE) | L21: CHECKS
D23: Illustrative example of value driver explanation - please edit fields to reflect value drivers for your Initiative | L23: Criteria (Column Reference) | P23: Check | Q23: Troubleshoot:
D24: Baseline | H24: Period | I24: KPI | J24: Inputs | L24: (A) Annualized Run Rate (K) = 2030 Value (P) | P24: =IF($R$1=0, "PASS", "ERROR") -> PASS | Q24: =IF(P24="Error", "Check column R for errors", "")
E25: # of calls handled by live agents | G25: [A] | H25: FY2025 | I25: # of calls | J25: 6000 | L25: (B) 2026 Value (L) = Sum of Monthly 2026 Values (CC) | P25: =IF($CI$1=0, "PASS", "ERROR") -> PASS | Q25: =IF(P25="Error", "Check column CI for errors", "")
E26: AHT | G26: [B] | H26: FY 2026 | I26: Seconds | J26: 150 | L26: (C) 2027 Value (M) = Sum of Monthly 2027 Values (CD) | P26: =IF($CJ$1=0, "PASS", "ERROR") -> ERROR | Q26: =IF(P26="Error", "Check column CJ for errors", "") -> Check column CJ for errors
E27: # of live agents handling calls | G27: [C] | H27: FY 2025 | I27: # of live agents | J27: 500 | L27: (D) 2028 Value (N) = Sum of Monthly 2028 Values (CE) | P27: =IF($CK$1=0, "PASS", "ERROR") -> ERROR | Q27: =IF(P27="Error", "Check column CK for errors", "") -> Check column CK for errors
E28: Average cost per agent | H28: FY 2026 | I28: $ / agent | J28: 50000 | L28: (E) 2029 Value (O) = Sum of Monthly 2029 Values (CF) | P28: =IF($CL$1=0, "PASS", "ERROR") -> PASS | Q28: =IF(P28="Error", "Check column CL for errors", "")
E29: Total spend on contact center for queue X | G29: [D] | H29: FY2025 | I29: $USD M | J29: =(J27*J28)/1000000 -> 25 | L29: (F) 2030 Value (P) = Sum of Monthly 2030 Values (CG) | P29: =IF($CM$1=0, "PASS", "ERROR") -> PASS | Q29: =IF(P29="Error", "Check column CM for errors", "")
D31: Goal | Y31: D
E32: # of calls handled by live agents | G32: [E] | I32: # of calls | J32: 4000
E33: AHT | G33: [F] | I33: Seconds | J33: 120
E34: # of live agents handling calls | G34: [G] | I34: # of live agents | J34: 260
E35: Average cost per agent | I35: $ / agent | J35: =J28 -> 50000
E36: Total spend on contact center for queue X | G36: [H] | H36: FY2026 | I36: $USD M | J36: =(J34*J35)/1000000 -> 13
D38: Incremental Improvement
E39: # of calls handled by live agents | G39: [A]-[E] | I39: # of calls | J39: =J25-J32 -> 2000
E40: AHT | G40: [B]-[F] | I40: Seconds | J40: =J26-J33 -> 30
E41: # of live agents handling calls | G41: [C]-[G] | I41: # of live agents | J41: =J27-J34 -> 240
E42: Total spend on contact center queue X | G42: [D]-[H] | I42: USD M | J42: =J29-J36 -> 12
D43: Baseline | H43: Period | I43: $USD M | J43: Inputs
E44: # xxxx | H44: FY2025 | I44: # xxxx | J44: 12000000
E45: xxxx unit cost | G45: [A] | H45: FY2025 | I45: $ xxxx | J45: 0.14
E46: xxxx total spend | G46: [B] | H46: FY2025 | I46: $USD K | J46: =(J44*J45)/1000 -> 1680
D48: Goal
E49: # xxxx | H49: FY2025 | I49: # xxxx | J49: =$J$25 -> 6000
E50: xxxx unit cost | G50: [C] | H50: FY2026 | I50: $ xxxx | J50: 0.1
E51: xxxx total spend | G51: [D] | H51: FY2026 | I51: $USD K | J51: =(J49*J50)/1000 -> 0.6
D53: Incremental Improvement
E54: =E50 -> xxxx unit cost | G54: [A]-[C] | I54: $ / xxxx | J54: =J45-J50 -> 0.04
E55: =E51 -> xxxx total spend | G55: [B]-[D] | I55: $USD K | J55: =J46-J51 -> 1679.4
D58: Baseline | H58: Period | I58: KPI | J58: Inputs
E59: # xxxx | H59: FY2025 | I59: # xxxx | J59: 12000000
E60: xxxx unit cost | G60: [A] | H60: FY2025 | I60: $ xxxx | J60: 0.14
E61: xxxx total spend | G61: [B] | H61: FY2025 | I61: $USD K | J61: =(J59*J60)/1000 -> 1680
D63: Goal
E64: # xxxx | H64: FY2025 | I64: # xxxx | J64: =$J$25 -> 6000
E65: xxxx unit cost | G65: [C] | H65: FY2026 | I65: $ xxxx | J65: 0.1
E66: xxxx total spend | G66: [D] | H66: FY2026 | I66: $USD K | J66: =(J64*J65)/1000 -> 0.6
D68: Incremental Improvement
E69: =E65 -> xxxx unit cost | G69: [A]-[C] | I69: $ / xxxx | J69: =J60-J65 -> 0.04
E70: =E66 -> xxxx total spend | G70: [B]-[D] | I70: $USD K | J70: =J61-J66 -> 1679.4
C73: SECTION II - NET RECURRING BENEFITS | CC73: ANNUAL SUMMARY | CI73: CHECK CELLS
D75: RECURRING BENEFITS | H75: Comment | I75: Baseline | J75: Goal | K75: Ann. Run Rate | L75: 2026 | M75: =L75+1 -> 2027 | N75: =M75+1 -> 2028 | O75: =N75+1 -> 2029 | P75: =O75+1 -> 2030 | Q75: Impacted BU | R75: Check | T75: 46023 | U75: =EOMONTH(T75, 1) -> 46081 | V75: =EOMONTH(U75, 1) -> 46112 | W75: =EOMONTH(V75, 1) -> 46142 | X75: =EOMONTH(W75, 1) -> 46173 | Y75: =EOMONTH(X75, 1) -> 46203 | Z75: =EOMONTH(Y75, 1) -> 46234 | AA75: =EOMONTH(Z75, 1) -> 46265 | AB75: =EOMONTH(AA75, 1) -> 46295 | ... CA75: =EOMONTH(BZ75, 1) -> 47848 | CC75: 2026 | CD75: =CC75+1 -> 2027 | CE75: =CD75+1 -> 2028 | CF75: =CE75+1 -> 2029 | CG75: =CF75+1 -> 2030 | CI75: 2026 | CJ75: =CI75+1 -> 2027 | CK75: =CJ75+1 -> 2028 | CL75: =CK75+1 -> 2029 | CM75: =CL75+1 -> 2030
E76: $USD M | I76: FY25 Hist. | J76: Future State | K76: Increment
E77: Revenue
I78: 0 | J78: 0 | K78: =J78-I78 -> 0 | R78: =IF(K78=P78, "", "Error") | CC78: =SUMIFS($T78:$CA78, $T$1:$CA$1, CC$75) -> 0 | CD78: =SUMIFS($T78:$CA78, $T$1:$CA$1, CD$75) -> 0 | CE78: =SUMIFS($T78:$CA78, $T$1:$CA$1, CE$75) -> 0 | CF78: =SUMIFS($T78:$CA78, $T$1:$CA$1, CF$75) -> 0 | CG78: =SUMIFS($T78:$CA78, $T$1:$CA$1, CG$75) -> 0 | CI78: =CC78=L78 -> 1 | CJ78: =CD78=M78 -> 1 | CK78: =CE78=N78 -> 1 | CL78: =CF78=O78 -> 1 | CM78: =CG78=P78 -> 1
I79: 0 | J79: 0 | K79: =J79-I79 -> 0 | R79: =IF(K79=P79, "", "Error") | CC79: =SUMIFS($T79:$CA79, $T$1:$CA$1, CC$75) -> 0 | CD79: =SUMIFS($T79:$CA79, $T$1:$CA$1, CD$75) -> 0 | CE79: =SUMIFS($T79:$CA79, $T$1:$CA$1, CE$75) -> 0 | CF79: =SUMIFS($T79:$CA79, $T$1:$CA$1, CF$75) -> 0 | CG79: =SUMIFS($T79:$CA79, $T$1:$CA$1, CG$75) -> 0 | CI79: =CC79=L79 -> 1 | CJ79: =CD79=M79 -> 1 | CK79: =CE79=N79 -> 1 | CL79: =CF79=O79 -> 1 | CM79: =CG79=P79 -> 1
E80: Revenue Subtotal | I80: =SUM(I78:I79) -> 0 | J80: =SUM(J78:J79) -> 0 | K80: =SUM(K78:K79) -> 0 | L80: =SUM(L78:L79) -> 0 | M80: =SUM(M78:M79) -> 0 | N80: =SUM(N78:N79) -> 0 | O80: =SUM(O78:O79) -> 0 | P80: =SUM(P78:P79) -> 0 | T80: =SUM(T78:T79) -> 0 | U80: =SUM(U78:U79) -> 0 | V80: =SUM(V78:V79) -> 0 | W80: =SUM(W78:W79) -> 0 | X80: =SUM(X78:X79) -> 0 | Y80: =SUM(Y78:Y79) -> 0 | Z80: =SUM(Z78:Z79) -> 0 | AA80: =SUM(AA78:AA79) -> 0 | ... CA80: =SUM(CA78:CA79) -> 0 | CC80: =SUM(CC78:CC79) -> 0 | CD80: =SUM(CD78:CD79) -> 0 | CE80: =SUM(CE78:CE79) -> 0 | CF80: =SUM(CF78:CF79) -> 0 | CG80: =SUM(CG78:CG79) -> 0 | CI80: =CC80=L80 -> 1 | CJ80: =CD80=M80 -> 1 | CK80: =CE80=N80 -> 1 | CL80: =CF80=O80 -> 1 | CM80: =CG80=P80 -> 1
E82: Cost of Sales
K83: =I83-J83 -> 0 | R83: =IF(K83=P83, "", "Error") | CC83: =SUMIFS($T83:$CA83, $T$1:$CA$1, CC$75) -> 0 | CD83: =SUMIFS($T83:$CA83, $T$1:$CA$1, CD$75) -> 0 | CE83: =SUMIFS($T83:$CA83, $T$1:$CA$1, CE$75) -> 0 | CF83: =SUMIFS($T83:$CA83, $T$1:$CA$1, CF$75) -> 0 | CG83: =SUMIFS($T83:$CA83, $T$1:$CA$1, CG$75) -> 0 | CI83: =CC83=L83 -> 1 | CJ83: =CD83=M83 -> 1 | CK83: =CE83=N83 -> 1 | CL83: =CF83=O83 -> 1 | CM83: =CG83=P83 -> 1
I84: 0 | J84: 0 | K84: =I84-J84 -> 0 | R84: =IF(K84=P84, "", "Error") | CC84: =SUMIFS($T84:$CA84, $T$1:$CA$1, CC$75) -> 0 | CD84: =SUMIFS($T84:$CA84, $T$1:$CA$1, CD$75) -> 0 | CE84: =SUMIFS($T84:$CA84, $T$1:$CA$1, CE$75) -> 0 | CF84: =SUMIFS($T84:$CA84, $T$1:$CA$1, CF$75) -> 0 | CG84: =SUMIFS($T84:$CA84, $T$1:$CA$1, CG$75) -> 0 | CI84: =CC84=L84 -> 1 | CJ84: =CD84=M84 -> 1 | CK84: =CE84=N84 -> 1 | CL84: =CF84=O84 -> 1 | CM84: =CG84=P84 -> 1
I85: 0 | J85: 0 | K85: =I85-J85 -> 0 | R85: =IF(K85=P85, "", "Error") | CC85: =SUMIFS($T85:$CA85, $T$1:$CA$1, CC$75) -> 0 | CD85: =SUMIFS($T85:$CA85, $T$1:$CA$1, CD$75) -> 0 | CE85: =SUMIFS($T85:$CA85, $T$1:$CA$1, CE$75) -> 0 | CF85: =SUMIFS($T85:$CA85, $T$1:$CA$1, CF$75) -> 0 | CG85: =SUMIFS($T85:$CA85, $T$1:$CA$1, CG$75) -> 0 | CI85: =CC85=L85 -> 1 | CJ85: =CD85=M85 -> 1 | CK85: =CE85=N85 -> 1 | CL85: =CF85=O85 -> 1 | CM85: =CG85=P85 -> 1
I86: 0 | J86: 0 | K86: =I86-J86 -> 0 | R86: =IF(K86=P86, "", "Error") | CC86: =SUMIFS($T86:$CA86, $T$1:$CA$1, CC$75) -> 0 | CD86: =SUMIFS($T86:$CA86, $T$1:$CA$1, CD$75) -> 0 | CE86: =SUMIFS($T86:$CA86, $T$1:$CA$1, CE$75) -> 0 | CF86: =SUMIFS($T86:$CA86, $T$1:$CA$1, CF$75) -> 0 | CG86: =SUMIFS($T86:$CA86, $T$1:$CA$1, CG$75) -> 0 | CI86: =CC86=L86 -> 1 | CJ86: =CD86=M86 -> 1 | CK86: =CE86=N86 -> 1 | CL86: =CF86=O86 -> 1 | CM86: =CG86=P86 -> 1
K87: =I87-J87 -> 0 | R87: =IF(K87=P87, "", "Error") | CC87: =SUMIFS($T87:$CA87, $T$1:$CA$1, CC$75) -> 0 | CD87: =SUMIFS($T87:$CA87, $T$1:$CA$1, CD$75) -> 0 | CE87: =SUMIFS($T87:$CA87, $T$1:$CA$1, CE$75) -> 0 | CF87: =SUMIFS($T87:$CA87, $T$1:$CA$1, CF$75) -> 0 | CG87: =SUMIFS($T87:$CA87, $T$1:$CA$1, CG$75) -> 0 | CI87: =CC87=L87 -> 1 | CJ87: =CD87=M87 -> 1 | CK87: =CE87=N87 -> 1 | CL87: =CF87=O87 -> 1 | CM87: =CG87=P87 -> 1
E88: Cost of Sales Subtotal | I88: =SUM(I83:I87) -> 0 | J88: =SUM(J83:J87) -> 0 | K88: =SUM(K83:K87) -> 0 | L88: =SUM(L83:L87) -> 0 | M88: =SUM(M83:M87) -> 0 | N88: =SUM(N83:N87) -> 0 | O88: =SUM(O83:O87) -> 0 | P88: =SUM(P83:P87) -> 0 | T88: =SUM(T83:T87) -> 0 | U88: =SUM(U83:U87) -> 0 | V88: =SUM(V83:V87) -> 0 | W88: =SUM(W83:W87) -> 0 | X88: =SUM(X83:X87) -> 0 | Y88: =SUM(Y83:Y87) -> 0 | Z88: =SUM(Z83:Z87) -> 0 | AA88: =SUM(AA83:AA87) -> 0 | ... CA88: =SUM(CA83:CA87) -> 0 | CC88: =SUM(CC83:CC87) -> 0 | CD88: =SUM(CD83:CD87) -> 0 | CE88: =SUM(CE83:CE87) -> 0 | CF88: =SUM(CF83:CF87) -> 0 | CG88: =SUM(CG83:CG87) -> 0 | CI88: =CC88=L88 -> 1 | CJ88: =CD88=M88 -> 1 | CK88: =CE88=N88 -> 1 | CL88: =CF88=O88 -> 1 | CM88: =CG88=P88 -> 1
E90: OPEX
E91: OPEX - Temporary Workers | I91: =J29 -> 25 | J91: =J36 -> 13 | K91: =I91-J91 -> 12 | N91: =K91 -> 12 | O91: =N91 -> 12 | P91: =O91 -> 12 | Q91: Global Risk | R91: =IF(K91=P91, "", "Error") | AR91: =$P$91/12 -> 1 | AS91: =$P$91/12 -> 1 | AT91: =$P$91/12 -> 1 | AU91: =$P$91/12 -> 1 | AV91: =$P$91/12 -> 1 | AW91: =$P$91/12 -> 1 | AX91: =$P$91/12 -> 1 | AY91: =$P$91/12 -> 1 | ... CA91: =$P$91/12 -> 1 | CB91: =20/12 -> 1.6666667 | CC91: =SUMIFS($T91:$CA91, $T$1:$CA$1, CC$75) -> 0 | CE91: =SUMIFS($T91:$CA91, $T$1:$CA$1, CE$75) -> 12 | CF91: =SUMIFS($T91:$CA91, $T$1:$CA$1, CF$75) -> 12 | CG91: =SUMIFS($T91:$CA91, $T$1:$CA$1, CG$75) -> 12 | CI91: =CC91=L91 -> 1 | CJ91: =CD91=M91 -> 1 | CK91: =CE91=N91 -> 1 | CL91: =CF91=O91 -> 1 | CM91: =CG91=P91 -> 1
I92: 0 | J92: 0 | K92: =I92-J92 -> 0 | R92: =IF(K92=P92, "", "Error") | CC92: =SUMIFS($T92:$CA92, $T$1:$CA$1, CC$75) -> 0 | CD92: =SUMIFS($T92:$CA92, $T$1:$CA$1, CD$75) -> 0 | CE92: =SUMIFS($T92:$CA92, $T$1:$CA$1, CE$75) -> 0 | CF92: =SUMIFS($T92:$CA92, $T$1:$CA$1, CF$75) -> 0 | CG92: =SUMIFS($T92:$CA92, $T$1:$CA$1, CG$75) -> 0 | CI92: =CC92=L92 -> 1 | CJ92: =CD92=M92 -> 1 | CK92: =CE92=N92 -> 1 | CL92: =CF92=O92 -> 1 | CM92: =CG92=P92 -> 1
I93: 0 | J93: 0 | K93: =I93-J93 -> 0 | R93: =IF(K93=P93, "", "Error") | CC93: =SUMIFS($T93:$CA93, $T$1:$CA$1, CC$75) -> 0 | CD93: =SUMIFS($T93:$CA93, $T$1:$CA$1, CD$75) -> 0 | CE93: =SUMIFS($T93:$CA93, $T$1:$CA$1, CE$75) -> 0 | CF93: =SUMIFS($T93:$CA93, $T$1:$CA$1, CF$75) -> 0 | CG93: =SUMIFS($T93:$CA93, $T$1:$CA$1, CG$75) -> 0 | CI93: =CC93=L93 -> 1 | CJ93: =CD93=M93 -> 1 | CK93: =CE93=N93 -> 1 | CL93: =CF93=O93 -> 1 | CM93: =CG93=P93 -> 1
I94: 0 | J94: 0 | K94: =I94-J94 -> 0 | R94: =IF(K94=P94, "", "Error") | CC94: =SUMIFS($T94:$CA94, $T$1:$CA$1, CC$75) -> 0 | CD94: =SUMIFS($T94:$CA94, $T$1:$CA$1, CD$75) -> 0 | CE94: =SUMIFS($T94:$CA94, $T$1:$CA$1, CE$75) -> 0 | CF94: =SUMIFS($T94:$CA94, $T$1:$CA$1, CF$75) -> 0 | CG94: =SUMIFS($T94:$CA94, $T$1:$CA$1, CG$75) -> 0 | CI94: =CC94=L94 -> 1 | CJ94: =CD94=M94 -> 1 | CK94: =CE94=N94 -> 1 | CL94: =CF94=O94 -> 1 | CM94: =CG94=P94 -> 1
I95: 0 | J95: 0 | K95: =I95-J95 -> 0 | R95: =IF(K95=P95, "", "Error") | CC95: =SUMIFS($T95:$CA95, $T$1:$CA$1, CC$75) -> 0 | CD95: =SUMIFS($T95:$CA95, $T$1:$CA$1, CD$75) -> 0 | CE95: =SUMIFS($T95:$CA95, $T$1:$CA$1, CE$75) -> 0 | CF95: =SUMIFS($T95:$CA95, $T$1:$CA$1, CF$75) -> 0 | CG95: =SUMIFS($T95:$CA95, $T$1:$CA$1, CG$75) -> 0 | CI95: =CC95=L95 -> 1 | CJ95: =CD95=M95 -> 1 | CK95: =CE95=N95 -> 1 | CL95: =CF95=O95 -> 1 | CM95: =CG95=P95 -> 1
E96: OpEx subtotal | I96: =SUM(I91:I95) -> 25 | J96: =SUM(J91:J95) -> 13 | K96: =SUM(K91:K95) -> 12 | L96: =SUM(L91:L95) -> 0 | M96: =SUM(M91:M95) -> 0 | N96: =SUM(N91:N95) -> 12 | O96: =SUM(O91:O95) -> 12 | P96: =SUM(P91:P95) -> 12 | T96: =SUM(T91:T95) -> 0 | U96: =SUM(U91:U95) -> 0 | V96: =SUM(V91:V95) -> 0 | W96: =SUM(W91:W95) -> 0 | X96: =SUM(X91:X95) -> 0 | Y96: =SUM(Y91:Y95) -> 0 | Z96: =SUM(Z91:Z95) -> 0 | AA96: =SUM(AA91:AA95) -> 0 | ... CA96: =SUM(CA91:CA95) -> 1 | CC96: =SUM(CC91:CC95) -> 0 | CD96: =SUM(CD91:CD95) -> 0 | CE96: =SUM(CE91:CE95) -> 12 | CF96: =SUM(CF91:CF95) -> 12 | CG96: =SUM(CG91:CG95) -> 12 | CI96: =CC96=L96 -> 1 | CJ96: =CD96=M96 -> 1 | CK96: =CE96=N96 -> 1 | CL96: =CF96=O96 -> 1 | CM96: =CG96=P96 -> 1
E100: Recurring Benefits Total | I100: =SUM(I80, I88, I96) -> 25 | J100: =SUM(J80, J88, J96) -> 13 | K100: =SUM(-K80, K88, K96) -> 12 | L100: =SUM(L80, L88, L96) -> 0 | M100: =SUM(M80, M88, M96) -> 0 | N100: =SUM(N80, N88, N96) -> 12 | O100: =SUM(O80, O88, O96) -> 12 | P100: =SUM(P80, P88, P96) -> 12 | T100: =SUM(T80, T88, T96) -> 0 | U100: =SUM(U80, U88, U96) -> 0 | V100: =SUM(V80, V88, V96) -> 0 | W100: =SUM(W80, W88, W96) -> 0 | X100: =SUM(X80, X88, X96) -> 0 | Y100: =SUM(Y80, Y88, Y96) -> 0 | Z100: =SUM(Z80, Z88, Z96) -> 0 | AA100: =SUM(AA80, AA88, AA96) -> 0 | ... CA100: =SUM(CA80, CA88, CA96) -> 1 | CC100: =SUM(CC80, CC88, CC96) -> 0 | CD100: =SUM(CD80, CD88, CD96) -> 0 | CE100: =SUM(CE80, CE88, CE96) -> 12 | CF100: =SUM(CF80, CF88, CF96) -> 12 | CG100: =SUM(CG80, CG88, CG96) -> 12 | CH100: =SUM(CH80, CH88, CH96) -> 0 | CI100: =CC100=L100 -> 1 | CJ100: =CD100=M100 -> 1 | CK100: =CE100=N100 -> 1 | CL100: =CF100=O100 -> 1 | CM100: =CG100=P100 -> 1
D102: RECURRING COSTS TO ACHIEVE IMPACT | H102: Comment | I102: Baseline | J102: Goal | K102: Ann. Run Rate | L102: 2026 | M102: =L102+1 -> 2027 | N102: =M102+1 -> 2028 | O102: =N102+1 -> 2029 | P102: =O102+1 -> 2030 | Q102: Impacted BU | R102: Check | T102: 46023 | U102: =EOMONTH(T102, 1) -> 46081 | V102: =EOMONTH(U102, 1) -> 46112 | W102: =EOMONTH(V102, 1) -> 46142 | X102: =EOMONTH(W102, 1) -> 46173 | Y102: =EOMONTH(X102, 1) -> 46203 | Z102: =EOMONTH(Y102, 1) -> 46234 | AA102: =EOMONTH(Z102, 1) -> 46265 | AB102: =EOMONTH(AA102, 1) -> 46295 | ... CA102: =EOMONTH(BZ102, 1) -> 47848 | CC102: 2026 | CD102: =CC102+1 -> 2027 | CE102: =CD102+1 -> 2028 | CF102: =CE102+1 -> 2029 | CG102: =CF102+1 -> 2030 | CI102: 2026 | CJ102: =CI102+1 -> 2027 | CK102: =CJ102+1 -> 2028 | CL102: =CK102+1 -> 2029 | CM102: =CL102+1 -> 2030
E103: $USD M | I103: FY25 Hist. | J103: Future State | K103: Increment
E104: Revenue
I105: 0 | J105: 0 | K105: =J105-I105 -> 0 | R105: =IF(K105=P105, "", "Error") | CC105: =SUMIFS($T105:$CA105, $T$1:$CA$1, CC$75) -> 0 | CD105: =SUMIFS($T105:$CA105, $T$1:$CA$1, CD$75) -> 0 | CE105: =SUMIFS($T105:$CA105, $T$1:$CA$1, CE$75) -> 0 | CF105: =SUMIFS($T105:$CA105, $T$1:$CA$1, CF$75) -> 0 | CG105: =SUMIFS($T105:$CA105, $T$1:$CA$1, CG$75) -> 0 | CI105: =CC105=L105 -> 1 | CJ105: =CD105=M105 -> 1 | CK105: =CE105=N105 -> 1 | CL105: =CF105=O105 -> 1 | CM105: =CG105=P105 -> 1
I106: 0 | J106: 0 | K106: =J106-I106 -> 0 | R106: =IF(K106=P106, "", "Error") | CC106: =SUMIFS($T106:$CA106, $T$1:$CA$1, CC$75) -> 0 | CD106: =SUMIFS($T106:$CA106, $T$1:$CA$1, CD$75) -> 0 | CE106: =SUMIFS($T106:$CA106, $T$1:$CA$1, CE$75) -> 0 | CF106: =SUMIFS($T106:$CA106, $T$1:$CA$1, CF$75) -> 0 | CG106: =SUMIFS($T106:$CA106, $T$1:$CA$1, CG$75) -> 0 | CI106: =CC106=L106 -> 1 | CJ106: =CD106=M106 -> 1 | CK106: =CE106=N106 -> 1 | CL106: =CF106=O106 -> 1 | CM106: =CG106=P106 -> 1
E107: Revenue Subtotal | I107: =SUM(I105:I106) -> 0 | J107: =SUM(J105:J106) -> 0 | K107: =SUM(K105:K106) -> 0 | L107: =SUM(L105:L106) -> 0 | M107: =SUM(M105:M106) -> 0 | N107: =SUM(N105:N106) -> 0 | O107: =SUM(O105:O106) -> 0 | P107: =SUM(P105:P106) -> 0 | T107: =SUM(T105:T106) -> 0 | U107: =SUM(U105:U106) -> 0 | V107: =SUM(V105:V106) -> 0 | W107: =SUM(W105:W106) -> 0 | X107: =SUM(X105:X106) -> 0 | Y107: =SUM(Y105:Y106) -> 0 | Z107: =SUM(Z105:Z106) -> 0 | AA107: =SUM(AA105:AA106) -> 0 | ... CA107: =SUM(CA105:CA106) -> 0 | CC107: =SUM(CC105:CC106) -> 0 | CD107: =SUM(CD105:CD106) -> 0 | CE107: =SUM(CE105:CE106) -> 0 | CF107: =SUM(CF105:CF106) -> 0 | CG107: =SUM(CG105:CG106) -> 0 | CI107: =CC107=L107 -> 1 | CJ107: =CD107=M107 -> 1 | CK107: =CE107=N107 -> 1 | CL107: =CF107=O107 -> 1 | CM107: =CG107=P107 -> 1
E109: Cost of Sales
I110: 0 | J110: 0 | K110: =J110-I110 -> 0 | R110: =IF(K110=P110, "", "Error") | CC110: =SUMIFS($T110:$CA110, $T$1:$CA$1, CC$75) -> 0 | CD110: =SUMIFS($T110:$CA110, $T$1:$CA$1, CD$75) -> 0 | CE110: =SUMIFS($T110:$CA110, $T$1:$CA$1, CE$75) -> 0 | CF110: =SUMIFS($T110:$CA110, $T$1:$CA$1, CF$75) -> 0 | CG110: =SUMIFS($T110:$CA110, $T$1:$CA$1, CG$75) -> 0 | CI110: =CC110=L110 -> 1 | CJ110: =CD110=M110 -> 1 | CK110: =CE110=N110 -> 1 | CL110: =CF110=O110 -> 1 | CM110: =CG110=P110 -> 1
I111: 0 | J111: 0 | K111: =J111-I111 -> 0 | R111: =IF(K111=P111, "", "Error") | CC111: =SUMIFS($T111:$CA111, $T$1:$CA$1, CC$75) -> 0 | CD111: =SUMIFS($T111:$CA111, $T$1:$CA$1, CD$75) -> 0 | CE111: =SUMIFS($T111:$CA111, $T$1:$CA$1, CE$75) -> 0 | CF111: =SUMIFS($T111:$CA111, $T$1:$CA$1, CF$75) -> 0 | CG111: =SUMIFS($T111:$CA111, $T$1:$CA$1, CG$75) -> 0 | CI111: =CC111=L111 -> 1 | CJ111: =CD111=M111 -> 1 | CK111: =CE111=N111 -> 1 | CL111: =CF111=O111 -> 1 | CM111: =CG111=P111 -> 1
I112: 0 | J112: 0 | K112: =J112-I112 -> 0 | R112: =IF(K112=P112, "", "Error") | CC112: =SUMIFS($T112:$CA112, $T$1:$CA$1, CC$75) -> 0 | CD112: =SUMIFS($T112:$CA112, $T$1:$CA$1, CD$75) -> 0 | CE112: =SUMIFS($T112:$CA112, $T$1:$CA$1, CE$75) -> 0 | CF112: =SUMIFS($T112:$CA112, $T$1:$CA$1, CF$75) -> 0 | CG112: =SUMIFS($T112:$CA112, $T$1:$CA$1, CG$75) -> 0 | CI112: =CC112=L112 -> 1 | CJ112: =CD112=M112 -> 1 | CK112: =CE112=N112 -> 1 | CL112: =CF112=O112 -> 1 | CM112: =CG112=P112 -> 1
I113: 0 | J113: 0 | K113: =J113-I113 -> 0 | R113: =IF(K113=P113, "", "Error") | CC113: =SUMIFS($T113:$CA113, $T$1:$CA$1, CC$75) -> 0 | CD113: =SUMIFS($T113:$CA113, $T$1:$CA$1, CD$75) -> 0 | CE113: =SUMIFS($T113:$CA113, $T$1:$CA$1, CE$75) -> 0 | CF113: =SUMIFS($T113:$CA113, $T$1:$CA$1, CF$75) -> 0 | CG113: =SUMIFS($T113:$CA113, $T$1:$CA$1, CG$75) -> 0 | CI113: =CC113=L113 -> 1 | CJ113: =CD113=M113 -> 1 | CK113: =CE113=N113 -> 1 | CL113: =CF113=O113 -> 1 | CM113: =CG113=P113 -> 1
E115: Cost of Sales Subtotal | I115: =SUM(I110:I114) -> 0 | J115: =SUM(J110:J114) -> 0 | K115: =SUM(K110:K114) -> 0 | L115: =SUM(L110:L114) -> 0 | M115: =SUM(M110:M114) -> 0 | N115: =SUM(N110:N114) -> 0 | O115: =SUM(O110:O114) -> 0 | P115: =SUM(P110:P114) -> 0 | T115: =SUM(T110:T114) -> 0 | U115: =SUM(U110:U114) -> 0 | V115: =SUM(V110:V114) -> 0 | W115: =SUM(W110:W114) -> 0 | X115: =SUM(X110:X114) -> 0 | Y115: =SUM(Y110:Y114) -> 0 | Z115: =SUM(Z110:Z114) -> 0 | AA115: =SUM(AA110:AA114) -> 0 | ... CA115: =SUM(CA110:CA114) -> 0 | CC115: =SUM(CC110:CC114) -> 0 | CD115: =SUM(CD110:CD114) -> 0 | CE115: =SUM(CE110:CE114) -> 0 | CF115: =SUM(CF110:CF114) -> 0 | CG115: =SUM(CG110:CG114) -> 0 | CI115: =CC115=L115 -> 1 | CJ115: =CD115=M115 -> 1 | CK115: =CE115=N115 -> 1 | CL115: =CF115=O115 -> 1 | CM115: =CG115=P115 -> 1
E117: OPEX
E118: OPEX - SaaS SW | H118: Platform licencing & LLM inference | I118: 0 | J118: 3.6 | K118: =J118-I118 -> 3.6 | N118: 3.6 | O118: 3.6 | P118: 3.6 | R118: =IF(K118=P118, "", "Error") | AR118: =3.6/12 -> 0.3 | AS118: =3.6/12 -> 0.3 | AT118: =3.6/12 -> 0.3 | AU118: =3.6/12 -> 0.3 | AV118: =3.6/12 -> 0.3 | AW118: =3.6/12 -> 0.3 | AX118: =3.6/12 -> 0.3 | AY118: =3.6/12 -> 0.3 | ... CA118: =3.6/12 -> 0.3 | CC118: =SUMIFS($T118:$CA118, $T$1:$CA$1, CC$75) -> 0 | CD118: =SUMIFS($T118:$CA118, $T$1:$CA$1, CD$75) -> 0 | CE118: =SUMIFS($T118:$CA118, $T$1:$CA$1, CE$75) -> 3.6 | CF118: =SUMIFS($T118:$CA118, $T$1:$CA$1, CF$75) -> 3.6 | CG118: =SUMIFS($T118:$CA118, $T$1:$CA$1, CG$75) -> 3.6 | CI118: =CC118=L118 -> 1 | CJ118: =CD118=M118 -> 1 | CK118: =CE118=N118 -> 1 | CL118: =CF118=O118 -> 1 | CM118: =CG118=P118 -> 1
E119: OPEX - Cloud Services | H119: Cloud infra | I119: 0 | J119: 1.2 | K119: =J119-I119 -> 1.2 | M119: 1.2 | N119: 1.2 | O119: 1.2 | P119: 1.2 | R119: =IF(K119=P119, "", "Error") | AF119: =1.2/12 -> 0.1 | AG119: =1.2/12 -> 0.1 | AH119: =1.2/12 -> 0.1 | AI119: =1.2/12 -> 0.1 | AJ119: =1.2/12 -> 0.1 | AK119: =1.2/12 -> 0.1 | AL119: =1.2/12 -> 0.1 | AM119: =1.2/12 -> 0.1 | ... CA119: =1.2/12 -> 0.1 | CC119: =SUMIFS($T119:$CA119, $T$1:$CA$1, CC$75) -> 0 | CD119: =SUMIFS($T119:$CA119, $T$1:$CA$1, CD$75) -> 1.2 | CE119: =SUMIFS($T119:$CA119, $T$1:$CA$1, CE$75) -> 1.2 | CF119: =SUMIFS($T119:$CA119, $T$1:$CA$1, CF$75) -> 1.2 | CG119: =SUMIFS($T119:$CA119, $T$1:$CA$1, CG$75) -> 1.2 | CI119: =CC119=L119 -> 1 | CJ119: =CD119=M119 -> 1 | CK119: =CE119=N119 -> 1 | CL119: =CF119=O119 -> 1 | CM119: =CG119=P119 -> 1
CC120: =SUMIFS($T120:$CA120, $T$1:$CA$1, CC$75) -> 0 | CD120: =SUMIFS($T120:$CA120, $T$1:$CA$1, CD$75) -> 0 | CE120: =SUMIFS($T120:$CA120, $T$1:$CA$1, CE$75) -> 0 | CF120: =SUMIFS($T120:$CA120, $T$1:$CA$1, CF$75) -> 0 | CG120: =SUMIFS($T120:$CA120, $T$1:$CA$1, CG$75) -> 0 | CI120: =CC120=L120 -> 1 | CJ120: =CD120=M120 -> 1 | CK120: =CE120=N120 -> 1 | CL120: =CF120=O120 -> 1 | CM120: =CG120=P120 -> 1
J121: 0 | K121: =J121-I121 -> 0 | R121: =IF(K121=P121, "", "Error") | CC121: =SUMIFS($T121:$CA121, $T$1:$CA$1, CC$75) -> 0 | CD121: =SUMIFS($T121:$CA121, $T$1:$CA$1, CD$75) -> 0 | CE121: =SUMIFS($T121:$CA121, $T$1:$CA$1, CE$75) -> 0 | CF121: =SUMIFS($T121:$CA121, $T$1:$CA$1, CF$75) -> 0 | CG121: =SUMIFS($T121:$CA121, $T$1:$CA$1, CG$75) -> 0 | CI121: =CC121=L121 -> 1 | CJ121: =CD121=M121 -> 1 | CK121: =CE121=N121 -> 1 | CL121: =CF121=O121 -> 1 | CM121: =CG121=P121 -> 1
I122: 0 | J122: 0 | K122: =J122-I122 -> 0 | R122: =IF(K122=P122, "", "Error") | CC122: =SUMIFS($T122:$CA122, $T$1:$CA$1, CC$75) -> 0 | CD122: =SUMIFS($T122:$CA122, $T$1:$CA$1, CD$75) -> 0 | CE122: =SUMIFS($T122:$CA122, $T$1:$CA$1, CE$75) -> 0 | CF122: =SUMIFS($T122:$CA122, $T$1:$CA$1, CF$75) -> 0 | CG122: =SUMIFS($T122:$CA122, $T$1:$CA$1, CG$75) -> 0 | CI122: =CC122=L122 -> 1 | CJ122: =CD122=M122 -> 1 | CK122: =CE122=N122 -> 1 | CL122: =CF122=O122 -> 1 | CM122: =CG122=P122 -> 1
E123: OpEx subtotal | I123: =SUM(I118:I122) -> 0 | J123: =SUM(J118:J122) -> 4.8 | K123: =SUM(K118:K122) -> 4.8 | L123: =SUM(L118:L122) -> 0 | M123: =SUM(M118:M122) -> 1.2 | N123: =SUM(N118:N122) -> 4.8 | O123: =SUM(O118:O122) -> 4.8 | P123: =SUM(P118:P122) -> 4.8 | T123: =SUM(T118:T122) -> 0 | U123: =SUM(U118:U122) -> 0 | V123: =SUM(V118:V122) -> 0 | W123: =SUM(W118:W122) -> 0 | X123: =SUM(X118:X122) -> 0 | Y123: =SUM(Y118:Y122) -> 0 | Z123: =SUM(Z118:Z122) -> 0 | AA123: =SUM(AA118:AA122) -> 0 | ... CA123: =SUM(CA118:CA122) -> 0.4 | CC123: =SUM(CC118:CC122) -> 0 | CD123: =SUM(CD118:CD122) -> 1.2 | CE123: =SUM(CE118:CE122) -> 4.8 | CF123: =SUM(CF118:CF122) -> 4.8 | CG123: =SUM(CG118:CG122) -> 4.8 | CI123: =CC123=L123 -> 1 | CJ123: =CD123=M123 -> 1 | CK123: =CE123=N123 -> 1 | CL123: =CF123=O123 -> 1 | CM123: =CG123=P123 -> 1
E126: Recurring Costs Total | I126: =SUM(-I107, I115, I123) -> 0 | J126: =SUM(-J107, J115, J123) -> 4.8 | K126: =SUM(-K107, K115, K123) -> 4.8 | L126: =SUM(-L107, L115, L123) -> 0 | M126: =SUM(-M107, M115, M123) -> 1.2 | N126: =SUM(-N107, N115, N123) -> 4.8 | O126: =SUM(-O107, O115, O123) -> 4.8 | P126: =SUM(-P107, P115, P123) -> 4.8 | T126: =SUM(-T107, T115, T123) -> 0 | U126: =SUM(-U107, U115, U123) -> 0 | V126: =SUM(-V107, V115, V123) -> 0 | W126: =SUM(-W107, W115, W123) -> 0 | X126: =SUM(-X107, X115, X123) -> 0 | Y126: =SUM(-Y107, Y115, Y123) -> 0 | Z126: =SUM(-Z107, Z115, Z123) -> 0 | AA126: =SUM(-AA107, AA115, AA123) -> 0 | ... CA126: =SUM(-CA107, CA115, CA123) -> 0.4 | CC126: =SUM(-CC107, CC115, CC123) -> 0 | CD126: =SUM(-CD107, CD115, CD123) -> 1.2 | CE126: =SUM(-CE107, CE115, CE123) -> 4.8 | CF126: =SUM(-CF107, CF115, CF123) -> 4.8 | CG126: =SUM(-CG107, CG115, CG123) -> 4.8 | CI126: =CC126=L126 -> 1 | CJ126: =CD126=M126 -> 1 | CK126: =CE126=N126 -> 1 | CL126: =CF126=O126 -> 1 | CM126: =CG126=P126 -> 1
E128: Net Recurring Benefit | I128: =SUM(I100, -I126) -> 25 | J128: =SUM(J100, -J126) -> 8.2 | K128: =SUM(K100, -K126) -> 7.2 | L128: =SUM(L100, -L126) -> 0 | M128: =SUM(M100, -M126) -> -1.2 | N128: =SUM(N100, -N126) -> 7.2 | O128: =SUM(O100, -O126) -> 7.2 | P128: =SUM(P100, -P126) -> 7.2 | R128: =IF(K128=P128, "", "Error") | T128: =SUM(T100, -T126) -> 0 | U128: =SUM(U100, -U126) -> 0 | V128: =SUM(V100, -V126) -> 0 | W128: =SUM(W100, -W126) -> 0 | X128: =SUM(X100, -X126) -> 0 | Y128: =SUM(Y100, -Y126) -> 0 | Z128: =SUM(Z100, -Z126) -> 0 | AA128: =SUM(AA100, -AA126) -> 0 | ... CA128: =SUM(CA100, -CA126) -> 0.6 | CC128: =SUM(CC100, -CC126) -> 0 | CD128: =SUM(CD100, -CD126) -> -1.2 | CE128: =SUM(CE100, -CE126) -> 7.2 | CF128: =SUM(CF100, -CF126) -> 7.2 | CG128: =SUM(CG100, -CG126) -> 7.2 | CI128: =CC128=L128 -> 1 | CJ128: =CD128=M128 -> 1 | CK128: =CE128=N128 -> 1 | CL128: =CF128=O128 -> 1 | CM128: =CG128=P128 -> 1
C131: SECTION III - ONE-TIME IMPLEMENTATION | CC131: ANNUAL SUMMARY | CI131: CHECK CELLS
T133: 2026 | AF133: 2027 | AR133: 2028 | BD133: 2029 | BP133: 2030
D134: ONE-TIME BENEFITS | K134: Comment | L134: 2026 | M134: =L134+1 -> 2027 | N134: =M134+1 -> 2028 | O134: =N134+1 -> 2029 | P134: =O134+1 -> 2030 | Q134: Impacted BU | T134: 46023 | U134: =EOMONTH(T134, 1) -> 46081 | V134: =EOMONTH(U134, 1) -> 46112 | W134: =EOMONTH(V134, 1) -> 46142 | X134: =EOMONTH(W134, 1) -> 46173 | Y134: =EOMONTH(X134, 1) -> 46203 | Z134: =EOMONTH(Y134, 1) -> 46234 | AA134: =EOMONTH(Z134, 1) -> 46265 | AB134: =EOMONTH(AA134, 1) -> 46295 | ... CA134: =EOMONTH(BZ134, 1) -> 47848 | CC134: 2026 | CD134: =CC134+1 -> 2027 | CE134: =CD134+1 -> 2028 | CF134: =CE134+1 -> 2029 | CG134: =CF134+1 -> 2030 | CI134: 2026 | CJ134: =CI134+1 -> 2027 | CK134: =CJ134+1 -> 2028 | CL134: =CK134+1 -> 2029 | CM134: =CL134+1 -> 2030
E136: Working Capital
CC137: =SUMIFS($T137:$CA137, $T$1:$CA$1, CC$75) -> 0 | CD137: =SUMIFS($T137:$CA137, $T$1:$CA$1, CD$75) -> 0 | CE137: =SUMIFS($T137:$CA137, $T$1:$CA$1, CE$75) -> 0 | CF137: =SUMIFS($T137:$CA137, $T$1:$CA$1, CF$75) -> 0 | CG137: =SUMIFS($T137:$CA137, $T$1:$CA$1, CG$75) -> 0 | CI137: =CC137=L137 -> 1 | CJ137: =CD137=M137 -> 1 | CK137: =CE137=N137 -> 1 | CL137: =CF137=O137 -> 1 | CM137: =CG137=P137 -> 1
CC138: =SUMIFS($T138:$CA138, $T$1:$CA$1, CC$75) -> 0 | CD138: =SUMIFS($T138:$CA138, $T$1:$CA$1, CD$75) -> 0 | CE138: =SUMIFS($T138:$CA138, $T$1:$CA$1, CE$75) -> 0 | CF138: =SUMIFS($T138:$CA138, $T$1:$CA$1, CF$75) -> 0 | CG138: =SUMIFS($T138:$CA138, $T$1:$CA$1, CG$75) -> 0 | CI138: =CC138=L138 -> 1 | CJ138: =CD138=M138 -> 1 | CK138: =CE138=N138 -> 1 | CL138: =CF138=O138 -> 1 | CM138: =CG138=P138 -> 1
E139: Working Capital Subtotal | L139: =SUM(L137:L138) -> 0 | M139: =SUM(M137:M138) -> 0 | N139: =SUM(N137:N138) -> 0 | O139: =SUM(O137:O138) -> 0 | P139: =SUM(P137:P138) -> 0 | T139: =SUM(T137:T138) -> 0 | U139: =SUM(U137:U138) -> 0 | V139: =SUM(V137:V138) -> 0 | W139: =SUM(W137:W138) -> 0 | X139: =SUM(X137:X138) -> 0 | Y139: =SUM(Y137:Y138) -> 0 | Z139: =SUM(Z137:Z138) -> 0 | AA139: =SUM(AA137:AA138) -> 0 | ... CA139: =SUM(CA137:CA138) -> 0 | CC139: =SUM(CC137:CC138) -> 0 | CD139: =SUM(CD137:CD138) -> 0 | CE139: =SUM(CE137:CE138) -> 0 | CF139: =SUM(CF137:CF138) -> 0 | CG139: =SUM(CG137:CG138) -> 0 | CI139: =CC139=L139 -> 1 | CJ139: =CD139=M139 -> 1 | CK139: =CE139=N139 -> 1 | CL139: =CF139=O139 -> 1 | CM139: =CG139=P139 -> 1
...

Sheet Rate Card
B2: RATE CARD — people-cost engine (shared by all initiative models)
B4: Blue cells with yellow fill = inputs you can change. Black = formulas. All initiative models pull the blended rate and policy tables from this sheet.
B6: 1. RATE BASIS
B8: Rate basis for people costs | D8: Yearly | F8: Choose how role rates are quoted, then TYPE YOUR RATES in the matching column of the role table below (Yearly->col D, Monthly->col E, Hourly->col F). The other columns show derived equivalents until you overwrite them. Hourly => monthly = $/hr x hours/day x days/month.
B10: Working hours per day | D10: 8 | F10: Used only when rate basis = Hourly.
B11: Billable days per month | D11: 21
B12: Months per year (for yearly basis) | D12: 12
B14: 2. STANDARD TEAM COMPOSITION & BLENDED RATE
B16: Role | C16: # in std team | D16: Yearly rate ($/yr) | E16: Monthly rate ($/mo) | F16: Hourly rate ($/hr) | G16: Monthly used ($/mo) | H16: Team cost ($/mo) | I16: Source / notes
B17: Engineer | C17: 3 | D17: 180000 | E17: =IF(D17="",0,D17/$D$12) -> 15000 | F17: =IF(D17="",0,E17/($D$10*$D$11)) -> 89.285714 | G17: =IF($D$8="Hourly",F17*$D$10*$D$11,IF($D$8="Monthly",E17,IF(D17="",0,D17/$D$12))) -> 15000 | H17: =IF(C17="",0,C17*G17) -> 45000
B18: QA Engineer | C18: 2 | D18: 140000 | E18: =IF(D18="",0,D18/$D$12) -> 11666.667 | F18: =IF(D18="",0,E18/($D$10*$D$11)) -> 69.444444 | G18: =IF($D$8="Hourly",F18*$D$10*$D$11,IF($D$8="Monthly",E18,IF(D18="",0,D18/$D$12))) -> 11666.667 | H18: =IF(C18="",0,C18*G18) -> 23333.333
B19: Solution Architect | C19: 1 | D19: 220000 | E19: =IF(D19="",0,D19/$D$12) -> 18333.333 | F19: =IF(D19="",0,E19/($D$10*$D$11)) -> 109.12698 | G19: =IF($D$8="Hourly",F19*$D$10*$D$11,IF($D$8="Monthly",E19,IF(D19="",0,D19/$D$12))) -> 18333.333 | H19: =IF(C19="",0,C19*G19) -> 18333.333
B20: Product Manager | C20: 1 | D20: 190000 | E20: =IF(D20="",0,D20/$D$12) -> 15833.333 | F20: =IF(D20="",0,E20/($D$10*$D$11)) -> 94.246032 | G20: =IF($D$8="Hourly",F20*$D$10*$D$11,IF($D$8="Monthly",E20,IF(D20="",0,D20/$D$12))) -> 15833.333 | H20: =IF(C20="",0,C20*G20) -> 15833.333
B21: Data Engineer | C21: 1 | D21: 185000 | E21: =IF(D21="",0,D21/$D$12) -> 15416.667 | F21: =IF(D21="",0,E21/($D$10*$D$11)) -> 91.765873 | G21: =IF($D$8="Hourly",F21*$D$10*$D$11,IF($D$8="Monthly",E21,IF(D21="",0,D21/$D$12))) -> 15416.667 | H21: =IF(C21="",0,C21*G21) -> 15416.667
B22: ML Engineer | C22: 1 | D22: 210000 | E22: =IF(D22="",0,D22/$D$12) -> 17500 | F22: =IF(D22="",0,E22/($D$10*$D$11)) -> 104.16667 | G22: =IF($D$8="Hourly",F22*$D$10*$D$11,IF($D$8="Monthly",E22,IF(D22="",0,D22/$D$12))) -> 17500 | H22: =IF(C22="",0,C22*G22) -> 17500
B23: Program Manager | C23: 1 | D23: 170000 | E23: =IF(D23="",0,D23/$D$12) -> 14166.667 | F23: =IF(D23="",0,E23/($D$10*$D$11)) -> 84.325397 | G23: =IF($D$8="Hourly",F23*$D$10*$D$11,IF($D$8="Monthly",E23,IF(D23="",0,D23/$D$12))) -> 14166.667 | H23: =IF(C23="",0,C23*G23) -> 14166.667
E24: =IF(D24="",0,D24/$D$12) -> 0 | F24: =IF(D24="",0,E24/($D$10*$D$11)) -> 0 | G24: =IF($D$8="Hourly",F24*$D$10*$D$11,IF($D$8="Monthly",E24,IF(D24="",0,D24/$D$12))) -> 0 | H24: =IF(C24="",0,C24*G24) -> 0 | I24: spare row — add roles as team shape is refined
E25: =IF(D25="",0,D25/$D$12) -> 0 | F25: =IF(D25="",0,E25/($D$10*$D$11)) -> 0 | G25: =IF($D$8="Hourly",F25*$D$10*$D$11,IF($D$8="Monthly",E25,IF(D25="",0,D25/$D$12))) -> 0 | H25: =IF(C25="",0,C25*G25) -> 0 | I25: spare row — add roles as team shape is refined
E26: =IF(D26="",0,D26/$D$12) -> 0 | F26: =IF(D26="",0,E26/($D$10*$D$11)) -> 0 | G26: =IF($D$8="Hourly",F26*$D$10*$D$11,IF($D$8="Monthly",E26,IF(D26="",0,D26/$D$12))) -> 0 | H26: =IF(C26="",0,C26*G26) -> 0 | I26: spare row — add roles as team shape is refined
B27: Total standard team | C27: =SUM(C17:C26) -> 10 | H27: =SUM(H17:H26) -> 149583.33
B29: BLENDED RATE — per team member | G29: =IF(C27=0,0,H27/C27) -> 14958.333 | H29: $/person/month | I29: Weighted average monthly cost of one member of the standard team. Initiative milestone tables use this unless a rate override is entered.
G30: =G29*$D$12 -> 179500 | H30: $/person/year
G31: =G29/($D$10*$D$11) -> 89.037698 | H31: $/person/hour
B33: 3. CONTINGENCY FACTOR REFERENCE
B35: Complexity / risk level | C35: Factor | F35: Based on the complexity and risks to deliver the milestone.
B36: Low | C36: 0.1
B37: Medium | C37: 0.15
B38: High | C38: 0.2
B39: Very high | C39: 0.5
B42: 4. CAPITALIZATION POLICY (labor) — default % of milestone labor capitalizable
B44: Milestone | C44: Cap % | F44: Share of labor cost treated as CapEx (feeds WAVE 'Capital Expenditures'); remainder is expensed one-time cost (WAVE 'OTC'). Defaults follow a typical internal-use software policy (ASC 350-40): application development/build stage capitalizable, planning and post-launch expensed. CONFIRM WITH FINANCE — initiative models reference these cells, override there if needed.
B45: Plan / Design | C45: 0
B46: Build / Test | C46: 0.8
B47: Pilot / Change Mgmt. | C47: 0
B48: Scale / Run | C48: 0
B49: Non-labor one-time (default) | C49: 0
B51: 5. NOTES
B52: • Role rates are PLACEHOLDERS — replace with the PayPal/FP&A rate card. For reference, the Servicing S2 model uses a $200,000/yr blended loaded delivery FTE rate (+10% delivery risk) and $180,000/yr for run-team FTEs.
B53: • Team composition mirrors the standard AAO delivery-pod thinking; add/remove roles as the initiative team shapes firm up (spare rows provided).
B54: • Build/Test capitalization default of 80% follows a typical internal-use software policy (application development stage capitalizable) — CONFIRM WITH FINANCE before S3.

Sheet Summary
B2: SDLC WORKSTREAM — PORTFOLIO SUMMARY ($M)
B3: All figures link to the initiative WAVE sheets. Payback/NPV per WAVE Section IV.
B5: Initiative | C5: NRB run rate | D5: NRB 2026 | E5: NRB 2027 | F5: NRB 2028 | G5: NRB 2029 | H5: NRB 2030 | I5: One-time cost (5yr) | J5: Run cost 2030 | K5: NPV (5yr) | L5: Payback (yrs)
B6: SDLC-1 — Agentic Loop Engineering | C6: ='SDLC-1 WAVE'!$K$117 -> 0 | D6: ='SDLC-1 WAVE'!$L$117 -> 0 | E6: ='SDLC-1 WAVE'!$M$117 -> 0 | F6: ='SDLC-1 WAVE'!$N$117 -> 0 | G6: ='SDLC-1 WAVE'!$O$117 -> 0 | H6: ='SDLC-1 WAVE'!$P$117 -> 0 | I6: =SUM('SDLC-1 WAVE'!$L$147:$P$147) -> 1.5247089 | J6: ='SDLC-1 WAVE'!$P$115 -> 0 | K6: ='SDLC-1 WAVE'!$G$168 -> -1.2988552 | L6: ='SDLC-1 WAVE'!$G$165 -> >5
B7: SDLC-2 — PDLC Re-imagination | C7: ='SDLC-2 WAVE'!$K$117 -> 0 | D7: ='SDLC-2 WAVE'!$L$117 -> 0 | E7: ='SDLC-2 WAVE'!$M$117 -> 0 | F7: ='SDLC-2 WAVE'!$N$117 -> 0 | G7: ='SDLC-2 WAVE'!$O$117 -> 0 | H7: ='SDLC-2 WAVE'!$P$117 -> 0 | I7: =SUM('SDLC-2 WAVE'!$L$147:$P$147) -> 1.5247089 | J7: ='SDLC-2 WAVE'!$P$115 -> 0 | K7: ='SDLC-2 WAVE'!$G$168 -> -1.2863017 | L7: ='SDLC-2 WAVE'!$G$165 -> >5
B8: TOTAL — SDLC WORKSTREAM | C8: =SUM(C6:C7) -> 0 | D8: =SUM(D6:D7) -> 0 | E8: =SUM(E6:E7) -> 0 | F8: =SUM(F6:F7) -> 0 | G8: =SUM(G6:G7) -> 0 | H8: =SUM(H6:H7) -> 0 | I8: =SUM(I6:I7) -> 3.0494178 | J8: =SUM(J6:J7) -> 0
B10: Note: NPV and payback are not additive across initiatives; totals shown for benefit/cost columns only.
B11: Capitalization policy note: this file defaults Build/Test labor to 80% capitalizable (Rate Card) pending Finance sign-off; the Servicing file defaults to 0% to mirror the S2 model's all-cash treatment. Align the policy across workstreams with Finance before the S2 gate.

Sheet SDLC-1 Model
B2: SDLC-1 — Agentic Loop Engineering | INITIATIVE MODEL
B3: Workstream: SDLC (ELT sponsor: Srini | WSL: Pooja | IOs: Pooja, Aruna) • Model status: Structure ready; baselines PENDING data requests — see open items
T5: 2026 | U5: 2026 | V5: 2026 | W5: 2026 | X5: 2026 | Y5: 2026 | Z5: 2026 | AA5: 2026 | AB5: 2026 | AC5: 2026 | AD5: 2026 | AE5: 2026 | AF5: 2027 | AG5: 2027 | AH5: 2027 | AI5: 2027 | AJ5: 2027 | AK5: 2027 | AL5: 2027 | AM5: 2027 | AN5: 2027 | AO5: 2027 | AP5: 2027 | AQ5: 2027 | AR5: 2028 | AS5: 2028 | AT5: 2028 | AU5: 2028 | AV5: 2028 | AW5: 2028 | AX5: 2028 | AY5: 2028 | AZ5: 2028 | BA5: 2028 | BB5: 2028 | BC5: 2028 | BD5: 2029 | BE5: 2029 | BF5: 2029 | BG5: 2029 | BH5: 2029 | BI5: 2029 | BJ5: 2029 | BK5: 2029 | BL5: 2029 | BM5: 2029 | BN5: 2029 | BO5: 2029 | BP5: 2030 | BQ5: 2030 | BR5: 2030 | BS5: 2030 | BT5: 2030 | BU5: 2030 | BV5: 2030 | BW5: 2030 | BX5: 2030 | BY5: 2030 | BZ5: 2030 | CA5: 2030
B6: Monthly grid (Jan-26 → Dec-30) → | K6: Run rate | L6: 2026 | M6: 2027 | N6: 2028 | O6: 2029 | P6: 2030 | T6: =DATE(2026,1,31) -> 46053 | U6: =EOMONTH(T6,1) -> 46081 | V6: =EOMONTH(U6,1) -> 46112 | W6: =EOMONTH(V6,1) -> 46142 | X6: =EOMONTH(W6,1) -> 46173 | Y6: =EOMONTH(X6,1) -> 46203 | Z6: =EOMONTH(Y6,1) -> 46234 | AA6: =EOMONTH(Z6,1) -> 46265 | AB6: =EOMONTH(AA6,1) -> 46295 | ... CA6: =EOMONTH(BZ6,1) -> 47848
B8: 0. INITIATIVE & STATUS
B10: Initiative name | D10: Agentic loop engineering — raise engineering throughput on the residual addressable base
B11: Initiative owner | D11: Pooja (WSL) — initiative owner TBC | I11: confirm with workstream lead
B12: Impacted BU | D12: CTO / SDLC
B13: Go-live / Estimated L4 date | D13: =DATE(2027,5,1) -> 46508 | I13: Benefit ramp is gated on this date.
B15: Source: Workplan: 'Project Zenith Automation workplan and data requests vS_1.xlsx', SDLC tab + SDLC Data Requests tab
B16: Source: Impact ranges: Aug 13 deck pp. 9, 19–21; Board deck pp. 12, 22 (preliminary — Finance to validate)
B17: Open items to refine with initiative owner:
B18: – FTE/CW population and fully loaded cost baseline pending (SDLC data request #1 — Thom/Thanh (SDLC), ETO (PDLC)); all baseline inputs below are 0 until received.
B19: – Banked Code Assist savings to reconcile so the residual addressable base nets them out (W3 objective).
B20: – Adoption ramp by domain/role pending (request #3); 20-domain harness build plan shared by Pooja (request #12).
B21: – Token consumption benchmark by role shared for SDLC (request #11) — to be validated, then wire into run costs.
B22: – Build shape below mirrors the Servicing S2 delivery pod as a placeholder — refine with IOs before S3.
B24: 1. SIZING ASSUMPTIONS (blue = inputs — refine with initiative owner)
B26: Baseline / denominator (PENDING data request #1)
B27: CTO SWE IC FTE population — in scope | D27: 0 | E27: # FTE | F27: PENDING — placeholder, not data. Data request #1 (Thom/Thanh)
B28: CTO SWE CW population — in scope | D28: 0 | E28: # CW | F28: PENDING — placeholder, not data. Data request #1
B29: Avg fully loaded cost per SWE FTE | D29: 0 | E29: $/yr | F29: PENDING — placeholder, not data. Data request #1
B30: Avg fully loaded cost per CW | D30: 0 | E30: $/yr | F30: PENDING — placeholder, not data. Data request #1
B31: Code Assist savings already banked (annual) | D31: 0 | E31: $/yr | F31: PENDING — placeholder, not data. Reconcile with Finance; netted out of the addressable base to avoid double count
B32: Impact drivers (Aug 13 deck pp. 9, 19–21 — preliminary, Finance to validate)
B33: Incremental productivity uplift on residual base | D33: 0.15 | E33: % | F33: PLACEHOLDER pending validation — source materials cite ~$173–204M total SDLC opportunity
B34: Steady-state adoption (share of population on harness) | D34: 0.8 | E34: % | F34: PLACEHOLDER — adoption ramp by domain/role pending (request #3)
B35: Capture rate — capacity converted to bankable cost | D35: 0.65 | E35: % | F35: PLACEHOLDER — capacity-to-cost capture and redeployment logic to agree with Finance
B36: Investment uplifts (consistent with Servicing S2 standard)
B37: Programme management, % of build | D37: 0.08 | E37: % | F37: Same standard as Servicing S2 (8%)
B38: Contingency, % of build incl. PM | D38: 0.1 | E38: % | F38: Same standard as Servicing S2 (10%)
B39: (spare assumption row)
B40: (spare assumption row)
B42: 2. BENEFIT CALCULATION (steady-state annual run-rate)
B44: Total in-scope engineering labor base | D44: =($D$27*$D$29+$D$28*$D$30) -> 0 | E44: $/yr | F44: FTE x cost + CW x cost
B45: Residual addressable base (net of banked Code Assist) | D45: =MAX($D$44-$D$31,0) -> 0 | E45: $/yr
B46: Gross capacity value created | D46: =$D$45*$D$33*$D$34 -> 0 | E46: $/yr | F46: Residual base x productivity uplift x adoption
B47: Bankable annual benefit (steady state) | D47: =$D$46*$D$35 -> 0 | E47: $/yr | F47: x capture rate — the benefit line that feeds WAVE
B49: 3. RAMP & PHASING
B51: Months to full run rate after go-live (linear ramp) | D51: 12 | F51: Benefit starts at go-live and ramps linearly to steady state over this many months.
B52: Monthly ramp % (run-rate captured in month) | T52: =MIN(1,MAX(0,((YEAR(T$6)-YEAR($D$13))*12+MONTH(T$6)-MONTH($D$13)+0.5)/MAX($D$51,0.5))) -> 0 | U52: =MIN(1,MAX(0,((YEAR(U$6)-YEAR($D$13))*12+MONTH(U$6)-MONTH($D$13)+0.5)/MAX($D$51,0.5))) -> 0 | V52: =MIN(1,MAX(0,((YEAR(V$6)-YEAR($D$13))*12+MONTH(V$6)-MONTH($D$13)+0.5)/MAX($D$51,0.5))) -> 0 | W52: =MIN(1,MAX(0,((YEAR(W$6)-YEAR($D$13))*12+MONTH(W$6)-MONTH($D$13)+0.5)/MAX($D$51,0.5))) -> 0 | X52: =MIN(1,MAX(0,((YEAR(X$6)-YEAR($D$13))*12+MONTH(X$6)-MONTH($D$13)+0.5)/MAX($D$51,0.5))) -> 0 | Y52: =MIN(1,MAX(0,((YEAR(Y$6)-YEAR($D$13))*12+MONTH(Y$6)-MONTH($D$13)+0.5)/MAX($D$51,0.5))) -> 0 | Z52: =MIN(1,MAX(0,((YEAR(Z$6)-YEAR($D$13))*12+MONTH(Z$6)-MONTH($D$13)+0.5)/MAX($D$51,0.5))) -> 0 | AA52: =MIN(1,MAX(0,((YEAR(AA$6)-YEAR($D$13))*12+MONTH(AA$6)-MONTH($D$13)+0.5)/MAX($D$51,0.5))) -> 0 | ... CA52: =MIN(1,MAX(0,((YEAR(CA$6)-YEAR($D$13))*12+MONTH(CA$6)-MONTH($D$13)+0.5)/MAX($D$51,0.5))) -> 1
B53: Resulting average ramp % by year (info) | L53: =SUMIFS($T52:$CA52,$T$5:$CA$5,2026)/12 -> 0 | M53: =SUMIFS($T52:$CA52,$T$5:$CA$5,2027)/12 -> 0.22222222 | N53: =SUMIFS($T52:$CA52,$T$5:$CA$5,2028)/12 -> 0.94444444 | O53: =SUMIFS($T52:$CA52,$T$5:$CA$5,2029)/12 -> 1 | P53: =SUMIFS($T52:$CA52,$T$5:$CA$5,2030)/12 -> 1
B55: 4. RECURRING BENEFIT LINES ($M — these rows feed the WAVE sheet)
B57: Line (WAVE category) | D57: Baseline $M | K57: Run rate
B58: OPEX - Engineering capacity release (loop engineering) [OPEX] | D58: =$D$44/1000000 -> 0 | K58: =SUMIFS($T58:$CA58,$T$5:$CA$5,2030) -> 0 | L58: =SUMIFS($T58:$CA58,$T$5:$CA$5,2026) -> 0 | M58: =SUMIFS($T58:$CA58,$T$5:$CA$5,2027) -> 0 | N58: =SUMIFS($T58:$CA58,$T$5:$CA$5,2028) -> 0 | O58: =SUMIFS($T58:$CA58,$T$5:$CA$5,2029) -> 0 | P58: =SUMIFS($T58:$CA58,$T$5:$CA$5,2030) -> 0 | T58: =($D$47)/1000000/12*T$52 -> 0 | U58: =($D$47)/1000000/12*U$52 -> 0 | V58: =($D$47)/1000000/12*V$52 -> 0 | W58: =($D$47)/1000000/12*W$52 -> 0 | X58: =($D$47)/1000000/12*X$52 -> 0 | Y58: =($D$47)/1000000/12*Y$52 -> 0 | Z58: =($D$47)/1000000/12*Z$52 -> 0 | AA58: =($D$47)/1000000/12*AA$52 -> 0 | ... CA58: =($D$47)/1000000/12*CA$52 -> 0
B59: Total recurring benefit ($M) | K59: =SUM(K58:K58) -> 0 | L59: =SUM(L58:L58) -> 0 | M59: =SUM(M58:M58) -> 0 | N59: =SUM(N58:N58) -> 0 | O59: =SUM(O58:O58) -> 0 | P59: =SUM(P58:P58) -> 0
B61: 5. ONE-TIME INVESTMENT — people cost by milestone (standard approach)
B63: Milestone | C63: Assumptions | D63: Team size | E63: Billing months | F63: Contingency Factor | G63: Labor Costs | H63: Start month | I63: Cap % (labor) | K63: Rate override ($/mo)
C64: Capture any assumptions on cost drivers, timelines, contingency factor etc. | E64: Months the team works at full utilization | F64: Low=10% Medium=15% High=20% Very high=50% | G64: Total labor costs for milestone | I64: Default links to Rate Card policy — type a % to override
B65: Plan / Design | C65: PLACEHOLDER shape mirroring the AAO delivery pod (Servicing S2: design team ≤4 for 1–2 months). Refine with IO. | D65: 4 | E65: 2 | F65: 0.1 | G65: =D65*E65*IF(K65="",'Rate Card'!$G$29,K65)*(1+F65) -> 131633.33 | H65: =DATE(2026,10,1) -> 46296 | I65: ='Rate Card'!$C$45 -> 0
B66: Build / Test | C66: PLACEHOLDER — one 8-FTE pod (PO, PM/Scrum, Tech Lead, 2 AI Eng, DevOps, QA, FA/UX) for ~5 months. | D66: 8 | E66: 5 | F66: 0.1 | G66: =D66*E66*IF(K66="",'Rate Card'!$G$29,K66)*(1+F66) -> 658166.67 | H66: =DATE(2026,12,1) -> 46357 | I66: ='Rate Card'!$C$46 -> 0.8
B67: Pilot / Change Mgmt. | C67: PLACEHOLDER — scale-up team of 5 (technical roles stay on) through domain rollout. | D67: 5 | E67: 6 | F67: 0.1 | G67: =D67*E67*IF(K67="",'Rate Card'!$G$29,K67)*(1+F67) -> 493625 | H67: =DATE(2027,5,1) -> 46508 | I67: ='Rate Card'!$C$47 -> 0
B68: Scale / Run | C68: Run-phase support carried as recurring run cost (Section 6), per the standard treatment — leave 0 here unless a dedicated scale team is planned. | D68: 0 | E68: 0 | F68: 0.1 | G68: =D68*E68*IF(K68="",'Rate Card'!$G$29,K68)*(1+F68) -> 0 | H68: =DATE(2027,11,1) -> 46692 | I68: ='Rate Card'!$C$48 -> 0
B70: Milestone labor phasing ($/month, spread evenly over billing months)
B71: Plan / Design | T71: =IF(AND(T$6>=EOMONTH($H$65,0),T$6<=EOMONTH(EDATE($H$65,$E$65-1),0)),$G$65/MAX($E$65,1),0) -> 0 | U71: =IF(AND(U$6>=EOMONTH($H$65,0),U$6<=EOMONTH(EDATE($H$65,$E$65-1),0)),$G$65/MAX($E$65,1),0) -> 0 | V71: =IF(AND(V$6>=EOMONTH($H$65,0),V$6<=EOMONTH(EDATE($H$65,$E$65-1),0)),$G$65/MAX($E$65,1),0) -> 0 | W71: =IF(AND(W$6>=EOMONTH($H$65,0),W$6<=EOMONTH(EDATE($H$65,$E$65-1),0)),$G$65/MAX($E$65,1),0) -> 0 | X71: =IF(AND(X$6>=EOMONTH($H$65,0),X$6<=EOMONTH(EDATE($H$65,$E$65-1),0)),$G$65/MAX($E$65,1),0) -> 0 | Y71: =IF(AND(Y$6>=EOMONTH($H$65,0),Y$6<=EOMONTH(EDATE($H$65,$E$65-1),0)),$G$65/MAX($E$65,1),0) -> 0 | Z71: =IF(AND(Z$6>=EOMONTH($H$65,0),Z$6<=EOMONTH(EDATE($H$65,$E$65-1),0)),$G$65/MAX($E$65,1),0) -> 0 | AA71: =IF(AND(AA$6>=EOMONTH($H$65,0),AA$6<=EOMONTH(EDATE($H$65,$E$65-1),0)),$G$65/MAX($E$65,1),0) -> 0 | ... CA71: =IF(AND(CA$6>=EOMONTH($H$65,0),CA$6<=EOMONTH(EDATE($H$65,$E$65-1),0)),$G$65/MAX($E$65,1),0) -> 0
B72: Build / Test | T72: =IF(AND(T$6>=EOMONTH($H$66,0),T$6<=EOMONTH(EDATE($H$66,$E$66-1),0)),$G$66/MAX($E$66,1),0) -> 0 | U72: =IF(AND(U$6>=EOMONTH($H$66,0),U$6<=EOMONTH(EDATE($H$66,$E$66-1),0)),$G$66/MAX($E$66,1),0) -> 0 | V72: =IF(AND(V$6>=EOMONTH($H$66,0),V$6<=EOMONTH(EDATE($H$66,$E$66-1),0)),$G$66/MAX($E$66,1),0) -> 0 | W72: =IF(AND(W$6>=EOMONTH($H$66,0),W$6<=EOMONTH(EDATE($H$66,$E$66-1),0)),$G$66/MAX($E$66,1),0) -> 0 | X72: =IF(AND(X$6>=EOMONTH($H$66,0),X$6<=EOMONTH(EDATE($H$66,$E$66-1),0)),$G$66/MAX($E$66,1),0) -> 0 | Y72: =IF(AND(Y$6>=EOMONTH($H$66,0),Y$6<=EOMONTH(EDATE($H$66,$E$66-1),0)),$G$66/MAX($E$66,1),0) -> 0 | Z72: =IF(AND(Z$6>=EOMONTH($H$66,0),Z$6<=EOMONTH(EDATE($H$66,$E$66-1),0)),$G$66/MAX($E$66,1),0) -> 0 | AA72: =IF(AND(AA$6>=EOMONTH($H$66,0),AA$6<=EOMONTH(EDATE($H$66,$E$66-1),0)),$G$66/MAX($E$66,1),0) -> 0 | ... CA72: =IF(AND(CA$6>=EOMONTH($H$66,0),CA$6<=EOMONTH(EDATE($H$66,$E$66-1),0)),$G$66/MAX($E$66,1),0) -> 0
B73: Pilot / Change Mgmt. | T73: =IF(AND(T$6>=EOMONTH($H$67,0),T$6<=EOMONTH(EDATE($H$67,$E$67-1),0)),$G$67/MAX($E$67,1),0) -> 0 | U73: =IF(AND(U$6>=EOMONTH($H$67,0),U$6<=EOMONTH(EDATE($H$67,$E$67-1),0)),$G$67/MAX($E$67,1),0) -> 0 | V73: =IF(AND(V$6>=EOMONTH($H$67,0),V$6<=EOMONTH(EDATE($H$67,$E$67-1),0)),$G$67/MAX($E$67,1),0) -> 0 | W73: =IF(AND(W$6>=EOMONTH($H$67,0),W$6<=EOMONTH(EDATE($H$67,$E$67-1),0)),$G$67/MAX($E$67,1),0) -> 0 | X73: =IF(AND(X$6>=EOMONTH($H$67,0),X$6<=EOMONTH(EDATE($H$67,$E$67-1),0)),$G$67/MAX($E$67,1),0) -> 0 | Y73: =IF(AND(Y$6>=EOMONTH($H$67,0),Y$6<=EOMONTH(EDATE($H$67,$E$67-1),0)),$G$67/MAX($E$67,1),0) -> 0 | Z73: =IF(AND(Z$6>=EOMONTH($H$67,0),Z$6<=EOMONTH(EDATE($H$67,$E$67-1),0)),$G$67/MAX($E$67,1),0) -> 0 | AA73: =IF(AND(AA$6>=EOMONTH($H$67,0),AA$6<=EOMONTH(EDATE($H$67,$E$67-1),0)),$G$67/MAX($E$67,1),0) -> 0 | ... CA73: =IF(AND(CA$6>=EOMONTH($H$67,0),CA$6<=EOMONTH(EDATE($H$67,$E$67-1),0)),$G$67/MAX($E$67,1),0) -> 0
B74: Scale / Run | T74: =IF(AND(T$6>=EOMONTH($H$68,0),T$6<=EOMONTH(EDATE($H$68,$E$68-1),0)),$G$68/MAX($E$68,1),0) -> 0 | U74: =IF(AND(U$6>=EOMONTH($H$68,0),U$6<=EOMONTH(EDATE($H$68,$E$68-1),0)),$G$68/MAX($E$68,1),0) -> 0 | V74: =IF(AND(V$6>=EOMONTH($H$68,0),V$6<=EOMONTH(EDATE($H$68,$E$68-1),0)),$G$68/MAX($E$68,1),0) -> 0 | W74: =IF(AND(W$6>=EOMONTH($H$68,0),W$6<=EOMONTH(EDATE($H$68,$E$68-1),0)),$G$68/MAX($E$68,1),0) -> 0 | X74: =IF(AND(X$6>=EOMONTH($H$68,0),X$6<=EOMONTH(EDATE($H$68,$E$68-1),0)),$G$68/MAX($E$68,1),0) -> 0 | Y74: =IF(AND(Y$6>=EOMONTH($H$68,0),Y$6<=EOMONTH(EDATE($H$68,$E$68-1),0)),$G$68/MAX($E$68,1),0) -> 0 | Z74: =IF(AND(Z$6>=EOMONTH($H$68,0),Z$6<=EOMONTH(EDATE($H$68,$E$68-1),0)),$G$68/MAX($E$68,1),0) -> 0 | AA74: =IF(AND(AA$6>=EOMONTH($H$68,0),AA$6<=EOMONTH(EDATE($H$68,$E$68-1),0)),$G$68/MAX($E$68,1),0) -> 0 | ... CA74: =IF(AND(CA$6>=EOMONTH($H$68,0),CA$6<=EOMONTH(EDATE($H$68,$E$68-1),0)),$G$68/MAX($E$68,1),0) -> 0
B75: Total milestone labor (all blocks) | G75: =SUM(G65:G68) -> 1283425
B77: One-time non-labor costs (vendor, integration, licences, change mgmt., etc.)
B78: Item | C78: Assumptions / notes | D78: Total $ | E78: Spread months | H78: Start month | I78: Cap %
B79: Vendor / integration / tooling set-up | C79: PENDING — placeholder, not data. Build-vs-buy perspective due at W6 tech workshop | D79: 0 | E79: 3 | H79: =DATE(2026,12,1) -> 46357 | I79: 0
B80: Programme management (8% of build) | C80: Formula: 8% x (milestone labor + non-labor build items) — Servicing S2 standard | D80: =$D$37*($G$75+$D$79) -> 102674 | E80: 9 | H80: =DATE(2026,10,1) -> 46296 | I80: 0
B81: Contingency (10% of build incl. PM) | C81: Formula: 10% x (build subtotal incl. PM) — Servicing S2 standard | D81: =$D$38*($G$75+$D$79+$D$80) -> 138609.9 | E81: 9 | H81: =DATE(2026,10,1) -> 46296 | I81: 0
B82: (spare) | D82: 0 | E82: 1 | H82: =DATE(2027,5,1) -> 46508 | I82: 0
B84: Non-labor phasing ($/month)
B85: phasing — item 1 | T85: =IF(AND(T$6>=EOMONTH($H$79,0),T$6<=EOMONTH(EDATE($H$79,$E$79-1),0)),$D$79/MAX($E$79,1),0) -> 0 | U85: =IF(AND(U$6>=EOMONTH($H$79,0),U$6<=EOMONTH(EDATE($H$79,$E$79-1),0)),$D$79/MAX($E$79,1),0) -> 0 | V85: =IF(AND(V$6>=EOMONTH($H$79,0),V$6<=EOMONTH(EDATE($H$79,$E$79-1),0)),$D$79/MAX($E$79,1),0) -> 0 | W85: =IF(AND(W$6>=EOMONTH($H$79,0),W$6<=EOMONTH(EDATE($H$79,$E$79-1),0)),$D$79/MAX($E$79,1),0) -> 0 | X85: =IF(AND(X$6>=EOMONTH($H$79,0),X$6<=EOMONTH(EDATE($H$79,$E$79-1),0)),$D$79/MAX($E$79,1),0) -> 0 | Y85: =IF(AND(Y$6>=EOMONTH($H$79,0),Y$6<=EOMONTH(EDATE($H$79,$E$79-1),0)),$D$79/MAX($E$79,1),0) -> 0 | Z85: =IF(AND(Z$6>=EOMONTH($H$79,0),Z$6<=EOMONTH(EDATE($H$79,$E$79-1),0)),$D$79/MAX($E$79,1),0) -> 0 | AA85: =IF(AND(AA$6>=EOMONTH($H$79,0),AA$6<=EOMONTH(EDATE($H$79,$E$79-1),0)),$D$79/MAX($E$79,1),0) -> 0 | ... CA85: =IF(AND(CA$6>=EOMONTH($H$79,0),CA$6<=EOMONTH(EDATE($H$79,$E$79-1),0)),$D$79/MAX($E$79,1),0) -> 0
B86: phasing — item 2 | T86: =IF(AND(T$6>=EOMONTH($H$80,0),T$6<=EOMONTH(EDATE($H$80,$E$80-1),0)),$D$80/MAX($E$80,1),0) -> 0 | U86: =IF(AND(U$6>=EOMONTH($H$80,0),U$6<=EOMONTH(EDATE($H$80,$E$80-1),0)),$D$80/MAX($E$80,1),0) -> 0 | V86: =IF(AND(V$6>=EOMONTH($H$80,0),V$6<=EOMONTH(EDATE($H$80,$E$80-1),0)),$D$80/MAX($E$80,1),0) -> 0 | W86: =IF(AND(W$6>=EOMONTH($H$80,0),W$6<=EOMONTH(EDATE($H$80,$E$80-1),0)),$D$80/MAX($E$80,1),0) -> 0 | X86: =IF(AND(X$6>=EOMONTH($H$80,0),X$6<=EOMONTH(EDATE($H$80,$E$80-1),0)),$D$80/MAX($E$80,1),0) -> 0 | Y86: =IF(AND(Y$6>=EOMONTH($H$80,0),Y$6<=EOMONTH(EDATE($H$80,$E$80-1),0)),$D$80/MAX($E$80,1),0) -> 0 | Z86: =IF(AND(Z$6>=EOMONTH($H$80,0),Z$6<=EOMONTH(EDATE($H$80,$E$80-1),0)),$D$80/MAX($E$80,1),0) -> 0 | AA86: =IF(AND(AA$6>=EOMONTH($H$80,0),AA$6<=EOMONTH(EDATE($H$80,$E$80-1),0)),$D$80/MAX($E$80,1),0) -> 0 | ... CA86: =IF(AND(CA$6>=EOMONTH($H$80,0),CA$6<=EOMONTH(EDATE($H$80,$E$80-1),0)),$D$80/MAX($E$80,1),0) -> 0
B87: phasing — item 3 | T87: =IF(AND(T$6>=EOMONTH($H$81,0),T$6<=EOMONTH(EDATE($H$81,$E$81-1),0)),$D$81/MAX($E$81,1),0) -> 0 | U87: =IF(AND(U$6>=EOMONTH($H$81,0),U$6<=EOMONTH(EDATE($H$81,$E$81-1),0)),$D$81/MAX($E$81,1),0) -> 0 | V87: =IF(AND(V$6>=EOMONTH($H$81,0),V$6<=EOMONTH(EDATE($H$81,$E$81-1),0)),$D$81/MAX($E$81,1),0) -> 0 | W87: =IF(AND(W$6>=EOMONTH($H$81,0),W$6<=EOMONTH(EDATE($H$81,$E$81-1),0)),$D$81/MAX($E$81,1),0) -> 0 | X87: =IF(AND(X$6>=EOMONTH($H$81,0),X$6<=EOMONTH(EDATE($H$81,$E$81-1),0)),$D$81/MAX($E$81,1),0) -> 0 | Y87: =IF(AND(Y$6>=EOMONTH($H$81,0),Y$6<=EOMONTH(EDATE($H$81,$E$81-1),0)),$D$81/MAX($E$81,1),0) -> 0 | Z87: =IF(AND(Z$6>=EOMONTH($H$81,0),Z$6<=EOMONTH(EDATE($H$81,$E$81-1),0)),$D$81/MAX($E$81,1),0) -> 0 | AA87: =IF(AND(AA$6>=EOMONTH($H$81,0),AA$6<=EOMONTH(EDATE($H$81,$E$81-1),0)),$D$81/MAX($E$81,1),0) -> 0 | ... CA87: =IF(AND(CA$6>=EOMONTH($H$81,0),CA$6<=EOMONTH(EDATE($H$81,$E$81-1),0)),$D$81/MAX($E$81,1),0) -> 0
B88: phasing — item 4 | T88: =IF(AND(T$6>=EOMONTH($H$82,0),T$6<=EOMONTH(EDATE($H$82,$E$82-1),0)),$D$82/MAX($E$82,1),0) -> 0 | U88: =IF(AND(U$6>=EOMONTH($H$82,0),U$6<=EOMONTH(EDATE($H$82,$E$82-1),0)),$D$82/MAX($E$82,1),0) -> 0 | V88: =IF(AND(V$6>=EOMONTH($H$82,0),V$6<=EOMONTH(EDATE($H$82,$E$82-1),0)),$D$82/MAX($E$82,1),0) -> 0 | W88: =IF(AND(W$6>=EOMONTH($H$82,0),W$6<=EOMONTH(EDATE($H$82,$E$82-1),0)),$D$82/MAX($E$82,1),0) -> 0 | X88: =IF(AND(X$6>=EOMONTH($H$82,0),X$6<=EOMONTH(EDATE($H$82,$E$82-1),0)),$D$82/MAX($E$82,1),0) -> 0 | Y88: =IF(AND(Y$6>=EOMONTH($H$82,0),Y$6<=EOMONTH(EDATE($H$82,$E$82-1),0)),$D$82/MAX($E$82,1),0) -> 0 | Z88: =IF(AND(Z$6>=EOMONTH($H$82,0),Z$6<=EOMONTH(EDATE($H$82,$E$82-1),0)),$D$82/MAX($E$82,1),0) -> 0 | AA88: =IF(AND(AA$6>=EOMONTH($H$82,0),AA$6<=EOMONTH(EDATE($H$82,$E$82-1),0)),$D$82/MAX($E$82,1),0) -> 0 | ... CA88: =IF(AND(CA$6>=EOMONTH($H$82,0),CA$6<=EOMONTH(EDATE($H$82,$E$82-1),0)),$D$82/MAX($E$82,1),0) -> 0
B90: One-time investment feed rows ($M — these feed the WAVE sheet)
B91: CAPEX — capitalized build labor | L91: =SUMIFS($T91:$CA91,$T$5:$CA$5,2026) -> 0.10530667 | M91: =SUMIFS($T91:$CA91,$T$5:$CA$5,2027) -> 0.42122667 | N91: =SUMIFS($T91:$CA91,$T$5:$CA$5,2028) -> 0 | O91: =SUMIFS($T91:$CA91,$T$5:$CA$5,2029) -> 0 | P91: =SUMIFS($T91:$CA91,$T$5:$CA$5,2030) -> 0 | T91: =(SUMPRODUCT(T71:T74,$I$65:$I$68))/1000000 -> 0 | U91: =(SUMPRODUCT(U71:U74,$I$65:$I$68))/1000000 -> 0 | V91: =(SUMPRODUCT(V71:V74,$I$65:$I$68))/1000000 -> 0 | W91: =(SUMPRODUCT(W71:W74,$I$65:$I$68))/1000000 -> 0 | X91: =(SUMPRODUCT(X71:X74,$I$65:$I$68))/1000000 -> 0 | Y91: =(SUMPRODUCT(Y71:Y74,$I$65:$I$68))/1000000 -> 0 | Z91: =(SUMPRODUCT(Z71:Z74,$I$65:$I$68))/1000000 -> 0 | AA91: =(SUMPRODUCT(AA71:AA74,$I$65:$I$68))/1000000 -> 0 | ... CA91: =(SUMPRODUCT(CA71:CA74,$I$65:$I$68))/1000000 -> 0
B92: CAPEX — capitalized non-labor | L92: =SUMIFS($T92:$CA92,$T$5:$CA$5,2026) -> 0 | M92: =SUMIFS($T92:$CA92,$T$5:$CA$5,2027) -> 0 | N92: =SUMIFS($T92:$CA92,$T$5:$CA$5,2028) -> 0 | O92: =SUMIFS($T92:$CA92,$T$5:$CA$5,2029) -> 0 | P92: =SUMIFS($T92:$CA92,$T$5:$CA$5,2030) -> 0 | T92: =SUMPRODUCT(T85:T88,$I$79:$I$82)/1000000 -> 0 | U92: =SUMPRODUCT(U85:U88,$I$79:$I$82)/1000000 -> 0 | V92: =SUMPRODUCT(V85:V88,$I$79:$I$82)/1000000 -> 0 | W92: =SUMPRODUCT(W85:W88,$I$79:$I$82)/1000000 -> 0 | X92: =SUMPRODUCT(X85:X88,$I$79:$I$82)/1000000 -> 0 | Y92: =SUMPRODUCT(Y85:Y88,$I$79:$I$82)/1000000 -> 0 | Z92: =SUMPRODUCT(Z85:Z88,$I$79:$I$82)/1000000 -> 0 | AA92: =SUMPRODUCT(AA85:AA88,$I$79:$I$82)/1000000 -> 0 | ... CA92: =SUMPRODUCT(CA85:CA88,$I$79:$I$82)/1000000 -> 0
B93: OTC — build labor (expensed) | L93: =SUMIFS($T93:$CA93,$T$5:$CA$5,2026) -> 0.15796 | M93: =SUMIFS($T93:$CA93,$T$5:$CA$5,2027) -> 0.59893167 | N93: =SUMIFS($T93:$CA93,$T$5:$CA$5,2028) -> 0 | O93: =SUMIFS($T93:$CA93,$T$5:$CA$5,2029) -> 0 | P93: =SUMIFS($T93:$CA93,$T$5:$CA$5,2030) -> 0 | T93: =(SUMPRODUCT(T71:T74,1-$I$65:$I$68))/1000000 -> 0 | U93: =(SUMPRODUCT(U71:U74,1-$I$65:$I$68))/1000000 -> 0 | V93: =(SUMPRODUCT(V71:V74,1-$I$65:$I$68))/1000000 -> 0 | W93: =(SUMPRODUCT(W71:W74,1-$I$65:$I$68))/1000000 -> 0 | X93: =(SUMPRODUCT(X71:X74,1-$I$65:$I$68))/1000000 -> 0 | Y93: =(SUMPRODUCT(Y71:Y74,1-$I$65:$I$68))/1000000 -> 0 | Z93: =(SUMPRODUCT(Z71:Z74,1-$I$65:$I$68))/1000000 -> 0 | AA93: =(SUMPRODUCT(AA71:AA74,1-$I$65:$I$68))/1000000 -> 0 | ... CA93: =(SUMPRODUCT(CA71:CA74,1-$I$65:$I$68))/1000000 -> 0
B94: OTC — non-labor (expensed) | L94: =SUMIFS($T94:$CA94,$T$5:$CA$5,2026) -> 0.080427967 | M94: =SUMIFS($T94:$CA94,$T$5:$CA$5,2027) -> 0.16085593 | N94: =SUMIFS($T94:$CA94,$T$5:$CA$5,2028) -> 0 | O94: =SUMIFS($T94:$CA94,$T$5:$CA$5,2029) -> 0 | P94: =SUMIFS($T94:$CA94,$T$5:$CA$5,2030) -> 0 | T94: =SUMPRODUCT(T85:T88,1-$I$79:$I$82)/1000000 -> 0 | U94: =SUMPRODUCT(U85:U88,1-$I$79:$I$82)/1000000 -> 0 | V94: =SUMPRODUCT(V85:V88,1-$I$79:$I$82)/1000000 -> 0 | W94: =SUMPRODUCT(W85:W88,1-$I$79:$I$82)/1000000 -> 0 | X94: =SUMPRODUCT(X85:X88,1-$I$79:$I$82)/1000000 -> 0 | Y94: =SUMPRODUCT(Y85:Y88,1-$I$79:$I$82)/1000000 -> 0 | Z94: =SUMPRODUCT(Z85:Z88,1-$I$79:$I$82)/1000000 -> 0 | AA94: =SUMPRODUCT(AA85:AA88,1-$I$79:$I$82)/1000000 -> 0 | ... CA94: =SUMPRODUCT(CA85:CA88,1-$I$79:$I$82)/1000000 -> 0
B95: Total one-time investment ($M) | L95: =SUM(L91:L94) -> 0.34369463 | M95: =SUM(M91:M94) -> 1.1810143 | N95: =SUM(N91:N94) -> 0 | O95: =SUM(O91:O94) -> 0 | P95: =SUM(P91:P94) -> 0
B97: 6. RECURRING RUN COSTS to achieve impact
B99: Line | C99: Assumptions / notes | D99: Annual $ (steady state) | H99: Start month | I99: Scales with ramp? (Y/N)
B100: OPEX - Model / token consumption | C100: PENDING — placeholder, not data. Per-developer consumption (request #11) x adopted developers; scales with ramp | D100: 0 | H100: =DATE(2027,5,1) -> 46508 | I100: Y
B101: OPEX - Harness platform & tooling run | C101: PENDING — placeholder, not data. Ongoing platform/support run cost | D101: 0 | H101: =DATE(2027,5,1) -> 46508 | I101: N
B102: OPEX - Champion / coaching capacity | C102: PENDING — placeholder, not data. Champion/coaching capacity plan | D102: 0 | H102: =DATE(2027,5,1) -> 46508 | I102: N
B104: Run-cost feed rows ($M)
B105: OPEX - Model / token consumption [RUN] | K105: =SUMIFS($T105:$CA105,$T$5:$CA$5,2030) -> 0 | L105: =SUMIFS($T105:$CA105,$T$5:$CA$5,2026) -> 0 | M105: =SUMIFS($T105:$CA105,$T$5:$CA$5,2027) -> 0 | N105: =SUMIFS($T105:$CA105,$T$5:$CA$5,2028) -> 0 | O105: =SUMIFS($T105:$CA105,$T$5:$CA$5,2029) -> 0 | P105: =SUMIFS($T105:$CA105,$T$5:$CA$5,2030) -> 0 | T105: =$D$100/1000000/12*IF($I$100="Y",T$52,IF(T$6>=EOMONTH($H$100,0),1,0)) -> 0 | U105: =$D$100/1000000/12*IF($I$100="Y",U$52,IF(U$6>=EOMONTH($H$100,0),1,0)) -> 0 | V105: =$D$100/1000000/12*IF($I$100="Y",V$52,IF(V$6>=EOMONTH($H$100,0),1,0)) -> 0 | W105: =$D$100/1000000/12*IF($I$100="Y",W$52,IF(W$6>=EOMONTH($H$100,0),1,0)) -> 0 | X105: =$D$100/1000000/12*IF($I$100="Y",X$52,IF(X$6>=EOMONTH($H$100,0),1,0)) -> 0 | Y105: =$D$100/1000000/12*IF($I$100="Y",Y$52,IF(Y$6>=EOMONTH($H$100,0),1,0)) -> 0 | Z105: =$D$100/1000000/12*IF($I$100="Y",Z$52,IF(Z$6>=EOMONTH($H$100,0),1,0)) -> 0 | AA105: =$D$100/1000000/12*IF($I$100="Y",AA$52,IF(AA$6>=EOMONTH($H$100,0),1,0)) -> 0 | ... CA105: =$D$100/1000000/12*IF($I$100="Y",CA$52,IF(CA$6>=EOMONTH($H$100,0),1,0)) -> 0
B106: OPEX - Harness platform & tooling run [RUN] | K106: =SUMIFS($T106:$CA106,$T$5:$CA$5,2030) -> 0 | L106: =SUMIFS($T106:$CA106,$T$5:$CA$5,2026) -> 0 | M106: =SUMIFS($T106:$CA106,$T$5:$CA$5,2027) -> 0 | N106: =SUMIFS($T106:$CA106,$T$5:$CA$5,2028) -> 0 | O106: =SUMIFS($T106:$CA106,$T$5:$CA$5,2029) -> 0 | P106: =SUMIFS($T106:$CA106,$T$5:$CA$5,2030) -> 0 | T106: =$D$101/1000000/12*IF($I$101="Y",T$52,IF(T$6>=EOMONTH($H$101,0),1,0)) -> 0 | U106: =$D$101/1000000/12*IF($I$101="Y",U$52,IF(U$6>=EOMONTH($H$101,0),1,0)) -> 0 | V106: =$D$101/1000000/12*IF($I$101="Y",V$52,IF(V$6>=EOMONTH($H$101,0),1,0)) -> 0 | W106: =$D$101/1000000/12*IF($I$101="Y",W$52,IF(W$6>=EOMONTH($H$101,0),1,0)) -> 0 | X106: =$D$101/1000000/12*IF($I$101="Y",X$52,IF(X$6>=EOMONTH($H$101,0),1,0)) -> 0 | Y106: =$D$101/1000000/12*IF($I$101="Y",Y$52,IF(Y$6>=EOMONTH($H$101,0),1,0)) -> 0 | Z106: =$D$101/1000000/12*IF($I$101="Y",Z$52,IF(Z$6>=EOMONTH($H$101,0),1,0)) -> 0 | AA106: =$D$101/1000000/12*IF($I$101="Y",AA$52,IF(AA$6>=EOMONTH($H$101,0),1,0)) -> 0 | ... CA106: =$D$101/1000000/12*IF($I$101="Y",CA$52,IF(CA$6>=EOMONTH($H$101,0),1,0)) -> 0
B107: OPEX - Champion / coaching capacity [RUN] | K107: =SUMIFS($T107:$CA107,$T$5:$CA$5,2030) -> 0 | L107: =SUMIFS($T107:$CA107,$T$5:$CA$5,2026) -> 0 | M107: =SUMIFS($T107:$CA107,$T$5:$CA$5,2027) -> 0 | N107: =SUMIFS($T107:$CA107,$T$5:$CA$5,2028) -> 0 | O107: =SUMIFS($T107:$CA107,$T$5:$CA$5,2029) -> 0 | P107: =SUMIFS($T107:$CA107,$T$5:$CA$5,2030) -> 0 | T107: =$D$102/1000000/12*IF($I$102="Y",T$52,IF(T$6>=EOMONTH($H$102,0),1,0)) -> 0 | U107: =$D$102/1000000/12*IF($I$102="Y",U$52,IF(U$6>=EOMONTH($H$102,0),1,0)) -> 0 | V107: =$D$102/1000000/12*IF($I$102="Y",V$52,IF(V$6>=EOMONTH($H$102,0),1,0)) -> 0 | W107: =$D$102/1000000/12*IF($I$102="Y",W$52,IF(W$6>=EOMONTH($H$102,0),1,0)) -> 0 | X107: =$D$102/1000000/12*IF($I$102="Y",X$52,IF(X$6>=EOMONTH($H$102,0),1,0)) -> 0 | Y107: =$D$102/1000000/12*IF($I$102="Y",Y$52,IF(Y$6>=EOMONTH($H$102,0),1,0)) -> 0 | Z107: =$D$102/1000000/12*IF($I$102="Y",Z$52,IF(Z$6>=EOMONTH($H$102,0),1,0)) -> 0 | AA107: =$D$102/1000000/12*IF($I$102="Y",AA$52,IF(AA$6>=EOMONTH($H$102,0),1,0)) -> 0 | ... CA107: =$D$102/1000000/12*IF($I$102="Y",CA$52,IF(CA$6>=EOMONTH($H$102,0),1,0)) -> 0
B108: Total run cost ($M) | K108: =SUM(K105:K107) -> 0 | L108: =SUM(L105:L107) -> 0 | M108: =SUM(M105:M107) -> 0 | N108: =SUM(N105:N107) -> 0 | O108: =SUM(O105:O107) -> 0 | P108: =SUM(P105:P107) -> 0
B110: 7. WAVE MAPPING (reference)
B112: Model row 58 — OPEX - Engineering capacity release (loop engineering) | F112: → WAVE row 79 (Section II — Recurring Benefits)
B113: Model row 105 — OPEX - Model / token consumption | F113: → WAVE row 107 (Section II — Recurring Costs)
B114: Model row 106 — OPEX - Harness platform & tooling run | F114: → WAVE row 108 (Section II — Recurring Costs)
B115: Model row 107 — OPEX - Champion / coaching capacity | F115: → WAVE row 109 (Section II — Recurring Costs)
B116: Model row 91 — CAPEX — capitalized build labor | F116: → WAVE row 136 (Section III — CapEx)
B117: Model row 92 — CAPEX — capitalized non-labor | F117: → WAVE row 137 (Section III — CapEx)
B118: Model row 93 — OTC — build labor (expensed) | F118: → WAVE row 141 (Section III — OTC)
B119: Model row 94 — OTC — non-labor (expensed) | F119: → WAVE row 142 (Section III — OTC)
B121: 8. FLEX / SCRATCH AREA — free space for refinements with the initiative owner

Sheet SDLC-1 WAVE
L1: 1 | M1: 2 | N1: 3 | O1: 4 | P1: 5 | R1: =COUNTIFS($R$66:$R$117, "Error") -> 0 | T1: 2026 | U1: 2026 | V1: 2026 | W1: 2026 | X1: 2026 | Y1: 2026 | Z1: 2026 | AA1: 2026 | AB1: 2026 | AC1: 2026 | AD1: 2026 | AE1: 2026 | AF1: 2027 | AG1: 2027 | AH1: 2027 | AI1: 2027 | AJ1: 2027 | AK1: 2027 | AL1: 2027 | AM1: 2027 | AN1: 2027 | AO1: 2027 | AP1: 2027 | AQ1: 2027 | AR1: 2028 | AS1: 2028 | AT1: 2028 | AU1: 2028 | AV1: 2028 | AW1: 2028 | AX1: 2028 | AY1: 2028 | AZ1: 2028 | BA1: 2028 | BB1: 2028 | BC1: 2028 | BD1: 2029 | BE1: 2029 | BF1: 2029 | BG1: 2029 | BH1: 2029 | BI1: 2029 | BJ1: 2029 | BK1: 2029 | BL1: 2029 | BM1: 2029 | BN1: 2029 | BO1: 2029 | BP1: 2030 | BQ1: 2030 | BR1: 2030 | BS1: 2030 | BT1: 2030 | BU1: 2030 | BV1: 2030 | BW1: 2030 | BX1: 2030 | BY1: 2030 | BZ1: 2030 | CA1: 2030 | CI1: =COUNTIFS(CI$66:CI$149, "FALSE") -> 0 | CJ1: =COUNTIFS(CJ$66:CJ$149, "FALSE") -> 0 | CK1: =COUNTIFS(CK$66:CK$149, "FALSE") -> 0 | CL1: =COUNTIFS(CL$66:CL$149, "FALSE") -> 0 | CM1: =COUNTIFS(CM$66:CM$149, "FALSE") -> 0
C2: ="#"&$F$6&" Initiative Business Case" -> #TBD Initiative Business Case
C4: INPUTS & ASSUMPTIONS
D6: Initiative # | F6: TBD
D7: Initiative Owner | F7: Pooja (WSL) — initiative owner TBC
D8: Initiative Name | F8: Agentic loop engineering — raise engineering throughput on the residual addressable base
D11: Estimated L4 date | F11: ='SDLC-1 Model'!$D$13 -> 46508
D12: Net Recurring Benefit ($M) | F12: =$K$117 -> 0
C14: SECTION I - PRIMARY VALUE DRIVER (ILLUSTRATIVE)
D16: Primary value driver — linked to the Model sheet; refine with the initiative owner
D17: Baseline | H17: Period | I17: KPI | J17: Inputs
E18: Total in-scope engineering labor base | H18: TTM 6/1/26 | I18: $USD M | J18: ='SDLC-1 Model'!$D$44/1000000 -> 0
E19: Code Assist savings already banked | H19: TTM 6/1/26 | I19: $USD M | J19: ='SDLC-1 Model'!$D$31/1000000 -> 0
E20: Residual addressable base | H20: TTM 6/1/26 | I20: $USD M | J20: ='SDLC-1 Model'!$D$45/1000000 -> 0
D23: Goal
E24: Productivity uplift x steady-state adoption | H24: Steady state | I24: % | J24: ='SDLC-1 Model'!$D$33*'SDLC-1 Model'!$D$34 -> 0.12
E25: Capture rate to bankable cost | H25: Steady state | I25: % | J25: ='SDLC-1 Model'!$D$35 -> 0.65
D28: Incremental Improvement
E29: Bankable annual benefit (run rate) | I29: $USD M | J29: ='SDLC-1 Model'!$D$47/1000000 -> 0
C60: SECTION II - NET RECURRING BENEFITS | CC60: ANNUAL SUMMARY | CI60: CHECK CELLS
T62: 2026 | AF62: 2027 | AR62: 2028 | BD62: 2029 | BP62: 2030 | CI62: CHECK
D63: RECURRING BENEFITS | H63: Comment | I63: Baseline | J63: Goal | K63: Ann. Run Rate | L63: 2026 | M63: =L63+1 -> 2027 | N63: =M63+1 -> 2028 | O63: =N63+1 -> 2029 | P63: =O63+1 -> 2030 | Q63: Impacted BU | R63: Check | T63: 46023 | U63: =EOMONTH(T63, 1) -> 46081 | V63: =EOMONTH(U63, 1) -> 46112 | W63: =EOMONTH(V63, 1) -> 46142 | X63: =EOMONTH(W63, 1) -> 46173 | Y63: =EOMONTH(X63, 1) -> 46203 | Z63: =EOMONTH(Y63, 1) -> 46234 | AA63: =EOMONTH(Z63, 1) -> 46265 | AB63: =EOMONTH(AA63, 1) -> 46295 | ... CA63: =EOMONTH(BZ63, 1) -> 47848 | CC63: 2026 | CD63: =CC63+1 -> 2027 | CE63: =CD63+1 -> 2028 | CF63: =CE63+1 -> 2029 | CG63: =CF63+1 -> 2030 | CI63: 2026 | CJ63: =CI63+1 -> 2027 | CK63: =CJ63+1 -> 2028 | CL63: =CK63+1 -> 2029 | CM63: =CL63+1 -> 2030
E64: $USD M | I64: =$H$18 -> TTM 6/1/26 | J64: Future State | K64: Increment
E65: Revenue
I66: 0 | J66: 0 | K66: =J66-I66 -> 0 | R66: =IF(K66=P66, "", "Error") | CC66: =SUMIFS($T66:$CA66, $T$1:$CA$1, CC$63) -> 0 | CD66: =SUMIFS($T66:$CA66, $T$1:$CA$1, CD$63) -> 0 | CE66: =SUMIFS($T66:$CA66, $T$1:$CA$1, CE$63) -> 0 | CF66: =SUMIFS($T66:$CA66, $T$1:$CA$1, CF$63) -> 0 | CG66: =SUMIFS($T66:$CA66, $T$1:$CA$1, CG$63) -> 0 | CI66: =CC66=L66 -> 1 | CJ66: =CD66=M66 -> 1 | CK66: =CE66=N66 -> 1 | CL66: =CF66=O66 -> 1 | CM66: =CG66=P66 -> 1
I67: 0 | J67: 0 | K67: =J67-I67 -> 0 | R67: =IF(K67=P67, "", "Error") | CC67: =SUMIFS($T67:$CA67, $T$1:$CA$1, CC$63) -> 0 | CD67: =SUMIFS($T67:$CA67, $T$1:$CA$1, CD$63) -> 0 | CE67: =SUMIFS($T67:$CA67, $T$1:$CA$1, CE$63) -> 0 | CF67: =SUMIFS($T67:$CA67, $T$1:$CA$1, CF$63) -> 0 | CG67: =SUMIFS($T67:$CA67, $T$1:$CA$1, CG$63) -> 0 | CI67: =CC67=L67 -> 1 | CJ67: =CD67=M67 -> 1 | CK67: =CE67=N67 -> 1 | CL67: =CF67=O67 -> 1 | CM67: =CG67=P67 -> 1
E68: Revenue Subtotal | I68: =SUM(I66:I67) -> 0 | J68: =SUM(J66:J67) -> 0 | K68: =SUM(K66:K67) -> 0 | L68: =SUM(L66:L67) -> 0 | M68: =SUM(M66:M67) -> 0 | N68: =SUM(N66:N67) -> 0 | O68: =SUM(O66:O67) -> 0 | P68: =SUM(P66:P67) -> 0 | T68: =SUM(T66:T67) -> 0 | U68: =SUM(U66:U67) -> 0 | V68: =SUM(V66:V67) -> 0 | W68: =SUM(W66:W67) -> 0 | X68: =SUM(X66:X67) -> 0 | Y68: =SUM(Y66:Y67) -> 0 | Z68: =SUM(Z66:Z67) -> 0 | AA68: =SUM(AA66:AA67) -> 0 | ... CA68: =SUM(CA66:CA67) -> 0 | CC68: =SUM(CC66:CC67) -> 0 | CD68: =SUM(CD66:CD67) -> 0 | CE68: =SUM(CE66:CE67) -> 0 | CF68: =SUM(CF66:CF67) -> 0 | CG68: =SUM(CG66:CG67) -> 0 | CI68: =CC68=L68 -> 1 | CJ68: =CD68=M68 -> 1 | CK68: =CE68=N68 -> 1 | CL68: =CF68=O68 -> 1 | CM68: =CG68=P68 -> 1
E70: Cost of Sales
K71: =I71-J71 -> 0 | R71: =IF(K71=P71, "", "Error") | CC71: =SUMIFS($T71:$CA71, $T$1:$CA$1, CC$63) -> 0 | CD71: =SUMIFS($T71:$CA71, $T$1:$CA$1, CD$63) -> 0 | CE71: =SUMIFS($T71:$CA71, $T$1:$CA$1, CE$63) -> 0 | CF71: =SUMIFS($T71:$CA71, $T$1:$CA$1, CF$63) -> 0 | CG71: =SUMIFS($T71:$CA71, $T$1:$CA$1, CG$63) -> 0 | CI71: =CC71=L71 -> 1 | CJ71: =CD71=M71 -> 1 | CK71: =CE71=N71 -> 1 | CL71: =CF71=O71 -> 1 | CM71: =CG71=P71 -> 1
I72: 0 | J72: 0 | K72: =I72-J72 -> 0 | R72: =IF(K72=P72, "", "Error") | CC72: =SUMIFS($T72:$CA72, $T$1:$CA$1, CC$63) -> 0 | CD72: =SUMIFS($T72:$CA72, $T$1:$CA$1, CD$63) -> 0 | CE72: =SUMIFS($T72:$CA72, $T$1:$CA$1, CE$63) -> 0 | CF72: =SUMIFS($T72:$CA72, $T$1:$CA$1, CF$63) -> 0 | CG72: =SUMIFS($T72:$CA72, $T$1:$CA$1, CG$63) -> 0 | CI72: =CC72=L72 -> 1 | CJ72: =CD72=M72 -> 1 | CK72: =CE72=N72 -> 1 | CL72: =CF72=O72 -> 1 | CM72: =CG72=P72 -> 1
I73: 0 | J73: 0 | K73: =I73-J73 -> 0 | R73: =IF(K73=P73, "", "Error") | CC73: =SUMIFS($T73:$CA73, $T$1:$CA$1, CC$63) -> 0 | CD73: =SUMIFS($T73:$CA73, $T$1:$CA$1, CD$63) -> 0 | CE73: =SUMIFS($T73:$CA73, $T$1:$CA$1, CE$63) -> 0 | CF73: =SUMIFS($T73:$CA73, $T$1:$CA$1, CF$63) -> 0 | CG73: =SUMIFS($T73:$CA73, $T$1:$CA$1, CG$63) -> 0 | CI73: =CC73=L73 -> 1 | CJ73: =CD73=M73 -> 1 | CK73: =CE73=N73 -> 1 | CL73: =CF73=O73 -> 1 | CM73: =CG73=P73 -> 1
I74: 0 | J74: 0 | K74: =I74-J74 -> 0 | R74: =IF(K74=P74, "", "Error") | CC74: =SUMIFS($T74:$CA74, $T$1:$CA$1, CC$63) -> 0 | CD74: =SUMIFS($T74:$CA74, $T$1:$CA$1, CD$63) -> 0 | CE74: =SUMIFS($T74:$CA74, $T$1:$CA$1, CE$63) -> 0 | CF74: =SUMIFS($T74:$CA74, $T$1:$CA$1, CF$63) -> 0 | CG74: =SUMIFS($T74:$CA74, $T$1:$CA$1, CG$63) -> 0 | CI74: =CC74=L74 -> 1 | CJ74: =CD74=M74 -> 1 | CK74: =CE74=N74 -> 1 | CL74: =CF74=O74 -> 1 | CM74: =CG74=P74 -> 1
K75: =I75-J75 -> 0 | R75: =IF(K75=P75, "", "Error") | CC75: =SUMIFS($T75:$CA75, $T$1:$CA$1, CC$63) -> 0 | CD75: =SUMIFS($T75:$CA75, $T$1:$CA$1, CD$63) -> 0 | CE75: =SUMIFS($T75:$CA75, $T$1:$CA$1, CE$63) -> 0 | CF75: =SUMIFS($T75:$CA75, $T$1:$CA$1, CF$63) -> 0 | CG75: =SUMIFS($T75:$CA75, $T$1:$CA$1, CG$63) -> 0 | CI75: =CC75=L75 -> 1 | CJ75: =CD75=M75 -> 1 | CK75: =CE75=N75 -> 1 | CL75: =CF75=O75 -> 1 | CM75: =CG75=P75 -> 1
E76: Cost of Sales Subtotal | I76: =SUM(I71:I75) -> 0 | J76: =SUM(J71:J75) -> 0 | K76: =SUM(K71:K75) -> 0 | L76: =SUM(L71:L75) -> 0 | M76: =SUM(M71:M75) -> 0 | N76: =SUM(N71:N75) -> 0 | O76: =SUM(O71:O75) -> 0 | P76: =SUM(P71:P75) -> 0 | T76: =SUM(T71:T75) -> 0 | U76: =SUM(U71:U75) -> 0 | V76: =SUM(V71:V75) -> 0 | W76: =SUM(W71:W75) -> 0 | X76: =SUM(X71:X75) -> 0 | Y76: =SUM(Y71:Y75) -> 0 | Z76: =SUM(Z71:Z75) -> 0 | AA76: =SUM(AA71:AA75) -> 0 | ... CA76: =SUM(CA71:CA75) -> 0 | CC76: =SUM(CC71:CC75) -> 0 | CD76: =SUM(CD71:CD75) -> 0 | CE76: =SUM(CE71:CE75) -> 0 | CF76: =SUM(CF71:CF75) -> 0 | CG76: =SUM(CG71:CG75) -> 0 | CI76: =CC76=L76 -> 1 | CJ76: =CD76=M76 -> 1 | CK76: =CE76=N76 -> 1 | CL76: =CF76=O76 -> 1 | CM76: =CG76=P76 -> 1
E78: OPEX
E79: OPEX - Engineering capacity release (loop engineering) | H79: Bankable share of capacity created on the residual addressable base | I79: ='SDLC-1 Model'!$D$58 -> 0 | J79: =I79-'SDLC-1 Model'!$K$58 -> 0 | K79: ='SDLC-1 Model'!$K$58 -> 0 | L79: ='SDLC-1 Model'!L58 -> 0 | M79: ='SDLC-1 Model'!M58 -> 0 | N79: ='SDLC-1 Model'!N58 -> 0 | O79: ='SDLC-1 Model'!O58 -> 0 | P79: ='SDLC-1 Model'!P58 -> 0 | Q79: CTO / SDLC | R79: =IF(K79=P79, "", "Error") | T79: ='SDLC-1 Model'!T58 -> 0 | U79: ='SDLC-1 Model'!U58 -> 0 | V79: ='SDLC-1 Model'!V58 -> 0 | W79: ='SDLC-1 Model'!W58 -> 0 | X79: ='SDLC-1 Model'!X58 -> 0 | Y79: ='SDLC-1 Model'!Y58 -> 0 | Z79: ='SDLC-1 Model'!Z58 -> 0 | AA79: ='SDLC-1 Model'!AA58 -> 0 | ... CA79: ='SDLC-1 Model'!CA58 -> 0 | CC79: =SUMIFS($T79:$CA79, $T$1:$CA$1, CC$63) -> 0 | CD79: =SUMIFS($T79:$CA79, $T$1:$CA$1, CD$63) -> 0 | CE79: =SUMIFS($T79:$CA79, $T$1:$CA$1, CE$63) -> 0 | CF79: =SUMIFS($T79:$CA79, $T$1:$CA$1, CF$63) -> 0 | CG79: =SUMIFS($T79:$CA79, $T$1:$CA$1, CG$63) -> 0 | CI79: =CC79=L79 -> 1 | CJ79: =CD79=M79 -> 1 | CK79: =CE79=N79 -> 1 | CL79: =CF79=O79 -> 1 | CM79: =CG79=P79 -> 1
I80: 0 | J80: 0 | K80: =I80-J80 -> 0 | R80: =IF(K80=P80, "", "Error") | CC80: =SUMIFS($T80:$CA80, $T$1:$CA$1, CC$63) -> 0 | CD80: =SUMIFS($T80:$CA80, $T$1:$CA$1, CD$63) -> 0 | CE80: =SUMIFS($T80:$CA80, $T$1:$CA$1, CE$63) -> 0 | CF80: =SUMIFS($T80:$CA80, $T$1:$CA$1, CF$63) -> 0 | CG80: =SUMIFS($T80:$CA80, $T$1:$CA$1, CG$63) -> 0 | CI80: =CC80=L80 -> 1 | CJ80: =CD80=M80 -> 1 | CK80: =CE80=N80 -> 1 | CL80: =CF80=O80 -> 1 | CM80: =CG80=P80 -> 1
I81: 0 | J81: 0 | K81: =I81-J81 -> 0 | R81: =IF(K81=P81, "", "Error") | CC81: =SUMIFS($T81:$CA81, $T$1:$CA$1, CC$63) -> 0 | CD81: =SUMIFS($T81:$CA81, $T$1:$CA$1, CD$63) -> 0 | CE81: =SUMIFS($T81:$CA81, $T$1:$CA$1, CE$63) -> 0 | CF81: =SUMIFS($T81:$CA81, $T$1:$CA$1, CF$63) -> 0 | CG81: =SUMIFS($T81:$CA81, $T$1:$CA$1, CG$63) -> 0 | CI81: =CC81=L81 -> 1 | CJ81: =CD81=M81 -> 1 | CK81: =CE81=N81 -> 1 | CL81: =CF81=O81 -> 1 | CM81: =CG81=P81 -> 1
I82: 0 | J82: 0 | K82: =I82-J82 -> 0 | R82: =IF(K82=P82, "", "Error") | CC82: =SUMIFS($T82:$CA82, $T$1:$CA$1, CC$63) -> 0 | CD82: =SUMIFS($T82:$CA82, $T$1:$CA$1, CD$63) -> 0 | CE82: =SUMIFS($T82:$CA82, $T$1:$CA$1, CE$63) -> 0 | CF82: =SUMIFS($T82:$CA82, $T$1:$CA$1, CF$63) -> 0 | CG82: =SUMIFS($T82:$CA82, $T$1:$CA$1, CG$63) -> 0 | CI82: =CC82=L82 -> 1 | CJ82: =CD82=M82 -> 1 | CK82: =CE82=N82 -> 1 | CL82: =CF82=O82 -> 1 | CM82: =CG82=P82 -> 1
I83: 0 | J83: 0 | K83: =I83-J83 -> 0 | R83: =IF(K83=P83, "", "Error") | CC83: =SUMIFS($T83:$CA83, $T$1:$CA$1, CC$63) -> 0 | CD83: =SUMIFS($T83:$CA83, $T$1:$CA$1, CD$63) -> 0 | CE83: =SUMIFS($T83:$CA83, $T$1:$CA$1, CE$63) -> 0 | CF83: =SUMIFS($T83:$CA83, $T$1:$CA$1, CF$63) -> 0 | CG83: =SUMIFS($T83:$CA83, $T$1:$CA$1, CG$63) -> 0 | CI83: =CC83=L83 -> 1 | CJ83: =CD83=M83 -> 1 | CK83: =CE83=N83 -> 1 | CL83: =CF83=O83 -> 1 | CM83: =CG83=P83 -> 1
E84: OpEx subtotal | I84: =SUM(I79:I83) -> 0 | J84: =SUM(J79:J83) -> 0 | K84: =SUM(K79:K83) -> 0 | L84: =SUM(L79:L83) -> 0 | M84: =SUM(M79:M83) -> 0 | N84: =SUM(N79:N83) -> 0 | O84: =SUM(O79:O83) -> 0 | P84: =SUM(P79:P83) -> 0 | T84: =SUM(T79:T83) -> 0 | U84: =SUM(U79:U83) -> 0 | V84: =SUM(V79:V83) -> 0 | W84: =SUM(W79:W83) -> 0 | X84: =SUM(X79:X83) -> 0 | Y84: =SUM(Y79:Y83) -> 0 | Z84: =SUM(Z79:Z83) -> 0 | AA84: =SUM(AA79:AA83) -> 0 | ... CA84: =SUM(CA79:CA83) -> 0 | CC84: =SUM(CC79:CC83) -> 0 | CD84: =SUM(CD79:CD83) -> 0 | CE84: =SUM(CE79:CE83) -> 0 | CF84: =SUM(CF79:CF83) -> 0 | CG84: =SUM(CG79:CG83) -> 0 | CI84: =CC84=L84 -> 1 | CJ84: =CD84=M84 -> 1 | CK84: =CE84=N84 -> 1 | CL84: =CF84=O84 -> 1 | CM84: =CG84=P84 -> 1
E88: Recurring Benefits Total | I88: =SUM(I68, I76, I84) -> 0 | J88: =SUM(J68, J76, J84) -> 0 | K88: =SUM(K68, K76, K84) -> 0 | L88: =SUM(L68, L76, L84) -> 0 | M88: =SUM(M68, M76, M84) -> 0 | N88: =SUM(N68, N76, N84) -> 0 | O88: =SUM(O68, O76, O84) -> 0 | P88: =SUM(P68, P76, P84) -> 0 | T88: =SUM(T68, T76, T84) -> 0 | U88: =SUM(U68, U76, U84) -> 0 | V88: =SUM(V68, V76, V84) -> 0 | W88: =SUM(W68, W76, W84) -> 0 | X88: =SUM(X68, X76, X84) -> 0 | Y88: =SUM(Y68, Y76, Y84) -> 0 | Z88: =SUM(Z68, Z76, Z84) -> 0 | AA88: =SUM(AA68, AA76, AA84) -> 0 | ... CA88: =SUM(CA68, CA76, CA84) -> 0 | CC88: =SUM(CC68, CC76, CC84) -> 0 | CD88: =SUM(CD68, CD76, CD84) -> 0 | CE88: =SUM(CE68, CE76, CE84) -> 0 | CF88: =SUM(CF68, CF76, CF84) -> 0 | CG88: =SUM(CG68, CG76, CG84) -> 0 | CH88: =SUM(CH68, CH76, CH84) -> 0 | CI88: =CC88=L88 -> 1 | CJ88: =CD88=M88 -> 1 | CK88: =CE88=N88 -> 1 | CL88: =CF88=O88 -> 1 | CM88: =CG88=P88 -> 1
T90: 2026 | AF90: 2027 | AR90: 2028 | BD90: 2029 | BP90: 2030 | CI90: CHECK
D91: RECURRING COSTS TO ACHIEVE IMPACT | H91: Comment | I91: Baseline | J91: Goal | K91: Ann. Run Rate | L91: 2026 | M91: =L91+1 -> 2027 | N91: =M91+1 -> 2028 | O91: =N91+1 -> 2029 | P91: =O91+1 -> 2030 | Q91: Impacted BU | R91: Check | T91: 46023 | U91: =EOMONTH(T91, 1) -> 46081 | V91: =EOMONTH(U91, 1) -> 46112 | W91: =EOMONTH(V91, 1) -> 46142 | X91: =EOMONTH(W91, 1) -> 46173 | Y91: =EOMONTH(X91, 1) -> 46203 | Z91: =EOMONTH(Y91, 1) -> 46234 | AA91: =EOMONTH(Z91, 1) -> 46265 | AB91: =EOMONTH(AA91, 1) -> 46295 | ... CA91: =EOMONTH(BZ91, 1) -> 47848 | CC91: 2026 | CD91: =CC91+1 -> 2027 | CE91: =CD91+1 -> 2028 | CF91: =CE91+1 -> 2029 | CG91: =CF91+1 -> 2030 | CI91: 2026 | CJ91: =CI91+1 -> 2027 | CK91: =CJ91+1 -> 2028 | CL91: =CK91+1 -> 2029 | CM91: =CL91+1 -> 2030
E92: $USD M | I92: =$H$18 -> TTM 6/1/26 | J92: Future State | K92: Increment
E93: Revenue
I94: 0 | J94: 0 | K94: =J94-I94 -> 0 | R94: =IF(K94=P94, "", "Error") | CC94: =SUMIFS($T94:$CA94, $T$1:$CA$1, CC$63) -> 0 | CD94: =SUMIFS($T94:$CA94, $T$1:$CA$1, CD$63) -> 0 | CE94: =SUMIFS($T94:$CA94, $T$1:$CA$1, CE$63) -> 0 | CF94: =SUMIFS($T94:$CA94, $T$1:$CA$1, CF$63) -> 0 | CG94: =SUMIFS($T94:$CA94, $T$1:$CA$1, CG$63) -> 0 | CI94: =CC94=L94 -> 1 | CJ94: =CD94=M94 -> 1 | CK94: =CE94=N94 -> 1 | CL94: =CF94=O94 -> 1 | CM94: =CG94=P94 -> 1
I95: 0 | J95: 0 | K95: =J95-I95 -> 0 | R95: =IF(K95=P95, "", "Error") | CC95: =SUMIFS($T95:$CA95, $T$1:$CA$1, CC$63) -> 0 | CD95: =SUMIFS($T95:$CA95, $T$1:$CA$1, CD$63) -> 0 | CE95: =SUMIFS($T95:$CA95, $T$1:$CA$1, CE$63) -> 0 | CF95: =SUMIFS($T95:$CA95, $T$1:$CA$1, CF$63) -> 0 | CG95: =SUMIFS($T95:$CA95, $T$1:$CA$1, CG$63) -> 0 | CI95: =CC95=L95 -> 1 | CJ95: =CD95=M95 -> 1 | CK95: =CE95=N95 -> 1 | CL95: =CF95=O95 -> 1 | CM95: =CG95=P95 -> 1
E96: Revenue Subtotal | I96: =SUM(I94:I95) -> 0 | J96: =SUM(J94:J95) -> 0 | K96: =SUM(K94:K95) -> 0 | L96: =SUM(L94:L95) -> 0 | M96: =SUM(M94:M95) -> 0 | N96: =SUM(N94:N95) -> 0 | O96: =SUM(O94:O95) -> 0 | P96: =SUM(P94:P95) -> 0 | T96: =SUM(T94:T95) -> 0 | U96: =SUM(U94:U95) -> 0 | V96: =SUM(V94:V95) -> 0 | W96: =SUM(W94:W95) -> 0 | X96: =SUM(X94:X95) -> 0 | Y96: =SUM(Y94:Y95) -> 0 | Z96: =SUM(Z94:Z95) -> 0 | AA96: =SUM(AA94:AA95) -> 0 | ... CA96: =SUM(CA94:CA95) -> 0 | CC96: =SUM(CC94:CC95) -> 0 | CD96: =SUM(CD94:CD95) -> 0 | CE96: =SUM(CE94:CE95) -> 0 | CF96: =SUM(CF94:CF95) -> 0 | CG96: =SUM(CG94:CG95) -> 0 | CI96: =CC96=L96 -> 1 | CJ96: =CD96=M96 -> 1 | CK96: =CE96=N96 -> 1 | CL96: =CF96=O96 -> 1 | CM96: =CG96=P96 -> 1
E98: Cost of Sales
I99: 0 | J99: 0 | K99: =J99-I99 -> 0 | L99: 0 | M99: 0 | N99: 0 | O99: 0 | P99: 0 | R99: =IF(K99=P99, "", "Error") | CC99: =SUMIFS($T99:$CA99, $T$1:$CA$1, CC$63) -> 0 | CD99: =SUMIFS($T99:$CA99, $T$1:$CA$1, CD$63) -> 0 | CE99: =SUMIFS($T99:$CA99, $T$1:$CA$1, CE$63) -> 0 | CF99: =SUMIFS($T99:$CA99, $T$1:$CA$1, CF$63) -> 0 | CG99: =SUMIFS($T99:$CA99, $T$1:$CA$1, CG$63) -> 0 | CI99: =CC99=L99 -> 1 | CJ99: =CD99=M99 -> 1 | CK99: =CE99=N99 -> 1 | CL99: =CF99=O99 -> 1 | CM99: =CG99=P99 -> 1
I100: 0 | J100: 0 | K100: =J100-I100 -> 0 | L100: 0 | M100: 0 | N100: 0 | O100: 0 | P100: 0 | R100: =IF(K100=P100, "", "Error") | CC100: =SUMIFS($T100:$CA100, $T$1:$CA$1, CC$63) -> 0 | CD100: =SUMIFS($T100:$CA100, $T$1:$CA$1, CD$63) -> 0 | CE100: =SUMIFS($T100:$CA100, $T$1:$CA$1, CE$63) -> 0 | CF100: =SUMIFS($T100:$CA100, $T$1:$CA$1, CF$63) -> 0 | CG100: =SUMIFS($T100:$CA100, $T$1:$CA$1, CG$63) -> 0 | CI100: =CC100=L100 -> 1 | CJ100: =CD100=M100 -> 1 | CK100: =CE100=N100 -> 1 | CL100: =CF100=O100 -> 1 | CM100: =CG100=P100 -> 1
I101: 0 | J101: 0 | K101: =J101-I101 -> 0 | L101: 0 | M101: 0 | N101: 0 | O101: 0 | P101: 0 | R101: =IF(K101=P101, "", "Error") | CC101: =SUMIFS($T101:$CA101, $T$1:$CA$1, CC$63) -> 0 | CD101: =SUMIFS($T101:$CA101, $T$1:$CA$1, CD$63) -> 0 | CE101: =SUMIFS($T101:$CA101, $T$1:$CA$1, CE$63) -> 0 | CF101: =SUMIFS($T101:$CA101, $T$1:$CA$1, CF$63) -> 0 | CG101: =SUMIFS($T101:$CA101, $T$1:$CA$1, CG$63) -> 0 | CI101: =CC101=L101 -> 1 | CJ101: =CD101=M101 -> 1 | CK101: =CE101=N101 -> 1 | CL101: =CF101=O101 -> 1 | CM101: =CG101=P101 -> 1
I102: 0 | J102: 0 | K102: =J102-I102 -> 0 | L102: 0 | M102: 0 | N102: 0 | O102: 0 | P102: 0 | R102: =IF(K102=P102, "", "Error") | CC102: =SUMIFS($T102:$CA102, $T$1:$CA$1, CC$63) -> 0 | CD102: =SUMIFS($T102:$CA102, $T$1:$CA$1, CD$63) -> 0 | CE102: =SUMIFS($T102:$CA102, $T$1:$CA$1, CE$63) -> 0 | CF102: =SUMIFS($T102:$CA102, $T$1:$CA$1, CF$63) -> 0 | CG102: =SUMIFS($T102:$CA102, $T$1:$CA$1, CG$63) -> 0 | CI102: =CC102=L102 -> 1 | CJ102: =CD102=M102 -> 1 | CK102: =CE102=N102 -> 1 | CL102: =CF102=O102 -> 1 | CM102: =CG102=P102 -> 1
K103: =J103-I103 -> 0 | L103: 0 | M103: 0 | N103: 0 | O103: 0 | P103: 0
E104: Cost of Sales Subtotal | I104: =SUM(I99:I103) -> 0 | J104: =SUM(J99:J103) -> 0 | K104: =SUM(K99:K103) -> 0 | L104: =SUM(L99:L103) -> 0 | M104: =SUM(M99:M103) -> 0 | N104: =SUM(N99:N103) -> 0 | O104: =SUM(O99:O103) -> 0 | P104: =SUM(P99:P103) -> 0 | T104: =SUM(T99:T103) -> 0 | U104: =SUM(U99:U103) -> 0 | V104: =SUM(V99:V103) -> 0 | W104: =SUM(W99:W103) -> 0 | X104: =SUM(X99:X103) -> 0 | Y104: =SUM(Y99:Y103) -> 0 | Z104: =SUM(Z99:Z103) -> 0 | AA104: =SUM(AA99:AA103) -> 0 | ... CA104: =SUM(CA99:CA103) -> 0 | CC104: =SUM(CC99:CC103) -> 0 | CD104: =SUM(CD99:CD103) -> 0 | CE104: =SUM(CE99:CE103) -> 0 | CF104: =SUM(CF99:CF103) -> 0 | CG104: =SUM(CG99:CG103) -> 0 | CI104: =CC104=L104 -> 1 | CJ104: =CD104=M104 -> 1 | CK104: =CE104=N104 -> 1 | CL104: =CF104=O104 -> 1 | CM104: =CG104=P104 -> 1
E106: OPEX
E107: OPEX - Model / token consumption | H107: PENDING — placeholder, not data. Per-developer consumption (request #11) x adopted developers; scales with ramp | I107: 0 | J107: =I107+'SDLC-1 Model'!$K$105 -> 0 | K107: ='SDLC-1 Model'!$K$105 -> 0 | L107: ='SDLC-1 Model'!L105 -> 0 | M107: ='SDLC-1 Model'!M105 -> 0 | N107: ='SDLC-1 Model'!N105 -> 0 | O107: ='SDLC-1 Model'!O105 -> 0 | P107: ='SDLC-1 Model'!P105 -> 0 | Q107: CTO / SDLC | R107: =IF(K107=P107, "", "Error") | T107: ='SDLC-1 Model'!T105 -> 0 | U107: ='SDLC-1 Model'!U105 -> 0 | V107: ='SDLC-1 Model'!V105 -> 0 | W107: ='SDLC-1 Model'!W105 -> 0 | X107: ='SDLC-1 Model'!X105 -> 0 | Y107: ='SDLC-1 Model'!Y105 -> 0 | Z107: ='SDLC-1 Model'!Z105 -> 0 | AA107: ='SDLC-1 Model'!AA105 -> 0 | ... CA107: ='SDLC-1 Model'!CA105 -> 0 | CC107: =SUMIFS($T107:$CA107, $T$1:$CA$1, CC$63) -> 0 | CD107: =SUMIFS($T107:$CA107, $T$1:$CA$1, CD$63) -> 0 | CE107: =SUMIFS($T107:$CA107, $T$1:$CA$1, CE$63) -> 0 | CF107: =SUMIFS($T107:$CA107, $T$1:$CA$1, CF$63) -> 0 | CG107: =SUMIFS($T107:$CA107, $T$1:$CA$1, CG$63) -> 0 | CI107: =CC107=L107 -> 1 | CJ107: =CD107=M107 -> 1 | CK107: =CE107=N107 -> 1 | CL107: =CF107=O107 -> 1 | CM107: =CG107=P107 -> 1
E108: OPEX - Harness platform & tooling run | H108: PENDING — placeholder, not data. Ongoing platform/support run cost | I108: 0 | J108: =I108+'SDLC-1 Model'!$K$106 -> 0 | K108: ='SDLC-1 Model'!$K$106 -> 0 | L108: ='SDLC-1 Model'!L106 -> 0 | M108: ='SDLC-1 Model'!M106 -> 0 | N108: ='SDLC-1 Model'!N106 -> 0 | O108: ='SDLC-1 Model'!O106 -> 0 | P108: ='SDLC-1 Model'!P106 -> 0 | Q108: CTO / SDLC | R108: =IF(K108=P108, "", "Error") | T108: ='SDLC-1 Model'!T106 -> 0 | U108: ='SDLC-1 Model'!U106 -> 0 | V108: ='SDLC-1 Model'!V106 -> 0 | W108: ='SDLC-1 Model'!W106 -> 0 | X108: ='SDLC-1 Model'!X106 -> 0 | Y108: ='SDLC-1 Model'!Y106 -> 0 | Z108: ='SDLC-1 Model'!Z106 -> 0 | AA108: ='SDLC-1 Model'!AA106 -> 0 | ... CA108: ='SDLC-1 Model'!CA106 -> 0 | CC108: =SUMIFS($T108:$CA108, $T$1:$CA$1, CC$63) -> 0 | CD108: =SUMIFS($T108:$CA108, $T$1:$CA$1, CD$63) -> 0 | CE108: =SUMIFS($T108:$CA108, $T$1:$CA$1, CE$63) -> 0 | CF108: =SUMIFS($T108:$CA108, $T$1:$CA$1, CF$63) -> 0 | CG108: =SUMIFS($T108:$CA108, $T$1:$CA$1, CG$63) -> 0 | CI108: =CC108=L108 -> 1 | CJ108: =CD108=M108 -> 1 | CK108: =CE108=N108 -> 1 | CL108: =CF108=O108 -> 1 | CM108: =CG108=P108 -> 1
E109: OPEX - Champion / coaching capacity | H109: PENDING — placeholder, not data. Champion/coaching capacity plan | I109: 0 | J109: =I109+'SDLC-1 Model'!$K$107 -> 0 | K109: ='SDLC-1 Model'!$K$107 -> 0 | L109: ='SDLC-1 Model'!L107 -> 0 | M109: ='SDLC-1 Model'!M107 -> 0 | N109: ='SDLC-1 Model'!N107 -> 0 | O109: ='SDLC-1 Model'!O107 -> 0 | P109: ='SDLC-1 Model'!P107 -> 0 | Q109: CTO / SDLC | R109: =IF(K109=P109, "", "Error") | T109: ='SDLC-1 Model'!T107 -> 0 | U109: ='SDLC-1 Model'!U107 -> 0 | V109: ='SDLC-1 Model'!V107 -> 0 | W109: ='SDLC-1 Model'!W107 -> 0 | X109: ='SDLC-1 Model'!X107 -> 0 | Y109: ='SDLC-1 Model'!Y107 -> 0 | Z109: ='SDLC-1 Model'!Z107 -> 0 | AA109: ='SDLC-1 Model'!AA107 -> 0 | ... CA109: ='SDLC-1 Model'!CA107 -> 0 | CC109: =SUMIFS($T109:$CA109, $T$1:$CA$1, CC$63) -> 0 | CD109: =SUMIFS($T109:$CA109, $T$1:$CA$1, CD$63) -> 0 | CE109: =SUMIFS($T109:$CA109, $T$1:$CA$1, CE$63) -> 0 | CF109: =SUMIFS($T109:$CA109, $T$1:$CA$1, CF$63) -> 0 | CG109: =SUMIFS($T109:$CA109, $T$1:$CA$1, CG$63) -> 0 | CI109: =CC109=L109 -> 1 | CJ109: =CD109=M109 -> 1 | CK109: =CE109=N109 -> 1 | CL109: =CF109=O109 -> 1 | CM109: =CG109=P109 -> 1
I110: 0 | J110: 0 | K110: =J110-I110 -> 0 | L110: 0 | M110: 0 | N110: 0 | O110: 0 | P110: 0 | R110: =IF(K110=P110, "", "Error") | CC110: =SUMIFS($T110:$CA110, $T$1:$CA$1, CC$63) -> 0 | CD110: =SUMIFS($T110:$CA110, $T$1:$CA$1, CD$63) -> 0 | CE110: =SUMIFS($T110:$CA110, $T$1:$CA$1, CE$63) -> 0 | CF110: =SUMIFS($T110:$CA110, $T$1:$CA$1, CF$63) -> 0 | CG110: =SUMIFS($T110:$CA110, $T$1:$CA$1, CG$63) -> 0 | CI110: =CC110=L110 -> 1 | CJ110: =CD110=M110 -> 1 | CK110: =CE110=N110 -> 1 | CL110: =CF110=O110 -> 1 | CM110: =CG110=P110 -> 1
I111: 0 | J111: 0 | K111: =J111-I111 -> 0 | L111: 0 | M111: 0 | N111: 0 | O111: 0 | P111: 0 | R111: =IF(K111=P111, "", "Error") | CC111: =SUMIFS($T111:$CA111, $T$1:$CA$1, CC$63) -> 0 | CD111: =SUMIFS($T111:$CA111, $T$1:$CA$1, CD$63) -> 0 | CE111: =SUMIFS($T111:$CA111, $T$1:$CA$1, CE$63) -> 0 | CF111: =SUMIFS($T111:$CA111, $T$1:$CA$1, CF$63) -> 0 | CG111: =SUMIFS($T111:$CA111, $T$1:$CA$1, CG$63) -> 0 | CI111: =CC111=L111 -> 1 | CJ111: =CD111=M111 -> 1 | CK111: =CE111=N111 -> 1 | CL111: =CF111=O111 -> 1 | CM111: =CG111=P111 -> 1
E112: OpEx subtotal | I112: =SUM(I107:I111) -> 0 | J112: =SUM(J107:J111) -> 0 | K112: =SUM(K107:K111) -> 0 | L112: =SUM(L107:L111) -> 0 | M112: =SUM(M107:M111) -> 0 | N112: =SUM(N107:N111) -> 0 | O112: =SUM(O107:O111) -> 0 | P112: =SUM(P107:P111) -> 0 | T112: =SUM(T107:T111) -> 0 | U112: =SUM(U107:U111) -> 0 | V112: =SUM(V107:V111) -> 0 | W112: =SUM(W107:W111) -> 0 | X112: =SUM(X107:X111) -> 0 | Y112: =SUM(Y107:Y111) -> 0 | Z112: =SUM(Z107:Z111) -> 0 | AA112: =SUM(AA107:AA111) -> 0 | ... CA112: =SUM(CA107:CA111) -> 0 | CC112: =SUM(CC107:CC111) -> 0 | CD112: =SUM(CD107:CD111) -> 0 | CE112: =SUM(CE107:CE111) -> 0 | CF112: =SUM(CF107:CF111) -> 0 | CG112: =SUM(CG107:CG111) -> 0 | CI112: =CC112=L112 -> 1 | CJ112: =CD112=M112 -> 1 | CK112: =CE112=N112 -> 1 | CL112: =CF112=O112 -> 1 | CM112: =CG112=P112 -> 1
E115: Recurring Costs Total | I115: =SUM(-I96, I104, I112) -> 0 | J115: =SUM(-J96, J104, J112) -> 0 | K115: =SUM(-K96, K104, K112) -> 0 | L115: =SUM(-L96, L104, L112) -> 0 | M115: =SUM(-M96, M104, M112) -> 0 | N115: =SUM(-N96, N104, N112) -> 0 | O115: =SUM(-O96, O104, O112) -> 0 | P115: =SUM(-P96, P104, P112) -> 0 | T115: =SUM(-T96, T104, T112) -> 0 | U115: =SUM(-U96, U104, U112) -> 0 | V115: =SUM(-V96, V104, V112) -> 0 | W115: =SUM(-W96, W104, W112) -> 0 | X115: =SUM(-X96, X104, X112) -> 0 | Y115: =SUM(-Y96, Y104, Y112) -> 0 | Z115: =SUM(-Z96, Z104, Z112) -> 0 | AA115: =SUM(-AA96, AA104, AA112) -> 0 | ... CA115: =SUM(-CA96, CA104, CA112) -> 0 | CC115: =SUM(-CC96, CC104, CC112) -> 0 | CD115: =SUM(-CD96, CD104, CD112) -> 0 | CE115: =SUM(-CE96, CE104, CE112) -> 0 | CF115: =SUM(-CF96, CF104, CF112) -> 0 | CG115: =SUM(-CG96, CG104, CG112) -> 0 | CI115: =CC115=L115 -> 1 | CJ115: =CD115=M115 -> 1 | CK115: =CE115=N115 -> 1 | CL115: =CF115=O115 -> 1 | CM115: =CG115=P115 -> 1
E117: Net Recurring Benefit | I117: =SUM(I88, -I115) -> 0 | J117: =SUM(J88, -J115) -> 0 | K117: =SUM(K88, -K115) -> 0 | L117: =SUM(L88, -L115) -> 0 | M117: =SUM(M88, -M115) -> 0 | N117: =SUM(N88, -N115) -> 0 | O117: =SUM(O88, -O115) -> 0 | P117: =SUM(P88, -P115) -> 0 | R117: =IF(K117=P117, "", "Error") | T117: =SUM(T88, -T115) -> 0 | U117: =SUM(U88, -U115) -> 0 | V117: =SUM(V88, -V115) -> 0 | W117: =SUM(W88, -W115) -> 0 | X117: =SUM(X88, -X115) -> 0 | Y117: =SUM(Y88, -Y115) -> 0 | Z117: =SUM(Z88, -Z115) -> 0 | AA117: =SUM(AA88, -AA115) -> 0 | ... CA117: =SUM(CA88, -CA115) -> 0 | CC117: =SUM(CC88, -CC115) -> 0 | CD117: =SUM(CD88, -CD115) -> 0 | CE117: =SUM(CE88, -CE115) -> 0 | CF117: =SUM(CF88, -CF115) -> 0 | CG117: =SUM(CG88, -CG115) -> 0 | CI117: =CC117=L117 -> 1 | CJ117: =CD117=M117 -> 1 | CK117: =CE117=N117 -> 1 | CL117: =CF117=O117 -> 1 | CM117: =CG117=P117 -> 1
C120: SECTION III - ONE-TIME IMPLEMENTATION | CC120: ANNUAL SUMMARY | CI120: CHECK CELLS
T122: 2026 | AF122: 2027 | AR122: 2028 | BD122: 2029 | BP122: 2030
D123: ONE-TIME BENEFITS | K123: Comment | L123: 2026 | M123: =L123+1 -> 2027 | N123: =M123+1 -> 2028 | O123: =N123+1 -> 2029 | P123: =O123+1 -> 2030 | Q123: Impacted BU | T123: 46023 | U123: =EOMONTH(T123, 1) -> 46081 | V123: =EOMONTH(U123, 1) -> 46112 | W123: =EOMONTH(V123, 1) -> 46142 | X123: =EOMONTH(W123, 1) -> 46173 | Y123: =EOMONTH(X123, 1) -> 46203 | Z123: =EOMONTH(Y123, 1) -> 46234 | AA123: =EOMONTH(Z123, 1) -> 46265 | AB123: =EOMONTH(AA123, 1) -> 46295 | ... CA123: =EOMONTH(BZ123, 1) -> 47848 | CC123: 2026 | CD123: =CC123+1 -> 2027 | CE123: =CD123+1 -> 2028 | CF123: =CE123+1 -> 2029 | CG123: =CF123+1 -> 2030 | CI123: 2026 | CJ123: =CI123+1 -> 2027 | CK123: =CJ123+1 -> 2028 | CL123: =CK123+1 -> 2029 | CM123: =CL123+1 -> 2030
E125: Working Capital
CC126: =SUMIFS($T126:$CA126, $T$1:$CA$1, CC$63) -> 0 | CD126: =SUMIFS($T126:$CA126, $T$1:$CA$1, CD$63) -> 0 | CE126: =SUMIFS($T126:$CA126, $T$1:$CA$1, CE$63) -> 0 | CF126: =SUMIFS($T126:$CA126, $T$1:$CA$1, CF$63) -> 0 | CG126: =SUMIFS($T126:$CA126, $T$1:$CA$1, CG$63) -> 0 | CI126: =CC126=L126 -> 1 | CJ126: =CD126=M126 -> 1 | CK126: =CE126=N126 -> 1 | CL126: =CF126=O126 -> 1 | CM126: =CG126=P126 -> 1
CC127: =SUMIFS($T127:$CA127, $T$1:$CA$1, CC$63) -> 0 | CD127: =SUMIFS($T127:$CA127, $T$1:$CA$1, CD$63) -> 0 | CE127: =SUMIFS($T127:$CA127, $T$1:$CA$1, CE$63) -> 0 | CF127: =SUMIFS($T127:$CA127, $T$1:$CA$1, CF$63) -> 0 | CG127: =SUMIFS($T127:$CA127, $T$1:$CA$1, CG$63) -> 0 | CI127: =CC127=L127 -> 1 | CJ127: =CD127=M127 -> 1 | CK127: =CE127=N127 -> 1 | CL127: =CF127=O127 -> 1 | CM127: =CG127=P127 -> 1
E128: Working Capital Subtotal | L128: =SUM(L126:L127) -> 0 | M128: =SUM(M126:M127) -> 0 | N128: =SUM(N126:N127) -> 0 | O128: =SUM(O126:O127) -> 0 | P128: =SUM(P126:P127) -> 0 | T128: =SUM(T126:T127) -> 0 | U128: =SUM(U126:U127) -> 0 | V128: =SUM(V126:V127) -> 0 | W128: =SUM(W126:W127) -> 0 | X128: =SUM(X126:X127) -> 0 | Y128: =SUM(Y126:Y127) -> 0 | Z128: =SUM(Z126:Z127) -> 0 | AA128: =SUM(AA126:AA127) -> 0 | ... CA128: =SUM(CA126:CA127) -> 0 | CC128: =SUM(CC126:CC127) -> 0 | CD128: =SUM(CD126:CD127) -> 0 | CE128: =SUM(CE126:CE127) -> 0 | CF128: =SUM(CF126:CF127) -> 0 | CG128: =SUM(CG126:CG127) -> 0 | CI128: =CC128=L128 -> 1 | CJ128: =CD128=M128 -> 1 | CK128: =CE128=N128 -> 1 | CL128: =CF128=O128 -> 1 | CM128: =CG128=P128 -> 1
E130: One-Time Benefits Total | L130: =L128 -> 0 | M130: =M128 -> 0 | N130: =N128 -> 0 | O130: =O128 -> 0 | P130: =P128 -> 0 | T130: =T128 -> 0 | U130: =U128 -> 0 | V130: =V128 -> 0 | W130: =W128 -> 0 | X130: =X128 -> 0 | Y130: =Y128 -> 0 | Z130: =Z128 -> 0 | AA130: =AA128 -> 0 | ... CA130: =CA128 -> 0 | CC130: =CC128 -> 0 | CD130: =CD128 -> 0 | CE130: =CE128 -> 0 | CF130: =CF128 -> 0 | CG130: =CG128 -> 0 | CI130: =CI128 -> 1 | CJ130: =CJ128 -> 1 | CK130: =CK128 -> 1 | CL130: =CL128 -> 1 | CM130: =CM128 -> 1
T132: 2026 | AF132: 2027 | AR132: 2028 | BD132: 2029 | BP132: 2030
D133: CAPEX AND ONE-TIME COSTS | K133: Comment | L133: 2026 | M133: =L133+1 -> 2027 | N133: =M133+1 -> 2028 | O133: =N133+1 -> 2029 | P133: =O133+1 -> 2030 | T133: 46023 | U133: =EOMONTH(T133, 1) -> 46081 | V133: =EOMONTH(U133, 1) -> 46112 | W133: =EOMONTH(V133, 1) -> 46142 | X133: =EOMONTH(W133, 1) -> 46173 | Y133: =EOMONTH(X133, 1) -> 46203 | Z133: =EOMONTH(Y133, 1) -> 46234 | AA133: =EOMONTH(Z133, 1) -> 46265 | AB133: =EOMONTH(AA133, 1) -> 46295 | ... CA133: =EOMONTH(BZ133, 1) -> 47848 | CC133: 2026 | CD133: =CC133+1 -> 2027 | CE133: =CD133+1 -> 2028 | CF133: =CE133+1 -> 2029 | CG133: =CF133+1 -> 2030 | CI133: 2026 | CJ133: =CI133+1 -> 2027 | CK133: =CJ133+1 -> 2028 | CL133: =CK133+1 -> 2029 | CM133: =CL133+1 -> 2030
E135: Capital Expenditures
E136: CAPEX — capitalized build labor | L136: ='SDLC-1 Model'!L91 -> 0.10530667 | M136: ='SDLC-1 Model'!M91 -> 0.42122667 | N136: ='SDLC-1 Model'!N91 -> 0 | O136: ='SDLC-1 Model'!O91 -> 0 | P136: ='SDLC-1 Model'!P91 -> 0 | Q136: CTO / SDLC | T136: ='SDLC-1 Model'!T91 -> 0 | U136: ='SDLC-1 Model'!U91 -> 0 | V136: ='SDLC-1 Model'!V91 -> 0 | W136: ='SDLC-1 Model'!W91 -> 0 | X136: ='SDLC-1 Model'!X91 -> 0 | Y136: ='SDLC-1 Model'!Y91 -> 0 | Z136: ='SDLC-1 Model'!Z91 -> 0 | AA136: ='SDLC-1 Model'!AA91 -> 0 | ... CA136: ='SDLC-1 Model'!CA91 -> 0 | CC136: =SUMIFS($T136:$CA136, $T$1:$CA$1, CC$63) -> 0.10530667 | CD136: =SUMIFS($T136:$CA136, $T$1:$CA$1, CD$63) -> 0.42122667 | CE136: =SUMIFS($T136:$CA136, $T$1:$CA$1, CE$63) -> 0 | CF136: =SUMIFS($T136:$CA136, $T$1:$CA$1, CF$63) -> 0 | CG136: =SUMIFS($T136:$CA136, $T$1:$CA$1, CG$63) -> 0 | CI136: =CC136=L136 -> 1 | CJ136: =CD136=M136 -> 1 | CK136: =CE136=N136 -> 1 | CL136: =CF136=O136 -> 1 | CM136: =CG136=P136 -> 1
E137: CAPEX — capitalized non-labor | L137: ='SDLC-1 Model'!L92 -> 0 | M137: ='SDLC-1 Model'!M92 -> 0 | N137: ='SDLC-1 Model'!N92 -> 0 | O137: ='SDLC-1 Model'!O92 -> 0 | P137: ='SDLC-1 Model'!P92 -> 0 | Q137: CTO / SDLC | T137: ='SDLC-1 Model'!T92 -> 0 | U137: ='SDLC-1 Model'!U92 -> 0 | V137: ='SDLC-1 Model'!V92 -> 0 | W137: ='SDLC-1 Model'!W92 -> 0 | X137: ='SDLC-1 Model'!X92 -> 0 | Y137: ='SDLC-1 Model'!Y92 -> 0 | Z137: ='SDLC-1 Model'!Z92 -> 0 | AA137: ='SDLC-1 Model'!AA92 -> 0 | ... CA137: ='SDLC-1 Model'!CA92 -> 0 | CC137: =SUMIFS($T137:$CA137, $T$1:$CA$1, CC$63) -> 0 | CD137: =SUMIFS($T137:$CA137, $T$1:$CA$1, CD$63) -> 0 | CE137: =SUMIFS($T137:$CA137, $T$1:$CA$1, CE$63) -> 0 | CF137: =SUMIFS($T137:$CA137, $T$1:$CA$1, CF$63) -> 0 | CG137: =SUMIFS($T137:$CA137, $T$1:$CA$1, CG$63) -> 0 | CI137: =CC137=L137 -> 1 | CJ137: =CD137=M137 -> 1 | CK137: =CE137=N137 -> 1 | CL137: =CF137=O137 -> 1 | CM137: =CG137=P137 -> 1
E138: Capital Expenditures Subtotal | L138: =SUM(L136:L137) -> 0.10530667 | M138: =SUM(M136:M137) -> 0.42122667 | N138: =SUM(N136:N137) -> 0 | O138: =SUM(O136:O137) -> 0 | P138: =SUM(P136:P137) -> 0 | T138: =SUM(T136:T137) -> 0 | U138: =SUM(U136:U137) -> 0 | V138: =SUM(V136:V137) -> 0 | W138: =SUM(W136:W137) -> 0 | X138: =SUM(X136:X137) -> 0 | Y138: =SUM(Y136:Y137) -> 0 | Z138: =SUM(Z136:Z137) -> 0 | AA138: =SUM(AA136:AA137) -> 0 | ... CA138: =SUM(CA136:CA137) -> 0 | CC138: =SUM(CC136:CC137) -> 0.10530667 | CD138: =SUM(CD136:CD137) -> 0.42122667 | CE138: =SUM(CE136:CE137) -> 0 | CF138: =SUM(CF136:CF137) -> 0 | CG138: =SUM(CG136:CG137) -> 0 | CI138: =CC138=L138 -> 1 | CJ138: =CD138=M138 -> 1 | CK138: =CE138=N138 -> 1 | CL138: =CF138=O138 -> 1 | CM138: =CG138=P138 -> 1
E140: OTC
E141: OTC — build labor (expensed) | L141: ='SDLC-1 Model'!L93 -> 0.15796 | M141: ='SDLC-1 Model'!M93 -> 0.59893167 | N141: ='SDLC-1 Model'!N93 -> 0 | O141: ='SDLC-1 Model'!O93 -> 0 | P141: ='SDLC-1 Model'!P93 -> 0 | Q141: CTO / SDLC | T141: ='SDLC-1 Model'!T93 -> 0 | U141: ='SDLC-1 Model'!U93 -> 0 | V141: ='SDLC-1 Model'!V93 -> 0 | W141: ='SDLC-1 Model'!W93 -> 0 | X141: ='SDLC-1 Model'!X93 -> 0 | Y141: ='SDLC-1 Model'!Y93 -> 0 | Z141: ='SDLC-1 Model'!Z93 -> 0 | AA141: ='SDLC-1 Model'!AA93 -> 0 | ... CA141: ='SDLC-1 Model'!CA93 -> 0 | CC141: =SUMIFS($T141:$CA141, $T$1:$CA$1, CC$63) -> 0.15796 | CD141: =SUMIFS($T141:$CA141, $T$1:$CA$1, CD$63) -> 0.59893167 | CE141: =SUMIFS($T141:$CA141, $T$1:$CA$1, CE$63) -> 0 | CF141: =SUMIFS($T141:$CA141, $T$1:$CA$1, CF$63) -> 0 | CG141: =SUMIFS($T141:$CA141, $T$1:$CA$1, CG$63) -> 0 | CI141: =CC141=L141 -> 1 | CJ141: =CD141=M141 -> 1 | CK141: =CE141=N141 -> 1 | CL141: =CF141=O141 -> 1 | CM141: =CG141=P141 -> 1
E142: OTC — non-labor (expensed) | L142: ='SDLC-1 Model'!L94 -> 0.080427967 | M142: ='SDLC-1 Model'!M94 -> 0.16085593 | N142: ='SDLC-1 Model'!N94 -> 0 | O142: ='SDLC-1 Model'!O94 -> 0 | P142: ='SDLC-1 Model'!P94 -> 0 | Q142: CTO / SDLC | T142: ='SDLC-1 Model'!T94 -> 0 | U142: ='SDLC-1 Model'!U94 -> 0 | V142: ='SDLC-1 Model'!V94 -> 0 | W142: ='SDLC-1 Model'!W94 -> 0 | X142: ='SDLC-1 Model'!X94 -> 0 | Y142: ='SDLC-1 Model'!Y94 -> 0 | Z142: ='SDLC-1 Model'!Z94 -> 0 | AA142: ='SDLC-1 Model'!AA94 -> 0 | ... CA142: ='SDLC-1 Model'!CA94 -> 0 | CC142: =SUMIFS($T142:$CA142, $T$1:$CA$1, CC$63) -> 0.080427967 | CD142: =SUMIFS($T142:$CA142, $T$1:$CA$1, CD$63) -> 0.16085593 | CE142: =SUMIFS($T142:$CA142, $T$1:$CA$1, CE$63) -> 0 | CF142: =SUMIFS($T142:$CA142, $T$1:$CA$1, CF$63) -> 0 | CG142: =SUMIFS($T142:$CA142, $T$1:$CA$1, CG$63) -> 0 | CI142: =CC142=L142 -> 1 | CJ142: =CD142=M142 -> 1 | CK142: =CE142=N142 -> 1 | CL142: =CF142=O142 -> 1 | CM142: =CG142=P142 -> 1
CC143: =SUMIFS($T143:$CA143, $T$1:$CA$1, CC$63) -> 0 | CD143: =SUMIFS($T143:$CA143, $T$1:$CA$1, CD$63) -> 0 | CE143: =SUMIFS($T143:$CA143, $T$1:$CA$1, CE$63) -> 0 | CF143: =SUMIFS($T143:$CA143, $T$1:$CA$1, CF$63) -> 0 | CG143: =SUMIFS($T143:$CA143, $T$1:$CA$1, CG$63) -> 0 | CI143: =CC143=L143 -> 1 | CJ143: =CD143=M143 -> 1 | CK143: =CE143=N143 -> 1 | CL143: =CF143=O143 -> 1 | CM143: =CG143=P143 -> 1
E144: OTC Subtotal | L144: =SUM(L141:L143) -> 0.23838797 | M144: =SUM(M141:M143) -> 0.7597876 | N144: =SUM(N141:N143) -> 0 | O144: =SUM(O141:O143) -> 0 | P144: =SUM(P141:P143) -> 0 | T144: =SUM(T141:T143) -> 0 | U144: =SUM(U141:U143) -> 0 | V144: =SUM(V141:V143) -> 0 | W144: =SUM(W141:W143) -> 0 | X144: =SUM(X141:X143) -> 0 | Y144: =SUM(Y141:Y143) -> 0 | Z144: =SUM(Z141:Z143) -> 0 | AA144: =SUM(AA141:AA143) -> 0 | ... CA144: =SUM(CA141:CA143) -> 0 | CC144: =SUM(CC141:CC143) -> 0.23838797 | CD144: =SUM(CD141:CD143) -> 0.7597876 | CE144: =SUM(CE141:CE143) -> 0 | CF144: =SUM(CF141:CF143) -> 0 | CG144: =SUM(CG141:CG143) -> 0 | CI144: =CC144=L144 -> 1 | CJ144: =CD144=M144 -> 1 | CK144: =CE144=N144 -> 1 | CL144: =CF144=O144 -> 1 | CM144: =CG144=P144 -> 1
E147: One-Time Costs Total | L147: =SUM(L138, L144) -> 0.34369463 | M147: =SUM(M138, M144) -> 1.1810143 | N147: =SUM(N138, N144) -> 0 | O147: =SUM(O138, O144) -> 0 | P147: =SUM(P138, P144) -> 0 | T147: =SUM(T138, T144) -> 0 | U147: =SUM(U138, U144) -> 0 | V147: =SUM(V138, V144) -> 0 | W147: =SUM(W138, W144) -> 0 | X147: =SUM(X138, X144) -> 0 | Y147: =SUM(Y138, Y144) -> 0 | Z147: =SUM(Z138, Z144) -> 0 | AA147: =SUM(AA138, AA144) -> 0 | ... CA147: =SUM(CA138, CA144) -> 0 | CC147: =SUM(CC138, CC144) -> 0.34369463 | CD147: =SUM(CD138, CD144) -> 1.1810143 | CE147: =SUM(CE138, CE144) -> 0 | CF147: =SUM(CF138, CF144) -> 0 | CG147: =SUM(CG138, CG144) -> 0 | CI147: =CC147=L147 -> 1 | CJ147: =CD147=M147 -> 1 | CK147: =CE147=N147 -> 1 | CL147: =CF147=O147 -> 1 | CM147: =CG147=P147 -> 1
E149: Total One-Time Implementation Cost | L149: =SUM(L130, -L147) -> -0.34369463 | M149: =SUM(M130, -M147) -> -1.1810143 | N149: =SUM(N130, -N147) -> 0 | O149: =SUM(O130, -O147) -> 0 | P149: =SUM(P130, -P147) -> 0 | T149: =SUM(T130, -T147) -> 0 | U149: =SUM(U130, -U147) -> 0 | V149: =SUM(V130, -V147) -> 0 | W149: =SUM(W130, -W147) -> 0 | X149: =SUM(X130, -X147) -> 0 | Y149: =SUM(Y130, -Y147) -> 0 | Z149: =SUM(Z130, -Z147) -> 0 | AA149: =SUM(AA130, -AA147) -> 0 | ... CA149: =SUM(CA130, -CA147) -> 0 | CC149: =SUM(CC130, -CC147) -> -0.34369463 | CD149: =SUM(CD130, -CD147) -> -1.1810143 | CE149: =SUM(CE130, -CE147) -> 0 | CF149: =SUM(CF130, -CF147) -> 0 | CG149: =SUM(CG130, -CG147) -> 0 | CI149: =CC149=L149 -> 1 | CJ149: =CD149=M149 -> 1 | CK149: =CE149=N149 -> 1 | CL149: =CF149=O149 -> 1 | CM149: =CG149=P149 -> 1
C152: SECTION IV - FINANCIAL METRICS | CC152: ANNUAL SUMMARY | CI152: CHECK CELLS
E155: Cash Flow | L155: 2026 | M155: =L155+1 -> 2027 | N155: =M155+1 -> 2028 | O155: =N155+1 -> 2029 | P155: =O155+1 -> 2030 | Q155: Total
E156: Operating Income | L156: =L117 -> 0 | M156: =M117 -> 0 | N156: =N117 -> 0 | O156: =O117 -> 0 | P156: =P117 -> 0 | Q156: =SUM(L156:P156) -> 0
E157: (+) One-Time Benefits | L157: =L130 -> 0 | M157: =M130 -> 0 | N157: =N130 -> 0 | O157: =O130 -> 0 | P157: =P130 -> 0 | Q157: =SUM(L157:P157) -> 0
E158: (-) One-Time Cash Costs | L158: =-L147 -> -0.34369463 | M158: =-M147 -> -1.1810143 | N158: =-N147 -> 0 | O158: =-O147 -> 0 | P158: =-P147 -> 0 | Q158: =SUM(L158:P158) -> -1.5247089
E159: Cash Flow | L159: =SUM(L156:L158) -> -0.34369463 | M159: =SUM(M156:M158) -> -1.1810143 | N159: =SUM(N156:N158) -> 0 | O159: =SUM(O156:O158) -> 0 | P159: =SUM(P156:P158) -> 0 | Q159: =SUM(L159:P159) -> -1.5247089
E160: Cumulative Cash Flow | L160: =L159 -> -0.34369463 | M160: =L160+M159 -> -1.5247089 | N160: =M160+N159 -> -1.5247089 | O160: =N160+O159 -> -1.5247089 | P160: =O160+P159 -> -1.5247089 | Q160: =P160 -> -1.5247089
E161: Payback timeline | L161: =IF(L160<0,1,0) -> 1 | M161: =IF(M160<0,1,IF(AND(L160<0,M159>0),-L160/M159,0)) -> 1 | N161: =IF(N160<0,1,IF(AND(M160<0,N159>0),-M160/N159,0)) -> 1 | O161: =IF(O160<0,1,IF(AND(N160<0,O159>0),-N160/O159,0)) -> 1 | P161: =IF(P160<0,1,IF(AND(O160<0,P159>0),-O160/P159,0)) -> 1
E163: Return on Investment | F163: NRB/OTC | G163: =IFERROR(K117/-SUM(L149:P149),"n/a") -> 0
E164: Internal Rate of Return | F164: 5-yr IRR | G164: =IFERROR(IRR($L$159:$P$159, 0.2),"n/a") -> n/a
E165: Breakeven timeline | F165: # yrs | G165: =IF(SUM(L161:P161)=5,">5",SUM(L161:P161)) -> >5
E167: WACC | G167: 0.095
E168: NPV | F168: $ | G168: =SUM(L168:P168) -> -1.2988552 | L168: =L159/(1+$G$167)^L$1 -> -0.31387638 | M168: =M159/(1+$G$167)^M$1 -> -0.98497885 | N168: =N159/(1+$G$167)^N$1 -> 0 | O168: =O159/(1+$G$167)^O$1 -> 0 | P168: =P159/(1+$G$167)^P$1 -> 0 | Q168: =SUM(L168:P168) -> -1.2988552
C171: END

Sheet SDLC-2 Model
B2: SDLC-2 — PDLC Re-imagination | INITIATIVE MODEL
B3: Workstream: SDLC (ELT sponsor: Srini | WSL: Pooja | IOs: Pooja, Aruna) • Model status: Structure ready; baselines PENDING data requests — see open items
T5: 2026 | U5: 2026 | V5: 2026 | W5: 2026 | X5: 2026 | Y5: 2026 | Z5: 2026 | AA5: 2026 | AB5: 2026 | AC5: 2026 | AD5: 2026 | AE5: 2026 | AF5: 2027 | AG5: 2027 | AH5: 2027 | AI5: 2027 | AJ5: 2027 | AK5: 2027 | AL5: 2027 | AM5: 2027 | AN5: 2027 | AO5: 2027 | AP5: 2027 | AQ5: 2027 | AR5: 2028 | AS5: 2028 | AT5: 2028 | AU5: 2028 | AV5: 2028 | AW5: 2028 | AX5: 2028 | AY5: 2028 | AZ5: 2028 | BA5: 2028 | BB5: 2028 | BC5: 2028 | BD5: 2029 | BE5: 2029 | BF5: 2029 | BG5: 2029 | BH5: 2029 | BI5: 2029 | BJ5: 2029 | BK5: 2029 | BL5: 2029 | BM5: 2029 | BN5: 2029 | BO5: 2029 | BP5: 2030 | BQ5: 2030 | BR5: 2030 | BS5: 2030 | BT5: 2030 | BU5: 2030 | BV5: 2030 | BW5: 2030 | BX5: 2030 | BY5: 2030 | BZ5: 2030 | CA5: 2030
B6: Monthly grid (Jan-26 → Dec-30) → | K6: Run rate | L6: 2026 | M6: 2027 | N6: 2028 | O6: 2029 | P6: 2030 | T6: =DATE(2026,1,31) -> 46053 | U6: =EOMONTH(T6,1) -> 46081 | V6: =EOMONTH(U6,1) -> 46112 | W6: =EOMONTH(V6,1) -> 46142 | X6: =EOMONTH(W6,1) -> 46173 | Y6: =EOMONTH(X6,1) -> 46203 | Z6: =EOMONTH(Y6,1) -> 46234 | AA6: =EOMONTH(Z6,1) -> 46265 | AB6: =EOMONTH(AA6,1) -> 46295 | ... CA6: =EOMONTH(BZ6,1) -> 47848
B8: 0. INITIATIVE & STATUS
B10: Initiative name | D10: PDLC re-imagination — agentic product development lifecycle across product, program and design
B11: Initiative owner | D11: Aruna (IO) — TBC | I11: confirm with workstream lead
B12: Impacted BU | D12: CTO / SDLC
B13: Go-live / Estimated L4 date | D13: =DATE(2027,6,1) -> 46539 | I13: Benefit ramp is gated on this date.
B15: Source: Workplan: 'Project Zenith Automation workplan and data requests vS_1.xlsx', SDLC tab + SDLC Data Requests tab
B16: Source: Impact ranges: Aug 13 deck pp. 9, 19–21; Board deck pp. 12, 22 (preliminary — Finance to validate)
B17: Open items to refine with initiative owner:
B18: – Product/program/design FTE population and cost pending (SDLC data request #1, PDLC side — ETO; 'back on McK' for time-spent validation, request #2).
B19: – PDLC output baseline (PRDs, epics, specs, releases) pending — request #4; converts uplift to capacity.
B20: – PDLC tooling & spend baseline (Figma, PRD gen, Jira) pending — request #5; sizes investment and nets run cost.
B21: – Build shape mirrors the Servicing S2 delivery pod as a placeholder — refine with IOs before S3.
B23: 1. SIZING ASSUMPTIONS (blue = inputs — refine with initiative owner)
B25: Baseline / denominator (PENDING data request #1 — PDLC side)
B26: Product + program + design FTE population — in scope | D26: 0 | E26: # FTE | F26: PENDING — placeholder, not data. Data request #1 (ETO)
B27: Avg fully loaded cost per PDLC FTE | D27: 0 | E27: $/yr | F27: PENDING — placeholder, not data. Data request #1
B28: Impact drivers (Aug 13 deck pp. 9, 19–21 — preliminary)
B29: PDLC productivity lift across product/program/design | D29: 0.2 | E29: % | F29: PLACEHOLDER — refine with time-spent-by-activity data (request #2)
B30: Steady-state adoption | D30: 0.75 | E30: % | F30: PLACEHOLDER
B31: Capture rate — capacity converted to bankable cost | D31: 0.65 | E31: % | F31: PLACEHOLDER — align with SDLC-1 capture logic
B32: Investment uplifts (consistent with Servicing S2 standard)
B33: Programme management, % of build | D33: 0.08 | E33: %
B34: Contingency, % of build incl. PM | D34: 0.1 | E34: %
B35: (spare assumption row)
B36: (spare assumption row)
B38: 2. BENEFIT CALCULATION (steady-state annual run-rate)
B40: Total in-scope PDLC labor base | D40: =$D$26*$D$27 -> 0 | E40: $/yr
B41: Gross capacity value created | D41: =$D$40*$D$29*$D$30 -> 0 | E41: $/yr
B42: Bankable annual benefit (steady state) | D42: =$D$41*$D$31 -> 0 | E42: $/yr | F42: Feeds WAVE benefit line
B44: 3. RAMP & PHASING
B46: Months to full run rate after go-live (linear ramp) | D46: 12 | F46: Benefit starts at go-live and ramps linearly to steady state over this many months.
B47: Monthly ramp % (run-rate captured in month) | T47: =MIN(1,MAX(0,((YEAR(T$6)-YEAR($D$13))*12+MONTH(T$6)-MONTH($D$13)+0.5)/MAX($D$46,0.5))) -> 0 | U47: =MIN(1,MAX(0,((YEAR(U$6)-YEAR($D$13))*12+MONTH(U$6)-MONTH($D$13)+0.5)/MAX($D$46,0.5))) -> 0 | V47: =MIN(1,MAX(0,((YEAR(V$6)-YEAR($D$13))*12+MONTH(V$6)-MONTH($D$13)+0.5)/MAX($D$46,0.5))) -> 0 | W47: =MIN(1,MAX(0,((YEAR(W$6)-YEAR($D$13))*12+MONTH(W$6)-MONTH($D$13)+0.5)/MAX($D$46,0.5))) -> 0 | X47: =MIN(1,MAX(0,((YEAR(X$6)-YEAR($D$13))*12+MONTH(X$6)-MONTH($D$13)+0.5)/MAX($D$46,0.5))) -> 0 | Y47: =MIN(1,MAX(0,((YEAR(Y$6)-YEAR($D$13))*12+MONTH(Y$6)-MONTH($D$13)+0.5)/MAX($D$46,0.5))) -> 0 | Z47: =MIN(1,MAX(0,((YEAR(Z$6)-YEAR($D$13))*12+MONTH(Z$6)-MONTH($D$13)+0.5)/MAX($D$46,0.5))) -> 0 | AA47: =MIN(1,MAX(0,((YEAR(AA$6)-YEAR($D$13))*12+MONTH(AA$6)-MONTH($D$13)+0.5)/MAX($D$46,0.5))) -> 0 | ... CA47: =MIN(1,MAX(0,((YEAR(CA$6)-YEAR($D$13))*12+MONTH(CA$6)-MONTH($D$13)+0.5)/MAX($D$46,0.5))) -> 1
B48: Resulting average ramp % by year (info) | L48: =SUMIFS($T47:$CA47,$T$5:$CA$5,2026)/12 -> 0 | M48: =SUMIFS($T47:$CA47,$T$5:$CA$5,2027)/12 -> 0.17013889 | N48: =SUMIFS($T47:$CA47,$T$5:$CA$5,2028)/12 -> 0.91319444 | O48: =SUMIFS($T47:$CA47,$T$5:$CA$5,2029)/12 -> 1 | P48: =SUMIFS($T47:$CA47,$T$5:$CA$5,2030)/12 -> 1
B50: 4. RECURRING BENEFIT LINES ($M — these rows feed the WAVE sheet)
B52: Line (WAVE category) | D52: Baseline $M | K52: Run rate
B53: OPEX - Product/program/design capacity release (PDLC) [OPEX] | D53: =$D$40/1000000 -> 0 | K53: =SUMIFS($T53:$CA53,$T$5:$CA$5,2030) -> 0 | L53: =SUMIFS($T53:$CA53,$T$5:$CA$5,2026) -> 0 | M53: =SUMIFS($T53:$CA53,$T$5:$CA$5,2027) -> 0 | N53: =SUMIFS($T53:$CA53,$T$5:$CA$5,2028) -> 0 | O53: =SUMIFS($T53:$CA53,$T$5:$CA$5,2029) -> 0 | P53: =SUMIFS($T53:$CA53,$T$5:$CA$5,2030) -> 0 | T53: =($D$42)/1000000/12*T$47 -> 0 | U53: =($D$42)/1000000/12*U$47 -> 0 | V53: =($D$42)/1000000/12*V$47 -> 0 | W53: =($D$42)/1000000/12*W$47 -> 0 | X53: =($D$42)/1000000/12*X$47 -> 0 | Y53: =($D$42)/1000000/12*Y$47 -> 0 | Z53: =($D$42)/1000000/12*Z$47 -> 0 | AA53: =($D$42)/1000000/12*AA$47 -> 0 | ... CA53: =($D$42)/1000000/12*CA$47 -> 0
B54: Total recurring benefit ($M) | K54: =SUM(K53:K53) -> 0 | L54: =SUM(L53:L53) -> 0 | M54: =SUM(M53:M53) -> 0 | N54: =SUM(N53:N53) -> 0 | O54: =SUM(O53:O53) -> 0 | P54: =SUM(P53:P53) -> 0
B56: 5. ONE-TIME INVESTMENT — people cost by milestone (standard approach)
B58: Milestone | C58: Assumptions | D58: Team size | E58: Billing months | F58: Contingency Factor | G58: Labor Costs | H58: Start month | I58: Cap % (labor) | K58: Rate override ($/mo)
C59: Capture any assumptions on cost drivers, timelines, contingency factor etc. | E59: Months the team works at full utilization | F59: Low=10% Medium=15% High=20% Very high=50% | G59: Total labor costs for milestone | I59: Default links to Rate Card policy — type a % to override
B60: Plan / Design | C60: PLACEHOLDER shape mirroring the AAO delivery pod — refine with IO. | D60: 4 | E60: 2 | F60: 0.1 | G60: =D60*E60*IF(K60="",'Rate Card'!$G$29,K60)*(1+F60) -> 131633.33 | H60: =DATE(2026,11,1) -> 46327 | I60: ='Rate Card'!$C$45 -> 0
B61: Build / Test | C61: PLACEHOLDER — one 8-FTE pod for ~5 months. | D61: 8 | E61: 5 | F61: 0.1 | G61: =D61*E61*IF(K61="",'Rate Card'!$G$29,K61)*(1+F61) -> 658166.67 | H61: =DATE(2027,1,1) -> 46388 | I61: ='Rate Card'!$C$46 -> 0.8
B62: Pilot / Change Mgmt. | C62: PLACEHOLDER — scale-up team of 5 through rollout. | D62: 5 | E62: 6 | F62: 0.1 | G62: =D62*E62*IF(K62="",'Rate Card'!$G$29,K62)*(1+F62) -> 493625 | H62: =DATE(2027,6,1) -> 46539 | I62: ='Rate Card'!$C$47 -> 0
B63: Scale / Run | C63: Run-phase support carried as recurring run cost (Section 6). | D63: 0 | E63: 0 | F63: 0.1 | G63: =D63*E63*IF(K63="",'Rate Card'!$G$29,K63)*(1+F63) -> 0 | H63: =DATE(2027,12,1) -> 46722 | I63: ='Rate Card'!$C$48 -> 0
B65: Milestone labor phasing ($/month, spread evenly over billing months)
B66: Plan / Design | T66: =IF(AND(T$6>=EOMONTH($H$60,0),T$6<=EOMONTH(EDATE($H$60,$E$60-1),0)),$G$60/MAX($E$60,1),0) -> 0 | U66: =IF(AND(U$6>=EOMONTH($H$60,0),U$6<=EOMONTH(EDATE($H$60,$E$60-1),0)),$G$60/MAX($E$60,1),0) -> 0 | V66: =IF(AND(V$6>=EOMONTH($H$60,0),V$6<=EOMONTH(EDATE($H$60,$E$60-1),0)),$G$60/MAX($E$60,1),0) -> 0 | W66: =IF(AND(W$6>=EOMONTH($H$60,0),W$6<=EOMONTH(EDATE($H$60,$E$60-1),0)),$G$60/MAX($E$60,1),0) -> 0 | X66: =IF(AND(X$6>=EOMONTH($H$60,0),X$6<=EOMONTH(EDATE($H$60,$E$60-1),0)),$G$60/MAX($E$60,1),0) -> 0 | Y66: =IF(AND(Y$6>=EOMONTH($H$60,0),Y$6<=EOMONTH(EDATE($H$60,$E$60-1),0)),$G$60/MAX($E$60,1),0) -> 0 | Z66: =IF(AND(Z$6>=EOMONTH($H$60,0),Z$6<=EOMONTH(EDATE($H$60,$E$60-1),0)),$G$60/MAX($E$60,1),0) -> 0 | AA66: =IF(AND(AA$6>=EOMONTH($H$60,0),AA$6<=EOMONTH(EDATE($H$60,$E$60-1),0)),$G$60/MAX($E$60,1),0) -> 0 | ... CA66: =IF(AND(CA$6>=EOMONTH($H$60,0),CA$6<=EOMONTH(EDATE($H$60,$E$60-1),0)),$G$60/MAX($E$60,1),0) -> 0
B67: Build / Test | T67: =IF(AND(T$6>=EOMONTH($H$61,0),T$6<=EOMONTH(EDATE($H$61,$E$61-1),0)),$G$61/MAX($E$61,1),0) -> 0 | U67: =IF(AND(U$6>=EOMONTH($H$61,0),U$6<=EOMONTH(EDATE($H$61,$E$61-1),0)),$G$61/MAX($E$61,1),0) -> 0 | V67: =IF(AND(V$6>=EOMONTH($H$61,0),V$6<=EOMONTH(EDATE($H$61,$E$61-1),0)),$G$61/MAX($E$61,1),0) -> 0 | W67: =IF(AND(W$6>=EOMONTH($H$61,0),W$6<=EOMONTH(EDATE($H$61,$E$61-1),0)),$G$61/MAX($E$61,1),0) -> 0 | X67: =IF(AND(X$6>=EOMONTH($H$61,0),X$6<=EOMONTH(EDATE($H$61,$E$61-1),0)),$G$61/MAX($E$61,1),0) -> 0 | Y67: =IF(AND(Y$6>=EOMONTH($H$61,0),Y$6<=EOMONTH(EDATE($H$61,$E$61-1),0)),$G$61/MAX($E$61,1),0) -> 0 | Z67: =IF(AND(Z$6>=EOMONTH($H$61,0),Z$6<=EOMONTH(EDATE($H$61,$E$61-1),0)),$G$61/MAX($E$61,1),0) -> 0 | AA67: =IF(AND(AA$6>=EOMONTH($H$61,0),AA$6<=EOMONTH(EDATE($H$61,$E$61-1),0)),$G$61/MAX($E$61,1),0) -> 0 | ... CA67: =IF(AND(CA$6>=EOMONTH($H$61,0),CA$6<=EOMONTH(EDATE($H$61,$E$61-1),0)),$G$61/MAX($E$61,1),0) -> 0
B68: Pilot / Change Mgmt. | T68: =IF(AND(T$6>=EOMONTH($H$62,0),T$6<=EOMONTH(EDATE($H$62,$E$62-1),0)),$G$62/MAX($E$62,1),0) -> 0 | U68: =IF(AND(U$6>=EOMONTH($H$62,0),U$6<=EOMONTH(EDATE($H$62,$E$62-1),0)),$G$62/MAX($E$62,1),0) -> 0 | V68: =IF(AND(V$6>=EOMONTH($H$62,0),V$6<=EOMONTH(EDATE($H$62,$E$62-1),0)),$G$62/MAX($E$62,1),0) -> 0 | W68: =IF(AND(W$6>=EOMONTH($H$62,0),W$6<=EOMONTH(EDATE($H$62,$E$62-1),0)),$G$62/MAX($E$62,1),0) -> 0 | X68: =IF(AND(X$6>=EOMONTH($H$62,0),X$6<=EOMONTH(EDATE($H$62,$E$62-1),0)),$G$62/MAX($E$62,1),0) -> 0 | Y68: =IF(AND(Y$6>=EOMONTH($H$62,0),Y$6<=EOMONTH(EDATE($H$62,$E$62-1),0)),$G$62/MAX($E$62,1),0) -> 0 | Z68: =IF(AND(Z$6>=EOMONTH($H$62,0),Z$6<=EOMONTH(EDATE($H$62,$E$62-1),0)),$G$62/MAX($E$62,1),0) -> 0 | AA68: =IF(AND(AA$6>=EOMONTH($H$62,0),AA$6<=EOMONTH(EDATE($H$62,$E$62-1),0)),$G$62/MAX($E$62,1),0) -> 0 | ... CA68: =IF(AND(CA$6>=EOMONTH($H$62,0),CA$6<=EOMONTH(EDATE($H$62,$E$62-1),0)),$G$62/MAX($E$62,1),0) -> 0
B69: Scale / Run | T69: =IF(AND(T$6>=EOMONTH($H$63,0),T$6<=EOMONTH(EDATE($H$63,$E$63-1),0)),$G$63/MAX($E$63,1),0) -> 0 | U69: =IF(AND(U$6>=EOMONTH($H$63,0),U$6<=EOMONTH(EDATE($H$63,$E$63-1),0)),$G$63/MAX($E$63,1),0) -> 0 | V69: =IF(AND(V$6>=EOMONTH($H$63,0),V$6<=EOMONTH(EDATE($H$63,$E$63-1),0)),$G$63/MAX($E$63,1),0) -> 0 | W69: =IF(AND(W$6>=EOMONTH($H$63,0),W$6<=EOMONTH(EDATE($H$63,$E$63-1),0)),$G$63/MAX($E$63,1),0) -> 0 | X69: =IF(AND(X$6>=EOMONTH($H$63,0),X$6<=EOMONTH(EDATE($H$63,$E$63-1),0)),$G$63/MAX($E$63,1),0) -> 0 | Y69: =IF(AND(Y$6>=EOMONTH($H$63,0),Y$6<=EOMONTH(EDATE($H$63,$E$63-1),0)),$G$63/MAX($E$63,1),0) -> 0 | Z69: =IF(AND(Z$6>=EOMONTH($H$63,0),Z$6<=EOMONTH(EDATE($H$63,$E$63-1),0)),$G$63/MAX($E$63,1),0) -> 0 | AA69: =IF(AND(AA$6>=EOMONTH($H$63,0),AA$6<=EOMONTH(EDATE($H$63,$E$63-1),0)),$G$63/MAX($E$63,1),0) -> 0 | ... CA69: =IF(AND(CA$6>=EOMONTH($H$63,0),CA$6<=EOMONTH(EDATE($H$63,$E$63-1),0)),$G$63/MAX($E$63,1),0) -> 0
B70: Total milestone labor (all blocks) | G70: =SUM(G60:G63) -> 1283425
B72: One-time non-labor costs (vendor, integration, licences, change mgmt., etc.)
B73: Item | C73: Assumptions / notes | D73: Total $ | E73: Spread months | H73: Start month | I73: Cap %
B74: Vendor / integration / tooling set-up | C74: PENDING — placeholder, not data. Build-vs-buy due W6 tech workshop | D74: 0 | E74: 3 | H74: =DATE(2027,1,1) -> 46388 | I74: 0
B75: Programme management (8% of build) | C75: 8% x (milestone labor + non-labor build items) | D75: =$D$33*($G$70+$D$74) -> 102674 | E75: 9 | H75: =DATE(2026,11,1) -> 46327 | I75: 0
B76: Contingency (10% of build incl. PM) | C76: 10% x (build subtotal incl. PM) | D76: =$D$34*($G$70+$D$74+$D$75) -> 138609.9 | E76: 9 | H76: =DATE(2026,11,1) -> 46327 | I76: 0
B77: (spare) | D77: 0 | E77: 1 | H77: =DATE(2027,6,1) -> 46539 | I77: 0
B79: Non-labor phasing ($/month)
B80: phasing — item 1 | T80: =IF(AND(T$6>=EOMONTH($H$74,0),T$6<=EOMONTH(EDATE($H$74,$E$74-1),0)),$D$74/MAX($E$74,1),0) -> 0 | U80: =IF(AND(U$6>=EOMONTH($H$74,0),U$6<=EOMONTH(EDATE($H$74,$E$74-1),0)),$D$74/MAX($E$74,1),0) -> 0 | V80: =IF(AND(V$6>=EOMONTH($H$74,0),V$6<=EOMONTH(EDATE($H$74,$E$74-1),0)),$D$74/MAX($E$74,1),0) -> 0 | W80: =IF(AND(W$6>=EOMONTH($H$74,0),W$6<=EOMONTH(EDATE($H$74,$E$74-1),0)),$D$74/MAX($E$74,1),0) -> 0 | X80: =IF(AND(X$6>=EOMONTH($H$74,0),X$6<=EOMONTH(EDATE($H$74,$E$74-1),0)),$D$74/MAX($E$74,1),0) -> 0 | Y80: =IF(AND(Y$6>=EOMONTH($H$74,0),Y$6<=EOMONTH(EDATE($H$74,$E$74-1),0)),$D$74/MAX($E$74,1),0) -> 0 | Z80: =IF(AND(Z$6>=EOMONTH($H$74,0),Z$6<=EOMONTH(EDATE($H$74,$E$74-1),0)),$D$74/MAX($E$74,1),0) -> 0 | AA80: =IF(AND(AA$6>=EOMONTH($H$74,0),AA$6<=EOMONTH(EDATE($H$74,$E$74-1),0)),$D$74/MAX($E$74,1),0) -> 0 | ... CA80: =IF(AND(CA$6>=EOMONTH($H$74,0),CA$6<=EOMONTH(EDATE($H$74,$E$74-1),0)),$D$74/MAX($E$74,1),0) -> 0
B81: phasing — item 2 | T81: =IF(AND(T$6>=EOMONTH($H$75,0),T$6<=EOMONTH(EDATE($H$75,$E$75-1),0)),$D$75/MAX($E$75,1),0) -> 0 | U81: =IF(AND(U$6>=EOMONTH($H$75,0),U$6<=EOMONTH(EDATE($H$75,$E$75-1),0)),$D$75/MAX($E$75,1),0) -> 0 | V81: =IF(AND(V$6>=EOMONTH($H$75,0),V$6<=EOMONTH(EDATE($H$75,$E$75-1),0)),$D$75/MAX($E$75,1),0) -> 0 | W81: =IF(AND(W$6>=EOMONTH($H$75,0),W$6<=EOMONTH(EDATE($H$75,$E$75-1),0)),$D$75/MAX($E$75,1),0) -> 0 | X81: =IF(AND(X$6>=EOMONTH($H$75,0),X$6<=EOMONTH(EDATE($H$75,$E$75-1),0)),$D$75/MAX($E$75,1),0) -> 0 | Y81: =IF(AND(Y$6>=EOMONTH($H$75,0),Y$6<=EOMONTH(EDATE($H$75,$E$75-1),0)),$D$75/MAX($E$75,1),0) -> 0 | Z81: =IF(AND(Z$6>=EOMONTH($H$75,0),Z$6<=EOMONTH(EDATE($H$75,$E$75-1),0)),$D$75/MAX($E$75,1),0) -> 0 | AA81: =IF(AND(AA$6>=EOMONTH($H$75,0),AA$6<=EOMONTH(EDATE($H$75,$E$75-1),0)),$D$75/MAX($E$75,1),0) -> 0 | ... CA81: =IF(AND(CA$6>=EOMONTH($H$75,0),CA$6<=EOMONTH(EDATE($H$75,$E$75-1),0)),$D$75/MAX($E$75,1),0) -> 0
B82: phasing — item 3 | T82: =IF(AND(T$6>=EOMONTH($H$76,0),T$6<=EOMONTH(EDATE($H$76,$E$76-1),0)),$D$76/MAX($E$76,1),0) -> 0 | U82: =IF(AND(U$6>=EOMONTH($H$76,0),U$6<=EOMONTH(EDATE($H$76,$E$76-1),0)),$D$76/MAX($E$76,1),0) -> 0 | V82: =IF(AND(V$6>=EOMONTH($H$76,0),V$6<=EOMONTH(EDATE($H$76,$E$76-1),0)),$D$76/MAX($E$76,1),0) -> 0 | W82: =IF(AND(W$6>=EOMONTH($H$76,0),W$6<=EOMONTH(EDATE($H$76,$E$76-1),0)),$D$76/MAX($E$76,1),0) -> 0 | X82: =IF(AND(X$6>=EOMONTH($H$76,0),X$6<=EOMONTH(EDATE($H$76,$E$76-1),0)),$D$76/MAX($E$76,1),0) -> 0 | Y82: =IF(AND(Y$6>=EOMONTH($H$76,0),Y$6<=EOMONTH(EDATE($H$76,$E$76-1),0)),$D$76/MAX($E$76,1),0) -> 0 | Z82: =IF(AND(Z$6>=EOMONTH($H$76,0),Z$6<=EOMONTH(EDATE($H$76,$E$76-1),0)),$D$76/MAX($E$76,1),0) -> 0 | AA82: =IF(AND(AA$6>=EOMONTH($H$76,0),AA$6<=EOMONTH(EDATE($H$76,$E$76-1),0)),$D$76/MAX($E$76,1),0) -> 0 | ... CA82: =IF(AND(CA$6>=EOMONTH($H$76,0),CA$6<=EOMONTH(EDATE($H$76,$E$76-1),0)),$D$76/MAX($E$76,1),0) -> 0
B83: phasing — item 4 | T83: =IF(AND(T$6>=EOMONTH($H$77,0),T$6<=EOMONTH(EDATE($H$77,$E$77-1),0)),$D$77/MAX($E$77,1),0) -> 0 | U83: =IF(AND(U$6>=EOMONTH($H$77,0),U$6<=EOMONTH(EDATE($H$77,$E$77-1),0)),$D$77/MAX($E$77,1),0) -> 0 | V83: =IF(AND(V$6>=EOMONTH($H$77,0),V$6<=EOMONTH(EDATE($H$77,$E$77-1),0)),$D$77/MAX($E$77,1),0) -> 0 | W83: =IF(AND(W$6>=EOMONTH($H$77,0),W$6<=EOMONTH(EDATE($H$77,$E$77-1),0)),$D$77/MAX($E$77,1),0) -> 0 | X83: =IF(AND(X$6>=EOMONTH($H$77,0),X$6<=EOMONTH(EDATE($H$77,$E$77-1),0)),$D$77/MAX($E$77,1),0) -> 0 | Y83: =IF(AND(Y$6>=EOMONTH($H$77,0),Y$6<=EOMONTH(EDATE($H$77,$E$77-1),0)),$D$77/MAX($E$77,1),0) -> 0 | Z83: =IF(AND(Z$6>=EOMONTH($H$77,0),Z$6<=EOMONTH(EDATE($H$77,$E$77-1),0)),$D$77/MAX($E$77,1),0) -> 0 | AA83: =IF(AND(AA$6>=EOMONTH($H$77,0),AA$6<=EOMONTH(EDATE($H$77,$E$77-1),0)),$D$77/MAX($E$77,1),0) -> 0 | ... CA83: =IF(AND(CA$6>=EOMONTH($H$77,0),CA$6<=EOMONTH(EDATE($H$77,$E$77-1),0)),$D$77/MAX($E$77,1),0) -> 0
B85: One-time investment feed rows ($M — these feed the WAVE sheet)
B86: CAPEX — capitalized build labor | L86: =SUMIFS($T86:$CA86,$T$5:$CA$5,2026) -> 0 | M86: =SUMIFS($T86:$CA86,$T$5:$CA$5,2027) -> 0.52653333 | N86: =SUMIFS($T86:$CA86,$T$5:$CA$5,2028) -> 0 | O86: =SUMIFS($T86:$CA86,$T$5:$CA$5,2029) -> 0 | P86: =SUMIFS($T86:$CA86,$T$5:$CA$5,2030) -> 0 | T86: =(SUMPRODUCT(T66:T69,$I$60:$I$63))/1000000 -> 0 | U86: =(SUMPRODUCT(U66:U69,$I$60:$I$63))/1000000 -> 0 | V86: =(SUMPRODUCT(V66:V69,$I$60:$I$63))/1000000 -> 0 | W86: =(SUMPRODUCT(W66:W69,$I$60:$I$63))/1000000 -> 0 | X86: =(SUMPRODUCT(X66:X69,$I$60:$I$63))/1000000 -> 0 | Y86: =(SUMPRODUCT(Y66:Y69,$I$60:$I$63))/1000000 -> 0 | Z86: =(SUMPRODUCT(Z66:Z69,$I$60:$I$63))/1000000 -> 0 | AA86: =(SUMPRODUCT(AA66:AA69,$I$60:$I$63))/1000000 -> 0 | ... CA86: =(SUMPRODUCT(CA66:CA69,$I$60:$I$63))/1000000 -> 0
B87: CAPEX — capitalized non-labor | L87: =SUMIFS($T87:$CA87,$T$5:$CA$5,2026) -> 0 | M87: =SUMIFS($T87:$CA87,$T$5:$CA$5,2027) -> 0 | N87: =SUMIFS($T87:$CA87,$T$5:$CA$5,2028) -> 0 | O87: =SUMIFS($T87:$CA87,$T$5:$CA$5,2029) -> 0 | P87: =SUMIFS($T87:$CA87,$T$5:$CA$5,2030) -> 0 | T87: =SUMPRODUCT(T80:T83,$I$74:$I$77)/1000000 -> 0 | U87: =SUMPRODUCT(U80:U83,$I$74:$I$77)/1000000 -> 0 | V87: =SUMPRODUCT(V80:V83,$I$74:$I$77)/1000000 -> 0 | W87: =SUMPRODUCT(W80:W83,$I$74:$I$77)/1000000 -> 0 | X87: =SUMPRODUCT(X80:X83,$I$74:$I$77)/1000000 -> 0 | Y87: =SUMPRODUCT(Y80:Y83,$I$74:$I$77)/1000000 -> 0 | Z87: =SUMPRODUCT(Z80:Z83,$I$74:$I$77)/1000000 -> 0 | AA87: =SUMPRODUCT(AA80:AA83,$I$74:$I$77)/1000000 -> 0 | ... CA87: =SUMPRODUCT(CA80:CA83,$I$74:$I$77)/1000000 -> 0
B88: OTC — build labor (expensed) | L88: =SUMIFS($T88:$CA88,$T$5:$CA$5,2026) -> 0.13163333 | M88: =SUMIFS($T88:$CA88,$T$5:$CA$5,2027) -> 0.62525833 | N88: =SUMIFS($T88:$CA88,$T$5:$CA$5,2028) -> 0 | O88: =SUMIFS($T88:$CA88,$T$5:$CA$5,2029) -> 0 | P88: =SUMIFS($T88:$CA88,$T$5:$CA$5,2030) -> 0 | T88: =(SUMPRODUCT(T66:T69,1-$I$60:$I$63))/1000000 -> 0 | U88: =(SUMPRODUCT(U66:U69,1-$I$60:$I$63))/1000000 -> 0 | V88: =(SUMPRODUCT(V66:V69,1-$I$60:$I$63))/1000000 -> 0 | W88: =(SUMPRODUCT(W66:W69,1-$I$60:$I$63))/1000000 -> 0 | X88: =(SUMPRODUCT(X66:X69,1-$I$60:$I$63))/1000000 -> 0 | Y88: =(SUMPRODUCT(Y66:Y69,1-$I$60:$I$63))/1000000 -> 0 | Z88: =(SUMPRODUCT(Z66:Z69,1-$I$60:$I$63))/1000000 -> 0 | AA88: =(SUMPRODUCT(AA66:AA69,1-$I$60:$I$63))/1000000 -> 0 | ... CA88: =(SUMPRODUCT(CA66:CA69,1-$I$60:$I$63))/1000000 -> 0
B89: OTC — non-labor (expensed) | L89: =SUMIFS($T89:$CA89,$T$5:$CA$5,2026) -> 0.053618644 | M89: =SUMIFS($T89:$CA89,$T$5:$CA$5,2027) -> 0.18766526 | N89: =SUMIFS($T89:$CA89,$T$5:$CA$5,2028) -> 0 | O89: =SUMIFS($T89:$CA89,$T$5:$CA$5,2029) -> 0 | P89: =SUMIFS($T89:$CA89,$T$5:$CA$5,2030) -> 0 | T89: =SUMPRODUCT(T80:T83,1-$I$74:$I$77)/1000000 -> 0 | U89: =SUMPRODUCT(U80:U83,1-$I$74:$I$77)/1000000 -> 0 | V89: =SUMPRODUCT(V80:V83,1-$I$74:$I$77)/1000000 -> 0 | W89: =SUMPRODUCT(W80:W83,1-$I$74:$I$77)/1000000 -> 0 | X89: =SUMPRODUCT(X80:X83,1-$I$74:$I$77)/1000000 -> 0 | Y89: =SUMPRODUCT(Y80:Y83,1-$I$74:$I$77)/1000000 -> 0 | Z89: =SUMPRODUCT(Z80:Z83,1-$I$74:$I$77)/1000000 -> 0 | AA89: =SUMPRODUCT(AA80:AA83,1-$I$74:$I$77)/1000000 -> 0 | ... CA89: =SUMPRODUCT(CA80:CA83,1-$I$74:$I$77)/1000000 -> 0
B90: Total one-time investment ($M) | L90: =SUM(L86:L89) -> 0.18525198 | M90: =SUM(M86:M89) -> 1.3394569 | N90: =SUM(N86:N89) -> 0 | O90: =SUM(O86:O89) -> 0 | P90: =SUM(P86:P89) -> 0
B92: 6. RECURRING RUN COSTS to achieve impact
B94: Line | C94: Assumptions / notes | D94: Annual $ (steady state) | H94: Start month | I94: Scales with ramp? (Y/N)
B95: OPEX - PDLC harness / product tooling run | C95: PENDING — placeholder, not data. Net of tooling spend baseline (request #5) | D95: 0 | H95: =DATE(2027,6,1) -> 46539 | I95: N
B96: OPEX - Model / token consumption | C96: PENDING — placeholder, not data. PDLC-side consumption not yet available (request #11) | D96: 0 | H96: =DATE(2027,6,1) -> 46539 | I96: Y
B98: Run-cost feed rows ($M)
B99: OPEX - PDLC harness / product tooling run [RUN] | K99: =SUMIFS($T99:$CA99,$T$5:$CA$5,2030) -> 0 | L99: =SUMIFS($T99:$CA99,$T$5:$CA$5,2026) -> 0 | M99: =SUMIFS($T99:$CA99,$T$5:$CA$5,2027) -> 0 | N99: =SUMIFS($T99:$CA99,$T$5:$CA$5,2028) -> 0 | O99: =SUMIFS($T99:$CA99,$T$5:$CA$5,2029) -> 0 | P99: =SUMIFS($T99:$CA99,$T$5:$CA$5,2030) -> 0 | T99: =$D$95/1000000/12*IF($I$95="Y",T$47,IF(T$6>=EOMONTH($H$95,0),1,0)) -> 0 | U99: =$D$95/1000000/12*IF($I$95="Y",U$47,IF(U$6>=EOMONTH($H$95,0),1,0)) -> 0 | V99: =$D$95/1000000/12*IF($I$95="Y",V$47,IF(V$6>=EOMONTH($H$95,0),1,0)) -> 0 | W99: =$D$95/1000000/12*IF($I$95="Y",W$47,IF(W$6>=EOMONTH($H$95,0),1,0)) -> 0 | X99: =$D$95/1000000/12*IF($I$95="Y",X$47,IF(X$6>=EOMONTH($H$95,0),1,0)) -> 0 | Y99: =$D$95/1000000/12*IF($I$95="Y",Y$47,IF(Y$6>=EOMONTH($H$95,0),1,0)) -> 0 | Z99: =$D$95/1000000/12*IF($I$95="Y",Z$47,IF(Z$6>=EOMONTH($H$95,0),1,0)) -> 0 | AA99: =$D$95/1000000/12*IF($I$95="Y",AA$47,IF(AA$6>=EOMONTH($H$95,0),1,0)) -> 0 | ... CA99: =$D$95/1000000/12*IF($I$95="Y",CA$47,IF(CA$6>=EOMONTH($H$95,0),1,0)) -> 0
B100: OPEX - Model / token consumption [RUN] | K100: =SUMIFS($T100:$CA100,$T$5:$CA$5,2030) -> 0 | L100: =SUMIFS($T100:$CA100,$T$5:$CA$5,2026) -> 0 | M100: =SUMIFS($T100:$CA100,$T$5:$CA$5,2027) -> 0 | N100: =SUMIFS($T100:$CA100,$T$5:$CA$5,2028) -> 0 | O100: =SUMIFS($T100:$CA100,$T$5:$CA$5,2029) -> 0 | P100: =SUMIFS($T100:$CA100,$T$5:$CA$5,2030) -> 0 | T100: =$D$96/1000000/12*IF($I$96="Y",T$47,IF(T$6>=EOMONTH($H$96,0),1,0)) -> 0 | U100: =$D$96/1000000/12*IF($I$96="Y",U$47,IF(U$6>=EOMONTH($H$96,0),1,0)) -> 0 | V100: =$D$96/1000000/12*IF($I$96="Y",V$47,IF(V$6>=EOMONTH($H$96,0),1,0)) -> 0 | W100: =$D$96/1000000/12*IF($I$96="Y",W$47,IF(W$6>=EOMONTH($H$96,0),1,0)) -> 0 | X100: =$D$96/1000000/12*IF($I$96="Y",X$47,IF(X$6>=EOMONTH($H$96,0),1,0)) -> 0 | Y100: =$D$96/1000000/12*IF($I$96="Y",Y$47,IF(Y$6>=EOMONTH($H$96,0),1,0)) -> 0 | Z100: =$D$96/1000000/12*IF($I$96="Y",Z$47,IF(Z$6>=EOMONTH($H$96,0),1,0)) -> 0 | AA100: =$D$96/1000000/12*IF($I$96="Y",AA$47,IF(AA$6>=EOMONTH($H$96,0),1,0)) -> 0 | ... CA100: =$D$96/1000000/12*IF($I$96="Y",CA$47,IF(CA$6>=EOMONTH($H$96,0),1,0)) -> 0
B101: Total run cost ($M) | K101: =SUM(K99:K100) -> 0 | L101: =SUM(L99:L100) -> 0 | M101: =SUM(M99:M100) -> 0 | N101: =SUM(N99:N100) -> 0 | O101: =SUM(O99:O100) -> 0 | P101: =SUM(P99:P100) -> 0
B103: 7. WAVE MAPPING (reference)
B105: Model row 53 — OPEX - Product/program/design capacity release (PDLC) | F105: → WAVE row 79 (Section II — Recurring Benefits)
B106: Model row 99 — OPEX - PDLC harness / product tooling run | F106: → WAVE row 107 (Section II — Recurring Costs)
B107: Model row 100 — OPEX - Model / token consumption | F107: → WAVE row 108 (Section II — Recurring Costs)
B108: Model row 86 — CAPEX — capitalized build labor | F108: → WAVE row 136 (Section III — CapEx)
B109: Model row 87 — CAPEX — capitalized non-labor | F109: → WAVE row 137 (Section III — CapEx)
B110: Model row 88 — OTC — build labor (expensed) | F110: → WAVE row 141 (Section III — OTC)
B111: Model row 89 — OTC — non-labor (expensed) | F111: → WAVE row 142 (Section III — OTC)
B113: 8. FLEX / SCRATCH AREA — free space for refinements with the initiative owner

Sheet SDLC-2 WAVE
L1: 1 | M1: 2 | N1: 3 | O1: 4 | P1: 5 | R1: =COUNTIFS($R$66:$R$117, "Error") -> 0 | T1: 2026 | U1: 2026 | V1: 2026 | W1: 2026 | X1: 2026 | Y1: 2026 | Z1: 2026 | AA1: 2026 | AB1: 2026 | AC1: 2026 | AD1: 2026 | AE1: 2026 | AF1: 2027 | AG1: 2027 | AH1: 2027 | AI1: 2027 | AJ1: 2027 | AK1: 2027 | AL1: 2027 | AM1: 2027 | AN1: 2027 | AO1: 2027 | AP1: 2027 | AQ1: 2027 | AR1: 2028 | AS1: 2028 | AT1: 2028 | AU1: 2028 | AV1: 2028 | AW1: 2028 | AX1: 2028 | AY1: 2028 | AZ1: 2028 | BA1: 2028 | BB1: 2028 | BC1: 2028 | BD1: 2029 | BE1: 2029 | BF1: 2029 | BG1: 2029 | BH1: 2029 | BI1: 2029 | BJ1: 2029 | BK1: 2029 | BL1: 2029 | BM1: 2029 | BN1: 2029 | BO1: 2029 | BP1: 2030 | BQ1: 2030 | BR1: 2030 | BS1: 2030 | BT1: 2030 | BU1: 2030 | BV1: 2030 | BW1: 2030 | BX1: 2030 | BY1: 2030 | BZ1: 2030 | CA1: 2030 | CI1: =COUNTIFS(CI$66:CI$149, "FALSE") -> 0 | CJ1: =COUNTIFS(CJ$66:CJ$149, "FALSE") -> 0 | CK1: =COUNTIFS(CK$66:CK$149, "FALSE") -> 0 | CL1: =COUNTIFS(CL$66:CL$149, "FALSE") -> 0 | CM1: =COUNTIFS(CM$66:CM$149, "FALSE") -> 0
C2: ="#"&$F$6&" Initiative Business Case" -> #TBD Initiative Business Case
C4: INPUTS & ASSUMPTIONS
D6: Initiative # | F6: TBD
D7: Initiative Owner | F7: Aruna (IO) — TBC
D8: Initiative Name | F8: PDLC re-imagination — agentic product development lifecycle across product, program and design
D11: Estimated L4 date | F11: ='SDLC-2 Model'!$D$13 -> 46539
D12: Net Recurring Benefit ($M) | F12: =$K$117 -> 0
C14: SECTION I - PRIMARY VALUE DRIVER (ILLUSTRATIVE)
D16: Primary value driver — linked to the Model sheet; refine with the initiative owner
D17: Baseline | H17: Period | I17: KPI | J17: Inputs
E18: Product/program/design FTE in scope | H18: TTM 6/1/26 | I18: # FTE | J18: ='SDLC-2 Model'!$D$26 -> 0
E19: Avg fully loaded cost per PDLC FTE | H19: TTM 6/1/26 | I19: $ / FTE | J19: ='SDLC-2 Model'!$D$27 -> 0
E20: Total in-scope PDLC labor base | H20: TTM 6/1/26 | I20: $USD M | J20: ='SDLC-2 Model'!$D$40/1000000 -> 0
D23: Goal
E24: PDLC lift x steady-state adoption | H24: Steady state | I24: % | J24: ='SDLC-2 Model'!$D$29*'SDLC-2 Model'!$D$30 -> 0.15
E25: Capture rate to bankable cost | H25: Steady state | I25: % | J25: ='SDLC-2 Model'!$D$31 -> 0.65
D28: Incremental Improvement
E29: Bankable annual benefit (run rate) | I29: $USD M | J29: ='SDLC-2 Model'!$D$42/1000000 -> 0
C60: SECTION II - NET RECURRING BENEFITS | CC60: ANNUAL SUMMARY | CI60: CHECK CELLS
T62: 2026 | AF62: 2027 | AR62: 2028 | BD62: 2029 | BP62: 2030 | CI62: CHECK
D63: RECURRING BENEFITS | H63: Comment | I63: Baseline | J63: Goal | K63: Ann. Run Rate | L63: 2026 | M63: =L63+1 -> 2027 | N63: =M63+1 -> 2028 | O63: =N63+1 -> 2029 | P63: =O63+1 -> 2030 | Q63: Impacted BU | R63: Check | T63: 46023 | U63: =EOMONTH(T63, 1) -> 46081 | V63: =EOMONTH(U63, 1) -> 46112 | W63: =EOMONTH(V63, 1) -> 46142 | X63: =EOMONTH(W63, 1) -> 46173 | Y63: =EOMONTH(X63, 1) -> 46203 | Z63: =EOMONTH(Y63, 1) -> 46234 | AA63: =EOMONTH(Z63, 1) -> 46265 | AB63: =EOMONTH(AA63, 1) -> 46295 | ... CA63: =EOMONTH(BZ63, 1) -> 47848 | CC63: 2026 | CD63: =CC63+1 -> 2027 | CE63: =CD63+1 -> 2028 | CF63: =CE63+1 -> 2029 | CG63: =CF63+1 -> 2030 | CI63: 2026 | CJ63: =CI63+1 -> 2027 | CK63: =CJ63+1 -> 2028 | CL63: =CK63+1 -> 2029 | CM63: =CL63+1 -> 2030
E64: $USD M | I64: =$H$18 -> TTM 6/1/26 | J64: Future State | K64: Increment
E65: Revenue
I66: 0 | J66: 0 | K66: =J66-I66 -> 0 | R66: =IF(K66=P66, "", "Error") | CC66: =SUMIFS($T66:$CA66, $T$1:$CA$1, CC$63) -> 0 | CD66: =SUMIFS($T66:$CA66, $T$1:$CA$1, CD$63) -> 0 | CE66: =SUMIFS($T66:$CA66, $T$1:$CA$1, CE$63) -> 0 | CF66: =SUMIFS($T66:$CA66, $T$1:$CA$1, CF$63) -> 0 | CG66: =SUMIFS($T66:$CA66, $T$1:$CA$1, CG$63) -> 0 | CI66: =CC66=L66 -> 1 | CJ66: =CD66=M66 -> 1 | CK66: =CE66=N66 -> 1 | CL66: =CF66=O66 -> 1 | CM66: =CG66=P66 -> 1
I67: 0 | J67: 0 | K67: =J67-I67 -> 0 | R67: =IF(K67=P67, "", "Error") | CC67: =SUMIFS($T67:$CA67, $T$1:$CA$1, CC$63) -> 0 | CD67: =SUMIFS($T67:$CA67, $T$1:$CA$1, CD$63) -> 0 | CE67: =SUMIFS($T67:$CA67, $T$1:$CA$1, CE$63) -> 0 | CF67: =SUMIFS($T67:$CA67, $T$1:$CA$1, CF$63) -> 0 | CG67: =SUMIFS($T67:$CA67, $T$1:$CA$1, CG$63) -> 0 | CI67: =CC67=L67 -> 1 | CJ67: =CD67=M67 -> 1 | CK67: =CE67=N67 -> 1 | CL67: =CF67=O67 -> 1 | CM67: =CG67=P67 -> 1
E68: Revenue Subtotal | I68: =SUM(I66:I67) -> 0 | J68: =SUM(J66:J67) -> 0 | K68: =SUM(K66:K67) -> 0 | L68: =SUM(L66:L67) -> 0 | M68: =SUM(M66:M67) -> 0 | N68: =SUM(N66:N67) -> 0 | O68: =SUM(O66:O67) -> 0 | P68: =SUM(P66:P67) -> 0 | T68: =SUM(T66:T67) -> 0 | U68: =SUM(U66:U67) -> 0 | V68: =SUM(V66:V67) -> 0 | W68: =SUM(W66:W67) -> 0 | X68: =SUM(X66:X67) -> 0 | Y68: =SUM(Y66:Y67) -> 0 | Z68: =SUM(Z66:Z67) -> 0 | AA68: =SUM(AA66:AA67) -> 0 | ... CA68: =SUM(CA66:CA67) -> 0 | CC68: =SUM(CC66:CC67) -> 0 | CD68: =SUM(CD66:CD67) -> 0 | CE68: =SUM(CE66:CE67) -> 0 | CF68: =SUM(CF66:CF67) -> 0 | CG68: =SUM(CG66:CG67) -> 0 | CI68: =CC68=L68 -> 1 | CJ68: =CD68=M68 -> 1 | CK68: =CE68=N68 -> 1 | CL68: =CF68=O68 -> 1 | CM68: =CG68=P68 -> 1
E70: Cost of Sales
K71: =I71-J71 -> 0 | R71: =IF(K71=P71, "", "Error") | CC71: =SUMIFS($T71:$CA71, $T$1:$CA$1, CC$63) -> 0 | CD71: =SUMIFS($T71:$CA71, $T$1:$CA$1, CD$63) -> 0 | CE71: =SUMIFS($T71:$CA71, $T$1:$CA$1, CE$63) -> 0 | CF71: =SUMIFS($T71:$CA71, $T$1:$CA$1, CF$63) -> 0 | CG71: =SUMIFS($T71:$CA71, $T$1:$CA$1, CG$63) -> 0 | CI71: =CC71=L71 -> 1 | CJ71: =CD71=M71 -> 1 | CK71: =CE71=N71 -> 1 | CL71: =CF71=O71 -> 1 | CM71: =CG71=P71 -> 1
I72: 0 | J72: 0 | K72: =I72-J72 -> 0 | R72: =IF(K72=P72, "", "Error") | CC72: =SUMIFS($T72:$CA72, $T$1:$CA$1, CC$63) -> 0 | CD72: =SUMIFS($T72:$CA72, $T$1:$CA$1, CD$63) -> 0 | CE72: =SUMIFS($T72:$CA72, $T$1:$CA$1, CE$63) -> 0 | CF72: =SUMIFS($T72:$CA72, $T$1:$CA$1, CF$63) -> 0 | CG72: =SUMIFS($T72:$CA72, $T$1:$CA$1, CG$63) -> 0 | CI72: =CC72=L72 -> 1 | CJ72: =CD72=M72 -> 1 | CK72: =CE72=N72 -> 1 | CL72: =CF72=O72 -> 1 | CM72: =CG72=P72 -> 1
I73: 0 | J73: 0 | K73: =I73-J73 -> 0 | R73: =IF(K73=P73, "", "Error") | CC73: =SUMIFS($T73:$CA73, $T$1:$CA$1, CC$63) -> 0 | CD73: =SUMIFS($T73:$CA73, $T$1:$CA$1, CD$63) -> 0 | CE73: =SUMIFS($T73:$CA73, $T$1:$CA$1, CE$63) -> 0 | CF73: =SUMIFS($T73:$CA73, $T$1:$CA$1, CF$63) -> 0 | CG73: =SUMIFS($T73:$CA73, $T$1:$CA$1, CG$63) -> 0 | CI73: =CC73=L73 -> 1 | CJ73: =CD73=M73 -> 1 | CK73: =CE73=N73 -> 1 | CL73: =CF73=O73 -> 1 | CM73: =CG73=P73 -> 1
I74: 0 | J74: 0 | K74: =I74-J74 -> 0 | R74: =IF(K74=P74, "", "Error") | CC74: =SUMIFS($T74:$CA74, $T$1:$CA$1, CC$63) -> 0 | CD74: =SUMIFS($T74:$CA74, $T$1:$CA$1, CD$63) -> 0 | CE74: =SUMIFS($T74:$CA74, $T$1:$CA$1, CE$63) -> 0 | CF74: =SUMIFS($T74:$CA74, $T$1:$CA$1, CF$63) -> 0 | CG74: =SUMIFS($T74:$CA74, $T$1:$CA$1, CG$63) -> 0 | CI74: =CC74=L74 -> 1 | CJ74: =CD74=M74 -> 1 | CK74: =CE74=N74 -> 1 | CL74: =CF74=O74 -> 1 | CM74: =CG74=P74 -> 1
K75: =I75-J75 -> 0 | R75: =IF(K75=P75, "", "Error") | CC75: =SUMIFS($T75:$CA75, $T$1:$CA$1, CC$63) -> 0 | CD75: =SUMIFS($T75:$CA75, $T$1:$CA$1, CD$63) -> 0 | CE75: =SUMIFS($T75:$CA75, $T$1:$CA$1, CE$63) -> 0 | CF75: =SUMIFS($T75:$CA75, $T$1:$CA$1, CF$63) -> 0 | CG75: =SUMIFS($T75:$CA75, $T$1:$CA$1, CG$63) -> 0 | CI75: =CC75=L75 -> 1 | CJ75: =CD75=M75 -> 1 | CK75: =CE75=N75 -> 1 | CL75: =CF75=O75 -> 1 | CM75: =CG75=P75 -> 1
E76: Cost of Sales Subtotal | I76: =SUM(I71:I75) -> 0 | J76: =SUM(J71:J75) -> 0 | K76: =SUM(K71:K75) -> 0 | L76: =SUM(L71:L75) -> 0 | M76: =SUM(M71:M75) -> 0 | N76: =SUM(N71:N75) -> 0 | O76: =SUM(O71:O75) -> 0 | P76: =SUM(P71:P75) -> 0 | T76: =SUM(T71:T75) -> 0 | U76: =SUM(U71:U75) -> 0 | V76: =SUM(V71:V75) -> 0 | W76: =SUM(W71:W75) -> 0 | X76: =SUM(X71:X75) -> 0 | Y76: =SUM(Y71:Y75) -> 0 | Z76: =SUM(Z71:Z75) -> 0 | AA76: =SUM(AA71:AA75) -> 0 | ... CA76: =SUM(CA71:CA75) -> 0 | CC76: =SUM(CC71:CC75) -> 0 | CD76: =SUM(CD71:CD75) -> 0 | CE76: =SUM(CE71:CE75) -> 0 | CF76: =SUM(CF71:CF75) -> 0 | CG76: =SUM(CG71:CG75) -> 0 | CI76: =CC76=L76 -> 1 | CJ76: =CD76=M76 -> 1 | CK76: =CE76=N76 -> 1 | CL76: =CF76=O76 -> 1 | CM76: =CG76=P76 -> 1
E78: OPEX
E79: OPEX - Product/program/design capacity release (PDLC) | H79: Bankable share of PDLC capacity created | I79: ='SDLC-2 Model'!$D$53 -> 0 | J79: =I79-'SDLC-2 Model'!$K$53 -> 0 | K79: ='SDLC-2 Model'!$K$53 -> 0 | L79: ='SDLC-2 Model'!L53 -> 0 | M79: ='SDLC-2 Model'!M53 -> 0 | N79: ='SDLC-2 Model'!N53 -> 0 | O79: ='SDLC-2 Model'!O53 -> 0 | P79: ='SDLC-2 Model'!P53 -> 0 | Q79: CTO / SDLC | R79: =IF(K79=P79, "", "Error") | T79: ='SDLC-2 Model'!T53 -> 0 | U79: ='SDLC-2 Model'!U53 -> 0 | V79: ='SDLC-2 Model'!V53 -> 0 | W79: ='SDLC-2 Model'!W53 -> 0 | X79: ='SDLC-2 Model'!X53 -> 0 | Y79: ='SDLC-2 Model'!Y53 -> 0 | Z79: ='SDLC-2 Model'!Z53 -> 0 | AA79: ='SDLC-2 Model'!AA53 -> 0 | ... CA79: ='SDLC-2 Model'!CA53 -> 0 | CC79: =SUMIFS($T79:$CA79, $T$1:$CA$1, CC$63) -> 0 | CD79: =SUMIFS($T79:$CA79, $T$1:$CA$1, CD$63) -> 0 | CE79: =SUMIFS($T79:$CA79, $T$1:$CA$1, CE$63) -> 0 | CF79: =SUMIFS($T79:$CA79, $T$1:$CA$1, CF$63) -> 0 | CG79: =SUMIFS($T79:$CA79, $T$1:$CA$1, CG$63) -> 0 | CI79: =CC79=L79 -> 1 | CJ79: =CD79=M79 -> 1 | CK79: =CE79=N79 -> 1 | CL79: =CF79=O79 -> 1 | CM79: =CG79=P79 -> 1
I80: 0 | J80: 0 | K80: =I80-J80 -> 0 | R80: =IF(K80=P80, "", "Error") | CC80: =SUMIFS($T80:$CA80, $T$1:$CA$1, CC$63) -> 0 | CD80: =SUMIFS($T80:$CA80, $T$1:$CA$1, CD$63) -> 0 | CE80: =SUMIFS($T80:$CA80, $T$1:$CA$1, CE$63) -> 0 | CF80: =SUMIFS($T80:$CA80, $T$1:$CA$1, CF$63) -> 0 | CG80: =SUMIFS($T80:$CA80, $T$1:$CA$1, CG$63) -> 0 | CI80: =CC80=L80 -> 1 | CJ80: =CD80=M80 -> 1 | CK80: =CE80=N80 -> 1 | CL80: =CF80=O80 -> 1 | CM80: =CG80=P80 -> 1
I81: 0 | J81: 0 | K81: =I81-J81 -> 0 | R81: =IF(K81=P81, "", "Error") | CC81: =SUMIFS($T81:$CA81, $T$1:$CA$1, CC$63) -> 0 | CD81: =SUMIFS($T81:$CA81, $T$1:$CA$1, CD$63) -> 0 | CE81: =SUMIFS($T81:$CA81, $T$1:$CA$1, CE$63) -> 0 | CF81: =SUMIFS($T81:$CA81, $T$1:$CA$1, CF$63) -> 0 | CG81: =SUMIFS($T81:$CA81, $T$1:$CA$1, CG$63) -> 0 | CI81: =CC81=L81 -> 1 | CJ81: =CD81=M81 -> 1 | CK81: =CE81=N81 -> 1 | CL81: =CF81=O81 -> 1 | CM81: =CG81=P81 -> 1
I82: 0 | J82: 0 | K82: =I82-J82 -> 0 | R82: =IF(K82=P82, "", "Error") | CC82: =SUMIFS($T82:$CA82, $T$1:$CA$1, CC$63) -> 0 | CD82: =SUMIFS($T82:$CA82, $T$1:$CA$1, CD$63) -> 0 | CE82: =SUMIFS($T82:$CA82, $T$1:$CA$1, CE$63) -> 0 | CF82: =SUMIFS($T82:$CA82, $T$1:$CA$1, CF$63) -> 0 | CG82: =SUMIFS($T82:$CA82, $T$1:$CA$1, CG$63) -> 0 | CI82: =CC82=L82 -> 1 | CJ82: =CD82=M82 -> 1 | CK82: =CE82=N82 -> 1 | CL82: =CF82=O82 -> 1 | CM82: =CG82=P82 -> 1
I83: 0 | J83: 0 | K83: =I83-J83 -> 0 | R83: =IF(K83=P83, "", "Error") | CC83: =SUMIFS($T83:$CA83, $T$1:$CA$1, CC$63) -> 0 | CD83: =SUMIFS($T83:$CA83, $T$1:$CA$1, CD$63) -> 0 | CE83: =SUMIFS($T83:$CA83, $T$1:$CA$1, CE$63) -> 0 | CF83: =SUMIFS($T83:$CA83, $T$1:$CA$1, CF$63) -> 0 | CG83: =SUMIFS($T83:$CA83, $T$1:$CA$1, CG$63) -> 0 | CI83: =CC83=L83 -> 1 | CJ83: =CD83=M83 -> 1 | CK83: =CE83=N83 -> 1 | CL83: =CF83=O83 -> 1 | CM83: =CG83=P83 -> 1
E84: OpEx subtotal | I84: =SUM(I79:I83) -> 0 | J84: =SUM(J79:J83) -> 0 | K84: =SUM(K79:K83) -> 0 | L84: =SUM(L79:L83) -> 0 | M84: =SUM(M79:M83) -> 0 | N84: =SUM(N79:N83) -> 0 | O84: =SUM(O79:O83) -> 0 | P84: =SUM(P79:P83) -> 0 | T84: =SUM(T79:T83) -> 0 | U84: =SUM(U79:U83) -> 0 | V84: =SUM(V79:V83) -> 0 | W84: =SUM(W79:W83) -> 0 | X84: =SUM(X79:X83) -> 0 | Y84: =SUM(Y79:Y83) -> 0 | Z84: =SUM(Z79:Z83) -> 0 | AA84: =SUM(AA79:AA83) -> 0 | ... CA84: =SUM(CA79:CA83) -> 0 | CC84: =SUM(CC79:CC83) -> 0 | CD84: =SUM(CD79:CD83) -> 0 | CE84: =SUM(CE79:CE83) -> 0 | CF84: =SUM(CF79:CF83) -> 0 | CG84: =SUM(CG79:CG83) -> 0 | CI84: =CC84=L84 -> 1 | CJ84: =CD84=M84 -> 1 | CK84: =CE84=N84 -> 1 | CL84: =CF84=O84 -> 1 | CM84: =CG84=P84 -> 1
E88: Recurring Benefits Total | I88: =SUM(I68, I76, I84) -> 0 | J88: =SUM(J68, J76, J84) -> 0 | K88: =SUM(K68, K76, K84) -> 0 | L88: =SUM(L68, L76, L84) -> 0 | M88: =SUM(M68, M76, M84) -> 0 | N88: =SUM(N68, N76, N84) -> 0 | O88: =SUM(O68, O76, O84) -> 0 | P88: =SUM(P68, P76, P84) -> 0 | T88: =SUM(T68, T76, T84) -> 0 | U88: =SUM(U68, U76, U84) -> 0 | V88: =SUM(V68, V76, V84) -> 0 | W88: =SUM(W68, W76, W84) -> 0 | X88: =SUM(X68, X76, X84) -> 0 | Y88: =SUM(Y68, Y76, Y84) -> 0 | Z88: =SUM(Z68, Z76, Z84) -> 0 | AA88: =SUM(AA68, AA76, AA84) -> 0 | ... CA88: =SUM(CA68, CA76, CA84) -> 0 | CC88: =SUM(CC68, CC76, CC84) -> 0 | CD88: =SUM(CD68, CD76, CD84) -> 0 | CE88: =SUM(CE68, CE76, CE84) -> 0 | CF88: =SUM(CF68, CF76, CF84) -> 0 | CG88: =SUM(CG68, CG76, CG84) -> 0 | CH88: =SUM(CH68, CH76, CH84) -> 0 | CI88: =CC88=L88 -> 1 | CJ88: =CD88=M88 -> 1 | CK88: =CE88=N88 -> 1 | CL88: =CF88=O88 -> 1 | CM88: =CG88=P88 -> 1
T90: 2026 | AF90: 2027 | AR90: 2028 | BD90: 2029 | BP90: 2030 | CI90: CHECK
D91: RECURRING COSTS TO ACHIEVE IMPACT | H91: Comment | I91: Baseline | J91: Goal | K91: Ann. Run Rate | L91: 2026 | M91: =L91+1 -> 2027 | N91: =M91+1 -> 2028 | O91: =N91+1 -> 2029 | P91: =O91+1 -> 2030 | Q91: Impacted BU | R91: Check | T91: 46023 | U91: =EOMONTH(T91, 1) -> 46081 | V91: =EOMONTH(U91, 1) -> 46112 | W91: =EOMONTH(V91, 1) -> 46142 | X91: =EOMONTH(W91, 1) -> 46173 | Y91: =EOMONTH(X91, 1) -> 46203 | Z91: =EOMONTH(Y91, 1) -> 46234 | AA91: =EOMONTH(Z91, 1) -> 46265 | AB91: =EOMONTH(AA91, 1) -> 46295 | ... CA91: =EOMONTH(BZ91, 1) -> 47848 | CC91: 2026 | CD91: =CC91+1 -> 2027 | CE91: =CD91+1 -> 2028 | CF91: =CE91+1 -> 2029 | CG91: =CF91+1 -> 2030 | CI91: 2026 | CJ91: =CI91+1 -> 2027 | CK91: =CJ91+1 -> 2028 | CL91: =CK91+1 -> 2029 | CM91: =CL91+1 -> 2030
E92: $USD M | I92: =$H$18 -> TTM 6/1/26 | J92: Future State | K92: Increment
E93: Revenue
I94: 0 | J94: 0 | K94: =J94-I94 -> 0 | R94: =IF(K94=P94, "", "Error") | CC94: =SUMIFS($T94:$CA94, $T$1:$CA$1, CC$63) -> 0 | CD94: =SUMIFS($T94:$CA94, $T$1:$CA$1, CD$63) -> 0 | CE94: =SUMIFS($T94:$CA94, $T$1:$CA$1, CE$63) -> 0 | CF94: =SUMIFS($T94:$CA94, $T$1:$CA$1, CF$63) -> 0 | CG94: =SUMIFS($T94:$CA94, $T$1:$CA$1, CG$63) -> 0 | CI94: =CC94=L94 -> 1 | CJ94: =CD94=M94 -> 1 | CK94: =CE94=N94 -> 1 | CL94: =CF94=O94 -> 1 | CM94: =CG94=P94 -> 1
I95: 0 | J95: 0 | K95: =J95-I95 -> 0 | R95: =IF(K95=P95, "", "Error") | CC95: =SUMIFS($T95:$CA95, $T$1:$CA$1, CC$63) -> 0 | CD95: =SUMIFS($T95:$CA95, $T$1:$CA$1, CD$63) -> 0 | CE95: =SUMIFS($T95:$CA95, $T$1:$CA$1, CE$63) -> 0 | CF95: =SUMIFS($T95:$CA95, $T$1:$CA$1, CF$63) -> 0 | CG95: =SUMIFS($T95:$CA95, $T$1:$CA$1, CG$63) -> 0 | CI95: =CC95=L95 -> 1 | CJ95: =CD95=M95 -> 1 | CK95: =CE95=N95 -> 1 | CL95: =CF95=O95 -> 1 | CM95: =CG95=P95 -> 1
E96: Revenue Subtotal | I96: =SUM(I94:I95) -> 0 | J96: =SUM(J94:J95) -> 0 | K96: =SUM(K94:K95) -> 0 | L96: =SUM(L94:L95) -> 0 | M96: =SUM(M94:M95) -> 0 | N96: =SUM(N94:N95) -> 0 | O96: =SUM(O94:O95) -> 0 | P96: =SUM(P94:P95) -> 0 | T96: =SUM(T94:T95) -> 0 | U96: =SUM(U94:U95) -> 0 | V96: =SUM(V94:V95) -> 0 | W96: =SUM(W94:W95) -> 0 | X96: =SUM(X94:X95) -> 0 | Y96: =SUM(Y94:Y95) -> 0 | Z96: =SUM(Z94:Z95) -> 0 | AA96: =SUM(AA94:AA95) -> 0 | ... CA96: =SUM(CA94:CA95) -> 0 | CC96: =SUM(CC94:CC95) -> 0 | CD96: =SUM(CD94:CD95) -> 0 | CE96: =SUM(CE94:CE95) -> 0 | CF96: =SUM(CF94:CF95) -> 0 | CG96: =SUM(CG94:CG95) -> 0 | CI96: =CC96=L96 -> 1 | CJ96: =CD96=M96 -> 1 | CK96: =CE96=N96 -> 1 | CL96: =CF96=O96 -> 1 | CM96: =CG96=P96 -> 1
E98: Cost of Sales
I99: 0 | J99: 0 | K99: =J99-I99 -> 0 | L99: 0 | M99: 0 | N99: 0 | O99: 0 | P99: 0 | R99: =IF(K99=P99, "", "Error") | CC99: =SUMIFS($T99:$CA99, $T$1:$CA$1, CC$63) -> 0 | CD99: =SUMIFS($T99:$CA99, $T$1:$CA$1, CD$63) -> 0 | CE99: =SUMIFS($T99:$CA99, $T$1:$CA$1, CE$63) -> 0 | CF99: =SUMIFS($T99:$CA99, $T$1:$CA$1, CF$63) -> 0 | CG99: =SUMIFS($T99:$CA99, $T$1:$CA$1, CG$63) -> 0 | CI99: =CC99=L99 -> 1 | CJ99: =CD99=M99 -> 1 | CK99: =CE99=N99 -> 1 | CL99: =CF99=O99 -> 1 | CM99: =CG99=P99 -> 1
I100: 0 | J100: 0 | K100: =J100-I100 -> 0 | L100: 0 | M100: 0 | N100: 0 | O100: 0 | P100: 0 | R100: =IF(K100=P100, "", "Error") | CC100: =SUMIFS($T100:$CA100, $T$1:$CA$1, CC$63) -> 0 | CD100: =SUMIFS($T100:$CA100, $T$1:$CA$1, CD$63) -> 0 | CE100: =SUMIFS($T100:$CA100, $T$1:$CA$1, CE$63) -> 0 | CF100: =SUMIFS($T100:$CA100, $T$1:$CA$1, CF$63) -> 0 | CG100: =SUMIFS($T100:$CA100, $T$1:$CA$1, CG$63) -> 0 | CI100: =CC100=L100 -> 1 | CJ100: =CD100=M100 -> 1 | CK100: =CE100=N100 -> 1 | CL100: =CF100=O100 -> 1 | CM100: =CG100=P100 -> 1
I101: 0 | J101: 0 | K101: =J101-I101 -> 0 | L101: 0 | M101: 0 | N101: 0 | O101: 0 | P101: 0 | R101: =IF(K101=P101, "", "Error") | CC101: =SUMIFS($T101:$CA101, $T$1:$CA$1, CC$63) -> 0 | CD101: =SUMIFS($T101:$CA101, $T$1:$CA$1, CD$63) -> 0 | CE101: =SUMIFS($T101:$CA101, $T$1:$CA$1, CE$63) -> 0 | CF101: =SUMIFS($T101:$CA101, $T$1:$CA$1, CF$63) -> 0 | CG101: =SUMIFS($T101:$CA101, $T$1:$CA$1, CG$63) -> 0 | CI101: =CC101=L101 -> 1 | CJ101: =CD101=M101 -> 1 | CK101: =CE101=N101 -> 1 | CL101: =CF101=O101 -> 1 | CM101: =CG101=P101 -> 1
I102: 0 | J102: 0 | K102: =J102-I102 -> 0 | L102: 0 | M102: 0 | N102: 0 | O102: 0 | P102: 0 | R102: =IF(K102=P102, "", "Error") | CC102: =SUMIFS($T102:$CA102, $T$1:$CA$1, CC$63) -> 0 | CD102: =SUMIFS($T102:$CA102, $T$1:$CA$1, CD$63) -> 0 | CE102: =SUMIFS($T102:$CA102, $T$1:$CA$1, CE$63) -> 0 | CF102: =SUMIFS($T102:$CA102, $T$1:$CA$1, CF$63) -> 0 | CG102: =SUMIFS($T102:$CA102, $T$1:$CA$1, CG$63) -> 0 | CI102: =CC102=L102 -> 1 | CJ102: =CD102=M102 -> 1 | CK102: =CE102=N102 -> 1 | CL102: =CF102=O102 -> 1 | CM102: =CG102=P102 -> 1
K103: =J103-I103 -> 0 | L103: 0 | M103: 0 | N103: 0 | O103: 0 | P103: 0
E104: Cost of Sales Subtotal | I104: =SUM(I99:I103) -> 0 | J104: =SUM(J99:J103) -> 0 | K104: =SUM(K99:K103) -> 0 | L104: =SUM(L99:L103) -> 0 | M104: =SUM(M99:M103) -> 0 | N104: =SUM(N99:N103) -> 0 | O104: =SUM(O99:O103) -> 0 | P104: =SUM(P99:P103) -> 0 | T104: =SUM(T99:T103) -> 0 | U104: =SUM(U99:U103) -> 0 | V104: =SUM(V99:V103) -> 0 | W104: =SUM(W99:W103) -> 0 | X104: =SUM(X99:X103) -> 0 | Y104: =SUM(Y99:Y103) -> 0 | Z104: =SUM(Z99:Z103) -> 0 | AA104: =SUM(AA99:AA103) -> 0 | ... CA104: =SUM(CA99:CA103) -> 0 | CC104: =SUM(CC99:CC103) -> 0 | CD104: =SUM(CD99:CD103) -> 0 | CE104: =SUM(CE99:CE103) -> 0 | CF104: =SUM(CF99:CF103) -> 0 | CG104: =SUM(CG99:CG103) -> 0 | CI104: =CC104=L104 -> 1 | CJ104: =CD104=M104 -> 1 | CK104: =CE104=N104 -> 1 | CL104: =CF104=O104 -> 1 | CM104: =CG104=P104 -> 1
E106: OPEX
E107: OPEX - PDLC harness / product tooling run | H107: PENDING — placeholder, not data. Net of tooling spend baseline (request #5) | I107: 0 | J107: =I107+'SDLC-2 Model'!$K$99 -> 0 | K107: ='SDLC-2 Model'!$K$99 -> 0 | L107: ='SDLC-2 Model'!L99 -> 0 | M107: ='SDLC-2 Model'!M99 -> 0 | N107: ='SDLC-2 Model'!N99 -> 0 | O107: ='SDLC-2 Model'!O99 -> 0 | P107: ='SDLC-2 Model'!P99 -> 0 | Q107: CTO / SDLC | R107: =IF(K107=P107, "", "Error") | T107: ='SDLC-2 Model'!T99 -> 0 | U107: ='SDLC-2 Model'!U99 -> 0 | V107: ='SDLC-2 Model'!V99 -> 0 | W107: ='SDLC-2 Model'!W99 -> 0 | X107: ='SDLC-2 Model'!X99 -> 0 | Y107: ='SDLC-2 Model'!Y99 -> 0 | Z107: ='SDLC-2 Model'!Z99 -> 0 | AA107: ='SDLC-2 Model'!AA99 -> 0 | ... CA107: ='SDLC-2 Model'!CA99 -> 0 | CC107: =SUMIFS($T107:$CA107, $T$1:$CA$1, CC$63) -> 0 | CD107: =SUMIFS($T107:$CA107, $T$1:$CA$1, CD$63) -> 0 | CE107: =SUMIFS($T107:$CA107, $T$1:$CA$1, CE$63) -> 0 | CF107: =SUMIFS($T107:$CA107, $T$1:$CA$1, CF$63) -> 0 | CG107: =SUMIFS($T107:$CA107, $T$1:$CA$1, CG$63) -> 0 | CI107: =CC107=L107 -> 1 | CJ107: =CD107=M107 -> 1 | CK107: =CE107=N107 -> 1 | CL107: =CF107=O107 -> 1 | CM107: =CG107=P107 -> 1
E108: OPEX - Model / token consumption | H108: PENDING — placeholder, not data. PDLC-side consumption not yet available (request #11) | I108: 0 | J108: =I108+'SDLC-2 Model'!$K$100 -> 0 | K108: ='SDLC-2 Model'!$K$100 -> 0 | L108: ='SDLC-2 Model'!L100 -> 0 | M108: ='SDLC-2 Model'!M100 -> 0 | N108: ='SDLC-2 Model'!N100 -> 0 | O108: ='SDLC-2 Model'!O100 -> 0 | P108: ='SDLC-2 Model'!P100 -> 0 | Q108: CTO / SDLC | R108: =IF(K108=P108, "", "Error") | T108: ='SDLC-2 Model'!T100 -> 0 | U108: ='SDLC-2 Model'!U100 -> 0 | V108: ='SDLC-2 Model'!V100 -> 0 | W108: ='SDLC-2 Model'!W100 -> 0 | X108: ='SDLC-2 Model'!X100 -> 0 | Y108: ='SDLC-2 Model'!Y100 -> 0 | Z108: ='SDLC-2 Model'!Z100 -> 0 | AA108: ='SDLC-2 Model'!AA100 -> 0 | ... CA108: ='SDLC-2 Model'!CA100 -> 0 | CC108: =SUMIFS($T108:$CA108, $T$1:$CA$1, CC$63) -> 0 | CD108: =SUMIFS($T108:$CA108, $T$1:$CA$1, CD$63) -> 0 | CE108: =SUMIFS($T108:$CA108, $T$1:$CA$1, CE$63) -> 0 | CF108: =SUMIFS($T108:$CA108, $T$1:$CA$1, CF$63) -> 0 | CG108: =SUMIFS($T108:$CA108, $T$1:$CA$1, CG$63) -> 0 | CI108: =CC108=L108 -> 1 | CJ108: =CD108=M108 -> 1 | CK108: =CE108=N108 -> 1 | CL108: =CF108=O108 -> 1 | CM108: =CG108=P108 -> 1
I109: 0 | J109: 0 | K109: =J109-I109 -> 0 | L109: 0 | M109: 0 | N109: 0 | O109: 0 | P109: 0 | R109: =IF(K109=P109, "", "Error") | CC109: =SUMIFS($T109:$CA109, $T$1:$CA$1, CC$63) -> 0 | CD109: =SUMIFS($T109:$CA109, $T$1:$CA$1, CD$63) -> 0 | CE109: =SUMIFS($T109:$CA109, $T$1:$CA$1, CE$63) -> 0 | CF109: =SUMIFS($T109:$CA109, $T$1:$CA$1, CF$63) -> 0 | CG109: =SUMIFS($T109:$CA109, $T$1:$CA$1, CG$63) -> 0 | CI109: =CC109=L109 -> 1 | CJ109: =CD109=M109 -> 1 | CK109: =CE109=N109 -> 1 | CL109: =CF109=O109 -> 1 | CM109: =CG109=P109 -> 1
I110: 0 | J110: 0 | K110: =J110-I110 -> 0 | L110: 0 | M110: 0 | N110: 0 | O110: 0 | P110: 0 | R110: =IF(K110=P110, "", "Error") | CC110: =SUMIFS($T110:$CA110, $T$1:$CA$1, CC$63) -> 0 | CD110: =SUMIFS($T110:$CA110, $T$1:$CA$1, CD$63) -> 0 | CE110: =SUMIFS($T110:$CA110, $T$1:$CA$1, CE$63) -> 0 | CF110: =SUMIFS($T110:$CA110, $T$1:$CA$1, CF$63) -> 0 | CG110: =SUMIFS($T110:$CA110, $T$1:$CA$1, CG$63) -> 0 | CI110: =CC110=L110 -> 1 | CJ110: =CD110=M110 -> 1 | CK110: =CE110=N110 -> 1 | CL110: =CF110=O110 -> 1 | CM110: =CG110=P110 -> 1
I111: 0 | J111: 0 | K111: =J111-I111 -> 0 | L111: 0 | M111: 0 | N111: 0 | O111: 0 | P111: 0 | R111: =IF(K111=P111, "", "Error") | CC111: =SUMIFS($T111:$CA111, $T$1:$CA$1, CC$63) -> 0 | CD111: =SUMIFS($T111:$CA111, $T$1:$CA$1, CD$63) -> 0 | CE111: =SUMIFS($T111:$CA111, $T$1:$CA$1, CE$63) -> 0 | CF111: =SUMIFS($T111:$CA111, $T$1:$CA$1, CF$63) -> 0 | CG111: =SUMIFS($T111:$CA111, $T$1:$CA$1, CG$63) -> 0 | CI111: =CC111=L111 -> 1 | CJ111: =CD111=M111 -> 1 | CK111: =CE111=N111 -> 1 | CL111: =CF111=O111 -> 1 | CM111: =CG111=P111 -> 1
E112: OpEx subtotal | I112: =SUM(I107:I111) -> 0 | J112: =SUM(J107:J111) -> 0 | K112: =SUM(K107:K111) -> 0 | L112: =SUM(L107:L111) -> 0 | M112: =SUM(M107:M111) -> 0 | N112: =SUM(N107:N111) -> 0 | O112: =SUM(O107:O111) -> 0 | P112: =SUM(P107:P111) -> 0 | T112: =SUM(T107:T111) -> 0 | U112: =SUM(U107:U111) -> 0 | V112: =SUM(V107:V111) -> 0 | W112: =SUM(W107:W111) -> 0 | X112: =SUM(X107:X111) -> 0 | Y112: =SUM(Y107:Y111) -> 0 | Z112: =SUM(Z107:Z111) -> 0 | AA112: =SUM(AA107:AA111) -> 0 | ... CA112: =SUM(CA107:CA111) -> 0 | CC112: =SUM(CC107:CC111) -> 0 | CD112: =SUM(CD107:CD111) -> 0 | CE112: =SUM(CE107:CE111) -> 0 | CF112: =SUM(CF107:CF111) -> 0 | CG112: =SUM(CG107:CG111) -> 0 | CI112: =CC112=L112 -> 1 | CJ112: =CD112=M112 -> 1 | CK112: =CE112=N112 -> 1 | CL112: =CF112=O112 -> 1 | CM112: =CG112=P112 -> 1
E115: Recurring Costs Total | I115: =SUM(-I96, I104, I112) -> 0 | J115: =SUM(-J96, J104, J112) -> 0 | K115: =SUM(-K96, K104, K112) -> 0 | L115: =SUM(-L96, L104, L112) -> 0 | M115: =SUM(-M96, M104, M112) -> 0 | N115: =SUM(-N96, N104, N112) -> 0 | O115: =SUM(-O96, O104, O112) -> 0 | P115: =SUM(-P96, P104, P112) -> 0 | T115: =SUM(-T96, T104, T112) -> 0 | U115: =SUM(-U96, U104, U112) -> 0 | V115: =SUM(-V96, V104, V112) -> 0 | W115: =SUM(-W96, W104, W112) -> 0 | X115: =SUM(-X96, X104, X112) -> 0 | Y115: =SUM(-Y96, Y104, Y112) -> 0 | Z115: =SUM(-Z96, Z104, Z112) -> 0 | AA115: =SUM(-AA96, AA104, AA112) -> 0 | ... CA115: =SUM(-CA96, CA104, CA112) -> 0 | CC115: =SUM(-CC96, CC104, CC112) -> 0 | CD115: =SUM(-CD96, CD104, CD112) -> 0 | CE115: =SUM(-CE96, CE104, CE112) -> 0 | CF115: =SUM(-CF96, CF104, CF112) -> 0 | CG115: =SUM(-CG96, CG104, CG112) -> 0 | CI115: =CC115=L115 -> 1 | CJ115: =CD115=M115 -> 1 | CK115: =CE115=N115 -> 1 | CL115: =CF115=O115 -> 1 | CM115: =CG115=P115 -> 1
E117: Net Recurring Benefit | I117: =SUM(I88, -I115) -> 0 | J117: =SUM(J88, -J115) -> 0 | K117: =SUM(K88, -K115) -> 0 | L117: =SUM(L88, -L115) -> 0 | M117: =SUM(M88, -M115) -> 0 | N117: =SUM(N88, -N115) -> 0 | O117: =SUM(O88, -O115) -> 0 | P117: =SUM(P88, -P115) -> 0 | R117: =IF(K117=P117, "", "Error") | T117: =SUM(T88, -T115) -> 0 | U117: =SUM(U88, -U115) -> 0 | V117: =SUM(V88, -V115) -> 0 | W117: =SUM(W88, -W115) -> 0 | X117: =SUM(X88, -X115) -> 0 | Y117: =SUM(Y88, -Y115) -> 0 | Z117: =SUM(Z88, -Z115) -> 0 | AA117: =SUM(AA88, -AA115) -> 0 | ... CA117: =SUM(CA88, -CA115) -> 0 | CC117: =SUM(CC88, -CC115) -> 0 | CD117: =SUM(CD88, -CD115) -> 0 | CE117: =SUM(CE88, -CE115) -> 0 | CF117: =SUM(CF88, -CF115) -> 0 | CG117: =SUM(CG88, -CG115) -> 0 | CI117: =CC117=L117 -> 1 | CJ117: =CD117=M117 -> 1 | CK117: =CE117=N117 -> 1 | CL117: =CF117=O117 -> 1 | CM117: =CG117=P117 -> 1
C120: SECTION III - ONE-TIME IMPLEMENTATION | CC120: ANNUAL SUMMARY | CI120: CHECK CELLS
T122: 2026 | AF122: 2027 | AR122: 2028 | BD122: 2029 | BP122: 2030
D123: ONE-TIME BENEFITS | K123: Comment | L123: 2026 | M123: =L123+1 -> 2027 | N123: =M123+1 -> 2028 | O123: =N123+1 -> 2029 | P123: =O123+1 -> 2030 | Q123: Impacted BU | T123: 46023 | U123: =EOMONTH(T123, 1) -> 46081 | V123: =EOMONTH(U123, 1) -> 46112 | W123: =EOMONTH(V123, 1) -> 46142 | X123: =EOMONTH(W123, 1) -> 46173 | Y123: =EOMONTH(X123, 1) -> 46203 | Z123: =EOMONTH(Y123, 1) -> 46234 | AA123: =EOMONTH(Z123, 1) -> 46265 | AB123: =EOMONTH(AA123, 1) -> 46295 | ... CA123: =EOMONTH(BZ123, 1) -> 47848 | CC123: 2026 | CD123: =CC123+1 -> 2027 | CE123: =CD123+1 -> 2028 | CF123: =CE123+1 -> 2029 | CG123: =CF123+1 -> 2030 | CI123: 2026 | CJ123: =CI123+1 -> 2027 | CK123: =CJ123+1 -> 2028 | CL123: =CK123+1 -> 2029 | CM123: =CL123+1 -> 2030
E125: Working Capital
CC126: =SUMIFS($T126:$CA126, $T$1:$CA$1, CC$63) -> 0 | CD126: =SUMIFS($T126:$CA126, $T$1:$CA$1, CD$63) -> 0 | CE126: =SUMIFS($T126:$CA126, $T$1:$CA$1, CE$63) -> 0 | CF126: =SUMIFS($T126:$CA126, $T$1:$CA$1, CF$63) -> 0 | CG126: =SUMIFS($T126:$CA126, $T$1:$CA$1, CG$63) -> 0 | CI126: =CC126=L126 -> 1 | CJ126: =CD126=M126 -> 1 | CK126: =CE126=N126 -> 1 | CL126: =CF126=O126 -> 1 | CM126: =CG126=P126 -> 1
CC127: =SUMIFS($T127:$CA127, $T$1:$CA$1, CC$63) -> 0 | CD127: =SUMIFS($T127:$CA127, $T$1:$CA$1, CD$63) -> 0 | CE127: =SUMIFS($T127:$CA127, $T$1:$CA$1, CE$63) -> 0 | CF127: =SUMIFS($T127:$CA127, $T$1:$CA$1, CF$63) -> 0 | CG127: =SUMIFS($T127:$CA127, $T$1:$CA$1, CG$63) -> 0 | CI127: =CC127=L127 -> 1 | CJ127: =CD127=M127 -> 1 | CK127: =CE127=N127 -> 1 | CL127: =CF127=O127 -> 1 | CM127: =CG127=P127 -> 1
E128: Working Capital Subtotal | L128: =SUM(L126:L127) -> 0 | M128: =SUM(M126:M127) -> 0 | N128: =SUM(N126:N127) -> 0 | O128: =SUM(O126:O127) -> 0 | P128: =SUM(P126:P127) -> 0 | T128: =SUM(T126:T127) -> 0 | U128: =SUM(U126:U127) -> 0 | V128: =SUM(V126:V127) -> 0 | W128: =SUM(W126:W127) -> 0 | X128: =SUM(X126:X127) -> 0 | Y128: =SUM(Y126:Y127) -> 0 | Z128: =SUM(Z126:Z127) -> 0 | AA128: =SUM(AA126:AA127) -> 0 | ... CA128: =SUM(CA126:CA127) -> 0 | CC128: =SUM(CC126:CC127) -> 0 | CD128: =SUM(CD126:CD127) -> 0 | CE128: =SUM(CE126:CE127) -> 0 | CF128: =SUM(CF126:CF127) -> 0 | CG128: =SUM(CG126:CG127) -> 0 | CI128: =CC128=L128 -> 1 | CJ128: =CD128=M128 -> 1 | CK128: =CE128=N128 -> 1 | CL128: =CF128=O128 -> 1 | CM128: =CG128=P128 -> 1
E130: One-Time Benefits Total | L130: =L128 -> 0 | M130: =M128 -> 0 | N130: =N128 -> 0 | O130: =O128 -> 0 | P130: =P128 -> 0 | T130: =T128 -> 0 | U130: =U128 -> 0 | V130: =V128 -> 0 | W130: =W128 -> 0 | X130: =X128 -> 0 | Y130: =Y128 -> 0 | Z130: =Z128 -> 0 | AA130: =AA128 -> 0 | ... CA130: =CA128 -> 0 | CC130: =CC128 -> 0 | CD130: =CD128 -> 0 | CE130: =CE128 -> 0 | CF130: =CF128 -> 0 | CG130: =CG128 -> 0 | CI130: =CI128 -> 1 | CJ130: =CJ128 -> 1 | CK130: =CK128 -> 1 | CL130: =CL128 -> 1 | CM130: =CM128 -> 1
T132: 2026 | AF132: 2027 | AR132: 2028 | BD132: 2029 | BP132: 2030
D133: CAPEX AND ONE-TIME COSTS | K133: Comment | L133: 2026 | M133: =L133+1 -> 2027 | N133: =M133+1 -> 2028 | O133: =N133+1 -> 2029 | P133: =O133+1 -> 2030 | T133: 46023 | U133: =EOMONTH(T133, 1) -> 46081 | V133: =EOMONTH(U133, 1) -> 46112 | W133: =EOMONTH(V133, 1) -> 46142 | X133: =EOMONTH(W133, 1) -> 46173 | Y133: =EOMONTH(X133, 1) -> 46203 | Z133: =EOMONTH(Y133, 1) -> 46234 | AA133: =EOMONTH(Z133, 1) -> 46265 | AB133: =EOMONTH(AA133, 1) -> 46295 | ... CA133: =EOMONTH(BZ133, 1) -> 47848 | CC133: 2026 | CD133: =CC133+1 -> 2027 | CE133: =CD133+1 -> 2028 | CF133: =CE133+1 -> 2029 | CG133: =CF133+1 -> 2030 | CI133: 2026 | CJ133: =CI133+1 -> 2027 | CK133: =CJ133+1 -> 2028 | CL133: =CK133+1 -> 2029 | CM133: =CL133+1 -> 2030
E135: Capital Expenditures
E136: CAPEX — capitalized build labor | L136: ='SDLC-2 Model'!L86 -> 0 | M136: ='SDLC-2 Model'!M86 -> 0.52653333 | N136: ='SDLC-2 Model'!N86 -> 0 | O136: ='SDLC-2 Model'!O86 -> 0 | P136: ='SDLC-2 Model'!P86 -> 0 | Q136: CTO / SDLC | T136: ='SDLC-2 Model'!T86 -> 0 | U136: ='SDLC-2 Model'!U86 -> 0 | V136: ='SDLC-2 Model'!V86 -> 0 | W136: ='SDLC-2 Model'!W86 -> 0 | X136: ='SDLC-2 Model'!X86 -> 0 | Y136: ='SDLC-2 Model'!Y86 -> 0 | Z136: ='SDLC-2 Model'!Z86 -> 0 | AA136: ='SDLC-2 Model'!AA86 -> 0 | ... CA136: ='SDLC-2 Model'!CA86 -> 0 | CC136: =SUMIFS($T136:$CA136, $T$1:$CA$1, CC$63) -> 0 | CD136: =SUMIFS($T136:$CA136, $T$1:$CA$1, CD$63) -> 0.52653333 | CE136: =SUMIFS($T136:$CA136, $T$1:$CA$1, CE$63) -> 0 | CF136: =SUMIFS($T136:$CA136, $T$1:$CA$1, CF$63) -> 0 | CG136: =SUMIFS($T136:$CA136, $T$1:$CA$1, CG$63) -> 0 | CI136: =CC136=L136 -> 1 | CJ136: =CD136=M136 -> 1 | CK136: =CE136=N136 -> 1 | CL136: =CF136=O136 -> 1 | CM136: =CG136=P136 -> 1
E137: CAPEX — capitalized non-labor | L137: ='SDLC-2 Model'!L87 -> 0 | M137: ='SDLC-2 Model'!M87 -> 0 | N137: ='SDLC-2 Model'!N87 -> 0 | O137: ='SDLC-2 Model'!O87 -> 0 | P137: ='SDLC-2 Model'!P87 -> 0 | Q137: CTO / SDLC | T137: ='SDLC-2 Model'!T87 -> 0 | U137: ='SDLC-2 Model'!U87 -> 0 | V137: ='SDLC-2 Model'!V87 -> 0 | W137: ='SDLC-2 Model'!W87 -> 0 | X137: ='SDLC-2 Model'!X87 -> 0 | Y137: ='SDLC-2 Model'!Y87 -> 0 | Z137: ='SDLC-2 Model'!Z87 -> 0 | AA137: ='SDLC-2 Model'!AA87 -> 0 | ... CA137: ='SDLC-2 Model'!CA87 -> 0 | CC137: =SUMIFS($T137:$CA137, $T$1:$CA$1, CC$63) -> 0 | CD137: =SUMIFS($T137:$CA137, $T$1:$CA$1, CD$63) -> 0 | CE137: =SUMIFS($T137:$CA137, $T$1:$CA$1, CE$63) -> 0 | CF137: =SUMIFS($T137:$CA137, $T$1:$CA$1, CF$63) -> 0 | CG137: =SUMIFS($T137:$CA137, $T$1:$CA$1, CG$63) -> 0 | CI137: =CC137=L137 -> 1 | CJ137: =CD137=M137 -> 1 | CK137: =CE137=N137 -> 1 | CL137: =CF137=O137 -> 1 | CM137: =CG137=P137 -> 1
E138: Capital Expenditures Subtotal | L138: =SUM(L136:L137) -> 0 | M138: =SUM(M136:M137) -> 0.52653333 | N138: =SUM(N136:N137) -> 0 | O138: =SUM(O136:O137) -> 0 | P138: =SUM(P136:P137) -> 0 | T138: =SUM(T136:T137) -> 0 | U138: =SUM(U136:U137) -> 0 | V138: =SUM(V136:V137) -> 0 | W138: =SUM(W136:W137) -> 0 | X138: =SUM(X136:X137) -> 0 | Y138: =SUM(Y136:Y137) -> 0 | Z138: =SUM(Z136:Z137) -> 0 | AA138: =SUM(AA136:AA137) -> 0 | ... CA138: =SUM(CA136:CA137) -> 0 | CC138: =SUM(CC136:CC137) -> 0 | CD138: =SUM(CD136:CD137) -> 0.52653333 | CE138: =SUM(CE136:CE137) -> 0 | CF138: =SUM(CF136:CF137) -> 0 | CG138: =SUM(CG136:CG137) -> 0 | CI138: =CC138=L138 -> 1 | CJ138: =CD138=M138 -> 1 | CK138: =CE138=N138 -> 1 | CL138: =CF138=O138 -> 1 | CM138: =CG138=P138 -> 1
E140: OTC
E141: OTC — build labor (expensed) | L141: ='SDLC-2 Model'!L88 -> 0.13163333 | M141: ='SDLC-2 Model'!M88 -> 0.62525833 | N141: ='SDLC-2 Model'!N88 -> 0 | O141: ='SDLC-2 Model'!O88 -> 0 | P141: ='SDLC-2 Model'!P88 -> 0 | Q141: CTO / SDLC | T141: ='SDLC-2 Model'!T88 -> 0 | U141: ='SDLC-2 Model'!U88 -> 0 | V141: ='SDLC-2 Model'!V88 -> 0 | W141: ='SDLC-2 Model'!W88 -> 0 | X141: ='SDLC-2 Model'!X88 -> 0 | Y141: ='SDLC-2 Model'!Y88 -> 0 | Z141: ='SDLC-2 Model'!Z88 -> 0 | AA141: ='SDLC-2 Model'!AA88 -> 0 | ... CA141: ='SDLC-2 Model'!CA88 -> 0 | CC141: =SUMIFS($T141:$CA141, $T$1:$CA$1, CC$63) -> 0.13163333 | CD141: =SUMIFS($T141:$CA141, $T$1:$CA$1, CD$63) -> 0.62525833 | CE141: =SUMIFS($T141:$CA141, $T$1:$CA$1, CE$63) -> 0 | CF141: =SUMIFS($T141:$CA141, $T$1:$CA$1, CF$63) -> 0 | CG141: =SUMIFS($T141:$CA141, $T$1:$CA$1, CG$63) -> 0 | CI141: =CC141=L141 -> 1 | CJ141: =CD141=M141 -> 1 | CK141: =CE141=N141 -> 1 | CL141: =CF141=O141 -> 1 | CM141: =CG141=P141 -> 1
E142: OTC — non-labor (expensed) | L142: ='SDLC-2 Model'!L89 -> 0.053618644 | M142: ='SDLC-2 Model'!M89 -> 0.18766526 | N142: ='SDLC-2 Model'!N89 -> 0 | O142: ='SDLC-2 Model'!O89 -> 0 | P142: ='SDLC-2 Model'!P89 -> 0 | Q142: CTO / SDLC | T142: ='SDLC-2 Model'!T89 -> 0 | U142: ='SDLC-2 Model'!U89 -> 0 | V142: ='SDLC-2 Model'!V89 -> 0 | W142: ='SDLC-2 Model'!W89 -> 0 | X142: ='SDLC-2 Model'!X89 -> 0 | Y142: ='SDLC-2 Model'!Y89 -> 0 | Z142: ='SDLC-2 Model'!Z89 -> 0 | AA142: ='SDLC-2 Model'!AA89 -> 0 | ... CA142: ='SDLC-2 Model'!CA89 -> 0 | CC142: =SUMIFS($T142:$CA142, $T$1:$CA$1, CC$63) -> 0.053618644 | CD142: =SUMIFS($T142:$CA142, $T$1:$CA$1, CD$63) -> 0.18766526 | CE142: =SUMIFS($T142:$CA142, $T$1:$CA$1, CE$63) -> 0 | CF142: =SUMIFS($T142:$CA142, $T$1:$CA$1, CF$63) -> 0 | CG142: =SUMIFS($T142:$CA142, $T$1:$CA$1, CG$63) -> 0 | CI142: =CC142=L142 -> 1 | CJ142: =CD142=M142 -> 1 | CK142: =CE142=N142 -> 1 | CL142: =CF142=O142 -> 1 | CM142: =CG142=P142 -> 1
CC143: =SUMIFS($T143:$CA143, $T$1:$CA$1, CC$63) -> 0 | CD143: =SUMIFS($T143:$CA143, $T$1:$CA$1, CD$63) -> 0 | CE143: =SUMIFS($T143:$CA143, $T$1:$CA$1, CE$63) -> 0 | CF143: =SUMIFS($T143:$CA143, $T$1:$CA$1, CF$63) -> 0 | CG143: =SUMIFS($T143:$CA143, $T$1:$CA$1, CG$63) -> 0 | CI143: =CC143=L143 -> 1 | CJ143: =CD143=M143 -> 1 | CK143: =CE143=N143 -> 1 | CL143: =CF143=O143 -> 1 | CM143: =CG143=P143 -> 1
E144: OTC Subtotal | L144: =SUM(L141:L143) -> 0.18525198 | M144: =SUM(M141:M143) -> 0.81292359 | N144: =SUM(N141:N143) -> 0 | O144: =SUM(O141:O143) -> 0 | P144: =SUM(P141:P143) -> 0 | T144: =SUM(T141:T143) -> 0 | U144: =SUM(U141:U143) -> 0 | V144: =SUM(V141:V143) -> 0 | W144: =SUM(W141:W143) -> 0 | X144: =SUM(X141:X143) -> 0 | Y144: =SUM(Y141:Y143) -> 0 | Z144: =SUM(Z141:Z143) -> 0 | AA144: =SUM(AA141:AA143) -> 0 | ... CA144: =SUM(CA141:CA143) -> 0 | CC144: =SUM(CC141:CC143) -> 0.18525198 | CD144: =SUM(CD141:CD143) -> 0.81292359 | CE144: =SUM(CE141:CE143) -> 0 | CF144: =SUM(CF141:CF143) -> 0 | CG144: =SUM(CG141:CG143) -> 0 | CI144: =CC144=L144 -> 1 | CJ144: =CD144=M144 -> 1 | CK144: =CE144=N144 -> 1 | CL144: =CF144=O144 -> 1 | CM144: =CG144=P144 -> 1
E147: One-Time Costs Total | L147: =SUM(L138, L144) -> 0.18525198 | M147: =SUM(M138, M144) -> 1.3394569 | N147: =SUM(N138, N144) -> 0 | O147: =SUM(O138, O144) -> 0 | P147: =SUM(P138, P144) -> 0 | T147: =SUM(T138, T144) -> 0 | U147: =SUM(U138, U144) -> 0 | V147: =SUM(V138, V144) -> 0 | W147: =SUM(W138, W144) -> 0 | X147: =SUM(X138, X144) -> 0 | Y147: =SUM(Y138, Y144) -> 0 | Z147: =SUM(Z138, Z144) -> 0 | AA147: =SUM(AA138, AA144) -> 0 | ... CA147: =SUM(CA138, CA144) -> 0 | CC147: =SUM(CC138, CC144) -> 0.18525198 | CD147: =SUM(CD138, CD144) -> 1.3394569 | CE147: =SUM(CE138, CE144) -> 0 | CF147: =SUM(CF138, CF144) -> 0 | CG147: =SUM(CG138, CG144) -> 0 | CI147: =CC147=L147 -> 1 | CJ147: =CD147=M147 -> 1 | CK147: =CE147=N147 -> 1 | CL147: =CF147=O147 -> 1 | CM147: =CG147=P147 -> 1
E149: Total One-Time Implementation Cost | L149: =SUM(L130, -L147) -> -0.18525198 | M149: =SUM(M130, -M147) -> -1.3394569 | N149: =SUM(N130, -N147) -> 0 | O149: =SUM(O130, -O147) -> 0 | P149: =SUM(P130, -P147) -> 0 | T149: =SUM(T130, -T147) -> 0 | U149: =SUM(U130, -U147) -> 0 | V149: =SUM(V130, -V147) -> 0 | W149: =SUM(W130, -W147) -> 0 | X149: =SUM(X130, -X147) -> 0 | Y149: =SUM(Y130, -Y147) -> 0 | Z149: =SUM(Z130, -Z147) -> 0 | AA149: =SUM(AA130, -AA147) -> 0 | ... CA149: =SUM(CA130, -CA147) -> 0 | CC149: =SUM(CC130, -CC147) -> -0.18525198 | CD149: =SUM(CD130, -CD147) -> -1.3394569 | CE149: =SUM(CE130, -CE147) -> 0 | CF149: =SUM(CF130, -CF147) -> 0 | CG149: =SUM(CG130, -CG147) -> 0 | CI149: =CC149=L149 -> 1 | CJ149: =CD149=M149 -> 1 | CK149: =CE149=N149 -> 1 | CL149: =CF149=O149 -> 1 | CM149: =CG149=P149 -> 1
C152: SECTION IV - FINANCIAL METRICS | CC152: ANNUAL SUMMARY | CI152: CHECK CELLS
E155: Cash Flow | L155: 2026 | M155: =L155+1 -> 2027 | N155: =M155+1 -> 2028 | O155: =N155+1 -> 2029 | P155: =O155+1 -> 2030 | Q155: Total
E156: Operating Income | L156: =L117 -> 0 | M156: =M117 -> 0 | N156: =N117 -> 0 | O156: =O117 -> 0 | P156: =P117 -> 0 | Q156: =SUM(L156:P156) -> 0
E157: (+) One-Time Benefits | L157: =L130 -> 0 | M157: =M130 -> 0 | N157: =N130 -> 0 | O157: =O130 -> 0 | P157: =P130 -> 0 | Q157: =SUM(L157:P157) -> 0
E158: (-) One-Time Cash Costs | L158: =-L147 -> -0.18525198 | M158: =-M147 -> -1.3394569 | N158: =-N147 -> 0 | O158: =-O147 -> 0 | P158: =-P147 -> 0 | Q158: =SUM(L158:P158) -> -1.5247089
E159: Cash Flow | L159: =SUM(L156:L158) -> -0.18525198 | M159: =SUM(M156:M158) -> -1.3394569 | N159: =SUM(N156:N158) -> 0 | O159: =SUM(O156:O158) -> 0 | P159: =SUM(P156:P158) -> 0 | Q159: =SUM(L159:P159) -> -1.5247089
E160: Cumulative Cash Flow | L160: =L159 -> -0.18525198 | M160: =L160+M159 -> -1.5247089 | N160: =M160+N159 -> -1.5247089 | O160: =N160+O159 -> -1.5247089 | P160: =O160+P159 -> -1.5247089 | Q160: =P160 -> -1.5247089
E161: Payback timeline | L161: =IF(L160<0,1,0) -> 1 | M161: =IF(M160<0,1,IF(AND(L160<0,M159>0),-L160/M159,0)) -> 1 | N161: =IF(N160<0,1,IF(AND(M160<0,N159>0),-M160/N159,0)) -> 1 | O161: =IF(O160<0,1,IF(AND(N160<0,O159>0),-N160/O159,0)) -> 1 | P161: =IF(P160<0,1,IF(AND(O160<0,P159>0),-O160/P159,0)) -> 1
E163: Return on Investment | F163: NRB/OTC | G163: =IFERROR(K117/-SUM(L149:P149),"n/a") -> 0
E164: Internal Rate of Return | F164: 5-yr IRR | G164: =IFERROR(IRR($L$159:$P$159, 0.2),"n/a") -> n/a
E165: Breakeven timeline | F165: # yrs | G165: =IF(SUM(L161:P161)=5,">5",SUM(L161:P161)) -> >5
E167: WACC | G167: 0.095
E168: NPV | F168: $ | G168: =SUM(L168:P168) -> -1.2863017 | L168: =L159/(1+$G$167)^L$1 -> -0.16917989 | M168: =M159/(1+$G$167)^M$1 -> -1.1171218 | N168: =N159/(1+$G$167)^N$1 -> 0 | O168: =O159/(1+$G$167)^O$1 -> 0 | P168: =P159/(1+$G$167)^P$1 -> 0 | Q168: =SUM(L168:P168) -> -1.2863017
C171: END

Sheet Standard Template
L1: 1 | M1: 2 | N1: 3 | O1: 4 | P1: 5 | R1: =COUNTIFS($R$66:$R$117, "Error") -> 0 | T1: 2026 | U1: 2026 | V1: 2026 | W1: 2026 | X1: 2026 | Y1: 2026 | Z1: 2026 | AA1: 2026 | AB1: 2026 | AC1: 2026 | AD1: 2026 | AE1: 2026 | AF1: 2027 | AG1: 2027 | AH1: 2027 | AI1: 2027 | AJ1: 2027 | AK1: 2027 | AL1: 2027 | AM1: 2027 | AN1: 2027 | AO1: 2027 | AP1: 2027 | AQ1: 2027 | AR1: 2028 | AS1: 2028 | AT1: 2028 | AU1: 2028 | AV1: 2028 | AW1: 2028 | AX1: 2028 | AY1: 2028 | AZ1: 2028 | BA1: 2028 | BB1: 2028 | BC1: 2028 | BD1: 2029 | BE1: 2029 | BF1: 2029 | BG1: 2029 | BH1: 2029 | BI1: 2029 | BJ1: 2029 | BK1: 2029 | BL1: 2029 | BM1: 2029 | BN1: 2029 | BO1: 2029 | BP1: 2030 | BQ1: 2030 | BR1: 2030 | BS1: 2030 | BT1: 2030 | BU1: 2030 | BV1: 2030 | BW1: 2030 | BX1: 2030 | BY1: 2030 | BZ1: 2030 | CA1: 2030 | CI1: =COUNTIFS(CI$66:CI$149, "FALSE") -> 0 | CJ1: =COUNTIFS(CJ$66:CJ$149, "FALSE") -> 0 | CK1: =COUNTIFS(CK$66:CK$149, "FALSE") -> 0 | CL1: =COUNTIFS(CL$66:CL$149, "FALSE") -> 0 | CM1: =COUNTIFS(CM$66:CM$149, "FALSE") -> 0
C2: ="#"&$F$6&" Initiative Business Case" -> # Initiative Business Case
C4: INPUTS & ASSUMPTIONS
D6: Initiative #
D7: Initiative Owner
D8: Initiative Name
D11: Estimated L4 date
D12: Net Recurring Benefit ($M) | F12: =$K$117 -> 0
C14: SECTION I - PRIMARY VALUE DRIVER (ILLUSTRATIVE)
D16: Illustrative example of value driver explanation - please edit fields to reflect value drivers for your Initiative
D17: Baseline | H17: Period | I17: KPI | J17: Inputs
E18: # CW headcount | H18: TTM 6/1/26 | I18: # CW
E19: Average hourly cost for CW | H19: =$H$18 -> TTM 6/1/26 | I19: $USD / # hr
E20: Average utliization hours for CW - annual | H20: =$H$18 -> TTM 6/1/26 | I20: # hr
E21: Total CW spend | H21: =$H$18 -> TTM 6/1/26 | I21: $USD M | J21: =(J18*J19*J20)/1000000 -> 0
D23: Goal
E24: # FTE headcount - lower cost location | H24: FY2026 | I24: # FTE's
E25: Average fully loaded annual cost per FTE - lower cost location | H25: FY2026 | I25: $ / FTE
E26: Total personnel spend for BU | H26: FY2026 | I26: $USD | J26: =(J24*J25)/1000000 -> 0
D28: Incremental Improvement
E29: Total personnel spend for X business unit | I29: $USD | J29: =J21-J26 -> 0
D31: Baseline | H31: Period | I31: $USD M | J31: Inputs
E32: # xxxx | H32: =$H$18 -> TTM 6/1/26 | I32: # xxxx | J32: 0
E33: xxxx unit cost | G33: [A] | H33: FY2025 | I33: $ xxxx | J33: 0
E34: xxxx total spend | G34: [B] | H34: FY2025 | I34: $USD K | J34: =(J32*J33)/1000 -> 0
D36: Goal
E37: # xxxx | H37: FY2025 | I37: # xxxx | J37: =$J$18 -> 0
E38: xxxx unit cost | G38: [C] | H38: FY2026 | I38: $ xxxx | J38: 0
E39: xxxx total spend | G39: [D] | H39: FY2026 | I39: $USD K | J39: =(J37*J38)/1000 -> 0
D41: Incremental Improvement
E42: =E38 -> xxxx unit cost | G42: [A]-[C] | I42: $ / xxxx | J42: =J33-J38 -> 0
E43: =E39 -> xxxx total spend | G43: [B]-[D] | I43: $USD K | J43: =J34-J39 -> 0
D45: Baseline | H45: Period | I45: KPI | J45: Inputs
E46: # xxxx | H46: FY2025 | I46: # xxxx | J46: 0
E47: xxxx unit cost | G47: [A] | H47: FY2025 | I47: $ xxxx | J47: 0
E48: xxxx total spend | G48: [B] | H48: FY2025 | I48: $USD K | J48: =(J46*J47)/1000 -> 0
D50: Goal
E51: # xxxx | H51: FY2025 | I51: # xxxx | J51: =$J$18 -> 0
E52: xxxx unit cost | G52: [C] | H52: FY2026 | I52: $ xxxx | J52: 0
E53: xxxx total spend | G53: [D] | H53: FY2026 | I53: $USD K | J53: =(J51*J52)/1000 -> 0
D55: Incremental Improvement
E56: =E52 -> xxxx unit cost | G56: [A]-[C] | I56: $ / xxxx | J56: =J47-J52 -> 0
E57: =E53 -> xxxx total spend | G57: [B]-[D] | I57: $USD K | J57: =J48-J53 -> 0
C60: SECTION II - NET RECURRING BENEFITS | CC60: ANNUAL SUMMARY | CI60: CHECK CELLS
T62: 2026 | AF62: 2027 | AR62: 2028 | BD62: 2029 | BP62: 2030 | CI62: CHECK
D63: RECURRING BENEFITS | H63: Comment | I63: Baseline | J63: Goal | K63: Ann. Run Rate | L63: 2026 | M63: =L63+1 -> 2027 | N63: =M63+1 -> 2028 | O63: =N63+1 -> 2029 | P63: =O63+1 -> 2030 | Q63: Impacted BU | R63: Check | T63: 46023 | U63: =EOMONTH(T63, 1) -> 46081 | V63: =EOMONTH(U63, 1) -> 46112 | W63: =EOMONTH(V63, 1) -> 46142 | X63: =EOMONTH(W63, 1) -> 46173 | Y63: =EOMONTH(X63, 1) -> 46203 | Z63: =EOMONTH(Y63, 1) -> 46234 | AA63: =EOMONTH(Z63, 1) -> 46265 | AB63: =EOMONTH(AA63, 1) -> 46295 | ... CA63: =EOMONTH(BZ63, 1) -> 47848 | CC63: 2026 | CD63: =CC63+1 -> 2027 | CE63: =CD63+1 -> 2028 | CF63: =CE63+1 -> 2029 | CG63: =CF63+1 -> 2030 | CI63: 2026 | CJ63: =CI63+1 -> 2027 | CK63: =CJ63+1 -> 2028 | CL63: =CK63+1 -> 2029 | CM63: =CL63+1 -> 2030
E64: $USD M | I64: ="TTM "&TEXT($H$18,"m/d/yy") -> TTM TTM 6/1/26 | J64: Future State | K64: Increment
E65: Revenue
I66: 0 | J66: 0 | K66: =J66-I66 -> 0 | R66: =IF(K66=P66, "", "Error") | CC66: =SUMIFS($T66:$CA66, $T$1:$CA$1, CC$63) -> 0 | CD66: =SUMIFS($T66:$CA66, $T$1:$CA$1, CD$63) -> 0 | CE66: =SUMIFS($T66:$CA66, $T$1:$CA$1, CE$63) -> 0 | CF66: =SUMIFS($T66:$CA66, $T$1:$CA$1, CF$63) -> 0 | CG66: =SUMIFS($T66:$CA66, $T$1:$CA$1, CG$63) -> 0 | CI66: =CC66=L66 -> 1 | CJ66: =CD66=M66 -> 1 | CK66: =CE66=N66 -> 1 | CL66: =CF66=O66 -> 1 | CM66: =CG66=P66 -> 1
I67: 0 | J67: 0 | K67: =J67-I67 -> 0 | R67: =IF(K67=P67, "", "Error") | CC67: =SUMIFS($T67:$CA67, $T$1:$CA$1, CC$63) -> 0 | CD67: =SUMIFS($T67:$CA67, $T$1:$CA$1, CD$63) -> 0 | CE67: =SUMIFS($T67:$CA67, $T$1:$CA$1, CE$63) -> 0 | CF67: =SUMIFS($T67:$CA67, $T$1:$CA$1, CF$63) -> 0 | CG67: =SUMIFS($T67:$CA67, $T$1:$CA$1, CG$63) -> 0 | CI67: =CC67=L67 -> 1 | CJ67: =CD67=M67 -> 1 | CK67: =CE67=N67 -> 1 | CL67: =CF67=O67 -> 1 | CM67: =CG67=P67 -> 1
E68: Revenue Subtotal | I68: =SUM(I66:I67) -> 0 | J68: =SUM(J66:J67) -> 0 | K68: =SUM(K66:K67) -> 0 | L68: =SUM(L66:L67) -> 0 | M68: =SUM(M66:M67) -> 0 | N68: =SUM(N66:N67) -> 0 | O68: =SUM(O66:O67) -> 0 | P68: =SUM(P66:P67) -> 0 | T68: =SUM(T66:T67) -> 0 | U68: =SUM(U66:U67) -> 0 | V68: =SUM(V66:V67) -> 0 | W68: =SUM(W66:W67) -> 0 | X68: =SUM(X66:X67) -> 0 | Y68: =SUM(Y66:Y67) -> 0 | Z68: =SUM(Z66:Z67) -> 0 | AA68: =SUM(AA66:AA67) -> 0 | ... CA68: =SUM(CA66:CA67) -> 0 | CC68: =SUM(CC66:CC67) -> 0 | CD68: =SUM(CD66:CD67) -> 0 | CE68: =SUM(CE66:CE67) -> 0 | CF68: =SUM(CF66:CF67) -> 0 | CG68: =SUM(CG66:CG67) -> 0 | CI68: =CC68=L68 -> 1 | CJ68: =CD68=M68 -> 1 | CK68: =CE68=N68 -> 1 | CL68: =CF68=O68 -> 1 | CM68: =CG68=P68 -> 1
E70: Cost of Sales
K71: =I71-J71 -> 0 | R71: =IF(K71=P71, "", "Error") | CC71: =SUMIFS($T71:$CA71, $T$1:$CA$1, CC$63) -> 0 | CD71: =SUMIFS($T71:$CA71, $T$1:$CA$1, CD$63) -> 0 | CE71: =SUMIFS($T71:$CA71, $T$1:$CA$1, CE$63) -> 0 | CF71: =SUMIFS($T71:$CA71, $T$1:$CA$1, CF$63) -> 0 | CG71: =SUMIFS($T71:$CA71, $T$1:$CA$1, CG$63) -> 0 | CI71: =CC71=L71 -> 1 | CJ71: =CD71=M71 -> 1 | CK71: =CE71=N71 -> 1 | CL71: =CF71=O71 -> 1 | CM71: =CG71=P71 -> 1
I72: 0 | J72: 0 | K72: =I72-J72 -> 0 | R72: =IF(K72=P72, "", "Error") | CC72: =SUMIFS($T72:$CA72, $T$1:$CA$1, CC$63) -> 0 | CD72: =SUMIFS($T72:$CA72, $T$1:$CA$1, CD$63) -> 0 | CE72: =SUMIFS($T72:$CA72, $T$1:$CA$1, CE$63) -> 0 | CF72: =SUMIFS($T72:$CA72, $T$1:$CA$1, CF$63) -> 0 | CG72: =SUMIFS($T72:$CA72, $T$1:$CA$1, CG$63) -> 0 | CI72: =CC72=L72 -> 1 | CJ72: =CD72=M72 -> 1 | CK72: =CE72=N72 -> 1 | CL72: =CF72=O72 -> 1 | CM72: =CG72=P72 -> 1
I73: 0 | J73: 0 | K73: =I73-J73 -> 0 | R73: =IF(K73=P73, "", "Error") | CC73: =SUMIFS($T73:$CA73, $T$1:$CA$1, CC$63) -> 0 | CD73: =SUMIFS($T73:$CA73, $T$1:$CA$1, CD$63) -> 0 | CE73: =SUMIFS($T73:$CA73, $T$1:$CA$1, CE$63) -> 0 | CF73: =SUMIFS($T73:$CA73, $T$1:$CA$1, CF$63) -> 0 | CG73: =SUMIFS($T73:$CA73, $T$1:$CA$1, CG$63) -> 0 | CI73: =CC73=L73 -> 1 | CJ73: =CD73=M73 -> 1 | CK73: =CE73=N73 -> 1 | CL73: =CF73=O73 -> 1 | CM73: =CG73=P73 -> 1
I74: 0 | J74: 0 | K74: =I74-J74 -> 0 | R74: =IF(K74=P74, "", "Error") | CC74: =SUMIFS($T74:$CA74, $T$1:$CA$1, CC$63) -> 0 | CD74: =SUMIFS($T74:$CA74, $T$1:$CA$1, CD$63) -> 0 | CE74: =SUMIFS($T74:$CA74, $T$1:$CA$1, CE$63) -> 0 | CF74: =SUMIFS($T74:$CA74, $T$1:$CA$1, CF$63) -> 0 | CG74: =SUMIFS($T74:$CA74, $T$1:$CA$1, CG$63) -> 0 | CI74: =CC74=L74 -> 1 | CJ74: =CD74=M74 -> 1 | CK74: =CE74=N74 -> 1 | CL74: =CF74=O74 -> 1 | CM74: =CG74=P74 -> 1
K75: =I75-J75 -> 0 | R75: =IF(K75=P75, "", "Error") | CC75: =SUMIFS($T75:$CA75, $T$1:$CA$1, CC$63) -> 0 | CD75: =SUMIFS($T75:$CA75, $T$1:$CA$1, CD$63) -> 0 | CE75: =SUMIFS($T75:$CA75, $T$1:$CA$1, CE$63) -> 0 | CF75: =SUMIFS($T75:$CA75, $T$1:$CA$1, CF$63) -> 0 | CG75: =SUMIFS($T75:$CA75, $T$1:$CA$1, CG$63) -> 0 | CI75: =CC75=L75 -> 1 | CJ75: =CD75=M75 -> 1 | CK75: =CE75=N75 -> 1 | CL75: =CF75=O75 -> 1 | CM75: =CG75=P75 -> 1
E76: Cost of Sales Subtotal | I76: =SUM(I71:I75) -> 0 | J76: =SUM(J71:J75) -> 0 | K76: =SUM(K71:K75) -> 0 | L76: =SUM(L71:L75) -> 0 | M76: =SUM(M71:M75) -> 0 | N76: =SUM(N71:N75) -> 0 | O76: =SUM(O71:O75) -> 0 | P76: =SUM(P71:P75) -> 0 | T76: =SUM(T71:T75) -> 0 | U76: =SUM(U71:U75) -> 0 | V76: =SUM(V71:V75) -> 0 | W76: =SUM(W71:W75) -> 0 | X76: =SUM(X71:X75) -> 0 | Y76: =SUM(Y71:Y75) -> 0 | Z76: =SUM(Z71:Z75) -> 0 | AA76: =SUM(AA71:AA75) -> 0 | ... CA76: =SUM(CA71:CA75) -> 0 | CC76: =SUM(CC71:CC75) -> 0 | CD76: =SUM(CD71:CD75) -> 0 | CE76: =SUM(CE71:CE75) -> 0 | CF76: =SUM(CF71:CF75) -> 0 | CG76: =SUM(CG71:CG75) -> 0 | CI76: =CC76=L76 -> 1 | CJ76: =CD76=M76 -> 1 | CK76: =CE76=N76 -> 1 | CL76: =CF76=O76 -> 1 | CM76: =CG76=P76 -> 1
E78: OPEX
I79: =J21 -> 0 | J79: 0 | K79: =I79-J79 -> 0 | L79: 0 | M79: =$K79 -> 0 | N79: =$K79 -> 0 | O79: =$K79 -> 0 | P79: =$K79 -> 0 | R79: =IF(K79=P79, "", "Error") | T79: 0 | U79: 0 | V79: 0 | W79: 0 | X79: 0 | Y79: 0 | Z79: 0 | AA79: 0 | AB79: 0 | AC79: 0 | AD79: 0 | AE79: 0 | AF79: =$K$79/12 -> 0 | AG79: =$K$79/12 -> 0 | AH79: =$K$79/12 -> 0 | AI79: =$K$79/12 -> 0 | AJ79: =$K$79/12 -> 0 | AK79: =$K$79/12 -> 0 | AL79: =$K$79/12 -> 0 | AM79: =$K$79/12 -> 0 | ... BO79: =$K$79/12 -> 0 | CC79: =SUMIFS($T79:$CA79, $T$1:$CA$1, CC$63) -> 0 | CD79: =SUMIFS($T79:$CA79, $T$1:$CA$1, CD$63) -> 0 | CE79: =SUMIFS($T79:$CA79, $T$1:$CA$1, CE$63) -> 0 | CF79: =SUMIFS($T79:$CA79, $T$1:$CA$1, CF$63) -> 0 | CG79: =SUMIFS($T79:$CA79, $T$1:$CA$1, CG$63) -> 0 | CI79: =CC79=L79 -> 1 | CJ79: =CD79=M79 -> 1 | CK79: =CE79=N79 -> 1 | CL79: =CF79=O79 -> 1 | CM79: =CG79=P79 -> 1
I80: 0 | J80: 0 | K80: =I80-J80 -> 0 | R80: =IF(K80=P80, "", "Error") | CC80: =SUMIFS($T80:$CA80, $T$1:$CA$1, CC$63) -> 0 | CD80: =SUMIFS($T80:$CA80, $T$1:$CA$1, CD$63) -> 0 | CE80: =SUMIFS($T80:$CA80, $T$1:$CA$1, CE$63) -> 0 | CF80: =SUMIFS($T80:$CA80, $T$1:$CA$1, CF$63) -> 0 | CG80: =SUMIFS($T80:$CA80, $T$1:$CA$1, CG$63) -> 0 | CI80: =CC80=L80 -> 1 | CJ80: =CD80=M80 -> 1 | CK80: =CE80=N80 -> 1 | CL80: =CF80=O80 -> 1 | CM80: =CG80=P80 -> 1
I81: 0 | J81: 0 | K81: =I81-J81 -> 0 | R81: =IF(K81=P81, "", "Error") | CC81: =SUMIFS($T81:$CA81, $T$1:$CA$1, CC$63) -> 0 | CD81: =SUMIFS($T81:$CA81, $T$1:$CA$1, CD$63) -> 0 | CE81: =SUMIFS($T81:$CA81, $T$1:$CA$1, CE$63) -> 0 | CF81: =SUMIFS($T81:$CA81, $T$1:$CA$1, CF$63) -> 0 | CG81: =SUMIFS($T81:$CA81, $T$1:$CA$1, CG$63) -> 0 | CI81: =CC81=L81 -> 1 | CJ81: =CD81=M81 -> 1 | CK81: =CE81=N81 -> 1 | CL81: =CF81=O81 -> 1 | CM81: =CG81=P81 -> 1
I82: 0 | J82: 0 | K82: =I82-J82 -> 0 | R82: =IF(K82=P82, "", "Error") | CC82: =SUMIFS($T82:$CA82, $T$1:$CA$1, CC$63) -> 0 | CD82: =SUMIFS($T82:$CA82, $T$1:$CA$1, CD$63) -> 0 | CE82: =SUMIFS($T82:$CA82, $T$1:$CA$1, CE$63) -> 0 | CF82: =SUMIFS($T82:$CA82, $T$1:$CA$1, CF$63) -> 0 | CG82: =SUMIFS($T82:$CA82, $T$1:$CA$1, CG$63) -> 0 | CI82: =CC82=L82 -> 1 | CJ82: =CD82=M82 -> 1 | CK82: =CE82=N82 -> 1 | CL82: =CF82=O82 -> 1 | CM82: =CG82=P82 -> 1
I83: 0 | J83: 0 | K83: =I83-J83 -> 0 | R83: =IF(K83=P83, "", "Error") | CC83: =SUMIFS($T83:$CA83, $T$1:$CA$1, CC$63) -> 0 | CD83: =SUMIFS($T83:$CA83, $T$1:$CA$1, CD$63) -> 0 | CE83: =SUMIFS($T83:$CA83, $T$1:$CA$1, CE$63) -> 0 | CF83: =SUMIFS($T83:$CA83, $T$1:$CA$1, CF$63) -> 0 | CG83: =SUMIFS($T83:$CA83, $T$1:$CA$1, CG$63) -> 0 | CI83: =CC83=L83 -> 1 | CJ83: =CD83=M83 -> 1 | CK83: =CE83=N83 -> 1 | CL83: =CF83=O83 -> 1 | CM83: =CG83=P83 -> 1
E84: OpEx subtotal | I84: =SUM(I79:I83) -> 0 | J84: =SUM(J79:J83) -> 0 | K84: =SUM(K79:K83) -> 0 | L84: =SUM(L79:L83) -> 0 | M84: =SUM(M79:M83) -> 0 | N84: =SUM(N79:N83) -> 0 | O84: =SUM(O79:O83) -> 0 | P84: =SUM(P79:P83) -> 0 | T84: =SUM(T79:T83) -> 0 | U84: =SUM(U79:U83) -> 0 | V84: =SUM(V79:V83) -> 0 | W84: =SUM(W79:W83) -> 0 | X84: =SUM(X79:X83) -> 0 | Y84: =SUM(Y79:Y83) -> 0 | Z84: =SUM(Z79:Z83) -> 0 | AA84: =SUM(AA79:AA83) -> 0 | ... CA84: =SUM(CA79:CA83) -> 0 | CC84: =SUM(CC79:CC83) -> 0 | CD84: =SUM(CD79:CD83) -> 0 | CE84: =SUM(CE79:CE83) -> 0 | CF84: =SUM(CF79:CF83) -> 0 | CG84: =SUM(CG79:CG83) -> 0 | CI84: =CC84=L84 -> 1 | CJ84: =CD84=M84 -> 1 | CK84: =CE84=N84 -> 1 | CL84: =CF84=O84 -> 1 | CM84: =CG84=P84 -> 1
E88: Recurring Benefits Total | I88: =SUM(I68, I76, I84) -> 0 | J88: =SUM(J68, J76, J84) -> 0 | K88: =SUM(-K68, K76, K84) -> 0 | L88: =SUM(L68, L76, L84) -> 0 | M88: =SUM(M68, M76, M84) -> 0 | N88: =SUM(N68, N76, N84) -> 0 | O88: =SUM(O68, O76, O84) -> 0 | P88: =SUM(P68, P76, P84) -> 0 | T88: =SUM(T68, T76, T84) -> 0 | U88: =SUM(U68, U76, U84) -> 0 | V88: =SUM(V68, V76, V84) -> 0 | W88: =SUM(W68, W76, W84) -> 0 | X88: =SUM(X68, X76, X84) -> 0 | Y88: =SUM(Y68, Y76, Y84) -> 0 | Z88: =SUM(Z68, Z76, Z84) -> 0 | AA88: =SUM(AA68, AA76, AA84) -> 0 | ... CA88: =SUM(CA68, CA76, CA84) -> 0 | CC88: =SUM(CC68, CC76, CC84) -> 0 | CD88: =SUM(CD68, CD76, CD84) -> 0 | CE88: =SUM(CE68, CE76, CE84) -> 0 | CF88: =SUM(CF68, CF76, CF84) -> 0 | CG88: =SUM(CG68, CG76, CG84) -> 0 | CH88: =SUM(CH68, CH76, CH84) -> 0 | CI88: =CC88=L88 -> 1 | CJ88: =CD88=M88 -> 1 | CK88: =CE88=N88 -> 1 | CL88: =CF88=O88 -> 1 | CM88: =CG88=P88 -> 1
T90: 2026 | AF90: 2027 | AR90: 2028 | BD90: 2029 | BP90: 2030 | CI90: CHECK
D91: RECURRING COSTS TO ACHIEVE IMPACT | H91: Comment | I91: Baseline | J91: Goal | K91: Ann. Run Rate | L91: 2026 | M91: =L91+1 -> 2027 | N91: =M91+1 -> 2028 | O91: =N91+1 -> 2029 | P91: =O91+1 -> 2030 | Q91: Impacted BU | R91: Check | T91: 46023 | U91: =EOMONTH(T91, 1) -> 46081 | V91: =EOMONTH(U91, 1) -> 46112 | W91: =EOMONTH(V91, 1) -> 46142 | X91: =EOMONTH(W91, 1) -> 46173 | Y91: =EOMONTH(X91, 1) -> 46203 | Z91: =EOMONTH(Y91, 1) -> 46234 | AA91: =EOMONTH(Z91, 1) -> 46265 | AB91: =EOMONTH(AA91, 1) -> 46295 | ... CA91: =EOMONTH(BZ91, 1) -> 47848 | CC91: 2026 | CD91: =CC91+1 -> 2027 | CE91: =CD91+1 -> 2028 | CF91: =CE91+1 -> 2029 | CG91: =CF91+1 -> 2030 | CI91: 2026 | CJ91: =CI91+1 -> 2027 | CK91: =CJ91+1 -> 2028 | CL91: =CK91+1 -> 2029 | CM91: =CL91+1 -> 2030
E92: $USD M | I92: ="TTM "&TEXT($H$18,"m/d/yy") -> TTM TTM 6/1/26 | J92: Future State | K92: Increment
E93: Revenue
I94: 0 | J94: 0 | K94: =J94-I94 -> 0 | R94: =IF(K94=P94, "", "Error") | CC94: =SUMIFS($T94:$CA94, $T$1:$CA$1, CC$63) -> 0 | CD94: =SUMIFS($T94:$CA94, $T$1:$CA$1, CD$63) -> 0 | CE94: =SUMIFS($T94:$CA94, $T$1:$CA$1, CE$63) -> 0 | CF94: =SUMIFS($T94:$CA94, $T$1:$CA$1, CF$63) -> 0 | CG94: =SUMIFS($T94:$CA94, $T$1:$CA$1, CG$63) -> 0 | CI94: =CC94=L94 -> 1 | CJ94: =CD94=M94 -> 1 | CK94: =CE94=N94 -> 1 | CL94: =CF94=O94 -> 1 | CM94: =CG94=P94 -> 1
I95: 0 | J95: 0 | K95: =J95-I95 -> 0 | R95: =IF(K95=P95, "", "Error") | CC95: =SUMIFS($T95:$CA95, $T$1:$CA$1, CC$63) -> 0 | CD95: =SUMIFS($T95:$CA95, $T$1:$CA$1, CD$63) -> 0 | CE95: =SUMIFS($T95:$CA95, $T$1:$CA$1, CE$63) -> 0 | CF95: =SUMIFS($T95:$CA95, $T$1:$CA$1, CF$63) -> 0 | CG95: =SUMIFS($T95:$CA95, $T$1:$CA$1, CG$63) -> 0 | CI95: =CC95=L95 -> 1 | CJ95: =CD95=M95 -> 1 | CK95: =CE95=N95 -> 1 | CL95: =CF95=O95 -> 1 | CM95: =CG95=P95 -> 1
E96: Revenue Subtotal | I96: =SUM(I94:I95) -> 0 | J96: =SUM(J94:J95) -> 0 | K96: =SUM(K94:K95) -> 0 | L96: =SUM(L94:L95) -> 0 | M96: =SUM(M94:M95) -> 0 | N96: =SUM(N94:N95) -> 0 | O96: =SUM(O94:O95) -> 0 | P96: =SUM(P94:P95) -> 0 | T96: =SUM(T94:T95) -> 0 | U96: =SUM(U94:U95) -> 0 | V96: =SUM(V94:V95) -> 0 | W96: =SUM(W94:W95) -> 0 | X96: =SUM(X94:X95) -> 0 | Y96: =SUM(Y94:Y95) -> 0 | Z96: =SUM(Z94:Z95) -> 0 | AA96: =SUM(AA94:AA95) -> 0 | ... CA96: =SUM(CA94:CA95) -> 0 | CC96: =SUM(CC94:CC95) -> 0 | CD96: =SUM(CD94:CD95) -> 0 | CE96: =SUM(CE94:CE95) -> 0 | CF96: =SUM(CF94:CF95) -> 0 | CG96: =SUM(CG94:CG95) -> 0 | CI96: =CC96=L96 -> 1 | CJ96: =CD96=M96 -> 1 | CK96: =CE96=N96 -> 1 | CL96: =CF96=O96 -> 1 | CM96: =CG96=P96 -> 1
E98: Cost of Sales
I99: 0 | J99: 0 | K99: =J99-I99 -> 0 | L99: 0 | M99: 0 | N99: 0 | O99: 0 | P99: 0 | R99: =IF(K99=P99, "", "Error") | CC99: =SUMIFS($T99:$CA99, $T$1:$CA$1, CC$63) -> 0 | CD99: =SUMIFS($T99:$CA99, $T$1:$CA$1, CD$63) -> 0 | CE99: =SUMIFS($T99:$CA99, $T$1:$CA$1, CE$63) -> 0 | CF99: =SUMIFS($T99:$CA99, $T$1:$CA$1, CF$63) -> 0 | CG99: =SUMIFS($T99:$CA99, $T$1:$CA$1, CG$63) -> 0 | CI99: =CC99=L99 -> 1 | CJ99: =CD99=M99 -> 1 | CK99: =CE99=N99 -> 1 | CL99: =CF99=O99 -> 1 | CM99: =CG99=P99 -> 1
I100: 0 | J100: 0 | K100: =J100-I100 -> 0 | L100: 0 | M100: 0 | N100: 0 | O100: 0 | P100: 0 | R100: =IF(K100=P100, "", "Error") | CC100: =SUMIFS($T100:$CA100, $T$1:$CA$1, CC$63) -> 0 | CD100: =SUMIFS($T100:$CA100, $T$1:$CA$1, CD$63) -> 0 | CE100: =SUMIFS($T100:$CA100, $T$1:$CA$1, CE$63) -> 0 | CF100: =SUMIFS($T100:$CA100, $T$1:$CA$1, CF$63) -> 0 | CG100: =SUMIFS($T100:$CA100, $T$1:$CA$1, CG$63) -> 0 | CI100: =CC100=L100 -> 1 | CJ100: =CD100=M100 -> 1 | CK100: =CE100=N100 -> 1 | CL100: =CF100=O100 -> 1 | CM100: =CG100=P100 -> 1
I101: 0 | J101: 0 | K101: =J101-I101 -> 0 | L101: 0 | M101: 0 | N101: 0 | O101: 0 | P101: 0 | R101: =IF(K101=P101, "", "Error") | CC101: =SUMIFS($T101:$CA101, $T$1:$CA$1, CC$63) -> 0 | CD101: =SUMIFS($T101:$CA101, $T$1:$CA$1, CD$63) -> 0 | CE101: =SUMIFS($T101:$CA101, $T$1:$CA$1, CE$63) -> 0 | CF101: =SUMIFS($T101:$CA101, $T$1:$CA$1, CF$63) -> 0 | CG101: =SUMIFS($T101:$CA101, $T$1:$CA$1, CG$63) -> 0 | CI101: =CC101=L101 -> 1 | CJ101: =CD101=M101 -> 1 | CK101: =CE101=N101 -> 1 | CL101: =CF101=O101 -> 1 | CM101: =CG101=P101 -> 1
I102: 0 | J102: 0 | K102: =J102-I102 -> 0 | L102: 0 | M102: 0 | N102: 0 | O102: 0 | P102: 0 | R102: =IF(K102=P102, "", "Error") | CC102: =SUMIFS($T102:$CA102, $T$1:$CA$1, CC$63) -> 0 | CD102: =SUMIFS($T102:$CA102, $T$1:$CA$1, CD$63) -> 0 | CE102: =SUMIFS($T102:$CA102, $T$1:$CA$1, CE$63) -> 0 | CF102: =SUMIFS($T102:$CA102, $T$1:$CA$1, CF$63) -> 0 | CG102: =SUMIFS($T102:$CA102, $T$1:$CA$1, CG$63) -> 0 | CI102: =CC102=L102 -> 1 | CJ102: =CD102=M102 -> 1 | CK102: =CE102=N102 -> 1 | CL102: =CF102=O102 -> 1 | CM102: =CG102=P102 -> 1
K103: =J103-I103 -> 0 | L103: 0 | M103: 0 | N103: 0 | O103: 0 | P103: 0
E104: Cost of Sales Subtotal | I104: =SUM(I99:I103) -> 0 | J104: =SUM(J99:J103) -> 0 | K104: =SUM(K99:K103) -> 0 | L104: =SUM(L99:L103) -> 0 | M104: =SUM(M99:M103) -> 0 | N104: =SUM(N99:N103) -> 0 | O104: =SUM(O99:O103) -> 0 | P104: =SUM(P99:P103) -> 0 | T104: =SUM(T99:T103) -> 0 | U104: =SUM(U99:U103) -> 0 | V104: =SUM(V99:V103) -> 0 | W104: =SUM(W99:W103) -> 0 | X104: =SUM(X99:X103) -> 0 | Y104: =SUM(Y99:Y103) -> 0 | Z104: =SUM(Z99:Z103) -> 0 | AA104: =SUM(AA99:AA103) -> 0 | ... CA104: =SUM(CA99:CA103) -> 0 | CC104: =SUM(CC99:CC103) -> 0 | CD104: =SUM(CD99:CD103) -> 0 | CE104: =SUM(CE99:CE103) -> 0 | CF104: =SUM(CF99:CF103) -> 0 | CG104: =SUM(CG99:CG103) -> 0 | CI104: =CC104=L104 -> 1 | CJ104: =CD104=M104 -> 1 | CK104: =CE104=N104 -> 1 | CL104: =CF104=O104 -> 1 | CM104: =CG104=P104 -> 1
E106: OPEX
I107: 0 | J107: =J26 -> 0 | K107: =J107-I107 -> 0 | L107: 0 | M107: =$K107 -> 0 | N107: =$K107 -> 0 | O107: =$K107 -> 0 | P107: =$K107 -> 0 | R107: =IF(K107=P107, "", "Error") | AF107: =$K$107/12 -> 0 | AG107: =$K$107/12 -> 0 | AH107: =$K$107/12 -> 0 | AI107: =$K$107/12 -> 0 | AJ107: =$K$107/12 -> 0 | AK107: =$K$107/12 -> 0 | AL107: =$K$107/12 -> 0 | AM107: =$K$107/12 -> 0 | ... CA107: =$K$107/12 -> 0 | CC107: =SUMIFS($T107:$CA107, $T$1:$CA$1, CC$63) -> 0 | CD107: =SUMIFS($T107:$CA107, $T$1:$CA$1, CD$63) -> 0 | CE107: =SUMIFS($T107:$CA107, $T$1:$CA$1, CE$63) -> 0 | CF107: =SUMIFS($T107:$CA107, $T$1:$CA$1, CF$63) -> 0 | CG107: =SUMIFS($T107:$CA107, $T$1:$CA$1, CG$63) -> 0 | CI107: =CC107=L107 -> 1 | CJ107: =CD107=M107 -> 1 | CK107: =CE107=N107 -> 1 | CL107: =CF107=O107 -> 1 | CM107: =CG107=P107 -> 1
I108: 0 | J108: 0 | K108: =J108-I108 -> 0 | L108: 0 | M108: 0 | N108: 0 | O108: 0 | P108: 0 | R108: =IF(K108=P108, "", "Error") | CC108: =SUMIFS($T108:$CA108, $T$1:$CA$1, CC$63) -> 0 | CD108: =SUMIFS($T108:$CA108, $T$1:$CA$1, CD$63) -> 0 | CE108: =SUMIFS($T108:$CA108, $T$1:$CA$1, CE$63) -> 0 | CF108: =SUMIFS($T108:$CA108, $T$1:$CA$1, CF$63) -> 0 | CG108: =SUMIFS($T108:$CA108, $T$1:$CA$1, CG$63) -> 0 | CI108: =CC108=L108 -> 1 | CJ108: =CD108=M108 -> 1 | CK108: =CE108=N108 -> 1 | CL108: =CF108=O108 -> 1 | CM108: =CG108=P108 -> 1
I109: 0 | J109: 0 | K109: =J109-I109 -> 0 | L109: 0 | M109: 0 | N109: 0 | O109: 0 | P109: 0 | R109: =IF(K109=P109, "", "Error") | CC109: =SUMIFS($T109:$CA109, $T$1:$CA$1, CC$63) -> 0 | CD109: =SUMIFS($T109:$CA109, $T$1:$CA$1, CD$63) -> 0 | CE109: =SUMIFS($T109:$CA109, $T$1:$CA$1, CE$63) -> 0 | CF109: =SUMIFS($T109:$CA109, $T$1:$CA$1, CF$63) -> 0 | CG109: =SUMIFS($T109:$CA109, $T$1:$CA$1, CG$63) -> 0 | CI109: =CC109=L109 -> 1 | CJ109: =CD109=M109 -> 1 | CK109: =CE109=N109 -> 1 | CL109: =CF109=O109 -> 1 | CM109: =CG109=P109 -> 1
I110: 0 | J110: 0 | K110: =J110-I110 -> 0 | L110: 0 | M110: 0 | N110: 0 | O110: 0 | P110: 0 | R110: =IF(K110=P110, "", "Error") | CC110: =SUMIFS($T110:$CA110, $T$1:$CA$1, CC$63) -> 0 | CD110: =SUMIFS($T110:$CA110, $T$1:$CA$1, CD$63) -> 0 | CE110: =SUMIFS($T110:$CA110, $T$1:$CA$1, CE$63) -> 0 | CF110: =SUMIFS($T110:$CA110, $T$1:$CA$1, CF$63) -> 0 | CG110: =SUMIFS($T110:$CA110, $T$1:$CA$1, CG$63) -> 0 | CI110: =CC110=L110 -> 1 | CJ110: =CD110=M110 -> 1 | CK110: =CE110=N110 -> 1 | CL110: =CF110=O110 -> 1 | CM110: =CG110=P110 -> 1
I111: 0 | J111: 0 | K111: =J111-I111 -> 0 | L111: 0 | M111: 0 | N111: 0 | O111: 0 | P111: 0 | R111: =IF(K111=P111, "", "Error") | CC111: =SUMIFS($T111:$CA111, $T$1:$CA$1, CC$63) -> 0 | CD111: =SUMIFS($T111:$CA111, $T$1:$CA$1, CD$63) -> 0 | CE111: =SUMIFS($T111:$CA111, $T$1:$CA$1, CE$63) -> 0 | CF111: =SUMIFS($T111:$CA111, $T$1:$CA$1, CF$63) -> 0 | CG111: =SUMIFS($T111:$CA111, $T$1:$CA$1, CG$63) -> 0 | CI111: =CC111=L111 -> 1 | CJ111: =CD111=M111 -> 1 | CK111: =CE111=N111 -> 1 | CL111: =CF111=O111 -> 1 | CM111: =CG111=P111 -> 1
E112: OpEx subtotal | I112: =SUM(I107:I111) -> 0 | J112: =SUM(J107:J111) -> 0 | K112: =SUM(K107:K111) -> 0 | L112: =SUM(L107:L111) -> 0 | M112: =SUM(M107:M111) -> 0 | N112: =SUM(N107:N111) -> 0 | O112: =SUM(O107:O111) -> 0 | P112: =SUM(P107:P111) -> 0 | T112: =SUM(T107:T111) -> 0 | U112: =SUM(U107:U111) -> 0 | V112: =SUM(V107:V111) -> 0 | W112: =SUM(W107:W111) -> 0 | X112: =SUM(X107:X111) -> 0 | Y112: =SUM(Y107:Y111) -> 0 | Z112: =SUM(Z107:Z111) -> 0 | AA112: =SUM(AA107:AA111) -> 0 | ... CA112: =SUM(CA107:CA111) -> 0 | CC112: =SUM(CC107:CC111) -> 0 | CD112: =SUM(CD107:CD111) -> 0 | CE112: =SUM(CE107:CE111) -> 0 | CF112: =SUM(CF107:CF111) -> 0 | CG112: =SUM(CG107:CG111) -> 0 | CI112: =CC112=L112 -> 1 | CJ112: =CD112=M112 -> 1 | CK112: =CE112=N112 -> 1 | CL112: =CF112=O112 -> 1 | CM112: =CG112=P112 -> 1
E115: Recurring Costs Total | I115: =SUM(-I96, I104, I112) -> 0 | J115: =SUM(-J96, J104, J112) -> 0 | K115: =SUM(-K96, K104, K112) -> 0 | L115: =SUM(-L96, L104, L112) -> 0 | M115: =SUM(-M96, M104, M112) -> 0 | N115: =SUM(-N96, N104, N112) -> 0 | O115: =SUM(-O96, O104, O112) -> 0 | P115: =SUM(-P96, P104, P112) -> 0 | T115: =SUM(-T96, T104, T112) -> 0 | U115: =SUM(-U96, U104, U112) -> 0 | V115: =SUM(-V96, V104, V112) -> 0 | W115: =SUM(-W96, W104, W112) -> 0 | X115: =SUM(-X96, X104, X112) -> 0 | Y115: =SUM(-Y96, Y104, Y112) -> 0 | Z115: =SUM(-Z96, Z104, Z112) -> 0 | AA115: =SUM(-AA96, AA104, AA112) -> 0 | ... CA115: =SUM(-CA96, CA104, CA112) -> 0 | CC115: =SUM(-CC96, CC104, CC112) -> 0 | CD115: =SUM(-CD96, CD104, CD112) -> 0 | CE115: =SUM(-CE96, CE104, CE112) -> 0 | CF115: =SUM(-CF96, CF104, CF112) -> 0 | CG115: =SUM(-CG96, CG104, CG112) -> 0 | CI115: =CC115=L115 -> 1 | CJ115: =CD115=M115 -> 1 | CK115: =CE115=N115 -> 1 | CL115: =CF115=O115 -> 1 | CM115: =CG115=P115 -> 1
E117: Net Recurring Benefit | I117: =SUM(I88, -I115) -> 0 | J117: =SUM(J88, -J115) -> 0 | K117: =SUM(K88, -K115) -> 0 | L117: =SUM(L88, -L115) -> 0 | M117: =SUM(M88, -M115) -> 0 | N117: =SUM(N88, -N115) -> 0 | O117: =SUM(O88, -O115) -> 0 | P117: =SUM(P88, -P115) -> 0 | R117: =IF(K117=P117, "", "Error") | T117: =SUM(T88, -T115) -> 0 | U117: =SUM(U88, -U115) -> 0 | V117: =SUM(V88, -V115) -> 0 | W117: =SUM(W88, -W115) -> 0 | X117: =SUM(X88, -X115) -> 0 | Y117: =SUM(Y88, -Y115) -> 0 | Z117: =SUM(Z88, -Z115) -> 0 | AA117: =SUM(AA88, -AA115) -> 0 | ... CA117: =SUM(CA88, -CA115) -> 0 | CC117: =SUM(CC88, -CC115) -> 0 | CD117: =SUM(CD88, -CD115) -> 0 | CE117: =SUM(CE88, -CE115) -> 0 | CF117: =SUM(CF88, -CF115) -> 0 | CG117: =SUM(CG88, -CG115) -> 0 | CI117: =CC117=L117 -> 1 | CJ117: =CD117=M117 -> 1 | CK117: =CE117=N117 -> 1 | CL117: =CF117=O117 -> 1 | CM117: =CG117=P117 -> 1
C120: SECTION III - ONE-TIME IMPLEMENTATION | CC120: ANNUAL SUMMARY | CI120: CHECK CELLS
T122: 2026 | AF122: 2027 | AR122: 2028 | BD122: 2029 | BP122: 2030
D123: ONE-TIME BENEFITS | K123: Comment | L123: 2026 | M123: =L123+1 -> 2027 | N123: =M123+1 -> 2028 | O123: =N123+1 -> 2029 | P123: =O123+1 -> 2030 | Q123: Impacted BU | T123: 46023 | U123: =EOMONTH(T123, 1) -> 46081 | V123: =EOMONTH(U123, 1) -> 46112 | W123: =EOMONTH(V123, 1) -> 46142 | X123: =EOMONTH(W123, 1) -> 46173 | Y123: =EOMONTH(X123, 1) -> 46203 | Z123: =EOMONTH(Y123, 1) -> 46234 | AA123: =EOMONTH(Z123, 1) -> 46265 | AB123: =EOMONTH(AA123, 1) -> 46295 | ... CA123: =EOMONTH(BZ123, 1) -> 47848 | CC123: 2026 | CD123: =CC123+1 -> 2027 | CE123: =CD123+1 -> 2028 | CF123: =CE123+1 -> 2029 | CG123: =CF123+1 -> 2030 | CI123: 2026 | CJ123: =CI123+1 -> 2027 | CK123: =CJ123+1 -> 2028 | CL123: =CK123+1 -> 2029 | CM123: =CL123+1 -> 2030
E125: Working Capital
CC126: =SUMIFS($T126:$CA126, $T$1:$CA$1, CC$63) -> 0 | CD126: =SUMIFS($T126:$CA126, $T$1:$CA$1, CD$63) -> 0 | CE126: =SUMIFS($T126:$CA126, $T$1:$CA$1, CE$63) -> 0 | CF126: =SUMIFS($T126:$CA126, $T$1:$CA$1, CF$63) -> 0 | CG126: =SUMIFS($T126:$CA126, $T$1:$CA$1, CG$63) -> 0 | CI126: =CC126=L126 -> 1 | CJ126: =CD126=M126 -> 1 | CK126: =CE126=N126 -> 1 | CL126: =CF126=O126 -> 1 | CM126: =CG126=P126 -> 1
CC127: =SUMIFS($T127:$CA127, $T$1:$CA$1, CC$63) -> 0 | CD127: =SUMIFS($T127:$CA127, $T$1:$CA$1, CD$63) -> 0 | CE127: =SUMIFS($T127:$CA127, $T$1:$CA$1, CE$63) -> 0 | CF127: =SUMIFS($T127:$CA127, $T$1:$CA$1, CF$63) -> 0 | CG127: =SUMIFS($T127:$CA127, $T$1:$CA$1, CG$63) -> 0 | CI127: =CC127=L127 -> 1 | CJ127: =CD127=M127 -> 1 | CK127: =CE127=N127 -> 1 | CL127: =CF127=O127 -> 1 | CM127: =CG127=P127 -> 1
E128: Working Capital Subtotal | L128: =SUM(L126:L127) -> 0 | M128: =SUM(M126:M127) -> 0 | N128: =SUM(N126:N127) -> 0 | O128: =SUM(O126:O127) -> 0 | P128: =SUM(P126:P127) -> 0 | T128: =SUM(T126:T127) -> 0 | U128: =SUM(U126:U127) -> 0 | V128: =SUM(V126:V127) -> 0 | W128: =SUM(W126:W127) -> 0 | X128: =SUM(X126:X127) -> 0 | Y128: =SUM(Y126:Y127) -> 0 | Z128: =SUM(Z126:Z127) -> 0 | AA128: =SUM(AA126:AA127) -> 0 | ... CA128: =SUM(CA126:CA127) -> 0 | CC128: =SUM(CC126:CC127) -> 0 | CD128: =SUM(CD126:CD127) -> 0 | CE128: =SUM(CE126:CE127) -> 0 | CF128: =SUM(CF126:CF127) -> 0 | CG128: =SUM(CG126:CG127) -> 0 | CI128: =CC128=L128 -> 1 | CJ128: =CD128=M128 -> 1 | CK128: =CE128=N128 -> 1 | CL128: =CF128=O128 -> 1 | CM128: =CG128=P128 -> 1
E130: One-Time Benefits Total | L130: =L128 -> 0 | M130: =M128 -> 0 | N130: =N128 -> 0 | O130: =O128 -> 0 | P130: =P128 -> 0 | T130: =T128 -> 0 | U130: =U128 -> 0 | V130: =V128 -> 0 | W130: =W128 -> 0 | X130: =X128 -> 0 | Y130: =Y128 -> 0 | Z130: =Z128 -> 0 | AA130: =AA128 -> 0 | ... CA130: =CA128 -> 0 | CC130: =CC128 -> 0 | CD130: =CD128 -> 0 | CE130: =CE128 -> 0 | CF130: =CF128 -> 0 | CG130: =CG128 -> 0 | CI130: =CI128 -> 1 | CJ130: =CJ128 -> 1 | CK130: =CK128 -> 1 | CL130: =CL128 -> 1 | CM130: =CM128 -> 1
T132: 2026 | AF132: 2027 | AR132: 2028 | BD132: 2029 | BP132: 2030
D133: CAPEX AND ONE-TIME COSTS | K133: Comment | L133: 2026 | M133: =L133+1 -> 2027 | N133: =M133+1 -> 2028 | O133: =N133+1 -> 2029 | P133: =O133+1 -> 2030 | T133: 46023 | U133: =EOMONTH(T133, 1) -> 46081 | V133: =EOMONTH(U133, 1) -> 46112 | W133: =EOMONTH(V133, 1) -> 46142 | X133: =EOMONTH(W133, 1) -> 46173 | Y133: =EOMONTH(X133, 1) -> 46203 | Z133: =EOMONTH(Y133, 1) -> 46234 | AA133: =EOMONTH(Z133, 1) -> 46265 | AB133: =EOMONTH(AA133, 1) -> 46295 | ... CA133: =EOMONTH(BZ133, 1) -> 47848 | CC133: 2026 | CD133: =CC133+1 -> 2027 | CE133: =CD133+1 -> 2028 | CF133: =CE133+1 -> 2029 | CG133: =CF133+1 -> 2030 | CI133: 2026 | CJ133: =CI133+1 -> 2027 | CK133: =CJ133+1 -> 2028 | CL133: =CK133+1 -> 2029 | CM133: =CL133+1 -> 2030
E135: Capital Expenditures
...
