Workbook

Sheet Cover
B2: PROJECT ZENITH — SERVICING WORKSTREAM | INITIATIVE MODELS & WAVE TEMPLATES
B4: Workstream | C4: Servicing — Improve NPS and eliminate avoidable contacts through Prevent, Self-Serve and Optimize. ELT sponsor: Aaron | WSL: Tahira Adatia | IOs: Jackie Yu, Matt Anderson, Bob Hurst.
B5: Purpose | C5: One file per workstream: the six S2 initiatives, each with a Model sheet (distilled from the S2 sizing model, tier-level) formula-linked into its own copy of the standard WAVE template. S2 submission: Fri 4 Sep 2026.
B6: Version / status | C6: v1 — seeded 1:1 from the S2 sizing model vDraft5 (Base scenario, 28 Aug 2026). All initiative benefits, one-time and run costs tie to S2 to the cent at seed values (see tie-out targets on each model sheet).
B7: Prepared | C7: Prepared by AAO model build, 31 Aug 2026. Sources: 20260828_Servicing_S2sizing_vDraft5.xlsb; Project Zenith workplan vS_1; Zenith Business Case Template by Lever (WAVE).
B8: Sources | C8: S2 sizing model vDraft5 (77-intent L2 engine, A0–A6 waterfall, C1–C3 investment); distillation is at difficulty-tier level with per-tier bases and effective rates reproducing the L2 engine exactly at seed values.
B10: HOW THIS FILE IS ORGANIZED
B12: Cover | C12: This sheet — orientation, legend, deviations, open items.
B13: Instructions | C13: The WAVE template's own instruction sheet (as uploaded; dead broken-reference drop-down cells cleared).
B14: Rate Card | C14: Shared people-cost engine — S2 8-FTE pod at $200k/yr blended (ties to S2 C2); contingency reference; capitalization policy (0% = S2 cash treatment).
B15: Summary | C15: Portfolio roll-up of all six initiatives (links to WAVE sheets).
B16: SVC-1 Model / WAVE | C16: Contact Avoidance (S2 lever A1) — $12.84M.
B17: SVC-2 Model / WAVE | C17: Enhanced Chat / Self-Serve (A2) — $14.77M.
B18: SVC-3 Model / WAVE | C18: Agentic Voice & AI Co-pilot (A3a + A3b) — $35.25M.
B19: SVC-4 Model / WAVE | C19: AI Workforce Management (A4a + A4b) — $7.65M.
B20: SVC-5 Model / WAVE | C20: Back-Office Automation (A5) — $6.83M.
B21: SVC-6 Model / WAVE | C21: Non-FTE Savings flow-through (A6) — $4.04M; FTE inputs link to the other five models.
B22: Standard Template | C22: Reference copy of the standard WAVE template (only error-guard fixes applied — see deviations).
B24: COLOR LEGEND
B26: Input — change freely
B27: Formula — do not overwrite
B28: Link to another sheet
B29: Section band
B31: MODEL -> WAVE LINKING
B33: • Each initiative has a '<code> Model' sheet (all logic and inputs) and a '<code> WAVE' sheet (the standard template). The WAVE sheet contains NO hardcoded numbers for this initiative — its benefit/cost rows link (green) to the Model sheet's feed rows in $M.
B34: • Model sheets use the same time grid as WAVE: columns L:P = FY2026–2030 annual, columns T:CA = Jan-2026..Dec-2030 monthly. Annual cells are SUMIFS of the monthly grid, so the WAVE monthly-vs-annual checks (CI1:CM1) pass by construction.
B35: • The 'Ann. Run Rate' (K) on feed rows is defined as the 2030 value, matching the WAVE rule 'Annualized Run Rate (K) = 2030 Value (P)'. Keep ramps reaching 100% before 2030.
B36: • Benefits ramp linearly from the go-live date over 'months to full run rate' — same convention as the Servicing S2 model. One-time costs spread evenly over each milestone's billing months.
B37: • People costs: milestone labor = Team size x Billing months x blended monthly rate (Rate Card) x (1 + contingency). Capitalization: each milestone carries a Cap % (default from Rate Card policy) that splits labor into WAVE CapEx vs OTC rows. Same for non-labor one-time items.
B38: • Waterfall de-duplication: each model's opening cost is the prior lever's closing baseline (S2 stacking order). Openings are seeded inputs — refresh from the S2 L2 engine if upstream levers or intent tiering change (tier-level bases cannot re-derive themselves).
... B57: • FTE-impacted figures use the S2 'A0 basis' (as consumed by the non-FTE flow-through); residual-basis reductions are lower (S2 QC flag) — do not mix bases when quoting headcount.

Sheet Instructions
L1: 1 | M1: 2 | N1: 3 | O1: 4 | P1: 5 | R1: =COUNTIFS($R$78:$R$128, "Error") -> 0 | T1: 2026 | U1: 2026 | V1: 2026 | W1: 2026 | X1: 2026 | Y1: 2026 | Z1: 2026 | AA1: 2026 | AB1: 2026 | AC1: 2026 | AD1: 2026 | AE1: 2026 | AF1: 2027 | AG1: 2027 | AH1: 2027 | AI1: 2027 | AJ1: 2027 | AK1: 2027 | AL1: 2027 | AM1: 2027 | AN1: 2027 | AO1: 2027 | AP1: 2027 | AQ1: 2027 | AR1: 2028 | AS1: 2028 | AT1: 2028 | AU1: 2028 | AV1: 2028 | AW1: 2028 | AX1: 2028 | AY1: 2028 | AZ1: 2028 | BA1: 2028 | BB1: 2028 | BC1: 2028 | BD1: 2029 | BE1: 2029 | BF1: 2029 | BG1: 2029 | BH1: 2029 | BI1: 2029 | BJ1: 2029 | BK1: 2029 | BL1: 2029 | BM1: 2029 | BN1: 2029 | BO1: 2029 | BP1: 2030 | BQ1: 2030 | BR1: 2030 | BS1: 2030 | BT1: 2030 | BU1: 2030 | BV1: 2030 | BW1: 2030 | BX1: 2030 | BY1: 2030 | BZ1: 2030 | CA1: 2030 | CI1: =COUNTIFS(CI$78:CI$159, "FALSE") -> 0 | CJ1: =COUNTIFS(CJ$78:CJ$159, "FALSE") -> 4 | CK1: =COUNTIFS(CK$78:CK$159, "FALSE") -> 4 | CL1: =COUNTIFS(CL$78:CL$159, "FALSE") -> 0 | CM1: =COUNTIFS(CM$78:CM$159, "FALSE") -> 0
C9: ="#"&$F$13&" Initiative Business Case" -> #123456 Initiative Business Case
C11: INPUTS & ASSUMPTIONS
D13: Initiative # | F13: 123456
D14: Initiative Owner | F14: John Smith
D15: Initiative Name | F15: Leverage agentic AI for customer service and care centers, reducing number of calls handled by live customer care agents and increasing productivity | I15: Names - 5-7 words
I16: Descriptions - 10-20 words
D18: Estimated L4 date | F18: 46736
D19: Net Recurring Benefit ($M) | F19: =$K$128 -> 7.2
C21: SECTION I - PRIMARY VALUE DRIVER (ILLUSTRATIVE) | L21: CHECKS
D23: Illustrative example of value driver explanation - please edit fields to reflect value drivers for your Initiative | L23: Criteria (Column Reference) | P23: Check | Q23: Troubleshoot:
D24: Baseline | H24: Period | I24: KPI | J24: Inputs | L24: (A) Annualized Run Rate (K) = 2030 Value (P) | P24: =IF($R$1=0, "PASS", "ERROR") -> PASS | Q24: =IF(P24="Error", "Check column R for errors", "")
E25: # of calls handled by live agents | G25: [A] | H25: FY2025 | I25: # of calls | J25: 6000 | L25: (B) 2026 Value (L) = Sum of Monthly 2026 Values (CC) | P25: =IF($CI$1=0, "PASS", "ERROR") -> PASS | Q25: =IF(P25="Error", "Check column CI for errors", "")
E26: AHT | G26: [B] | H26: FY 2026 | I26: Seconds | J26: 150 | L26: (C) 2027 Value (M) = Sum of Monthly 2027 Values (CD) | P26: =IF($CJ$1=0, "PASS", "ERROR") -> ERROR | Q26: =IF(P26="Error", "Check column CJ for errors", "") -> Check column CJ for errors
E27: # of live agents handling calls | G27: [C] | H27: FY 2025 | I27: # of live agents | J27: 500 | L27: (D) 2028 Value (N) = Sum of Monthly 2028 Values (CE) | P27: =IF($CK$1=0, "PASS", "ERROR") -> ERROR | Q27: =IF(P27="Error", "Check column CK for errors", "") -> Check column CK for errors
E28: Average cost per agent | H28: FY 2026 | I28: $ / agent | J28: 50000 | L28: (E) 2029 Value (O) = Sum of Monthly 2029 Values (CF) | P28: =IF($CL$1=0, "PASS", "ERROR") -> PASS | Q28: =IF(P28="Error", "Check column CL for errors", "")
E29: Total spend on contact center for queue X | G29: [D] | H29: FY2025 | I29: $USD M | J29: =(J27*J28)/1000000 -> 25 | L29: (F) 2030 Value (P) = Sum of Monthly 2030 Values (CG) | P29: =IF($CM$1=0, "PASS", "ERROR") -> PASS | Q29: =IF(P29="Error", "Check column CM for errors", "")
D31: Goal | Y31: D
E32: # of calls handled by live agents | G32: [E] | I32: # of calls | J32: 4000
E33: AHT | G33: [F] | I33: Seconds | J33: 120
E34: # of live agents handling calls | G34: [G] | I34: # of live agents | J34: 260
E35: Average cost per agent | I35: $ / agent | J35: =J28 -> 50000
E36: Total spend on contact center for queue X | G36: [H] | H36: FY2026 | I36: $USD M | J36: =(J34*J35)/1000000 -> 13
D38: Incremental Improvement
E39: # of calls handled by live agents | G39: [A]-[E] | I39: # of calls | J39: =J25-J32 -> 2000
E40: AHT | G40: [B]-[F] | I40: Seconds | J40: =J26-J33 -> 30
E41: # of live agents handling calls | G41: [C]-[G] | I41: # of live agents | J41: =J27-J34 -> 240
E42: Total spend on contact center queue X | G42: [D]-[H] | I42: USD M | J42: =J29-J36 -> 12
D43: Baseline | H43: Period | I43: $USD M | J43: Inputs
E44: # xxxx | H44: FY2025 | I44: # xxxx | J44: 12000000
E45: xxxx unit cost | G45: [A] | H45: FY2025 | I45: $ xxxx | J45: 0.14
E46: xxxx total spend | G46: [B] | H46: FY2025 | I46: $USD K | J46: =(J44*J45)/1000 -> 1680
D48: Goal
E49: # xxxx | H49: FY2025 | I49: # xxxx | J49: =$J$25 -> 6000
E50: xxxx unit cost | G50: [C] | H50: FY2026 | I50: $ xxxx | J50: 0.1
E51: xxxx total spend | G51: [D] | H51: FY2026 | I51: $USD K | J51: =(J49*J50)/1000 -> 0.6
D53: Incremental Improvement
E54: =E50 -> xxxx unit cost | G54: [A]-[C] | I54: $ / xxxx | J54: =J45-J50 -> 0.04
E55: =E51 -> xxxx total spend | G55: [B]-[D] | I55: $USD K | J55: =J46-J51 -> 1679.4
D58: Baseline | H58: Period | I58: KPI | J58: Inputs
E59: # xxxx | H59: FY2025 | I59: # xxxx | J59: 12000000
E60: xxxx unit cost | G60: [A] | H60: FY2025 | I60: $ xxxx | J60: 0.14
E61: xxxx total spend | G61: [B] | H61: FY2025 | I61: $USD K | J61: =(J59*J60)/1000 -> 1680
D63: Goal
E64: # xxxx | H64: FY2025 | I64: # xxxx | J64: =$J$25 -> 6000
E65: xxxx unit cost | G65: [C] | H65: FY2026 | I65: $ xxxx | J65: 0.1
E66: xxxx total spend | G66: [D] | H66: FY2026 | I66: $USD K | J66: =(J64*J65)/1000 -> 0.6
D68: Incremental Improvement
E69: =E65 -> xxxx unit cost | G69: [A]-[C] | I69: $ / xxxx | J69: =J60-J65 -> 0.04
E70: =E66 -> xxxx total spend | G70: [B]-[D] | I70: $USD K | J70: =J61-J66 -> 1679.4
C73: SECTION II - NET RECURRING BENEFITS | CC73: ANNUAL SUMMARY | CI73: CHECK CELLS
D75: RECURRING BENEFITS | H75: Comment | I75: Baseline | J75: Goal | K75: Ann. Run Rate | L75: 2026 | M75: =L75+1 -> 2027 | N75: =M75+1 -> 2028 | O75: =N75+1 -> 2029 | P75: =O75+1 -> 2030 | Q75: Impacted BU | R75: Check | T75: 46023 | U75: =EOMONTH(T75, 1) -> 46081 | V75: =EOMONTH(U75, 1) -> 46112 | W75: =EOMONTH(V75, 1) -> 46142 | X75: =EOMONTH(W75, 1) -> 46173 | Y75: =EOMONTH(X75, 1) -> 46203 | Z75: =EOMONTH(Y75, 1) -> 46234 | AA75: =EOMONTH(Z75, 1) -> 46265 | AB75: =EOMONTH(AA75, 1) -> 46295 | ... CA75: =EOMONTH(BZ75, 1) -> 47848 | CC75: 2026 | CD75: =CC75+1 -> 2027 | CE75: =CD75+1 -> 2028 | CF75: =CE75+1 -> 2029 | CG75: =CF75+1 -> 2030 | CI75: 2026 | CJ75: =CI75+1 -> 2027 | CK75: =CJ75+1 -> 2028 | CL75: =CK75+1 -> 2029 | CM75: =CL75+1 -> 2030
E76: $USD M | I76: FY25 Hist. | J76: Future State | K76: Increment
E77: Revenue
I78: 0 | J78: 0 | K78: =J78-I78 -> 0 | R78: =IF(K78=P78, "", "Error") | CC78: =SUMIFS($T78:$CA78, $T$1:$CA$1, CC$75) -> 0 | CD78: =SUMIFS($T78:$CA78, $T$1:$CA$1, CD$75) -> 0 | CE78: =SUMIFS($T78:$CA78, $T$1:$CA$1, CE$75) -> 0 | CF78: =SUMIFS($T78:$CA78, $T$1:$CA$1, CF$75) -> 0 | CG78: =SUMIFS($T78:$CA78, $T$1:$CA$1, CG$75) -> 0 | CI78: =CC78=L78 -> 1 | CJ78: =CD78=M78 -> 1 | CK78: =CE78=N78 -> 1 | CL78: =CF78=O78 -> 1 | CM78: =CG78=P78 -> 1
I79: 0 | J79: 0 | K79: =J79-I79 -> 0 | R79: =IF(K79=P79, "", "Error") | CC79: =SUMIFS($T79:$CA79, $T$1:$CA$1, CC$75) -> 0 | CD79: =SUMIFS($T79:$CA79, $T$1:$CA$1, CD$75) -> 0 | CE79: =SUMIFS($T79:$CA79, $T$1:$CA$1, CE$75) -> 0 | CF79: =SUMIFS($T79:$CA79, $T$1:$CA$1, CF$75) -> 0 | CG79: =SUMIFS($T79:$CA79, $T$1:$CA$1, CG$75) -> 0 | CI79: =CC79=L79 -> 1 | CJ79: =CD79=M79 -> 1 | CK79: =CE79=N79 -> 1 | CL79: =CF79=O79 -> 1 | CM79: =CG79=P79 -> 1
E80: Revenue Subtotal | I80: =SUM(I78:I79) -> 0 | J80: =SUM(J78:J79) -> 0 | K80: =SUM(K78:K79) -> 0 | L80: =SUM(L78:L79) -> 0 | M80: =SUM(M78:M79) -> 0 | N80: =SUM(N78:N79) -> 0 | O80: =SUM(O78:O79) -> 0 | P80: =SUM(P78:P79) -> 0 | T80: =SUM(T78:T79) -> 0 | U80: =SUM(U78:U79) -> 0 | V80: =SUM(V78:V79) -> 0 | W80: =SUM(W78:W79) -> 0 | X80: =SUM(X78:X79) -> 0 | Y80: =SUM(Y78:Y79) -> 0 | Z80: =SUM(Z78:Z79) -> 0 | AA80: =SUM(AA78:AA79) -> 0 | ... CA80: =SUM(CA78:CA79) -> 0 | CC80: =SUM(CC78:CC79) -> 0 | CD80: =SUM(CD78:CD79) -> 0 | CE80: =SUM(CE78:CE79) -> 0 | CF80: =SUM(CF78:CF79) -> 0 | CG80: =SUM(CG78:CG79) -> 0 | CI80: =CC80=L80 -> 1 | CJ80: =CD80=M80 -> 1 | CK80: =CE80=N80 -> 1 | CL80: =CF80=O80 -> 1 | CM80: =CG80=P80 -> 1
E82: Cost of Sales
K83: =I83-J83 -> 0 | R83: =IF(K83=P83, "", "Error") | CC83: =SUMIFS($T83:$CA83, $T$1:$CA$1, CC$75) -> 0 | CD83: =SUMIFS($T83:$CA83, $T$1:$CA$1, CD$75) -> 0 | CE83: =SUMIFS($T83:$CA83, $T$1:$CA$1, CE$75) -> 0 | CF83: =SUMIFS($T83:$CA83, $T$1:$CA$1, CF$75) -> 0 | CG83: =SUMIFS($T83:$CA83, $T$1:$CA$1, CG$75) -> 0 | CI83: =CC83=L83 -> 1 | CJ83: =CD83=M83 -> 1 | CK83: =CE83=N83 -> 1 | CL83: =CF83=O83 -> 1 | CM83: =CG83=P83 -> 1
I84: 0 | J84: 0 | K84: =I84-J84 -> 0 | R84: =IF(K84=P84, "", "Error") | CC84: =SUMIFS($T84:$CA84, $T$1:$CA$1, CC$75) -> 0 | CD84: =SUMIFS($T84:$CA84, $T$1:$CA$1, CD$75) -> 0 | CE84: =SUMIFS($T84:$CA84, $T$1:$CA$1, CE$75) -> 0 | CF84: =SUMIFS($T84:$CA84, $T$1:$CA$1, CF$75) -> 0 | CG84: =SUMIFS($T84:$CA84, $T$1:$CA$1, CG$75) -> 0 | CI84: =CC84=L84 -> 1 | CJ84: =CD84=M84 -> 1 | CK84: =CE84=N84 -> 1 | CL84: =CF84=O84 -> 1 | CM84: =CG84=P84 -> 1
I85: 0 | J85: 0 | K85: =I85-J85 -> 0 | R85: =IF(K85=P85, "", "Error") | CC85: =SUMIFS($T85:$CA85, $T$1:$CA$1, CC$75) -> 0 | CD85: =SUMIFS($T85:$CA85, $T$1:$CA$1, CD$75) -> 0 | CE85: =SUMIFS($T85:$CA85, $T$1:$CA$1, CE$75) -> 0 | CF85: =SUMIFS($T85:$CA85, $T$1:$CA$1, CF$75) -> 0 | CG85: =SUMIFS($T85:$CA85, $T$1:$CA$1, CG$75) -> 0 | CI85: =CC85=L85 -> 1 | CJ85: =CD85=M85 -> 1 | CK85: =CE85=N85 -> 1 | CL85: =CF85=O85 -> 1 | CM85: =CG85=P85 -> 1
I86: 0 | J86: 0 | K86: =I86-J86 -> 0 | R86: =IF(K86=P86, "", "Error") | CC86: =SUMIFS($T86:$CA86, $T$1:$CA$1, CC$75) -> 0 | CD86: =SUMIFS($T86:$CA86, $T$1:$CA$1, CD$75) -> 0 | CE86: =SUMIFS($T86:$CA86, $T$1:$CA$1, CE$75) -> 0 | CF86: =SUMIFS($T86:$CA86, $T$1:$CA$1, CF$75) -> 0 | CG86: =SUMIFS($T86:$CA86, $T$1:$CA$1, CG$75) -> 0 | CI86: =CC86=L86 -> 1 | CJ86: =CD86=M86 -> 1 | CK86: =CE86=N86 -> 1 | CL86: =CF86=O86 -> 1 | CM86: =CG86=P86 -> 1
K87: =I87-J87 -> 0 | R87: =IF(K87=P87, "", "Error") | CC87: =SUMIFS($T87:$CA87, $T$1:$CA$1, CC$75) -> 0 | CD87: =SUMIFS($T87:$CA87, $T$1:$CA$1, CD$75) -> 0 | CE87: =SUMIFS($T87:$CA87, $T$1:$CA$1, CE$75) -> 0 | CF87: =SUMIFS($T87:$CA87, $T$1:$CA$1, CF$75) -> 0 | CG87: =SUMIFS($T87:$CA87, $T$1:$CA$1, CG$75) -> 0 | CI87: =CC87=L87 -> 1 | CJ87: =CD87=M87 -> 1 | CK87: =CE87=N87 -> 1 | CL87: =CF87=O87 -> 1 | CM87: =CG87=P87 -> 1
E88: Cost of Sales Subtotal | I88: =SUM(I83:I87) -> 0 | J88: =SUM(J83:J87) -> 0 | K88: =SUM(K83:K87) -> 0 | L88: =SUM(L83:L87) -> 0 | M88: =SUM(M83:M87) -> 0 | N88: =SUM(N83:N87) -> 0 | O88: =SUM(O83:O87) -> 0 | P88: =SUM(P83:P87) -> 0 | T88: =SUM(T83:T87) -> 0 | U88: =SUM(U83:U87) -> 0 | V88: =SUM(V83:V87) -> 0 | W88: =SUM(W83:W87) -> 0 | X88: =SUM(X83:X87) -> 0 | Y88: =SUM(Y83:Y87) -> 0 | Z88: =SUM(Z83:Z87) -> 0 | AA88: =SUM(AA83:AA87) -> 0 | ... CA88: =SUM(CA83:CA87) -> 0 | CC88: =SUM(CC83:CC87) -> 0 | CD88: =SUM(CD83:CD87) -> 0 | CE88: =SUM(CE83:CE87) -> 0 | CF88: =SUM(CF83:CF87) -> 0 | CG88: =SUM(CG83:CG87) -> 0 | CI88: =CC88=L88 -> 1 | CJ88: =CD88=M88 -> 1 | CK88: =CE88=N88 -> 1 | CL88: =CF88=O88 -> 1 | CM88: =CG88=P88 -> 1
E90: OPEX
E91: OPEX - Temporary Workers | I91: =J29 -> 25 | J91: =J36 -> 13 | K91: =I91-J91 -> 12 | N91: =K91 -> 12 | O91: =N91 -> 12 | P91: =O91 -> 12 | Q91: Global Risk | R91: =IF(K91=P91, "", "Error") | AR91: =$P$91/12 -> 1 | AS91: =$P$91/12 -> 1 | AT91: =$P$91/12 -> 1 | AU91: =$P$91/12 -> 1 | AV91: =$P$91/12 -> 1 | AW91: =$P$91/12 -> 1 | AX91: =$P$91/12 -> 1 | AY91: =$P$91/12 -> 1 | ... CA91: =$P$91/12 -> 1 | CB91: =20/12 -> 1.6666667 | CC91: =SUMIFS($T91:$CA91, $T$1:$CA$1, CC$75) -> 0 | CE91: =SUMIFS($T91:$CA91, $T$1:$CA$1, CE$75) -> 12 | CF91: =SUMIFS($T91:$CA91, $T$1:$CA$1, CF$75) -> 12 | CG91: =SUMIFS($T91:$CA91, $T$1:$CA$1, CG$75) -> 12 | CI91: =CC91=L91 -> 1 | CJ91: =CD91=M91 -> 1 | CK91: =CE91=N91 -> 1 | CL91: =CF91=O91 -> 1 | CM91: =CG91=P91 -> 1
I92: 0 | J92: 0 | K92: =I92-J92 -> 0 | R92: =IF(K92=P92, "", "Error") | CC92: =SUMIFS($T92:$CA92, $T$1:$CA$1, CC$75) -> 0 | CD92: =SUMIFS($T92:$CA92, $T$1:$CA$1, CD$75) -> 0 | CE92: =SUMIFS($T92:$CA92, $T$1:$CA$1, CE$75) -> 0 | CF92: =SUMIFS($T92:$CA92, $T$1:$CA$1, CF$75) -> 0 | CG92: =SUMIFS($T92:$CA92, $T$1:$CA$1, CG$75) -> 0 | CI92: =CC92=L92 -> 1 | CJ92: =CD92=M92 -> 1 | CK92: =CE92=N92 -> 1 | CL92: =CF92=O92 -> 1 | CM92: =CG92=P92 -> 1
I93: 0 | J93: 0 | K93: =I93-J93 -> 0 | R93: =IF(K93=P93, "", "Error") | CC93: =SUMIFS($T93:$CA93, $T$1:$CA$1, CC$75) -> 0 | CD93: =SUMIFS($T93:$CA93, $T$1:$CA$1, CD$75) -> 0 | CE93: =SUMIFS($T93:$CA93, $T$1:$CA$1, CE$75) -> 0 | CF93: =SUMIFS($T93:$CA93, $T$1:$CA$1, CF$75) -> 0 | CG93: =SUMIFS($T93:$CA93, $T$1:$CA$1, CG$75) -> 0 | CI93: =CC93=L93 -> 1 | CJ93: =CD93=M93 -> 1 | CK93: =CE93=N93 -> 1 | CL93: =CF93=O93 -> 1 | CM93: =CG93=P93 -> 1
I94: 0 | J94: 0 | K94: =I94-J94 -> 0 | R94: =IF(K94=P94, "", "Error") | CC94: =SUMIFS($T94:$CA94, $T$1:$CA$1, CC$75) -> 0 | CD94: =SUMIFS($T94:$CA94, $T$1:$CA$1, CD$75) -> 0 | CE94: =SUMIFS($T94:$CA94, $T$1:$CA$1, CE$75) -> 0 | CF94: =SUMIFS($T94:$CA94, $T$1:$CA$1, CF$75) -> 0 | CG94: =SUMIFS($T94:$CA94, $T$1:$CA$1, CG$75) -> 0 | CI94: =CC94=L94 -> 1 | CJ94: =CD94=M94 -> 1 | CK94: =CE94=N94 -> 1 | CL94: =CF94=O94 -> 1 | CM94: =CG94=P94 -> 1
I95: 0 | J95: 0 | K95: =I95-J95 -> 0 | R95: =IF(K95=P95, "", "Error") | CC95: =SUMIFS($T95:$CA95, $T$1:$CA$1, CC$75) -> 0 | CD95: =SUMIFS($T95:$CA95, $T$1:$CA$1, CD$75) -> 0 | CE95: =SUMIFS($T95:$CA95, $T$1:$CA$1, CE$75) -> 0 | CF95: =SUMIFS($T95:$CA95, $T$1:$CA$1, CF$75) -> 0 | CG95: =SUMIFS($T95:$CA95, $T$1:$CA$1, CG$75) -> 0 | CI95: =CC95=L95 -> 1 | CJ95: =CD95=M95 -> 1 | CK95: =CE95=N95 -> 1 | CL95: =CF95=O95 -> 1 | CM95: =CG95=P95 -> 1
E96: OpEx subtotal | I96: =SUM(I91:I95) -> 25 | J96: =SUM(J91:J95) -> 13 | K96: =SUM(K91:K95) -> 12 | L96: =SUM(L91:L95) -> 0 | M96: =SUM(M91:M95) -> 0 | N96: =SUM(N91:N95) -> 12 | O96: =SUM(O91:O95) -> 12 | P96: =SUM(P91:P95) -> 12 | T96: =SUM(T91:T95) -> 0 | U96: =SUM(U91:U95) -> 0 | V96: =SUM(V91:V95) -> 0 | W96: =SUM(W91:W95) -> 0 | X96: =SUM(X91:X95) -> 0 | Y96: =SUM(Y91:Y95) -> 0 | Z96: =SUM(Z91:Z95) -> 0 | AA96: =SUM(AA91:AA95) -> 0 | ... CA96: =SUM(CA91:CA95) -> 1 | CC96: =SUM(CC91:CC95) -> 0 | CD96: =SUM(CD91:CD95) -> 0 | CE96: =SUM(CE91:CE95) -> 12 | CF96: =SUM(CF91:CF95) -> 12 | CG96: =SUM(CG91:CG95) -> 12 | CI96: =CC96=L96 -> 1 | CJ96: =CD96=M96 -> 1 | CK96: =CE96=N96 -> 1 | CL96: =CF96=O96 -> 1 | CM96: =CG96=P96 -> 1
E100: Recurring Benefits Total | I100: =SUM(I80, I88, I96) -> 25 | J100: =SUM(J80, J88, J96) -> 13 | K100: =SUM(-K80, K88, K96) -> 12 | L100: =SUM(L80, L88, L96) -> 0 | M100: =SUM(M80, M88, M96) -> 0 | N100: =SUM(N80, N88, N96) -> 12 | O100: =SUM(O80, O88, O96) -> 12 | P100: =SUM(P80, P88, P96) -> 12 | T100: =SUM(T80, T88, T96) -> 0 | U100: =SUM(U80, U88, U96) -> 0 | V100: =SUM(V80, V88, V96) -> 0 | W100: =SUM(W80, W88, W96) -> 0 | X100: =SUM(X80, X88, X96) -> 0 | Y100: =SUM(Y80, Y88, Y96) -> 0 | Z100: =SUM(Z80, Z88, Z96) -> 0 | AA100: =SUM(AA80, AA88, AA96) -> 0 | ... CA100: =SUM(CA80, CA88, CA96) -> 1 | CC100: =SUM(CC80, CC88, CC96) -> 0 | CD100: =SUM(CD80, CD88, CD96) -> 0 | CE100: =SUM(CE80, CE88, CE96) -> 12 | CF100: =SUM(CF80, CF88, CF96) -> 12 | CG100: =SUM(CG80, CG88, CG96) -> 12 | CH100: =SUM(CH80, CH88, CH96) -> 0 | CI100: =CC100=L100 -> 1 | CJ100: =CD100=M100 -> 1 | CK100: =CE100=N100 -> 1 | CL100: =CF100=O100 -> 1 | CM100: =CG100=P100 -> 1
D102: RECURRING COSTS TO ACHIEVE IMPACT | H102: Comment | I102: Baseline | J102: Goal | K102: Ann. Run Rate | L102: 2026 | M102: =L102+1 -> 2027 | N102: =M102+1 -> 2028 | O102: =N102+1 -> 2029 | P102: =O102+1 -> 2030 | Q102: Impacted BU | R102: Check | T102: 46023 | U102: =EOMONTH(T102, 1) -> 46081 | V102: =EOMONTH(U102, 1) -> 46112 | W102: =EOMONTH(V102, 1) -> 46142 | X102: =EOMONTH(W102, 1) -> 46173 | Y102: =EOMONTH(X102, 1) -> 46203 | Z102: =EOMONTH(Y102, 1) -> 46234 | AA102: =EOMONTH(Z102, 1) -> 46265 | AB102: =EOMONTH(AA102, 1) -> 46295 | ... CA102: =EOMONTH(BZ102, 1) -> 47848 | CC102: 2026 | CD102: =CC102+1 -> 2027 | CE102: =CD102+1 -> 2028 | CF102: =CE102+1 -> 2029 | CG102: =CF102+1 -> 2030 | CI102: 2026 | CJ102: =CI102+1 -> 2027 | CK102: =CJ102+1 -> 2028 | CL102: =CK102+1 -> 2029 | CM102: =CL102+1 -> 2030
E103: $USD M | I103: FY25 Hist. | J103: Future State | K103: Increment
E104: Revenue
I105: 0 | J105: 0 | K105: =J105-I105 -> 0 | R105: =IF(K105=P105, "", "Error") | CC105: =SUMIFS($T105:$CA105, $T$1:$CA$1, CC$75) -> 0 | CD105: =SUMIFS($T105:$CA105, $T$1:$CA$1, CD$75) -> 0 | CE105: =SUMIFS($T105:$CA105, $T$1:$CA$1, CE$75) -> 0 | CF105: =SUMIFS($T105:$CA105, $T$1:$CA$1, CF$75) -> 0 | CG105: =SUMIFS($T105:$CA105, $T$1:$CA$1, CG$75) -> 0 | CI105: =CC105=L105 -> 1 | CJ105: =CD105=M105 -> 1 | CK105: =CE105=N105 -> 1 | CL105: =CF105=O105 -> 1 | CM105: =CG105=P105 -> 1
I106: 0 | J106: 0 | K106: =J106-I106 -> 0 | R106: =IF(K106=P106, "", "Error") | CC106: =SUMIFS($T106:$CA106, $T$1:$CA$1, CC$75) -> 0 | CD106: =SUMIFS($T106:$CA106, $T$1:$CA$1, CD$75) -> 0 | CE106: =SUMIFS($T106:$CA106, $T$1:$CA$1, CE$75) -> 0 | CF106: =SUMIFS($T106:$CA106, $T$1:$CA$1, CF$75) -> 0 | CG106: =SUMIFS($T106:$CA106, $T$1:$CA$1, CG$75) -> 0 | CI106: =CC106=L106 -> 1 | CJ106: =CD106=M106 -> 1 | CK106: =CE106=N106 -> 1 | CL106: =CF106=O106 -> 1 | CM106: =CG106=P106 -> 1
E107: Revenue Subtotal | I107: =SUM(I105:I106) -> 0 | J107: =SUM(J105:J106) -> 0 | K107: =SUM(K105:K106) -> 0 | L107: =SUM(L105:L106) -> 0 | M107: =SUM(M105:M106) -> 0 | N107: =SUM(N105:N106) -> 0 | O107: =SUM(O105:O106) -> 0 | P107: =SUM(P105:P106) -> 0 | T107: =SUM(T105:T106) -> 0 | U107: =SUM(U105:U106) -> 0 | V107: =SUM(V105:V106) -> 0 | W107: =SUM(W105:W106) -> 0 | X107: =SUM(X105:X106) -> 0 | Y107: =SUM(Y105:Y106) -> 0 | Z107: =SUM(Z105:Z106) -> 0 | AA107: =SUM(AA105:AA106) -> 0 | ... CA107: =SUM(CA105:CA106) -> 0 | CC107: =SUM(CC105:CC106) -> 0 | CD107: =SUM(CD105:CD106) -> 0 | CE107: =SUM(CE105:CE106) -> 0 | CF107: =SUM(CF105:CF106) -> 0 | CG107: =SUM(CG105:CG106) -> 0 | CI107: =CC107=L107 -> 1 | CJ107: =CD107=M107 -> 1 | CK107: =CE107=N107 -> 1 | CL107: =CF107=O107 -> 1 | CM107: =CG107=P107 -> 1
E109: Cost of Sales
I110: 0 | J110: 0 | K110: =J110-I110 -> 0 | R110: =IF(K110=P110, "", "Error") | CC110: =SUMIFS($T110:$CA110, $T$1:$CA$1, CC$75) -> 0 | CD110: =SUMIFS($T110:$CA110, $T$1:$CA$1, CD$75) -> 0 | CE110: =SUMIFS($T110:$CA110, $T$1:$CA$1, CE$75) -> 0 | CF110: =SUMIFS($T110:$CA110, $T$1:$CA$1, CF$75) -> 0 | CG110: =SUMIFS($T110:$CA110, $T$1:$CA$1, CG$75) -> 0 | CI110: =CC110=L110 -> 1 | CJ110: =CD110=M110 -> 1 | CK110: =CE110=N110 -> 1 | CL110: =CF110=O110 -> 1 | CM110: =CG110=P110 -> 1
I111: 0 | J111: 0 | K111: =J111-I111 -> 0 | R111: =IF(K111=P111, "", "Error") | CC111: =SUMIFS($T111:$CA111, $T$1:$CA$1, CC$75) -> 0 | CD111: =SUMIFS($T111:$CA111, $T$1:$CA$1, CD$75) -> 0 | CE111: =SUMIFS($T111:$CA111, $T$1:$CA$1, CE$75) -> 0 | CF111: =SUMIFS($T111:$CA111, $T$1:$CA$1, CF$75) -> 0 | CG111: =SUMIFS($T111:$CA111, $T$1:$CA$1, CG$75) -> 0 | CI111: =CC111=L111 -> 1 | CJ111: =CD111=M111 -> 1 | CK111: =CE111=N111 -> 1 | CL111: =CF111=O111 -> 1 | CM111: =CG111=P111 -> 1
I112: 0 | J112: 0 | K112: =J112-I112 -> 0 | R112: =IF(K112=P112, "", "Error") | CC112: =SUMIFS($T112:$CA112, $T$1:$CA$1, CC$75) -> 0 | CD112: =SUMIFS($T112:$CA112, $T$1:$CA$1, CD$75) -> 0 | CE112: =SUMIFS($T112:$CA112, $T$1:$CA$1, CE$75) -> 0 | CF112: =SUMIFS($T112:$CA112, $T$1:$CA$1, CF$75) -> 0 | CG112: =SUMIFS($T112:$CA112, $T$1:$CA$1, CG$75) -> 0 | CI112: =CC112=L112 -> 1 | CJ112: =CD112=M112 -> 1 | CK112: =CE112=N112 -> 1 | CL112: =CF112=O112 -> 1 | CM112: =CG112=P112 -> 1
I113: 0 | J113: 0 | K113: =J113-I113 -> 0 | R113: =IF(K113=P113, "", "Error") | CC113: =SUMIFS($T113:$CA113, $T$1:$CA$1, CC$75) -> 0 | CD113: =SUMIFS($T113:$CA113, $T$1:$CA$1, CD$75) -> 0 | CE113: =SUMIFS($T113:$CA113, $T$1:$CA$1, CE$75) -> 0 | CF113: =SUMIFS($T113:$CA113, $T$1:$CA$1, CF$75) -> 0 | CG113: =SUMIFS($T113:$CA113, $T$1:$CA$1, CG$75) -> 0 | CI113: =CC113=L113 -> 1 | CJ113: =CD113=M113 -> 1 | CK113: =CE113=N113 -> 1 | CL113: =CF113=O113 -> 1 | CM113: =CG113=P113 -> 1
E115: Cost of Sales Subtotal | I115: =SUM(I110:I114) -> 0 | J115: =SUM(J110:J114) -> 0 | K115: =SUM(K110:K114) -> 0 | L115: =SUM(L110:L114) -> 0 | M115: =SUM(M110:M114) -> 0 | N115: =SUM(N110:N114) -> 0 | O115: =SUM(O110:O114) -> 0 | P115: =SUM(P110:P114) -> 0 | T115: =SUM(T110:T114) -> 0 | U115: =SUM(U110:U114) -> 0 | V115: =SUM(V110:V114) -> 0 | W115: =SUM(W110:W114) -> 0 | X115: =SUM(X110:X114) -> 0 | Y115: =SUM(Y110:Y114) -> 0 | Z115: =SUM(Z110:Z114) -> 0 | AA115: =SUM(AA110:AA114) -> 0 | ... CA115: =SUM(CA110:CA114) -> 0 | CC115: =SUM(CC110:CC114) -> 0 | CD115: =SUM(CD110:CD114) -> 0 | CE115: =SUM(CE110:CE114) -> 0 | CF115: =SUM(CF110:CF114) -> 0 | CG115: =SUM(CG110:CG114) -> 0 | CI115: =CC115=L115 -> 1 | CJ115: =CD115=M115 -> 1 | CK115: =CE115=N115 -> 1 | CL115: =CF115=O115 -> 1 | CM115: =CG115=P115 -> 1
E117: OPEX
E118: OPEX - SaaS SW | H118: Platform licencing & LLM inference | I118: 0 | J118: 3.6 | K118: =J118-I118 -> 3.6 | N118: 3.6 | O118: 3.6 | P118: 3.6 | R118: =IF(K118=P118, "", "Error") | AR118: =3.6/12 -> 0.3 | AS118: =3.6/12 -> 0.3 | AT118: =3.6/12 -> 0.3 | AU118: =3.6/12 -> 0.3 | AV118: =3.6/12 -> 0.3 | AW118: =3.6/12 -> 0.3 | AX118: =3.6/12 -> 0.3 | AY118: =3.6/12 -> 0.3 | ... CA118: =3.6/12 -> 0.3 | CC118: =SUMIFS($T118:$CA118, $T$1:$CA$1, CC$75) -> 0 | CD118: =SUMIFS($T118:$CA118, $T$1:$CA$1, CD$75) -> 0 | CE118: =SUMIFS($T118:$CA118, $T$1:$CA$1, CE$75) -> 3.6 | CF118: =SUMIFS($T118:$CA118, $T$1:$CA$1, CF$75) -> 3.6 | CG118: =SUMIFS($T118:$CA118, $T$1:$CA$1, CG$75) -> 3.6 | CI118: =CC118=L118 -> 1 | CJ118: =CD118=M118 -> 1 | CK118: =CE118=N118 -> 1 | CL118: =CF118=O118 -> 1 | CM118: =CG118=P118 -> 1
E119: OPEX - Cloud Services | H119: Cloud infra | I119: 0 | J119: 1.2 | K119: =J119-I119 -> 1.2 | M119: 1.2 | N119: 1.2 | O119: 1.2 | P119: 1.2 | R119: =IF(K119=P119, "", "Error") | AF119: =1.2/12 -> 0.1 | AG119: =1.2/12 -> 0.1 | AH119: =1.2/12 -> 0.1 | AI119: =1.2/12 -> 0.1 | AJ119: =1.2/12 -> 0.1 | AK119: =1.2/12 -> 0.1 | AL119: =1.2/12 -> 0.1 | AM119: =1.2/12 -> 0.1 | ... CA119: =1.2/12 -> 0.1 | CC119: =SUMIFS($T119:$CA119, $T$1:$CA$1, CC$75) -> 0 | CD119: =SUMIFS($T119:$CA119, $T$1:$CA$1, CD$75) -> 1.2 | CE119: =SUMIFS($T119:$CA119, $T$1:$CA$1, CE$75) -> 1.2 | CF119: =SUMIFS($T119:$CA119, $T$1:$CA$1, CF$75) -> 1.2 | CG119: =SUMIFS($T119:$CA119, $T$1:$CA$1, CG$75) -> 1.2 | CI119: =CC119=L119 -> 1 | CJ119: =CD119=M119 -> 1 | CK119: =CE119=N119 -> 1 | CL119: =CF119=O119 -> 1 | CM119: =CG119=P119 -> 1
CC120: =SUMIFS($T120:$CA120, $T$1:$CA$1, CC$75) -> 0 | CD120: =SUMIFS($T120:$CA120, $T$1:$CA$1, CD$75) -> 0 | CE120: =SUMIFS($T120:$CA120, $T$1:$CA$1, CE$75) -> 0 | CF120: =SUMIFS($T120:$CA120, $T$1:$CA$1, CF$75) -> 0 | CG120: =SUMIFS($T120:$CA120, $T$1:$CA$1, CG$75) -> 0 | CI120: =CC120=L120 -> 1 | CJ120: =CD120=M120 -> 1 | CK120: =CE120=N120 -> 1 | CL120: =CF120=O120 -> 1 | CM120: =CG120=P120 -> 1
J121: 0 | K121: =J121-I121 -> 0 | R121: =IF(K121=P121, "", "Error") | CC121: =SUMIFS($T121:$CA121, $T$1:$CA$1, CC$75) -> 0 | CD121: =SUMIFS($T121:$CA121, $T$1:$CA$1, CD$75) -> 0 | CE121: =SUMIFS($T121:$CA121, $T$1:$CA$1, CE$75) -> 0 | CF121: =SUMIFS($T121:$CA121, $T$1:$CA$1, CF$75) -> 0 | CG121: =SUMIFS($T121:$CA121, $T$1:$CA$1, CG$75) -> 0 | CI121: =CC121=L121 -> 1 | CJ121: =CD121=M121 -> 1 | CK121: =CE121=N121 -> 1 | CL121: =CF121=O121 -> 1 | CM121: =CG121=P121 -> 1
I122: 0 | J122: 0 | K122: =J122-I122 -> 0 | R122: =IF(K122=P122, "", "Error") | CC122: =SUMIFS($T122:$CA122, $T$1:$CA$1, CC$75) -> 0 | CD122: =SUMIFS($T122:$CA122, $T$1:$CA$1, CD$75) -> 0 | CE122: =SUMIFS($T122:$CA122, $T$1:$CA$1, CE$75) -> 0 | CF122: =SUMIFS($T122:$CA122, $T$1:$CA$1, CF$75) -> 0 | CG122: =SUMIFS($T122:$CA122, $T$1:$CA$1, CG$75) -> 0 | CI122: =CC122=L122 -> 1 | CJ122: =CD122=M122 -> 1 | CK122: =CE122=N122 -> 1 | CL122: =CF122=O122 -> 1 | CM122: =CG122=P122 -> 1
E123: OpEx subtotal | I123: =SUM(I118:I122) -> 0 | J123: =SUM(J118:J122) -> 4.8 | K123: =SUM(K118:K122) -> 4.8 | L123: =SUM(L118:L122) -> 0 | M123: =SUM(M118:M122) -> 1.2 | N123: =SUM(N118:N122) -> 4.8 | O123: =SUM(O118:O122) -> 4.8 | P123: =SUM(P118:P122) -> 4.8 | T123: =SUM(T118:T122) -> 0 | U123: =SUM(U118:U122) -> 0 | V123: =SUM(V118:V122) -> 0 | W123: =SUM(W118:W122) -> 0 | X123: =SUM(X118:X122) -> 0 | Y123: =SUM(Y118:Y122) -> 0 | Z123: =SUM(Z118:Z122) -> 0 | AA123: =SUM(AA118:AA122) -> 0 | ... CA123: =SUM(CA118:CA122) -> 0.4 | CC123: =SUM(CC118:CC122) -> 0 | CD123: =SUM(CD118:CD122) -> 1.2 | CE123: =SUM(CE118:CE122) -> 4.8 | CF123: =SUM(CF118:CF122) -> 4.8 | CG123: =SUM(CG118:CG122) -> 4.8 | CI123: =CC123=L123 -> 1 | CJ123: =CD123=M123 -> 1 | CK123: =CE123=N123 -> 1 | CL123: =CF123=O123 -> 1 | CM123: =CG123=P123 -> 1
E126: Recurring Costs Total | I126: =SUM(-I107, I115, I123) -> 0 | J126: =SUM(-J107, J115, J123) -> 4.8 | K126: =SUM(-K107, K115, K123) -> 4.8 | L126: =SUM(-L107, L115, L123) -> 0 | M126: =SUM(-M107, M115, M123) -> 1.2 | N126: =SUM(-N107, N115, N123) -> 4.8 | O126: =SUM(-O107, O115, O123) -> 4.8 | P126: =SUM(-P107, P115, P123) -> 4.8 | T126: =SUM(-T107, T115, T123) -> 0 | U126: =SUM(-U107, U115, U123) -> 0 | V126: =SUM(-V107, V115, V123) -> 0 | W126: =SUM(-W107, W115, W123) -> 0 | X126: =SUM(-X107, X115, X123) -> 0 | Y126: =SUM(-Y107, Y115, Y123) -> 0 | Z126: =SUM(-Z107, Z115, Z123) -> 0 | AA126: =SUM(-AA107, AA115, AA123) -> 0 | ... CA126: =SUM(-CA107, CA115, CA123) -> 0.4 | CC126: =SUM(-CC107, CC115, CC123) -> 0 | CD126: =SUM(-CD107, CD115, CD123) -> 1.2 | CE126: =SUM(-CE107, CE115, CE123) -> 4.8 | CF126: =SUM(-CF107, CF115, CF123) -> 4.8 | CG126: =SUM(-CG107, CG115, CG123) -> 4.8 | CI126: =CC126=L126 -> 1 | CJ126: =CD126=M126 -> 1 | CK126: =CE126=N126 -> 1 | CL126: =CF126=O126 -> 1 | CM126: =CG126=P126 -> 1
E128: Net Recurring Benefit | I128: =SUM(I100, -I126) -> 25 | J128: =SUM(J100, -J126) -> 8.2 | K128: =SUM(K100, -K126) -> 7.2 | L128: =SUM(L100, -L126) -> 0 | M128: =SUM(M100, -M126) -> -1.2 | N128: =SUM(N100, -N126) -> 7.2 | O128: =SUM(O100, -O126) -> 7.2 | P128: =SUM(P100, -P126) -> 7.2 | R128: =IF(K128=P128, "", "Error") | T128: =SUM(T100, -T126) -> 0 | U128: =SUM(U100, -U126) -> 0 | V128: =SUM(V100, -V126) -> 0 | W128: =SUM(W100, -W126) -> 0 | X128: =SUM(X100, -X126) -> 0 | Y128: =SUM(Y100, -Y126) -> 0 | Z128: =SUM(Z100, -Z126) -> 0 | AA128: =SUM(AA100, -AA126) -> 0 | ... CA128: =SUM(CA100, -CA126) -> 0.6 | CC128: =SUM(CC100, -CC126) -> 0 | CD128: =SUM(CD100, -CD126) -> -1.2 | CE128: =SUM(CE100, -CE126) -> 7.2 | CF128: =SUM(CF100, -CF126) -> 7.2 | CG128: =SUM(CG100, -CG126) -> 7.2 | CI128: =CC128=L128 -> 1 | CJ128: =CD128=M128 -> 1 | CK128: =CE128=N128 -> 1 | CL128: =CF128=O128 -> 1 | CM128: =CG128=P128 -> 1
C131: SECTION III - ONE-TIME IMPLEMENTATION | CC131: ANNUAL SUMMARY | CI131: CHECK CELLS
T133: 2026 | AF133: 2027 | AR133: 2028 | BD133: 2029 | BP133: 2030
D134: ONE-TIME BENEFITS | K134: Comment | L134: 2026 | M134: =L134+1 -> 2027 | N134: =M134+1 -> 2028 | O134: =N134+1 -> 2029 | P134: =O134+1 -> 2030 | Q134: Impacted BU | T134: 46023 | U134: =EOMONTH(T134, 1) -> 46081 | V134: =EOMONTH(U134, 1) -> 46112 | W134: =EOMONTH(V134, 1) -> 46142 | X134: =EOMONTH(W134, 1) -> 46173 | Y134: =EOMONTH(X134, 1) -> 46203 | Z134: =EOMONTH(Y134, 1) -> 46234 | AA134: =EOMONTH(Z134, 1) -> 46265 | AB134: =EOMONTH(AA134, 1) -> 46295 | ... CA134: =EOMONTH(BZ134, 1) -> 47848 | CC134: 2026 | CD134: =CC134+1 -> 2027 | CE134: =CD134+1 -> 2028 | CF134: =CE134+1 -> 2029 | CG134: =CF134+1 -> 2030 | CI134: 2026 | CJ134: =CI134+1 -> 2027 | CK134: =CJ134+1 -> 2028 | CL134: =CK134+1 -> 2029 | CM134: =CL134+1 -> 2030
E136: Working Capital
CC137: =SUMIFS($T137:$CA137, $T$1:$CA$1, CC$75) -> 0 | CD137: =SUMIFS($T137:$CA137, $T$1:$CA$1, CD$75) -> 0 | CE137: =SUMIFS($T137:$CA137, $T$1:$CA$1, CE$75) -> 0 | CF137: =SUMIFS($T137:$CA137, $T$1:$CA$1, CF$75) -> 0 | CG137: =SUMIFS($T137:$CA137, $T$1:$CA$1, CG$75) -> 0 | CI137: =CC137=L137 -> 1 | CJ137: =CD137=M137 -> 1 | CK137: =CE137=N137 -> 1 | CL137: =CF137=O137 -> 1 | CM137: =CG137=P137 -> 1
CC138: =SUMIFS($T138:$CA138, $T$1:$CA$1, CC$75) -> 0 | CD138: =SUMIFS($T138:$CA138, $T$1:$CA$1, CD$75) -> 0 | CE138: =SUMIFS($T138:$CA138, $T$1:$CA$1, CE$75) -> 0 | CF138: =SUMIFS($T138:$CA138, $T$1:$CA$1, CF$75) -> 0 | CG138: =SUMIFS($T138:$CA138, $T$1:$CA$1, CG$75) -> 0 | CI138: =CC138=L138 -> 1 | CJ138: =CD138=M138 -> 1 | CK138: =CE138=N138 -> 1 | CL138: =CF138=O138 -> 1 | CM138: =CG138=P138 -> 1
E139: Working Capital Subtotal | L139: =SUM(L137:L138) -> 0 | M139: =SUM(M137:M138) -> 0 | N139: =SUM(N137:N138) -> 0 | O139: =SUM(O137:O138) -> 0 | P139: =SUM(P137:P138) -> 0 | T139: =SUM(T137:T138) -> 0 | U139: =SUM(U137:U138) -> 0 | V139: =SUM(V137:V138) -> 0 | W139: =SUM(W137:W138) -> 0 | X139: =SUM(X137:X138) -> 0 | Y139: =SUM(Y137:Y138) -> 0 | Z139: =SUM(Z137:Z138) -> 0 | AA139: =SUM(AA137:AA138) -> 0 | ... CA139: =SUM(CA137:CA138) -> 0 | CC139: =SUM(CC137:CC138) -> 0 | CD139: =SUM(CD137:CD138) -> 0 | CE139: =SUM(CE137:CE138) -> 0 | CF139: =SUM(CF137:CF138) -> 0 | CG139: =SUM(CG137:CG138) -> 0 | CI139: =CC139=L139 -> 1 | CJ139: =CD139=M139 -> 1 | CK139: =CE139=N139 -> 1 | CL139: =CF139=O139 -> 1 | CM139: =CG139=P139 -> 1
...

Sheet Rate Card
B2: RATE CARD — people-cost engine (shared by all initiative models)
B4: Blue cells with yellow fill = inputs you can change. Black = formulas. All initiative models pull the blended rate and policy tables from this sheet.
B6: 1. RATE BASIS
B8: Rate basis for people costs | D8: Yearly | F8: Choose how role rates are quoted, then TYPE YOUR RATES in the matching column of the role table below (Yearly->col D, Monthly->col E, Hourly->col F). The other columns show derived equivalents until you overwrite them. Hourly => monthly = $/hr x hours/day x days/month.
B10: Working hours per day | D10: 8 | F10: Used only when rate basis = Hourly.
B11: Billable days per month | D11: 21
B12: Months per year (for yearly basis) | D12: 12
B14: 2. STANDARD TEAM COMPOSITION & BLENDED RATE
B16: Role | C16: # in std team | D16: Yearly rate ($/yr) | E16: Monthly rate ($/mo) | F16: Hourly rate ($/hr) | G16: Monthly used ($/mo) | H16: Team cost ($/mo) | I16: Source / notes
B17: Product Owner | C17: 1 | D17: 200000 | E17: =IF(D17="",0,D17/$D$12) -> 16666.667 | F17: =IF(D17="",0,E17/($D$10*$D$11)) -> 99.206349 | G17: =IF($D$8="Hourly",F17*$D$10*$D$11,IF($D$8="Monthly",E17,IF(D17="",0,D17/$D$12))) -> 16666.667 | H17: =IF(C17="",0,C17*G17) -> 16666.667
B18: PM / Scrum Master | C18: 1 | D18: 200000 | E18: =IF(D18="",0,D18/$D$12) -> 16666.667 | F18: =IF(D18="",0,E18/($D$10*$D$11)) -> 99.206349 | G18: =IF($D$8="Hourly",F18*$D$10*$D$11,IF($D$8="Monthly",E18,IF(D18="",0,D18/$D$12))) -> 16666.667 | H18: =IF(C18="",0,C18*G18) -> 16666.667
B19: Tech Lead | C19: 1 | D19: 200000 | E19: =IF(D19="",0,D19/$D$12) -> 16666.667 | F19: =IF(D19="",0,E19/($D$10*$D$11)) -> 99.206349 | G19: =IF($D$8="Hourly",F19*$D$10*$D$11,IF($D$8="Monthly",E19,IF(D19="",0,D19/$D$12))) -> 16666.667 | H19: =IF(C19="",0,C19*G19) -> 16666.667
B20: AI Engineer | C20: 2 | D20: 200000 | E20: =IF(D20="",0,D20/$D$12) -> 16666.667 | F20: =IF(D20="",0,E20/($D$10*$D$11)) -> 99.206349 | G20: =IF($D$8="Hourly",F20*$D$10*$D$11,IF($D$8="Monthly",E20,IF(D20="",0,D20/$D$12))) -> 16666.667 | H20: =IF(C20="",0,C20*G20) -> 33333.333
B21: DevOps Engineer | C21: 1 | D21: 200000 | E21: =IF(D21="",0,D21/$D$12) -> 16666.667 | F21: =IF(D21="",0,E21/($D$10*$D$11)) -> 99.206349 | G21: =IF($D$8="Hourly",F21*$D$10*$D$11,IF($D$8="Monthly",E21,IF(D21="",0,D21/$D$12))) -> 16666.667 | H21: =IF(C21="",0,C21*G21) -> 16666.667
B22: QA Engineer | C22: 1 | D22: 200000 | E22: =IF(D22="",0,D22/$D$12) -> 16666.667 | F22: =IF(D22="",0,E22/($D$10*$D$11)) -> 99.206349 | G22: =IF($D$8="Hourly",F22*$D$10*$D$11,IF($D$8="Monthly",E22,IF(D22="",0,D22/$D$12))) -> 16666.667 | H22: =IF(C22="",0,C22*G22) -> 16666.667
B23: FA / UX | C23: 1 | D23: 200000 | E23: =IF(D23="",0,D23/$D$12) -> 16666.667 | F23: =IF(D23="",0,E23/($D$10*$D$11)) -> 99.206349 | G23: =IF($D$8="Hourly",F23*$D$10*$D$11,IF($D$8="Monthly",E23,IF(D23="",0,D23/$D$12))) -> 16666.667 | H23: =IF(C23="",0,C23*G23) -> 16666.667
E24: =IF(D24="",0,D24/$D$12) -> 0 | F24: =IF(D24="",0,E24/($D$10*$D$11)) -> 0 | G24: =IF($D$8="Hourly",F24*$D$10*$D$11,IF($D$8="Monthly",E24,IF(D24="",0,D24/$D$12))) -> 0 | H24: =IF(C24="",0,C24*G24) -> 0 | I24: spare row — add roles as team shape is refined
E25: =IF(D25="",0,D25/$D$12) -> 0 | F25: =IF(D25="",0,E25/($D$10*$D$11)) -> 0 | G25: =IF($D$8="Hourly",F25*$D$10*$D$11,IF($D$8="Monthly",E25,IF(D25="",0,D25/$D$12))) -> 0 | H25: =IF(C25="",0,C25*G25) -> 0 | I25: spare row — add roles as team shape is refined
E26: =IF(D26="",0,D26/$D$12) -> 0 | F26: =IF(D26="",0,E26/($D$10*$D$11)) -> 0 | G26: =IF($D$8="Hourly",F26*$D$10*$D$11,IF($D$8="Monthly",E26,IF(D26="",0,D26/$D$12))) -> 0 | H26: =IF(C26="",0,C26*G26) -> 0 | I26: spare row — add roles as team shape is refined
B27: Total standard team | C27: =SUM(C17:C26) -> 8 | H27: =SUM(H17:H26) -> 133333.33
B29: BLENDED RATE — per team member | G29: =IF(C27=0,0,H27/C27) -> 16666.667 | H29: $/person/month | I29: Weighted average monthly cost of one member of the standard team. Initiative milestone tables use this unless a rate override is entered.
G30: =G29*$D$12 -> 200000 | H30: $/person/year
G31: =G29/($D$10*$D$11) -> 99.206349 | H31: $/person/hour
B33: 3. CONTINGENCY FACTOR REFERENCE
B35: Complexity / risk level | C35: Factor | F35: Based on the complexity and risks to deliver the milestone.
B36: Low | C36: 0.1
B37: Medium | C37: 0.15
B38: High | C38: 0.2
B39: Very high | C39: 0.5
B42: 4. CAPITALIZATION POLICY (labor) — default % of milestone labor capitalizable
B44: Milestone | C44: Cap % | F44: Share of labor cost treated as CapEx (feeds WAVE 'Capital Expenditures'); remainder is expensed one-time cost (WAVE 'OTC'). Defaults follow a typical internal-use software policy (ASC 350-40): application development/build stage capitalizable, planning and post-launch expensed. CONFIRM WITH FINANCE — initiative models reference these cells, override there if needed.
B45: Plan / Design | C45: 0
B46: Build / Test | C46: 0
B47: Pilot / Change Mgmt. | C47: 0
B48: Scale / Run | C48: 0
B49: Non-labor one-time (default) | C49: 0
B51: 5. NOTES
B52: • Roles = the S2 model's standard 8-FTE build pod; every role priced at the S2 blended loaded delivery rate of $200,000/yr, so the blended rate ties to the S2 investment build exactly. Differentiate role rates here once the client rate card arrives (C1–C3 were designed for a rate-card drop-in).
B53: • Milestone contingency of 10% in the initiative models = the S2 'risk adjustment on delivery labour'. PM (8%) and contingency (10%) uplifts are separate formula lines in each model's one-time non-labor table — total one-time per initiative ties to S2 C2 row 35.
B54: • Capitalization defaults are 0% because the S2 model treats all one-time spend as cash/expensed (no CapEx split anywhere in C1–C3). Set Build/Test cap % here (e.g. 80%) once Finance confirms treatment — the CapEx/OTC split then flows to the WAVE sheets automatically.
B55: • Run-team labor sits in each model's recurring run-cost table at $180,000/FTE/yr (S2 run rate).

Sheet Summary
B2: SERVICING WORKSTREAM — PORTFOLIO SUMMARY ($M)
B3: All figures link to the initiative WAVE sheets. Payback/NPV per WAVE Section IV.
B5: Initiative | C5: NRB run rate | D5: NRB 2026 | E5: NRB 2027 | F5: NRB 2028 | G5: NRB 2029 | H5: NRB 2030 | I5: One-time cost (5yr) | J5: Run cost 2030 | K5: NPV (5yr) | L5: Payback (yrs)
B6: SVC-1 — Contact Avoidance | C6: ='SVC-1 WAVE'!$K$117 -> 12.338616 | D6: ='SVC-1 WAVE'!$L$117 -> 0 | E6: ='SVC-1 WAVE'!$M$117 -> 2.0205931 | F6: ='SVC-1 WAVE'!$N$117 -> 12.249459 | G6: ='SVC-1 WAVE'!$O$117 -> 12.338616 | H6: ='SVC-1 WAVE'!$P$117 -> 12.338616 | I6: =SUM('SVC-1 WAVE'!$L$147:$P$147) -> 1.9602 | J6: ='SVC-1 WAVE'!$P$115 -> 0.5 | K6: ='SVC-1 WAVE'!$G$168 -> 25.80883 | L6: ='SVC-1 WAVE'!$G$165 -> 0
B7: SVC-2 — Enhanced Chat / Self-Serve | C7: ='SVC-2 WAVE'!$K$117 -> 12.43123 | D7: ='SVC-2 WAVE'!$L$117 -> 0 | E7: ='SVC-2 WAVE'!$M$117 -> 0.91249807 | F7: ='SVC-2 WAVE'!$N$117 -> 11.7042 | G7: ='SVC-2 WAVE'!$O$117 -> 12.43123 | H7: ='SVC-2 WAVE'!$P$117 -> 12.43123 | I7: =SUM('SVC-2 WAVE'!$L$147:$P$147) -> 2.5047 | J7: ='SVC-2 WAVE'!$P$115 -> 2.34 | K7: ='SVC-2 WAVE'!$G$168 -> 24.155774 | L7: ='SVC-2 WAVE'!$G$165 -> 1.1090693
B8: SVC-3 — Agentic Voice & AI Co-pilot | C8: ='SVC-3 WAVE'!$K$117 -> 29.700739 | D8: ='SVC-3 WAVE'!$L$117 -> 0 | E8: ='SVC-3 WAVE'!$M$117 -> 1.9375616 | F8: ='SVC-3 WAVE'!$N$117 -> 27.046511 | G8: ='SVC-3 WAVE'!$O$117 -> 29.700739 | H8: ='SVC-3 WAVE'!$P$117 -> 29.700739 | I8: =SUM('SVC-3 WAVE'!$L$147:$P$147) -> 4.90644 | J8: ='SVC-3 WAVE'!$P$115 -> 5.55 | K8: ='SVC-3 WAVE'!$G$168 -> 57.697013 | L8: ='SVC-3 WAVE'!$G$165 -> 1.0877635
B9: SVC-4 — AI Workforce Management | C9: ='SVC-4 WAVE'!$K$117 -> 6.3044496 | D9: ='SVC-4 WAVE'!$L$117 -> 0 | E9: ='SVC-4 WAVE'!$M$117 -> 1.2386124 | F9: ='SVC-4 WAVE'!$N$117 -> 6.3044496 | G9: ='SVC-4 WAVE'!$O$117 -> 6.3044496 | H9: ='SVC-4 WAVE'!$P$117 -> 6.3044496 | I9: =SUM('SVC-4 WAVE'!$L$147:$P$147) -> 3.53628 | J9: ='SVC-4 WAVE'!$P$115 -> 1.35 | K9: ='SVC-4 WAVE'!$G$168 -> 11.275502 | L9: ='SVC-4 WAVE'!$G$165 -> 1.3644517
B10: SVC-5 — Back-Office Automation | C10: ='SVC-5 WAVE'!$K$117 -> 5.5535036 | D10: ='SVC-5 WAVE'!$L$117 -> 0 | E10: ='SVC-5 WAVE'!$M$117 -> 0.24279197 | F10: ='SVC-5 WAVE'!$N$117 -> 5.0173783 | G10: ='SVC-5 WAVE'!$O$117 -> 5.5535036 | H10: ='SVC-5 WAVE'!$P$117 -> 5.5535036 | I10: =SUM('SVC-5 WAVE'!$L$147:$P$147) -> 2.72052 | J10: ='SVC-5 WAVE'!$P$115 -> 1.28 | K10: ='SVC-5 WAVE'!$G$168 -> 9.1799853 | L10: ='SVC-5 WAVE'!$G$165 -> 1.4409851
B11: SVC-6 — Non-FTE Savings | C11: ='SVC-6 WAVE'!$K$117 -> 4.0395467 | D11: ='SVC-6 WAVE'!$L$117 -> 0 | E11: ='SVC-6 WAVE'!$M$117 -> 0.67325778 | F11: ='SVC-6 WAVE'!$N$117 -> 3.8712322 | G11: ='SVC-6 WAVE'!$O$117 -> 4.0395467 | H11: ='SVC-6 WAVE'!$P$117 -> 4.0395467 | I11: =SUM('SVC-6 WAVE'!$L$147:$P$147) -> 0 | J11: ='SVC-6 WAVE'!$P$115 -> 0 | K11: ='SVC-6 WAVE'!$G$168 -> 8.88588 | L11: ='SVC-6 WAVE'!$G$165 -> 0
B12: TOTAL — SERVICING WORKSTREAM | C12: =SUM(C6:C11) -> 70.368085 | D12: =SUM(D6:D11) -> 0 | E12: =SUM(E6:E11) -> 7.0253149 | F12: =SUM(F6:F11) -> 66.19323 | G12: =SUM(G6:G11) -> 70.368085 | H12: =SUM(H6:H11) -> 70.368085 | I12: =SUM(I6:I11) -> 15.62814 | J12: =SUM(J6:J11) -> 11.02
B14: Note: NPV and payback are not additive across initiatives; totals shown for benefit/cost columns only.
B15: Capitalization policy note: this file defaults ALL cap % to 0% to mirror the S2 model's all-cash treatment; the SDLC/Sales files default Build/Test labor to 80%. Align the policy across workstreams with Finance before the S2 gate.

Sheet SVC-1 Model
B2: SVC-1 — Contact Avoidance | INITIATIVE MODEL
B3: Workstream: Servicing (ELT sponsor: Aaron | WSL: Tahira | IOs: Jackie Yu, Matt Anderson, Bob Hurst) • Model status: Seeded 1:1 from S2 vDraft5 (Base) — benefit ties to $12.84M
T5: 2026 | U5: 2026 | V5: 2026 | W5: 2026 | X5: 2026 | Y5: 2026 | Z5: 2026 | AA5: 2026 | AB5: 2026 | AC5: 2026 | AD5: 2026 | AE5: 2026 | AF5: 2027 | AG5: 2027 | AH5: 2027 | AI5: 2027 | AJ5: 2027 | AK5: 2027 | AL5: 2027 | AM5: 2027 | AN5: 2027 | AO5: 2027 | AP5: 2027 | AQ5: 2027 | AR5: 2028 | AS5: 2028 | AT5: 2028 | AU5: 2028 | AV5: 2028 | AW5: 2028 | AX5: 2028 | AY5: 2028 | AZ5: 2028 | BA5: 2028 | BB5: 2028 | BC5: 2028 | BD5: 2029 | BE5: 2029 | BF5: 2029 | BG5: 2029 | BH5: 2029 | BI5: 2029 | BJ5: 2029 | BK5: 2029 | BL5: 2029 | BM5: 2029 | BN5: 2029 | BO5: 2029 | BP5: 2030 | BQ5: 2030 | BR5: 2030 | BS5: 2030 | BT5: 2030 | BU5: 2030 | BV5: 2030 | BW5: 2030 | BX5: 2030 | BY5: 2030 | BZ5: 2030 | CA5: 2030
B6: Monthly grid (Jan-26 → Dec-30) → | K6: Run rate | L6: 2026 | M6: 2027 | N6: 2028 | O6: 2029 | P6: 2030 | T6: =DATE(2026,1,31) -> 46053 | U6: =EOMONTH(T6,1) -> 46081 | V6: =EOMONTH(U6,1) -> 46112 | W6: =EOMONTH(V6,1) -> 46142 | X6: =EOMONTH(W6,1) -> 46173 | Y6: =EOMONTH(X6,1) -> 46203 | Z6: =EOMONTH(Y6,1) -> 46234 | AA6: =EOMONTH(Z6,1) -> 46265 | AB6: =EOMONTH(AA6,1) -> 46295 | ... CA6: =EOMONTH(BZ6,1) -> 47848
B8: 0. INITIATIVE & STATUS
B10: Initiative name | D10: Prevent avoidable contacts at source through product fixes and upstream journey improvements
B11: Initiative owner | D11: Servicing IO — TBC (pool: Jackie Yu, Matt Anderson, Bob Hurst) | I11: confirm with workstream lead
B12: Impacted BU | D12: Global Servicing
B13: Go-live / Estimated L4 date | D13: =DATE(2027,8,1) -> 46600 | I13: Benefit ramp is gated on this date.
B15: Source: Servicing S2 sizing model vDraft5 (28 Aug 2026), Base scenario. Distilled to tier level; per-tier eligible bases and effective rates reproduce the S2 L2-intent engine output exactly (verified).
B16: Source: Workplan: 'Project Zenith Automation workplan and data requests vS_1.xlsx', Servicing tabs
B17: Open items to refine with initiative owner:
B18: – Tier rates are the S2 assumptions (Easy 20% / Medium 10% / Hard 5% of eligible contacts); scenario variants in S2: Upside 28/18/8, Downside 12/7/3.
B19: – $31.4M of opening cost is ineligible (NEI + unmappable 'Others' + no-product-fix rows) — ~20% of the front-office base carries zero avoidance benefit; upside if taxonomy improves.
B20: – S2 contact baseline is 37.7M offered contacts annualized from 7 months (x12/7), ~5% above the $148M FP&A reference — FP&A to confirm; workplan cites a different 20.4M baseline (basis differs).
B22: 1. SIZING ASSUMPTIONS (blue = inputs — refine with initiative owner)
B24: Opening baseline (S2 waterfall position: first lever, opens on A0 baseline)
B25: Opening front-office cost baseline | D25: 1.5602454e+08 | E25: $/yr | F25: Servicing S2 sizing model vDraft5 (28 Aug 2026), Base scenario. A0 intent cost baseline (annualized 7-mo actuals x 12/7). Opening cost follows the S2 stacking waterfall (each lever opens on the prior lever's closing baseline; order: 1 Avoidance → 2 Chat → 3a Voice → 3b Co-pilot → 4a SBR → 4b Utilisation). Tier-level bases below are snapshots of the S2 L2 engine — refresh them from the S2 model if upstream levers or tiering change.
B26: Investment uplifts (S2 standard)
B27: Programme management, % of build | D27: 0.08 | E27: % | F27: S2 COST_PMO
B28: Contingency, % of build incl. PM | D28: 0.1 | E28: % | F28: S2 COST_CONT
B29: Run team headcount | D29: 2 | E29: # FTE | F29: S2 C3: keep-the-lights-on
B30: Run team loaded rate | D30: 180000 | E30: $/FTE/yr | F30: S2 COST_RUN_RATE
B31: (spare assumption row)
B32: (spare assumption row)
B34: Eligible opening cost by difficulty tier (S2 Intent Tiering, avoidance column)
B35: Tier | D35: Eligible cost base ($/yr) | F35: Effective rate | H35: Benefit ($/yr) | J35: FTE base | K35: FTE released | M35: Rates = S2 tier assumptions (CA_*). Bases = S2 eligible opening cost aggregated from the 77-intent engine.
B36: Easy (12 L2 intents) | D36: 15982020 | F36: 0.2 | H36: =D36*F36 -> 3196403.9 | J36: 738.162 | K36: =J36*F36 -> 147.6324 | M36: S2 rate: 20% of contacts avoidable
B37: Medium (43 L2 intents) | D37: 84197500 | F37: 0.1 | H37: =D37*F37 -> 8419750 | J37: 3579.664 | K37: =J37*F37 -> 357.9664 | M37: S2 rate: 10%
B38: Hard (19 L2 intents) | D38: 24449246 | F38: 0.05 | H38: =D38*F38 -> 1222462.3 | J38: 705.871 | K38: =J38*F38 -> 35.29355 | M38: S2 rate: 5%
B39: Ineligible (NEI / unmappable / no product fix) | D39: 31395771 | F39: 0 | H39: =D39*F39 -> 0 | J39: 897.612 | K39: =J39*F39 -> 0 | M39: H='No' rows + NEI + 'Others' — no benefit booked
B40: Subtotal — Eligible opening cost by difficulty tier | D40: =SUM(D36:D39) -> 1.5602454e+08 | H40: =SUM(H36:H39) -> 12838616 | J40: =SUM(J36:J39) -> 5921.309 | K40: =SUM(K36:K39) -> 540.89235
B42: 2. BENEFIT CALCULATION (steady-state annual run-rate)
B44: Total annual benefit (steady state) | D44: =$H$40 -> 12838616 | E44: $/yr | F44: Ties to S2 A1 benefit $12,838,616
B45: FTE impacted (feeds Non-FTE model SVC-6) | D45: =$K$40 -> 540.89235 | E45: # FTE | F45: Ties to S2: 540.9 FTE
B46: Closing cost (hand-off baseline to SVC-2) | D46: =$D$25-$D$44 -> 1.4318592e+08 | E46: $/yr | F46: S2: $143,185,920
B48: 3. RAMP & PHASING
B50: Months to full run rate after go-live (linear ramp) | D50: 6 | F50: Benefit starts at go-live and ramps linearly to steady state over this many months.
B51: Monthly ramp % (run-rate captured in month) | T51: =MIN(1,MAX(0,((YEAR(T$6)-YEAR($D$13))*12+MONTH(T$6)-MONTH($D$13)+0.5)/MAX($D$50,0.5))) -> 0 | U51: =MIN(1,MAX(0,((YEAR(U$6)-YEAR($D$13))*12+MONTH(U$6)-MONTH($D$13)+0.5)/MAX($D$50,0.5))) -> 0 | V51: =MIN(1,MAX(0,((YEAR(V$6)-YEAR($D$13))*12+MONTH(V$6)-MONTH($D$13)+0.5)/MAX($D$50,0.5))) -> 0 | W51: =MIN(1,MAX(0,((YEAR(W$6)-YEAR($D$13))*12+MONTH(W$6)-MONTH($D$13)+0.5)/MAX($D$50,0.5))) -> 0 | X51: =MIN(1,MAX(0,((YEAR(X$6)-YEAR($D$13))*12+MONTH(X$6)-MONTH($D$13)+0.5)/MAX($D$50,0.5))) -> 0 | Y51: =MIN(1,MAX(0,((YEAR(Y$6)-YEAR($D$13))*12+MONTH(Y$6)-MONTH($D$13)+0.5)/MAX($D$50,0.5))) -> 0 | Z51: =MIN(1,MAX(0,((YEAR(Z$6)-YEAR($D$13))*12+MONTH(Z$6)-MONTH($D$13)+0.5)/MAX($D$50,0.5))) -> 0 | AA51: =MIN(1,MAX(0,((YEAR(AA$6)-YEAR($D$13))*12+MONTH(AA$6)-MONTH($D$13)+0.5)/MAX($D$50,0.5))) -> 0 | ... CA51: =MIN(1,MAX(0,((YEAR(CA$6)-YEAR($D$13))*12+MONTH(CA$6)-MONTH($D$13)+0.5)/MAX($D$50,0.5))) -> 1
B52: Resulting average ramp % by year (info) | L52: =SUMIFS($T51:$CA51,$T$5:$CA$5,2026)/12 -> 0 | M52: =SUMIFS($T51:$CA51,$T$5:$CA$5,2027)/12 -> 0.17361111 | N52: =SUMIFS($T51:$CA51,$T$5:$CA$5,2028)/12 -> 0.99305556 | O52: =SUMIFS($T51:$CA51,$T$5:$CA$5,2029)/12 -> 1 | P52: =SUMIFS($T51:$CA51,$T$5:$CA$5,2030)/12 -> 1
B54: 4. RECURRING BENEFIT LINES ($M — these rows feed the WAVE sheet)
B56: Line (WAVE category) | D56: Baseline $M | K56: Run rate
B57: OPEX - Front-office cost reduction (avoided contacts) [OPEX] | D57: =$D$25/1000000 -> 156.02454 | K57: =SUMIFS($T57:$CA57,$T$5:$CA$5,2030) -> 12.838616 | L57: =SUMIFS($T57:$CA57,$T$5:$CA$5,2026) -> 0 | M57: =SUMIFS($T57:$CA57,$T$5:$CA$5,2027) -> 2.2289264 | N57: =SUMIFS($T57:$CA57,$T$5:$CA$5,2028) -> 12.749459 | O57: =SUMIFS($T57:$CA57,$T$5:$CA$5,2029) -> 12.838616 | P57: =SUMIFS($T57:$CA57,$T$5:$CA$5,2030) -> 12.838616 | T57: =($D$44)/1000000/12*T$51 -> 0 | U57: =($D$44)/1000000/12*U$51 -> 0 | V57: =($D$44)/1000000/12*V$51 -> 0 | W57: =($D$44)/1000000/12*W$51 -> 0 | X57: =($D$44)/1000000/12*X$51 -> 0 | Y57: =($D$44)/1000000/12*Y$51 -> 0 | Z57: =($D$44)/1000000/12*Z$51 -> 0 | AA57: =($D$44)/1000000/12*AA$51 -> 0 | ... CA57: =($D$44)/1000000/12*CA$51 -> 1.0698847
B58: Total recurring benefit ($M) | K58: =SUM(K57:K57) -> 12.838616 | L58: =SUM(L57:L57) -> 0 | M58: =SUM(M57:M57) -> 2.2289264 | N58: =SUM(N57:N57) -> 12.749459 | O58: =SUM(O57:O57) -> 12.838616 | P58: =SUM(P57:P57) -> 12.838616
B60: 5. ONE-TIME INVESTMENT — people cost by milestone (standard approach)
B62: Milestone | C62: Assumptions | D62: Team size | E62: Billing months | F62: Contingency Factor | G62: Labor Costs | H62: Start month | I62: Cap % (labor) | K62: Rate override ($/mo)
C63: Capture any assumptions on cost drivers, timelines, contingency factor etc. | E63: Months the team works at full utilization | F63: Low=10% Medium=15% High=20% Very high=50% | G63: Total labor costs for milestone | I63: Default links to Rate Card policy — type a % to override
B64: Plan / Design | C64: S2 build shape: design team of 4 for 2 months. Durations are the S2 assumption, not IO-validated delivery plans. | D64: 4 | E64: 2 | F64: 0.1 | G64: =D64*E64*IF(K64="",'Rate Card'!$G$29,K64)*(1+F64) -> 146666.67 | H64: =DATE(2027,1,1) -> 46388 | I64: ='Rate Card'!$C$45 -> 0
B65: Build / Test | C65: S2: one 8-FTE pod (PO, PM/Scrum, Tech Lead, 2 AI Eng, DevOps, QA, FA/UX) for 5 months. | D65: 8 | E65: 5 | F65: 0.1 | G65: =D65*E65*IF(K65="",'Rate Card'!$G$29,K65)*(1+F65) -> 733333.33 | H65: =DATE(2027,3,1) -> 46447 | I65: ='Rate Card'!$C$46 -> 0
B66: Pilot / Change Mgmt. | C66: S2 scale-up & rollout: 5 FTE (product roles step down) for 6 months — drives the benefit ramp. | D66: 5 | E66: 6 | F66: 0.1 | G66: =D66*E66*IF(K66="",'Rate Card'!$G$29,K66)*(1+F66) -> 550000 | H66: =DATE(2027,8,1) -> 46600 | I66: ='Rate Card'!$C$47 -> 0
B67: Scale / Run | C67: Run-phase support carried as recurring run cost (Section 6) — S2 treats run as a consolidated run team. | D67: 0 | E67: 0 | F67: 0.1 | G67: =D67*E67*IF(K67="",'Rate Card'!$G$29,K67)*(1+F67) -> 0 | H67: =DATE(2028,2,1) -> 46784 | I67: ='Rate Card'!$C$48 -> 0
B69: Milestone labor phasing ($/month, spread evenly over billing months)
B70: Plan / Design | T70: =IF(AND(T$6>=EOMONTH($H$64,0),T$6<=EOMONTH(EDATE($H$64,$E$64-1),0)),$G$64/MAX($E$64,1),0) -> 0 | U70: =IF(AND(U$6>=EOMONTH($H$64,0),U$6<=EOMONTH(EDATE($H$64,$E$64-1),0)),$G$64/MAX($E$64,1),0) -> 0 | V70: =IF(AND(V$6>=EOMONTH($H$64,0),V$6<=EOMONTH(EDATE($H$64,$E$64-1),0)),$G$64/MAX($E$64,1),0) -> 0 | W70: =IF(AND(W$6>=EOMONTH($H$64,0),W$6<=EOMONTH(EDATE($H$64,$E$64-1),0)),$G$64/MAX($E$64,1),0) -> 0 | X70: =IF(AND(X$6>=EOMONTH($H$64,0),X$6<=EOMONTH(EDATE($H$64,$E$64-1),0)),$G$64/MAX($E$64,1),0) -> 0 | Y70: =IF(AND(Y$6>=EOMONTH($H$64,0),Y$6<=EOMONTH(EDATE($H$64,$E$64-1),0)),$G$64/MAX($E$64,1),0) -> 0 | Z70: =IF(AND(Z$6>=EOMONTH($H$64,0),Z$6<=EOMONTH(EDATE($H$64,$E$64-1),0)),$G$64/MAX($E$64,1),0) -> 0 | AA70: =IF(AND(AA$6>=EOMONTH($H$64,0),AA$6<=EOMONTH(EDATE($H$64,$E$64-1),0)),$G$64/MAX($E$64,1),0) -> 0 | ... CA70: =IF(AND(CA$6>=EOMONTH($H$64,0),CA$6<=EOMONTH(EDATE($H$64,$E$64-1),0)),$G$64/MAX($E$64,1),0) -> 0
B71: Build / Test | T71: =IF(AND(T$6>=EOMONTH($H$65,0),T$6<=EOMONTH(EDATE($H$65,$E$65-1),0)),$G$65/MAX($E$65,1),0) -> 0 | U71: =IF(AND(U$6>=EOMONTH($H$65,0),U$6<=EOMONTH(EDATE($H$65,$E$65-1),0)),$G$65/MAX($E$65,1),0) -> 0 | V71: =IF(AND(V$6>=EOMONTH($H$65,0),V$6<=EOMONTH(EDATE($H$65,$E$65-1),0)),$G$65/MAX($E$65,1),0) -> 0 | W71: =IF(AND(W$6>=EOMONTH($H$65,0),W$6<=EOMONTH(EDATE($H$65,$E$65-1),0)),$G$65/MAX($E$65,1),0) -> 0 | X71: =IF(AND(X$6>=EOMONTH($H$65,0),X$6<=EOMONTH(EDATE($H$65,$E$65-1),0)),$G$65/MAX($E$65,1),0) -> 0 | Y71: =IF(AND(Y$6>=EOMONTH($H$65,0),Y$6<=EOMONTH(EDATE($H$65,$E$65-1),0)),$G$65/MAX($E$65,1),0) -> 0 | Z71: =IF(AND(Z$6>=EOMONTH($H$65,0),Z$6<=EOMONTH(EDATE($H$65,$E$65-1),0)),$G$65/MAX($E$65,1),0) -> 0 | AA71: =IF(AND(AA$6>=EOMONTH($H$65,0),AA$6<=EOMONTH(EDATE($H$65,$E$65-1),0)),$G$65/MAX($E$65,1),0) -> 0 | ... CA71: =IF(AND(CA$6>=EOMONTH($H$65,0),CA$6<=EOMONTH(EDATE($H$65,$E$65-1),0)),$G$65/MAX($E$65,1),0) -> 0
B72: Pilot / Change Mgmt. | T72: =IF(AND(T$6>=EOMONTH($H$66,0),T$6<=EOMONTH(EDATE($H$66,$E$66-1),0)),$G$66/MAX($E$66,1),0) -> 0 | U72: =IF(AND(U$6>=EOMONTH($H$66,0),U$6<=EOMONTH(EDATE($H$66,$E$66-1),0)),$G$66/MAX($E$66,1),0) -> 0 | V72: =IF(AND(V$6>=EOMONTH($H$66,0),V$6<=EOMONTH(EDATE($H$66,$E$66-1),0)),$G$66/MAX($E$66,1),0) -> 0 | W72: =IF(AND(W$6>=EOMONTH($H$66,0),W$6<=EOMONTH(EDATE($H$66,$E$66-1),0)),$G$66/MAX($E$66,1),0) -> 0 | X72: =IF(AND(X$6>=EOMONTH($H$66,0),X$6<=EOMONTH(EDATE($H$66,$E$66-1),0)),$G$66/MAX($E$66,1),0) -> 0 | Y72: =IF(AND(Y$6>=EOMONTH($H$66,0),Y$6<=EOMONTH(EDATE($H$66,$E$66-1),0)),$G$66/MAX($E$66,1),0) -> 0 | Z72: =IF(AND(Z$6>=EOMONTH($H$66,0),Z$6<=EOMONTH(EDATE($H$66,$E$66-1),0)),$G$66/MAX($E$66,1),0) -> 0 | AA72: =IF(AND(AA$6>=EOMONTH($H$66,0),AA$6<=EOMONTH(EDATE($H$66,$E$66-1),0)),$G$66/MAX($E$66,1),0) -> 0 | ... CA72: =IF(AND(CA$6>=EOMONTH($H$66,0),CA$6<=EOMONTH(EDATE($H$66,$E$66-1),0)),$G$66/MAX($E$66,1),0) -> 0
B73: Scale / Run | T73: =IF(AND(T$6>=EOMONTH($H$67,0),T$6<=EOMONTH(EDATE($H$67,$E$67-1),0)),$G$67/MAX($E$67,1),0) -> 0 | U73: =IF(AND(U$6>=EOMONTH($H$67,0),U$6<=EOMONTH(EDATE($H$67,$E$67-1),0)),$G$67/MAX($E$67,1),0) -> 0 | V73: =IF(AND(V$6>=EOMONTH($H$67,0),V$6<=EOMONTH(EDATE($H$67,$E$67-1),0)),$G$67/MAX($E$67,1),0) -> 0 | W73: =IF(AND(W$6>=EOMONTH($H$67,0),W$6<=EOMONTH(EDATE($H$67,$E$67-1),0)),$G$67/MAX($E$67,1),0) -> 0 | X73: =IF(AND(X$6>=EOMONTH($H$67,0),X$6<=EOMONTH(EDATE($H$67,$E$67-1),0)),$G$67/MAX($E$67,1),0) -> 0 | Y73: =IF(AND(Y$6>=EOMONTH($H$67,0),Y$6<=EOMONTH(EDATE($H$67,$E$67-1),0)),$G$67/MAX($E$67,1),0) -> 0 | Z73: =IF(AND(Z$6>=EOMONTH($H$67,0),Z$6<=EOMONTH(EDATE($H$67,$E$67-1),0)),$G$67/MAX($E$67,1),0) -> 0 | AA73: =IF(AND(AA$6>=EOMONTH($H$67,0),AA$6<=EOMONTH(EDATE($H$67,$E$67-1),0)),$G$67/MAX($E$67,1),0) -> 0 | ... CA73: =IF(AND(CA$6>=EOMONTH($H$67,0),CA$6<=EOMONTH(EDATE($H$67,$E$67-1),0)),$G$67/MAX($E$67,1),0) -> 0
B74: Total milestone labor (all blocks) | G74: =SUM(G64:G67) -> 1430000
B76: One-time non-labor costs (vendor, integration, licences, change mgmt., etc.)
B77: Item | C77: Assumptions / notes | D77: Total $ | E77: Spread months | H77: Start month | I77: Cap %
B78: Platform and licence set-up | C78: S2 C2 planning number ($0 for this initiative) | D78: 0 | E78: 2 | H78: =DATE(2027,3,1) -> 46447 | I78: 0
B79: Hardware and infrastructure | C79: S2 C2 planning number — no basis documented in S2; validate | D79: 120000 | E79: 5 | H79: =DATE(2027,3,1) -> 46447 | I79: 0
B80: Integration connectors | C80: S2 C2 planning number | D80: 60000 | E80: 5 | H80: =DATE(2027,3,1) -> 46447 | I80: 0
B81: Cloud compute for build & evaluation | C81: S2 C2 planning number | D81: 40000 | E81: 5 | H81: =DATE(2027,3,1) -> 46447 | I81: 0
B82: Programme management (8% of build) | C82: S2 standard: 8% x (delivery labour + other one-time) | D82: =$D$27*($G$74+$D$78+$D$79+$D$80+$D$81) -> 132000 | E82: 13 | H82: =DATE(2027,1,1) -> 46388 | I82: 0
B83: Contingency (10% of build incl. PM) | C83: S2 standard: 10% x subtotal incl. PM. Total one-time ties to S2: $1,960,200 | D83: =$D$28*($G$74+$D$78+$D$79+$D$80+$D$81+$D$82) -> 178200 | E83: 13 | H83: =DATE(2027,1,1) -> 46388 | I83: 0
B84: (spare) | D84: 0 | E84: 1 | H84: =DATE(2027,8,1) -> 46600 | I84: 0
B86: Non-labor phasing ($/month)
B87: phasing — item 1 | T87: =IF(AND(T$6>=EOMONTH($H$78,0),T$6<=EOMONTH(EDATE($H$78,$E$78-1),0)),$D$78/MAX($E$78,1),0) -> 0 | U87: =IF(AND(U$6>=EOMONTH($H$78,0),U$6<=EOMONTH(EDATE($H$78,$E$78-1),0)),$D$78/MAX($E$78,1),0) -> 0 | V87: =IF(AND(V$6>=EOMONTH($H$78,0),V$6<=EOMONTH(EDATE($H$78,$E$78-1),0)),$D$78/MAX($E$78,1),0) -> 0 | W87: =IF(AND(W$6>=EOMONTH($H$78,0),W$6<=EOMONTH(EDATE($H$78,$E$78-1),0)),$D$78/MAX($E$78,1),0) -> 0 | X87: =IF(AND(X$6>=EOMONTH($H$78,0),X$6<=EOMONTH(EDATE($H$78,$E$78-1),0)),$D$78/MAX($E$78,1),0) -> 0 | Y87: =IF(AND(Y$6>=EOMONTH($H$78,0),Y$6<=EOMONTH(EDATE($H$78,$E$78-1),0)),$D$78/MAX($E$78,1),0) -> 0 | Z87: =IF(AND(Z$6>=EOMONTH($H$78,0),Z$6<=EOMONTH(EDATE($H$78,$E$78-1),0)),$D$78/MAX($E$78,1),0) -> 0 | AA87: =IF(AND(AA$6>=EOMONTH($H$78,0),AA$6<=EOMONTH(EDATE($H$78,$E$78-1),0)),$D$78/MAX($E$78,1),0) -> 0 | ... CA87: =IF(AND(CA$6>=EOMONTH($H$78,0),CA$6<=EOMONTH(EDATE($H$78,$E$78-1),0)),$D$78/MAX($E$78,1),0) -> 0
B88: phasing — item 2 | T88: =IF(AND(T$6>=EOMONTH($H$79,0),T$6<=EOMONTH(EDATE($H$79,$E$79-1),0)),$D$79/MAX($E$79,1),0) -> 0 | U88: =IF(AND(U$6>=EOMONTH($H$79,0),U$6<=EOMONTH(EDATE($H$79,$E$79-1),0)),$D$79/MAX($E$79,1),0) -> 0 | V88: =IF(AND(V$6>=EOMONTH($H$79,0),V$6<=EOMONTH(EDATE($H$79,$E$79-1),0)),$D$79/MAX($E$79,1),0) -> 0 | W88: =IF(AND(W$6>=EOMONTH($H$79,0),W$6<=EOMONTH(EDATE($H$79,$E$79-1),0)),$D$79/MAX($E$79,1),0) -> 0 | X88: =IF(AND(X$6>=EOMONTH($H$79,0),X$6<=EOMONTH(EDATE($H$79,$E$79-1),0)),$D$79/MAX($E$79,1),0) -> 0 | Y88: =IF(AND(Y$6>=EOMONTH($H$79,0),Y$6<=EOMONTH(EDATE($H$79,$E$79-1),0)),$D$79/MAX($E$79,1),0) -> 0 | Z88: =IF(AND(Z$6>=EOMONTH($H$79,0),Z$6<=EOMONTH(EDATE($H$79,$E$79-1),0)),$D$79/MAX($E$79,1),0) -> 0 | AA88: =IF(AND(AA$6>=EOMONTH($H$79,0),AA$6<=EOMONTH(EDATE($H$79,$E$79-1),0)),$D$79/MAX($E$79,1),0) -> 0 | ... CA88: =IF(AND(CA$6>=EOMONTH($H$79,0),CA$6<=EOMONTH(EDATE($H$79,$E$79-1),0)),$D$79/MAX($E$79,1),0) -> 0
B89: phasing — item 3 | T89: =IF(AND(T$6>=EOMONTH($H$80,0),T$6<=EOMONTH(EDATE($H$80,$E$80-1),0)),$D$80/MAX($E$80,1),0) -> 0 | U89: =IF(AND(U$6>=EOMONTH($H$80,0),U$6<=EOMONTH(EDATE($H$80,$E$80-1),0)),$D$80/MAX($E$80,1),0) -> 0 | V89: =IF(AND(V$6>=EOMONTH($H$80,0),V$6<=EOMONTH(EDATE($H$80,$E$80-1),0)),$D$80/MAX($E$80,1),0) -> 0 | W89: =IF(AND(W$6>=EOMONTH($H$80,0),W$6<=EOMONTH(EDATE($H$80,$E$80-1),0)),$D$80/MAX($E$80,1),0) -> 0 | X89: =IF(AND(X$6>=EOMONTH($H$80,0),X$6<=EOMONTH(EDATE($H$80,$E$80-1),0)),$D$80/MAX($E$80,1),0) -> 0 | Y89: =IF(AND(Y$6>=EOMONTH($H$80,0),Y$6<=EOMONTH(EDATE($H$80,$E$80-1),0)),$D$80/MAX($E$80,1),0) -> 0 | Z89: =IF(AND(Z$6>=EOMONTH($H$80,0),Z$6<=EOMONTH(EDATE($H$80,$E$80-1),0)),$D$80/MAX($E$80,1),0) -> 0 | AA89: =IF(AND(AA$6>=EOMONTH($H$80,0),AA$6<=EOMONTH(EDATE($H$80,$E$80-1),0)),$D$80/MAX($E$80,1),0) -> 0 | ... CA89: =IF(AND(CA$6>=EOMONTH($H$80,0),CA$6<=EOMONTH(EDATE($H$80,$E$80-1),0)),$D$80/MAX($E$80,1),0) -> 0
B90: phasing — item 4 | T90: =IF(AND(T$6>=EOMONTH($H$81,0),T$6<=EOMONTH(EDATE($H$81,$E$81-1),0)),$D$81/MAX($E$81,1),0) -> 0 | U90: =IF(AND(U$6>=EOMONTH($H$81,0),U$6<=EOMONTH(EDATE($H$81,$E$81-1),0)),$D$81/MAX($E$81,1),0) -> 0 | V90: =IF(AND(V$6>=EOMONTH($H$81,0),V$6<=EOMONTH(EDATE($H$81,$E$81-1),0)),$D$81/MAX($E$81,1),0) -> 0 | W90: =IF(AND(W$6>=EOMONTH($H$81,0),W$6<=EOMONTH(EDATE($H$81,$E$81-1),0)),$D$81/MAX($E$81,1),0) -> 0 | X90: =IF(AND(X$6>=EOMONTH($H$81,0),X$6<=EOMONTH(EDATE($H$81,$E$81-1),0)),$D$81/MAX($E$81,1),0) -> 0 | Y90: =IF(AND(Y$6>=EOMONTH($H$81,0),Y$6<=EOMONTH(EDATE($H$81,$E$81-1),0)),$D$81/MAX($E$81,1),0) -> 0 | Z90: =IF(AND(Z$6>=EOMONTH($H$81,0),Z$6<=EOMONTH(EDATE($H$81,$E$81-1),0)),$D$81/MAX($E$81,1),0) -> 0 | AA90: =IF(AND(AA$6>=EOMONTH($H$81,0),AA$6<=EOMONTH(EDATE($H$81,$E$81-1),0)),$D$81/MAX($E$81,1),0) -> 0 | ... CA90: =IF(AND(CA$6>=EOMONTH($H$81,0),CA$6<=EOMONTH(EDATE($H$81,$E$81-1),0)),$D$81/MAX($E$81,1),0) -> 0
B91: phasing — item 5 | T91: =IF(AND(T$6>=EOMONTH($H$82,0),T$6<=EOMONTH(EDATE($H$82,$E$82-1),0)),$D$82/MAX($E$82,1),0) -> 0 | U91: =IF(AND(U$6>=EOMONTH($H$82,0),U$6<=EOMONTH(EDATE($H$82,$E$82-1),0)),$D$82/MAX($E$82,1),0) -> 0 | V91: =IF(AND(V$6>=EOMONTH($H$82,0),V$6<=EOMONTH(EDATE($H$82,$E$82-1),0)),$D$82/MAX($E$82,1),0) -> 0 | W91: =IF(AND(W$6>=EOMONTH($H$82,0),W$6<=EOMONTH(EDATE($H$82,$E$82-1),0)),$D$82/MAX($E$82,1),0) -> 0 | X91: =IF(AND(X$6>=EOMONTH($H$82,0),X$6<=EOMONTH(EDATE($H$82,$E$82-1),0)),$D$82/MAX($E$82,1),0) -> 0 | Y91: =IF(AND(Y$6>=EOMONTH($H$82,0),Y$6<=EOMONTH(EDATE($H$82,$E$82-1),0)),$D$82/MAX($E$82,1),0) -> 0 | Z91: =IF(AND(Z$6>=EOMONTH($H$82,0),Z$6<=EOMONTH(EDATE($H$82,$E$82-1),0)),$D$82/MAX($E$82,1),0) -> 0 | AA91: =IF(AND(AA$6>=EOMONTH($H$82,0),AA$6<=EOMONTH(EDATE($H$82,$E$82-1),0)),$D$82/MAX($E$82,1),0) -> 0 | ... CA91: =IF(AND(CA$6>=EOMONTH($H$82,0),CA$6<=EOMONTH(EDATE($H$82,$E$82-1),0)),$D$82/MAX($E$82,1),0) -> 0
B92: phasing — item 6 | T92: =IF(AND(T$6>=EOMONTH($H$83,0),T$6<=EOMONTH(EDATE($H$83,$E$83-1),0)),$D$83/MAX($E$83,1),0) -> 0 | U92: =IF(AND(U$6>=EOMONTH($H$83,0),U$6<=EOMONTH(EDATE($H$83,$E$83-1),0)),$D$83/MAX($E$83,1),0) -> 0 | V92: =IF(AND(V$6>=EOMONTH($H$83,0),V$6<=EOMONTH(EDATE($H$83,$E$83-1),0)),$D$83/MAX($E$83,1),0) -> 0 | W92: =IF(AND(W$6>=EOMONTH($H$83,0),W$6<=EOMONTH(EDATE($H$83,$E$83-1),0)),$D$83/MAX($E$83,1),0) -> 0 | X92: =IF(AND(X$6>=EOMONTH($H$83,0),X$6<=EOMONTH(EDATE($H$83,$E$83-1),0)),$D$83/MAX($E$83,1),0) -> 0 | Y92: =IF(AND(Y$6>=EOMONTH($H$83,0),Y$6<=EOMONTH(EDATE($H$83,$E$83-1),0)),$D$83/MAX($E$83,1),0) -> 0 | Z92: =IF(AND(Z$6>=EOMONTH($H$83,0),Z$6<=EOMONTH(EDATE($H$83,$E$83-1),0)),$D$83/MAX($E$83,1),0) -> 0 | AA92: =IF(AND(AA$6>=EOMONTH($H$83,0),AA$6<=EOMONTH(EDATE($H$83,$E$83-1),0)),$D$83/MAX($E$83,1),0) -> 0 | ... CA92: =IF(AND(CA$6>=EOMONTH($H$83,0),CA$6<=EOMONTH(EDATE($H$83,$E$83-1),0)),$D$83/MAX($E$83,1),0) -> 0
B93: phasing — item 7 | T93: =IF(AND(T$6>=EOMONTH($H$84,0),T$6<=EOMONTH(EDATE($H$84,$E$84-1),0)),$D$84/MAX($E$84,1),0) -> 0 | U93: =IF(AND(U$6>=EOMONTH($H$84,0),U$6<=EOMONTH(EDATE($H$84,$E$84-1),0)),$D$84/MAX($E$84,1),0) -> 0 | V93: =IF(AND(V$6>=EOMONTH($H$84,0),V$6<=EOMONTH(EDATE($H$84,$E$84-1),0)),$D$84/MAX($E$84,1),0) -> 0 | W93: =IF(AND(W$6>=EOMONTH($H$84,0),W$6<=EOMONTH(EDATE($H$84,$E$84-1),0)),$D$84/MAX($E$84,1),0) -> 0 | X93: =IF(AND(X$6>=EOMONTH($H$84,0),X$6<=EOMONTH(EDATE($H$84,$E$84-1),0)),$D$84/MAX($E$84,1),0) -> 0 | Y93: =IF(AND(Y$6>=EOMONTH($H$84,0),Y$6<=EOMONTH(EDATE($H$84,$E$84-1),0)),$D$84/MAX($E$84,1),0) -> 0 | Z93: =IF(AND(Z$6>=EOMONTH($H$84,0),Z$6<=EOMONTH(EDATE($H$84,$E$84-1),0)),$D$84/MAX($E$84,1),0) -> 0 | AA93: =IF(AND(AA$6>=EOMONTH($H$84,0),AA$6<=EOMONTH(EDATE($H$84,$E$84-1),0)),$D$84/MAX($E$84,1),0) -> 0 | ... CA93: =IF(AND(CA$6>=EOMONTH($H$84,0),CA$6<=EOMONTH(EDATE($H$84,$E$84-1),0)),$D$84/MAX($E$84,1),0) -> 0
B95: One-time investment feed rows ($M — these feed the WAVE sheet)
B96: CAPEX — capitalized build labor | L96: =SUMIFS($T96:$CA96,$T$5:$CA$5,2026) -> 0 | M96: =SUMIFS($T96:$CA96,$T$5:$CA$5,2027) -> 0 | N96: =SUMIFS($T96:$CA96,$T$5:$CA$5,2028) -> 0 | O96: =SUMIFS($T96:$CA96,$T$5:$CA$5,2029) -> 0 | P96: =SUMIFS($T96:$CA96,$T$5:$CA$5,2030) -> 0 | T96: =(SUMPRODUCT(T70:T73,$I$64:$I$67))/1000000 -> 0 | U96: =(SUMPRODUCT(U70:U73,$I$64:$I$67))/1000000 -> 0 | V96: =(SUMPRODUCT(V70:V73,$I$64:$I$67))/1000000 -> 0 | W96: =(SUMPRODUCT(W70:W73,$I$64:$I$67))/1000000 -> 0 | X96: =(SUMPRODUCT(X70:X73,$I$64:$I$67))/1000000 -> 0 | Y96: =(SUMPRODUCT(Y70:Y73,$I$64:$I$67))/1000000 -> 0 | Z96: =(SUMPRODUCT(Z70:Z73,$I$64:$I$67))/1000000 -> 0 | AA96: =(SUMPRODUCT(AA70:AA73,$I$64:$I$67))/1000000 -> 0 | ... CA96: =(SUMPRODUCT(CA70:CA73,$I$64:$I$67))/1000000 -> 0
B97: CAPEX — capitalized non-labor | L97: =SUMIFS($T97:$CA97,$T$5:$CA$5,2026) -> 0 | M97: =SUMIFS($T97:$CA97,$T$5:$CA$5,2027) -> 0 | N97: =SUMIFS($T97:$CA97,$T$5:$CA$5,2028) -> 0 | O97: =SUMIFS($T97:$CA97,$T$5:$CA$5,2029) -> 0 | P97: =SUMIFS($T97:$CA97,$T$5:$CA$5,2030) -> 0 | T97: =SUMPRODUCT(T87:T93,$I$78:$I$84)/1000000 -> 0 | U97: =SUMPRODUCT(U87:U93,$I$78:$I$84)/1000000 -> 0 | V97: =SUMPRODUCT(V87:V93,$I$78:$I$84)/1000000 -> 0 | W97: =SUMPRODUCT(W87:W93,$I$78:$I$84)/1000000 -> 0 | X97: =SUMPRODUCT(X87:X93,$I$78:$I$84)/1000000 -> 0 | Y97: =SUMPRODUCT(Y87:Y93,$I$78:$I$84)/1000000 -> 0 | Z97: =SUMPRODUCT(Z87:Z93,$I$78:$I$84)/1000000 -> 0 | AA97: =SUMPRODUCT(AA87:AA93,$I$78:$I$84)/1000000 -> 0 | ... CA97: =SUMPRODUCT(CA87:CA93,$I$78:$I$84)/1000000 -> 0
B98: OTC — build labor (expensed) | L98: =SUMIFS($T98:$CA98,$T$5:$CA$5,2026) -> 0 | M98: =SUMIFS($T98:$CA98,$T$5:$CA$5,2027) -> 1.3383333 | N98: =SUMIFS($T98:$CA98,$T$5:$CA$5,2028) -> 0.091666667 | O98: =SUMIFS($T98:$CA98,$T$5:$CA$5,2029) -> 0 | P98: =SUMIFS($T98:$CA98,$T$5:$CA$5,2030) -> 0 | T98: =(SUMPRODUCT(T70:T73,1-$I$64:$I$67))/1000000 -> 0 | U98: =(SUMPRODUCT(U70:U73,1-$I$64:$I$67))/1000000 -> 0 | V98: =(SUMPRODUCT(V70:V73,1-$I$64:$I$67))/1000000 -> 0 | W98: =(SUMPRODUCT(W70:W73,1-$I$64:$I$67))/1000000 -> 0 | X98: =(SUMPRODUCT(X70:X73,1-$I$64:$I$67))/1000000 -> 0 | Y98: =(SUMPRODUCT(Y70:Y73,1-$I$64:$I$67))/1000000 -> 0 | Z98: =(SUMPRODUCT(Z70:Z73,1-$I$64:$I$67))/1000000 -> 0 | AA98: =(SUMPRODUCT(AA70:AA73,1-$I$64:$I$67))/1000000 -> 0 | ... CA98: =(SUMPRODUCT(CA70:CA73,1-$I$64:$I$67))/1000000 -> 0
B99: OTC — non-labor (expensed) | L99: =SUMIFS($T99:$CA99,$T$5:$CA$5,2026) -> 0 | M99: =SUMIFS($T99:$CA99,$T$5:$CA$5,2027) -> 0.50633846 | N99: =SUMIFS($T99:$CA99,$T$5:$CA$5,2028) -> 0.023861538 | O99: =SUMIFS($T99:$CA99,$T$5:$CA$5,2029) -> 0 | P99: =SUMIFS($T99:$CA99,$T$5:$CA$5,2030) -> 0 | T99: =SUMPRODUCT(T87:T93,1-$I$78:$I$84)/1000000 -> 0 | U99: =SUMPRODUCT(U87:U93,1-$I$78:$I$84)/1000000 -> 0 | V99: =SUMPRODUCT(V87:V93,1-$I$78:$I$84)/1000000 -> 0 | W99: =SUMPRODUCT(W87:W93,1-$I$78:$I$84)/1000000 -> 0 | X99: =SUMPRODUCT(X87:X93,1-$I$78:$I$84)/1000000 -> 0 | Y99: =SUMPRODUCT(Y87:Y93,1-$I$78:$I$84)/1000000 -> 0 | Z99: =SUMPRODUCT(Z87:Z93,1-$I$78:$I$84)/1000000 -> 0 | AA99: =SUMPRODUCT(AA87:AA93,1-$I$78:$I$84)/1000000 -> 0 | ... CA99: =SUMPRODUCT(CA87:CA93,1-$I$78:$I$84)/1000000 -> 0
B100: Total one-time investment ($M) | L100: =SUM(L96:L99) -> 0 | M100: =SUM(M96:M99) -> 1.8446718 | N100: =SUM(N96:N99) -> 0.11552821 | O100: =SUM(O96:O99) -> 0 | P100: =SUM(P96:P99) -> 0
B102: 6. RECURRING RUN COSTS to achieve impact
B104: Line | C104: Assumptions / notes | D104: Annual $ (steady state) | H104: Start month | I104: Scales with ramp? (Y/N)
B105: OPEX - Run team (keep-the-lights-on) | C105: S2 C3: 2.0 FTE x $180k | D105: =$D$29*$D$30 -> 360000 | H105: =DATE(2027,8,1) -> 46600 | I105: N
B106: OPEX - Vendor support & maintenance | C106: S2 C3 planning number | D106: 100000 | H106: =DATE(2027,8,1) -> 46600 | I106: N
B107: OPEX - Incremental infrastructure | C107: S2 C3 planning number | D107: 40000 | H107: =DATE(2027,8,1) -> 46600 | I107: N
B109: Run-cost feed rows ($M)
B110: OPEX - Run team (keep-the-lights-on) [RUN] | K110: =SUMIFS($T110:$CA110,$T$5:$CA$5,2030) -> 0.36 | L110: =SUMIFS($T110:$CA110,$T$5:$CA$5,2026) -> 0 | M110: =SUMIFS($T110:$CA110,$T$5:$CA$5,2027) -> 0.15 | N110: =SUMIFS($T110:$CA110,$T$5:$CA$5,2028) -> 0.36 | O110: =SUMIFS($T110:$CA110,$T$5:$CA$5,2029) -> 0.36 | P110: =SUMIFS($T110:$CA110,$T$5:$CA$5,2030) -> 0.36 | T110: =$D$105/1000000/12*IF($I$105="Y",T$51,IF(T$6>=EOMONTH($H$105,0),1,0)) -> 0 | U110: =$D$105/1000000/12*IF($I$105="Y",U$51,IF(U$6>=EOMONTH($H$105,0),1,0)) -> 0 | V110: =$D$105/1000000/12*IF($I$105="Y",V$51,IF(V$6>=EOMONTH($H$105,0),1,0)) -> 0 | W110: =$D$105/1000000/12*IF($I$105="Y",W$51,IF(W$6>=EOMONTH($H$105,0),1,0)) -> 0 | X110: =$D$105/1000000/12*IF($I$105="Y",X$51,IF(X$6>=EOMONTH($H$105,0),1,0)) -> 0 | Y110: =$D$105/1000000/12*IF($I$105="Y",Y$51,IF(Y$6>=EOMONTH($H$105,0),1,0)) -> 0 | Z110: =$D$105/1000000/12*IF($I$105="Y",Z$51,IF(Z$6>=EOMONTH($H$105,0),1,0)) -> 0 | AA110: =$D$105/1000000/12*IF($I$105="Y",AA$51,IF(AA$6>=EOMONTH($H$105,0),1,0)) -> 0 | ... CA110: =$D$105/1000000/12*IF($I$105="Y",CA$51,IF(CA$6>=EOMONTH($H$105,0),1,0)) -> 0.03
B111: OPEX - Vendor support & maintenance [RUN] | K111: =SUMIFS($T111:$CA111,$T$5:$CA$5,2030) -> 0.1 | L111: =SUMIFS($T111:$CA111,$T$5:$CA$5,2026) -> 0 | M111: =SUMIFS($T111:$CA111,$T$5:$CA$5,2027) -> 0.041666667 | N111: =SUMIFS($T111:$CA111,$T$5:$CA$5,2028) -> 0.1 | O111: =SUMIFS($T111:$CA111,$T$5:$CA$5,2029) -> 0.1 | P111: =SUMIFS($T111:$CA111,$T$5:$CA$5,2030) -> 0.1 | T111: =$D$106/1000000/12*IF($I$106="Y",T$51,IF(T$6>=EOMONTH($H$106,0),1,0)) -> 0 | U111: =$D$106/1000000/12*IF($I$106="Y",U$51,IF(U$6>=EOMONTH($H$106,0),1,0)) -> 0 | V111: =$D$106/1000000/12*IF($I$106="Y",V$51,IF(V$6>=EOMONTH($H$106,0),1,0)) -> 0 | W111: =$D$106/1000000/12*IF($I$106="Y",W$51,IF(W$6>=EOMONTH($H$106,0),1,0)) -> 0 | X111: =$D$106/1000000/12*IF($I$106="Y",X$51,IF(X$6>=EOMONTH($H$106,0),1,0)) -> 0 | Y111: =$D$106/1000000/12*IF($I$106="Y",Y$51,IF(Y$6>=EOMONTH($H$106,0),1,0)) -> 0 | Z111: =$D$106/1000000/12*IF($I$106="Y",Z$51,IF(Z$6>=EOMONTH($H$106,0),1,0)) -> 0 | AA111: =$D$106/1000000/12*IF($I$106="Y",AA$51,IF(AA$6>=EOMONTH($H$106,0),1,0)) -> 0 | ... CA111: =$D$106/1000000/12*IF($I$106="Y",CA$51,IF(CA$6>=EOMONTH($H$106,0),1,0)) -> 0.0083333333
B112: OPEX - Incremental infrastructure [RUN] | K112: =SUMIFS($T112:$CA112,$T$5:$CA$5,2030) -> 0.04 | L112: =SUMIFS($T112:$CA112,$T$5:$CA$5,2026) -> 0 | M112: =SUMIFS($T112:$CA112,$T$5:$CA$5,2027) -> 0.016666667 | N112: =SUMIFS($T112:$CA112,$T$5:$CA$5,2028) -> 0.04 | O112: =SUMIFS($T112:$CA112,$T$5:$CA$5,2029) -> 0.04 | P112: =SUMIFS($T112:$CA112,$T$5:$CA$5,2030) -> 0.04 | T112: =$D$107/1000000/12*IF($I$107="Y",T$51,IF(T$6>=EOMONTH($H$107,0),1,0)) -> 0 | U112: =$D$107/1000000/12*IF($I$107="Y",U$51,IF(U$6>=EOMONTH($H$107,0),1,0)) -> 0 | V112: =$D$107/1000000/12*IF($I$107="Y",V$51,IF(V$6>=EOMONTH($H$107,0),1,0)) -> 0 | W112: =$D$107/1000000/12*IF($I$107="Y",W$51,IF(W$6>=EOMONTH($H$107,0),1,0)) -> 0 | X112: =$D$107/1000000/12*IF($I$107="Y",X$51,IF(X$6>=EOMONTH($H$107,0),1,0)) -> 0 | Y112: =$D$107/1000000/12*IF($I$107="Y",Y$51,IF(Y$6>=EOMONTH($H$107,0),1,0)) -> 0 | Z112: =$D$107/1000000/12*IF($I$107="Y",Z$51,IF(Z$6>=EOMONTH($H$107,0),1,0)) -> 0 | AA112: =$D$107/1000000/12*IF($I$107="Y",AA$51,IF(AA$6>=EOMONTH($H$107,0),1,0)) -> 0 | ... CA112: =$D$107/1000000/12*IF($I$107="Y",CA$51,IF(CA$6>=EOMONTH($H$107,0),1,0)) -> 0.0033333333
B113: Total run cost ($M) | K113: =SUM(K110:K112) -> 0.5 | L113: =SUM(L110:L112) -> 0 | M113: =SUM(M110:M112) -> 0.20833333 | N113: =SUM(N110:N112) -> 0.5 | O113: =SUM(O110:O112) -> 0.5 | P113: =SUM(P110:P112) -> 0.5
B115: 7. WAVE MAPPING (reference)
B117: Model row 57 — OPEX - Front-office cost reduction (avoided contacts) | F117: → WAVE row 79 (Section II — Recurring Benefits)
B118: Model row 110 — OPEX - Run team (keep-the-lights-on) | F118: → WAVE row 107 (Section II — Recurring Costs)
B119: Model row 111 — OPEX - Vendor support & maintenance | F119: → WAVE row 108 (Section II — Recurring Costs)
B120: Model row 112 — OPEX - Incremental infrastructure | F120: → WAVE row 109 (Section II — Recurring Costs)
B121: Model row 96 — CAPEX — capitalized build labor | F121: → WAVE row 136 (Section III — CapEx)
B122: Model row 97 — CAPEX — capitalized non-labor | F122: → WAVE row 137 (Section III — CapEx)
B123: Model row 98 — OTC — build labor (expensed) | F123: → WAVE row 141 (Section III — OTC)
B124: Model row 99 — OTC — non-labor (expensed) | F124: → WAVE row 142 (Section III — OTC)
B126: 8. FLEX / SCRATCH AREA — free space for refinements with the initiative owner

Sheet SVC-1 WAVE
L1: 1 | M1: 2 | N1: 3 | O1: 4 | P1: 5 | R1: =COUNTIFS($R$66:$R$117, "Error") -> 0 | T1: 2026 | U1: 2026 | V1: 2026 | W1: 2026 | X1: 2026 | Y1: 2026 | Z1: 2026 | AA1: 2026 | AB1: 2026 | AC1: 2026 | AD1: 2026 | AE1: 2026 | AF1: 2027 | AG1: 2027 | AH1: 2027 | AI1: 2027 | AJ1: 2027 | AK1: 2027 | AL1: 2027 | AM1: 2027 | AN1: 2027 | AO1: 2027 | AP1: 2027 | AQ1: 2027 | AR1: 2028 | AS1: 2028 | AT1: 2028 | AU1: 2028 | AV1: 2028 | AW1: 2028 | AX1: 2028 | AY1: 2028 | AZ1: 2028 | BA1: 2028 | BB1: 2028 | BC1: 2028 | BD1: 2029 | BE1: 2029 | BF1: 2029 | BG1: 2029 | BH1: 2029 | BI1: 2029 | BJ1: 2029 | BK1: 2029 | BL1: 2029 | BM1: 2029 | BN1: 2029 | BO1: 2029 | BP1: 2030 | BQ1: 2030 | BR1: 2030 | BS1: 2030 | BT1: 2030 | BU1: 2030 | BV1: 2030 | BW1: 2030 | BX1: 2030 | BY1: 2030 | BZ1: 2030 | CA1: 2030 | CI1: =COUNTIFS(CI$66:CI$149, "FALSE") -> 0 | CJ1: =COUNTIFS(CJ$66:CJ$149, "FALSE") -> 0 | CK1: =COUNTIFS(CK$66:CK$149, "FALSE") -> 0 | CL1: =COUNTIFS(CL$66:CL$149, "FALSE") -> 0 | CM1: =COUNTIFS(CM$66:CM$149, "FALSE") -> 0
C2: ="#"&$F$6&" Initiative Business Case" -> #TBD Initiative Business Case
C4: INPUTS & ASSUMPTIONS
D6: Initiative # | F6: TBD
D7: Initiative Owner | F7: Servicing IO — TBC (pool: Jackie Yu, Matt Anderson, Bob Hurst)
D8: Initiative Name | F8: Prevent avoidable contacts at source through product fixes and upstream journey improvements
D11: Estimated L4 date | F11: ='SVC-1 Model'!$D$13 -> 46600
D12: Net Recurring Benefit ($M) | F12: =$K$117 -> 12.338616
C14: SECTION I - PRIMARY VALUE DRIVER (ILLUSTRATIVE)
D16: Primary value driver — linked to the Model sheet; refine with the initiative owner
D17: Baseline | H17: Period | I17: KPI | J17: Inputs
E18: Front-office servicing cost baseline (annualized) | H18: Jan–Jul 2026 x 12/7 | I18: $USD M | J18: ='SVC-1 Model'!$D$25/1000000 -> 156.02454
E19: Eligible base (Easy+Medium+Hard tiers) | H19: same | I19: $USD M | J19: =('SVC-1 Model'!$D$25-'SVC-1 Model'!$D$39)/1000000 -> 124.62877
E20: Implied front-office FTE (S2 A0) | H20: same | I20: # FTE | J20: ='SVC-1 Model'!$J$40 -> 5921.309
D23: Goal
E24: Blended avoidance rate on opening cost | H24: Steady state | I24: % | J24: ='SVC-1 Model'!$D$44/'SVC-1 Model'!$D$25 -> 0.082285879
E25: FTE impacted | H25: Steady state | I25: # FTE | J25: ='SVC-1 Model'!$D$45 -> 540.89235
D28: Incremental Improvement
E29: Annual benefit (run rate) | I29: $USD M | J29: ='SVC-1 Model'!$D$44/1000000 -> 12.838616
C60: SECTION II - NET RECURRING BENEFITS | CC60: ANNUAL SUMMARY | CI60: CHECK CELLS
T62: 2026 | AF62: 2027 | AR62: 2028 | BD62: 2029 | BP62: 2030 | CI62: CHECK
D63: RECURRING BENEFITS | H63: Comment | I63: Baseline | J63: Goal | K63: Ann. Run Rate | L63: 2026 | M63: =L63+1 -> 2027 | N63: =M63+1 -> 2028 | O63: =N63+1 -> 2029 | P63: =O63+1 -> 2030 | Q63: Impacted BU | R63: Check | T63: 46023 | U63: =EOMONTH(T63, 1) -> 46081 | V63: =EOMONTH(U63, 1) -> 46112 | W63: =EOMONTH(V63, 1) -> 46142 | X63: =EOMONTH(W63, 1) -> 46173 | Y63: =EOMONTH(X63, 1) -> 46203 | Z63: =EOMONTH(Y63, 1) -> 46234 | AA63: =EOMONTH(Z63, 1) -> 46265 | AB63: =EOMONTH(AA63, 1) -> 46295 | ... CA63: =EOMONTH(BZ63, 1) -> 47848 | CC63: 2026 | CD63: =CC63+1 -> 2027 | CE63: =CD63+1 -> 2028 | CF63: =CE63+1 -> 2029 | CG63: =CF63+1 -> 2030 | CI63: 2026 | CJ63: =CI63+1 -> 2027 | CK63: =CJ63+1 -> 2028 | CL63: =CK63+1 -> 2029 | CM63: =CL63+1 -> 2030
E64: $USD M | I64: =$H$18 -> Jan–Jul 2026 x 12/7 | J64: Future State | K64: Increment
E65: Revenue
I66: 0 | J66: 0 | K66: =J66-I66 -> 0 | R66: =IF(K66=P66, "", "Error") | CC66: =SUMIFS($T66:$CA66, $T$1:$CA$1, CC$63) -> 0 | CD66: =SUMIFS($T66:$CA66, $T$1:$CA$1, CD$63) -> 0 | CE66: =SUMIFS($T66:$CA66, $T$1:$CA$1, CE$63) -> 0 | CF66: =SUMIFS($T66:$CA66, $T$1:$CA$1, CF$63) -> 0 | CG66: =SUMIFS($T66:$CA66, $T$1:$CA$1, CG$63) -> 0 | CI66: =CC66=L66 -> 1 | CJ66: =CD66=M66 -> 1 | CK66: =CE66=N66 -> 1 | CL66: =CF66=O66 -> 1 | CM66: =CG66=P66 -> 1
I67: 0 | J67: 0 | K67: =J67-I67 -> 0 | R67: =IF(K67=P67, "", "Error") | CC67: =SUMIFS($T67:$CA67, $T$1:$CA$1, CC$63) -> 0 | CD67: =SUMIFS($T67:$CA67, $T$1:$CA$1, CD$63) -> 0 | CE67: =SUMIFS($T67:$CA67, $T$1:$CA$1, CE$63) -> 0 | CF67: =SUMIFS($T67:$CA67, $T$1:$CA$1, CF$63) -> 0 | CG67: =SUMIFS($T67:$CA67, $T$1:$CA$1, CG$63) -> 0 | CI67: =CC67=L67 -> 1 | CJ67: =CD67=M67 -> 1 | CK67: =CE67=N67 -> 1 | CL67: =CF67=O67 -> 1 | CM67: =CG67=P67 -> 1
E68: Revenue Subtotal | I68: =SUM(I66:I67) -> 0 | J68: =SUM(J66:J67) -> 0 | K68: =SUM(K66:K67) -> 0 | L68: =SUM(L66:L67) -> 0 | M68: =SUM(M66:M67) -> 0 | N68: =SUM(N66:N67) -> 0 | O68: =SUM(O66:O67) -> 0 | P68: =SUM(P66:P67) -> 0 | T68: =SUM(T66:T67) -> 0 | U68: =SUM(U66:U67) -> 0 | V68: =SUM(V66:V67) -> 0 | W68: =SUM(W66:W67) -> 0 | X68: =SUM(X66:X67) -> 0 | Y68: =SUM(Y66:Y67) -> 0 | Z68: =SUM(Z66:Z67) -> 0 | AA68: =SUM(AA66:AA67) -> 0 | ... CA68: =SUM(CA66:CA67) -> 0 | CC68: =SUM(CC66:CC67) -> 0 | CD68: =SUM(CD66:CD67) -> 0 | CE68: =SUM(CE66:CE67) -> 0 | CF68: =SUM(CF66:CF67) -> 0 | CG68: =SUM(CG66:CG67) -> 0 | CI68: =CC68=L68 -> 1 | CJ68: =CD68=M68 -> 1 | CK68: =CE68=N68 -> 1 | CL68: =CF68=O68 -> 1 | CM68: =CG68=P68 -> 1
E70: Cost of Sales
K71: =I71-J71 -> 0 | R71: =IF(K71=P71, "", "Error") | CC71: =SUMIFS($T71:$CA71, $T$1:$CA$1, CC$63) -> 0 | CD71: =SUMIFS($T71:$CA71, $T$1:$CA$1, CD$63) -> 0 | CE71: =SUMIFS($T71:$CA71, $T$1:$CA$1, CE$63) -> 0 | CF71: =SUMIFS($T71:$CA71, $T$1:$CA$1, CF$63) -> 0 | CG71: =SUMIFS($T71:$CA71, $T$1:$CA$1, CG$63) -> 0 | CI71: =CC71=L71 -> 1 | CJ71: =CD71=M71 -> 1 | CK71: =CE71=N71 -> 1 | CL71: =CF71=O71 -> 1 | CM71: =CG71=P71 -> 1
I72: 0 | J72: 0 | K72: =I72-J72 -> 0 | R72: =IF(K72=P72, "", "Error") | CC72: =SUMIFS($T72:$CA72, $T$1:$CA$1, CC$63) -> 0 | CD72: =SUMIFS($T72:$CA72, $T$1:$CA$1, CD$63) -> 0 | CE72: =SUMIFS($T72:$CA72, $T$1:$CA$1, CE$63) -> 0 | CF72: =SUMIFS($T72:$CA72, $T$1:$CA$1, CF$63) -> 0 | CG72: =SUMIFS($T72:$CA72, $T$1:$CA$1, CG$63) -> 0 | CI72: =CC72=L72 -> 1 | CJ72: =CD72=M72 -> 1 | CK72: =CE72=N72 -> 1 | CL72: =CF72=O72 -> 1 | CM72: =CG72=P72 -> 1
I73: 0 | J73: 0 | K73: =I73-J73 -> 0 | R73: =IF(K73=P73, "", "Error") | CC73: =SUMIFS($T73:$CA73, $T$1:$CA$1, CC$63) -> 0 | CD73: =SUMIFS($T73:$CA73, $T$1:$CA$1, CD$63) -> 0 | CE73: =SUMIFS($T73:$CA73, $T$1:$CA$1, CE$63) -> 0 | CF73: =SUMIFS($T73:$CA73, $T$1:$CA$1, CF$63) -> 0 | CG73: =SUMIFS($T73:$CA73, $T$1:$CA$1, CG$63) -> 0 | CI73: =CC73=L73 -> 1 | CJ73: =CD73=M73 -> 1 | CK73: =CE73=N73 -> 1 | CL73: =CF73=O73 -> 1 | CM73: =CG73=P73 -> 1
I74: 0 | J74: 0 | K74: =I74-J74 -> 0 | R74: =IF(K74=P74, "", "Error") | CC74: =SUMIFS($T74:$CA74, $T$1:$CA$1, CC$63) -> 0 | CD74: =SUMIFS($T74:$CA74, $T$1:$CA$1, CD$63) -> 0 | CE74: =SUMIFS($T74:$CA74, $T$1:$CA$1, CE$63) -> 0 | CF74: =SUMIFS($T74:$CA74, $T$1:$CA$1, CF$63) -> 0 | CG74: =SUMIFS($T74:$CA74, $T$1:$CA$1, CG$63) -> 0 | CI74: =CC74=L74 -> 1 | CJ74: =CD74=M74 -> 1 | CK74: =CE74=N74 -> 1 | CL74: =CF74=O74 -> 1 | CM74: =CG74=P74 -> 1
K75: =I75-J75 -> 0 | R75: =IF(K75=P75, "", "Error") | CC75: =SUMIFS($T75:$CA75, $T$1:$CA$1, CC$63) -> 0 | CD75: =SUMIFS($T75:$CA75, $T$1:$CA$1, CD$63) -> 0 | CE75: =SUMIFS($T75:$CA75, $T$1:$CA$1, CE$63) -> 0 | CF75: =SUMIFS($T75:$CA75, $T$1:$CA$1, CF$63) -> 0 | CG75: =SUMIFS($T75:$CA75, $T$1:$CA$1, CG$63) -> 0 | CI75: =CC75=L75 -> 1 | CJ75: =CD75=M75 -> 1 | CK75: =CE75=N75 -> 1 | CL75: =CF75=O75 -> 1 | CM75: =CG75=P75 -> 1
E76: Cost of Sales Subtotal | I76: =SUM(I71:I75) -> 0 | J76: =SUM(J71:J75) -> 0 | K76: =SUM(K71:K75) -> 0 | L76: =SUM(L71:L75) -> 0 | M76: =SUM(M71:M75) -> 0 | N76: =SUM(N71:N75) -> 0 | O76: =SUM(O71:O75) -> 0 | P76: =SUM(P71:P75) -> 0 | T76: =SUM(T71:T75) -> 0 | U76: =SUM(U71:U75) -> 0 | V76: =SUM(V71:V75) -> 0 | W76: =SUM(W71:W75) -> 0 | X76: =SUM(X71:X75) -> 0 | Y76: =SUM(Y71:Y75) -> 0 | Z76: =SUM(Z71:Z75) -> 0 | AA76: =SUM(AA71:AA75) -> 0 | ... CA76: =SUM(CA71:CA75) -> 0 | CC76: =SUM(CC71:CC75) -> 0 | CD76: =SUM(CD71:CD75) -> 0 | CE76: =SUM(CE71:CE75) -> 0 | CF76: =SUM(CF71:CF75) -> 0 | CG76: =SUM(CG71:CG75) -> 0 | CI76: =CC76=L76 -> 1 | CJ76: =CD76=M76 -> 1 | CK76: =CE76=N76 -> 1 | CL76: =CF76=O76 -> 1 | CM76: =CG76=P76 -> 1
E78: OPEX
E79: OPEX - Front-office cost reduction (avoided contacts) | H79: Eligible cost x tier avoidance rates (S2 tier engine, distilled) | I79: ='SVC-1 Model'!$D$57 -> 156.02454 | J79: =I79-'SVC-1 Model'!$K$57 -> 143.18592 | K79: ='SVC-1 Model'!$K$57 -> 12.838616 | L79: ='SVC-1 Model'!L57 -> 0 | M79: ='SVC-1 Model'!M57 -> 2.2289264 | N79: ='SVC-1 Model'!N57 -> 12.749459 | O79: ='SVC-1 Model'!O57 -> 12.838616 | P79: ='SVC-1 Model'!P57 -> 12.838616 | Q79: Global Servicing | R79: =IF(K79=P79, "", "Error") | T79: ='SVC-1 Model'!T57 -> 0 | U79: ='SVC-1 Model'!U57 -> 0 | V79: ='SVC-1 Model'!V57 -> 0 | W79: ='SVC-1 Model'!W57 -> 0 | X79: ='SVC-1 Model'!X57 -> 0 | Y79: ='SVC-1 Model'!Y57 -> 0 | Z79: ='SVC-1 Model'!Z57 -> 0 | AA79: ='SVC-1 Model'!AA57 -> 0 | ... CA79: ='SVC-1 Model'!CA57 -> 1.0698847 | CC79: =SUMIFS($T79:$CA79, $T$1:$CA$1, CC$63) -> 0 | CD79: =SUMIFS($T79:$CA79, $T$1:$CA$1, CD$63) -> 2.2289264 | CE79: =SUMIFS($T79:$CA79, $T$1:$CA$1, CE$63) -> 12.749459 | CF79: =SUMIFS($T79:$CA79, $T$1:$CA$1, CF$63) -> 12.838616 | CG79: =SUMIFS($T79:$CA79, $T$1:$CA$1, CG$63) -> 12.838616 | CI79: =CC79=L79 -> 1 | CJ79: =CD79=M79 -> 1 | CK79: =CE79=N79 -> 1 | CL79: =CF79=O79 -> 1 | CM79: =CG79=P79 -> 1
I80: 0 | J80: 0 | K80: =I80-J80 -> 0 | R80: =IF(K80=P80, "", "Error") | CC80: =SUMIFS($T80:$CA80, $T$1:$CA$1, CC$63) -> 0 | CD80: =SUMIFS($T80:$CA80, $T$1:$CA$1, CD$63) -> 0 | CE80: =SUMIFS($T80:$CA80, $T$1:$CA$1, CE$63) -> 0 | CF80: =SUMIFS($T80:$CA80, $T$1:$CA$1, CF$63) -> 0 | CG80: =SUMIFS($T80:$CA80, $T$1:$CA$1, CG$63) -> 0 | CI80: =CC80=L80 -> 1 | CJ80: =CD80=M80 -> 1 | CK80: =CE80=N80 -> 1 | CL80: =CF80=O80 -> 1 | CM80: =CG80=P80 -> 1
I81: 0 | J81: 0 | K81: =I81-J81 -> 0 | R81: =IF(K81=P81, "", "Error") | CC81: =SUMIFS($T81:$CA81, $T$1:$CA$1, CC$63) -> 0 | CD81: =SUMIFS($T81:$CA81, $T$1:$CA$1, CD$63) -> 0 | CE81: =SUMIFS($T81:$CA81, $T$1:$CA$1, CE$63) -> 0 | CF81: =SUMIFS($T81:$CA81, $T$1:$CA$1, CF$63) -> 0 | CG81: =SUMIFS($T81:$CA81, $T$1:$CA$1, CG$63) -> 0 | CI81: =CC81=L81 -> 1 | CJ81: =CD81=M81 -> 1 | CK81: =CE81=N81 -> 1 | CL81: =CF81=O81 -> 1 | CM81: =CG81=P81 -> 1
I82: 0 | J82: 0 | K82: =I82-J82 -> 0 | R82: =IF(K82=P82, "", "Error") | CC82: =SUMIFS($T82:$CA82, $T$1:$CA$1, CC$63) -> 0 | CD82: =SUMIFS($T82:$CA82, $T$1:$CA$1, CD$63) -> 0 | CE82: =SUMIFS($T82:$CA82, $T$1:$CA$1, CE$63) -> 0 | CF82: =SUMIFS($T82:$CA82, $T$1:$CA$1, CF$63) -> 0 | CG82: =SUMIFS($T82:$CA82, $T$1:$CA$1, CG$63) -> 0 | CI82: =CC82=L82 -> 1 | CJ82: =CD82=M82 -> 1 | CK82: =CE82=N82 -> 1 | CL82: =CF82=O82 -> 1 | CM82: =CG82=P82 -> 1
I83: 0 | J83: 0 | K83: =I83-J83 -> 0 | R83: =IF(K83=P83, "", "Error") | CC83: =SUMIFS($T83:$CA83, $T$1:$CA$1, CC$63) -> 0 | CD83: =SUMIFS($T83:$CA83, $T$1:$CA$1, CD$63) -> 0 | CE83: =SUMIFS($T83:$CA83, $T$1:$CA$1, CE$63) -> 0 | CF83: =SUMIFS($T83:$CA83, $T$1:$CA$1, CF$63) -> 0 | CG83: =SUMIFS($T83:$CA83, $T$1:$CA$1, CG$63) -> 0 | CI83: =CC83=L83 -> 1 | CJ83: =CD83=M83 -> 1 | CK83: =CE83=N83 -> 1 | CL83: =CF83=O83 -> 1 | CM83: =CG83=P83 -> 1
E84: OpEx subtotal | I84: =SUM(I79:I83) -> 156.02454 | J84: =SUM(J79:J83) -> 143.18592 | K84: =SUM(K79:K83) -> 12.838616 | L84: =SUM(L79:L83) -> 0 | M84: =SUM(M79:M83) -> 2.2289264 | N84: =SUM(N79:N83) -> 12.749459 | O84: =SUM(O79:O83) -> 12.838616 | P84: =SUM(P79:P83) -> 12.838616 | T84: =SUM(T79:T83) -> 0 | U84: =SUM(U79:U83) -> 0 | V84: =SUM(V79:V83) -> 0 | W84: =SUM(W79:W83) -> 0 | X84: =SUM(X79:X83) -> 0 | Y84: =SUM(Y79:Y83) -> 0 | Z84: =SUM(Z79:Z83) -> 0 | AA84: =SUM(AA79:AA83) -> 0 | ... CA84: =SUM(CA79:CA83) -> 1.0698847 | CC84: =SUM(CC79:CC83) -> 0 | CD84: =SUM(CD79:CD83) -> 2.2289264 | CE84: =SUM(CE79:CE83) -> 12.749459 | CF84: =SUM(CF79:CF83) -> 12.838616 | CG84: =SUM(CG79:CG83) -> 12.838616 | CI84: =CC84=L84 -> 1 | CJ84: =CD84=M84 -> 1 | CK84: =CE84=N84 -> 1 | CL84: =CF84=O84 -> 1 | CM84: =CG84=P84 -> 1
E88: Recurring Benefits Total | I88: =SUM(I68, I76, I84) -> 156.02454 | J88: =SUM(J68, J76, J84) -> 143.18592 | K88: =SUM(K68, K76, K84) -> 12.838616 | L88: =SUM(L68, L76, L84) -> 0 | M88: =SUM(M68, M76, M84) -> 2.2289264 | N88: =SUM(N68, N76, N84) -> 12.749459 | O88: =SUM(O68, O76, O84) -> 12.838616 | P88: =SUM(P68, P76, P84) -> 12.838616 | T88: =SUM(T68, T76, T84) -> 0 | U88: =SUM(U68, U76, U84) -> 0 | V88: =SUM(V68, V76, V84) -> 0 | W88: =SUM(W68, W76, W84) -> 0 | X88: =SUM(X68, X76, X84) -> 0 | Y88: =SUM(Y68, Y76, Y84) -> 0 | Z88: =SUM(Z68, Z76, Z84) -> 0 | AA88: =SUM(AA68, AA76, AA84) -> 0 | ... CA88: =SUM(CA68, CA76, CA84) -> 1.0698847 | CC88: =SUM(CC68, CC76, CC84) -> 0 | CD88: =SUM(CD68, CD76, CD84) -> 2.2289264 | CE88: =SUM(CE68, CE76, CE84) -> 12.749459 | CF88: =SUM(CF68, CF76, CF84) -> 12.838616 | CG88: =SUM(CG68, CG76, CG84) -> 12.838616 | CH88: =SUM(CH68, CH76, CH84) -> 0 | CI88: =CC88=L88 -> 1 | CJ88: =CD88=M88 -> 1 | CK88: =CE88=N88 -> 1 | CL88: =CF88=O88 -> 1 | CM88: =CG88=P88 -> 1
T90: 2026 | AF90: 2027 | AR90: 2028 | BD90: 2029 | BP90: 2030 | CI90: CHECK
D91: RECURRING COSTS TO ACHIEVE IMPACT | H91: Comment | I91: Baseline | J91: Goal | K91: Ann. Run Rate | L91: 2026 | M91: =L91+1 -> 2027 | N91: =M91+1 -> 2028 | O91: =N91+1 -> 2029 | P91: =O91+1 -> 2030 | Q91: Impacted BU | R91: Check | T91: 46023 | U91: =EOMONTH(T91, 1) -> 46081 | V91: =EOMONTH(U91, 1) -> 46112 | W91: =EOMONTH(V91, 1) -> 46142 | X91: =EOMONTH(W91, 1) -> 46173 | Y91: =EOMONTH(X91, 1) -> 46203 | Z91: =EOMONTH(Y91, 1) -> 46234 | AA91: =EOMONTH(Z91, 1) -> 46265 | AB91: =EOMONTH(AA91, 1) -> 46295 | ... CA91: =EOMONTH(BZ91, 1) -> 47848 | CC91: 2026 | CD91: =CC91+1 -> 2027 | CE91: =CD91+1 -> 2028 | CF91: =CE91+1 -> 2029 | CG91: =CF91+1 -> 2030 | CI91: 2026 | CJ91: =CI91+1 -> 2027 | CK91: =CJ91+1 -> 2028 | CL91: =CK91+1 -> 2029 | CM91: =CL91+1 -> 2030
E92: $USD M | I92: =$H$18 -> Jan–Jul 2026 x 12/7 | J92: Future State | K92: Increment
E93: Revenue
I94: 0 | J94: 0 | K94: =J94-I94 -> 0 | R94: =IF(K94=P94, "", "Error") | CC94: =SUMIFS($T94:$CA94, $T$1:$CA$1, CC$63) -> 0 | CD94: =SUMIFS($T94:$CA94, $T$1:$CA$1, CD$63) -> 0 | CE94: =SUMIFS($T94:$CA94, $T$1:$CA$1, CE$63) -> 0 | CF94: =SUMIFS($T94:$CA94, $T$1:$CA$1, CF$63) -> 0 | CG94: =SUMIFS($T94:$CA94, $T$1:$CA$1, CG$63) -> 0 | CI94: =CC94=L94 -> 1 | CJ94: =CD94=M94 -> 1 | CK94: =CE94=N94 -> 1 | CL94: =CF94=O94 -> 1 | CM94: =CG94=P94 -> 1
I95: 0 | J95: 0 | K95: =J95-I95 -> 0 | R95: =IF(K95=P95, "", "Error") | CC95: =SUMIFS($T95:$CA95, $T$1:$CA$1, CC$63) -> 0 | CD95: =SUMIFS($T95:$CA95, $T$1:$CA$1, CD$63) -> 0 | CE95: =SUMIFS($T95:$CA95, $T$1:$CA$1, CE$63) -> 0 | CF95: =SUMIFS($T95:$CA95, $T$1:$CA$1, CF$63) -> 0 | CG95: =SUMIFS($T95:$CA95, $T$1:$CA$1, CG$63) -> 0 | CI95: =CC95=L95 -> 1 | CJ95: =CD95=M95 -> 1 | CK95: =CE95=N95 -> 1 | CL95: =CF95=O95 -> 1 | CM95: =CG95=P95 -> 1
E96: Revenue Subtotal | I96: =SUM(I94:I95) -> 0 | J96: =SUM(J94:J95) -> 0 | K96: =SUM(K94:K95) -> 0 | L96: =SUM(L94:L95) -> 0 | M96: =SUM(M94:M95) -> 0 | N96: =SUM(N94:N95) -> 0 | O96: =SUM(O94:O95) -> 0 | P96: =SUM(P94:P95) -> 0 | T96: =SUM(T94:T95) -> 0 | U96: =SUM(U94:U95) -> 0 | V96: =SUM(V94:V95) -> 0 | W96: =SUM(W94:W95) -> 0 | X96: =SUM(X94:X95) -> 0 | Y96: =SUM(Y94:Y95) -> 0 | Z96: =SUM(Z94:Z95) -> 0 | AA96: =SUM(AA94:AA95) -> 0 | ... CA96: =SUM(CA94:CA95) -> 0 | CC96: =SUM(CC94:CC95) -> 0 | CD96: =SUM(CD94:CD95) -> 0 | CE96: =SUM(CE94:CE95) -> 0 | CF96: =SUM(CF94:CF95) -> 0 | CG96: =SUM(CG94:CG95) -> 0 | CI96: =CC96=L96 -> 1 | CJ96: =CD96=M96 -> 1 | CK96: =CE96=N96 -> 1 | CL96: =CF96=O96 -> 1 | CM96: =CG96=P96 -> 1
E98: Cost of Sales
I99: 0 | J99: 0 | K99: =J99-I99 -> 0 | L99: 0 | M99: 0 | N99: 0 | O99: 0 | P99: 0 | R99: =IF(K99=P99, "", "Error") | CC99: =SUMIFS($T99:$CA99, $T$1:$CA$1, CC$63) -> 0 | CD99: =SUMIFS($T99:$CA99, $T$1:$CA$1, CD$63) -> 0 | CE99: =SUMIFS($T99:$CA99, $T$1:$CA$1, CE$63) -> 0 | CF99: =SUMIFS($T99:$CA99, $T$1:$CA$1, CF$63) -> 0 | CG99: =SUMIFS($T99:$CA99, $T$1:$CA$1, CG$63) -> 0 | CI99: =CC99=L99 -> 1 | CJ99: =CD99=M99 -> 1 | CK99: =CE99=N99 -> 1 | CL99: =CF99=O99 -> 1 | CM99: =CG99=P99 -> 1
I100: 0 | J100: 0 | K100: =J100-I100 -> 0 | L100: 0 | M100: 0 | N100: 0 | O100: 0 | P100: 0 | R100: =IF(K100=P100, "", "Error") | CC100: =SUMIFS($T100:$CA100, $T$1:$CA$1, CC$63) -> 0 | CD100: =SUMIFS($T100:$CA100, $T$1:$CA$1, CD$63) -> 0 | CE100: =SUMIFS($T100:$CA100, $T$1:$CA$1, CE$63) -> 0 | CF100: =SUMIFS($T100:$CA100, $T$1:$CA$1, CF$63) -> 0 | CG100: =SUMIFS($T100:$CA100, $T$1:$CA$1, CG$63) -> 0 | CI100: =CC100=L100 -> 1 | CJ100: =CD100=M100 -> 1 | CK100: =CE100=N100 -> 1 | CL100: =CF100=O100 -> 1 | CM100: =CG100=P100 -> 1
I101: 0 | J101: 0 | K101: =J101-I101 -> 0 | L101: 0 | M101: 0 | N101: 0 | O101: 0 | P101: 0 | R101: =IF(K101=P101, "", "Error") | CC101: =SUMIFS($T101:$CA101, $T$1:$CA$1, CC$63) -> 0 | CD101: =SUMIFS($T101:$CA101, $T$1:$CA$1, CD$63) -> 0 | CE101: =SUMIFS($T101:$CA101, $T$1:$CA$1, CE$63) -> 0 | CF101: =SUMIFS($T101:$CA101, $T$1:$CA$1, CF$63) -> 0 | CG101: =SUMIFS($T101:$CA101, $T$1:$CA$1, CG$63) -> 0 | CI101: =CC101=L101 -> 1 | CJ101: =CD101=M101 -> 1 | CK101: =CE101=N101 -> 1 | CL101: =CF101=O101 -> 1 | CM101: =CG101=P101 -> 1
I102: 0 | J102: 0 | K102: =J102-I102 -> 0 | L102: 0 | M102: 0 | N102: 0 | O102: 0 | P102: 0 | R102: =IF(K102=P102, "", "Error") | CC102: =SUMIFS($T102:$CA102, $T$1:$CA$1, CC$63) -> 0 | CD102: =SUMIFS($T102:$CA102, $T$1:$CA$1, CD$63) -> 0 | CE102: =SUMIFS($T102:$CA102, $T$1:$CA$1, CE$63) -> 0 | CF102: =SUMIFS($T102:$CA102, $T$1:$CA$1, CF$63) -> 0 | CG102: =SUMIFS($T102:$CA102, $T$1:$CA$1, CG$63) -> 0 | CI102: =CC102=L102 -> 1 | CJ102: =CD102=M102 -> 1 | CK102: =CE102=N102 -> 1 | CL102: =CF102=O102 -> 1 | CM102: =CG102=P102 -> 1
K103: =J103-I103 -> 0 | L103: 0 | M103: 0 | N103: 0 | O103: 0 | P103: 0
E104: Cost of Sales Subtotal | I104: =SUM(I99:I103) -> 0 | J104: =SUM(J99:J103) -> 0 | K104: =SUM(K99:K103) -> 0 | L104: =SUM(L99:L103) -> 0 | M104: =SUM(M99:M103) -> 0 | N104: =SUM(N99:N103) -> 0 | O104: =SUM(O99:O103) -> 0 | P104: =SUM(P99:P103) -> 0 | T104: =SUM(T99:T103) -> 0 | U104: =SUM(U99:U103) -> 0 | V104: =SUM(V99:V103) -> 0 | W104: =SUM(W99:W103) -> 0 | X104: =SUM(X99:X103) -> 0 | Y104: =SUM(Y99:Y103) -> 0 | Z104: =SUM(Z99:Z103) -> 0 | AA104: =SUM(AA99:AA103) -> 0 | ... CA104: =SUM(CA99:CA103) -> 0 | CC104: =SUM(CC99:CC103) -> 0 | CD104: =SUM(CD99:CD103) -> 0 | CE104: =SUM(CE99:CE103) -> 0 | CF104: =SUM(CF99:CF103) -> 0 | CG104: =SUM(CG99:CG103) -> 0 | CI104: =CC104=L104 -> 1 | CJ104: =CD104=M104 -> 1 | CK104: =CE104=N104 -> 1 | CL104: =CF104=O104 -> 1 | CM104: =CG104=P104 -> 1
E106: OPEX
E107: OPEX - Run team (keep-the-lights-on) | H107: S2 C3: 2.0 FTE x $180k | I107: 0 | J107: =I107+'SVC-1 Model'!$K$110 -> 0.36 | K107: ='SVC-1 Model'!$K$110 -> 0.36 | L107: ='SVC-1 Model'!L110 -> 0 | M107: ='SVC-1 Model'!M110 -> 0.15 | N107: ='SVC-1 Model'!N110 -> 0.36 | O107: ='SVC-1 Model'!O110 -> 0.36 | P107: ='SVC-1 Model'!P110 -> 0.36 | Q107: Global Servicing | R107: =IF(K107=P107, "", "Error") | T107: ='SVC-1 Model'!T110 -> 0 | U107: ='SVC-1 Model'!U110 -> 0 | V107: ='SVC-1 Model'!V110 -> 0 | W107: ='SVC-1 Model'!W110 -> 0 | X107: ='SVC-1 Model'!X110 -> 0 | Y107: ='SVC-1 Model'!Y110 -> 0 | Z107: ='SVC-1 Model'!Z110 -> 0 | AA107: ='SVC-1 Model'!AA110 -> 0 | ... CA107: ='SVC-1 Model'!CA110 -> 0.03 | CC107: =SUMIFS($T107:$CA107, $T$1:$CA$1, CC$63) -> 0 | CD107: =SUMIFS($T107:$CA107, $T$1:$CA$1, CD$63) -> 0.15 | CE107: =SUMIFS($T107:$CA107, $T$1:$CA$1, CE$63) -> 0.36 | CF107: =SUMIFS($T107:$CA107, $T$1:$CA$1, CF$63) -> 0.36 | CG107: =SUMIFS($T107:$CA107, $T$1:$CA$1, CG$63) -> 0.36 | CI107: =CC107=L107 -> 1 | CJ107: =CD107=M107 -> 1 | CK107: =CE107=N107 -> 1 | CL107: =CF107=O107 -> 1 | CM107: =CG107=P107 -> 1
E108: OPEX - Vendor support & maintenance | H108: S2 C3 planning number | I108: 0 | J108: =I108+'SVC-1 Model'!$K$111 -> 0.1 | K108: ='SVC-1 Model'!$K$111 -> 0.1 | L108: ='SVC-1 Model'!L111 -> 0 | M108: ='SVC-1 Model'!M111 -> 0.041666667 | N108: ='SVC-1 Model'!N111 -> 0.1 | O108: ='SVC-1 Model'!O111 -> 0.1 | P108: ='SVC-1 Model'!P111 -> 0.1 | Q108: Global Servicing | R108: =IF(K108=P108, "", "Error") | T108: ='SVC-1 Model'!T111 -> 0 | U108: ='SVC-1 Model'!U111 -> 0 | V108: ='SVC-1 Model'!V111 -> 0 | W108: ='SVC-1 Model'!W111 -> 0 | X108: ='SVC-1 Model'!X111 -> 0 | Y108: ='SVC-1 Model'!Y111 -> 0 | Z108: ='SVC-1 Model'!Z111 -> 0 | AA108: ='SVC-1 Model'!AA111 -> 0 | ... CA108: ='SVC-1 Model'!CA111 -> 0.0083333333 | CC108: =SUMIFS($T108:$CA108, $T$1:$CA$1, CC$63) -> 0 | CD108: =SUMIFS($T108:$CA108, $T$1:$CA$1, CD$63) -> 0.041666667 | CE108: =SUMIFS($T108:$CA108, $T$1:$CA$1, CE$63) -> 0.1 | CF108: =SUMIFS($T108:$CA108, $T$1:$CA$1, CF$63) -> 0.1 | CG108: =SUMIFS($T108:$CA108, $T$1:$CA$1, CG$63) -> 0.1 | CI108: =CC108=L108 -> 1 | CJ108: =CD108=M108 -> 1 | CK108: =CE108=N108 -> 1 | CL108: =CF108=O108 -> 1 | CM108: =CG108=P108 -> 1
E109: OPEX - Incremental infrastructure | H109: S2 C3 planning number | I109: 0 | J109: =I109+'SVC-1 Model'!$K$112 -> 0.04 | K109: ='SVC-1 Model'!$K$112 -> 0.04 | L109: ='SVC-1 Model'!L112 -> 0 | M109: ='SVC-1 Model'!M112 -> 0.016666667 | N109: ='SVC-1 Model'!N112 -> 0.04 | O109: ='SVC-1 Model'!O112 -> 0.04 | P109: ='SVC-1 Model'!P112 -> 0.04 | Q109: Global Servicing | R109: =IF(K109=P109, "", "Error") | T109: ='SVC-1 Model'!T112 -> 0 | U109: ='SVC-1 Model'!U112 -> 0 | V109: ='SVC-1 Model'!V112 -> 0 | W109: ='SVC-1 Model'!W112 -> 0 | X109: ='SVC-1 Model'!X112 -> 0 | Y109: ='SVC-1 Model'!Y112 -> 0 | Z109: ='SVC-1 Model'!Z112 -> 0 | AA109: ='SVC-1 Model'!AA112 -> 0 | ... CA109: ='SVC-1 Model'!CA112 -> 0.0033333333 | CC109: =SUMIFS($T109:$CA109, $T$1:$CA$1, CC$63) -> 0 | CD109: =SUMIFS($T109:$CA109, $T$1:$CA$1, CD$63) -> 0.016666667 | CE109: =SUMIFS($T109:$CA109, $T$1:$CA$1, CE$63) -> 0.04 | CF109: =SUMIFS($T109:$CA109, $T$1:$CA$1, CF$63) -> 0.04 | CG109: =SUMIFS($T109:$CA109, $T$1:$CA$1, CG$63) -> 0.04 | CI109: =CC109=L109 -> 1 | CJ109: =CD109=M109 -> 1 | CK109: =CE109=N109 -> 1 | CL109: =CF109=O109 -> 1 | CM109: =CG109=P109 -> 1
I110: 0 | J110: 0 | K110: =J110-I110 -> 0 | L110: 0 | M110: 0 | N110: 0 | O110: 0 | P110: 0 | R110: =IF(K110=P110, "", "Error") | CC110: =SUMIFS($T110:$CA110, $T$1:$CA$1, CC$63) -> 0 | CD110: =SUMIFS($T110:$CA110, $T$1:$CA$1, CD$63) -> 0 | CE110: =SUMIFS($T110:$CA110, $T$1:$CA$1, CE$63) -> 0 | CF110: =SUMIFS($T110:$CA110, $T$1:$CA$1, CF$63) -> 0 | CG110: =SUMIFS($T110:$CA110, $T$1:$CA$1, CG$63) -> 0 | CI110: =CC110=L110 -> 1 | CJ110: =CD110=M110 -> 1 | CK110: =CE110=N110 -> 1 | CL110: =CF110=O110 -> 1 | CM110: =CG110=P110 -> 1
I111: 0 | J111: 0 | K111: =J111-I111 -> 0 | L111: 0 | M111: 0 | N111: 0 | O111: 0 | P111: 0 | R111: =IF(K111=P111, "", "Error") | CC111: =SUMIFS($T111:$CA111, $T$1:$CA$1, CC$63) -> 0 | CD111: =SUMIFS($T111:$CA111, $T$1:$CA$1, CD$63) -> 0 | CE111: =SUMIFS($T111:$CA111, $T$1:$CA$1, CE$63) -> 0 | CF111: =SUMIFS($T111:$CA111, $T$1:$CA$1, CF$63) -> 0 | CG111: =SUMIFS($T111:$CA111, $T$1:$CA$1, CG$63) -> 0 | CI111: =CC111=L111 -> 1 | CJ111: =CD111=M111 -> 1 | CK111: =CE111=N111 -> 1 | CL111: =CF111=O111 -> 1 | CM111: =CG111=P111 -> 1
E112: OpEx subtotal | I112: =SUM(I107:I111) -> 0 | J112: =SUM(J107:J111) -> 0.5 | K112: =SUM(K107:K111) -> 0.5 | L112: =SUM(L107:L111) -> 0 | M112: =SUM(M107:M111) -> 0.20833333 | N112: =SUM(N107:N111) -> 0.5 | O112: =SUM(O107:O111) -> 0.5 | P112: =SUM(P107:P111) -> 0.5 | T112: =SUM(T107:T111) -> 0 | U112: =SUM(U107:U111) -> 0 | V112: =SUM(V107:V111) -> 0 | W112: =SUM(W107:W111) -> 0 | X112: =SUM(X107:X111) -> 0 | Y112: =SUM(Y107:Y111) -> 0 | Z112: =SUM(Z107:Z111) -> 0 | AA112: =SUM(AA107:AA111) -> 0 | ... CA112: =SUM(CA107:CA111) -> 0.041666667 | CC112: =SUM(CC107:CC111) -> 0 | CD112: =SUM(CD107:CD111) -> 0.20833333 | CE112: =SUM(CE107:CE111) -> 0.5 | CF112: =SUM(CF107:CF111) -> 0.5 | CG112: =SUM(CG107:CG111) -> 0.5 | CI112: =CC112=L112 -> 1 | CJ112: =CD112=M112 -> 1 | CK112: =CE112=N112 -> 1 | CL112: =CF112=O112 -> 1 | CM112: =CG112=P112 -> 1
E115: Recurring Costs Total | I115: =SUM(-I96, I104, I112) -> 0 | J115: =SUM(-J96, J104, J112) -> 0.5 | K115: =SUM(-K96, K104, K112) -> 0.5 | L115: =SUM(-L96, L104, L112) -> 0 | M115: =SUM(-M96, M104, M112) -> 0.20833333 | N115: =SUM(-N96, N104, N112) -> 0.5 | O115: =SUM(-O96, O104, O112) -> 0.5 | P115: =SUM(-P96, P104, P112) -> 0.5 | T115: =SUM(-T96, T104, T112) -> 0 | U115: =SUM(-U96, U104, U112) -> 0 | V115: =SUM(-V96, V104, V112) -> 0 | W115: =SUM(-W96, W104, W112) -> 0 | X115: =SUM(-X96, X104, X112) -> 0 | Y115: =SUM(-Y96, Y104, Y112) -> 0 | Z115: =SUM(-Z96, Z104, Z112) -> 0 | AA115: =SUM(-AA96, AA104, AA112) -> 0 | ... CA115: =SUM(-CA96, CA104, CA112) -> 0.041666667 | CC115: =SUM(-CC96, CC104, CC112) -> 0 | CD115: =SUM(-CD96, CD104, CD112) -> 0.20833333 | CE115: =SUM(-CE96, CE104, CE112) -> 0.5 | CF115: =SUM(-CF96, CF104, CF112) -> 0.5 | CG115: =SUM(-CG96, CG104, CG112) -> 0.5 | CI115: =CC115=L115 -> 1 | CJ115: =CD115=M115 -> 1 | CK115: =CE115=N115 -> 1 | CL115: =CF115=O115 -> 1 | CM115: =CG115=P115 -> 1
E117: Net Recurring Benefit | I117: =SUM(I88, -I115) -> 156.02454 | J117: =SUM(J88, -J115) -> 142.68592 | K117: =SUM(K88, -K115) -> 12.338616 | L117: =SUM(L88, -L115) -> 0 | M117: =SUM(M88, -M115) -> 2.0205931 | N117: =SUM(N88, -N115) -> 12.249459 | O117: =SUM(O88, -O115) -> 12.338616 | P117: =SUM(P88, -P115) -> 12.338616 | R117: =IF(K117=P117, "", "Error") | T117: =SUM(T88, -T115) -> 0 | U117: =SUM(U88, -U115) -> 0 | V117: =SUM(V88, -V115) -> 0 | W117: =SUM(W88, -W115) -> 0 | X117: =SUM(X88, -X115) -> 0 | Y117: =SUM(Y88, -Y115) -> 0 | Z117: =SUM(Z88, -Z115) -> 0 | AA117: =SUM(AA88, -AA115) -> 0 | ... CA117: =SUM(CA88, -CA115) -> 1.028218 | CC117: =SUM(CC88, -CC115) -> 0 | CD117: =SUM(CD88, -CD115) -> 2.0205931 | CE117: =SUM(CE88, -CE115) -> 12.249459 | CF117: =SUM(CF88, -CF115) -> 12.338616 | CG117: =SUM(CG88, -CG115) -> 12.338616 | CI117: =CC117=L117 -> 1 | CJ117: =CD117=M117 -> 1 | CK117: =CE117=N117 -> 1 | CL117: =CF117=O117 -> 1 | CM117: =CG117=P117 -> 1
C120: SECTION III - ONE-TIME IMPLEMENTATION | CC120: ANNUAL SUMMARY | CI120: CHECK CELLS
T122: 2026 | AF122: 2027 | AR122: 2028 | BD122: 2029 | BP122: 2030
D123: ONE-TIME BENEFITS | K123: Comment | L123: 2026 | M123: =L123+1 -> 2027 | N123: =M123+1 -> 2028 | O123: =N123+1 -> 2029 | P123: =O123+1 -> 2030 | Q123: Impacted BU | T123: 46023 | U123: =EOMONTH(T123, 1) -> 46081 | V123: =EOMONTH(U123, 1) -> 46112 | W123: =EOMONTH(V123, 1) -> 46142 | X123: =EOMONTH(W123, 1) -> 46173 | Y123: =EOMONTH(X123, 1) -> 46203 | Z123: =EOMONTH(Y123, 1) -> 46234 | AA123: =EOMONTH(Z123, 1) -> 46265 | AB123: =EOMONTH(AA123, 1) -> 46295 | ... CA123: =EOMONTH(BZ123, 1) -> 47848 | CC123: 2026 | CD123: =CC123+1 -> 2027 | CE123: =CD123+1 -> 2028 | CF123: =CE123+1 -> 2029 | CG123: =CF123+1 -> 2030 | CI123: 2026 | CJ123: =CI123+1 -> 2027 | CK123: =CJ123+1 -> 2028 | CL123: =CK123+1 -> 2029 | CM123: =CL123+1 -> 2030
E125: Working Capital
CC126: =SUMIFS($T126:$CA126, $T$1:$CA$1, CC$63) -> 0 | CD126: =SUMIFS($T126:$CA126, $T$1:$CA$1, CD$63) -> 0 | CE126: =SUMIFS($T126:$CA126, $T$1:$CA$1, CE$63) -> 0 | CF126: =SUMIFS($T126:$CA126, $T$1:$CA$1, CF$63) -> 0 | CG126: =SUMIFS($T126:$CA126, $T$1:$CA$1, CG$63) -> 0 | CI126: =CC126=L126 -> 1 | CJ126: =CD126=M126 -> 1 | CK126: =CE126=N126 -> 1 | CL126: =CF126=O126 -> 1 | CM126: =CG126=P126 -> 1
CC127: =SUMIFS($T127:$CA127, $T$1:$CA$1, CC$63) -> 0 | CD127: =SUMIFS($T127:$CA127, $T$1:$CA$1, CD$63) -> 0 | CE127: =SUMIFS($T127:$CA127, $T$1:$CA$1, CE$63) -> 0 | CF127: =SUMIFS($T127:$CA127, $T$1:$CA$1, CF$63) -> 0 | CG127: =SUMIFS($T127:$CA127, $T$1:$CA$1, CG$63) -> 0 | CI127: =CC127=L127 -> 1 | CJ127: =CD127=M127 -> 1 | CK127: =CE127=N127 -> 1 | CL127: =CF127=O127 -> 1 | CM127: =CG127=P127 -> 1
E128: Working Capital Subtotal | L128: =SUM(L126:L127) -> 0 | M128: =SUM(M126:M127) -> 0 | N128: =SUM(N126:N127) -> 0 | O128: =SUM(O126:O127) -> 0 | P128: =SUM(P126:P127) -> 0 | T128: =SUM(T126:T127) -> 0 | U128: =SUM(U126:U127) -> 0 | V128: =SUM(V126:V127) -> 0 | W128: =SUM(W126:W127) -> 0 | X128: =SUM(X126:X127) -> 0 | Y128: =SUM(Y126:Y127) -> 0 | Z128: =SUM(Z126:Z127) -> 0 | AA128: =SUM(AA126:AA127) -> 0 | ... CA128: =SUM(CA126:CA127) -> 0 | CC128: =SUM(CC126:CC127) -> 0 | CD128: =SUM(CD126:CD127) -> 0 | CE128: =SUM(CE126:CE127) -> 0 | CF128: =SUM(CF126:CF127) -> 0 | CG128: =SUM(CG126:CG127) -> 0 | CI128: =CC128=L128 -> 1 | CJ128: =CD128=M128 -> 1 | CK128: =CE128=N128 -> 1 | CL128: =CF128=O128 -> 1 | CM128: =CG128=P128 -> 1
E130: One-Time Benefits Total | L130: =L128 -> 0 | M130: =M128 -> 0 | N130: =N128 -> 0 | O130: =O128 -> 0 | P130: =P128 -> 0 | T130: =T128 -> 0 | U130: =U128 -> 0 | V130: =V128 -> 0 | W130: =W128 -> 0 | X130: =X128 -> 0 | Y130: =Y128 -> 0 | Z130: =Z128 -> 0 | AA130: =AA128 -> 0 | ... CA130: =CA128 -> 0 | CC130: =CC128 -> 0 | CD130: =CD128 -> 0 | CE130: =CE128 -> 0 | CF130: =CF128 -> 0 | CG130: =CG128 -> 0 | CI130: =CI128 -> 1 | CJ130: =CJ128 -> 1 | CK130: =CK128 -> 1 | CL130: =CL128 -> 1 | CM130: =CM128 -> 1
T132: 2026 | AF132: 2027 | AR132: 2028 | BD132: 2029 | BP132: 2030
D133: CAPEX AND ONE-TIME COSTS | K133: Comment | L133: 2026 | M133: =L133+1 -> 2027 | N133: =M133+1 -> 2028 | O133: =N133+1 -> 2029 | P133: =O133+1 -> 2030 | T133: 46023 | U133: =EOMONTH(T133, 1) -> 46081 | V133: =EOMONTH(U133, 1) -> 46112 | W133: =EOMONTH(V133, 1) -> 46142 | X133: =EOMONTH(W133, 1) -> 46173 | Y133: =EOMONTH(X133, 1) -> 46203 | Z133: =EOMONTH(Y133, 1) -> 46234 | AA133: =EOMONTH(Z133, 1) -> 46265 | AB133: =EOMONTH(AA133, 1) -> 46295 | ... CA133: =EOMONTH(BZ133, 1) -> 47848 | CC133: 2026 | CD133: =CC133+1 -> 2027 | CE133: =CD133+1 -> 2028 | CF133: =CE133+1 -> 2029 | CG133: =CF133+1 -> 2030 | CI133: 2026 | CJ133: =CI133+1 -> 2027 | CK133: =CJ133+1 -> 2028 | CL133: =CK133+1 -> 2029 | CM133: =CL133+1 -> 2030
E135: Capital Expenditures
E136: CAPEX — capitalized build labor | L136: ='SVC-1 Model'!L96 -> 0 | M136: ='SVC-1 Model'!M96 -> 0 | N136: ='SVC-1 Model'!N96 -> 0 | O136: ='SVC-1 Model'!O96 -> 0 | P136: ='SVC-1 Model'!P96 -> 0 | Q136: Global Servicing | T136: ='SVC-1 Model'!T96 -> 0 | U136: ='SVC-1 Model'!U96 -> 0 | V136: ='SVC-1 Model'!V96 -> 0 | W136: ='SVC-1 Model'!W96 -> 0 | X136: ='SVC-1 Model'!X96 -> 0 | Y136: ='SVC-1 Model'!Y96 -> 0 | Z136: ='SVC-1 Model'!Z96 -> 0 | AA136: ='SVC-1 Model'!AA96 -> 0 | ... CA136: ='SVC-1 Model'!CA96 -> 0 | CC136: =SUMIFS($T136:$CA136, $T$1:$CA$1, CC$63) -> 0 | CD136: =SUMIFS($T136:$CA136, $T$1:$CA$1, CD$63) -> 0 | CE136: =SUMIFS($T136:$CA136, $T$1:$CA$1, CE$63) -> 0 | CF136: =SUMIFS($T136:$CA136, $T$1:$CA$1, CF$63) -> 0 | CG136: =SUMIFS($T136:$CA136, $T$1:$CA$1, CG$63) -> 0 | CI136: =CC136=L136 -> 1 | CJ136: =CD136=M136 -> 1 | CK136: =CE136=N136 -> 1 | CL136: =CF136=O136 -> 1 | CM136: =CG136=P136 -> 1
E137: CAPEX — capitalized non-labor | L137: ='SVC-1 Model'!L97 -> 0 | M137: ='SVC-1 Model'!M97 -> 0 | N137: ='SVC-1 Model'!N97 -> 0 | O137: ='SVC-1 Model'!O97 -> 0 | P137: ='SVC-1 Model'!P97 -> 0 | Q137: Global Servicing | T137: ='SVC-1 Model'!T97 -> 0 | U137: ='SVC-1 Model'!U97 -> 0 | V137: ='SVC-1 Model'!V97 -> 0 | W137: ='SVC-1 Model'!W97 -> 0 | X137: ='SVC-1 Model'!X97 -> 0 | Y137: ='SVC-1 Model'!Y97 -> 0 | Z137: ='SVC-1 Model'!Z97 -> 0 | AA137: ='SVC-1 Model'!AA97 -> 0 | ... CA137: ='SVC-1 Model'!CA97 -> 0 | CC137: =SUMIFS($T137:$CA137, $T$1:$CA$1, CC$63) -> 0 | CD137: =SUMIFS($T137:$CA137, $T$1:$CA$1, CD$63) -> 0 | CE137: =SUMIFS($T137:$CA137, $T$1:$CA$1, CE$63) -> 0 | CF137: =SUMIFS($T137:$CA137, $T$1:$CA$1, CF$63) -> 0 | CG137: =SUMIFS($T137:$CA137, $T$1:$CA$1, CG$63) -> 0 | CI137: =CC137=L137 -> 1 | CJ137: =CD137=M137 -> 1 | CK137: =CE137=N137 -> 1 | CL137: =CF137=O137 -> 1 | CM137: =CG137=P137 -> 1
E138: Capital Expenditures Subtotal | L138: =SUM(L136:L137) -> 0 | M138: =SUM(M136:M137) -> 0 | N138: =SUM(N136:N137) -> 0 | O138: =SUM(O136:O137) -> 0 | P138: =SUM(P136:P137) -> 0 | T138: =SUM(T136:T137) -> 0 | U138: =SUM(U136:U137) -> 0 | V138: =SUM(V136:V137) -> 0 | W138: =SUM(W136:W137) -> 0 | X138: =SUM(X136:X137) -> 0 | Y138: =SUM(Y136:Y137) -> 0 | Z138: =SUM(Z136:Z137) -> 0 | AA138: =SUM(AA136:AA137) -> 0 | ... CA138: =SUM(CA136:CA137) -> 0 | CC138: =SUM(CC136:CC137) -> 0 | CD138: =SUM(CD136:CD137) -> 0 | CE138: =SUM(CE136:CE137) -> 0 | CF138: =SUM(CF136:CF137) -> 0 | CG138: =SUM(CG136:CG137) -> 0 | CI138: =CC138=L138 -> 1 | CJ138: =CD138=M138 -> 1 | CK138: =CE138=N138 -> 1 | CL138: =CF138=O138 -> 1 | CM138: =CG138=P138 -> 1
E140: OTC
E141: OTC — build labor (expensed) | L141: ='SVC-1 Model'!L98 -> 0 | M141: ='SVC-1 Model'!M98 -> 1.3383333 | N141: ='SVC-1 Model'!N98 -> 0.091666667 | O141: ='SVC-1 Model'!O98 -> 0 | P141: ='SVC-1 Model'!P98 -> 0 | Q141: Global Servicing | T141: ='SVC-1 Model'!T98 -> 0 | U141: ='SVC-1 Model'!U98 -> 0 | V141: ='SVC-1 Model'!V98 -> 0 | W141: ='SVC-1 Model'!W98 -> 0 | X141: ='SVC-1 Model'!X98 -> 0 | Y141: ='SVC-1 Model'!Y98 -> 0 | Z141: ='SVC-1 Model'!Z98 -> 0 | AA141: ='SVC-1 Model'!AA98 -> 0 | ... CA141: ='SVC-1 Model'!CA98 -> 0 | CC141: =SUMIFS($T141:$CA141, $T$1:$CA$1, CC$63) -> 0 | CD141: =SUMIFS($T141:$CA141, $T$1:$CA$1, CD$63) -> 1.3383333 | CE141: =SUMIFS($T141:$CA141, $T$1:$CA$1, CE$63) -> 0.091666667 | CF141: =SUMIFS($T141:$CA141, $T$1:$CA$1, CF$63) -> 0 | CG141: =SUMIFS($T141:$CA141, $T$1:$CA$1, CG$63) -> 0 | CI141: =CC141=L141 -> 1 | CJ141: =CD141=M141 -> 1 | CK141: =CE141=N141 -> 1 | CL141: =CF141=O141 -> 1 | CM141: =CG141=P141 -> 1
E142: OTC — non-labor (expensed) | L142: ='SVC-1 Model'!L99 -> 0 | M142: ='SVC-1 Model'!M99 -> 0.50633846 | N142: ='SVC-1 Model'!N99 -> 0.023861538 | O142: ='SVC-1 Model'!O99 -> 0 | P142: ='SVC-1 Model'!P99 -> 0 | Q142: Global Servicing | T142: ='SVC-1 Model'!T99 -> 0 | U142: ='SVC-1 Model'!U99 -> 0 | V142: ='SVC-1 Model'!V99 -> 0 | W142: ='SVC-1 Model'!W99 -> 0 | X142: ='SVC-1 Model'!X99 -> 0 | Y142: ='SVC-1 Model'!Y99 -> 0 | Z142: ='SVC-1 Model'!Z99 -> 0 | AA142: ='SVC-1 Model'!AA99 -> 0 | ... CA142: ='SVC-1 Model'!CA99 -> 0 | CC142: =SUMIFS($T142:$CA142, $T$1:$CA$1, CC$63) -> 0 | CD142: =SUMIFS($T142:$CA142, $T$1:$CA$1, CD$63) -> 0.50633846 | CE142: =SUMIFS($T142:$CA142, $T$1:$CA$1, CE$63) -> 0.023861538 | CF142: =SUMIFS($T142:$CA142, $T$1:$CA$1, CF$63) -> 0 | CG142: =SUMIFS($T142:$CA142, $T$1:$CA$1, CG$63) -> 0 | CI142: =CC142=L142 -> 1 | CJ142: =CD142=M142 -> 1 | CK142: =CE142=N142 -> 1 | CL142: =CF142=O142 -> 1 | CM142: =CG142=P142 -> 1
CC143: =SUMIFS($T143:$CA143, $T$1:$CA$1, CC$63) -> 0 | CD143: =SUMIFS($T143:$CA143, $T$1:$CA$1, CD$63) -> 0 | CE143: =SUMIFS($T143:$CA143, $T$1:$CA$1, CE$63) -> 0 | CF143: =SUMIFS($T143:$CA143, $T$1:$CA$1, CF$63) -> 0 | CG143: =SUMIFS($T143:$CA143, $T$1:$CA$1, CG$63) -> 0 | CI143: =CC143=L143 -> 1 | CJ143: =CD143=M143 -> 1 | CK143: =CE143=N143 -> 1 | CL143: =CF143=O143 -> 1 | CM143: =CG143=P143 -> 1
E144: OTC Subtotal | L144: =SUM(L141:L143) -> 0 | M144: =SUM(M141:M143) -> 1.8446718 | N144: =SUM(N141:N143) -> 0.11552821 | O144: =SUM(O141:O143) -> 0 | P144: =SUM(P141:P143) -> 0 | T144: =SUM(T141:T143) -> 0 | U144: =SUM(U141:U143) -> 0 | V144: =SUM(V141:V143) -> 0 | W144: =SUM(W141:W143) -> 0 | X144: =SUM(X141:X143) -> 0 | Y144: =SUM(Y141:Y143) -> 0 | Z144: =SUM(Z141:Z143) -> 0 | AA144: =SUM(AA141:AA143) -> 0 | ... CA144: =SUM(CA141:CA143) -> 0 | CC144: =SUM(CC141:CC143) -> 0 | CD144: =SUM(CD141:CD143) -> 1.8446718 | CE144: =SUM(CE141:CE143) -> 0.11552821 | CF144: =SUM(CF141:CF143) -> 0 | CG144: =SUM(CG141:CG143) -> 0 | CI144: =CC144=L144 -> 1 | CJ144: =CD144=M144 -> 1 | CK144: =CE144=N144 -> 1 | CL144: =CF144=O144 -> 1 | CM144: =CG144=P144 -> 1
E147: One-Time Costs Total | L147: =SUM(L138, L144) -> 0 | M147: =SUM(M138, M144) -> 1.8446718 | N147: =SUM(N138, N144) -> 0.11552821 | O147: =SUM(O138, O144) -> 0 | P147: =SUM(P138, P144) -> 0 | T147: =SUM(T138, T144) -> 0 | U147: =SUM(U138, U144) -> 0 | V147: =SUM(V138, V144) -> 0 | W147: =SUM(W138, W144) -> 0 | X147: =SUM(X138, X144) -> 0 | Y147: =SUM(Y138, Y144) -> 0 | Z147: =SUM(Z138, Z144) -> 0 | AA147: =SUM(AA138, AA144) -> 0 | ... CA147: =SUM(CA138, CA144) -> 0 | CC147: =SUM(CC138, CC144) -> 0 | CD147: =SUM(CD138, CD144) -> 1.8446718 | CE147: =SUM(CE138, CE144) -> 0.11552821 | CF147: =SUM(CF138, CF144) -> 0 | CG147: =SUM(CG138, CG144) -> 0 | CI147: =CC147=L147 -> 1 | CJ147: =CD147=M147 -> 1 | CK147: =CE147=N147 -> 1 | CL147: =CF147=O147 -> 1 | CM147: =CG147=P147 -> 1
E149: Total One-Time Implementation Cost | L149: =SUM(L130, -L147) -> 0 | M149: =SUM(M130, -M147) -> -1.8446718 | N149: =SUM(N130, -N147) -> -0.11552821 | O149: =SUM(O130, -O147) -> 0 | P149: =SUM(P130, -P147) -> 0 | T149: =SUM(T130, -T147) -> 0 | U149: =SUM(U130, -U147) -> 0 | V149: =SUM(V130, -V147) -> 0 | W149: =SUM(W130, -W147) -> 0 | X149: =SUM(X130, -X147) -> 0 | Y149: =SUM(Y130, -Y147) -> 0 | Z149: =SUM(Z130, -Z147) -> 0 | AA149: =SUM(AA130, -AA147) -> 0 | ... CA149: =SUM(CA130, -CA147) -> 0 | CC149: =SUM(CC130, -CC147) -> 0 | CD149: =SUM(CD130, -CD147) -> -1.8446718 | CE149: =SUM(CE130, -CE147) -> -0.11552821 | CF149: =SUM(CF130, -CF147) -> 0 | CG149: =SUM(CG130, -CG147) -> 0 | CI149: =CC149=L149 -> 1 | CJ149: =CD149=M149 -> 1 | CK149: =CE149=N149 -> 1 | CL149: =CF149=O149 -> 1 | CM149: =CG149=P149 -> 1
C152: SECTION IV - FINANCIAL METRICS | CC152: ANNUAL SUMMARY | CI152: CHECK CELLS
E155: Cash Flow | L155: 2026 | M155: =L155+1 -> 2027 | N155: =M155+1 -> 2028 | O155: =N155+1 -> 2029 | P155: =O155+1 -> 2030 | Q155: Total
E156: Operating Income | L156: =L117 -> 0 | M156: =M117 -> 2.0205931 | N156: =N117 -> 12.249459 | O156: =O117 -> 12.338616 | P156: =P117 -> 12.338616 | Q156: =SUM(L156:P156) -> 38.947285
E157: (+) One-Time Benefits | L157: =L130 -> 0 | M157: =M130 -> 0 | N157: =N130 -> 0 | O157: =O130 -> 0 | P157: =P130 -> 0 | Q157: =SUM(L157:P157) -> 0
E158: (-) One-Time Cash Costs | L158: =-L147 -> 0 | M158: =-M147 -> -1.8446718 | N158: =-N147 -> -0.11552821 | O158: =-O147 -> 0 | P158: =-P147 -> 0 | Q158: =SUM(L158:P158) -> -1.9602
E159: Cash Flow | L159: =SUM(L156:L158) -> 0 | M159: =SUM(M156:M158) -> 0.17592129 | N159: =SUM(N156:N158) -> 12.133931 | O159: =SUM(O156:O158) -> 12.338616 | P159: =SUM(P156:P158) -> 12.338616 | Q159: =SUM(L159:P159) -> 36.987085
E160: Cumulative Cash Flow | L160: =L159 -> 0 | M160: =L160+M159 -> 0.17592129 | N160: =M160+N159 -> 12.309852 | O160: =N160+O159 -> 24.648468 | P160: =O160+P159 -> 36.987085 | Q160: =P160 -> 36.987085
E161: Payback timeline | L161: =IF(L160<0,1,0) -> 0 | M161: =IF(M160<0,1,IF(AND(L160<0,M159>0),-L160/M159,0)) -> 0 | N161: =IF(N160<0,1,IF(AND(M160<0,N159>0),-M160/N159,0)) -> 0 | O161: =IF(O160<0,1,IF(AND(N160<0,O159>0),-N160/O159,0)) -> 0 | P161: =IF(P160<0,1,IF(AND(O160<0,P159>0),-O160/P159,0)) -> 0
E163: Return on Investment | F163: NRB/OTC | G163: =IFERROR(K117/-SUM(L149:P149),"n/a") -> 6.29457
E164: Internal Rate of Return | F164: 5-yr IRR | G164: =IFERROR(IRR($L$159:$P$159, 0.2),"n/a") -> n/a
E165: Breakeven timeline | F165: # yrs | G165: =IF(SUM(L161:P161)=5,">5",SUM(L161:P161)) -> 0
E167: WACC | G167: 0.095
E168: NPV | F168: $ | G168: =SUM(L168:P168) -> 25.80883 | L168: =L159/(1+$G$167)^L$1 -> 0 | M168: =M159/(1+$G$167)^M$1 -> 0.14672029 | N168: =N159/(1+$G$167)^N$1 -> 9.2418552 | O168: =O159/(1+$G$167)^O$1 -> 8.5824242 | P168: =P159/(1+$G$167)^P$1 -> 7.8378304 | Q168: =SUM(L168:P168) -> 25.80883
C171: END

Sheet SVC-2 Model
B2: SVC-2 — Enhanced Chat / Self-Serve | INITIATIVE MODEL
B3: Workstream: Servicing (ELT sponsor: Aaron | WSL: Tahira | IOs: Jackie Yu, Matt Anderson, Bob Hurst) • Model status: Seeded 1:1 from S2 vDraft5 (Base) — benefit ties to $14.77M
T5: 2026 | U5: 2026 | V5: 2026 | W5: 2026 | X5: 2026 | Y5: 2026 | Z5: 2026 | AA5: 2026 | AB5: 2026 | AC5: 2026 | AD5: 2026 | AE5: 2026 | AF5: 2027 | AG5: 2027 | AH5: 2027 | AI5: 2027 | AJ5: 2027 | AK5: 2027 | AL5: 2027 | AM5: 2027 | AN5: 2027 | AO5: 2027 | AP5: 2027 | AQ5: 2027 | AR5: 2028 | AS5: 2028 | AT5: 2028 | AU5: 2028 | AV5: 2028 | AW5: 2028 | AX5: 2028 | AY5: 2028 | AZ5: 2028 | BA5: 2028 | BB5: 2028 | BC5: 2028 | BD5: 2029 | BE5: 2029 | BF5: 2029 | BG5: 2029 | BH5: 2029 | BI5: 2029 | BJ5: 2029 | BK5: 2029 | BL5: 2029 | BM5: 2029 | BN5: 2029 | BO5: 2029 | BP5: 2030 | BQ5: 2030 | BR5: 2030 | BS5: 2030 | BT5: 2030 | BU5: 2030 | BV5: 2030 | BW5: 2030 | BX5: 2030 | BY5: 2030 | BZ5: 2030 | CA5: 2030
B6: Monthly grid (Jan-26 → Dec-30) → | K6: Run rate | L6: 2026 | M6: 2027 | N6: 2028 | O6: 2029 | P6: 2030 | T6: =DATE(2026,1,31) -> 46053 | U6: =EOMONTH(T6,1) -> 46081 | V6: =EOMONTH(U6,1) -> 46112 | W6: =EOMONTH(V6,1) -> 46142 | X6: =EOMONTH(W6,1) -> 46173 | Y6: =EOMONTH(X6,1) -> 46203 | Z6: =EOMONTH(Y6,1) -> 46234 | AA6: =EOMONTH(Z6,1) -> 46265 | AB6: =EOMONTH(AA6,1) -> 46295 | ... CA6: =EOMONTH(BZ6,1) -> 47848
B8: 0. INITIATIVE & STATUS
B10: Initiative name | D10: Enhanced chat and self-serve containment on messaging and email demand
B11: Initiative owner | D11: Servicing IO — TBC (pool: Jackie Yu, Matt Anderson, Bob Hurst) | I11: confirm with workstream lead
B12: Impacted BU | D12: Global Servicing
B13: Go-live / Estimated L4 date | D13: =DATE(2027,9,1) -> 46631 | I13: Benefit ramp is gated on this date.
B15: Source: Servicing S2 sizing model vDraft5 (28 Aug 2026), Base scenario. Distilled to tier level; per-tier eligible bases and effective rates reproduce the S2 L2-intent engine output exactly (verified).
B16: Source: Workplan: 'Project Zenith Automation workplan and data requests vS_1.xlsx', Servicing tabs
B17: Open items to refine with initiative owner:
B18: – Voice channel is out of scope for this lever (S2 channel gate: chat acts on messaging + email only — $39.0M of the $143.2M opening baseline).
B19: – Effective rates embed the S2 ceiling logic (target containment capped at 90% of demand) and the 30% funnel-hardening haircut — underlying target rates: Easy 50% / Medium 40% / Hard 20% of escalated demand.
B20: – S2 books nothing where current PPA containment already beats the tier ceiling (2 intents).
B22: 1. SIZING ASSUMPTIONS (blue = inputs — refine with initiative owner)
B24: Opening baseline (S2 waterfall: opens on SVC-1 closing)
B25: Opening cost baseline (all channels) | D25: 1.4318592e+08 | E25: $/yr | F25: Servicing S2 sizing model vDraft5 (28 Aug 2026), Base scenario. Opening cost follows the S2 stacking waterfall (each lever opens on the prior lever's closing baseline; order: 1 Avoidance → 2 Chat → 3a Voice → 3b Co-pilot → 4a SBR → 4b Utilisation). Tier-level bases below are snapshots of the S2 L2 engine — refresh them from the S2 model if upstream levers or tiering change.
B26: Investment uplifts (S2 standard)
B27: Programme management, % of build | D27: 0.08 | E27: %
B28: Contingency, % of build incl. PM | D28: 0.1 | E28: %
B29: Run team headcount | D29: 3 | E29: # FTE | F29: S2 C3
B30: Run team loaded rate | D30: 180000 | E30: $/FTE/yr
B31: FTE impacted (A0 basis — feeds SVC-6) | D31: 867.7176 | E31: # FTE | F31: S2 A2 'Resource impacted' (V column, A0 basis). Residual-basis reduction is 779.7 — S2 uses the A0 basis in the non-FTE flow-through; refresh from S2 if rates change
B32: (spare assumption row)
B33: (spare assumption row)
B35: Eligible opening cost by tier — messaging + email channels only (S2 chat-tier column)
B36: Tier | D36: Eligible cost base ($/yr) | F36: Effective rate | H36: Benefit ($/yr) | M36: Effective rates implied from the S2 engine (benefit / eligible base per tier) — they bundle target rate, 90% containment ceiling and funnel hardening. Edit to test different containment ambitions.
B37: Easy (68 L2 intents) | D37: 27286882 | F37: 0.43111287 | H37: =D37*F37 -> 11763726 | M37: S2 target 50% of escalated demand; ceiling 90% binds on many rows -> effective 43.1%
B38: Medium (6 L2 intents) | D38: 3525444.7 | F38: 0.3886587 | H38: =D38*F38 -> 1370194.8 | M38: S2 target 40%; effective 38.9% after ceiling/hardening
B39: Hard (3 L2 intents) | D39: 8186544.4 | F39: 0.2 | H39: =D39*F39 -> 1637308.9 | M39: S2 target 20%
B40: Subtotal — Eligible opening cost by tier — messaging + email channels only | D40: =SUM(D37:D39) -> 38998872 | H40: =SUM(H37:H39) -> 14771230
B42: 2. BENEFIT CALCULATION (steady-state annual run-rate)
B44: Total annual benefit (steady state) | D44: =$H$40 -> 14771230 | E44: $/yr | F44: Ties to S2 A2 benefit $14,771,230
B45: Closing cost (hand-off baseline to SVC-3) | D45: =$D$25-$D$44 -> 1.2841469e+08 | E45: $/yr | F45: S2: $128,414,690
B47: 3. RAMP & PHASING
B49: Months to full run rate after go-live (linear ramp) | D49: 7 | F49: Benefit starts at go-live and ramps linearly to steady state over this many months.
B50: Monthly ramp % (run-rate captured in month) | T50: =MIN(1,MAX(0,((YEAR(T$6)-YEAR($D$13))*12+MONTH(T$6)-MONTH($D$13)+0.5)/MAX($D$49,0.5))) -> 0 | U50: =MIN(1,MAX(0,((YEAR(U$6)-YEAR($D$13))*12+MONTH(U$6)-MONTH($D$13)+0.5)/MAX($D$49,0.5))) -> 0 | V50: =MIN(1,MAX(0,((YEAR(V$6)-YEAR($D$13))*12+MONTH(V$6)-MONTH($D$13)+0.5)/MAX($D$49,0.5))) -> 0 | W50: =MIN(1,MAX(0,((YEAR(W$6)-YEAR($D$13))*12+MONTH(W$6)-MONTH($D$13)+0.5)/MAX($D$49,0.5))) -> 0 | X50: =MIN(1,MAX(0,((YEAR(X$6)-YEAR($D$13))*12+MONTH(X$6)-MONTH($D$13)+0.5)/MAX($D$49,0.5))) -> 0 | Y50: =MIN(1,MAX(0,((YEAR(Y$6)-YEAR($D$13))*12+MONTH(Y$6)-MONTH($D$13)+0.5)/MAX($D$49,0.5))) -> 0 | Z50: =MIN(1,MAX(0,((YEAR(Z$6)-YEAR($D$13))*12+MONTH(Z$6)-MONTH($D$13)+0.5)/MAX($D$49,0.5))) -> 0 | AA50: =MIN(1,MAX(0,((YEAR(AA$6)-YEAR($D$13))*12+MONTH(AA$6)-MONTH($D$13)+0.5)/MAX($D$49,0.5))) -> 0 | ... CA50: =MIN(1,MAX(0,((YEAR(CA$6)-YEAR($D$13))*12+MONTH(CA$6)-MONTH($D$13)+0.5)/MAX($D$49,0.5))) -> 1
B51: Resulting average ramp % by year (info) | L51: =SUMIFS($T50:$CA50,$T$5:$CA$5,2026)/12 -> 0 | M51: =SUMIFS($T50:$CA50,$T$5:$CA$5,2027)/12 -> 0.095238095 | N51: =SUMIFS($T50:$CA50,$T$5:$CA$5,2028)/12 -> 0.94642857 | O51: =SUMIFS($T50:$CA50,$T$5:$CA$5,2029)/12 -> 1 | P51: =SUMIFS($T50:$CA50,$T$5:$CA$5,2030)/12 -> 1
B53: 4. RECURRING BENEFIT LINES ($M — these rows feed the WAVE sheet)
B55: Line (WAVE category) | D55: Baseline $M | K55: Run rate
B56: OPEX - Front-office cost reduction (chat/self-serve containment) [OPEX] | D56: =$D$25/1000000 -> 143.18592 | K56: =SUMIFS($T56:$CA56,$T$5:$CA$5,2030) -> 14.77123 | L56: =SUMIFS($T56:$CA56,$T$5:$CA$5,2026) -> 0 | M56: =SUMIFS($T56:$CA56,$T$5:$CA$5,2027) -> 1.4067838 | N56: =SUMIFS($T56:$CA56,$T$5:$CA$5,2028) -> 13.979914 | O56: =SUMIFS($T56:$CA56,$T$5:$CA$5,2029) -> 14.77123 | P56: =SUMIFS($T56:$CA56,$T$5:$CA$5,2030) -> 14.77123 | T56: =($D$44)/1000000/12*T$50 -> 0 | U56: =($D$44)/1000000/12*U$50 -> 0 | V56: =($D$44)/1000000/12*V$50 -> 0 | W56: =($D$44)/1000000/12*W$50 -> 0 | X56: =($D$44)/1000000/12*X$50 -> 0 | Y56: =($D$44)/1000000/12*Y$50 -> 0 | Z56: =($D$44)/1000000/12*Z$50 -> 0 | AA56: =($D$44)/1000000/12*AA$50 -> 0 | ... CA56: =($D$44)/1000000/12*CA$50 -> 1.2309358
B57: Total recurring benefit ($M) | K57: =SUM(K56:K56) -> 14.77123 | L57: =SUM(L56:L56) -> 0 | M57: =SUM(M56:M56) -> 1.4067838 | N57: =SUM(N56:N56) -> 13.979914 | O57: =SUM(O56:O56) -> 14.77123 | P57: =SUM(P56:P56) -> 14.77123
B59: 5. ONE-TIME INVESTMENT — people cost by milestone (standard approach)
B61: Milestone | C61: Assumptions | D61: Team size | E61: Billing months | F61: Contingency Factor | G61: Labor Costs | H61: Start month | I61: Cap % (labor) | K61: Rate override ($/mo)
C62: Capture any assumptions on cost drivers, timelines, contingency factor etc. | E62: Months the team works at full utilization | F62: Low=10% Medium=15% High=20% Very high=50% | G62: Total labor costs for milestone | I62: Default links to Rate Card policy — type a % to override
B63: Plan / Design | C63: S2 build shape: 4 FTE x 2 months. | D63: 4 | E63: 2 | F63: 0.1 | G63: =D63*E63*IF(K63="",'Rate Card'!$G$29,K63)*(1+F63) -> 146666.67 | H63: =DATE(2027,1,1) -> 46388 | I63: ='Rate Card'!$C$45 -> 0
B64: Build / Test | C64: S2: 8-FTE pod x 6 months. | D64: 8 | E64: 6 | F64: 0.1 | G64: =D64*E64*IF(K64="",'Rate Card'!$G$29,K64)*(1+F64) -> 880000 | H64: =DATE(2027,3,1) -> 46447 | I64: ='Rate Card'!$C$46 -> 0
B65: Pilot / Change Mgmt. | C65: S2 scale-up: 5 FTE x 7 months. | D65: 5 | E65: 7 | F65: 0.1 | G65: =D65*E65*IF(K65="",'Rate Card'!$G$29,K65)*(1+F65) -> 641666.67 | H65: =DATE(2027,9,1) -> 46631 | I65: ='Rate Card'!$C$47 -> 0
B66: Scale / Run | C66: Run-phase support in Section 6 run costs. | D66: 0 | E66: 0 | F66: 0.1 | G66: =D66*E66*IF(K66="",'Rate Card'!$G$29,K66)*(1+F66) -> 0 | H66: =DATE(2028,4,1) -> 46844 | I66: ='Rate Card'!$C$48 -> 0
B68: Milestone labor phasing ($/month, spread evenly over billing months)
B69: Plan / Design | T69: =IF(AND(T$6>=EOMONTH($H$63,0),T$6<=EOMONTH(EDATE($H$63,$E$63-1),0)),$G$63/MAX($E$63,1),0) -> 0 | U69: =IF(AND(U$6>=EOMONTH($H$63,0),U$6<=EOMONTH(EDATE($H$63,$E$63-1),0)),$G$63/MAX($E$63,1),0) -> 0 | V69: =IF(AND(V$6>=EOMONTH($H$63,0),V$6<=EOMONTH(EDATE($H$63,$E$63-1),0)),$G$63/MAX($E$63,1),0) -> 0 | W69: =IF(AND(W$6>=EOMONTH($H$63,0),W$6<=EOMONTH(EDATE($H$63,$E$63-1),0)),$G$63/MAX($E$63,1),0) -> 0 | X69: =IF(AND(X$6>=EOMONTH($H$63,0),X$6<=EOMONTH(EDATE($H$63,$E$63-1),0)),$G$63/MAX($E$63,1),0) -> 0 | Y69: =IF(AND(Y$6>=EOMONTH($H$63,0),Y$6<=EOMONTH(EDATE($H$63,$E$63-1),0)),$G$63/MAX($E$63,1),0) -> 0 | Z69: =IF(AND(Z$6>=EOMONTH($H$63,0),Z$6<=EOMONTH(EDATE($H$63,$E$63-1),0)),$G$63/MAX($E$63,1),0) -> 0 | AA69: =IF(AND(AA$6>=EOMONTH($H$63,0),AA$6<=EOMONTH(EDATE($H$63,$E$63-1),0)),$G$63/MAX($E$63,1),0) -> 0 | ... CA69: =IF(AND(CA$6>=EOMONTH($H$63,0),CA$6<=EOMONTH(EDATE($H$63,$E$63-1),0)),$G$63/MAX($E$63,1),0) -> 0
B70: Build / Test | T70: =IF(AND(T$6>=EOMONTH($H$64,0),T$6<=EOMONTH(EDATE($H$64,$E$64-1),0)),$G$64/MAX($E$64,1),0) -> 0 | U70: =IF(AND(U$6>=EOMONTH($H$64,0),U$6<=EOMONTH(EDATE($H$64,$E$64-1),0)),$G$64/MAX($E$64,1),0) -> 0 | V70: =IF(AND(V$6>=EOMONTH($H$64,0),V$6<=EOMONTH(EDATE($H$64,$E$64-1),0)),$G$64/MAX($E$64,1),0) -> 0 | W70: =IF(AND(W$6>=EOMONTH($H$64,0),W$6<=EOMONTH(EDATE($H$64,$E$64-1),0)),$G$64/MAX($E$64,1),0) -> 0 | X70: =IF(AND(X$6>=EOMONTH($H$64,0),X$6<=EOMONTH(EDATE($H$64,$E$64-1),0)),$G$64/MAX($E$64,1),0) -> 0 | Y70: =IF(AND(Y$6>=EOMONTH($H$64,0),Y$6<=EOMONTH(EDATE($H$64,$E$64-1),0)),$G$64/MAX($E$64,1),0) -> 0 | Z70: =IF(AND(Z$6>=EOMONTH($H$64,0),Z$6<=EOMONTH(EDATE($H$64,$E$64-1),0)),$G$64/MAX($E$64,1),0) -> 0 | AA70: =IF(AND(AA$6>=EOMONTH($H$64,0),AA$6<=EOMONTH(EDATE($H$64,$E$64-1),0)),$G$64/MAX($E$64,1),0) -> 0 | ... CA70: =IF(AND(CA$6>=EOMONTH($H$64,0),CA$6<=EOMONTH(EDATE($H$64,$E$64-1),0)),$G$64/MAX($E$64,1),0) -> 0
B71: Pilot / Change Mgmt. | T71: =IF(AND(T$6>=EOMONTH($H$65,0),T$6<=EOMONTH(EDATE($H$65,$E$65-1),0)),$G$65/MAX($E$65,1),0) -> 0 | U71: =IF(AND(U$6>=EOMONTH($H$65,0),U$6<=EOMONTH(EDATE($H$65,$E$65-1),0)),$G$65/MAX($E$65,1),0) -> 0 | V71: =IF(AND(V$6>=EOMONTH($H$65,0),V$6<=EOMONTH(EDATE($H$65,$E$65-1),0)),$G$65/MAX($E$65,1),0) -> 0 | W71: =IF(AND(W$6>=EOMONTH($H$65,0),W$6<=EOMONTH(EDATE($H$65,$E$65-1),0)),$G$65/MAX($E$65,1),0) -> 0 | X71: =IF(AND(X$6>=EOMONTH($H$65,0),X$6<=EOMONTH(EDATE($H$65,$E$65-1),0)),$G$65/MAX($E$65,1),0) -> 0 | Y71: =IF(AND(Y$6>=EOMONTH($H$65,0),Y$6<=EOMONTH(EDATE($H$65,$E$65-1),0)),$G$65/MAX($E$65,1),0) -> 0 | Z71: =IF(AND(Z$6>=EOMONTH($H$65,0),Z$6<=EOMONTH(EDATE($H$65,$E$65-1),0)),$G$65/MAX($E$65,1),0) -> 0 | AA71: =IF(AND(AA$6>=EOMONTH($H$65,0),AA$6<=EOMONTH(EDATE($H$65,$E$65-1),0)),$G$65/MAX($E$65,1),0) -> 0 | ... CA71: =IF(AND(CA$6>=EOMONTH($H$65,0),CA$6<=EOMONTH(EDATE($H$65,$E$65-1),0)),$G$65/MAX($E$65,1),0) -> 0
B72: Scale / Run | T72: =IF(AND(T$6>=EOMONTH($H$66,0),T$6<=EOMONTH(EDATE($H$66,$E$66-1),0)),$G$66/MAX($E$66,1),0) -> 0 | U72: =IF(AND(U$6>=EOMONTH($H$66,0),U$6<=EOMONTH(EDATE($H$66,$E$66-1),0)),$G$66/MAX($E$66,1),0) -> 0 | V72: =IF(AND(V$6>=EOMONTH($H$66,0),V$6<=EOMONTH(EDATE($H$66,$E$66-1),0)),$G$66/MAX($E$66,1),0) -> 0 | W72: =IF(AND(W$6>=EOMONTH($H$66,0),W$6<=EOMONTH(EDATE($H$66,$E$66-1),0)),$G$66/MAX($E$66,1),0) -> 0 | X72: =IF(AND(X$6>=EOMONTH($H$66,0),X$6<=EOMONTH(EDATE($H$66,$E$66-1),0)),$G$66/MAX($E$66,1),0) -> 0 | Y72: =IF(AND(Y$6>=EOMONTH($H$66,0),Y$6<=EOMONTH(EDATE($H$66,$E$66-1),0)),$G$66/MAX($E$66,1),0) -> 0 | Z72: =IF(AND(Z$6>=EOMONTH($H$66,0),Z$6<=EOMONTH(EDATE($H$66,$E$66-1),0)),$G$66/MAX($E$66,1),0) -> 0 | AA72: =IF(AND(AA$6>=EOMONTH($H$66,0),AA$6<=EOMONTH(EDATE($H$66,$E$66-1),0)),$G$66/MAX($E$66,1),0) -> 0 | ... CA72: =IF(AND(CA$6>=EOMONTH($H$66,0),CA$6<=EOMONTH(EDATE($H$66,$E$66-1),0)),$G$66/MAX($E$66,1),0) -> 0
B73: Total milestone labor (all blocks) | G73: =SUM(G63:G66) -> 1668333.3
B75: One-time non-labor costs (vendor, integration, licences, change mgmt., etc.)
B76: Item | C76: Assumptions / notes | D76: Total $ | E76: Spread months | H76: Start month | I76: Cap %
B77: Platform and licence set-up | C77: S2 C2 planning number | D77: 80000 | E77: 2 | H77: =DATE(2027,3,1) -> 46447 | I77: 0
B78: Hardware and infrastructure | C78: S2 C2 planning number | D78: 180000 | E78: 6 | H78: =DATE(2027,3,1) -> 46447 | I78: 0
B79: Integration connectors | C79: S2 C2 planning number | D79: 120000 | E79: 6 | H79: =DATE(2027,3,1) -> 46447 | I79: 0
B80: Cloud compute for build & evaluation | C80: S2 C2 planning number | D80: 60000 | E80: 6 | H80: =DATE(2027,3,1) -> 46447 | I80: 0
B81: Programme management (8% of build) | C81: S2 standard | D81: =$D$27*($G$73+$D$77+$D$78+$D$79+$D$80) -> 168666.67 | E81: 15 | H81: =DATE(2027,1,1) -> 46388 | I81: 0
B82: Contingency (10% of build incl. PM) | C82: Total one-time ties to S2: $2,504,700 | D82: =$D$28*($G$73+$D$77+$D$78+$D$79+$D$80+$D$81) -> 227700 | E82: 15 | H82: =DATE(2027,1,1) -> 46388 | I82: 0
B83: (spare) | D83: 0 | E83: 1 | H83: =DATE(2027,9,1) -> 46631 | I83: 0
B85: Non-labor phasing ($/month)
B86: phasing — item 1 | T86: =IF(AND(T$6>=EOMONTH($H$77,0),T$6<=EOMONTH(EDATE($H$77,$E$77-1),0)),$D$77/MAX($E$77,1),0) -> 0 | U86: =IF(AND(U$6>=EOMONTH($H$77,0),U$6<=EOMONTH(EDATE($H$77,$E$77-1),0)),$D$77/MAX($E$77,1),0) -> 0 | V86: =IF(AND(V$6>=EOMONTH($H$77,0),V$6<=EOMONTH(EDATE($H$77,$E$77-1),0)),$D$77/MAX($E$77,1),0) -> 0 | W86: =IF(AND(W$6>=EOMONTH($H$77,0),W$6<=EOMONTH(EDATE($H$77,$E$77-1),0)),$D$77/MAX($E$77,1),0) -> 0 | X86: =IF(AND(X$6>=EOMONTH($H$77,0),X$6<=EOMONTH(EDATE($H$77,$E$77-1),0)),$D$77/MAX($E$77,1),0) -> 0 | Y86: =IF(AND(Y$6>=EOMONTH($H$77,0),Y$6<=EOMONTH(EDATE($H$77,$E$77-1),0)),$D$77/MAX($E$77,1),0) -> 0 | Z86: =IF(AND(Z$6>=EOMONTH($H$77,0),Z$6<=EOMONTH(EDATE($H$77,$E$77-1),0)),$D$77/MAX($E$77,1),0) -> 0 | AA86: =IF(AND(AA$6>=EOMONTH($H$77,0),AA$6<=EOMONTH(EDATE($H$77,$E$77-1),0)),$D$77/MAX($E$77,1),0) -> 0 | ... CA86: =IF(AND(CA$6>=EOMONTH($H$77,0),CA$6<=EOMONTH(EDATE($H$77,$E$77-1),0)),$D$77/MAX($E$77,1),0) -> 0
B87: phasing — item 2 | T87: =IF(AND(T$6>=EOMONTH($H$78,0),T$6<=EOMONTH(EDATE($H$78,$E$78-1),0)),$D$78/MAX($E$78,1),0) -> 0 | U87: =IF(AND(U$6>=EOMONTH($H$78,0),U$6<=EOMONTH(EDATE($H$78,$E$78-1),0)),$D$78/MAX($E$78,1),0) -> 0 | V87: =IF(AND(V$6>=EOMONTH($H$78,0),V$6<=EOMONTH(EDATE($H$78,$E$78-1),0)),$D$78/MAX($E$78,1),0) -> 0 | W87: =IF(AND(W$6>=EOMONTH($H$78,0),W$6<=EOMONTH(EDATE($H$78,$E$78-1),0)),$D$78/MAX($E$78,1),0) -> 0 | X87: =IF(AND(X$6>=EOMONTH($H$78,0),X$6<=EOMONTH(EDATE($H$78,$E$78-1),0)),$D$78/MAX($E$78,1),0) -> 0 | Y87: =IF(AND(Y$6>=EOMONTH($H$78,0),Y$6<=EOMONTH(EDATE($H$78,$E$78-1),0)),$D$78/MAX($E$78,1),0) -> 0 | Z87: =IF(AND(Z$6>=EOMONTH($H$78,0),Z$6<=EOMONTH(EDATE($H$78,$E$78-1),0)),$D$78/MAX($E$78,1),0) -> 0 | AA87: =IF(AND(AA$6>=EOMONTH($H$78,0),AA$6<=EOMONTH(EDATE($H$78,$E$78-1),0)),$D$78/MAX($E$78,1),0) -> 0 | ... CA87: =IF(AND(CA$6>=EOMONTH($H$78,0),CA$6<=EOMONTH(EDATE($H$78,$E$78-1),0)),$D$78/MAX($E$78,1),0) -> 0
B88: phasing — item 3 | T88: =IF(AND(T$6>=EOMONTH($H$79,0),T$6<=EOMONTH(EDATE($H$79,$E$79-1),0)),$D$79/MAX($E$79,1),0) -> 0 | U88: =IF(AND(U$6>=EOMONTH($H$79,0),U$6<=EOMONTH(EDATE($H$79,$E$79-1),0)),$D$79/MAX($E$79,1),0) -> 0 | V88: =IF(AND(V$6>=EOMONTH($H$79,0),V$6<=EOMONTH(EDATE($H$79,$E$79-1),0)),$D$79/MAX($E$79,1),0) -> 0 | W88: =IF(AND(W$6>=EOMONTH($H$79,0),W$6<=EOMONTH(EDATE($H$79,$E$79-1),0)),$D$79/MAX($E$79,1),0) -> 0 | X88: =IF(AND(X$6>=EOMONTH($H$79,0),X$6<=EOMONTH(EDATE($H$79,$E$79-1),0)),$D$79/MAX($E$79,1),0) -> 0 | Y88: =IF(AND(Y$6>=EOMONTH($H$79,0),Y$6<=EOMONTH(EDATE($H$79,$E$79-1),0)),$D$79/MAX($E$79,1),0) -> 0 | Z88: =IF(AND(Z$6>=EOMONTH($H$79,0),Z$6<=EOMONTH(EDATE($H$79,$E$79-1),0)),$D$79/MAX($E$79,1),0) -> 0 | AA88: =IF(AND(AA$6>=EOMONTH($H$79,0),AA$6<=EOMONTH(EDATE($H$79,$E$79-1),0)),$D$79/MAX($E$79,1),0) -> 0 | ... CA88: =IF(AND(CA$6>=EOMONTH($H$79,0),CA$6<=EOMONTH(EDATE($H$79,$E$79-1),0)),$D$79/MAX($E$79,1),0) -> 0
B89: phasing — item 4 | T89: =IF(AND(T$6>=EOMONTH($H$80,0),T$6<=EOMONTH(EDATE($H$80,$E$80-1),0)),$D$80/MAX($E$80,1),0) -> 0 | U89: =IF(AND(U$6>=EOMONTH($H$80,0),U$6<=EOMONTH(EDATE($H$80,$E$80-1),0)),$D$80/MAX($E$80,1),0) -> 0 | V89: =IF(AND(V$6>=EOMONTH($H$80,0),V$6<=EOMONTH(EDATE($H$80,$E$80-1),0)),$D$80/MAX($E$80,1),0) -> 0 | W89: =IF(AND(W$6>=EOMONTH($H$80,0),W$6<=EOMONTH(EDATE($H$80,$E$80-1),0)),$D$80/MAX($E$80,1),0) -> 0 | X89: =IF(AND(X$6>=EOMONTH($H$80,0),X$6<=EOMONTH(EDATE($H$80,$E$80-1),0)),$D$80/MAX($E$80,1),0) -> 0 | Y89: =IF(AND(Y$6>=EOMONTH($H$80,0),Y$6<=EOMONTH(EDATE($H$80,$E$80-1),0)),$D$80/MAX($E$80,1),0) -> 0 | Z89: =IF(AND(Z$6>=EOMONTH($H$80,0),Z$6<=EOMONTH(EDATE($H$80,$E$80-1),0)),$D$80/MAX($E$80,1),0) -> 0 | AA89: =IF(AND(AA$6>=EOMONTH($H$80,0),AA$6<=EOMONTH(EDATE($H$80,$E$80-1),0)),$D$80/MAX($E$80,1),0) -> 0 | ... CA89: =IF(AND(CA$6>=EOMONTH($H$80,0),CA$6<=EOMONTH(EDATE($H$80,$E$80-1),0)),$D$80/MAX($E$80,1),0) -> 0
B90: phasing — item 5 | T90: =IF(AND(T$6>=EOMONTH($H$81,0),T$6<=EOMONTH(EDATE($H$81,$E$81-1),0)),$D$81/MAX($E$81,1),0) -> 0 | U90: =IF(AND(U$6>=EOMONTH($H$81,0),U$6<=EOMONTH(EDATE($H$81,$E$81-1),0)),$D$81/MAX($E$81,1),0) -> 0 | V90: =IF(AND(V$6>=EOMONTH($H$81,0),V$6<=EOMONTH(EDATE($H$81,$E$81-1),0)),$D$81/MAX($E$81,1),0) -> 0 | W90: =IF(AND(W$6>=EOMONTH($H$81,0),W$6<=EOMONTH(EDATE($H$81,$E$81-1),0)),$D$81/MAX($E$81,1),0) -> 0 | X90: =IF(AND(X$6>=EOMONTH($H$81,0),X$6<=EOMONTH(EDATE($H$81,$E$81-1),0)),$D$81/MAX($E$81,1),0) -> 0 | Y90: =IF(AND(Y$6>=EOMONTH($H$81,0),Y$6<=EOMONTH(EDATE($H$81,$E$81-1),0)),$D$81/MAX($E$81,1),0) -> 0 | Z90: =IF(AND(Z$6>=EOMONTH($H$81,0),Z$6<=EOMONTH(EDATE($H$81,$E$81-1),0)),$D$81/MAX($E$81,1),0) -> 0 | AA90: =IF(AND(AA$6>=EOMONTH($H$81,0),AA$6<=EOMONTH(EDATE($H$81,$E$81-1),0)),$D$81/MAX($E$81,1),0) -> 0 | ... CA90: =IF(AND(CA$6>=EOMONTH($H$81,0),CA$6<=EOMONTH(EDATE($H$81,$E$81-1),0)),$D$81/MAX($E$81,1),0) -> 0
B91: phasing — item 6 | T91: =IF(AND(T$6>=EOMONTH($H$82,0),T$6<=EOMONTH(EDATE($H$82,$E$82-1),0)),$D$82/MAX($E$82,1),0) -> 0 | U91: =IF(AND(U$6>=EOMONTH($H$82,0),U$6<=EOMONTH(EDATE($H$82,$E$82-1),0)),$D$82/MAX($E$82,1),0) -> 0 | V91: =IF(AND(V$6>=EOMONTH($H$82,0),V$6<=EOMONTH(EDATE($H$82,$E$82-1),0)),$D$82/MAX($E$82,1),0) -> 0 | W91: =IF(AND(W$6>=EOMONTH($H$82,0),W$6<=EOMONTH(EDATE($H$82,$E$82-1),0)),$D$82/MAX($E$82,1),0) -> 0 | X91: =IF(AND(X$6>=EOMONTH($H$82,0),X$6<=EOMONTH(EDATE($H$82,$E$82-1),0)),$D$82/MAX($E$82,1),0) -> 0 | Y91: =IF(AND(Y$6>=EOMONTH($H$82,0),Y$6<=EOMONTH(EDATE($H$82,$E$82-1),0)),$D$82/MAX($E$82,1),0) -> 0 | Z91: =IF(AND(Z$6>=EOMONTH($H$82,0),Z$6<=EOMONTH(EDATE($H$82,$E$82-1),0)),$D$82/MAX($E$82,1),0) -> 0 | AA91: =IF(AND(AA$6>=EOMONTH($H$82,0),AA$6<=EOMONTH(EDATE($H$82,$E$82-1),0)),$D$82/MAX($E$82,1),0) -> 0 | ... CA91: =IF(AND(CA$6>=EOMONTH($H$82,0),CA$6<=EOMONTH(EDATE($H$82,$E$82-1),0)),$D$82/MAX($E$82,1),0) -> 0
B92: phasing — item 7 | T92: =IF(AND(T$6>=EOMONTH($H$83,0),T$6<=EOMONTH(EDATE($H$83,$E$83-1),0)),$D$83/MAX($E$83,1),0) -> 0 | U92: =IF(AND(U$6>=EOMONTH($H$83,0),U$6<=EOMONTH(EDATE($H$83,$E$83-1),0)),$D$83/MAX($E$83,1),0) -> 0 | V92: =IF(AND(V$6>=EOMONTH($H$83,0),V$6<=EOMONTH(EDATE($H$83,$E$83-1),0)),$D$83/MAX($E$83,1),0) -> 0 | W92: =IF(AND(W$6>=EOMONTH($H$83,0),W$6<=EOMONTH(EDATE($H$83,$E$83-1),0)),$D$83/MAX($E$83,1),0) -> 0 | X92: =IF(AND(X$6>=EOMONTH($H$83,0),X$6<=EOMONTH(EDATE($H$83,$E$83-1),0)),$D$83/MAX($E$83,1),0) -> 0 | Y92: =IF(AND(Y$6>=EOMONTH($H$83,0),Y$6<=EOMONTH(EDATE($H$83,$E$83-1),0)),$D$83/MAX($E$83,1),0) -> 0 | Z92: =IF(AND(Z$6>=EOMONTH($H$83,0),Z$6<=EOMONTH(EDATE($H$83,$E$83-1),0)),$D$83/MAX($E$83,1),0) -> 0 | AA92: =IF(AND(AA$6>=EOMONTH($H$83,0),AA$6<=EOMONTH(EDATE($H$83,$E$83-1),0)),$D$83/MAX($E$83,1),0) -> 0 | ... CA92: =IF(AND(CA$6>=EOMONTH($H$83,0),CA$6<=EOMONTH(EDATE($H$83,$E$83-1),0)),$D$83/MAX($E$83,1),0) -> 0
B94: One-time investment feed rows ($M — these feed the WAVE sheet)
B95: CAPEX — capitalized build labor | L95: =SUMIFS($T95:$CA95,$T$5:$CA$5,2026) -> 0 | M95: =SUMIFS($T95:$CA95,$T$5:$CA$5,2027) -> 0 | N95: =SUMIFS($T95:$CA95,$T$5:$CA$5,2028) -> 0 | O95: =SUMIFS($T95:$CA95,$T$5:$CA$5,2029) -> 0 | P95: =SUMIFS($T95:$CA95,$T$5:$CA$5,2030) -> 0 | T95: =(SUMPRODUCT(T69:T72,$I$63:$I$66))/1000000 -> 0 | U95: =(SUMPRODUCT(U69:U72,$I$63:$I$66))/1000000 -> 0 | V95: =(SUMPRODUCT(V69:V72,$I$63:$I$66))/1000000 -> 0 | W95: =(SUMPRODUCT(W69:W72,$I$63:$I$66))/1000000 -> 0 | X95: =(SUMPRODUCT(X69:X72,$I$63:$I$66))/1000000 -> 0 | Y95: =(SUMPRODUCT(Y69:Y72,$I$63:$I$66))/1000000 -> 0 | Z95: =(SUMPRODUCT(Z69:Z72,$I$63:$I$66))/1000000 -> 0 | AA95: =(SUMPRODUCT(AA69:AA72,$I$63:$I$66))/1000000 -> 0 | ... CA95: =(SUMPRODUCT(CA69:CA72,$I$63:$I$66))/1000000 -> 0
B96: CAPEX — capitalized non-labor | L96: =SUMIFS($T96:$CA96,$T$5:$CA$5,2026) -> 0 | M96: =SUMIFS($T96:$CA96,$T$5:$CA$5,2027) -> 0 | N96: =SUMIFS($T96:$CA96,$T$5:$CA$5,2028) -> 0 | O96: =SUMIFS($T96:$CA96,$T$5:$CA$5,2029) -> 0 | P96: =SUMIFS($T96:$CA96,$T$5:$CA$5,2030) -> 0 | T96: =SUMPRODUCT(T86:T92,$I$77:$I$83)/1000000 -> 0 | U96: =SUMPRODUCT(U86:U92,$I$77:$I$83)/1000000 -> 0 | V96: =SUMPRODUCT(V86:V92,$I$77:$I$83)/1000000 -> 0 | W96: =SUMPRODUCT(W86:W92,$I$77:$I$83)/1000000 -> 0 | X96: =SUMPRODUCT(X86:X92,$I$77:$I$83)/1000000 -> 0 | Y96: =SUMPRODUCT(Y86:Y92,$I$77:$I$83)/1000000 -> 0 | Z96: =SUMPRODUCT(Z86:Z92,$I$77:$I$83)/1000000 -> 0 | AA96: =SUMPRODUCT(AA86:AA92,$I$77:$I$83)/1000000 -> 0 | ... CA96: =SUMPRODUCT(CA86:CA92,$I$77:$I$83)/1000000 -> 0
B97: OTC — build labor (expensed) | L97: =SUMIFS($T97:$CA97,$T$5:$CA$5,2026) -> 0 | M97: =SUMIFS($T97:$CA97,$T$5:$CA$5,2027) -> 1.3933333 | N97: =SUMIFS($T97:$CA97,$T$5:$CA$5,2028) -> 0.275 | O97: =SUMIFS($T97:$CA97,$T$5:$CA$5,2029) -> 0 | P97: =SUMIFS($T97:$CA97,$T$5:$CA$5,2030) -> 0 | T97: =(SUMPRODUCT(T69:T72,1-$I$63:$I$66))/1000000 -> 0 | U97: =(SUMPRODUCT(U69:U72,1-$I$63:$I$66))/1000000 -> 0 | V97: =(SUMPRODUCT(V69:V72,1-$I$63:$I$66))/1000000 -> 0 | W97: =(SUMPRODUCT(W69:W72,1-$I$63:$I$66))/1000000 -> 0 | X97: =(SUMPRODUCT(X69:X72,1-$I$63:$I$66))/1000000 -> 0 | Y97: =(SUMPRODUCT(Y69:Y72,1-$I$63:$I$66))/1000000 -> 0 | Z97: =(SUMPRODUCT(Z69:Z72,1-$I$63:$I$66))/1000000 -> 0 | AA97: =(SUMPRODUCT(AA69:AA72,1-$I$63:$I$66))/1000000 -> 0 | ... CA97: =(SUMPRODUCT(CA69:CA72,1-$I$63:$I$66))/1000000 -> 0
B98: OTC — non-labor (expensed) | L98: =SUMIFS($T98:$CA98,$T$5:$CA$5,2026) -> 0 | M98: =SUMIFS($T98:$CA98,$T$5:$CA$5,2027) -> 0.75709333 | N98: =SUMIFS($T98:$CA98,$T$5:$CA$5,2028) -> 0.079273333 | O98: =SUMIFS($T98:$CA98,$T$5:$CA$5,2029) -> 0 | P98: =SUMIFS($T98:$CA98,$T$5:$CA$5,2030) -> 0 | T98: =SUMPRODUCT(T86:T92,1-$I$77:$I$83)/1000000 -> 0 | U98: =SUMPRODUCT(U86:U92,1-$I$77:$I$83)/1000000 -> 0 | V98: =SUMPRODUCT(V86:V92,1-$I$77:$I$83)/1000000 -> 0 | W98: =SUMPRODUCT(W86:W92,1-$I$77:$I$83)/1000000 -> 0 | X98: =SUMPRODUCT(X86:X92,1-$I$77:$I$83)/1000000 -> 0 | Y98: =SUMPRODUCT(Y86:Y92,1-$I$77:$I$83)/1000000 -> 0 | Z98: =SUMPRODUCT(Z86:Z92,1-$I$77:$I$83)/1000000 -> 0 | AA98: =SUMPRODUCT(AA86:AA92,1-$I$77:$I$83)/1000000 -> 0 | ... CA98: =SUMPRODUCT(CA86:CA92,1-$I$77:$I$83)/1000000 -> 0
B99: Total one-time investment ($M) | L99: =SUM(L95:L98) -> 0 | M99: =SUM(M95:M98) -> 2.1504267 | N99: =SUM(N95:N98) -> 0.35427333 | O99: =SUM(O95:O98) -> 0 | P99: =SUM(P95:P98) -> 0
B101: 6. RECURRING RUN COSTS to achieve impact
B103: Line | C103: Assumptions / notes | D103: Annual $ (steady state) | H103: Start month | I103: Scales with ramp? (Y/N)
B104: OPEX - Inference & token consumption | C104: S2 C3 planning assumption — replace with consumption forecast; scales with ramp | D104: 1200000 | H104: =DATE(2027,9,1) -> 46631 | I104: Y
B105: OPEX - AI platform subscription | C105: S2 C3 planning number | D105: 300000 | H105: =DATE(2027,9,1) -> 46631 | I105: N
B106: OPEX - Run team (keep-the-lights-on) | C106: S2 C3: 3.0 FTE x $180k | D106: =$D$29*$D$30 -> 540000 | H106: =DATE(2027,9,1) -> 46631 | I106: N
B107: OPEX - Vendor support & maintenance | C107: S2 C3 planning number | D107: 200000 | H107: =DATE(2027,9,1) -> 46631 | I107: N
B108: OPEX - Incremental infrastructure | C108: S2 C3 planning number | D108: 100000 | H108: =DATE(2027,9,1) -> 46631 | I108: N
B110: Run-cost feed rows ($M)
B111: OPEX - Inference & token consumption [RUN] | K111: =SUMIFS($T111:$CA111,$T$5:$CA$5,2030) -> 1.2 | L111: =SUMIFS($T111:$CA111,$T$5:$CA$5,2026) -> 0 | M111: =SUMIFS($T111:$CA111,$T$5:$CA$5,2027) -> 0.11428571 | N111: =SUMIFS($T111:$CA111,$T$5:$CA$5,2028) -> 1.1357143 | O111: =SUMIFS($T111:$CA111,$T$5:$CA$5,2029) -> 1.2 | P111: =SUMIFS($T111:$CA111,$T$5:$CA$5,2030) -> 1.2 | T111: =$D$104/1000000/12*IF($I$104="Y",T$50,IF(T$6>=EOMONTH($H$104,0),1,0)) -> 0 | U111: =$D$104/1000000/12*IF($I$104="Y",U$50,IF(U$6>=EOMONTH($H$104,0),1,0)) -> 0 | V111: =$D$104/1000000/12*IF($I$104="Y",V$50,IF(V$6>=EOMONTH($H$104,0),1,0)) -> 0 | W111: =$D$104/1000000/12*IF($I$104="Y",W$50,IF(W$6>=EOMONTH($H$104,0),1,0)) -> 0 | X111: =$D$104/1000000/12*IF($I$104="Y",X$50,IF(X$6>=EOMONTH($H$104,0),1,0)) -> 0 | Y111: =$D$104/1000000/12*IF($I$104="Y",Y$50,IF(Y$6>=EOMONTH($H$104,0),1,0)) -> 0 | Z111: =$D$104/1000000/12*IF($I$104="Y",Z$50,IF(Z$6>=EOMONTH($H$104,0),1,0)) -> 0 | AA111: =$D$104/1000000/12*IF($I$104="Y",AA$50,IF(AA$6>=EOMONTH($H$104,0),1,0)) -> 0 | ... CA111: =$D$104/1000000/12*IF($I$104="Y",CA$50,IF(CA$6>=EOMONTH($H$104,0),1,0)) -> 0.1
B112: OPEX - AI platform subscription [RUN] | K112: =SUMIFS($T112:$CA112,$T$5:$CA$5,2030) -> 0.3 | L112: =SUMIFS($T112:$CA112,$T$5:$CA$5,2026) -> 0 | M112: =SUMIFS($T112:$CA112,$T$5:$CA$5,2027) -> 0.1 | N112: =SUMIFS($T112:$CA112,$T$5:$CA$5,2028) -> 0.3 | O112: =SUMIFS($T112:$CA112,$T$5:$CA$5,2029) -> 0.3 | P112: =SUMIFS($T112:$CA112,$T$5:$CA$5,2030) -> 0.3 | T112: =$D$105/1000000/12*IF($I$105="Y",T$50,IF(T$6>=EOMONTH($H$105,0),1,0)) -> 0 | U112: =$D$105/1000000/12*IF($I$105="Y",U$50,IF(U$6>=EOMONTH($H$105,0),1,0)) -> 0 | V112: =$D$105/1000000/12*IF($I$105="Y",V$50,IF(V$6>=EOMONTH($H$105,0),1,0)) -> 0 | W112: =$D$105/1000000/12*IF($I$105="Y",W$50,IF(W$6>=EOMONTH($H$105,0),1,0)) -> 0 | X112: =$D$105/1000000/12*IF($I$105="Y",X$50,IF(X$6>=EOMONTH($H$105,0),1,0)) -> 0 | Y112: =$D$105/1000000/12*IF($I$105="Y",Y$50,IF(Y$6>=EOMONTH($H$105,0),1,0)) -> 0 | Z112: =$D$105/1000000/12*IF($I$105="Y",Z$50,IF(Z$6>=EOMONTH($H$105,0),1,0)) -> 0 | AA112: =$D$105/1000000/12*IF($I$105="Y",AA$50,IF(AA$6>=EOMONTH($H$105,0),1,0)) -> 0 | ... CA112: =$D$105/1000000/12*IF($I$105="Y",CA$50,IF(CA$6>=EOMONTH($H$105,0),1,0)) -> 0.025
B113: OPEX - Run team (keep-the-lights-on) [RUN] | K113: =SUMIFS($T113:$CA113,$T$5:$CA$5,2030) -> 0.54 | L113: =SUMIFS($T113:$CA113,$T$5:$CA$5,2026) -> 0 | M113: =SUMIFS($T113:$CA113,$T$5:$CA$5,2027) -> 0.18 | N113: =SUMIFS($T113:$CA113,$T$5:$CA$5,2028) -> 0.54 | O113: =SUMIFS($T113:$CA113,$T$5:$CA$5,2029) -> 0.54 | P113: =SUMIFS($T113:$CA113,$T$5:$CA$5,2030) -> 0.54 | T113: =$D$106/1000000/12*IF($I$106="Y",T$50,IF(T$6>=EOMONTH($H$106,0),1,0)) -> 0 | U113: =$D$106/1000000/12*IF($I$106="Y",U$50,IF(U$6>=EOMONTH($H$106,0),1,0)) -> 0 | V113: =$D$106/1000000/12*IF($I$106="Y",V$50,IF(V$6>=EOMONTH($H$106,0),1,0)) -> 0 | W113: =$D$106/1000000/12*IF($I$106="Y",W$50,IF(W$6>=EOMONTH($H$106,0),1,0)) -> 0 | X113: =$D$106/1000000/12*IF($I$106="Y",X$50,IF(X$6>=EOMONTH($H$106,0),1,0)) -> 0 | Y113: =$D$106/1000000/12*IF($I$106="Y",Y$50,IF(Y$6>=EOMONTH($H$106,0),1,0)) -> 0 | Z113: =$D$106/1000000/12*IF($I$106="Y",Z$50,IF(Z$6>=EOMONTH($H$106,0),1,0)) -> 0 | AA113: =$D$106/1000000/12*IF($I$106="Y",AA$50,IF(AA$6>=EOMONTH($H$106,0),1,0)) -> 0 | ... CA113: =$D$106/1000000/12*IF($I$106="Y",CA$50,IF(CA$6>=EOMONTH($H$106,0),1,0)) -> 0.045
B114: OPEX - Vendor support & maintenance [RUN] | K114: =SUMIFS($T114:$CA114,$T$5:$CA$5,2030) -> 0.2 | L114: =SUMIFS($T114:$CA114,$T$5:$CA$5,2026) -> 0 | M114: =SUMIFS($T114:$CA114,$T$5:$CA$5,2027) -> 0.066666667 | N114: =SUMIFS($T114:$CA114,$T$5:$CA$5,2028) -> 0.2 | O114: =SUMIFS($T114:$CA114,$T$5:$CA$5,2029) -> 0.2 | P114: =SUMIFS($T114:$CA114,$T$5:$CA$5,2030) -> 0.2 | T114: =$D$107/1000000/12*IF($I$107="Y",T$50,IF(T$6>=EOMONTH($H$107,0),1,0)) -> 0 | U114: =$D$107/1000000/12*IF($I$107="Y",U$50,IF(U$6>=EOMONTH($H$107,0),1,0)) -> 0 | V114: =$D$107/1000000/12*IF($I$107="Y",V$50,IF(V$6>=EOMONTH($H$107,0),1,0)) -> 0 | W114: =$D$107/1000000/12*IF($I$107="Y",W$50,IF(W$6>=EOMONTH($H$107,0),1,0)) -> 0 | X114: =$D$107/1000000/12*IF($I$107="Y",X$50,IF(X$6>=EOMONTH($H$107,0),1,0)) -> 0 | Y114: =$D$107/1000000/12*IF($I$107="Y",Y$50,IF(Y$6>=EOMONTH($H$107,0),1,0)) -> 0 | Z114: =$D$107/1000000/12*IF($I$107="Y",Z$50,IF(Z$6>=EOMONTH($H$107,0),1,0)) -> 0 | AA114: =$D$107/1000000/12*IF($I$107="Y",AA$50,IF(AA$6>=EOMONTH($H$107,0),1,0)) -> 0 | ... CA114: =$D$107/1000000/12*IF($I$107="Y",CA$50,IF(CA$6>=EOMONTH($H$107,0),1,0)) -> 0.016666667
B115: OPEX - Incremental infrastructure [RUN] | K115: =SUMIFS($T115:$CA115,$T$5:$CA$5,2030) -> 0.1 | L115: =SUMIFS($T115:$CA115,$T$5:$CA$5,2026) -> 0 | M115: =SUMIFS($T115:$CA115,$T$5:$CA$5,2027) -> 0.033333333 | N115: =SUMIFS($T115:$CA115,$T$5:$CA$5,2028) -> 0.1 | O115: =SUMIFS($T115:$CA115,$T$5:$CA$5,2029) -> 0.1 | P115: =SUMIFS($T115:$CA115,$T$5:$CA$5,2030) -> 0.1 | T115: =$D$108/1000000/12*IF($I$108="Y",T$50,IF(T$6>=EOMONTH($H$108,0),1,0)) -> 0 | U115: =$D$108/1000000/12*IF($I$108="Y",U$50,IF(U$6>=EOMONTH($H$108,0),1,0)) -> 0 | V115: =$D$108/1000000/12*IF($I$108="Y",V$50,IF(V$6>=EOMONTH($H$108,0),1,0)) -> 0 | W115: =$D$108/1000000/12*IF($I$108="Y",W$50,IF(W$6>=EOMONTH($H$108,0),1,0)) -> 0 | X115: =$D$108/1000000/12*IF($I$108="Y",X$50,IF(X$6>=EOMONTH($H$108,0),1,0)) -> 0 | Y115: =$D$108/1000000/12*IF($I$108="Y",Y$50,IF(Y$6>=EOMONTH($H$108,0),1,0)) -> 0 | Z115: =$D$108/1000000/12*IF($I$108="Y",Z$50,IF(Z$6>=EOMONTH($H$108,0),1,0)) -> 0 | AA115: =$D$108/1000000/12*IF($I$108="Y",AA$50,IF(AA$6>=EOMONTH($H$108,0),1,0)) -> 0 | ... CA115: =$D$108/1000000/12*IF($I$108="Y",CA$50,IF(CA$6>=EOMONTH($H$108,0),1,0)) -> 0.0083333333
B116: Total run cost ($M) | K116: =SUM(K111:K115) -> 2.34 | L116: =SUM(L111:L115) -> 0 | M116: =SUM(M111:M115) -> 0.49428571 | N116: =SUM(N111:N115) -> 2.2757143 | O116: =SUM(O111:O115) -> 2.34 | P116: =SUM(P111:P115) -> 2.34
B118: 7. WAVE MAPPING (reference)
B120: Model row 56 — OPEX - Front-office cost reduction (chat/self-serve containment) | F120: → WAVE row 79 (Section II — Recurring Benefits)
B121: Model row 111 — OPEX - Inference & token consumption | F121: → WAVE row 107 (Section II — Recurring Costs)
B122: Model row 112 — OPEX - AI platform subscription | F122: → WAVE row 108 (Section II — Recurring Costs)
B123: Model row 113 — OPEX - Run team (keep-the-lights-on) | F123: → WAVE row 109 (Section II — Recurring Costs)
B124: Model row 114 — OPEX - Vendor support & maintenance | F124: → WAVE row 110 (Section II — Recurring Costs)
B125: Model row 115 — OPEX - Incremental infrastructure | F125: → WAVE row 111 (Section II — Recurring Costs)
...

Sheet SVC-2 WAVE
L1: 1 | M1: 2 | N1: 3 | O1: 4 | P1: 5 | R1: =COUNTIFS($R$66:$R$117, "Error") -> 0 | T1: 2026 | U1: 2026 | V1: 2026 | W1: 2026 | X1: 2026 | Y1: 2026 | Z1: 2026 | AA1: 2026 | AB1: 2026 | AC1: 2026 | AD1: 2026 | AE1: 2026 | AF1: 2027 | AG1: 2027 | AH1: 2027 | AI1: 2027 | AJ1: 2027 | AK1: 2027 | AL1: 2027 | AM1: 2027 | AN1: 2027 | AO1: 2027 | AP1: 2027 | AQ1: 2027 | AR1: 2028 | AS1: 2028 | AT1: 2028 | AU1: 2028 | AV1: 2028 | AW1: 2028 | AX1: 2028 | AY1: 2028 | AZ1: 2028 | BA1: 2028 | BB1: 2028 | BC1: 2028 | BD1: 2029 | BE1: 2029 | BF1: 2029 | BG1: 2029 | BH1: 2029 | BI1: 2029 | BJ1: 2029 | BK1: 2029 | BL1: 2029 | BM1: 2029 | BN1: 2029 | BO1: 2029 | BP1: 2030 | BQ1: 2030 | BR1: 2030 | BS1: 2030 | BT1: 2030 | BU1: 2030 | BV1: 2030 | BW1: 2030 | BX1: 2030 | BY1: 2030 | BZ1: 2030 | CA1: 2030 | CI1: =COUNTIFS(CI$66:CI$149, "FALSE") -> 0 | CJ1: =COUNTIFS(CJ$66:CJ$149, "FALSE") -> 0 | CK1: =COUNTIFS(CK$66:CK$149, "FALSE") -> 0 | CL1: =COUNTIFS(CL$66:CL$149, "FALSE") -> 0 | CM1: =COUNTIFS(CM$66:CM$149, "FALSE") -> 0
C2: ="#"&$F$6&" Initiative Business Case" -> #TBD Initiative Business Case
C4: INPUTS & ASSUMPTIONS
D6: Initiative # | F6: TBD
D7: Initiative Owner | F7: Servicing IO — TBC (pool: Jackie Yu, Matt Anderson, Bob Hurst)
D8: Initiative Name | F8: Enhanced chat and self-serve containment on messaging and email demand
D11: Estimated L4 date | F11: ='SVC-2 Model'!$D$13 -> 46631
D12: Net Recurring Benefit ($M) | F12: =$K$117 -> 12.43123
C14: SECTION I - PRIMARY VALUE DRIVER (ILLUSTRATIVE)
D16: Primary value driver — linked to the Model sheet; refine with the initiative owner
D17: Baseline | H17: Period | I17: KPI | J17: Inputs
E18: Opening cost baseline (post contact-avoidance) | H18: Post-upstream levers (S2 waterfall) | I18: $USD M | J18: ='SVC-2 Model'!$D$25/1000000 -> 143.18592
E19: In-scope base (messaging + email) | H19: same | I19: $USD M | J19: =('SVC-2 Model'!$D$40)/1000000 -> 38.998872
D23: Goal
E24: Blended containment uplift on in-scope base | H24: Steady state | I24: % | J24: ='SVC-2 Model'!$D$44/'SVC-2 Model'!$D$40 -> 0.37876044
E25: FTE impacted (A0 basis) | H25: Steady state | I25: # FTE | J25: ='SVC-2 Model'!$D$31 -> 867.7176
D28: Incremental Improvement
E29: Annual benefit (run rate) | I29: $USD M | J29: ='SVC-2 Model'!$D$44/1000000 -> 14.77123
C60: SECTION II - NET RECURRING BENEFITS | CC60: ANNUAL SUMMARY | CI60: CHECK CELLS
T62: 2026 | AF62: 2027 | AR62: 2028 | BD62: 2029 | BP62: 2030 | CI62: CHECK
D63: RECURRING BENEFITS | H63: Comment | I63: Baseline | J63: Goal | K63: Ann. Run Rate | L63: 2026 | M63: =L63+1 -> 2027 | N63: =M63+1 -> 2028 | O63: =N63+1 -> 2029 | P63: =O63+1 -> 2030 | Q63: Impacted BU | R63: Check | T63: 46023 | U63: =EOMONTH(T63, 1) -> 46081 | V63: =EOMONTH(U63, 1) -> 46112 | W63: =EOMONTH(V63, 1) -> 46142 | X63: =EOMONTH(W63, 1) -> 46173 | Y63: =EOMONTH(X63, 1) -> 46203 | Z63: =EOMONTH(Y63, 1) -> 46234 | AA63: =EOMONTH(Z63, 1) -> 46265 | AB63: =EOMONTH(AA63, 1) -> 46295 | ... CA63: =EOMONTH(BZ63, 1) -> 47848 | CC63: 2026 | CD63: =CC63+1 -> 2027 | CE63: =CD63+1 -> 2028 | CF63: =CE63+1 -> 2029 | CG63: =CF63+1 -> 2030 | CI63: 2026 | CJ63: =CI63+1 -> 2027 | CK63: =CJ63+1 -> 2028 | CL63: =CK63+1 -> 2029 | CM63: =CL63+1 -> 2030
E64: $USD M | I64: =$H$18 -> Post-upstream levers (S2 waterfall) | J64: Future State | K64: Increment
E65: Revenue
I66: 0 | J66: 0 | K66: =J66-I66 -> 0 | R66: =IF(K66=P66, "", "Error") | CC66: =SUMIFS($T66:$CA66, $T$1:$CA$1, CC$63) -> 0 | CD66: =SUMIFS($T66:$CA66, $T$1:$CA$1, CD$63) -> 0 | CE66: =SUMIFS($T66:$CA66, $T$1:$CA$1, CE$63) -> 0 | CF66: =SUMIFS($T66:$CA66, $T$1:$CA$1, CF$63) -> 0 | CG66: =SUMIFS($T66:$CA66, $T$1:$CA$1, CG$63) -> 0 | CI66: =CC66=L66 -> 1 | CJ66: =CD66=M66 -> 1 | CK66: =CE66=N66 -> 1 | CL66: =CF66=O66 -> 1 | CM66: =CG66=P66 -> 1
I67: 0 | J67: 0 | K67: =J67-I67 -> 0 | R67: =IF(K67=P67, "", "Error") | CC67: =SUMIFS($T67:$CA67, $T$1:$CA$1, CC$63) -> 0 | CD67: =SUMIFS($T67:$CA67, $T$1:$CA$1, CD$63) -> 0 | CE67: =SUMIFS($T67:$CA67, $T$1:$CA$1, CE$63) -> 0 | CF67: =SUMIFS($T67:$CA67, $T$1:$CA$1, CF$63) -> 0 | CG67: =SUMIFS($T67:$CA67, $T$1:$CA$1, CG$63) -> 0 | CI67: =CC67=L67 -> 1 | CJ67: =CD67=M67 -> 1 | CK67: =CE67=N67 -> 1 | CL67: =CF67=O67 -> 1 | CM67: =CG67=P67 -> 1
E68: Revenue Subtotal | I68: =SUM(I66:I67) -> 0 | J68: =SUM(J66:J67) -> 0 | K68: =SUM(K66:K67) -> 0 | L68: =SUM(L66:L67) -> 0 | M68: =SUM(M66:M67) -> 0 | N68: =SUM(N66:N67) -> 0 | O68: =SUM(O66:O67) -> 0 | P68: =SUM(P66:P67) -> 0 | T68: =SUM(T66:T67) -> 0 | U68: =SUM(U66:U67) -> 0 | V68: =SUM(V66:V67) -> 0 | W68: =SUM(W66:W67) -> 0 | X68: =SUM(X66:X67) -> 0 | Y68: =SUM(Y66:Y67) -> 0 | Z68: =SUM(Z66:Z67) -> 0 | AA68: =SUM(AA66:AA67) -> 0 | ... CA68: =SUM(CA66:CA67) -> 0 | CC68: =SUM(CC66:CC67) -> 0 | CD68: =SUM(CD66:CD67) -> 0 | CE68: =SUM(CE66:CE67) -> 0 | CF68: =SUM(CF66:CF67) -> 0 | CG68: =SUM(CG66:CG67) -> 0 | CI68: =CC68=L68 -> 1 | CJ68: =CD68=M68 -> 1 | CK68: =CE68=N68 -> 1 | CL68: =CF68=O68 -> 1 | CM68: =CG68=P68 -> 1
E70: Cost of Sales
K71: =I71-J71 -> 0 | R71: =IF(K71=P71, "", "Error") | CC71: =SUMIFS($T71:$CA71, $T$1:$CA$1, CC$63) -> 0 | CD71: =SUMIFS($T71:$CA71, $T$1:$CA$1, CD$63) -> 0 | CE71: =SUMIFS($T71:$CA71, $T$1:$CA$1, CE$63) -> 0 | CF71: =SUMIFS($T71:$CA71, $T$1:$CA$1, CF$63) -> 0 | CG71: =SUMIFS($T71:$CA71, $T$1:$CA$1, CG$63) -> 0 | CI71: =CC71=L71 -> 1 | CJ71: =CD71=M71 -> 1 | CK71: =CE71=N71 -> 1 | CL71: =CF71=O71 -> 1 | CM71: =CG71=P71 -> 1
I72: 0 | J72: 0 | K72: =I72-J72 -> 0 | R72: =IF(K72=P72, "", "Error") | CC72: =SUMIFS($T72:$CA72, $T$1:$CA$1, CC$63) -> 0 | CD72: =SUMIFS($T72:$CA72, $T$1:$CA$1, CD$63) -> 0 | CE72: =SUMIFS($T72:$CA72, $T$1:$CA$1, CE$63) -> 0 | CF72: =SUMIFS($T72:$CA72, $T$1:$CA$1, CF$63) -> 0 | CG72: =SUMIFS($T72:$CA72, $T$1:$CA$1, CG$63) -> 0 | CI72: =CC72=L72 -> 1 | CJ72: =CD72=M72 -> 1 | CK72: =CE72=N72 -> 1 | CL72: =CF72=O72 -> 1 | CM72: =CG72=P72 -> 1
I73: 0 | J73: 0 | K73: =I73-J73 -> 0 | R73: =IF(K73=P73, "", "Error") | CC73: =SUMIFS($T73:$CA73, $T$1:$CA$1, CC$63) -> 0 | CD73: =SUMIFS($T73:$CA73, $T$1:$CA$1, CD$63) -> 0 | CE73: =SUMIFS($T73:$CA73, $T$1:$CA$1, CE$63) -> 0 | CF73: =SUMIFS($T73:$CA73, $T$1:$CA$1, CF$63) -> 0 | CG73: =SUMIFS($T73:$CA73, $T$1:$CA$1, CG$63) -> 0 | CI73: =CC73=L73 -> 1 | CJ73: =CD73=M73 -> 1 | CK73: =CE73=N73 -> 1 | CL73: =CF73=O73 -> 1 | CM73: =CG73=P73 -> 1
I74: 0 | J74: 0 | K74: =I74-J74 -> 0 | R74: =IF(K74=P74, "", "Error") | CC74: =SUMIFS($T74:$CA74, $T$1:$CA$1, CC$63) -> 0 | CD74: =SUMIFS($T74:$CA74, $T$1:$CA$1, CD$63) -> 0 | CE74: =SUMIFS($T74:$CA74, $T$1:$CA$1, CE$63) -> 0 | CF74: =SUMIFS($T74:$CA74, $T$1:$CA$1, CF$63) -> 0 | CG74: =SUMIFS($T74:$CA74, $T$1:$CA$1, CG$63) -> 0 | CI74: =CC74=L74 -> 1 | CJ74: =CD74=M74 -> 1 | CK74: =CE74=N74 -> 1 | CL74: =CF74=O74 -> 1 | CM74: =CG74=P74 -> 1
K75: =I75-J75 -> 0 | R75: =IF(K75=P75, "", "Error") | CC75: =SUMIFS($T75:$CA75, $T$1:$CA$1, CC$63) -> 0 | CD75: =SUMIFS($T75:$CA75, $T$1:$CA$1, CD$63) -> 0 | CE75: =SUMIFS($T75:$CA75, $T$1:$CA$1, CE$63) -> 0 | CF75: =SUMIFS($T75:$CA75, $T$1:$CA$1, CF$63) -> 0 | CG75: =SUMIFS($T75:$CA75, $T$1:$CA$1, CG$63) -> 0 | CI75: =CC75=L75 -> 1 | CJ75: =CD75=M75 -> 1 | CK75: =CE75=N75 -> 1 | CL75: =CF75=O75 -> 1 | CM75: =CG75=P75 -> 1
E76: Cost of Sales Subtotal | I76: =SUM(I71:I75) -> 0 | J76: =SUM(J71:J75) -> 0 | K76: =SUM(K71:K75) -> 0 | L76: =SUM(L71:L75) -> 0 | M76: =SUM(M71:M75) -> 0 | N76: =SUM(N71:N75) -> 0 | O76: =SUM(O71:O75) -> 0 | P76: =SUM(P71:P75) -> 0 | T76: =SUM(T71:T75) -> 0 | U76: =SUM(U71:U75) -> 0 | V76: =SUM(V71:V75) -> 0 | W76: =SUM(W71:W75) -> 0 | X76: =SUM(X71:X75) -> 0 | Y76: =SUM(Y71:Y75) -> 0 | Z76: =SUM(Z71:Z75) -> 0 | AA76: =SUM(AA71:AA75) -> 0 | ... CA76: =SUM(CA71:CA75) -> 0 | CC76: =SUM(CC71:CC75) -> 0 | CD76: =SUM(CD71:CD75) -> 0 | CE76: =SUM(CE71:CE75) -> 0 | CF76: =SUM(CF71:CF75) -> 0 | CG76: =SUM(CG71:CG75) -> 0 | CI76: =CC76=L76 -> 1 | CJ76: =CD76=M76 -> 1 | CK76: =CE76=N76 -> 1 | CL76: =CF76=O76 -> 1 | CM76: =CG76=P76 -> 1
E78: OPEX
E79: OPEX - Front-office cost reduction (chat/self-serve containment) | H79: Messaging+email eligible cost x tier containment rates (S2 engine, distilled) | I79: ='SVC-2 Model'!$D$56 -> 143.18592 | J79: =I79-'SVC-2 Model'!$K$56 -> 128.41469 | K79: ='SVC-2 Model'!$K$56 -> 14.77123 | L79: ='SVC-2 Model'!L56 -> 0 | M79: ='SVC-2 Model'!M56 -> 1.4067838 | N79: ='SVC-2 Model'!N56 -> 13.979914 | O79: ='SVC-2 Model'!O56 -> 14.77123 | P79: ='SVC-2 Model'!P56 -> 14.77123 | Q79: Global Servicing | R79: =IF(K79=P79, "", "Error") | T79: ='SVC-2 Model'!T56 -> 0 | U79: ='SVC-2 Model'!U56 -> 0 | V79: ='SVC-2 Model'!V56 -> 0 | W79: ='SVC-2 Model'!W56 -> 0 | X79: ='SVC-2 Model'!X56 -> 0 | Y79: ='SVC-2 Model'!Y56 -> 0 | Z79: ='SVC-2 Model'!Z56 -> 0 | AA79: ='SVC-2 Model'!AA56 -> 0 | ... CA79: ='SVC-2 Model'!CA56 -> 1.2309358 | CC79: =SUMIFS($T79:$CA79, $T$1:$CA$1, CC$63) -> 0 | CD79: =SUMIFS($T79:$CA79, $T$1:$CA$1, CD$63) -> 1.4067838 | CE79: =SUMIFS($T79:$CA79, $T$1:$CA$1, CE$63) -> 13.979914 | CF79: =SUMIFS($T79:$CA79, $T$1:$CA$1, CF$63) -> 14.77123 | CG79: =SUMIFS($T79:$CA79, $T$1:$CA$1, CG$63) -> 14.77123 | CI79: =CC79=L79 -> 1 | CJ79: =CD79=M79 -> 1 | CK79: =CE79=N79 -> 1 | CL79: =CF79=O79 -> 1 | CM79: =CG79=P79 -> 1
I80: 0 | J80: 0 | K80: =I80-J80 -> 0 | R80: =IF(K80=P80, "", "Error") | CC80: =SUMIFS($T80:$CA80, $T$1:$CA$1, CC$63) -> 0 | CD80: =SUMIFS($T80:$CA80, $T$1:$CA$1, CD$63) -> 0 | CE80: =SUMIFS($T80:$CA80, $T$1:$CA$1, CE$63) -> 0 | CF80: =SUMIFS($T80:$CA80, $T$1:$CA$1, CF$63) -> 0 | CG80: =SUMIFS($T80:$CA80, $T$1:$CA$1, CG$63) -> 0 | CI80: =CC80=L80 -> 1 | CJ80: =CD80=M80 -> 1 | CK80: =CE80=N80 -> 1 | CL80: =CF80=O80 -> 1 | CM80: =CG80=P80 -> 1
I81: 0 | J81: 0 | K81: =I81-J81 -> 0 | R81: =IF(K81=P81, "", "Error") | CC81: =SUMIFS($T81:$CA81, $T$1:$CA$1, CC$63) -> 0 | CD81: =SUMIFS($T81:$CA81, $T$1:$CA$1, CD$63) -> 0 | CE81: =SUMIFS($T81:$CA81, $T$1:$CA$1, CE$63) -> 0 | CF81: =SUMIFS($T81:$CA81, $T$1:$CA$1, CF$63) -> 0 | CG81: =SUMIFS($T81:$CA81, $T$1:$CA$1, CG$63) -> 0 | CI81: =CC81=L81 -> 1 | CJ81: =CD81=M81 -> 1 | CK81: =CE81=N81 -> 1 | CL81: =CF81=O81 -> 1 | CM81: =CG81=P81 -> 1
I82: 0 | J82: 0 | K82: =I82-J82 -> 0 | R82: =IF(K82=P82, "", "Error") | CC82: =SUMIFS($T82:$CA82, $T$1:$CA$1, CC$63) -> 0 | CD82: =SUMIFS($T82:$CA82, $T$1:$CA$1, CD$63) -> 0 | CE82: =SUMIFS($T82:$CA82, $T$1:$CA$1, CE$63) -> 0 | CF82: =SUMIFS($T82:$CA82, $T$1:$CA$1, CF$63) -> 0 | CG82: =SUMIFS($T82:$CA82, $T$1:$CA$1, CG$63) -> 0 | CI82: =CC82=L82 -> 1 | CJ82: =CD82=M82 -> 1 | CK82: =CE82=N82 -> 1 | CL82: =CF82=O82 -> 1 | CM82: =CG82=P82 -> 1
I83: 0 | J83: 0 | K83: =I83-J83 -> 0 | R83: =IF(K83=P83, "", "Error") | CC83: =SUMIFS($T83:$CA83, $T$1:$CA$1, CC$63) -> 0 | CD83: =SUMIFS($T83:$CA83, $T$1:$CA$1, CD$63) -> 0 | CE83: =SUMIFS($T83:$CA83, $T$1:$CA$1, CE$63) -> 0 | CF83: =SUMIFS($T83:$CA83, $T$1:$CA$1, CF$63) -> 0 | CG83: =SUMIFS($T83:$CA83, $T$1:$CA$1, CG$63) -> 0 | CI83: =CC83=L83 -> 1 | CJ83: =CD83=M83 -> 1 | CK83: =CE83=N83 -> 1 | CL83: =CF83=O83 -> 1 | CM83: =CG83=P83 -> 1
E84: OpEx subtotal | I84: =SUM(I79:I83) -> 143.18592 | J84: =SUM(J79:J83) -> 128.41469 | K84: =SUM(K79:K83) -> 14.77123 | L84: =SUM(L79:L83) -> 0 | M84: =SUM(M79:M83) -> 1.4067838 | N84: =SUM(N79:N83) -> 13.979914 | O84: =SUM(O79:O83) -> 14.77123 | P84: =SUM(P79:P83) -> 14.77123 | T84: =SUM(T79:T83) -> 0 | U84: =SUM(U79:U83) -> 0 | V84: =SUM(V79:V83) -> 0 | W84: =SUM(W79:W83) -> 0 | X84: =SUM(X79:X83) -> 0 | Y84: =SUM(Y79:Y83) -> 0 | Z84: =SUM(Z79:Z83) -> 0 | AA84: =SUM(AA79:AA83) -> 0 | ... CA84: =SUM(CA79:CA83) -> 1.2309358 | CC84: =SUM(CC79:CC83) -> 0 | CD84: =SUM(CD79:CD83) -> 1.4067838 | CE84: =SUM(CE79:CE83) -> 13.979914 | CF84: =SUM(CF79:CF83) -> 14.77123 | CG84: =SUM(CG79:CG83) -> 14.77123 | CI84: =CC84=L84 -> 1 | CJ84: =CD84=M84 -> 1 | CK84: =CE84=N84 -> 1 | CL84: =CF84=O84 -> 1 | CM84: =CG84=P84 -> 1
E88: Recurring Benefits Total | I88: =SUM(I68, I76, I84) -> 143.18592 | J88: =SUM(J68, J76, J84) -> 128.41469 | K88: =SUM(K68, K76, K84) -> 14.77123 | L88: =SUM(L68, L76, L84) -> 0 | M88: =SUM(M68, M76, M84) -> 1.4067838 | N88: =SUM(N68, N76, N84) -> 13.979914 | O88: =SUM(O68, O76, O84) -> 14.77123 | P88: =SUM(P68, P76, P84) -> 14.77123 | T88: =SUM(T68, T76, T84) -> 0 | U88: =SUM(U68, U76, U84) -> 0 | V88: =SUM(V68, V76, V84) -> 0 | W88: =SUM(W68, W76, W84) -> 0 | X88: =SUM(X68, X76, X84) -> 0 | Y88: =SUM(Y68, Y76, Y84) -> 0 | Z88: =SUM(Z68, Z76, Z84) -> 0 | AA88: =SUM(AA68, AA76, AA84) -> 0 | ... CA88: =SUM(CA68, CA76, CA84) -> 1.2309358 | CC88: =SUM(CC68, CC76, CC84) -> 0 | CD88: =SUM(CD68, CD76, CD84) -> 1.4067838 | CE88: =SUM(CE68, CE76, CE84) -> 13.979914 | CF88: =SUM(CF68, CF76, CF84) -> 14.77123 | CG88: =SUM(CG68, CG76, CG84) -> 14.77123 | CH88: =SUM(CH68, CH76, CH84) -> 0 | CI88: =CC88=L88 -> 1 | CJ88: =CD88=M88 -> 1 | CK88: =CE88=N88 -> 1 | CL88: =CF88=O88 -> 1 | CM88: =CG88=P88 -> 1
T90: 2026 | AF90: 2027 | AR90: 2028 | BD90: 2029 | BP90: 2030 | CI90: CHECK
D91: RECURRING COSTS TO ACHIEVE IMPACT | H91: Comment | I91: Baseline | J91: Goal | K91: Ann. Run Rate | L91: 2026 | M91: =L91+1 -> 2027 | N91: =M91+1 -> 2028 | O91: =N91+1 -> 2029 | P91: =O91+1 -> 2030 | Q91: Impacted BU | R91: Check | T91: 46023 | U91: =EOMONTH(T91, 1) -> 46081 | V91: =EOMONTH(U91, 1) -> 46112 | W91: =EOMONTH(V91, 1) -> 46142 | X91: =EOMONTH(W91, 1) -> 46173 | Y91: =EOMONTH(X91, 1) -> 46203 | Z91: =EOMONTH(Y91, 1) -> 46234 | AA91: =EOMONTH(Z91, 1) -> 46265 | AB91: =EOMONTH(AA91, 1) -> 46295 | ... CA91: =EOMONTH(BZ91, 1) -> 47848 | CC91: 2026 | CD91: =CC91+1 -> 2027 | CE91: =CD91+1 -> 2028 | CF91: =CE91+1 -> 2029 | CG91: =CF91+1 -> 2030 | CI91: 2026 | CJ91: =CI91+1 -> 2027 | CK91: =CJ91+1 -> 2028 | CL91: =CK91+1 -> 2029 | CM91: =CL91+1 -> 2030
E92: $USD M | I92: =$H$18 -> Post-upstream levers (S2 waterfall) | J92: Future State | K92: Increment
E93: Revenue
I94: 0 | J94: 0 | K94: =J94-I94 -> 0 | R94: =IF(K94=P94, "", "Error") | CC94: =SUMIFS($T94:$CA94, $T$1:$CA$1, CC$63) -> 0 | CD94: =SUMIFS($T94:$CA94, $T$1:$CA$1, CD$63) -> 0 | CE94: =SUMIFS($T94:$CA94, $T$1:$CA$1, CE$63) -> 0 | CF94: =SUMIFS($T94:$CA94, $T$1:$CA$1, CF$63) -> 0 | CG94: =SUMIFS($T94:$CA94, $T$1:$CA$1, CG$63) -> 0 | CI94: =CC94=L94 -> 1 | CJ94: =CD94=M94 -> 1 | CK94: =CE94=N94 -> 1 | CL94: =CF94=O94 -> 1 | CM94: =CG94=P94 -> 1
I95: 0 | J95: 0 | K95: =J95-I95 -> 0 | R95: =IF(K95=P95, "", "Error") | CC95: =SUMIFS($T95:$CA95, $T$1:$CA$1, CC$63) -> 0 | CD95: =SUMIFS($T95:$CA95, $T$1:$CA$1, CD$63) -> 0 | CE95: =SUMIFS($T95:$CA95, $T$1:$CA$1, CE$63) -> 0 | CF95: =SUMIFS($T95:$CA95, $T$1:$CA$1, CF$63) -> 0 | CG95: =SUMIFS($T95:$CA95, $T$1:$CA$1, CG$63) -> 0 | CI95: =CC95=L95 -> 1 | CJ95: =CD95=M95 -> 1 | CK95: =CE95=N95 -> 1 | CL95: =CF95=O95 -> 1 | CM95: =CG95=P95 -> 1
E96: Revenue Subtotal | I96: =SUM(I94:I95) -> 0 | J96: =SUM(J94:J95) -> 0 | K96: =SUM(K94:K95) -> 0 | L96: =SUM(L94:L95) -> 0 | M96: =SUM(M94:M95) -> 0 | N96: =SUM(N94:N95) -> 0 | O96: =SUM(O94:O95) -> 0 | P96: =SUM(P94:P95) -> 0 | T96: =SUM(T94:T95) -> 0 | U96: =SUM(U94:U95) -> 0 | V96: =SUM(V94:V95) -> 0 | W96: =SUM(W94:W95) -> 0 | X96: =SUM(X94:X95) -> 0 | Y96: =SUM(Y94:Y95) -> 0 | Z96: =SUM(Z94:Z95) -> 0 | AA96: =SUM(AA94:AA95) -> 0 | ... CA96: =SUM(CA94:CA95) -> 0 | CC96: =SUM(CC94:CC95) -> 0 | CD96: =SUM(CD94:CD95) -> 0 | CE96: =SUM(CE94:CE95) -> 0 | CF96: =SUM(CF94:CF95) -> 0 | CG96: =SUM(CG94:CG95) -> 0 | CI96: =CC96=L96 -> 1 | CJ96: =CD96=M96 -> 1 | CK96: =CE96=N96 -> 1 | CL96: =CF96=O96 -> 1 | CM96: =CG96=P96 -> 1
E98: Cost of Sales
I99: 0 | J99: 0 | K99: =J99-I99 -> 0 | L99: 0 | M99: 0 | N99: 0 | O99: 0 | P99: 0 | R99: =IF(K99=P99, "", "Error") | CC99: =SUMIFS($T99:$CA99, $T$1:$CA$1, CC$63) -> 0 | CD99: =SUMIFS($T99:$CA99, $T$1:$CA$1, CD$63) -> 0 | CE99: =SUMIFS($T99:$CA99, $T$1:$CA$1, CE$63) -> 0 | CF99: =SUMIFS($T99:$CA99, $T$1:$CA$1, CF$63) -> 0 | CG99: =SUMIFS($T99:$CA99, $T$1:$CA$1, CG$63) -> 0 | CI99: =CC99=L99 -> 1 | CJ99: =CD99=M99 -> 1 | CK99: =CE99=N99 -> 1 | CL99: =CF99=O99 -> 1 | CM99: =CG99=P99 -> 1
I100: 0 | J100: 0 | K100: =J100-I100 -> 0 | L100: 0 | M100: 0 | N100: 0 | O100: 0 | P100: 0 | R100: =IF(K100=P100, "", "Error") | CC100: =SUMIFS($T100:$CA100, $T$1:$CA$1, CC$63) -> 0 | CD100: =SUMIFS($T100:$CA100, $T$1:$CA$1, CD$63) -> 0 | CE100: =SUMIFS($T100:$CA100, $T$1:$CA$1, CE$63) -> 0 | CF100: =SUMIFS($T100:$CA100, $T$1:$CA$1, CF$63) -> 0 | CG100: =SUMIFS($T100:$CA100, $T$1:$CA$1, CG$63) -> 0 | CI100: =CC100=L100 -> 1 | CJ100: =CD100=M100 -> 1 | CK100: =CE100=N100 -> 1 | CL100: =CF100=O100 -> 1 | CM100: =CG100=P100 -> 1
I101: 0 | J101: 0 | K101: =J101-I101 -> 0 | L101: 0 | M101: 0 | N101: 0 | O101: 0 | P101: 0 | R101: =IF(K101=P101, "", "Error") | CC101: =SUMIFS($T101:$CA101, $T$1:$CA$1, CC$63) -> 0 | CD101: =SUMIFS($T101:$CA101, $T$1:$CA$1, CD$63) -> 0 | CE101: =SUMIFS($T101:$CA101, $T$1:$CA$1, CE$63) -> 0 | CF101: =SUMIFS($T101:$CA101, $T$1:$CA$1, CF$63) -> 0 | CG101: =SUMIFS($T101:$CA101, $T$1:$CA$1, CG$63) -> 0 | CI101: =CC101=L101 -> 1 | CJ101: =CD101=M101 -> 1 | CK101: =CE101=N101 -> 1 | CL101: =CF101=O101 -> 1 | CM101: =CG101=P101 -> 1
I102: 0 | J102: 0 | K102: =J102-I102 -> 0 | L102: 0 | M102: 0 | N102: 0 | O102: 0 | P102: 0 | R102: =IF(K102=P102, "", "Error") | CC102: =SUMIFS($T102:$CA102, $T$1:$CA$1, CC$63) -> 0 | CD102: =SUMIFS($T102:$CA102, $T$1:$CA$1, CD$63) -> 0 | CE102: =SUMIFS($T102:$CA102, $T$1:$CA$1, CE$63) -> 0 | CF102: =SUMIFS($T102:$CA102, $T$1:$CA$1, CF$63) -> 0 | CG102: =SUMIFS($T102:$CA102, $T$1:$CA$1, CG$63) -> 0 | CI102: =CC102=L102 -> 1 | CJ102: =CD102=M102 -> 1 | CK102: =CE102=N102 -> 1 | CL102: =CF102=O102 -> 1 | CM102: =CG102=P102 -> 1
K103: =J103-I103 -> 0 | L103: 0 | M103: 0 | N103: 0 | O103: 0 | P103: 0
E104: Cost of Sales Subtotal | I104: =SUM(I99:I103) -> 0 | J104: =SUM(J99:J103) -> 0 | K104: =SUM(K99:K103) -> 0 | L104: =SUM(L99:L103) -> 0 | M104: =SUM(M99:M103) -> 0 | N104: =SUM(N99:N103) -> 0 | O104: =SUM(O99:O103) -> 0 | P104: =SUM(P99:P103) -> 0 | T104: =SUM(T99:T103) -> 0 | U104: =SUM(U99:U103) -> 0 | V104: =SUM(V99:V103) -> 0 | W104: =SUM(W99:W103) -> 0 | X104: =SUM(X99:X103) -> 0 | Y104: =SUM(Y99:Y103) -> 0 | Z104: =SUM(Z99:Z103) -> 0 | AA104: =SUM(AA99:AA103) -> 0 | ... CA104: =SUM(CA99:CA103) -> 0 | CC104: =SUM(CC99:CC103) -> 0 | CD104: =SUM(CD99:CD103) -> 0 | CE104: =SUM(CE99:CE103) -> 0 | CF104: =SUM(CF99:CF103) -> 0 | CG104: =SUM(CG99:CG103) -> 0 | CI104: =CC104=L104 -> 1 | CJ104: =CD104=M104 -> 1 | CK104: =CE104=N104 -> 1 | CL104: =CF104=O104 -> 1 | CM104: =CG104=P104 -> 1
E106: OPEX
E107: OPEX - Inference & token consumption | H107: S2 C3 planning assumption — replace with consumption forecast; scales with ramp | I107: 0 | J107: =I107+'SVC-2 Model'!$K$111 -> 1.2 | K107: ='SVC-2 Model'!$K$111 -> 1.2 | L107: ='SVC-2 Model'!L111 -> 0 | M107: ='SVC-2 Model'!M111 -> 0.11428571 | N107: ='SVC-2 Model'!N111 -> 1.1357143 | O107: ='SVC-2 Model'!O111 -> 1.2 | P107: ='SVC-2 Model'!P111 -> 1.2 | Q107: Global Servicing | R107: =IF(K107=P107, "", "Error") | T107: ='SVC-2 Model'!T111 -> 0 | U107: ='SVC-2 Model'!U111 -> 0 | V107: ='SVC-2 Model'!V111 -> 0 | W107: ='SVC-2 Model'!W111 -> 0 | X107: ='SVC-2 Model'!X111 -> 0 | Y107: ='SVC-2 Model'!Y111 -> 0 | Z107: ='SVC-2 Model'!Z111 -> 0 | AA107: ='SVC-2 Model'!AA111 -> 0 | ... CA107: ='SVC-2 Model'!CA111 -> 0.1 | CC107: =SUMIFS($T107:$CA107, $T$1:$CA$1, CC$63) -> 0 | CD107: =SUMIFS($T107:$CA107, $T$1:$CA$1, CD$63) -> 0.11428571 | CE107: =SUMIFS($T107:$CA107, $T$1:$CA$1, CE$63) -> 1.1357143 | CF107: =SUMIFS($T107:$CA107, $T$1:$CA$1, CF$63) -> 1.2 | CG107: =SUMIFS($T107:$CA107, $T$1:$CA$1, CG$63) -> 1.2 | CI107: =CC107=L107 -> 1 | CJ107: =CD107=M107 -> 1 | CK107: =CE107=N107 -> 1 | CL107: =CF107=O107 -> 1 | CM107: =CG107=P107 -> 1
E108: OPEX - AI platform subscription | H108: S2 C3 planning number | I108: 0 | J108: =I108+'SVC-2 Model'!$K$112 -> 0.3 | K108: ='SVC-2 Model'!$K$112 -> 0.3 | L108: ='SVC-2 Model'!L112 -> 0 | M108: ='SVC-2 Model'!M112 -> 0.1 | N108: ='SVC-2 Model'!N112 -> 0.3 | O108: ='SVC-2 Model'!O112 -> 0.3 | P108: ='SVC-2 Model'!P112 -> 0.3 | Q108: Global Servicing | R108: =IF(K108=P108, "", "Error") | T108: ='SVC-2 Model'!T112 -> 0 | U108: ='SVC-2 Model'!U112 -> 0 | V108: ='SVC-2 Model'!V112 -> 0 | W108: ='SVC-2 Model'!W112 -> 0 | X108: ='SVC-2 Model'!X112 -> 0 | Y108: ='SVC-2 Model'!Y112 -> 0 | Z108: ='SVC-2 Model'!Z112 -> 0 | AA108: ='SVC-2 Model'!AA112 -> 0 | ... CA108: ='SVC-2 Model'!CA112 -> 0.025 | CC108: =SUMIFS($T108:$CA108, $T$1:$CA$1, CC$63) -> 0 | CD108: =SUMIFS($T108:$CA108, $T$1:$CA$1, CD$63) -> 0.1 | CE108: =SUMIFS($T108:$CA108, $T$1:$CA$1, CE$63) -> 0.3 | CF108: =SUMIFS($T108:$CA108, $T$1:$CA$1, CF$63) -> 0.3 | CG108: =SUMIFS($T108:$CA108, $T$1:$CA$1, CG$63) -> 0.3 | CI108: =CC108=L108 -> 1 | CJ108: =CD108=M108 -> 1 | CK108: =CE108=N108 -> 1 | CL108: =CF108=O108 -> 1 | CM108: =CG108=P108 -> 1
E109: OPEX - Run team (keep-the-lights-on) | H109: S2 C3: 3.0 FTE x $180k | I109: 0 | J109: =I109+'SVC-2 Model'!$K$113 -> 0.54 | K109: ='SVC-2 Model'!$K$113 -> 0.54 | L109: ='SVC-2 Model'!L113 -> 0 | M109: ='SVC-2 Model'!M113 -> 0.18 | N109: ='SVC-2 Model'!N113 -> 0.54 | O109: ='SVC-2 Model'!O113 -> 0.54 | P109: ='SVC-2 Model'!P113 -> 0.54 | Q109: Global Servicing | R109: =IF(K109=P109, "", "Error") | T109: ='SVC-2 Model'!T113 -> 0 | U109: ='SVC-2 Model'!U113 -> 0 | V109: ='SVC-2 Model'!V113 -> 0 | W109: ='SVC-2 Model'!W113 -> 0 | X109: ='SVC-2 Model'!X113 -> 0 | Y109: ='SVC-2 Model'!Y113 -> 0 | Z109: ='SVC-2 Model'!Z113 -> 0 | AA109: ='SVC-2 Model'!AA113 -> 0 | ... CA109: ='SVC-2 Model'!CA113 -> 0.045 | CC109: =SUMIFS($T109:$CA109, $T$1:$CA$1, CC$63) -> 0 | CD109: =SUMIFS($T109:$CA109, $T$1:$CA$1, CD$63) -> 0.18 | CE109: =SUMIFS($T109:$CA109, $T$1:$CA$1, CE$63) -> 0.54 | CF109: =SUMIFS($T109:$CA109, $T$1:$CA$1, CF$63) -> 0.54 | CG109: =SUMIFS($T109:$CA109, $T$1:$CA$1, CG$63) -> 0.54 | CI109: =CC109=L109 -> 1 | CJ109: =CD109=M109 -> 1 | CK109: =CE109=N109 -> 1 | CL109: =CF109=O109 -> 1 | CM109: =CG109=P109 -> 1
E110: OPEX - Vendor support & maintenance | H110: S2 C3 planning number | I110: 0 | J110: =I110+'SVC-2 Model'!$K$114 -> 0.2 | K110: ='SVC-2 Model'!$K$114 -> 0.2 | L110: ='SVC-2 Model'!L114 -> 0 | M110: ='SVC-2 Model'!M114 -> 0.066666667 | N110: ='SVC-2 Model'!N114 -> 0.2 | O110: ='SVC-2 Model'!O114 -> 0.2 | P110: ='SVC-2 Model'!P114 -> 0.2 | Q110: Global Servicing | R110: =IF(K110=P110, "", "Error") | T110: ='SVC-2 Model'!T114 -> 0 | U110: ='SVC-2 Model'!U114 -> 0 | V110: ='SVC-2 Model'!V114 -> 0 | W110: ='SVC-2 Model'!W114 -> 0 | X110: ='SVC-2 Model'!X114 -> 0 | Y110: ='SVC-2 Model'!Y114 -> 0 | Z110: ='SVC-2 Model'!Z114 -> 0 | AA110: ='SVC-2 Model'!AA114 -> 0 | ... CA110: ='SVC-2 Model'!CA114 -> 0.016666667 | CC110: =SUMIFS($T110:$CA110, $T$1:$CA$1, CC$63) -> 0 | CD110: =SUMIFS($T110:$CA110, $T$1:$CA$1, CD$63) -> 0.066666667 | CE110: =SUMIFS($T110:$CA110, $T$1:$CA$1, CE$63) -> 0.2 | CF110: =SUMIFS($T110:$CA110, $T$1:$CA$1, CF$63) -> 0.2 | CG110: =SUMIFS($T110:$CA110, $T$1:$CA$1, CG$63) -> 0.2 | CI110: =CC110=L110 -> 1 | CJ110: =CD110=M110 -> 1 | CK110: =CE110=N110 -> 1 | CL110: =CF110=O110 -> 1 | CM110: =CG110=P110 -> 1
E111: OPEX - Incremental infrastructure | H111: S2 C3 planning number | I111: 0 | J111: =I111+'SVC-2 Model'!$K$115 -> 0.1 | K111: ='SVC-2 Model'!$K$115 -> 0.1 | L111: ='SVC-2 Model'!L115 -> 0 | M111: ='SVC-2 Model'!M115 -> 0.033333333 | N111: ='SVC-2 Model'!N115 -> 0.1 | O111: ='SVC-2 Model'!O115 -> 0.1 | P111: ='SVC-2 Model'!P115 -> 0.1 | Q111: Global Servicing | R111: =IF(K111=P111, "", "Error") | T111: ='SVC-2 Model'!T115 -> 0 | U111: ='SVC-2 Model'!U115 -> 0 | V111: ='SVC-2 Model'!V115 -> 0 | W111: ='SVC-2 Model'!W115 -> 0 | X111: ='SVC-2 Model'!X115 -> 0 | Y111: ='SVC-2 Model'!Y115 -> 0 | Z111: ='SVC-2 Model'!Z115 -> 0 | AA111: ='SVC-2 Model'!AA115 -> 0 | ... CA111: ='SVC-2 Model'!CA115 -> 0.0083333333 | CC111: =SUMIFS($T111:$CA111, $T$1:$CA$1, CC$63) -> 0 | CD111: =SUMIFS($T111:$CA111, $T$1:$CA$1, CD$63) -> 0.033333333 | CE111: =SUMIFS($T111:$CA111, $T$1:$CA$1, CE$63) -> 0.1 | CF111: =SUMIFS($T111:$CA111, $T$1:$CA$1, CF$63) -> 0.1 | CG111: =SUMIFS($T111:$CA111, $T$1:$CA$1, CG$63) -> 0.1 | CI111: =CC111=L111 -> 1 | CJ111: =CD111=M111 -> 1 | CK111: =CE111=N111 -> 1 | CL111: =CF111=O111 -> 1 | CM111: =CG111=P111 -> 1
E112: OpEx subtotal | I112: =SUM(I107:I111) -> 0 | J112: =SUM(J107:J111) -> 2.34 | K112: =SUM(K107:K111) -> 2.34 | L112: =SUM(L107:L111) -> 0 | M112: =SUM(M107:M111) -> 0.49428571 | N112: =SUM(N107:N111) -> 2.2757143 | O112: =SUM(O107:O111) -> 2.34 | P112: =SUM(P107:P111) -> 2.34 | T112: =SUM(T107:T111) -> 0 | U112: =SUM(U107:U111) -> 0 | V112: =SUM(V107:V111) -> 0 | W112: =SUM(W107:W111) -> 0 | X112: =SUM(X107:X111) -> 0 | Y112: =SUM(Y107:Y111) -> 0 | Z112: =SUM(Z107:Z111) -> 0 | AA112: =SUM(AA107:AA111) -> 0 | ... CA112: =SUM(CA107:CA111) -> 0.195 | CC112: =SUM(CC107:CC111) -> 0 | CD112: =SUM(CD107:CD111) -> 0.49428571 | CE112: =SUM(CE107:CE111) -> 2.2757143 | CF112: =SUM(CF107:CF111) -> 2.34 | CG112: =SUM(CG107:CG111) -> 2.34 | CI112: =CC112=L112 -> 1 | CJ112: =CD112=M112 -> 1 | CK112: =CE112=N112 -> 1 | CL112: =CF112=O112 -> 1 | CM112: =CG112=P112 -> 1
E115: Recurring Costs Total | I115: =SUM(-I96, I104, I112) -> 0 | J115: =SUM(-J96, J104, J112) -> 2.34 | K115: =SUM(-K96, K104, K112) -> 2.34 | L115: =SUM(-L96, L104, L112) -> 0 | M115: =SUM(-M96, M104, M112) -> 0.49428571 | N115: =SUM(-N96, N104, N112) -> 2.2757143 | O115: =SUM(-O96, O104, O112) -> 2.34 | P115: =SUM(-P96, P104, P112) -> 2.34 | T115: =SUM(-T96, T104, T112) -> 0 | U115: =SUM(-U96, U104, U112) -> 0 | V115: =SUM(-V96, V104, V112) -> 0 | W115: =SUM(-W96, W104, W112) -> 0 | X115: =SUM(-X96, X104, X112) -> 0 | Y115: =SUM(-Y96, Y104, Y112) -> 0 | Z115: =SUM(-Z96, Z104, Z112) -> 0 | AA115: =SUM(-AA96, AA104, AA112) -> 0 | ... CA115: =SUM(-CA96, CA104, CA112) -> 0.195 | CC115: =SUM(-CC96, CC104, CC112) -> 0 | CD115: =SUM(-CD96, CD104, CD112) -> 0.49428571 | CE115: =SUM(-CE96, CE104, CE112) -> 2.2757143 | CF115: =SUM(-CF96, CF104, CF112) -> 2.34 | CG115: =SUM(-CG96, CG104, CG112) -> 2.34 | CI115: =CC115=L115 -> 1 | CJ115: =CD115=M115 -> 1 | CK115: =CE115=N115 -> 1 | CL115: =CF115=O115 -> 1 | CM115: =CG115=P115 -> 1
E117: Net Recurring Benefit | I117: =SUM(I88, -I115) -> 143.18592 | J117: =SUM(J88, -J115) -> 126.07469 | K117: =SUM(K88, -K115) -> 12.43123 | L117: =SUM(L88, -L115) -> 0 | M117: =SUM(M88, -M115) -> 0.91249807 | N117: =SUM(N88, -N115) -> 11.7042 | O117: =SUM(O88, -O115) -> 12.43123 | P117: =SUM(P88, -P115) -> 12.43123 | R117: =IF(K117=P117, "", "Error") | T117: =SUM(T88, -T115) -> 0 | U117: =SUM(U88, -U115) -> 0 | V117: =SUM(V88, -V115) -> 0 | W117: =SUM(W88, -W115) -> 0 | X117: =SUM(X88, -X115) -> 0 | Y117: =SUM(Y88, -Y115) -> 0 | Z117: =SUM(Z88, -Z115) -> 0 | AA117: =SUM(AA88, -AA115) -> 0 | ... CA117: =SUM(CA88, -CA115) -> 1.0359358 | CC117: =SUM(CC88, -CC115) -> 0 | CD117: =SUM(CD88, -CD115) -> 0.91249807 | CE117: =SUM(CE88, -CE115) -> 11.7042 | CF117: =SUM(CF88, -CF115) -> 12.43123 | CG117: =SUM(CG88, -CG115) -> 12.43123 | CI117: =CC117=L117 -> 1 | CJ117: =CD117=M117 -> 1 | CK117: =CE117=N117 -> 1 | CL117: =CF117=O117 -> 1 | CM117: =CG117=P117 -> 1
C120: SECTION III - ONE-TIME IMPLEMENTATION | CC120: ANNUAL SUMMARY | CI120: CHECK CELLS
T122: 2026 | AF122: 2027 | AR122: 2028 | BD122: 2029 | BP122: 2030
D123: ONE-TIME BENEFITS | K123: Comment | L123: 2026 | M123: =L123+1 -> 2027 | N123: =M123+1 -> 2028 | O123: =N123+1 -> 2029 | P123: =O123+1 -> 2030 | Q123: Impacted BU | T123: 46023 | U123: =EOMONTH(T123, 1) -> 46081 | V123: =EOMONTH(U123, 1) -> 46112 | W123: =EOMONTH(V123, 1) -> 46142 | X123: =EOMONTH(W123, 1) -> 46173 | Y123: =EOMONTH(X123, 1) -> 46203 | Z123: =EOMONTH(Y123, 1) -> 46234 | AA123: =EOMONTH(Z123, 1) -> 46265 | AB123: =EOMONTH(AA123, 1) -> 46295 | ... CA123: =EOMONTH(BZ123, 1) -> 47848 | CC123: 2026 | CD123: =CC123+1 -> 2027 | CE123: =CD123+1 -> 2028 | CF123: =CE123+1 -> 2029 | CG123: =CF123+1 -> 2030 | CI123: 2026 | CJ123: =CI123+1 -> 2027 | CK123: =CJ123+1 -> 2028 | CL123: =CK123+1 -> 2029 | CM123: =CL123+1 -> 2030
E125: Working Capital
CC126: =SUMIFS($T126:$CA126, $T$1:$CA$1, CC$63) -> 0 | CD126: =SUMIFS($T126:$CA126, $T$1:$CA$1, CD$63) -> 0 | CE126: =SUMIFS($T126:$CA126, $T$1:$CA$1, CE$63) -> 0 | CF126: =SUMIFS($T126:$CA126, $T$1:$CA$1, CF$63) -> 0 | CG126: =SUMIFS($T126:$CA126, $T$1:$CA$1, CG$63) -> 0 | CI126: =CC126=L126 -> 1 | CJ126: =CD126=M126 -> 1 | CK126: =CE126=N126 -> 1 | CL126: =CF126=O126 -> 1 | CM126: =CG126=P126 -> 1
CC127: =SUMIFS($T127:$CA127, $T$1:$CA$1, CC$63) -> 0 | CD127: =SUMIFS($T127:$CA127, $T$1:$CA$1, CD$63) -> 0 | CE127: =SUMIFS($T127:$CA127, $T$1:$CA$1, CE$63) -> 0 | CF127: =SUMIFS($T127:$CA127, $T$1:$CA$1, CF$63) -> 0 | CG127: =SUMIFS($T127:$CA127, $T$1:$CA$1, CG$63) -> 0 | CI127: =CC127=L127 -> 1 | CJ127: =CD127=M127 -> 1 | CK127: =CE127=N127 -> 1 | CL127: =CF127=O127 -> 1 | CM127: =CG127=P127 -> 1
E128: Working Capital Subtotal | L128: =SUM(L126:L127) -> 0 | M128: =SUM(M126:M127) -> 0 | N128: =SUM(N126:N127) -> 0 | O128: =SUM(O126:O127) -> 0 | P128: =SUM(P126:P127) -> 0 | T128: =SUM(T126:T127) -> 0 | U128: =SUM(U126:U127) -> 0 | V128: =SUM(V126:V127) -> 0 | W128: =SUM(W126:W127) -> 0 | X128: =SUM(X126:X127) -> 0 | Y128: =SUM(Y126:Y127) -> 0 | Z128: =SUM(Z126:Z127) -> 0 | AA128: =SUM(AA126:AA127) -> 0 | ... CA128: =SUM(CA126:CA127) -> 0 | CC128: =SUM(CC126:CC127) -> 0 | CD128: =SUM(CD126:CD127) -> 0 | CE128: =SUM(CE126:CE127) -> 0 | CF128: =SUM(CF126:CF127) -> 0 | CG128: =SUM(CG126:CG127) -> 0 | CI128: =CC128=L128 -> 1 | CJ128: =CD128=M128 -> 1 | CK128: =CE128=N128 -> 1 | CL128: =CF128=O128 -> 1 | CM128: =CG128=P128 -> 1
E130: One-Time Benefits Total | L130: =L128 -> 0 | M130: =M128 -> 0 | N130: =N128 -> 0 | O130: =O128 -> 0 | P130: =P128 -> 0 | T130: =T128 -> 0 | U130: =U128 -> 0 | V130: =V128 -> 0 | W130: =W128 -> 0 | X130: =X128 -> 0 | Y130: =Y128 -> 0 | Z130: =Z128 -> 0 | AA130: =AA128 -> 0 | ... CA130: =CA128 -> 0 | CC130: =CC128 -> 0 | CD130: =CD128 -> 0 | CE130: =CE128 -> 0 | CF130: =CF128 -> 0 | CG130: =CG128 -> 0 | CI130: =CI128 -> 1 | CJ130: =CJ128 -> 1 | CK130: =CK128 -> 1 | CL130: =CL128 -> 1 | CM130: =CM128 -> 1
T132: 2026 | AF132: 2027 | AR132: 2028 | BD132: 2029 | BP132: 2030
D133: CAPEX AND ONE-TIME COSTS | K133: Comment | L133: 2026 | M133: =L133+1 -> 2027 | N133: =M133+1 -> 2028 | O133: =N133+1 -> 2029 | P133: =O133+1 -> 2030 | T133: 46023 | U133: =EOMONTH(T133, 1) -> 46081 | V133: =EOMONTH(U133, 1) -> 46112 | W133: =EOMONTH(V133, 1) -> 46142 | X133: =EOMONTH(W133, 1) -> 46173 | Y133: =EOMONTH(X133, 1) -> 46203 | Z133: =EOMONTH(Y133, 1) -> 46234 | AA133: =EOMONTH(Z133, 1) -> 46265 | AB133: =EOMONTH(AA133, 1) -> 46295 | ... CA133: =EOMONTH(BZ133, 1) -> 47848 | CC133: 2026 | CD133: =CC133+1 -> 2027 | CE133: =CD133+1 -> 2028 | CF133: =CE133+1 -> 2029 | CG133: =CF133+1 -> 2030 | CI133: 2026 | CJ133: =CI133+1 -> 2027 | CK133: =CJ133+1 -> 2028 | CL133: =CK133+1 -> 2029 | CM133: =CL133+1 -> 2030
E135: Capital Expenditures
E136: CAPEX — capitalized build labor | L136: ='SVC-2 Model'!L95 -> 0 | M136: ='SVC-2 Model'!M95 -> 0 | N136: ='SVC-2 Model'!N95 -> 0 | O136: ='SVC-2 Model'!O95 -> 0 | P136: ='SVC-2 Model'!P95 -> 0 | Q136: Global Servicing | T136: ='SVC-2 Model'!T95 -> 0 | U136: ='SVC-2 Model'!U95 -> 0 | V136: ='SVC-2 Model'!V95 -> 0 | W136: ='SVC-2 Model'!W95 -> 0 | X136: ='SVC-2 Model'!X95 -> 0 | Y136: ='SVC-2 Model'!Y95 -> 0 | Z136: ='SVC-2 Model'!Z95 -> 0 | AA136: ='SVC-2 Model'!AA95 -> 0 | ... CA136: ='SVC-2 Model'!CA95 -> 0 | CC136: =SUMIFS($T136:$CA136, $T$1:$CA$1, CC$63) -> 0 | CD136: =SUMIFS($T136:$CA136, $T$1:$CA$1, CD$63) -> 0 | CE136: =SUMIFS($T136:$CA136, $T$1:$CA$1, CE$63) -> 0 | CF136: =SUMIFS($T136:$CA136, $T$1:$CA$1, CF$63) -> 0 | CG136: =SUMIFS($T136:$CA136, $T$1:$CA$1, CG$63) -> 0 | CI136: =CC136=L136 -> 1 | CJ136: =CD136=M136 -> 1 | CK136: =CE136=N136 -> 1 | CL136: =CF136=O136 -> 1 | CM136: =CG136=P136 -> 1
E137: CAPEX — capitalized non-labor | L137: ='SVC-2 Model'!L96 -> 0 | M137: ='SVC-2 Model'!M96 -> 0 | N137: ='SVC-2 Model'!N96 -> 0 | O137: ='SVC-2 Model'!O96 -> 0 | P137: ='SVC-2 Model'!P96 -> 0 | Q137: Global Servicing | T137: ='SVC-2 Model'!T96 -> 0 | U137: ='SVC-2 Model'!U96 -> 0 | V137: ='SVC-2 Model'!V96 -> 0 | W137: ='SVC-2 Model'!W96 -> 0 | X137: ='SVC-2 Model'!X96 -> 0 | Y137: ='SVC-2 Model'!Y96 -> 0 | Z137: ='SVC-2 Model'!Z96 -> 0 | AA137: ='SVC-2 Model'!AA96 -> 0 | ... CA137: ='SVC-2 Model'!CA96 -> 0 | CC137: =SUMIFS($T137:$CA137, $T$1:$CA$1, CC$63) -> 0 | CD137: =SUMIFS($T137:$CA137, $T$1:$CA$1, CD$63) -> 0 | CE137: =SUMIFS($T137:$CA137, $T$1:$CA$1, CE$63) -> 0 | CF137: =SUMIFS($T137:$CA137, $T$1:$CA$1, CF$63) -> 0 | CG137: =SUMIFS($T137:$CA137, $T$1:$CA$1, CG$63) -> 0 | CI137: =CC137=L137 -> 1 | CJ137: =CD137=M137 -> 1 | CK137: =CE137=N137 -> 1 | CL137: =CF137=O137 -> 1 | CM137: =CG137=P137 -> 1
E138: Capital Expenditures Subtotal | L138: =SUM(L136:L137) -> 0 | M138: =SUM(M136:M137) -> 0 | N138: =SUM(N136:N137) -> 0 | O138: =SUM(O136:O137) -> 0 | P138: =SUM(P136:P137) -> 0 | T138: =SUM(T136:T137) -> 0 | U138: =SUM(U136:U137) -> 0 | V138: =SUM(V136:V137) -> 0 | W138: =SUM(W136:W137) -> 0 | X138: =SUM(X136:X137) -> 0 | Y138: =SUM(Y136:Y137) -> 0 | Z138: =SUM(Z136:Z137) -> 0 | AA138: =SUM(AA136:AA137) -> 0 | ... CA138: =SUM(CA136:CA137) -> 0 | CC138: =SUM(CC136:CC137) -> 0 | CD138: =SUM(CD136:CD137) -> 0 | CE138: =SUM(CE136:CE137) -> 0 | CF138: =SUM(CF136:CF137) -> 0 | CG138: =SUM(CG136:CG137) -> 0 | CI138: =CC138=L138 -> 1 | CJ138: =CD138=M138 -> 1 | CK138: =CE138=N138 -> 1 | CL138: =CF138=O138 -> 1 | CM138: =CG138=P138 -> 1
E140: OTC
E141: OTC — build labor (expensed) | L141: ='SVC-2 Model'!L97 -> 0 | M141: ='SVC-2 Model'!M97 -> 1.3933333 | N141: ='SVC-2 Model'!N97 -> 0.275 | O141: ='SVC-2 Model'!O97 -> 0 | P141: ='SVC-2 Model'!P97 -> 0 | Q141: Global Servicing | T141: ='SVC-2 Model'!T97 -> 0 | U141: ='SVC-2 Model'!U97 -> 0 | V141: ='SVC-2 Model'!V97 -> 0 | W141: ='SVC-2 Model'!W97 -> 0 | X141: ='SVC-2 Model'!X97 -> 0 | Y141: ='SVC-2 Model'!Y97 -> 0 | Z141: ='SVC-2 Model'!Z97 -> 0 | AA141: ='SVC-2 Model'!AA97 -> 0 | ... CA141: ='SVC-2 Model'!CA97 -> 0 | CC141: =SUMIFS($T141:$CA141, $T$1:$CA$1, CC$63) -> 0 | CD141: =SUMIFS($T141:$CA141, $T$1:$CA$1, CD$63) -> 1.3933333 | CE141: =SUMIFS($T141:$CA141, $T$1:$CA$1, CE$63) -> 0.275 | CF141: =SUMIFS($T141:$CA141, $T$1:$CA$1, CF$63) -> 0 | CG141: =SUMIFS($T141:$CA141, $T$1:$CA$1, CG$63) -> 0 | CI141: =CC141=L141 -> 1 | CJ141: =CD141=M141 -> 1 | CK141: =CE141=N141 -> 1 | CL141: =CF141=O141 -> 1 | CM141: =CG141=P141 -> 1
E142: OTC — non-labor (expensed) | L142: ='SVC-2 Model'!L98 -> 0 | M142: ='SVC-2 Model'!M98 -> 0.75709333 | N142: ='SVC-2 Model'!N98 -> 0.079273333 | O142: ='SVC-2 Model'!O98 -> 0 | P142: ='SVC-2 Model'!P98 -> 0 | Q142: Global Servicing | T142: ='SVC-2 Model'!T98 -> 0 | U142: ='SVC-2 Model'!U98 -> 0 | V142: ='SVC-2 Model'!V98 -> 0 | W142: ='SVC-2 Model'!W98 -> 0 | X142: ='SVC-2 Model'!X98 -> 0 | Y142: ='SVC-2 Model'!Y98 -> 0 | Z142: ='SVC-2 Model'!Z98 -> 0 | AA142: ='SVC-2 Model'!AA98 -> 0 | ... CA142: ='SVC-2 Model'!CA98 -> 0 | CC142: =SUMIFS($T142:$CA142, $T$1:$CA$1, CC$63) -> 0 | CD142: =SUMIFS($T142:$CA142, $T$1:$CA$1, CD$63) -> 0.75709333 | CE142: =SUMIFS($T142:$CA142, $T$1:$CA$1, CE$63) -> 0.079273333 | CF142: =SUMIFS($T142:$CA142, $T$1:$CA$1, CF$63) -> 0 | CG142: =SUMIFS($T142:$CA142, $T$1:$CA$1, CG$63) -> 0 | CI142: =CC142=L142 -> 1 | CJ142: =CD142=M142 -> 1 | CK142: =CE142=N142 -> 1 | CL142: =CF142=O142 -> 1 | CM142: =CG142=P142 -> 1
CC143: =SUMIFS($T143:$CA143, $T$1:$CA$1, CC$63) -> 0 | CD143: =SUMIFS($T143:$CA143, $T$1:$CA$1, CD$63) -> 0 | CE143: =SUMIFS($T143:$CA143, $T$1:$CA$1, CE$63) -> 0 | CF143: =SUMIFS($T143:$CA143, $T$1:$CA$1, CF$63) -> 0 | CG143: =SUMIFS($T143:$CA143, $T$1:$CA$1, CG$63) -> 0 | CI143: =CC143=L143 -> 1 | CJ143: =CD143=M143 -> 1 | CK143: =CE143=N143 -> 1 | CL143: =CF143=O143 -> 1 | CM143: =CG143=P143 -> 1
E144: OTC Subtotal | L144: =SUM(L141:L143) -> 0 | M144: =SUM(M141:M143) -> 2.1504267 | N144: =SUM(N141:N143) -> 0.35427333 | O144: =SUM(O141:O143) -> 0 | P144: =SUM(P141:P143) -> 0 | T144: =SUM(T141:T143) -> 0 | U144: =SUM(U141:U143) -> 0 | V144: =SUM(V141:V143) -> 0 | W144: =SUM(W141:W143) -> 0 | X144: =SUM(X141:X143) -> 0 | Y144: =SUM(Y141:Y143) -> 0 | Z144: =SUM(Z141:Z143) -> 0 | AA144: =SUM(AA141:AA143) -> 0 | ... CA144: =SUM(CA141:CA143) -> 0 | CC144: =SUM(CC141:CC143) -> 0 | CD144: =SUM(CD141:CD143) -> 2.1504267 | CE144: =SUM(CE141:CE143) -> 0.35427333 | CF144: =SUM(CF141:CF143) -> 0 | CG144: =SUM(CG141:CG143) -> 0 | CI144: =CC144=L144 -> 1 | CJ144: =CD144=M144 -> 1 | CK144: =CE144=N144 -> 1 | CL144: =CF144=O144 -> 1 | CM144: =CG144=P144 -> 1
E147: One-Time Costs Total | L147: =SUM(L138, L144) -> 0 | M147: =SUM(M138, M144) -> 2.1504267 | N147: =SUM(N138, N144) -> 0.35427333 | O147: =SUM(O138, O144) -> 0 | P147: =SUM(P138, P144) -> 0 | T147: =SUM(T138, T144) -> 0 | U147: =SUM(U138, U144) -> 0 | V147: =SUM(V138, V144) -> 0 | W147: =SUM(W138, W144) -> 0 | X147: =SUM(X138, X144) -> 0 | Y147: =SUM(Y138, Y144) -> 0 | Z147: =SUM(Z138, Z144) -> 0 | AA147: =SUM(AA138, AA144) -> 0 | ... CA147: =SUM(CA138, CA144) -> 0 | CC147: =SUM(CC138, CC144) -> 0 | CD147: =SUM(CD138, CD144) -> 2.1504267 | CE147: =SUM(CE138, CE144) -> 0.35427333 | CF147: =SUM(CF138, CF144) -> 0 | CG147: =SUM(CG138, CG144) -> 0 | CI147: =CC147=L147 -> 1 | CJ147: =CD147=M147 -> 1 | CK147: =CE147=N147 -> 1 | CL147: =CF147=O147 -> 1 | CM147: =CG147=P147 -> 1
E149: Total One-Time Implementation Cost | L149: =SUM(L130, -L147) -> 0 | M149: =SUM(M130, -M147) -> -2.1504267 | N149: =SUM(N130, -N147) -> -0.35427333 | O149: =SUM(O130, -O147) -> 0 | P149: =SUM(P130, -P147) -> 0 | T149: =SUM(T130, -T147) -> 0 | U149: =SUM(U130, -U147) -> 0 | V149: =SUM(V130, -V147) -> 0 | W149: =SUM(W130, -W147) -> 0 | X149: =SUM(X130, -X147) -> 0 | Y149: =SUM(Y130, -Y147) -> 0 | Z149: =SUM(Z130, -Z147) -> 0 | AA149: =SUM(AA130, -AA147) -> 0 | ... CA149: =SUM(CA130, -CA147) -> 0 | CC149: =SUM(CC130, -CC147) -> 0 | CD149: =SUM(CD130, -CD147) -> -2.1504267 | CE149: =SUM(CE130, -CE147) -> -0.35427333 | CF149: =SUM(CF130, -CF147) -> 0 | CG149: =SUM(CG130, -CG147) -> 0 | CI149: =CC149=L149 -> 1 | CJ149: =CD149=M149 -> 1 | CK149: =CE149=N149 -> 1 | CL149: =CF149=O149 -> 1 | CM149: =CG149=P149 -> 1
C152: SECTION IV - FINANCIAL METRICS | CC152: ANNUAL SUMMARY | CI152: CHECK CELLS
E155: Cash Flow | L155: 2026 | M155: =L155+1 -> 2027 | N155: =M155+1 -> 2028 | O155: =N155+1 -> 2029 | P155: =O155+1 -> 2030 | Q155: Total
E156: Operating Income | L156: =L117 -> 0 | M156: =M117 -> 0.91249807 | N156: =N117 -> 11.7042 | O156: =O117 -> 12.43123 | P156: =P117 -> 12.43123 | Q156: =SUM(L156:P156) -> 37.479157
E157: (+) One-Time Benefits | L157: =L130 -> 0 | M157: =M130 -> 0 | N157: =N130 -> 0 | O157: =O130 -> 0 | P157: =P130 -> 0 | Q157: =SUM(L157:P157) -> 0
E158: (-) One-Time Cash Costs | L158: =-L147 -> 0 | M158: =-M147 -> -2.1504267 | N158: =-N147 -> -0.35427333 | O158: =-O147 -> 0 | P158: =-P147 -> 0 | Q158: =SUM(L158:P158) -> -2.5047
E159: Cash Flow | L159: =SUM(L156:L158) -> 0 | M159: =SUM(M156:M158) -> -1.2379286 | N159: =SUM(N156:N158) -> 11.349926 | O159: =SUM(O156:O158) -> 12.43123 | P159: =SUM(P156:P158) -> 12.43123 | Q159: =SUM(L159:P159) -> 34.974457
E160: Cumulative Cash Flow | L160: =L159 -> 0 | M160: =L160+M159 -> -1.2379286 | N160: =M160+N159 -> 10.111998 | O160: =N160+O159 -> 22.543227 | P160: =O160+P159 -> 34.974457 | Q160: =P160 -> 34.974457
E161: Payback timeline | L161: =IF(L160<0,1,0) -> 0 | M161: =IF(M160<0,1,IF(AND(L160<0,M159>0),-L160/M159,0)) -> 1 | N161: =IF(N160<0,1,IF(AND(M160<0,N159>0),-M160/N159,0)) -> 0.10906931 | O161: =IF(O160<0,1,IF(AND(N160<0,O159>0),-N160/O159,0)) -> 0 | P161: =IF(P160<0,1,IF(AND(O160<0,P159>0),-O160/P159,0)) -> 0
E163: Return on Investment | F163: NRB/OTC | G163: =IFERROR(K117/-SUM(L149:P149),"n/a") -> 4.9631612
E164: Internal Rate of Return | F164: 5-yr IRR | G164: =IFERROR(IRR($L$159:$P$159, 0.2),"n/a") -> 9.2444058
E165: Breakeven timeline | F165: # yrs | G165: =IF(SUM(L161:P161)=5,">5",SUM(L161:P161)) -> 1.1090693
E167: WACC | G167: 0.095
E168: NPV | F168: $ | G168: =SUM(L168:P168) -> 24.155774 | L168: =L159/(1+$G$167)^L$1 -> 0 | M168: =M159/(1+$G$167)^M$1 -> -1.032446 | N168: =N159/(1+$G$167)^N$1 -> 8.644715 | O168: =O159/(1+$G$167)^O$1 -> 8.6468439 | P168: =P159/(1+$G$167)^P$1 -> 7.8966611 | Q168: =SUM(L168:P168) -> 24.155774
C171: END

Sheet SVC-3 Model
B2: SVC-3 — Agentic Voice & AI Co-pilot | INITIATIVE MODEL
B3: Workstream: Servicing (ELT sponsor: Aaron | WSL: Tahira | IOs: Jackie Yu, Matt Anderson, Bob Hurst) • Model status: Seeded 1:1 from S2 vDraft5 (Base) — benefit ties to $35.25M (3a $26.95M + 3b $8.30M)
T5: 2026 | U5: 2026 | V5: 2026 | W5: 2026 | X5: 2026 | Y5: 2026 | Z5: 2026 | AA5: 2026 | AB5: 2026 | AC5: 2026 | AD5: 2026 | AE5: 2026 | AF5: 2027 | AG5: 2027 | AH5: 2027 | AI5: 2027 | AJ5: 2027 | AK5: 2027 | AL5: 2027 | AM5: 2027 | AN5: 2027 | AO5: 2027 | AP5: 2027 | AQ5: 2027 | AR5: 2028 | AS5: 2028 | AT5: 2028 | AU5: 2028 | AV5: 2028 | AW5: 2028 | AX5: 2028 | AY5: 2028 | AZ5: 2028 | BA5: 2028 | BB5: 2028 | BC5: 2028 | BD5: 2029 | BE5: 2029 | BF5: 2029 | BG5: 2029 | BH5: 2029 | BI5: 2029 | BJ5: 2029 | BK5: 2029 | BL5: 2029 | BM5: 2029 | BN5: 2029 | BO5: 2029 | BP5: 2030 | BQ5: 2030 | BR5: 2030 | BS5: 2030 | BT5: 2030 | BU5: 2030 | BV5: 2030 | BW5: 2030 | BX5: 2030 | BY5: 2030 | BZ5: 2030 | CA5: 2030
B6: Monthly grid (Jan-26 → Dec-30) → | K6: Run rate | L6: 2026 | M6: 2027 | N6: 2028 | O6: 2029 | P6: 2030 | T6: =DATE(2026,1,31) -> 46053 | U6: =EOMONTH(T6,1) -> 46081 | V6: =EOMONTH(U6,1) -> 46112 | W6: =EOMONTH(V6,1) -> 46142 | X6: =EOMONTH(W6,1) -> 46173 | Y6: =EOMONTH(X6,1) -> 46203 | Z6: =EOMONTH(Y6,1) -> 46234 | AA6: =EOMONTH(Z6,1) -> 46265 | AB6: =EOMONTH(AA6,1) -> 46295 | ... CA6: =EOMONTH(BZ6,1) -> 47848
B8: 0. INITIATIVE & STATUS
B10: Initiative name | D10: Agentic AI voice — end-to-end contact resolution plus AI co-pilot agent assist
B11: Initiative owner | D11: Servicing IO — TBC (pool: Jackie Yu, Matt Anderson, Bob Hurst) | I11: confirm with workstream lead
B12: Impacted BU | D12: Global Servicing
B13: Go-live / Estimated L4 date | D13: =DATE(2027,9,1) -> 46631 | I13: Benefit ramp is gated on this date.
B15: Source: Servicing S2 sizing model vDraft5 (28 Aug 2026), Base scenario. Distilled to tier level; per-tier eligible bases and effective rates reproduce the S2 L2-intent engine output exactly (verified).
B16: Source: Workplan: 'Project Zenith Automation workplan and data requests vS_1.xlsx', Servicing tabs
B17: Open items to refine with initiative owner:
B18: – S2 splits this initiative into 3a (contact resolution/abatement, voice only) and 3b (co-pilot handle-time reduction on residual + text); check #9 in S2 enforces that they sum to the combined voice benefit. Both sub-levers modeled below; WAVE carries them as two benefit lines.
B19: – 3b QC from S2: after-call-work share is zero on every intent (M10 split carries no ACW minutes) — co-pilot voice rates are built from talk+hold only; 6 intents have talk shares >1 (data fault); 5 intents ride flat fallback rates incl. the largest single voice benefit ($0.7M).
B20: – Sensitivity (S2): voice resolution rates ±30% swing total benefit $13.5M — largest driver in the model.
B22: 1. SIZING ASSUMPTIONS (blue = inputs — refine with initiative owner)
B24: Opening baselines (S2 waterfall: 3a opens on SVC-2 closing; 3b on 3a closing)
B25: Opening cost — 3a (all channels) | D25: 1.2841469e+08 | E25: $/yr | F25: Servicing S2 sizing model vDraft5 (28 Aug 2026), Base scenario. Opening cost follows the S2 stacking waterfall (each lever opens on the prior lever's closing baseline; order: 1 Avoidance → 2 Chat → 3a Voice → 3b Co-pilot → 4a SBR → 4b Utilisation). Tier-level bases below are snapshots of the S2 L2 engine — refresh them from the S2 model if upstream levers or tiering change.
B26: Opening cost — 3b (post-3a residual) | D26: 1.0146563e+08 | E26: $/yr | F26: Equals 3a closing; refresh if 3a changes
B27: Investment uplifts (S2 standard)
B28: Programme management, % of build | D28: 0.08 | E28: %
B29: Contingency, % of build incl. PM | D29: 0.1 | E29: %
B30: Run team headcount (3a + 3b consolidated) | D30: 5.5 | E30: # FTE | F30: S2 C3: 3.0 (3a) + 2.5 (3b)
B31: Run team loaded rate | D31: 180000 | E31: $/FTE/yr
B32: FTE impacted — 3a (A0 basis, feeds SVC-6) | D32: 1017.2846 | E32: # FTE | F32: S2 A3a V102
B33: FTE impacted — 3b (A0 basis, feeds SVC-6) | D33: 528.2645 | E33: # FTE | F33: S2 A3b V102
B34: (spare assumption row)
B35: (spare assumption row)
B37: S2 lever 3a — Agentic voice: voice-channel eligible cost by tier (voice-tier column)
B38: Tier | D38: Eligible cost base ($/yr) | F38: Effective rate | H38: Benefit ($/yr) | M38: Voice channel only (messaging/email pass through). Effective rates implied from the S2 engine — bundle target rate, 80% ceiling, funnel hardening.
B39: Easy (27 L2 intents) | D39: 22606259 | F39: 0.35948695 | H39: =D39*F39 -> 8126655.2 | M39: S2 target 40% of escalated voice demand; 80% ceiling + hardening -> effective 35.9%
B40: Medium (37 L2 intents) | D40: 51560922 | F40: 0.28011012 | H40: =D40*F40 -> 14442736 | M40: S2 target 30%; effective 28.0%
B41: Hard (13 L2 intents) | D41: 30019867 | F41: 0.14589229 | H41: =D41*F41 -> 4379667.2 | M41: S2 target 15%; effective 14.6%
B42: Subtotal — S2 lever 3a — Agentic voice: voice-channel eligible cost by tier | D42: =SUM(D39:D41) -> 1.0418705e+08 | H42: =SUM(H39:H41) -> 26949059
B44: S2 lever 3b — AI co-pilot: voice residual (post-3a) cost by tier
B45: Tier | D45: Eligible cost base ($/yr) | F45: Effective rate | H45: Benefit ($/yr) | M45: Handle-time reduction on contacts that still reach an agent (voice).
B46: Easy | D46: 14479604 | F46: 0.10035728 | H46: =D46*F46 -> 1453133.7 | M46: Component-built: talk 10% + hold 35% x M10 minute shares, x hardening
B47: Medium | D47: 37118186 | F47: 0.077770816 | H47: =D47*F47 -> 2886711.6 | M47: talk 8% / hold 30% components
B48: Hard | D48: 25640200 | F48: 0.061504725 | H48: =D48*F48 -> 1576993.5 | M48: talk 5% / hold 20% components; 5 intents on flat fallback rates
B49: Subtotal — S2 lever 3b — AI co-pilot: voice residual | D49: =SUM(D46:D48) -> 77237990 | H49: =SUM(H46:H48) -> 5916838.7
B51: S2 lever 3b — AI co-pilot: text (messaging + email) cost by tier
B52: Tier | D52: Eligible cost base ($/yr) | F52: Effective rate | H52: Benefit ($/yr) | M52: Text handled-cost reduction (blended rate per tier).
B53: Easy | D53: 3311158.9 | F53: 0.12864182 | H53: =D53*F53 -> 425953.51 | M53: S2 flat text rate 15% x hardening
B54: Medium | D54: 12792361 | F54: 0.10524583 | H54: =D54*F54 -> 1346342.6 | M54: S2 flat 12%
B55: Hard | D55: 8124122.3 | F55: 0.075398419 | H55: =D55*F55 -> 612545.98 | M55: S2 flat 8%
B56: Subtotal — S2 lever 3b — AI co-pilot: text | D56: =SUM(D53:D55) -> 24227642 | H56: =SUM(H53:H55) -> 2384842.1
B58: 2. BENEFIT CALCULATION (steady-state annual run-rate)
B60: Benefit — S2 lever 3a (agentic voice resolution) | D60: =$H$42 -> 26949059 | E60: $/yr | F60: Ties to S2: $26,949,059
B61: Benefit — S2 lever 3b (AI co-pilot, voice + text) | D61: =$H$49+$H$56 -> 8301680.8 | E61: $/yr | F61: Ties to S2: $8,301,681
B62: Total annual benefit (steady state) | D62: =$D$60+$D$61 -> 35250739 | E62: $/yr | F62: Ties to S2 combined: $35,250,739
B63: FTE impacted total (feeds SVC-6) | D63: =$D$32+$D$33 -> 1545.5491 | E63: # FTE
B64: Closing cost (hand-off baseline to SVC-4) | D64: =$D$26-$D$61 -> 93163951 | E64: $/yr | F64: S2: $93,163,951
B66: 3. RAMP & PHASING
B68: Months to full run rate after go-live (linear ramp) | D68: 8 | F68: Benefit starts at go-live and ramps linearly to steady state over this many months.
B69: Monthly ramp % (run-rate captured in month) | T69: =MIN(1,MAX(0,((YEAR(T$6)-YEAR($D$13))*12+MONTH(T$6)-MONTH($D$13)+0.5)/MAX($D$68,0.5))) -> 0 | U69: =MIN(1,MAX(0,((YEAR(U$6)-YEAR($D$13))*12+MONTH(U$6)-MONTH($D$13)+0.5)/MAX($D$68,0.5))) -> 0 | V69: =MIN(1,MAX(0,((YEAR(V$6)-YEAR($D$13))*12+MONTH(V$6)-MONTH($D$13)+0.5)/MAX($D$68,0.5))) -> 0 | W69: =MIN(1,MAX(0,((YEAR(W$6)-YEAR($D$13))*12+MONTH(W$6)-MONTH($D$13)+0.5)/MAX($D$68,0.5))) -> 0 | X69: =MIN(1,MAX(0,((YEAR(X$6)-YEAR($D$13))*12+MONTH(X$6)-MONTH($D$13)+0.5)/MAX($D$68,0.5))) -> 0 | Y69: =MIN(1,MAX(0,((YEAR(Y$6)-YEAR($D$13))*12+MONTH(Y$6)-MONTH($D$13)+0.5)/MAX($D$68,0.5))) -> 0 | Z69: =MIN(1,MAX(0,((YEAR(Z$6)-YEAR($D$13))*12+MONTH(Z$6)-MONTH($D$13)+0.5)/MAX($D$68,0.5))) -> 0 | AA69: =MIN(1,MAX(0,((YEAR(AA$6)-YEAR($D$13))*12+MONTH(AA$6)-MONTH($D$13)+0.5)/MAX($D$68,0.5))) -> 0 | ... CA69: =MIN(1,MAX(0,((YEAR(CA$6)-YEAR($D$13))*12+MONTH(CA$6)-MONTH($D$13)+0.5)/MAX($D$68,0.5))) -> 1
B70: Resulting average ramp % by year (info) | L70: =SUMIFS($T69:$CA69,$T$5:$CA$5,2026)/12 -> 0 | M70: =SUMIFS($T69:$CA69,$T$5:$CA$5,2027)/12 -> 0.083333333 | N70: =SUMIFS($T69:$CA69,$T$5:$CA$5,2028)/12 -> 0.91666667 | O70: =SUMIFS($T69:$CA69,$T$5:$CA$5,2029)/12 -> 1 | P70: =SUMIFS($T69:$CA69,$T$5:$CA$5,2030)/12 -> 1
B72: 4. RECURRING BENEFIT LINES ($M — these rows feed the WAVE sheet)
B74: Line (WAVE category) | D74: Baseline $M | K74: Run rate
B75: OPEX - Agentic voice contact resolution (3a) [OPEX] | D75: =$D$25/1000000 -> 128.41469 | K75: =SUMIFS($T75:$CA75,$T$5:$CA$5,2030) -> 26.949059 | L75: =SUMIFS($T75:$CA75,$T$5:$CA$5,2026) -> 0 | M75: =SUMIFS($T75:$CA75,$T$5:$CA$5,2027) -> 2.2457549 | N75: =SUMIFS($T75:$CA75,$T$5:$CA$5,2028) -> 24.703304 | O75: =SUMIFS($T75:$CA75,$T$5:$CA$5,2029) -> 26.949059 | P75: =SUMIFS($T75:$CA75,$T$5:$CA$5,2030) -> 26.949059 | T75: =($D$60)/1000000/12*T$69 -> 0 | U75: =($D$60)/1000000/12*U$69 -> 0 | V75: =($D$60)/1000000/12*V$69 -> 0 | W75: =($D$60)/1000000/12*W$69 -> 0 | X75: =($D$60)/1000000/12*X$69 -> 0 | Y75: =($D$60)/1000000/12*Y$69 -> 0 | Z75: =($D$60)/1000000/12*Z$69 -> 0 | AA75: =($D$60)/1000000/12*AA$69 -> 0 | ... CA75: =($D$60)/1000000/12*CA$69 -> 2.2457549
B76: OPEX - AI co-pilot handle-time reduction (3b) [OPEX] | D76: =$D$26/1000000 -> 101.46563 | K76: =SUMIFS($T76:$CA76,$T$5:$CA$5,2030) -> 8.3016808 | L76: =SUMIFS($T76:$CA76,$T$5:$CA$5,2026) -> 0 | M76: =SUMIFS($T76:$CA76,$T$5:$CA$5,2027) -> 0.69180674 | N76: =SUMIFS($T76:$CA76,$T$5:$CA$5,2028) -> 7.6098741 | O76: =SUMIFS($T76:$CA76,$T$5:$CA$5,2029) -> 8.3016808 | P76: =SUMIFS($T76:$CA76,$T$5:$CA$5,2030) -> 8.3016808 | T76: =($D$61)/1000000/12*T$69 -> 0 | U76: =($D$61)/1000000/12*U$69 -> 0 | V76: =($D$61)/1000000/12*V$69 -> 0 | W76: =($D$61)/1000000/12*W$69 -> 0 | X76: =($D$61)/1000000/12*X$69 -> 0 | Y76: =($D$61)/1000000/12*Y$69 -> 0 | Z76: =($D$61)/1000000/12*Z$69 -> 0 | AA76: =($D$61)/1000000/12*AA$69 -> 0 | ... CA76: =($D$61)/1000000/12*CA$69 -> 0.69180674
B77: Total recurring benefit ($M) | K77: =SUM(K75:K76) -> 35.250739 | L77: =SUM(L75:L76) -> 0 | M77: =SUM(M75:M76) -> 2.9375616 | N77: =SUM(N75:N76) -> 32.313178 | O77: =SUM(O75:O76) -> 35.250739 | P77: =SUM(P75:P76) -> 35.250739
B79: 5. ONE-TIME INVESTMENT — people cost by milestone (standard approach)
B81: Build A — Agentic voice resolution (3a)
B82: Milestone | C82: Assumptions | D82: Team size | E82: Billing months | F82: Contingency Factor | G82: Labor Costs | H82: Start month | I82: Cap % (labor) | K82: Rate override ($/mo)
C83: Capture any assumptions on cost drivers, timelines, contingency factor etc. | E83: Months the team works at full utilization | F83: Low=10% Medium=15% High=20% Very high=50% | G83: Total labor costs for milestone | I83: Default links to Rate Card policy — type a % to override
B84: Plan / Design | C84: S2: 4 FTE x 2 months. | D84: 4 | E84: 2 | F84: 0.1 | G84: =D84*E84*IF(K84="",'Rate Card'!$G$29,K84)*(1+F84) -> 146666.67 | H84: =DATE(2027,1,1) -> 46388 | I84: ='Rate Card'!$C$45 -> 0
B85: Build / Test | C85: S2: 8-FTE pod x 6 months. | D85: 8 | E85: 6 | F85: 0.1 | G85: =D85*E85*IF(K85="",'Rate Card'!$G$29,K85)*(1+F85) -> 880000 | H85: =DATE(2027,3,1) -> 46447 | I85: ='Rate Card'!$C$46 -> 0
B86: Pilot / Change Mgmt. | C86: S2 scale-up: 5 FTE x 8 months. | D86: 5 | E86: 8 | F86: 0.1 | G86: =D86*E86*IF(K86="",'Rate Card'!$G$29,K86)*(1+F86) -> 733333.33 | H86: =DATE(2027,9,1) -> 46631 | I86: ='Rate Card'!$C$47 -> 0
B87: Scale / Run | C87: Run-phase in Section 6. | D87: 0 | E87: 0 | F87: 0.1 | G87: =D87*E87*IF(K87="",'Rate Card'!$G$29,K87)*(1+F87) -> 0 | H87: =DATE(2028,5,1) -> 46874 | I87: ='Rate Card'!$C$48 -> 0
B89: Build B — AI co-pilot (3b)
B90: Milestone | C90: Assumptions | D90: Team size | E90: Billing months | F90: Contingency Factor | G90: Labor Costs | H90: Start month | I90: Cap % (labor) | K90: Rate override ($/mo)
B91: Plan / Design | C91: S2: 4 FTE x 2 months. | D91: 4 | E91: 2 | F91: 0.1 | G91: =D91*E91*IF(K91="",'Rate Card'!$G$29,K91)*(1+F91) -> 146666.67 | H91: =DATE(2027,1,1) -> 46388 | I91: ='Rate Card'!$C$45 -> 0
B92: Build / Test | C92: S2: 8-FTE pod x 5 months. | D92: 8 | E92: 5 | F92: 0.1 | G92: =D92*E92*IF(K92="",'Rate Card'!$G$29,K92)*(1+F92) -> 733333.33 | H92: =DATE(2027,3,1) -> 46447 | I92: ='Rate Card'!$C$46 -> 0
B93: Pilot / Change Mgmt. | C93: S2 scale-up: 5 FTE x 6 months. | D93: 5 | E93: 6 | F93: 0.1 | G93: =D93*E93*IF(K93="",'Rate Card'!$G$29,K93)*(1+F93) -> 550000 | H93: =DATE(2027,8,1) -> 46600 | I93: ='Rate Card'!$C$47 -> 0
B94: Scale / Run | C94: Run-phase in Section 6. | D94: 0 | E94: 0 | F94: 0.1 | G94: =D94*E94*IF(K94="",'Rate Card'!$G$29,K94)*(1+F94) -> 0 | H94: =DATE(2028,2,1) -> 46784 | I94: ='Rate Card'!$C$48 -> 0
B96: Milestone labor phasing ($/month, spread evenly over billing months)
B97: Plan / Design (Build A — Agentic voice resolution (3a)) | T97: =IF(AND(T$6>=EOMONTH($H$84,0),T$6<=EOMONTH(EDATE($H$84,$E$84-1),0)),$G$84/MAX($E$84,1),0) -> 0 | U97: =IF(AND(U$6>=EOMONTH($H$84,0),U$6<=EOMONTH(EDATE($H$84,$E$84-1),0)),$G$84/MAX($E$84,1),0) -> 0 | V97: =IF(AND(V$6>=EOMONTH($H$84,0),V$6<=EOMONTH(EDATE($H$84,$E$84-1),0)),$G$84/MAX($E$84,1),0) -> 0 | W97: =IF(AND(W$6>=EOMONTH($H$84,0),W$6<=EOMONTH(EDATE($H$84,$E$84-1),0)),$G$84/MAX($E$84,1),0) -> 0 | X97: =IF(AND(X$6>=EOMONTH($H$84,0),X$6<=EOMONTH(EDATE($H$84,$E$84-1),0)),$G$84/MAX($E$84,1),0) -> 0 | Y97: =IF(AND(Y$6>=EOMONTH($H$84,0),Y$6<=EOMONTH(EDATE($H$84,$E$84-1),0)),$G$84/MAX($E$84,1),0) -> 0 | Z97: =IF(AND(Z$6>=EOMONTH($H$84,0),Z$6<=EOMONTH(EDATE($H$84,$E$84-1),0)),$G$84/MAX($E$84,1),0) -> 0 | AA97: =IF(AND(AA$6>=EOMONTH($H$84,0),AA$6<=EOMONTH(EDATE($H$84,$E$84-1),0)),$G$84/MAX($E$84,1),0) -> 0 | ... CA97: =IF(AND(CA$6>=EOMONTH($H$84,0),CA$6<=EOMONTH(EDATE($H$84,$E$84-1),0)),$G$84/MAX($E$84,1),0) -> 0
B98: Build / Test (Build A — Agentic voice resolution (3a)) | T98: =IF(AND(T$6>=EOMONTH($H$85,0),T$6<=EOMONTH(EDATE($H$85,$E$85-1),0)),$G$85/MAX($E$85,1),0) -> 0 | U98: =IF(AND(U$6>=EOMONTH($H$85,0),U$6<=EOMONTH(EDATE($H$85,$E$85-1),0)),$G$85/MAX($E$85,1),0) -> 0 | V98: =IF(AND(V$6>=EOMONTH($H$85,0),V$6<=EOMONTH(EDATE($H$85,$E$85-1),0)),$G$85/MAX($E$85,1),0) -> 0 | W98: =IF(AND(W$6>=EOMONTH($H$85,0),W$6<=EOMONTH(EDATE($H$85,$E$85-1),0)),$G$85/MAX($E$85,1),0) -> 0 | X98: =IF(AND(X$6>=EOMONTH($H$85,0),X$6<=EOMONTH(EDATE($H$85,$E$85-1),0)),$G$85/MAX($E$85,1),0) -> 0 | Y98: =IF(AND(Y$6>=EOMONTH($H$85,0),Y$6<=EOMONTH(EDATE($H$85,$E$85-1),0)),$G$85/MAX($E$85,1),0) -> 0 | Z98: =IF(AND(Z$6>=EOMONTH($H$85,0),Z$6<=EOMONTH(EDATE($H$85,$E$85-1),0)),$G$85/MAX($E$85,1),0) -> 0 | AA98: =IF(AND(AA$6>=EOMONTH($H$85,0),AA$6<=EOMONTH(EDATE($H$85,$E$85-1),0)),$G$85/MAX($E$85,1),0) -> 0 | ... CA98: =IF(AND(CA$6>=EOMONTH($H$85,0),CA$6<=EOMONTH(EDATE($H$85,$E$85-1),0)),$G$85/MAX($E$85,1),0) -> 0
B99: Pilot / Change Mgmt. (Build A — Agentic voice resolution (3a)) | T99: =IF(AND(T$6>=EOMONTH($H$86,0),T$6<=EOMONTH(EDATE($H$86,$E$86-1),0)),$G$86/MAX($E$86,1),0) -> 0 | U99: =IF(AND(U$6>=EOMONTH($H$86,0),U$6<=EOMONTH(EDATE($H$86,$E$86-1),0)),$G$86/MAX($E$86,1),0) -> 0 | V99: =IF(AND(V$6>=EOMONTH($H$86,0),V$6<=EOMONTH(EDATE($H$86,$E$86-1),0)),$G$86/MAX($E$86,1),0) -> 0 | W99: =IF(AND(W$6>=EOMONTH($H$86,0),W$6<=EOMONTH(EDATE($H$86,$E$86-1),0)),$G$86/MAX($E$86,1),0) -> 0 | X99: =IF(AND(X$6>=EOMONTH($H$86,0),X$6<=EOMONTH(EDATE($H$86,$E$86-1),0)),$G$86/MAX($E$86,1),0) -> 0 | Y99: =IF(AND(Y$6>=EOMONTH($H$86,0),Y$6<=EOMONTH(EDATE($H$86,$E$86-1),0)),$G$86/MAX($E$86,1),0) -> 0 | Z99: =IF(AND(Z$6>=EOMONTH($H$86,0),Z$6<=EOMONTH(EDATE($H$86,$E$86-1),0)),$G$86/MAX($E$86,1),0) -> 0 | AA99: =IF(AND(AA$6>=EOMONTH($H$86,0),AA$6<=EOMONTH(EDATE($H$86,$E$86-1),0)),$G$86/MAX($E$86,1),0) -> 0 | ... CA99: =IF(AND(CA$6>=EOMONTH($H$86,0),CA$6<=EOMONTH(EDATE($H$86,$E$86-1),0)),$G$86/MAX($E$86,1),0) -> 0
