Workbook

Sheet Instructions
B1: Instructions
B3: Purpose and functionality of the workbook
B4: This workbook is designed to classify each TAM 2.0 non-target platform into 3 tranches based on imperative to exit and exit complexity
B6: Context
B29: Worksheet specific notes
B31: Summary sheet
B32: • One row per capability / sub-capability with the relevant SPOCs, the number of platforms listed, and live counts of platforms in Tranche 1, 2, and 3
B33: • Counts update automatically as the capability tabs are filled in; use the Open → links to jump straight to your section, and the tracker at the top of each tab to navigate within it
B34: Capability sheets (one tab per capability, one section per sub-capability)
B35: • List all current-state platforms in your domain
B36: • Set the State for each platform: Target state and Exceptions are not classified into tranches
B37: • For each non-target platform in your domain, classify the imperative to exit / benefits and exit complexity as High / Medium / Low
... B41: Note: Aim to be directionally correct not precise

Sheet Summary
A1: Platform Assessment — Summary
A2: Tranche roll-up by capability and sub-capability — counts update automatically from each tab.
A4: # | B4: Capability | C4: Sub-capability | D4: SPOCs | E4: Platforms listed | F4: Tranche 1 | G4: Tranche 2 | H4: Tranche 3 | I4: Link
A5: 1 | B5: Boarding | C5: Boarding Experience | D5: • Alan Johnson • Lindsay Guthmiller • Fredrick Mjema • David Pritchett | E5: =COUNTA('Boarding'!$B$14:$B$39) | F5: =COUNTIF('Boarding'!$G$14:$G$39,"Tranche 1") | G5: =COUNTIF('Boarding'!$G$14:$G$39,"Tranche 2") | H5: =COUNTIF('Boarding'!$G$14:$G$39,"Tranche 3") | I5: =HYPERLINK("#'Boarding'!A12","Open →")
A6: 2 | C6: Ingress | D6: • Alan Johnson • Fredrick Mjema • Vivek Pujeri • Patrick Bateman • Rebecca Fishel • Bradley Bossenbroek | E6: =COUNTA('Boarding'!$B$46:$B$55) | F6: =COUNTIF('Boarding'!$G$46:$G$55,"Tranche 1") | G6: =COUNTIF('Boarding'!$G$46:$G$55,"Tranche 2") | H6: =COUNTIF('Boarding'!$G$46:$G$55,"Tranche 3") | I6: =HYPERLINK("#'Boarding'!A44","Open →")
A7: 3 | C7: Boarding Orchestration | E7: =COUNTA('Boarding'!$B$62:$B$73) | F7: =COUNTIF('Boarding'!$G$62:$G$73,"Tranche 1") | G7: =COUNTIF('Boarding'!$G$62:$G$73,"Tranche 2") | H7: =COUNTIF('Boarding'!$G$62:$G$73,"Tranche 3") | I7: =HYPERLINK("#'Boarding'!A60","Open →")
A8: 4 | C8: Integration & Messaging | E8: =COUNTA('Boarding'!$B$80:$B$89) | F8: =COUNTIF('Boarding'!$G$80:$G$89,"Tranche 1") | G8: =COUNTIF('Boarding'!$G$80:$G$89,"Tranche 2") | H8: =COUNTIF('Boarding'!$G$80:$G$89,"Tranche 3") | I8: =HYPERLINK("#'Boarding'!A78","Open →")
A9: 5 | C9: Credit & Underwriting | E9: =COUNTA('Boarding'!$B$96:$B$105) | F9: =COUNTIF('Boarding'!$G$96:$G$105,"Tranche 1") | G9: =COUNTIF('Boarding'!$G$96:$G$105,"Tranche 2") | H9: =COUNTIF('Boarding'!$G$96:$G$105,"Tranche 3") | I9: =HYPERLINK("#'Boarding'!A94","Open →")
A10: 6 | C10: CPQ / Quote-pricing | D10: • Jake Gwynn • Vivek Pujeri | E10: =COUNTA('Boarding'!$B$112:$B$121) | F10: =COUNTIF('Boarding'!$G$112:$G$121,"Tranche 1") | G10: =COUNTIF('Boarding'!$G$112:$G$121,"Tranche 2") | H10: =COUNTIF('Boarding'!$G$112:$G$121,"Tranche 3") | I10: =HYPERLINK("#'Boarding'!A110","Open →")
A11: 7 | B11: Single-in | C11: Global API | D11: • Alexander Dewison | E11: =COUNTA('Single-in'!$B$13:$B$22) | F11: =COUNTIF('Single-in'!$G$13:$G$22,"Tranche 1") | G11: =COUNTIF('Single-in'!$G$13:$G$22,"Tranche 2") | H11: =COUNTIF('Single-in'!$G$13:$G$22,"Tranche 3") | I11: =HYPERLINK("#'Single-in'!A11","Open →")
A12: 8 | C12: Payment Apps & SDKs | D12: • Stuart Taylor • Scott Moser | E12: =COUNTA('Single-in'!$B$29:$B$51) | F12: =COUNTIF('Single-in'!$G$29:$G$51,"Tranche 1") | G12: =COUNTIF('Single-in'!$G$29:$G$51,"Tranche 2") | H12: =COUNTIF('Single-in'!$G$29:$G$51,"Tranche 3") | I12: =HYPERLINK("#'Single-in'!A27","Open →")
A13: 9 | C13: Developer Experience | D13: • Alexander Dewison | E13: =COUNTA('Single-in'!$B$58:$B$67) | F13: =COUNTIF('Single-in'!$G$58:$G$67,"Tranche 1") | G13: =COUNTIF('Single-in'!$G$58:$G$67,"Tranche 2") | H13: =COUNTIF('Single-in'!$G$58:$G$67,"Tranche 3") | I13: =HYPERLINK("#'Single-in'!A56","Open →")
A14: 10 | C14: Hosted Solutions | D14: • Alexander Dewison | E14: =COUNTA('Single-in'!$B$74:$B$83) | F14: =COUNTIF('Single-in'!$G$74:$G$83,"Tranche 1") | G14: =COUNTIF('Single-in'!$G$74:$G$83,"Tranche 2") | H14: =COUNTIF('Single-in'!$G$74:$G$83,"Tranche 3") | I14: =HYPERLINK("#'Single-in'!A72","Open →")
A15: 11 | C15: Unified Proposition | D15: • Alexander Dewison | E15: =COUNTA('Single-in'!$B$90:$B$99) | F15: =COUNTIF('Single-in'!$G$90:$G$99,"Tranche 1") | G15: =COUNTIF('Single-in'!$G$90:$G$99,"Tranche 2") | H15: =COUNTIF('Single-in'!$G$90:$G$99,"Tranche 3") | I15: =HYPERLINK("#'Single-in'!A88","Open →")
A16: 12 | B16: Sales & Servicing | C16: CRM | D16: • Khali White • Lindsay Guthmiller • Tuarai Girard • Vivek Pujeri • Charlie Wright • Jason Randall • David Pritchett | E16: =COUNTA('Sales & Servicing'!$B$12:$B$27) | F16: =COUNTIF('Sales & Servicing'!$G$12:$G$27,"Tranche 1") | G16: =COUNTIF('Sales & Servicing'!$G$12:$G$27,"Tranche 2") | H16: =COUNTIF('Sales & Servicing'!$G$12:$G$27,"Tranche 3") | I16: =HYPERLINK("#'Sales & Servicing'!A10","Open →")
A17: 13 | C17: Servicing Tools | E17: =COUNTA('Sales & Servicing'!$B$34:$B$49) | F17: =COUNTIF('Sales & Servicing'!$G$34:$G$49,"Tranche 1") | G17: =COUNTIF('Sales & Servicing'!$G$34:$G$49,"Tranche 2") | H17: =COUNTIF('Sales & Servicing'!$G$34:$G$49,"Tranche 3") | I17: =HYPERLINK("#'Sales & Servicing'!A32","Open →")
A18: 14 | C18: Sales Automation | E18: =COUNTA('Sales & Servicing'!$B$56:$B$65) | F18: =COUNTIF('Sales & Servicing'!$G$56:$G$65,"Tranche 1") | G18: =COUNTIF('Sales & Servicing'!$G$56:$G$65,"Tranche 2") | H18: =COUNTIF('Sales & Servicing'!$G$56:$G$65,"Tranche 3") | I18: =HYPERLINK("#'Sales & Servicing'!A54","Open →")
A19: 15 | C19: Risks | E19: =COUNTA('Sales & Servicing'!$B$72:$B$81) | F19: =COUNTIF('Sales & Servicing'!$G$72:$G$81,"Tranche 1") | G19: =COUNTIF('Sales & Servicing'!$G$72:$G$81,"Tranche 2") | H19: =COUNTIF('Sales & Servicing'!$G$72:$G$81,"Tranche 3") | I19: =HYPERLINK("#'Sales & Servicing'!A70","Open →")
A20: 16 | B20: Payment Processing | C20: Gateway | D20: • TBC | E20: =COUNTA('Payment Processing'!$B$14:$B$52) | F20: =COUNTIF('Payment Processing'!$G$14:$G$52,"Tranche 1") | G20: =COUNTIF('Payment Processing'!$G$14:$G$52,"Tranche 2") | H20: =COUNTIF('Payment Processing'!$G$14:$G$52,"Tranche 3") | I20: =HYPERLINK("#'Payment Processing'!A12","Open →")
A21: 17 | C21: Switch | E21: =COUNTA('Payment Processing'!$B$59:$B$68) | F21: =COUNTIF('Payment Processing'!$G$59:$G$68,"Tranche 1") | G21: =COUNTIF('Payment Processing'!$G$59:$G$68,"Tranche 2") | H21: =COUNTIF('Payment Processing'!$G$59:$G$68,"Tranche 3") | I21: =HYPERLINK("#'Payment Processing'!A57","Open →")
A22: 18 | C22: Clearing Back-end | D22: • Mike Clark • Philip Ringer • Jon Beere • Alan Bainbridge • Richard Jones • Peter Downey | E22: =COUNTA('Payment Processing'!$B$75:$B$89) | F22: =COUNTIF('Payment Processing'!$G$75:$G$89,"Tranche 1") | G22: =COUNTIF('Payment Processing'!$G$75:$G$89,"Tranche 2") | H22: =COUNTIF('Payment Processing'!$G$75:$G$89,"Tranche 3") | I22: =HYPERLINK("#'Payment Processing'!A73","Open →")
A23: 19 | C23: Authorization Host | D23: • Mike Clark • Philip Ringer • Jon Beere • Anushree Kolhe • James Annunziata | E23: =COUNTA('Payment Processing'!$B$96:$B$112) | F23: =COUNTIF('Payment Processing'!$G$96:$G$112,"Tranche 1") | G23: =COUNTIF('Payment Processing'!$G$96:$G$112,"Tranche 2") | H23: =COUNTIF('Payment Processing'!$G$96:$G$112,"Tranche 3") | I23: =HYPERLINK("#'Payment Processing'!A94","Open →")
A24: 20 | C24: Transaction monitoring | D24: • TBC | E24: =COUNTA('Payment Processing'!$B$119:$B$128) | F24: =COUNTIF('Payment Processing'!$G$119:$G$128,"Tranche 1") | G24: =COUNTIF('Payment Processing'!$G$119:$G$128,"Tranche 2") | H24: =COUNTIF('Payment Processing'!$G$119:$G$128,"Tranche 3") | I24: =HYPERLINK("#'Payment Processing'!A117","Open →")
A25: 21 | C25: APMs/LPMs | D25: • TBC | E25: =COUNTA('Payment Processing'!$B$135:$B$144) | F25: =COUNTIF('Payment Processing'!$G$135:$G$144,"Tranche 1") | G25: =COUNTIF('Payment Processing'!$G$135:$G$144,"Tranche 2") | H25: =COUNTIF('Payment Processing'!$G$135:$G$144,"Tranche 3") | I25: =HYPERLINK("#'Payment Processing'!A133","Open →")
A26: 22 | B26: VAS | C26: Routing | D26: • Jason Harding • Srini Turlapati • Andre Dubreuil • Sunny Thakkar | E26: =COUNTA('VAS'!$B$17:$B$26) | F26: =COUNTIF('VAS'!$G$17:$G$26,"Tranche 1") | G26: =COUNTIF('VAS'!$G$17:$G$26,"Tranche 2") | H26: =COUNTIF('VAS'!$G$17:$G$26,"Tranche 3") | I26: =HYPERLINK("#'VAS'!A15","Open →")
A27: 23 | C27: Networking Payment Tokens | D27: • Jason Harding • Srini Turlapati | E27: =COUNTA('VAS'!$B$33:$B$42) | F27: =COUNTIF('VAS'!$G$33:$G$42,"Tranche 1") | G27: =COUNTIF('VAS'!$G$33:$G$42,"Tranche 2") | H27: =COUNTIF('VAS'!$G$33:$G$42,"Tranche 3") | I27: =HYPERLINK("#'VAS'!A31","Open →")
A28: 24 | C28: DCC eDCC | D28: • Marcus Lang • VikramSuhas Joshi • Jaroslav Farkas | E28: =COUNTA('VAS'!$B$49:$B$58) | F28: =COUNTIF('VAS'!$G$49:$G$58,"Tranche 1") | G28: =COUNTIF('VAS'!$G$49:$G$58,"Tranche 2") | H28: =COUNTIF('VAS'!$G$49:$G$58,"Tranche 3") | I28: =HYPERLINK("#'VAS'!A47","Open →")
A29: 25 | C29: Fraud | D29: • Justin Moore • Srini Turlapati | E29: =COUNTA('VAS'!$B$65:$B$76) | F29: =COUNTIF('VAS'!$G$65:$G$76,"Tranche 1") | G29: =COUNTIF('VAS'!$G$65:$G$76,"Tranche 2") | H29: =COUNTIF('VAS'!$G$65:$G$76,"Tranche 3") | I29: =HYPERLINK("#'VAS'!A63","Open →")
A30: 26 | C30: Credential Management | D30: • Jason Harding • Srini Turlapati • Andre Dubreuil | E30: =COUNTA('VAS'!$B$83:$B$92) | F30: =COUNTIF('VAS'!$G$83:$G$92,"Tranche 1") | G30: =COUNTIF('VAS'!$G$83:$G$92,"Tranche 2") | H30: =COUNTIF('VAS'!$G$83:$G$92,"Tranche 3") | I30: =HYPERLINK("#'VAS'!A81","Open →")
A31: 27 | C31: Gifts | D31: • Genessa Prictor • Srini Turlapati • John Nail | E31: =COUNTA('VAS'!$B$99:$B$110) | F31: =COUNTIF('VAS'!$G$99:$G$110,"Tranche 1") | G31: =COUNTIF('VAS'!$G$99:$G$110,"Tranche 2") | H31: =COUNTIF('VAS'!$G$99:$G$110,"Tranche 3") | I31: =HYPERLINK("#'VAS'!A97","Open →")
A32: 28 | C32: Managed Optimization | D32: • Jason Harding • Srini Turlapati • Andre Dubreuil | E32: =COUNTA('VAS'!$B$117:$B$126) | F32: =COUNTIF('VAS'!$G$117:$G$126,"Tranche 1") | G32: =COUNTIF('VAS'!$G$117:$G$126,"Tranche 2") | H32: =COUNTIF('VAS'!$G$117:$G$126,"Tranche 3") | I32: =HYPERLINK("#'VAS'!A115","Open →")
A33: 29 | C33: 3DS / exemptions | D33: • Sunny Thakkar • Srini Turlapati | E33: =COUNTA('VAS'!$B$133:$B$142) | F33: =COUNTIF('VAS'!$G$133:$G$142,"Tranche 1") | G33: =COUNTIF('VAS'!$G$133:$G$142,"Tranche 2") | H33: =COUNTIF('VAS'!$G$133:$G$142,"Tranche 3") | I33: =HYPERLINK("#'VAS'!A131","Open →")
A34: 30 | C34: FX | D34: • Srini Turlapati • VikramSuhas Joshi | E34: =COUNTA('VAS'!$B$149:$B$158) | F34: =COUNTIF('VAS'!$G$149:$G$158,"Tranche 1") | G34: =COUNTIF('VAS'!$G$149:$G$158,"Tranche 2") | H34: =COUNTIF('VAS'!$G$149:$G$158,"Tranche 3") | I34: =HYPERLINK("#'VAS'!A147","Open →")
A35: 31 | B35: Unified Data and AI | C35: Overall | D35: • Ryan Heaton • Himanshu Shah | E35: =COUNTA('Unified Data and AI'!$B$9:$B$21) | F35: =COUNTIF('Unified Data and AI'!$G$9:$G$21,"Tranche 1") | G35: =COUNTIF('Unified Data and AI'!$G$9:$G$21,"Tranche 2") | H35: =COUNTIF('Unified Data and AI'!$G$9:$G$21,"Tranche 3") | I35: =HYPERLINK("#'Unified Data and AI'!A7","Open →")
A36: 32 | B36: Global Infrastructure | C36: Data Centers | D36: • TBC | E36: =COUNTA('Global Infrastructure'!$B$14:$B$23) | F36: =COUNTIF('Global Infrastructure'!$G$14:$G$23,"Tranche 1") | G36: =COUNTIF('Global Infrastructure'!$G$14:$G$23,"Tranche 2") | H36: =COUNTIF('Global Infrastructure'!$G$14:$G$23,"Tranche 3") | I36: =HYPERLINK("#'Global Infrastructure'!A12","Open →")
A37: 33 | C37: Cloud | D37: • TBC | E37: =COUNTA('Global Infrastructure'!$B$30:$B$39) | F37: =COUNTIF('Global Infrastructure'!$G$30:$G$39,"Tranche 1") | G37: =COUNTIF('Global Infrastructure'!$G$30:$G$39,"Tranche 2") | H37: =COUNTIF('Global Infrastructure'!$G$30:$G$39,"Tranche 3") | I37: =HYPERLINK("#'Global Infrastructure'!A28","Open →")
A38: 34 | C38: Observability | D38: • TBC | E38: =COUNTA('Global Infrastructure'!$B$46:$B$55) | F38: =COUNTIF('Global Infrastructure'!$G$46:$G$55,"Tranche 1") | G38: =COUNTIF('Global Infrastructure'!$G$46:$G$55,"Tranche 2") | H38: =COUNTIF('Global Infrastructure'!$G$46:$G$55,"Tranche 3") | I38: =HYPERLINK("#'Global Infrastructure'!A44","Open →")
A39: 35 | C39: Security | D39: • TBC | E39: =COUNTA('Global Infrastructure'!$B$62:$B$71) | F39: =COUNTIF('Global Infrastructure'!$G$62:$G$71,"Tranche 1") | G39: =COUNTIF('Global Infrastructure'!$G$62:$G$71,"Tranche 2") | H39: =COUNTIF('Global Infrastructure'!$G$62:$G$71,"Tranche 3") | I39: =HYPERLINK("#'Global Infrastructure'!A60","Open →")
A40: 36 | C40: AI Tools | D40: • TBC | E40: =COUNTA('Global Infrastructure'!$B$78:$B$87) | F40: =COUNTIF('Global Infrastructure'!$G$78:$G$87,"Tranche 1") | G40: =COUNTIF('Global Infrastructure'!$G$78:$G$87,"Tranche 2") | H40: =COUNTIF('Global Infrastructure'!$G$78:$G$87,"Tranche 3") | I40: =HYPERLINK("#'Global Infrastructure'!A76","Open →")
A41: 37 | C41: Design Systems | D41: • TBC | E41: =COUNTA('Global Infrastructure'!$B$94:$B$103) | F41: =COUNTIF('Global Infrastructure'!$G$94:$G$103,"Tranche 1") | G41: =COUNTIF('Global Infrastructure'!$G$94:$G$103,"Tranche 2") | H41: =COUNTIF('Global Infrastructure'!$G$94:$G$103,"Tranche 3") | I41: =HYPERLINK("#'Global Infrastructure'!A92","Open →")
A42: 38 | B42: Single-out | C42: Portal | D42: • Jaemi Bremner • Amutha Velayutham | E42: =COUNTA('Single-out'!$B$14:$B$36) | F42: =COUNTIF('Single-out'!$G$14:$G$36,"Tranche 1") | G42: =COUNTIF('Single-out'!$G$14:$G$36,"Tranche 2") | H42: =COUNTIF('Single-out'!$G$14:$G$36,"Tranche 3") | I42: =HYPERLINK("#'Single-out'!A12","Open →")
A43: 39 | C43: Reporting | D43: • Helen Ryan • Srini Turlapati • Shaily Daftari • Amutha Velayutham | E43: =COUNTA('Single-out'!$B$43:$B$53) | F43: =COUNTIF('Single-out'!$G$43:$G$53,"Tranche 1") | G43: =COUNTIF('Single-out'!$G$43:$G$53,"Tranche 2") | H43: =COUNTIF('Single-out'!$G$43:$G$53,"Tranche 3") | I43: =HYPERLINK("#'Single-out'!A41","Open →")
A44: 40 | C44: Billing | D44: • TBC | E44: =COUNTA('Single-out'!$B$60:$B$69) | F44: =COUNTIF('Single-out'!$G$60:$G$69,"Tranche 1") | G44: =COUNTIF('Single-out'!$G$60:$G$69,"Tranche 2") | H44: =COUNTIF('Single-out'!$G$60:$G$69,"Tranche 3") | I44: =HYPERLINK("#'Single-out'!A58","Open →")
A45: 41 | C45: Disputes | D45: • Helen Ryan • Srini Turlapati • Rosemary Kiley • Travis Dowden • Kimberly Singleton • Neville DCosta | E45: =COUNTA('Single-out'!$B$76:$B$85) | F45: =COUNTIF('Single-out'!$G$76:$G$85,"Tranche 1") | G45: =COUNTIF('Single-out'!$G$76:$G$85,"Tranche 2") | H45: =COUNTIF('Single-out'!$G$76:$G$85,"Tranche 3") | I45: =HYPERLINK("#'Single-out'!A74","Open →")
A46: 42 | C46: Payouts | D46: • Rupert French | E46: =COUNTA('Single-out'!$B$92:$B$101) | F46: =COUNTIF('Single-out'!$G$92:$G$101,"Tranche 1") | G46: =COUNTIF('Single-out'!$G$92:$G$101,"Tranche 2") | H46: =COUNTIF('Single-out'!$G$92:$G$101,"Tranche 3") | I46: =HYPERLINK("#'Single-out'!A90","Open →")
A47: 43 | C47: PFaaS Products | D47: • David Blair • Curtis Landry • Andre Dubreuil • Soltan Nayabkhil | E47: =COUNTA('Single-out'!$B$108:$B$117) | F47: =COUNTIF('Single-out'!$G$108:$G$117,"Tranche 1") | G47: =COUNTIF('Single-out'!$G$108:$G$117,"Tranche 2") | H47: =COUNTIF('Single-out'!$G$108:$G$117,"Tranche 3") | I47: =HYPERLINK("#'Single-out'!A106","Open →")
D48: Total | E48: =SUM(E5:E47) | F48: =SUM(F5:F47) | G48: =SUM(G5:G47) | H48: =SUM(H5:H47)
C49: =HYPERLINK("#'Parking'!A1","Parking — POS software →") | D49: not tranched | E49: =COUNTA(Parking!$B$9:$B$33)

Sheet Boarding
A1: Boarding — Platform Assessment
A2: =HYPERLINK("#'Summary'!A1","← Back to Summary") | C2: Pick a State, score High / Medium / Low — the tranche, the matrix and the Summary update automatically.
A4: Tracker — jump to a sub-capability:
A5: 1. | B5: =HYPERLINK("#'Boarding'!A12","Boarding Experience")
A6: 2. | B6: =HYPERLINK("#'Boarding'!A44","Ingress")
A7: 3. | B7: =HYPERLINK("#'Boarding'!A60","Boarding Orchestration")
A8: 4. | B8: =HYPERLINK("#'Boarding'!A78","Integration & Messaging")
A9: 5. | B9: =HYPERLINK("#'Boarding'!A94","Credit & Underwriting")
A10: 6. | B10: =HYPERLINK("#'Boarding'!A110","CPQ / Quote-pricing")
A12: Boarding Experience | G12: =HYPERLINK("#'Boarding'!A4","▲ tracker") | K12: Assessment Outcome
A13: # | B13: Platform | C13: State | D13: Imperative to exit | E13: Exit complexity | F13: Supporting facts | G13: Tranche (auto) | K13: Low | L13: Medium | M13: High
A14: ① | B14: Launchpad | C14: Target state | G14: =IF(OR($B14="",$D14="",$E14=""),"",IF(OR($C14="Target state",$C14="Exception"),"Out of scope",IF($D14="Low","No tranche",IF($E14="Low","Tranche 1",IF($E14="Medium","Tranche 2",IF($D14="High","Tranche 3","No tranche")))))) | I14: Benefits | J14: High | K14: ="Tranche 1"&CHAR(10)&_xlfn.TEXTJOIN(CHAR(10),TRUE,O$14:O$39) | L14: ="Tranche 2"&CHAR(10)&_xlfn.TEXTJOIN(CHAR(10),TRUE,P$14:P$39) | M14: ="Tranche 3"&CHAR(10)&_xlfn.TEXTJOIN(CHAR(10),TRUE,Q$14:Q$39) | O14: =IF(AND($B14<>"",$C14<>"Target state",$C14<>"Exception",$D14="High",$E14="Low"),$A14&" "&$B14,"") | P14: =IF(AND($B14<>"",$C14<>"Target state",$C14<>"Exception",$D14="High",$E14="Medium"),$A14&" "&$B14,"") | Q14: =IF(AND($B14<>"",$C14<>"Target state",$C14<>"Exception",$D14="High",$E14="High"),$A14&" "&$B14,"") | R14: =IF(AND($B14<>"",$C14<>"Target state",$C14<>"Exception",$D14="Medium",$E14="Low"),$A14&" "&$B14,"") | S14: =IF(AND($B14<>"",$C14<>"Target state",$C14<>"Exception",$D14="Medium",$E14="Medium"),$A14&" "&$B14,"") | T14: =IF(AND($B14<>"",$C14<>"Target state",$C14<>"Exception",$D14="Medium",$E14="High"),$A14&" "&$B14,"") | U14: =IF(AND($B14<>"",$C14<>"Target state",$C14<>"Exception",$D14="Low",$E14="Low"),$A14&" "&$B14,"") | V14: =IF(AND($B14<>"",$C14<>"Target state",$C14<>"Exception",$D14="Low",$E14="Medium"),$A14&" "&$B14,"") | W14: =IF(AND($B14<>"",$C14<>"Target state",$C14<>"Exception",$D14="Low",$E14="High"),$A14&" "&$B14,"")
A15: ② | B15: ELAPP | C15: Non-target state | F15: Non-strategic TSYS Broomfield boarding application covering about 178K merchants; around $835K in yearly cost; replaced by Base CRM and IDGen under ECHO | G15: =IF(OR($B15="",$D15="",$E15=""),"",IF(OR($C15="Target state",$C15="Exception"),"Out of scope",IF($D15="Low","No tranche",IF($E15="Low","Tranche 1",IF($E15="Medium","Tranche 2",IF($D15="High","Tranche 3","No tranche")))))) | O15: =IF(AND($B15<>"",$C15<>"Target state",$C15<>"Exception",$D15="High",$E15="Low"),$A15&" "&$B15,"") | P15: =IF(AND($B15<>"",$C15<>"Target state",$C15<>"Exception",$D15="High",$E15="Medium"),$A15&" "&$B15,"") | Q15: =IF(AND($B15<>"",$C15<>"Target state",$C15<>"Exception",$D15="High",$E15="High"),$A15&" "&$B15,"") | R15: =IF(AND($B15<>"",$C15<>"Target state",$C15<>"Exception",$D15="Medium",$E15="Low"),$A15&" "&$B15,"") | S15: =IF(AND($B15<>"",$C15<>"Target state",$C15<>"Exception",$D15="Medium",$E15="Medium"),$A15&" "&$B15,"") | T15: =IF(AND($B15<>"",$C15<>"Target state",$C15<>"Exception",$D15="Medium",$E15="High"),$A15&" "&$B15,"") | U15: =IF(AND($B15<>"",$C15<>"Target state",$C15<>"Exception",$D15="Low",$E15="Low"),$A15&" "&$B15,"") | V15: =IF(AND($B15<>"",$C15<>"Target state",$C15<>"Exception",$D15="Low",$E15="Medium"),$A15&" "&$B15,"") | W15: =IF(AND($B15<>"",$C15<>"Target state",$C15<>"Exception",$D15="Low",$E15="High"),$A15&" "&$B15,"")
A16: ③ | B16: Merchant Application Package (MAP) | C16: Non-target state | F16: Non-strategic Omaha boarding solution also used by CPay covering about 87K merchants; around $430K in yearly third-party cost | G16: =IF(OR($B16="",$D16="",$E16=""),"",IF(OR($C16="Target state",$C16="Exception"),"Out of scope",IF($D16="Low","No tranche",IF($E16="Low","Tranche 1",IF($E16="Medium","Tranche 2",IF($D16="High","Tranche 3","No tranche")))))) | O16: =IF(AND($B16<>"",$C16<>"Target state",$C16<>"Exception",$D16="High",$E16="Low"),$A16&" "&$B16,"") | P16: =IF(AND($B16<>"",$C16<>"Target state",$C16<>"Exception",$D16="High",$E16="Medium"),$A16&" "&$B16,"") | Q16: =IF(AND($B16<>"",$C16<>"Target state",$C16<>"Exception",$D16="High",$E16="High"),$A16&" "&$B16,"") | R16: =IF(AND($B16<>"",$C16<>"Target state",$C16<>"Exception",$D16="Medium",$E16="Low"),$A16&" "&$B16,"") | S16: =IF(AND($B16<>"",$C16<>"Target state",$C16<>"Exception",$D16="Medium",$E16="Medium"),$A16&" "&$B16,"") | T16: =IF(AND($B16<>"",$C16<>"Target state",$C16<>"Exception",$D16="Medium",$E16="High"),$A16&" "&$B16,"") | U16: =IF(AND($B16<>"",$C16<>"Target state",$C16<>"Exception",$D16="Low",$E16="Low"),$A16&" "&$B16,"") | V16: =IF(AND($B16<>"",$C16<>"Target state",$C16<>"Exception",$D16="Low",$E16="Medium"),$A16&" "&$B16,"") | W16: =IF(AND($B16<>"",$C16<>"Target state",$C16<>"Exception",$D16="Low",$E16="High"),$A16&" "&$B16,"")
A17: ④ | B17: Central Station (CPay) | C17: Non-target state | F17: Non-strategic all-in-one business management platform for the Central Payments portfolio across 30K MIDs spanning sales, underwriting, boarding and service; about $360K in yearly cost | G17: =IF(OR($B17="",$D17="",$E17=""),"",IF(OR($C17="Target state",$C17="Exception"),"Out of scope",IF($D17="Low","No tranche",IF($E17="Low","Tranche 1",IF($E17="Medium","Tranche 2",IF($D17="High","Tranche 3","No tranche")))))) | O17: =IF(AND($B17<>"",$C17<>"Target state",$C17<>"Exception",$D17="High",$E17="Low"),$A17&" "&$B17,"") | P17: =IF(AND($B17<>"",$C17<>"Target state",$C17<>"Exception",$D17="High",$E17="Medium"),$A17&" "&$B17,"") | Q17: =IF(AND($B17<>"",$C17<>"Target state",$C17<>"Exception",$D17="High",$E17="High"),$A17&" "&$B17,"") | R17: =IF(AND($B17<>"",$C17<>"Target state",$C17<>"Exception",$D17="Medium",$E17="Low"),$A17&" "&$B17,"") | S17: =IF(AND($B17<>"",$C17<>"Target state",$C17<>"Exception",$D17="Medium",$E17="Medium"),$A17&" "&$B17,"") | T17: =IF(AND($B17<>"",$C17<>"Target state",$C17<>"Exception",$D17="Medium",$E17="High"),$A17&" "&$B17,"") | U17: =IF(AND($B17<>"",$C17<>"Target state",$C17<>"Exception",$D17="Low",$E17="Low"),$A17&" "&$B17,"") | V17: =IF(AND($B17<>"",$C17<>"Target state",$C17<>"Exception",$D17="Low",$E17="Medium"),$A17&" "&$B17,"") | W17: =IF(AND($B17<>"",$C17<>"Target state",$C17<>"Exception",$D17="Low",$E17="High"),$A17&" "&$B17,"")
A18: ⑤ | B18: EVONow | C18: Non-target state | F18: Non-strategic partner and merchant online application feeding the underwriting system; about $150K in yearly cost; folds into the EVO simplification program | G18: =IF(OR($B18="",$D18="",$E18=""),"",IF(OR($C18="Target state",$C18="Exception"),"Out of scope",IF($D18="Low","No tranche",IF($E18="Low","Tranche 1",IF($E18="Medium","Tranche 2",IF($D18="High","Tranche 3","No tranche")))))) | O18: =IF(AND($B18<>"",$C18<>"Target state",$C18<>"Exception",$D18="High",$E18="Low"),$A18&" "&$B18,"") | P18: =IF(AND($B18<>"",$C18<>"Target state",$C18<>"Exception",$D18="High",$E18="Medium"),$A18&" "&$B18,"") | Q18: =IF(AND($B18<>"",$C18<>"Target state",$C18<>"Exception",$D18="High",$E18="High"),$A18&" "&$B18,"") | R18: =IF(AND($B18<>"",$C18<>"Target state",$C18<>"Exception",$D18="Medium",$E18="Low"),$A18&" "&$B18,"") | S18: =IF(AND($B18<>"",$C18<>"Target state",$C18<>"Exception",$D18="Medium",$E18="Medium"),$A18&" "&$B18,"") | T18: =IF(AND($B18<>"",$C18<>"Target state",$C18<>"Exception",$D18="Medium",$E18="High"),$A18&" "&$B18,"") | U18: =IF(AND($B18<>"",$C18<>"Target state",$C18<>"Exception",$D18="Low",$E18="Low"),$A18&" "&$B18,"") | V18: =IF(AND($B18<>"",$C18<>"Target state",$C18<>"Exception",$D18="Low",$E18="Medium"),$A18&" "&$B18,"") | W18: =IF(AND($B18<>"",$C18<>"Target state",$C18<>"Exception",$D18="Low",$E18="High"),$A18&" "&$B18,"")
A19: ⑥ | B19: MOSS CA | C19: Non-target state | F19: Non-strategic boarding platform for the legacy GP Canada market with 2.3K active users; about $410K in yearly cost; repository flags initial disposition Keep & Enhance — confirm with SPOC | G19: =IF(OR($B19="",$D19="",$E19=""),"",IF(OR($C19="Target state",$C19="Exception"),"Out of scope",IF($D19="Low","No tranche",IF($E19="Low","Tranche 1",IF($E19="Medium","Tranche 2",IF($D19="High","Tranche 3","No tranche")))))) | O19: =IF(AND($B19<>"",$C19<>"Target state",$C19<>"Exception",$D19="High",$E19="Low"),$A19&" "&$B19,"") | P19: =IF(AND($B19<>"",$C19<>"Target state",$C19<>"Exception",$D19="High",$E19="Medium"),$A19&" "&$B19,"") | Q19: =IF(AND($B19<>"",$C19<>"Target state",$C19<>"Exception",$D19="High",$E19="High"),$A19&" "&$B19,"") | R19: =IF(AND($B19<>"",$C19<>"Target state",$C19<>"Exception",$D19="Medium",$E19="Low"),$A19&" "&$B19,"") | S19: =IF(AND($B19<>"",$C19<>"Target state",$C19<>"Exception",$D19="Medium",$E19="Medium"),$A19&" "&$B19,"") | T19: =IF(AND($B19<>"",$C19<>"Target state",$C19<>"Exception",$D19="Medium",$E19="High"),$A19&" "&$B19,"") | U19: =IF(AND($B19<>"",$C19<>"Target state",$C19<>"Exception",$D19="Low",$E19="Low"),$A19&" "&$B19,"") | V19: =IF(AND($B19<>"",$C19<>"Target state",$C19<>"Exception",$D19="Low",$E19="Medium"),$A19&" "&$B19,"") | W19: =IF(AND($B19<>"",$C19<>"Target state",$C19<>"Exception",$D19="Low",$E19="High"),$A19&" "&$B19,"")
A20: ⑦ | B20: MOSS AP | C20: Non-target state | F20: Non-strategic boarding platform for the legacy GP Asia Pacific market with about 230 active users; about $460K in yearly cost; repository flags initial disposition Keep & Enhance — confirm with SPOC | G20: =IF(OR($B20="",$D20="",$E20=""),"",IF(OR($C20="Target state",$C20="Exception"),"Out of scope",IF($D20="Low","No tranche",IF($E20="Low","Tranche 1",IF($E20="Medium","Tranche 2",IF($D20="High","Tranche 3","No tranche")))))) | O20: =IF(AND($B20<>"",$C20<>"Target state",$C20<>"Exception",$D20="High",$E20="Low"),$A20&" "&$B20,"") | P20: =IF(AND($B20<>"",$C20<>"Target state",$C20<>"Exception",$D20="High",$E20="Medium"),$A20&" "&$B20,"") | Q20: =IF(AND($B20<>"",$C20<>"Target state",$C20<>"Exception",$D20="High",$E20="High"),$A20&" "&$B20,"") | R20: =IF(AND($B20<>"",$C20<>"Target state",$C20<>"Exception",$D20="Medium",$E20="Low"),$A20&" "&$B20,"") | S20: =IF(AND($B20<>"",$C20<>"Target state",$C20<>"Exception",$D20="Medium",$E20="Medium"),$A20&" "&$B20,"") | T20: =IF(AND($B20<>"",$C20<>"Target state",$C20<>"Exception",$D20="Medium",$E20="High"),$A20&" "&$B20,"") | U20: =IF(AND($B20<>"",$C20<>"Target state",$C20<>"Exception",$D20="Low",$E20="Low"),$A20&" "&$B20,"") | V20: =IF(AND($B20<>"",$C20<>"Target state",$C20<>"Exception",$D20="Low",$E20="Medium"),$A20&" "&$B20,"") | W20: =IF(AND($B20<>"",$C20<>"Target state",$C20<>"Exception",$D20="Low",$E20="High"),$A20&" "&$B20,"")
A21: ⑧ | B21: MOSS UK | C21: Non-target state | F21: Non-strategic boarding platform for the legacy GP UK market with about 1.1K active users; about $990K in yearly cost; repository flags initial disposition Keep & Enhance — confirm with SPOC | G21: =IF(OR($B21="",$D21="",$E21=""),"",IF(OR($C21="Target state",$C21="Exception"),"Out of scope",IF($D21="Low","No tranche",IF($E21="Low","Tranche 1",IF($E21="Medium","Tranche 2",IF($D21="High","Tranche 3","No tranche")))))) | O21: =IF(AND($B21<>"",$C21<>"Target state",$C21<>"Exception",$D21="High",$E21="Low"),$A21&" "&$B21,"") | P21: =IF(AND($B21<>"",$C21<>"Target state",$C21<>"Exception",$D21="High",$E21="Medium"),$A21&" "&$B21,"") | Q21: =IF(AND($B21<>"",$C21<>"Target state",$C21<>"Exception",$D21="High",$E21="High"),$A21&" "&$B21,"") | R21: =IF(AND($B21<>"",$C21<>"Target state",$C21<>"Exception",$D21="Medium",$E21="Low"),$A21&" "&$B21,"") | S21: =IF(AND($B21<>"",$C21<>"Target state",$C21<>"Exception",$D21="Medium",$E21="Medium"),$A21&" "&$B21,"") | T21: =IF(AND($B21<>"",$C21<>"Target state",$C21<>"Exception",$D21="Medium",$E21="High"),$A21&" "&$B21,"") | U21: =IF(AND($B21<>"",$C21<>"Target state",$C21<>"Exception",$D21="Low",$E21="Low"),$A21&" "&$B21,"") | V21: =IF(AND($B21<>"",$C21<>"Target state",$C21<>"Exception",$D21="Low",$E21="Medium"),$A21&" "&$B21,"") | W21: =IF(AND($B21<>"",$C21<>"Target state",$C21<>"Exception",$D21="Low",$E21="High"),$A21&" "&$B21,"")
A22: ⑨ | B22: MOSS Mexico | C22: Non-target state | F22: Non-strategic boarding platform for the LATAM market; limited usage detail in the repository | G22: =IF(OR($B22="",$D22="",$E22=""),"",IF(OR($C22="Target state",$C22="Exception"),"Out of scope",IF($D22="Low","No tranche",IF($E22="Low","Tranche 1",IF($E22="Medium","Tranche 2",IF($D22="High","Tranche 3","No tranche")))))) | O22: =IF(AND($B22<>"",$C22<>"Target state",$C22<>"Exception",$D22="High",$E22="Low"),$A22&" "&$B22,"") | P22: =IF(AND($B22<>"",$C22<>"Target state",$C22<>"Exception",$D22="High",$E22="Medium"),$A22&" "&$B22,"") | Q22: =IF(AND($B22<>"",$C22<>"Target state",$C22<>"Exception",$D22="High",$E22="High"),$A22&" "&$B22,"") | R22: =IF(AND($B22<>"",$C22<>"Target state",$C22<>"Exception",$D22="Medium",$E22="Low"),$A22&" "&$B22,"") | S22: =IF(AND($B22<>"",$C22<>"Target state",$C22<>"Exception",$D22="Medium",$E22="Medium"),$A22&" "&$B22,"") | T22: =IF(AND($B22<>"",$C22<>"Target state",$C22<>"Exception",$D22="Medium",$E22="High"),$A22&" "&$B22,"") | U22: =IF(AND($B22<>"",$C22<>"Target state",$C22<>"Exception",$D22="Low",$E22="Low"),$A22&" "&$B22,"") | V22: =IF(AND($B22<>"",$C22<>"Target state",$C22<>"Exception",$D22="Low",$E22="Medium"),$A22&" "&$B22,"") | W22: =IF(AND($B22<>"",$C22<>"Target state",$C22<>"Exception",$D22="Low",$E22="High"),$A22&" "&$B22,"")
A23: ⑩ | B23: i-Apply | C23: Non-target state | F23: Non-strategic application platform for NBG Pay serving all application types; to be replaced by e-service systems | G23: =IF(OR($B23="",$D23="",$E23=""),"",IF(OR($C23="Target state",$C23="Exception"),"Out of scope",IF($D23="Low","No tranche",IF($E23="Low","Tranche 1",IF($E23="Medium","Tranche 2",IF($D23="High","Tranche 3","No tranche")))))) | J23: Medium | K23: ="Tranche 1"&CHAR(10)&_xlfn.TEXTJOIN(CHAR(10),TRUE,R$14:R$39) | L23: ="Tranche 2"&CHAR(10)&_xlfn.TEXTJOIN(CHAR(10),TRUE,S$14:S$39) | M23: =_xlfn.TEXTJOIN(CHAR(10),TRUE,T$14:T$39) | O23: =IF(AND($B23<>"",$C23<>"Target state",$C23<>"Exception",$D23="High",$E23="Low"),$A23&" "&$B23,"") | P23: =IF(AND($B23<>"",$C23<>"Target state",$C23<>"Exception",$D23="High",$E23="Medium"),$A23&" "&$B23,"") | Q23: =IF(AND($B23<>"",$C23<>"Target state",$C23<>"Exception",$D23="High",$E23="High"),$A23&" "&$B23,"") | R23: =IF(AND($B23<>"",$C23<>"Target state",$C23<>"Exception",$D23="Medium",$E23="Low"),$A23&" "&$B23,"") | S23: =IF(AND($B23<>"",$C23<>"Target state",$C23<>"Exception",$D23="Medium",$E23="Medium"),$A23&" "&$B23,"") | T23: =IF(AND($B23<>"",$C23<>"Target state",$C23<>"Exception",$D23="Medium",$E23="High"),$A23&" "&$B23,"") | U23: =IF(AND($B23<>"",$C23<>"Target state",$C23<>"Exception",$D23="Low",$E23="Low"),$A23&" "&$B23,"") | V23: =IF(AND($B23<>"",$C23<>"Target state",$C23<>"Exception",$D23="Low",$E23="Medium"),$A23&" "&$B23,"") | W23: =IF(AND($B23<>"",$C23<>"Target state",$C23<>"Exception",$D23="Low",$E23="High"),$A23&" "&$B23,"")
A24: ⑪ | B24: MVSI Onboard | C24: Non-target state | F24: Non-strategic onboarding platform for a subset of Ezidebit clients; about $50K in yearly licence cost; confirmed for decommission | G24: =IF(OR($B24="",$D24="",$E24=""),"",IF(OR($C24="Target state",$C24="Exception"),"Out of scope",IF($D24="Low","No tranche",IF($E24="Low","Tranche 1",IF($E24="Medium","Tranche 2",IF($D24="High","Tranche 3","No tranche")))))) | O24: =IF(AND($B24<>"",$C24<>"Target state",$C24<>"Exception",$D24="High",$E24="Low"),$A24&" "&$B24,"") | P24: =IF(AND($B24<>"",$C24<>"Target state",$C24<>"Exception",$D24="High",$E24="Medium"),$A24&" "&$B24,"") | Q24: =IF(AND($B24<>"",$C24<>"Target state",$C24<>"Exception",$D24="High",$E24="High"),$A24&" "&$B24,"") | R24: =IF(AND($B24<>"",$C24<>"Target state",$C24<>"Exception",$D24="Medium",$E24="Low"),$A24&" "&$B24,"") | S24: =IF(AND($B24<>"",$C24<>"Target state",$C24<>"Exception",$D24="Medium",$E24="Medium"),$A24&" "&$B24,"") | T24: =IF(AND($B24<>"",$C24<>"Target state",$C24<>"Exception",$D24="Medium",$E24="High"),$A24&" "&$B24,"") | U24: =IF(AND($B24<>"",$C24<>"Target state",$C24<>"Exception",$D24="Low",$E24="Low"),$A24&" "&$B24,"") | V24: =IF(AND($B24<>"",$C24<>"Target state",$C24<>"Exception",$D24="Low",$E24="Medium"),$A24&" "&$B24,"") | W24: =IF(AND($B24<>"",$C24<>"Target state",$C24<>"Exception",$D24="Low",$E24="High"),$A24&" "&$B24,"")
A25: ⑫ | B25: Online Boarding Portal | C25: Non-target state | F25: Non-strategic legacy Heartland and Portico boarding front end for partners feeding Instant Boarding | G25: =IF(OR($B25="",$D25="",$E25=""),"",IF(OR($C25="Target state",$C25="Exception"),"Out of scope",IF($D25="Low","No tranche",IF($E25="Low","Tranche 1",IF($E25="Medium","Tranche 2",IF($D25="High","Tranche 3","No tranche")))))) | O25: =IF(AND($B25<>"",$C25<>"Target state",$C25<>"Exception",$D25="High",$E25="Low"),$A25&" "&$B25,"") | P25: =IF(AND($B25<>"",$C25<>"Target state",$C25<>"Exception",$D25="High",$E25="Medium"),$A25&" "&$B25,"") | Q25: =IF(AND($B25<>"",$C25<>"Target state",$C25<>"Exception",$D25="High",$E25="High"),$A25&" "&$B25,"") | R25: =IF(AND($B25<>"",$C25<>"Target state",$C25<>"Exception",$D25="Medium",$E25="Low"),$A25&" "&$B25,"") | S25: =IF(AND($B25<>"",$C25<>"Target state",$C25<>"Exception",$D25="Medium",$E25="Medium"),$A25&" "&$B25,"") | T25: =IF(AND($B25<>"",$C25<>"Target state",$C25<>"Exception",$D25="Medium",$E25="High"),$A25&" "&$B25,"") | U25: =IF(AND($B25<>"",$C25<>"Target state",$C25<>"Exception",$D25="Low",$E25="Low"),$A25&" "&$B25,"") | V25: =IF(AND($B25<>"",$C25<>"Target state",$C25<>"Exception",$D25="Low",$E25="Medium"),$A25&" "&$B25,"") | W25: =IF(AND($B25<>"",$C25<>"Target state",$C25<>"Exception",$D25="Low",$E25="High"),$A25&" "&$B25,"")
A26: ⑬ | B26: Rapid Activation | C26: Non-target state | F26: Non-strategic legacy GPI boarding for partners and sales users with modest monthly boarding volume | G26: =IF(OR($B26="",$D26="",$E26=""),"",IF(OR($C26="Target state",$C26="Exception"),"Out of scope",IF($D26="Low","No tranche",IF($E26="Low","Tranche 1",IF($E26="Medium","Tranche 2",IF($D26="High","Tranche 3","No tranche")))))) | O26: =IF(AND($B26<>"",$C26<>"Target state",$C26<>"Exception",$D26="High",$E26="Low"),$A26&" "&$B26,"") | P26: =IF(AND($B26<>"",$C26<>"Target state",$C26<>"Exception",$D26="High",$E26="Medium"),$A26&" "&$B26,"") | Q26: =IF(AND($B26<>"",$C26<>"Target state",$C26<>"Exception",$D26="High",$E26="High"),$A26&" "&$B26,"") | R26: =IF(AND($B26<>"",$C26<>"Target state",$C26<>"Exception",$D26="Medium",$E26="Low"),$A26&" "&$B26,"") | S26: =IF(AND($B26<>"",$C26<>"Target state",$C26<>"Exception",$D26="Medium",$E26="Medium"),$A26&" "&$B26,"") | T26: =IF(AND($B26<>"",$C26<>"Target state",$C26<>"Exception",$D26="Medium",$E26="High"),$A26&" "&$B26,"") | U26: =IF(AND($B26<>"",$C26<>"Target state",$C26<>"Exception",$D26="Low",$E26="Low"),$A26&" "&$B26,"") | V26: =IF(AND($B26<>"",$C26<>"Target state",$C26<>"Exception",$D26="Low",$E26="Medium"),$A26&" "&$B26,"") | W26: =IF(AND($B26<>"",$C26<>"Target state",$C26<>"Exception",$D26="Low",$E26="High"),$A26&" "&$B26,"")
A27: ⑭ | B27: Hermes | C27: Non-target state | F27: Non-strategic third-party boarding system for Czech bank advisors and sales reps; about 26K clients processed; modest annual cost | G27: =IF(OR($B27="",$D27="",$E27=""),"",IF(OR($C27="Target state",$C27="Exception"),"Out of scope",IF($D27="Low","No tranche",IF($E27="Low","Tranche 1",IF($E27="Medium","Tranche 2",IF($D27="High","Tranche 3","No tranche")))))) | O27: =IF(AND($B27<>"",$C27<>"Target state",$C27<>"Exception",$D27="High",$E27="Low"),$A27&" "&$B27,"") | P27: =IF(AND($B27<>"",$C27<>"Target state",$C27<>"Exception",$D27="High",$E27="Medium"),$A27&" "&$B27,"") | Q27: =IF(AND($B27<>"",$C27<>"Target state",$C27<>"Exception",$D27="High",$E27="High"),$A27&" "&$B27,"") | R27: =IF(AND($B27<>"",$C27<>"Target state",$C27<>"Exception",$D27="Medium",$E27="Low"),$A27&" "&$B27,"") | S27: =IF(AND($B27<>"",$C27<>"Target state",$C27<>"Exception",$D27="Medium",$E27="Medium"),$A27&" "&$B27,"") | T27: =IF(AND($B27<>"",$C27<>"Target state",$C27<>"Exception",$D27="Medium",$E27="High"),$A27&" "&$B27,"") | U27: =IF(AND($B27<>"",$C27<>"Target state",$C27<>"Exception",$D27="Low",$E27="Low"),$A27&" "&$B27,"") | V27: =IF(AND($B27<>"",$C27<>"Target state",$C27<>"Exception",$D27="Low",$E27="Medium"),$A27&" "&$B27,"") | W27: =IF(AND($B27<>"",$C27<>"Target state",$C27<>"Exception",$D27="Low",$E27="High"),$A27&" "&$B27,"")
A28: ⑮ | B28: Portico Website (POS Gateway) | C28: Non-target state | F28: Non-strategic internal UI for manual Portico boarding, configuration and research across US, Canada and UK portfolios | G28: =IF(OR($B28="",$D28="",$E28=""),"",IF(OR($C28="Target state",$C28="Exception"),"Out of scope",IF($D28="Low","No tranche",IF($E28="Low","Tranche 1",IF($E28="Medium","Tranche 2",IF($D28="High","Tranche 3","No tranche")))))) | O28: =IF(AND($B28<>"",$C28<>"Target state",$C28<>"Exception",$D28="High",$E28="Low"),$A28&" "&$B28,"") | P28: =IF(AND($B28<>"",$C28<>"Target state",$C28<>"Exception",$D28="High",$E28="Medium"),$A28&" "&$B28,"") | Q28: =IF(AND($B28<>"",$C28<>"Target state",$C28<>"Exception",$D28="High",$E28="High"),$A28&" "&$B28,"") | R28: =IF(AND($B28<>"",$C28<>"Target state",$C28<>"Exception",$D28="Medium",$E28="Low"),$A28&" "&$B28,"") | S28: =IF(AND($B28<>"",$C28<>"Target state",$C28<>"Exception",$D28="Medium",$E28="Medium"),$A28&" "&$B28,"") | T28: =IF(AND($B28<>"",$C28<>"Target state",$C28<>"Exception",$D28="Medium",$E28="High"),$A28&" "&$B28,"") | U28: =IF(AND($B28<>"",$C28<>"Target state",$C28<>"Exception",$D28="Low",$E28="Low"),$A28&" "&$B28,"") | V28: =IF(AND($B28<>"",$C28<>"Target state",$C28<>"Exception",$D28="Low",$E28="Medium"),$A28&" "&$B28,"") | W28: =IF(AND($B28<>"",$C28<>"Target state",$C28<>"Exception",$D28="Low",$E28="High"),$A28&" "&$B28,"")
A29: ⑯ | B29: NetSuite (Cayan) | C29: Non-target state | F29: Non-strategic SaaS boarding and servicing customization for the Cayan portfolio with about 670 users; around $670K in yearly cost | G29: =IF(OR($B29="",$D29="",$E29=""),"",IF(OR($C29="Target state",$C29="Exception"),"Out of scope",IF($D29="Low","No tranche",IF($E29="Low","Tranche 1",IF($E29="Medium","Tranche 2",IF($D29="High","Tranche 3","No tranche")))))) | O29: =IF(AND($B29<>"",$C29<>"Target state",$C29<>"Exception",$D29="High",$E29="Low"),$A29&" "&$B29,"") | P29: =IF(AND($B29<>"",$C29<>"Target state",$C29<>"Exception",$D29="High",$E29="Medium"),$A29&" "&$B29,"") | Q29: =IF(AND($B29<>"",$C29<>"Target state",$C29<>"Exception",$D29="High",$E29="High"),$A29&" "&$B29,"") | R29: =IF(AND($B29<>"",$C29<>"Target state",$C29<>"Exception",$D29="Medium",$E29="Low"),$A29&" "&$B29,"") | S29: =IF(AND($B29<>"",$C29<>"Target state",$C29<>"Exception",$D29="Medium",$E29="Medium"),$A29&" "&$B29,"") | T29: =IF(AND($B29<>"",$C29<>"Target state",$C29<>"Exception",$D29="Medium",$E29="High"),$A29&" "&$B29,"") | U29: =IF(AND($B29<>"",$C29<>"Target state",$C29<>"Exception",$D29="Low",$E29="Low"),$A29&" "&$B29,"") | V29: =IF(AND($B29<>"",$C29<>"Target state",$C29<>"Exception",$D29="Low",$E29="Medium"),$A29&" "&$B29,"") | W29: =IF(AND($B29<>"",$C29<>"Target state",$C29<>"Exception",$D29="Low",$E29="High"),$A29&" "&$B29,"")
A30: ⑰ | B30: Payroll CRM | C30: Non-target state | F30: Non-strategic boarding system for payroll clients with about 150 users; modest annual cost | G30: =IF(OR($B30="",$D30="",$E30=""),"",IF(OR($C30="Target state",$C30="Exception"),"Out of scope",IF($D30="Low","No tranche",IF($E30="Low","Tranche 1",IF($E30="Medium","Tranche 2",IF($D30="High","Tranche 3","No tranche")))))) | O30: =IF(AND($B30<>"",$C30<>"Target state",$C30<>"Exception",$D30="High",$E30="Low"),$A30&" "&$B30,"") | P30: =IF(AND($B30<>"",$C30<>"Target state",$C30<>"Exception",$D30="High",$E30="Medium"),$A30&" "&$B30,"") | Q30: =IF(AND($B30<>"",$C30<>"Target state",$C30<>"Exception",$D30="High",$E30="High"),$A30&" "&$B30,"") | R30: =IF(AND($B30<>"",$C30<>"Target state",$C30<>"Exception",$D30="Medium",$E30="Low"),$A30&" "&$B30,"") | S30: =IF(AND($B30<>"",$C30<>"Target state",$C30<>"Exception",$D30="Medium",$E30="Medium"),$A30&" "&$B30,"") | T30: =IF(AND($B30<>"",$C30<>"Target state",$C30<>"Exception",$D30="Medium",$E30="High"),$A30&" "&$B30,"") | U30: =IF(AND($B30<>"",$C30<>"Target state",$C30<>"Exception",$D30="Low",$E30="Low"),$A30&" "&$B30,"") | V30: =IF(AND($B30<>"",$C30<>"Target state",$C30<>"Exception",$D30="Low",$E30="Medium"),$A30&" "&$B30,"") | W30: =IF(AND($B30<>"",$C30<>"Target state",$C30<>"Exception",$D30="Low",$E30="High"),$A30&" "&$B30,"")
A31: ⑱ | B31: eContracts | C31: Non-target state | F31: Non-strategic merchant agreement and eSignature generation used in Poland; about 78K merchants processed; modest annual cost | G31: =IF(OR($B31="",$D31="",$E31=""),"",IF(OR($C31="Target state",$C31="Exception"),"Out of scope",IF($D31="Low","No tranche",IF($E31="Low","Tranche 1",IF($E31="Medium","Tranche 2",IF($D31="High","Tranche 3","No tranche")))))) | O31: =IF(AND($B31<>"",$C31<>"Target state",$C31<>"Exception",$D31="High",$E31="Low"),$A31&" "&$B31,"") | P31: =IF(AND($B31<>"",$C31<>"Target state",$C31<>"Exception",$D31="High",$E31="Medium"),$A31&" "&$B31,"") | Q31: =IF(AND($B31<>"",$C31<>"Target state",$C31<>"Exception",$D31="High",$E31="High"),$A31&" "&$B31,"") | R31: =IF(AND($B31<>"",$C31<>"Target state",$C31<>"Exception",$D31="Medium",$E31="Low"),$A31&" "&$B31,"") | S31: =IF(AND($B31<>"",$C31<>"Target state",$C31<>"Exception",$D31="Medium",$E31="Medium"),$A31&" "&$B31,"") | T31: =IF(AND($B31<>"",$C31<>"Target state",$C31<>"Exception",$D31="Medium",$E31="High"),$A31&" "&$B31,"") | U31: =IF(AND($B31<>"",$C31<>"Target state",$C31<>"Exception",$D31="Low",$E31="Low"),$A31&" "&$B31,"") | V31: =IF(AND($B31<>"",$C31<>"Target state",$C31<>"Exception",$D31="Low",$E31="Medium"),$A31&" "&$B31,"") | W31: =IF(AND($B31<>"",$C31<>"Target state",$C31<>"Exception",$D31="Low",$E31="High"),$A31&" "&$B31,"")
A32: ⑲ | B32: AssureSign | C32: Non-target state | F32: Third-party eSignature vendor for ELAPP priced per document; follows the ELAPP replacement path | G32: =IF(OR($B32="",$D32="",$E32=""),"",IF(OR($C32="Target state",$C32="Exception"),"Out of scope",IF($D32="Low","No tranche",IF($E32="Low","Tranche 1",IF($E32="Medium","Tranche 2",IF($D32="High","Tranche 3","No tranche")))))) | J32: Low | K32: =_xlfn.TEXTJOIN(CHAR(10),TRUE,U$14:U$39) | L32: =_xlfn.TEXTJOIN(CHAR(10),TRUE,V$14:V$39) | M32: =_xlfn.TEXTJOIN(CHAR(10),TRUE,W$14:W$39) | O32: =IF(AND($B32<>"",$C32<>"Target state",$C32<>"Exception",$D32="High",$E32="Low"),$A32&" "&$B32,"") | P32: =IF(AND($B32<>"",$C32<>"Target state",$C32<>"Exception",$D32="High",$E32="Medium"),$A32&" "&$B32,"") | Q32: =IF(AND($B32<>"",$C32<>"Target state",$C32<>"Exception",$D32="High",$E32="High"),$A32&" "&$B32,"") | R32: =IF(AND($B32<>"",$C32<>"Target state",$C32<>"Exception",$D32="Medium",$E32="Low"),$A32&" "&$B32,"") | S32: =IF(AND($B32<>"",$C32<>"Target state",$C32<>"Exception",$D32="Medium",$E32="Medium"),$A32&" "&$B32,"") | T32: =IF(AND($B32<>"",$C32<>"Target state",$C32<>"Exception",$D32="Medium",$E32="High"),$A32&" "&$B32,"") | U32: =IF(AND($B32<>"",$C32<>"Target state",$C32<>"Exception",$D32="Low",$E32="Low"),$A32&" "&$B32,"") | V32: =IF(AND($B32<>"",$C32<>"Target state",$C32<>"Exception",$D32="Low",$E32="Medium"),$A32&" "&$B32,"") | W32: =IF(AND($B32<>"",$C32<>"Target state",$C32<>"Exception",$D32="Low",$E32="High"),$A32&" "&$B32,"")
A33: ⑳ | B33: Agreement Express | C33: Non-target state | F33: Third-party eSignature tool used by the Cayan NetSuite boarding flow; on the decommission path | G33: =IF(OR($B33="",$D33="",$E33=""),"",IF(OR($C33="Target state",$C33="Exception"),"Out of scope",IF($D33="Low","No tranche",IF($E33="Low","Tranche 1",IF($E33="Medium","Tranche 2",IF($D33="High","Tranche 3","No tranche")))))) | O33: =IF(AND($B33<>"",$C33<>"Target state",$C33<>"Exception",$D33="High",$E33="Low"),$A33&" "&$B33,"") | P33: =IF(AND($B33<>"",$C33<>"Target state",$C33<>"Exception",$D33="High",$E33="Medium"),$A33&" "&$B33,"") | Q33: =IF(AND($B33<>"",$C33<>"Target state",$C33<>"Exception",$D33="High",$E33="High"),$A33&" "&$B33,"") | R33: =IF(AND($B33<>"",$C33<>"Target state",$C33<>"Exception",$D33="Medium",$E33="Low"),$A33&" "&$B33,"") | S33: =IF(AND($B33<>"",$C33<>"Target state",$C33<>"Exception",$D33="Medium",$E33="Medium"),$A33&" "&$B33,"") | T33: =IF(AND($B33<>"",$C33<>"Target state",$C33<>"Exception",$D33="Medium",$E33="High"),$A33&" "&$B33,"") | U33: =IF(AND($B33<>"",$C33<>"Target state",$C33<>"Exception",$D33="Low",$E33="Low"),$A33&" "&$B33,"") | V33: =IF(AND($B33<>"",$C33<>"Target state",$C33<>"Exception",$D33="Low",$E33="Medium"),$A33&" "&$B33,"") | W33: =IF(AND($B33<>"",$C33<>"Target state",$C33<>"Exception",$D33="Low",$E33="High"),$A33&" "&$B33,"")
A34: ㉑ | B34: Switch | C34: Non-target state | F34: Non-strategic boarding system for the Mainstream portfolio acquisition processing on the legacy TSYS stack; confirmed for decommission | G34: =IF(OR($B34="",$D34="",$E34=""),"",IF(OR($C34="Target state",$C34="Exception"),"Out of scope",IF($D34="Low","No tranche",IF($E34="Low","Tranche 1",IF($E34="Medium","Tranche 2",IF($D34="High","Tranche 3","No tranche")))))) | O34: =IF(AND($B34<>"",$C34<>"Target state",$C34<>"Exception",$D34="High",$E34="Low"),$A34&" "&$B34,"") | P34: =IF(AND($B34<>"",$C34<>"Target state",$C34<>"Exception",$D34="High",$E34="Medium"),$A34&" "&$B34,"") | Q34: =IF(AND($B34<>"",$C34<>"Target state",$C34<>"Exception",$D34="High",$E34="High"),$A34&" "&$B34,"") | R34: =IF(AND($B34<>"",$C34<>"Target state",$C34<>"Exception",$D34="Medium",$E34="Low"),$A34&" "&$B34,"") | S34: =IF(AND($B34<>"",$C34<>"Target state",$C34<>"Exception",$D34="Medium",$E34="Medium"),$A34&" "&$B34,"") | T34: =IF(AND($B34<>"",$C34<>"Target state",$C34<>"Exception",$D34="Medium",$E34="High"),$A34&" "&$B34,"") | U34: =IF(AND($B34<>"",$C34<>"Target state",$C34<>"Exception",$D34="Low",$E34="Low"),$A34&" "&$B34,"") | V34: =IF(AND($B34<>"",$C34<>"Target state",$C34<>"Exception",$D34="Low",$E34="Medium"),$A34&" "&$B34,"") | W34: =IF(AND($B34<>"",$C34<>"Target state",$C34<>"Exception",$D34="Low",$E34="High"),$A34&" "&$B34,"")
A35: ㉒ | B35: Fi911 | C35: Non-target state | F35: Third-party boarding and deployment platform supporting the NCR portfolio and Jumpman; about $240K in yearly cost; strategy is to move to in-house boarding | G35: =IF(OR($B35="",$D35="",$E35=""),"",IF(OR($C35="Target state",$C35="Exception"),"Out of scope",IF($D35="Low","No tranche",IF($E35="Low","Tranche 1",IF($E35="Medium","Tranche 2",IF($D35="High","Tranche 3","No tranche")))))) | O35: =IF(AND($B35<>"",$C35<>"Target state",$C35<>"Exception",$D35="High",$E35="Low"),$A35&" "&$B35,"") | P35: =IF(AND($B35<>"",$C35<>"Target state",$C35<>"Exception",$D35="High",$E35="Medium"),$A35&" "&$B35,"") | Q35: =IF(AND($B35<>"",$C35<>"Target state",$C35<>"Exception",$D35="High",$E35="High"),$A35&" "&$B35,"") | R35: =IF(AND($B35<>"",$C35<>"Target state",$C35<>"Exception",$D35="Medium",$E35="Low"),$A35&" "&$B35,"") | S35: =IF(AND($B35<>"",$C35<>"Target state",$C35<>"Exception",$D35="Medium",$E35="Medium"),$A35&" "&$B35,"") | T35: =IF(AND($B35<>"",$C35<>"Target state",$C35<>"Exception",$D35="Medium",$E35="High"),$A35&" "&$B35,"") | U35: =IF(AND($B35<>"",$C35<>"Target state",$C35<>"Exception",$D35="Low",$E35="Low"),$A35&" "&$B35,"") | V35: =IF(AND($B35<>"",$C35<>"Target state",$C35<>"Exception",$D35="Low",$E35="Medium"),$A35&" "&$B35,"") | W35: =IF(AND($B35<>"",$C35<>"Target state",$C35<>"Exception",$D35="Low",$E35="High"),$A35&" "&$B35,"")
A36: ㉓ | G36: =IF(OR($B36="",$D36="",$E36=""),"",IF(OR($C36="Target state",$C36="Exception"),"Out of scope",IF($D36="Low","No tranche",IF($E36="Low","Tranche 1",IF($E36="Medium","Tranche 2",IF($D36="High","Tranche 3","No tranche")))))) | O36: =IF(AND($B36<>"",$C36<>"Target state",$C36<>"Exception",$D36="High",$E36="Low"),$A36&" "&$B36,"") | P36: =IF(AND($B36<>"",$C36<>"Target state",$C36<>"Exception",$D36="High",$E36="Medium"),$A36&" "&$B36,"") | Q36: =IF(AND($B36<>"",$C36<>"Target state",$C36<>"Exception",$D36="High",$E36="High"),$A36&" "&$B36,"") | R36: =IF(AND($B36<>"",$C36<>"Target state",$C36<>"Exception",$D36="Medium",$E36="Low"),$A36&" "&$B36,"") | S36: =IF(AND($B36<>"",$C36<>"Target state",$C36<>"Exception",$D36="Medium",$E36="Medium"),$A36&" "&$B36,"") | T36: =IF(AND($B36<>"",$C36<>"Target state",$C36<>"Exception",$D36="Medium",$E36="High"),$A36&" "&$B36,"") | U36: =IF(AND($B36<>"",$C36<>"Target state",$C36<>"Exception",$D36="Low",$E36="Low"),$A36&" "&$B36,"") | V36: =IF(AND($B36<>"",$C36<>"Target state",$C36<>"Exception",$D36="Low",$E36="Medium"),$A36&" "&$B36,"") | W36: =IF(AND($B36<>"",$C36<>"Target state",$C36<>"Exception",$D36="Low",$E36="High"),$A36&" "&$B36,"")
A37: ㉔ | G37: =IF(OR($B37="",$D37="",$E37=""),"",IF(OR($C37="Target state",$C37="Exception"),"Out of scope",IF($D37="Low","No tranche",IF($E37="Low","Tranche 1",IF($E37="Medium","Tranche 2",IF($D37="High","Tranche 3","No tranche")))))) | O37: =IF(AND($B37<>"",$C37<>"Target state",$C37<>"Exception",$D37="High",$E37="Low"),$A37&" "&$B37,"") | P37: =IF(AND($B37<>"",$C37<>"Target state",$C37<>"Exception",$D37="High",$E37="Medium"),$A37&" "&$B37,"") | Q37: =IF(AND($B37<>"",$C37<>"Target state",$C37<>"Exception",$D37="High",$E37="High"),$A37&" "&$B37,"") | R37: =IF(AND($B37<>"",$C37<>"Target state",$C37<>"Exception",$D37="Medium",$E37="Low"),$A37&" "&$B37,"") | S37: =IF(AND($B37<>"",$C37<>"Target state",$C37<>"Exception",$D37="Medium",$E37="Medium"),$A37&" "&$B37,"") | T37: =IF(AND($B37<>"",$C37<>"Target state",$C37<>"Exception",$D37="Medium",$E37="High"),$A37&" "&$B37,"") | U37: =IF(AND($B37<>"",$C37<>"Target state",$C37<>"Exception",$D37="Low",$E37="Low"),$A37&" "&$B37,"") | V37: =IF(AND($B37<>"",$C37<>"Target state",$C37<>"Exception",$D37="Low",$E37="Medium"),$A37&" "&$B37,"") | W37: =IF(AND($B37<>"",$C37<>"Target state",$C37<>"Exception",$D37="Low",$E37="High"),$A37&" "&$B37,"")
A38: ㉕ | G38: =IF(OR($B38="",$D38="",$E38=""),"",IF(OR($C38="Target state",$C38="Exception"),"Out of scope",IF($D38="Low","No tranche",IF($E38="Low","Tranche 1",IF($E38="Medium","Tranche 2",IF($D38="High","Tranche 3","No tranche")))))) | O38: =IF(AND($B38<>"",$C38<>"Target state",$C38<>"Exception",$D38="High",$E38="Low"),$A38&" "&$B38,"") | P38: =IF(AND($B38<>"",$C38<>"Target state",$C38<>"Exception",$D38="High",$E38="Medium"),$A38&" "&$B38,"") | Q38: =IF(AND($B38<>"",$C38<>"Target state",$C38<>"Exception",$D38="High",$E38="High"),$A38&" "&$B38,"") | R38: =IF(AND($B38<>"",$C38<>"Target state",$C38<>"Exception",$D38="Medium",$E38="Low"),$A38&" "&$B38,"") | S38: =IF(AND($B38<>"",$C38<>"Target state",$C38<>"Exception",$D38="Medium",$E38="Medium"),$A38&" "&$B38,"") | T38: =IF(AND($B38<>"",$C38<>"Target state",$C38<>"Exception",$D38="Medium",$E38="High"),$A38&" "&$B38,"") | U38: =IF(AND($B38<>"",$C38<>"Target state",$C38<>"Exception",$D38="Low",$E38="Low"),$A38&" "&$B38,"") | V38: =IF(AND($B38<>"",$C38<>"Target state",$C38<>"Exception",$D38="Low",$E38="Medium"),$A38&" "&$B38,"") | W38: =IF(AND($B38<>"",$C38<>"Target state",$C38<>"Exception",$D38="Low",$E38="High"),$A38&" "&$B38,"")
A39: ㉖ | G39: =IF(OR($B39="",$D39="",$E39=""),"",IF(OR($C39="Target state",$C39="Exception"),"Out of scope",IF($D39="Low","No tranche",IF($E39="Low","Tranche 1",IF($E39="Medium","Tranche 2",IF($D39="High","Tranche 3","No tranche")))))) | O39: =IF(AND($B39<>"",$C39<>"Target state",$C39<>"Exception",$D39="High",$E39="Low"),$A39&" "&$B39,"") | P39: =IF(AND($B39<>"",$C39<>"Target state",$C39<>"Exception",$D39="High",$E39="Medium"),$A39&" "&$B39,"") | Q39: =IF(AND($B39<>"",$C39<>"Target state",$C39<>"Exception",$D39="High",$E39="High"),$A39&" "&$B39,"") | R39: =IF(AND($B39<>"",$C39<>"Target state",$C39<>"Exception",$D39="Medium",$E39="Low"),$A39&" "&$B39,"") | S39: =IF(AND($B39<>"",$C39<>"Target state",$C39<>"Exception",$D39="Medium",$E39="Medium"),$A39&" "&$B39,"") | T39: =IF(AND($B39<>"",$C39<>"Target state",$C39<>"Exception",$D39="Medium",$E39="High"),$A39&" "&$B39,"") | U39: =IF(AND($B39<>"",$C39<>"Target state",$C39<>"Exception",$D39="Low",$E39="Low"),$A39&" "&$B39,"") | V39: =IF(AND($B39<>"",$C39<>"Target state",$C39<>"Exception",$D39="Low",$E39="Medium"),$A39&" "&$B39,"") | W39: =IF(AND($B39<>"",$C39<>"Target state",$C39<>"Exception",$D39="Low",$E39="High"),$A39&" "&$B39,"")
K40: Complexity
A44: Ingress | G44: =HYPERLINK("#'Boarding'!A4","▲ tracker") | K44: Assessment Outcome
A45: # | B45: Platform | C45: State | D45: Imperative to exit | E45: Exit complexity | F45: Supporting facts | G45: Tranche (auto) | K45: Low | L45: Medium | M45: High
A46: ① | B46: Instant Boarding | C46: Non-target state | F46: Service-based boarding interface processing about 32K US payments and payroll applications a year from external systems; repository flags initial disposition Keep & Enhance — confirm with SPOC | G46: =IF(OR($B46="",$D46="",$E46=""),"",IF(OR($C46="Target state",$C46="Exception"),"Out of scope",IF($D46="Low","No tranche",IF($E46="Low","Tranche 1",IF($E46="Medium","Tranche 2",IF($D46="High","Tranche 3","No tranche")))))) | I46: Benefits | J46: High | K46: ="Tranche 1"&CHAR(10)&_xlfn.TEXTJOIN(CHAR(10),TRUE,O$46:O$55) | L46: ="Tranche 2"&CHAR(10)&_xlfn.TEXTJOIN(CHAR(10),TRUE,P$46:P$55) | M46: ="Tranche 3"&CHAR(10)&_xlfn.TEXTJOIN(CHAR(10),TRUE,Q$46:Q$55) | O46: =IF(AND($B46<>"",$C46<>"Target state",$C46<>"Exception",$D46="High",$E46="Low"),$A46&" "&$B46,"") | P46: =IF(AND($B46<>"",$C46<>"Target state",$C46<>"Exception",$D46="High",$E46="Medium"),$A46&" "&$B46,"") | Q46: =IF(AND($B46<>"",$C46<>"Target state",$C46<>"Exception",$D46="High",$E46="High"),$A46&" "&$B46,"") | R46: =IF(AND($B46<>"",$C46<>"Target state",$C46<>"Exception",$D46="Medium",$E46="Low"),$A46&" "&$B46,"") | S46: =IF(AND($B46<>"",$C46<>"Target state",$C46<>"Exception",$D46="Medium",$E46="Medium"),$A46&" "&$B46,"") | T46: =IF(AND($B46<>"",$C46<>"Target state",$C46<>"Exception",$D46="Medium",$E46="High"),$A46&" "&$B46,"") | U46: =IF(AND($B46<>"",$C46<>"Target state",$C46<>"Exception",$D46="Low",$E46="Low"),$A46&" "&$B46,"") | V46: =IF(AND($B46<>"",$C46<>"Target state",$C46<>"Exception",$D46="Low",$E46="Medium"),$A46&" "&$B46,"") | W46: =IF(AND($B46<>"",$C46<>"Target state",$C46<>"Exception",$D46="Low",$E46="High"),$A46&" "&$B46,"")
A47: ② | B47: ELAPP Boarding API | C47: Non-target state | F47: Non-strategic merchant boarding API for partner integrators with about 9.3K MIDs boarded; around $280K in yearly cost; replaced by Base CRM | G47: =IF(OR($B47="",$D47="",$E47=""),"",IF(OR($C47="Target state",$C47="Exception"),"Out of scope",IF($D47="Low","No tranche",IF($E47="Low","Tranche 1",IF($E47="Medium","Tranche 2",IF($D47="High","Tranche 3","No tranche")))))) | O47: =IF(AND($B47<>"",$C47<>"Target state",$C47<>"Exception",$D47="High",$E47="Low"),$A47&" "&$B47,"") | P47: =IF(AND($B47<>"",$C47<>"Target state",$C47<>"Exception",$D47="High",$E47="Medium"),$A47&" "&$B47,"") | Q47: =IF(AND($B47<>"",$C47<>"Target state",$C47<>"Exception",$D47="High",$E47="High"),$A47&" "&$B47,"") | R47: =IF(AND($B47<>"",$C47<>"Target state",$C47<>"Exception",$D47="Medium",$E47="Low"),$A47&" "&$B47,"") | S47: =IF(AND($B47<>"",$C47<>"Target state",$C47<>"Exception",$D47="Medium",$E47="Medium"),$A47&" "&$B47,"") | T47: =IF(AND($B47<>"",$C47<>"Target state",$C47<>"Exception",$D47="Medium",$E47="High"),$A47&" "&$B47,"") | U47: =IF(AND($B47<>"",$C47<>"Target state",$C47<>"Exception",$D47="Low",$E47="Low"),$A47&" "&$B47,"") | V47: =IF(AND($B47<>"",$C47<>"Target state",$C47<>"Exception",$D47="Low",$E47="Medium"),$A47&" "&$B47,"") | W47: =IF(AND($B47<>"",$C47<>"Target state",$C47<>"Exception",$D47="Low",$E47="High"),$A47&" "&$B47,"")
A48: ③ | B48: MerchantFlo | C48: Non-target state | F48: Non-strategic boarding integration with a B2B API into OnTrak and a legacy Mindbody email flow; about $130K in yearly cost; B2B is replaced by Base CRM while the Mindbody flow persists | G48: =IF(OR($B48="",$D48="",$E48=""),"",IF(OR($C48="Target state",$C48="Exception"),"Out of scope",IF($D48="Low","No tranche",IF($E48="Low","Tranche 1",IF($E48="Medium","Tranche 2",IF($D48="High","Tranche 3","No tranche")))))) | O48: =IF(AND($B48<>"",$C48<>"Target state",$C48<>"Exception",$D48="High",$E48="Low"),$A48&" "&$B48,"") | P48: =IF(AND($B48<>"",$C48<>"Target state",$C48<>"Exception",$D48="High",$E48="Medium"),$A48&" "&$B48,"") | Q48: =IF(AND($B48<>"",$C48<>"Target state",$C48<>"Exception",$D48="High",$E48="High"),$A48&" "&$B48,"") | R48: =IF(AND($B48<>"",$C48<>"Target state",$C48<>"Exception",$D48="Medium",$E48="Low"),$A48&" "&$B48,"") | S48: =IF(AND($B48<>"",$C48<>"Target state",$C48<>"Exception",$D48="Medium",$E48="Medium"),$A48&" "&$B48,"") | T48: =IF(AND($B48<>"",$C48<>"Target state",$C48<>"Exception",$D48="Medium",$E48="High"),$A48&" "&$B48,"") | U48: =IF(AND($B48<>"",$C48<>"Target state",$C48<>"Exception",$D48="Low",$E48="Low"),$A48&" "&$B48,"") | V48: =IF(AND($B48<>"",$C48<>"Target state",$C48<>"Exception",$D48="Low",$E48="Medium"),$A48&" "&$B48,"") | W48: =IF(AND($B48<>"",$C48<>"Target state",$C48<>"Exception",$D48="Low",$E48="High"),$A48&" "&$B48,"")
A49: ④ | B49: Automated Boarding | C49: Non-target state | F49: Automated merchant and terminal boarding for OpenEdge and Genius on Edge; repository flags initial disposition Keep & Enhance — confirm with SPOC | G49: =IF(OR($B49="",$D49="",$E49=""),"",IF(OR($C49="Target state",$C49="Exception"),"Out of scope",IF($D49="Low","No tranche",IF($E49="Low","Tranche 1",IF($E49="Medium","Tranche 2",IF($D49="High","Tranche 3","No tranche")))))) | O49: =IF(AND($B49<>"",$C49<>"Target state",$C49<>"Exception",$D49="High",$E49="Low"),$A49&" "&$B49,"") | P49: =IF(AND($B49<>"",$C49<>"Target state",$C49<>"Exception",$D49="High",$E49="Medium"),$A49&" "&$B49,"") | Q49: =IF(AND($B49<>"",$C49<>"Target state",$C49<>"Exception",$D49="High",$E49="High"),$A49&" "&$B49,"") | R49: =IF(AND($B49<>"",$C49<>"Target state",$C49<>"Exception",$D49="Medium",$E49="Low"),$A49&" "&$B49,"") | S49: =IF(AND($B49<>"",$C49<>"Target state",$C49<>"Exception",$D49="Medium",$E49="Medium"),$A49&" "&$B49,"") | T49: =IF(AND($B49<>"",$C49<>"Target state",$C49<>"Exception",$D49="Medium",$E49="High"),$A49&" "&$B49,"") | U49: =IF(AND($B49<>"",$C49<>"Target state",$C49<>"Exception",$D49="Low",$E49="Low"),$A49&" "&$B49,"") | V49: =IF(AND($B49<>"",$C49<>"Target state",$C49<>"Exception",$D49="Low",$E49="Medium"),$A49&" "&$B49,"") | W49: =IF(AND($B49<>"",$C49<>"Target state",$C49<>"Exception",$D49="Low",$E49="High"),$A49&" "&$B49,"")
A50: ⑤ | B50: Multi Location Boarding | C50: Non-target state | F50: Non-strategic web application boarding multiple locations at once into Instant Boarding with about 1.8K users; modest annual cost | G50: =IF(OR($B50="",$D50="",$E50=""),"",IF(OR($C50="Target state",$C50="Exception"),"Out of scope",IF($D50="Low","No tranche",IF($E50="Low","Tranche 1",IF($E50="Medium","Tranche 2",IF($D50="High","Tranche 3","No tranche")))))) | J50: Medium | K50: ="Tranche 1"&CHAR(10)&_xlfn.TEXTJOIN(CHAR(10),TRUE,R$46:R$55) | L50: ="Tranche 2"&CHAR(10)&_xlfn.TEXTJOIN(CHAR(10),TRUE,S$46:S$55) | M50: =_xlfn.TEXTJOIN(CHAR(10),TRUE,T$46:T$55) | O50: =IF(AND($B50<>"",$C50<>"Target state",$C50<>"Exception",$D50="High",$E50="Low"),$A50&" "&$B50,"") | P50: =IF(AND($B50<>"",$C50<>"Target state",$C50<>"Exception",$D50="High",$E50="Medium"),$A50&" "&$B50,"") | Q50: =IF(AND($B50<>"",$C50<>"Target state",$C50<>"Exception",$D50="High",$E50="High"),$A50&" "&$B50,"") | R50: =IF(AND($B50<>"",$C50<>"Target state",$C50<>"Exception",$D50="Medium",$E50="Low"),$A50&" "&$B50,"") | S50: =IF(AND($B50<>"",$C50<>"Target state",$C50<>"Exception",$D50="Medium",$E50="Medium"),$A50&" "&$B50,"") | T50: =IF(AND($B50<>"",$C50<>"Target state",$C50<>"Exception",$D50="Medium",$E50="High"),$A50&" "&$B50,"") | U50: =IF(AND($B50<>"",$C50<>"Target state",$C50<>"Exception",$D50="Low",$E50="Low"),$A50&" "&$B50,"") | V50: =IF(AND($B50<>"",$C50<>"Target state",$C50<>"Exception",$D50="Low",$E50="Medium"),$A50&" "&$B50,"") | W50: =IF(AND($B50<>"",$C50<>"Target state",$C50<>"Exception",$D50="Low",$E50="High"),$A50&" "&$B50,"")
A51: ⑥ | B51: GPI: EdgeBuilder | C51: Non-target state | F51: Non-strategic service boarding merchants to the Edge gateway and linking Salesforce data; already in maintenance mode | G51: =IF(OR($B51="",$D51="",$E51=""),"",IF(OR($C51="Target state",$C51="Exception"),"Out of scope",IF($D51="Low","No tranche",IF($E51="Low","Tranche 1",IF($E51="Medium","Tranche 2",IF($D51="High","Tranche 3","No tranche")))))) | O51: =IF(AND($B51<>"",$C51<>"Target state",$C51<>"Exception",$D51="High",$E51="Low"),$A51&" "&$B51,"") | P51: =IF(AND($B51<>"",$C51<>"Target state",$C51<>"Exception",$D51="High",$E51="Medium"),$A51&" "&$B51,"") | Q51: =IF(AND($B51<>"",$C51<>"Target state",$C51<>"Exception",$D51="High",$E51="High"),$A51&" "&$B51,"") | R51: =IF(AND($B51<>"",$C51<>"Target state",$C51<>"Exception",$D51="Medium",$E51="Low"),$A51&" "&$B51,"") | S51: =IF(AND($B51<>"",$C51<>"Target state",$C51<>"Exception",$D51="Medium",$E51="Medium"),$A51&" "&$B51,"") | T51: =IF(AND($B51<>"",$C51<>"Target state",$C51<>"Exception",$D51="Medium",$E51="High"),$A51&" "&$B51,"") | U51: =IF(AND($B51<>"",$C51<>"Target state",$C51<>"Exception",$D51="Low",$E51="Low"),$A51&" "&$B51,"") | V51: =IF(AND($B51<>"",$C51<>"Target state",$C51<>"Exception",$D51="Low",$E51="Medium"),$A51&" "&$B51,"") | W51: =IF(AND($B51<>"",$C51<>"Target state",$C51<>"Exception",$D51="Low",$E51="High"),$A51&" "&$B51,"")
A52: ⑦ | G52: =IF(OR($B52="",$D52="",$E52=""),"",IF(OR($C52="Target state",$C52="Exception"),"Out of scope",IF($D52="Low","No tranche",IF($E52="Low","Tranche 1",IF($E52="Medium","Tranche 2",IF($D52="High","Tranche 3","No tranche")))))) | O52: =IF(AND($B52<>"",$C52<>"Target state",$C52<>"Exception",$D52="High",$E52="Low"),$A52&" "&$B52,"") | P52: =IF(AND($B52<>"",$C52<>"Target state",$C52<>"Exception",$D52="High",$E52="Medium"),$A52&" "&$B52,"") | Q52: =IF(AND($B52<>"",$C52<>"Target state",$C52<>"Exception",$D52="High",$E52="High"),$A52&" "&$B52,"") | R52: =IF(AND($B52<>"",$C52<>"Target state",$C52<>"Exception",$D52="Medium",$E52="Low"),$A52&" "&$B52,"") | S52: =IF(AND($B52<>"",$C52<>"Target state",$C52<>"Exception",$D52="Medium",$E52="Medium"),$A52&" "&$B52,"") | T52: =IF(AND($B52<>"",$C52<>"Target state",$C52<>"Exception",$D52="Medium",$E52="High"),$A52&" "&$B52,"") | U52: =IF(AND($B52<>"",$C52<>"Target state",$C52<>"Exception",$D52="Low",$E52="Low"),$A52&" "&$B52,"") | V52: =IF(AND($B52<>"",$C52<>"Target state",$C52<>"Exception",$D52="Low",$E52="Medium"),$A52&" "&$B52,"") | W52: =IF(AND($B52<>"",$C52<>"Target state",$C52<>"Exception",$D52="Low",$E52="High"),$A52&" "&$B52,"")
A53: ⑧ | G53: =IF(OR($B53="",$D53="",$E53=""),"",IF(OR($C53="Target state",$C53="Exception"),"Out of scope",IF($D53="Low","No tranche",IF($E53="Low","Tranche 1",IF($E53="Medium","Tranche 2",IF($D53="High","Tranche 3","No tranche")))))) | J53: Low | K53: =_xlfn.TEXTJOIN(CHAR(10),TRUE,U$46:U$55) | L53: =_xlfn.TEXTJOIN(CHAR(10),TRUE,V$46:V$55) | M53: =_xlfn.TEXTJOIN(CHAR(10),TRUE,W$46:W$55) | O53: =IF(AND($B53<>"",$C53<>"Target state",$C53<>"Exception",$D53="High",$E53="Low"),$A53&" "&$B53,"") | P53: =IF(AND($B53<>"",$C53<>"Target state",$C53<>"Exception",$D53="High",$E53="Medium"),$A53&" "&$B53,"") | Q53: =IF(AND($B53<>"",$C53<>"Target state",$C53<>"Exception",$D53="High",$E53="High"),$A53&" "&$B53,"") | R53: =IF(AND($B53<>"",$C53<>"Target state",$C53<>"Exception",$D53="Medium",$E53="Low"),$A53&" "&$B53,"") | S53: =IF(AND($B53<>"",$C53<>"Target state",$C53<>"Exception",$D53="Medium",$E53="Medium"),$A53&" "&$B53,"") | T53: =IF(AND($B53<>"",$C53<>"Target state",$C53<>"Exception",$D53="Medium",$E53="High"),$A53&" "&$B53,"") | U53: =IF(AND($B53<>"",$C53<>"Target state",$C53<>"Exception",$D53="Low",$E53="Low"),$A53&" "&$B53,"") | V53: =IF(AND($B53<>"",$C53<>"Target state",$C53<>"Exception",$D53="Low",$E53="Medium"),$A53&" "&$B53,"") | W53: =IF(AND($B53<>"",$C53<>"Target state",$C53<>"Exception",$D53="Low",$E53="High"),$A53&" "&$B53,"")
A54: ⑨ | G54: =IF(OR($B54="",$D54="",$E54=""),"",IF(OR($C54="Target state",$C54="Exception"),"Out of scope",IF($D54="Low","No tranche",IF($E54="Low","Tranche 1",IF($E54="Medium","Tranche 2",IF($D54="High","Tranche 3","No tranche")))))) | O54: =IF(AND($B54<>"",$C54<>"Target state",$C54<>"Exception",$D54="High",$E54="Low"),$A54&" "&$B54,"") | P54: =IF(AND($B54<>"",$C54<>"Target state",$C54<>"Exception",$D54="High",$E54="Medium"),$A54&" "&$B54,"") | Q54: =IF(AND($B54<>"",$C54<>"Target state",$C54<>"Exception",$D54="High",$E54="High"),$A54&" "&$B54,"") | R54: =IF(AND($B54<>"",$C54<>"Target state",$C54<>"Exception",$D54="Medium",$E54="Low"),$A54&" "&$B54,"") | S54: =IF(AND($B54<>"",$C54<>"Target state",$C54<>"Exception",$D54="Medium",$E54="Medium"),$A54&" "&$B54,"") | T54: =IF(AND($B54<>"",$C54<>"Target state",$C54<>"Exception",$D54="Medium",$E54="High"),$A54&" "&$B54,"") | U54: =IF(AND($B54<>"",$C54<>"Target state",$C54<>"Exception",$D54="Low",$E54="Low"),$A54&" "&$B54,"") | V54: =IF(AND($B54<>"",$C54<>"Target state",$C54<>"Exception",$D54="Low",$E54="Medium"),$A54&" "&$B54,"") | W54: =IF(AND($B54<>"",$C54<>"Target state",$C54<>"Exception",$D54="Low",$E54="High"),$A54&" "&$B54,"")
A55: ⑩ | G55: =IF(OR($B55="",$D55="",$E55=""),"",IF(OR($C55="Target state",$C55="Exception"),"Out of scope",IF($D55="Low","No tranche",IF($E55="Low","Tranche 1",IF($E55="Medium","Tranche 2",IF($D55="High","Tranche 3","No tranche")))))) | O55: =IF(AND($B55<>"",$C55<>"Target state",$C55<>"Exception",$D55="High",$E55="Low"),$A55&" "&$B55,"") | P55: =IF(AND($B55<>"",$C55<>"Target state",$C55<>"Exception",$D55="High",$E55="Medium"),$A55&" "&$B55,"") | Q55: =IF(AND($B55<>"",$C55<>"Target state",$C55<>"Exception",$D55="High",$E55="High"),$A55&" "&$B55,"") | R55: =IF(AND($B55<>"",$C55<>"Target state",$C55<>"Exception",$D55="Medium",$E55="Low"),$A55&" "&$B55,"") | S55: =IF(AND($B55<>"",$C55<>"Target state",$C55<>"Exception",$D55="Medium",$E55="Medium"),$A55&" "&$B55,"") | T55: =IF(AND($B55<>"",$C55<>"Target state",$C55<>"Exception",$D55="Medium",$E55="High"),$A55&" "&$B55,"") | U55: =IF(AND($B55<>"",$C55<>"Target state",$C55<>"Exception",$D55="Low",$E55="Low"),$A55&" "&$B55,"") | V55: =IF(AND($B55<>"",$C55<>"Target state",$C55<>"Exception",$D55="Low",$E55="Medium"),$A55&" "&$B55,"") | W55: =IF(AND($B55<>"",$C55<>"Target state",$C55<>"Exception",$D55="Low",$E55="High"),$A55&" "&$B55,"")
K56: Complexity
A60: Boarding Orchestration | G60: =HYPERLINK("#'Boarding'!A4","▲ tracker") | K60: Assessment Outcome
A61: # | B61: Platform | C61: State | D61: Imperative to exit | E61: Exit complexity | F61: Supporting facts | G61: Tranche (auto) | K61: Low | L61: Medium | M61: High
A62: ① | B62: Onboard | C62: Non-target state | F62: Non-strategic boarding system for the EVO frontend boarding into A360 and GSAP with Discover MAP and Amex Opt Blue enrollments; about $150K in yearly cost; on the decommission path | G62: =IF(OR($B62="",$D62="",$E62=""),"",IF(OR($C62="Target state",$C62="Exception"),"Out of scope",IF($D62="Low","No tranche",IF($E62="Low","Tranche 1",IF($E62="Medium","Tranche 2",IF($D62="High","Tranche 3","No tranche")))))) | I62: Benefits | J62: High | K62: ="Tranche 1"&CHAR(10)&_xlfn.TEXTJOIN(CHAR(10),TRUE,O$62:O$73) | L62: ="Tranche 2"&CHAR(10)&_xlfn.TEXTJOIN(CHAR(10),TRUE,P$62:P$73) | M62: ="Tranche 3"&CHAR(10)&_xlfn.TEXTJOIN(CHAR(10),TRUE,Q$62:Q$73) | O62: =IF(AND($B62<>"",$C62<>"Target state",$C62<>"Exception",$D62="High",$E62="Low"),$A62&" "&$B62,"") | P62: =IF(AND($B62<>"",$C62<>"Target state",$C62<>"Exception",$D62="High",$E62="Medium"),$A62&" "&$B62,"") | Q62: =IF(AND($B62<>"",$C62<>"Target state",$C62<>"Exception",$D62="High",$E62="High"),$A62&" "&$B62,"") | R62: =IF(AND($B62<>"",$C62<>"Target state",$C62<>"Exception",$D62="Medium",$E62="Low"),$A62&" "&$B62,"") | S62: =IF(AND($B62<>"",$C62<>"Target state",$C62<>"Exception",$D62="Medium",$E62="Medium"),$A62&" "&$B62,"") | T62: =IF(AND($B62<>"",$C62<>"Target state",$C62<>"Exception",$D62="Medium",$E62="High"),$A62&" "&$B62,"") | U62: =IF(AND($B62<>"",$C62<>"Target state",$C62<>"Exception",$D62="Low",$E62="Low"),$A62&" "&$B62,"") | V62: =IF(AND($B62<>"",$C62<>"Target state",$C62<>"Exception",$D62="Low",$E62="Medium"),$A62&" "&$B62,"") | W62: =IF(AND($B62<>"",$C62<>"Target state",$C62<>"Exception",$D62="Low",$E62="High"),$A62&" "&$B62,"")
A63: ② | B63: Merchant Enrollment Advantage (MEA) | C63: Non-target state | F63: Non-strategic GP US boarding application orchestrating boarding across host systems for about 113K merchants; around $260K in yearly cost | G63: =IF(OR($B63="",$D63="",$E63=""),"",IF(OR($C63="Target state",$C63="Exception"),"Out of scope",IF($D63="Low","No tranche",IF($E63="Low","Tranche 1",IF($E63="Medium","Tranche 2",IF($D63="High","Tranche 3","No tranche")))))) | O63: =IF(AND($B63<>"",$C63<>"Target state",$C63<>"Exception",$D63="High",$E63="Low"),$A63&" "&$B63,"") | P63: =IF(AND($B63<>"",$C63<>"Target state",$C63<>"Exception",$D63="High",$E63="Medium"),$A63&" "&$B63,"") | Q63: =IF(AND($B63<>"",$C63<>"Target state",$C63<>"Exception",$D63="High",$E63="High"),$A63&" "&$B63,"") | R63: =IF(AND($B63<>"",$C63<>"Target state",$C63<>"Exception",$D63="Medium",$E63="Low"),$A63&" "&$B63,"") | S63: =IF(AND($B63<>"",$C63<>"Target state",$C63<>"Exception",$D63="Medium",$E63="Medium"),$A63&" "&$B63,"") | T63: =IF(AND($B63<>"",$C63<>"Target state",$C63<>"Exception",$D63="Medium",$E63="High"),$A63&" "&$B63,"") | U63: =IF(AND($B63<>"",$C63<>"Target state",$C63<>"Exception",$D63="Low",$E63="Low"),$A63&" "&$B63,"") | V63: =IF(AND($B63<>"",$C63<>"Target state",$C63<>"Exception",$D63="Low",$E63="Medium"),$A63&" "&$B63,"") | W63: =IF(AND($B63<>"",$C63<>"Target state",$C63<>"Exception",$D63="Low",$E63="High"),$A63&" "&$B63,"")
A64: ③ | B64: MMS | C64: Non-target state | F64: Non-strategic legacy front-end loader pushing bank and merchant information into TSYS systems across 3.9M merchants; about $490K in yearly cost; profiles still required in TMAS for full-service clients | G64: =IF(OR($B64="",$D64="",$E64=""),"",IF(OR($C64="Target state",$C64="Exception"),"Out of scope",IF($D64="Low","No tranche",IF($E64="Low","Tranche 1",IF($E64="Medium","Tranche 2",IF($D64="High","Tranche 3","No tranche")))))) | O64: =IF(AND($B64<>"",$C64<>"Target state",$C64<>"Exception",$D64="High",$E64="Low"),$A64&" "&$B64,"") | P64: =IF(AND($B64<>"",$C64<>"Target state",$C64<>"Exception",$D64="High",$E64="Medium"),$A64&" "&$B64,"") | Q64: =IF(AND($B64<>"",$C64<>"Target state",$C64<>"Exception",$D64="High",$E64="High"),$A64&" "&$B64,"") | R64: =IF(AND($B64<>"",$C64<>"Target state",$C64<>"Exception",$D64="Medium",$E64="Low"),$A64&" "&$B64,"") | S64: =IF(AND($B64<>"",$C64<>"Target state",$C64<>"Exception",$D64="Medium",$E64="Medium"),$A64&" "&$B64,"") | T64: =IF(AND($B64<>"",$C64<>"Target state",$C64<>"Exception",$D64="Medium",$E64="High"),$A64&" "&$B64,"") | U64: =IF(AND($B64<>"",$C64<>"Target state",$C64<>"Exception",$D64="Low",$E64="Low"),$A64&" "&$B64,"") | V64: =IF(AND($B64<>"",$C64<>"Target state",$C64<>"Exception",$D64="Low",$E64="Medium"),$A64&" "&$B64,"") | W64: =IF(AND($B64<>"",$C64<>"Target state",$C64<>"Exception",$D64="Low",$E64="High"),$A64&" "&$B64,"")
A65: ④ | B65: Discover Enrollment System (DES) | C65: Non-target state | F65: Non-strategic GP application enrolling merchants with Discover across US and Canada portfolios | G65: =IF(OR($B65="",$D65="",$E65=""),"",IF(OR($C65="Target state",$C65="Exception"),"Out of scope",IF($D65="Low","No tranche",IF($E65="Low","Tranche 1",IF($E65="Medium","Tranche 2",IF($D65="High","Tranche 3","No tranche")))))) | O65: =IF(AND($B65<>"",$C65<>"Target state",$C65<>"Exception",$D65="High",$E65="Low"),$A65&" "&$B65,"") | P65: =IF(AND($B65<>"",$C65<>"Target state",$C65<>"Exception",$D65="High",$E65="Medium"),$A65&" "&$B65,"") | Q65: =IF(AND($B65<>"",$C65<>"Target state",$C65<>"Exception",$D65="High",$E65="High"),$A65&" "&$B65,"") | R65: =IF(AND($B65<>"",$C65<>"Target state",$C65<>"Exception",$D65="Medium",$E65="Low"),$A65&" "&$B65,"") | S65: =IF(AND($B65<>"",$C65<>"Target state",$C65<>"Exception",$D65="Medium",$E65="Medium"),$A65&" "&$B65,"") | T65: =IF(AND($B65<>"",$C65<>"Target state",$C65<>"Exception",$D65="Medium",$E65="High"),$A65&" "&$B65,"") | U65: =IF(AND($B65<>"",$C65<>"Target state",$C65<>"Exception",$D65="Low",$E65="Low"),$A65&" "&$B65,"") | V65: =IF(AND($B65<>"",$C65<>"Target state",$C65<>"Exception",$D65="Low",$E65="Medium"),$A65&" "&$B65,"") | W65: =IF(AND($B65<>"",$C65<>"Target state",$C65<>"Exception",$D65="Low",$E65="High"),$A65&" "&$B65,"")
A66: ⑤ | B66: Genesis | C66: Non-target state | F66: Non-strategic boarding system for NWS and VAPS merchants outside Client Manager with about 90 users; around $330K in yearly cost; repository flags Keep & Enhance with selective migration — confirm with SPOC | G66: =IF(OR($B66="",$D66="",$E66=""),"",IF(OR($C66="Target state",$C66="Exception"),"Out of scope",IF($D66="Low","No tranche",IF($E66="Low","Tranche 1",IF($E66="Medium","Tranche 2",IF($D66="High","Tranche 3","No tranche")))))) | J66: Medium | K66: ="Tranche 1"&CHAR(10)&_xlfn.TEXTJOIN(CHAR(10),TRUE,R$62:R$73) | L66: ="Tranche 2"&CHAR(10)&_xlfn.TEXTJOIN(CHAR(10),TRUE,S$62:S$73) | M66: =_xlfn.TEXTJOIN(CHAR(10),TRUE,T$62:T$73) | O66: =IF(AND($B66<>"",$C66<>"Target state",$C66<>"Exception",$D66="High",$E66="Low"),$A66&" "&$B66,"") | P66: =IF(AND($B66<>"",$C66<>"Target state",$C66<>"Exception",$D66="High",$E66="Medium"),$A66&" "&$B66,"") | Q66: =IF(AND($B66<>"",$C66<>"Target state",$C66<>"Exception",$D66="High",$E66="High"),$A66&" "&$B66,"") | R66: =IF(AND($B66<>"",$C66<>"Target state",$C66<>"Exception",$D66="Medium",$E66="Low"),$A66&" "&$B66,"") | S66: =IF(AND($B66<>"",$C66<>"Target state",$C66<>"Exception",$D66="Medium",$E66="Medium"),$A66&" "&$B66,"") | T66: =IF(AND($B66<>"",$C66<>"Target state",$C66<>"Exception",$D66="Medium",$E66="High"),$A66&" "&$B66,"") | U66: =IF(AND($B66<>"",$C66<>"Target state",$C66<>"Exception",$D66="Low",$E66="Low"),$A66&" "&$B66,"") | V66: =IF(AND($B66<>"",$C66<>"Target state",$C66<>"Exception",$D66="Low",$E66="Medium"),$A66&" "&$B66,"") | W66: =IF(AND($B66<>"",$C66<>"Target state",$C66<>"Exception",$D66="Low",$E66="High"),$A66&" "&$B66,"")
A67: ⑥ | B67: Client Manager | C67: Non-target state | F67: Boarding system for Passport backend merchants with about 1.3K users; repository flags Keep & Enhance with selective migration — confirm whether this row should be Target state | G67: =IF(OR($B67="",$D67="",$E67=""),"",IF(OR($C67="Target state",$C67="Exception"),"Out of scope",IF($D67="Low","No tranche",IF($E67="Low","Tranche 1",IF($E67="Medium","Tranche 2",IF($D67="High","Tranche 3","No tranche")))))) | O67: =IF(AND($B67<>"",$C67<>"Target state",$C67<>"Exception",$D67="High",$E67="Low"),$A67&" "&$B67,"") | P67: =IF(AND($B67<>"",$C67<>"Target state",$C67<>"Exception",$D67="High",$E67="Medium"),$A67&" "&$B67,"") | Q67: =IF(AND($B67<>"",$C67<>"Target state",$C67<>"Exception",$D67="High",$E67="High"),$A67&" "&$B67,"") | R67: =IF(AND($B67<>"",$C67<>"Target state",$C67<>"Exception",$D67="Medium",$E67="Low"),$A67&" "&$B67,"") | S67: =IF(AND($B67<>"",$C67<>"Target state",$C67<>"Exception",$D67="Medium",$E67="Medium"),$A67&" "&$B67,"") | T67: =IF(AND($B67<>"",$C67<>"Target state",$C67<>"Exception",$D67="Medium",$E67="High"),$A67&" "&$B67,"") | U67: =IF(AND($B67<>"",$C67<>"Target state",$C67<>"Exception",$D67="Low",$E67="Low"),$A67&" "&$B67,"") | V67: =IF(AND($B67<>"",$C67<>"Target state",$C67<>"Exception",$D67="Low",$E67="Medium"),$A67&" "&$B67,"") | W67: =IF(AND($B67<>"",$C67<>"Target state",$C67<>"Exception",$D67="Low",$E67="High"),$A67&" "&$B67,"")
A68: ⑦ | B68: SEAT | C68: Non-target state | F68: Non-strategic sales entity and application workflow configuration tool with about 150 users; around $150K in yearly cost; repository flags Further Input — confirm with SPOC | G68: =IF(OR($B68="",$D68="",$E68=""),"",IF(OR($C68="Target state",$C68="Exception"),"Out of scope",IF($D68="Low","No tranche",IF($E68="Low","Tranche 1",IF($E68="Medium","Tranche 2",IF($D68="High","Tranche 3","No tranche")))))) | O68: =IF(AND($B68<>"",$C68<>"Target state",$C68<>"Exception",$D68="High",$E68="Low"),$A68&" "&$B68,"") | P68: =IF(AND($B68<>"",$C68<>"Target state",$C68<>"Exception",$D68="High",$E68="Medium"),$A68&" "&$B68,"") | Q68: =IF(AND($B68<>"",$C68<>"Target state",$C68<>"Exception",$D68="High",$E68="High"),$A68&" "&$B68,"") | R68: =IF(AND($B68<>"",$C68<>"Target state",$C68<>"Exception",$D68="Medium",$E68="Low"),$A68&" "&$B68,"") | S68: =IF(AND($B68<>"",$C68<>"Target state",$C68<>"Exception",$D68="Medium",$E68="Medium"),$A68&" "&$B68,"") | T68: =IF(AND($B68<>"",$C68<>"Target state",$C68<>"Exception",$D68="Medium",$E68="High"),$A68&" "&$B68,"") | U68: =IF(AND($B68<>"",$C68<>"Target state",$C68<>"Exception",$D68="Low",$E68="Low"),$A68&" "&$B68,"") | V68: =IF(AND($B68<>"",$C68<>"Target state",$C68<>"Exception",$D68="Low",$E68="Medium"),$A68&" "&$B68,"") | W68: =IF(AND($B68<>"",$C68<>"Target state",$C68<>"Exception",$D68="Low",$E68="High"),$A68&" "&$B68,"")
A69: ⑧ | B69: Flex (EVO boarding) | C69: Non-target state | F69: Non-strategic EVO boarding of demographics, plans and fees with equipment ordering and deployment ticketing; about $150K in yearly cost; on the decommission path. Distinct from the Canadian FLEX terminal application parked separately | G69: =IF(OR($B69="",$D69="",$E69=""),"",IF(OR($C69="Target state",$C69="Exception"),"Out of scope",IF($D69="Low","No tranche",IF($E69="Low","Tranche 1",IF($E69="Medium","Tranche 2",IF($D69="High","Tranche 3","No tranche")))))) | O69: =IF(AND($B69<>"",$C69<>"Target state",$C69<>"Exception",$D69="High",$E69="Low"),$A69&" "&$B69,"") | P69: =IF(AND($B69<>"",$C69<>"Target state",$C69<>"Exception",$D69="High",$E69="Medium"),$A69&" "&$B69,"") | Q69: =IF(AND($B69<>"",$C69<>"Target state",$C69<>"Exception",$D69="High",$E69="High"),$A69&" "&$B69,"") | R69: =IF(AND($B69<>"",$C69<>"Target state",$C69<>"Exception",$D69="Medium",$E69="Low"),$A69&" "&$B69,"") | S69: =IF(AND($B69<>"",$C69<>"Target state",$C69<>"Exception",$D69="Medium",$E69="Medium"),$A69&" "&$B69,"") | T69: =IF(AND($B69<>"",$C69<>"Target state",$C69<>"Exception",$D69="Medium",$E69="High"),$A69&" "&$B69,"") | U69: =IF(AND($B69<>"",$C69<>"Target state",$C69<>"Exception",$D69="Low",$E69="Low"),$A69&" "&$B69,"") | V69: =IF(AND($B69<>"",$C69<>"Target state",$C69<>"Exception",$D69="Low",$E69="Medium"),$A69&" "&$B69,"") | W69: =IF(AND($B69<>"",$C69<>"Target state",$C69<>"Exception",$D69="Low",$E69="High"),$A69&" "&$B69,"")
A70: ⑨ | G70: =IF(OR($B70="",$D70="",$E70=""),"",IF(OR($C70="Target state",$C70="Exception"),"Out of scope",IF($D70="Low","No tranche",IF($E70="Low","Tranche 1",IF($E70="Medium","Tranche 2",IF($D70="High","Tranche 3","No tranche")))))) | J70: Low | K70: =_xlfn.TEXTJOIN(CHAR(10),TRUE,U$62:U$73) | L70: =_xlfn.TEXTJOIN(CHAR(10),TRUE,V$62:V$73) | M70: =_xlfn.TEXTJOIN(CHAR(10),TRUE,W$62:W$73) | O70: =IF(AND($B70<>"",$C70<>"Target state",$C70<>"Exception",$D70="High",$E70="Low"),$A70&" "&$B70,"") | P70: =IF(AND($B70<>"",$C70<>"Target state",$C70<>"Exception",$D70="High",$E70="Medium"),$A70&" "&$B70,"") | Q70: =IF(AND($B70<>"",$C70<>"Target state",$C70<>"Exception",$D70="High",$E70="High"),$A70&" "&$B70,"") | R70: =IF(AND($B70<>"",$C70<>"Target state",$C70<>"Exception",$D70="Medium",$E70="Low"),$A70&" "&$B70,"") | S70: =IF(AND($B70<>"",$C70<>"Target state",$C70<>"Exception",$D70="Medium",$E70="Medium"),$A70&" "&$B70,"") | T70: =IF(AND($B70<>"",$C70<>"Target state",$C70<>"Exception",$D70="Medium",$E70="High"),$A70&" "&$B70,"") | U70: =IF(AND($B70<>"",$C70<>"Target state",$C70<>"Exception",$D70="Low",$E70="Low"),$A70&" "&$B70,"") | V70: =IF(AND($B70<>"",$C70<>"Target state",$C70<>"Exception",$D70="Low",$E70="Medium"),$A70&" "&$B70,"") | W70: =IF(AND($B70<>"",$C70<>"Target state",$C70<>"Exception",$D70="Low",$E70="High"),$A70&" "&$B70,"")
A71: ⑩ | G71: =IF(OR($B71="",$D71="",$E71=""),"",IF(OR($C71="Target state",$C71="Exception"),"Out of scope",IF($D71="Low","No tranche",IF($E71="Low","Tranche 1",IF($E71="Medium","Tranche 2",IF($D71="High","Tranche 3","No tranche")))))) | O71: =IF(AND($B71<>"",$C71<>"Target state",$C71<>"Exception",$D71="High",$E71="Low"),$A71&" "&$B71,"") | P71: =IF(AND($B71<>"",$C71<>"Target state",$C71<>"Exception",$D71="High",$E71="Medium"),$A71&" "&$B71,"") | Q71: =IF(AND($B71<>"",$C71<>"Target state",$C71<>"Exception",$D71="High",$E71="High"),$A71&" "&$B71,"") | R71: =IF(AND($B71<>"",$C71<>"Target state",$C71<>"Exception",$D71="Medium",$E71="Low"),$A71&" "&$B71,"") | S71: =IF(AND($B71<>"",$C71<>"Target state",$C71<>"Exception",$D71="Medium",$E71="Medium"),$A71&" "&$B71,"") | T71: =IF(AND($B71<>"",$C71<>"Target state",$C71<>"Exception",$D71="Medium",$E71="High"),$A71&" "&$B71,"") | U71: =IF(AND($B71<>"",$C71<>"Target state",$C71<>"Exception",$D71="Low",$E71="Low"),$A71&" "&$B71,"") | V71: =IF(AND($B71<>"",$C71<>"Target state",$C71<>"Exception",$D71="Low",$E71="Medium"),$A71&" "&$B71,"") | W71: =IF(AND($B71<>"",$C71<>"Target state",$C71<>"Exception",$D71="Low",$E71="High"),$A71&" "&$B71,"")
A72: ⑪ | G72: =IF(OR($B72="",$D72="",$E72=""),"",IF(OR($C72="Target state",$C72="Exception"),"Out of scope",IF($D72="Low","No tranche",IF($E72="Low","Tranche 1",IF($E72="Medium","Tranche 2",IF($D72="High","Tranche 3","No tranche")))))) | O72: =IF(AND($B72<>"",$C72<>"Target state",$C72<>"Exception",$D72="High",$E72="Low"),$A72&" "&$B72,"") | P72: =IF(AND($B72<>"",$C72<>"Target state",$C72<>"Exception",$D72="High",$E72="Medium"),$A72&" "&$B72,"") | Q72: =IF(AND($B72<>"",$C72<>"Target state",$C72<>"Exception",$D72="High",$E72="High"),$A72&" "&$B72,"") | R72: =IF(AND($B72<>"",$C72<>"Target state",$C72<>"Exception",$D72="Medium",$E72="Low"),$A72&" "&$B72,"") | S72: =IF(AND($B72<>"",$C72<>"Target state",$C72<>"Exception",$D72="Medium",$E72="Medium"),$A72&" "&$B72,"") | T72: =IF(AND($B72<>"",$C72<>"Target state",$C72<>"Exception",$D72="Medium",$E72="High"),$A72&" "&$B72,"") | U72: =IF(AND($B72<>"",$C72<>"Target state",$C72<>"Exception",$D72="Low",$E72="Low"),$A72&" "&$B72,"") | V72: =IF(AND($B72<>"",$C72<>"Target state",$C72<>"Exception",$D72="Low",$E72="Medium"),$A72&" "&$B72,"") | W72: =IF(AND($B72<>"",$C72<>"Target state",$C72<>"Exception",$D72="Low",$E72="High"),$A72&" "&$B72,"")
A73: ⑫ | G73: =IF(OR($B73="",$D73="",$E73=""),"",IF(OR($C73="Target state",$C73="Exception"),"Out of scope",IF($D73="Low","No tranche",IF($E73="Low","Tranche 1",IF($E73="Medium","Tranche 2",IF($D73="High","Tranche 3","No tranche")))))) | O73: =IF(AND($B73<>"",$C73<>"Target state",$C73<>"Exception",$D73="High",$E73="Low"),$A73&" "&$B73,"") | P73: =IF(AND($B73<>"",$C73<>"Target state",$C73<>"Exception",$D73="High",$E73="Medium"),$A73&" "&$B73,"") | Q73: =IF(AND($B73<>"",$C73<>"Target state",$C73<>"Exception",$D73="High",$E73="High"),$A73&" "&$B73,"") | R73: =IF(AND($B73<>"",$C73<>"Target state",$C73<>"Exception",$D73="Medium",$E73="Low"),$A73&" "&$B73,"") | S73: =IF(AND($B73<>"",$C73<>"Target state",$C73<>"Exception",$D73="Medium",$E73="Medium"),$A73&" "&$B73,"") | T73: =IF(AND($B73<>"",$C73<>"Target state",$C73<>"Exception",$D73="Medium",$E73="High"),$A73&" "&$B73,"") | U73: =IF(AND($B73<>"",$C73<>"Target state",$C73<>"Exception",$D73="Low",$E73="Low"),$A73&" "&$B73,"") | V73: =IF(AND($B73<>"",$C73<>"Target state",$C73<>"Exception",$D73="Low",$E73="Medium"),$A73&" "&$B73,"") | W73: =IF(AND($B73<>"",$C73<>"Target state",$C73<>"Exception",$D73="Low",$E73="High"),$A73&" "&$B73,"")
K74: Complexity
A78: Integration & Messaging | G78: =HYPERLINK("#'Boarding'!A4","▲ tracker") | K78: Assessment Outcome
A79: # | B79: Platform | C79: State | D79: Imperative to exit | E79: Exit complexity | F79: Supporting facts | G79: Tranche (auto) | K79: Low | L79: Medium | M79: High
A80: ① | B80: The Central API | C80: Non-target state | F80: Communications backbone for Heartland POS providing boarding automation, invoicing, monitoring and service activations; about $1.3M in yearly cost; sustain in KTLO per the repository | G80: =IF(OR($B80="",$D80="",$E80=""),"",IF(OR($C80="Target state",$C80="Exception"),"Out of scope",IF($D80="Low","No tranche",IF($E80="Low","Tranche 1",IF($E80="Medium","Tranche 2",IF($D80="High","Tranche 3","No tranche")))))) | I80: Benefits | J80: High | K80: ="Tranche 1"&CHAR(10)&_xlfn.TEXTJOIN(CHAR(10),TRUE,O$80:O$89) | L80: ="Tranche 2"&CHAR(10)&_xlfn.TEXTJOIN(CHAR(10),TRUE,P$80:P$89) | M80: ="Tranche 3"&CHAR(10)&_xlfn.TEXTJOIN(CHAR(10),TRUE,Q$80:Q$89) | O80: =IF(AND($B80<>"",$C80<>"Target state",$C80<>"Exception",$D80="High",$E80="Low"),$A80&" "&$B80,"") | P80: =IF(AND($B80<>"",$C80<>"Target state",$C80<>"Exception",$D80="High",$E80="Medium"),$A80&" "&$B80,"") | Q80: =IF(AND($B80<>"",$C80<>"Target state",$C80<>"Exception",$D80="High",$E80="High"),$A80&" "&$B80,"") | R80: =IF(AND($B80<>"",$C80<>"Target state",$C80<>"Exception",$D80="Medium",$E80="Low"),$A80&" "&$B80,"") | S80: =IF(AND($B80<>"",$C80<>"Target state",$C80<>"Exception",$D80="Medium",$E80="Medium"),$A80&" "&$B80,"") | T80: =IF(AND($B80<>"",$C80<>"Target state",$C80<>"Exception",$D80="Medium",$E80="High"),$A80&" "&$B80,"") | U80: =IF(AND($B80<>"",$C80<>"Target state",$C80<>"Exception",$D80="Low",$E80="Low"),$A80&" "&$B80,"") | V80: =IF(AND($B80<>"",$C80<>"Target state",$C80<>"Exception",$D80="Low",$E80="Medium"),$A80&" "&$B80,"") | W80: =IF(AND($B80<>"",$C80<>"Target state",$C80<>"Exception",$D80="Low",$E80="High"),$A80&" "&$B80,"")
A81: ② | G81: =IF(OR($B81="",$D81="",$E81=""),"",IF(OR($C81="Target state",$C81="Exception"),"Out of scope",IF($D81="Low","No tranche",IF($E81="Low","Tranche 1",IF($E81="Medium","Tranche 2",IF($D81="High","Tranche 3","No tranche")))))) | O81: =IF(AND($B81<>"",$C81<>"Target state",$C81<>"Exception",$D81="High",$E81="Low"),$A81&" "&$B81,"") | P81: =IF(AND($B81<>"",$C81<>"Target state",$C81<>"Exception",$D81="High",$E81="Medium"),$A81&" "&$B81,"") | Q81: =IF(AND($B81<>"",$C81<>"Target state",$C81<>"Exception",$D81="High",$E81="High"),$A81&" "&$B81,"") | R81: =IF(AND($B81<>"",$C81<>"Target state",$C81<>"Exception",$D81="Medium",$E81="Low"),$A81&" "&$B81,"") | S81: =IF(AND($B81<>"",$C81<>"Target state",$C81<>"Exception",$D81="Medium",$E81="Medium"),$A81&" "&$B81,"") | T81: =IF(AND($B81<>"",$C81<>"Target state",$C81<>"Exception",$D81="Medium",$E81="High"),$A81&" "&$B81,"") | U81: =IF(AND($B81<>"",$C81<>"Target state",$C81<>"Exception",$D81="Low",$E81="Low"),$A81&" "&$B81,"") | V81: =IF(AND($B81<>"",$C81<>"Target state",$C81<>"Exception",$D81="Low",$E81="Medium"),$A81&" "&$B81,"") | W81: =IF(AND($B81<>"",$C81<>"Target state",$C81<>"Exception",$D81="Low",$E81="High"),$A81&" "&$B81,"")
A82: ③ | G82: =IF(OR($B82="",$D82="",$E82=""),"",IF(OR($C82="Target state",$C82="Exception"),"Out of scope",IF($D82="Low","No tranche",IF($E82="Low","Tranche 1",IF($E82="Medium","Tranche 2",IF($D82="High","Tranche 3","No tranche")))))) | O82: =IF(AND($B82<>"",$C82<>"Target state",$C82<>"Exception",$D82="High",$E82="Low"),$A82&" "&$B82,"") | P82: =IF(AND($B82<>"",$C82<>"Target state",$C82<>"Exception",$D82="High",$E82="Medium"),$A82&" "&$B82,"") | Q82: =IF(AND($B82<>"",$C82<>"Target state",$C82<>"Exception",$D82="High",$E82="High"),$A82&" "&$B82,"") | R82: =IF(AND($B82<>"",$C82<>"Target state",$C82<>"Exception",$D82="Medium",$E82="Low"),$A82&" "&$B82,"") | S82: =IF(AND($B82<>"",$C82<>"Target state",$C82<>"Exception",$D82="Medium",$E82="Medium"),$A82&" "&$B82,"") | T82: =IF(AND($B82<>"",$C82<>"Target state",$C82<>"Exception",$D82="Medium",$E82="High"),$A82&" "&$B82,"") | U82: =IF(AND($B82<>"",$C82<>"Target state",$C82<>"Exception",$D82="Low",$E82="Low"),$A82&" "&$B82,"") | V82: =IF(AND($B82<>"",$C82<>"Target state",$C82<>"Exception",$D82="Low",$E82="Medium"),$A82&" "&$B82,"") | W82: =IF(AND($B82<>"",$C82<>"Target state",$C82<>"Exception",$D82="Low",$E82="High"),$A82&" "&$B82,"")
A83: ④ | G83: =IF(OR($B83="",$D83="",$E83=""),"",IF(OR($C83="Target state",$C83="Exception"),"Out of scope",IF($D83="Low","No tranche",IF($E83="Low","Tranche 1",IF($E83="Medium","Tranche 2",IF($D83="High","Tranche 3","No tranche")))))) | O83: =IF(AND($B83<>"",$C83<>"Target state",$C83<>"Exception",$D83="High",$E83="Low"),$A83&" "&$B83,"") | P83: =IF(AND($B83<>"",$C83<>"Target state",$C83<>"Exception",$D83="High",$E83="Medium"),$A83&" "&$B83,"") | Q83: =IF(AND($B83<>"",$C83<>"Target state",$C83<>"Exception",$D83="High",$E83="High"),$A83&" "&$B83,"") | R83: =IF(AND($B83<>"",$C83<>"Target state",$C83<>"Exception",$D83="Medium",$E83="Low"),$A83&" "&$B83,"") | S83: =IF(AND($B83<>"",$C83<>"Target state",$C83<>"Exception",$D83="Medium",$E83="Medium"),$A83&" "&$B83,"") | T83: =IF(AND($B83<>"",$C83<>"Target state",$C83<>"Exception",$D83="Medium",$E83="High"),$A83&" "&$B83,"") | U83: =IF(AND($B83<>"",$C83<>"Target state",$C83<>"Exception",$D83="Low",$E83="Low"),$A83&" "&$B83,"") | V83: =IF(AND($B83<>"",$C83<>"Target state",$C83<>"Exception",$D83="Low",$E83="Medium"),$A83&" "&$B83,"") | W83: =IF(AND($B83<>"",$C83<>"Target state",$C83<>"Exception",$D83="Low",$E83="High"),$A83&" "&$B83,"")
A84: ⑤ | G84: =IF(OR($B84="",$D84="",$E84=""),"",IF(OR($C84="Target state",$C84="Exception"),"Out of scope",IF($D84="Low","No tranche",IF($E84="Low","Tranche 1",IF($E84="Medium","Tranche 2",IF($D84="High","Tranche 3","No tranche")))))) | J84: Medium | K84: ="Tranche 1"&CHAR(10)&_xlfn.TEXTJOIN(CHAR(10),TRUE,R$80:R$89) | L84: ="Tranche 2"&CHAR(10)&_xlfn.TEXTJOIN(CHAR(10),TRUE,S$80:S$89) | M84: =_xlfn.TEXTJOIN(CHAR(10),TRUE,T$80:T$89) | O84: =IF(AND($B84<>"",$C84<>"Target state",$C84<>"Exception",$D84="High",$E84="Low"),$A84&" "&$B84,"") | P84: =IF(AND($B84<>"",$C84<>"Target state",$C84<>"Exception",$D84="High",$E84="Medium"),$A84&" "&$B84,"") | Q84: =IF(AND($B84<>"",$C84<>"Target state",$C84<>"Exception",$D84="High",$E84="High"),$A84&" "&$B84,"") | R84: =IF(AND($B84<>"",$C84<>"Target state",$C84<>"Exception",$D84="Medium",$E84="Low"),$A84&" "&$B84,"") | S84: =IF(AND($B84<>"",$C84<>"Target state",$C84<>"Exception",$D84="Medium",$E84="Medium"),$A84&" "&$B84,"") | T84: =IF(AND($B84<>"",$C84<>"Target state",$C84<>"Exception",$D84="Medium",$E84="High"),$A84&" "&$B84,"") | U84: =IF(AND($B84<>"",$C84<>"Target state",$C84<>"Exception",$D84="Low",$E84="Low"),$A84&" "&$B84,"") | V84: =IF(AND($B84<>"",$C84<>"Target state",$C84<>"Exception",$D84="Low",$E84="Medium"),$A84&" "&$B84,"") | W84: =IF(AND($B84<>"",$C84<>"Target state",$C84<>"Exception",$D84="Low",$E84="High"),$A84&" "&$B84,"")
A85: ⑥ | G85: =IF(OR($B85="",$D85="",$E85=""),"",IF(OR($C85="Target state",$C85="Exception"),"Out of scope",IF($D85="Low","No tranche",IF($E85="Low","Tranche 1",IF($E85="Medium","Tranche 2",IF($D85="High","Tranche 3","No tranche")))))) | O85: =IF(AND($B85<>"",$C85<>"Target state",$C85<>"Exception",$D85="High",$E85="Low"),$A85&" "&$B85,"") | P85: =IF(AND($B85<>"",$C85<>"Target state",$C85<>"Exception",$D85="High",$E85="Medium"),$A85&" "&$B85,"") | Q85: =IF(AND($B85<>"",$C85<>"Target state",$C85<>"Exception",$D85="High",$E85="High"),$A85&" "&$B85,"") | R85: =IF(AND($B85<>"",$C85<>"Target state",$C85<>"Exception",$D85="Medium",$E85="Low"),$A85&" "&$B85,"") | S85: =IF(AND($B85<>"",$C85<>"Target state",$C85<>"Exception",$D85="Medium",$E85="Medium"),$A85&" "&$B85,"") | T85: =IF(AND($B85<>"",$C85<>"Target state",$C85<>"Exception",$D85="Medium",$E85="High"),$A85&" "&$B85,"") | U85: =IF(AND($B85<>"",$C85<>"Target state",$C85<>"Exception",$D85="Low",$E85="Low"),$A85&" "&$B85,"") | V85: =IF(AND($B85<>"",$C85<>"Target state",$C85<>"Exception",$D85="Low",$E85="Medium"),$A85&" "&$B85,"") | W85: =IF(AND($B85<>"",$C85<>"Target state",$C85<>"Exception",$D85="Low",$E85="High"),$A85&" "&$B85,"")
A86: ⑦ | G86: =IF(OR($B86="",$D86="",$E86=""),"",IF(OR($C86="Target state",$C86="Exception"),"Out of scope",IF($D86="Low","No tranche",IF($E86="Low","Tranche 1",IF($E86="Medium","Tranche 2",IF($D86="High","Tranche 3","No tranche")))))) | O86: =IF(AND($B86<>"",$C86<>"Target state",$C86<>"Exception",$D86="High",$E86="Low"),$A86&" "&$B86,"") | P86: =IF(AND($B86<>"",$C86<>"Target state",$C86<>"Exception",$D86="High",$E86="Medium"),$A86&" "&$B86,"") | Q86: =IF(AND($B86<>"",$C86<>"Target state",$C86<>"Exception",$D86="High",$E86="High"),$A86&" "&$B86,"") | R86: =IF(AND($B86<>"",$C86<>"Target state",$C86<>"Exception",$D86="Medium",$E86="Low"),$A86&" "&$B86,"") | S86: =IF(AND($B86<>"",$C86<>"Target state",$C86<>"Exception",$D86="Medium",$E86="Medium"),$A86&" "&$B86,"") | T86: =IF(AND($B86<>"",$C86<>"Target state",$C86<>"Exception",$D86="Medium",$E86="High"),$A86&" "&$B86,"") | U86: =IF(AND($B86<>"",$C86<>"Target state",$C86<>"Exception",$D86="Low",$E86="Low"),$A86&" "&$B86,"") | V86: =IF(AND($B86<>"",$C86<>"Target state",$C86<>"Exception",$D86="Low",$E86="Medium"),$A86&" "&$B86,"") | W86: =IF(AND($B86<>"",$C86<>"Target state",$C86<>"Exception",$D86="Low",$E86="High"),$A86&" "&$B86,"")
A87: ⑧ | G87: =IF(OR($B87="",$D87="",$E87=""),"",IF(OR($C87="Target state",$C87="Exception"),"Out of scope",IF($D87="Low","No tranche",IF($E87="Low","Tranche 1",IF($E87="Medium","Tranche 2",IF($D87="High","Tranche 3","No tranche")))))) | J87: Low | K87: =_xlfn.TEXTJOIN(CHAR(10),TRUE,U$80:U$89) | L87: =_xlfn.TEXTJOIN(CHAR(10),TRUE,V$80:V$89) | M87: =_xlfn.TEXTJOIN(CHAR(10),TRUE,W$80:W$89) | O87: =IF(AND($B87<>"",$C87<>"Target state",$C87<>"Exception",$D87="High",$E87="Low"),$A87&" "&$B87,"") | P87: =IF(AND($B87<>"",$C87<>"Target state",$C87<>"Exception",$D87="High",$E87="Medium"),$A87&" "&$B87,"") | Q87: =IF(AND($B87<>"",$C87<>"Target state",$C87<>"Exception",$D87="High",$E87="High"),$A87&" "&$B87,"") | R87: =IF(AND($B87<>"",$C87<>"Target state",$C87<>"Exception",$D87="Medium",$E87="Low"),$A87&" "&$B87,"") | S87: =IF(AND($B87<>"",$C87<>"Target state",$C87<>"Exception",$D87="Medium",$E87="Medium"),$A87&" "&$B87,"") | T87: =IF(AND($B87<>"",$C87<>"Target state",$C87<>"Exception",$D87="Medium",$E87="High"),$A87&" "&$B87,"") | U87: =IF(AND($B87<>"",$C87<>"Target state",$C87<>"Exception",$D87="Low",$E87="Low"),$A87&" "&$B87,"") | V87: =IF(AND($B87<>"",$C87<>"Target state",$C87<>"Exception",$D87="Low",$E87="Medium"),$A87&" "&$B87,"") | W87: =IF(AND($B87<>"",$C87<>"Target state",$C87<>"Exception",$D87="Low",$E87="High"),$A87&" "&$B87,"")
A88: ⑨ | G88: =IF(OR($B88="",$D88="",$E88=""),"",IF(OR($C88="Target state",$C88="Exception"),"Out of scope",IF($D88="Low","No tranche",IF($E88="Low","Tranche 1",IF($E88="Medium","Tranche 2",IF($D88="High","Tranche 3","No tranche")))))) | O88: =IF(AND($B88<>"",$C88<>"Target state",$C88<>"Exception",$D88="High",$E88="Low"),$A88&" "&$B88,"") | P88: =IF(AND($B88<>"",$C88<>"Target state",$C88<>"Exception",$D88="High",$E88="Medium"),$A88&" "&$B88,"") | Q88: =IF(AND($B88<>"",$C88<>"Target state",$C88<>"Exception",$D88="High",$E88="High"),$A88&" "&$B88,"") | R88: =IF(AND($B88<>"",$C88<>"Target state",$C88<>"Exception",$D88="Medium",$E88="Low"),$A88&" "&$B88,"") | S88: =IF(AND($B88<>"",$C88<>"Target state",$C88<>"Exception",$D88="Medium",$E88="Medium"),$A88&" "&$B88,"") | T88: =IF(AND($B88<>"",$C88<>"Target state",$C88<>"Exception",$D88="Medium",$E88="High"),$A88&" "&$B88,"") | U88: =IF(AND($B88<>"",$C88<>"Target state",$C88<>"Exception",$D88="Low",$E88="Low"),$A88&" "&$B88,"") | V88: =IF(AND($B88<>"",$C88<>"Target state",$C88<>"Exception",$D88="Low",$E88="Medium"),$A88&" "&$B88,"") | W88: =IF(AND($B88<>"",$C88<>"Target state",$C88<>"Exception",$D88="Low",$E88="High"),$A88&" "&$B88,"")
A89: ⑩ | G89: =IF(OR($B89="",$D89="",$E89=""),"",IF(OR($C89="Target state",$C89="Exception"),"Out of scope",IF($D89="Low","No tranche",IF($E89="Low","Tranche 1",IF($E89="Medium","Tranche 2",IF($D89="High","Tranche 3","No tranche")))))) | O89: =IF(AND($B89<>"",$C89<>"Target state",$C89<>"Exception",$D89="High",$E89="Low"),$A89&" "&$B89,"") | P89: =IF(AND($B89<>"",$C89<>"Target state",$C89<>"Exception",$D89="High",$E89="Medium"),$A89&" "&$B89,"") | Q89: =IF(AND($B89<>"",$C89<>"Target state",$C89<>"Exception",$D89="High",$E89="High"),$A89&" "&$B89,"") | R89: =IF(AND($B89<>"",$C89<>"Target state",$C89<>"Exception",$D89="Medium",$E89="Low"),$A89&" "&$B89,"") | S89: =IF(AND($B89<>"",$C89<>"Target state",$C89<>"Exception",$D89="Medium",$E89="Medium"),$A89&" "&$B89,"") | T89: =IF(AND($B89<>"",$C89<>"Target state",$C89<>"Exception",$D89="Medium",$E89="High"),$A89&" "&$B89,"") | U89: =IF(AND($B89<>"",$C89<>"Target state",$C89<>"Exception",$D89="Low",$E89="Low"),$A89&" "&$B89,"") | V89: =IF(AND($B89<>"",$C89<>"Target state",$C89<>"Exception",$D89="Low",$E89="Medium"),$A89&" "&$B89,"") | W89: =IF(AND($B89<>"",$C89<>"Target state",$C89<>"Exception",$D89="Low",$E89="High"),$A89&" "&$B89,"")
K90: Complexity
A94: Credit & Underwriting | G94: =HYPERLINK("#'Boarding'!A4","▲ tracker") | K94: Assessment Outcome
A95: # | B95: Platform | C95: State | D95: Imperative to exit | E95: Exit complexity | F95: Supporting facts | G95: Tranche (auto) | K95: Low | L95: Medium | M95: High
A96: ① | B96: Underwriting Web | C96: Non-target state | F96: Non-strategic EVO tool for approving merchant applications with Mastercard MATCH and credit bureau checks; about $150K in yearly cost; repository flags Further Input — confirm with SPOC | G96: =IF(OR($B96="",$D96="",$E96=""),"",IF(OR($C96="Target state",$C96="Exception"),"Out of scope",IF($D96="Low","No tranche",IF($E96="Low","Tranche 1",IF($E96="Medium","Tranche 2",IF($D96="High","Tranche 3","No tranche")))))) | I96: Benefits | J96: High | K96: ="Tranche 1"&CHAR(10)&_xlfn.TEXTJOIN(CHAR(10),TRUE,O$96:O$105) | L96: ="Tranche 2"&CHAR(10)&_xlfn.TEXTJOIN(CHAR(10),TRUE,P$96:P$105) | M96: ="Tranche 3"&CHAR(10)&_xlfn.TEXTJOIN(CHAR(10),TRUE,Q$96:Q$105) | O96: =IF(AND($B96<>"",$C96<>"Target state",$C96<>"Exception",$D96="High",$E96="Low"),$A96&" "&$B96,"") | P96: =IF(AND($B96<>"",$C96<>"Target state",$C96<>"Exception",$D96="High",$E96="Medium"),$A96&" "&$B96,"") | Q96: =IF(AND($B96<>"",$C96<>"Target state",$C96<>"Exception",$D96="High",$E96="High"),$A96&" "&$B96,"") | R96: =IF(AND($B96<>"",$C96<>"Target state",$C96<>"Exception",$D96="Medium",$E96="Low"),$A96&" "&$B96,"") | S96: =IF(AND($B96<>"",$C96<>"Target state",$C96<>"Exception",$D96="Medium",$E96="Medium"),$A96&" "&$B96,"") | T96: =IF(AND($B96<>"",$C96<>"Target state",$C96<>"Exception",$D96="Medium",$E96="High"),$A96&" "&$B96,"") | U96: =IF(AND($B96<>"",$C96<>"Target state",$C96<>"Exception",$D96="Low",$E96="Low"),$A96&" "&$B96,"") | V96: =IF(AND($B96<>"",$C96<>"Target state",$C96<>"Exception",$D96="Low",$E96="Medium"),$A96&" "&$B96,"") | W96: =IF(AND($B96<>"",$C96<>"Target state",$C96<>"Exception",$D96="Low",$E96="High"),$A96&" "&$B96,"")
A97: ② | B97: Universal Underwriting | C97: Non-target state | F97: Non-strategic service generating Experian reports and validation rules for Instant Boarding and Client Manager across about 32K applications a year; modest annual cost | G97: =IF(OR($B97="",$D97="",$E97=""),"",IF(OR($C97="Target state",$C97="Exception"),"Out of scope",IF($D97="Low","No tranche",IF($E97="Low","Tranche 1",IF($E97="Medium","Tranche 2",IF($D97="High","Tranche 3","No tranche")))))) | O97: =IF(AND($B97<>"",$C97<>"Target state",$C97<>"Exception",$D97="High",$E97="Low"),$A97&" "&$B97,"") | P97: =IF(AND($B97<>"",$C97<>"Target state",$C97<>"Exception",$D97="High",$E97="Medium"),$A97&" "&$B97,"") | Q97: =IF(AND($B97<>"",$C97<>"Target state",$C97<>"Exception",$D97="High",$E97="High"),$A97&" "&$B97,"") | R97: =IF(AND($B97<>"",$C97<>"Target state",$C97<>"Exception",$D97="Medium",$E97="Low"),$A97&" "&$B97,"") | S97: =IF(AND($B97<>"",$C97<>"Target state",$C97<>"Exception",$D97="Medium",$E97="Medium"),$A97&" "&$B97,"") | T97: =IF(AND($B97<>"",$C97<>"Target state",$C97<>"Exception",$D97="Medium",$E97="High"),$A97&" "&$B97,"") | U97: =IF(AND($B97<>"",$C97<>"Target state",$C97<>"Exception",$D97="Low",$E97="Low"),$A97&" "&$B97,"") | V97: =IF(AND($B97<>"",$C97<>"Target state",$C97<>"Exception",$D97="Low",$E97="Medium"),$A97&" "&$B97,"") | W97: =IF(AND($B97<>"",$C97<>"Target state",$C97<>"Exception",$D97="Low",$E97="High"),$A97&" "&$B97,"")
A98: ③ | B98: Mercury USA | C98: Non-target state | F98: Non-strategic credit, boarding and underwriting tool being sunset with EVONowHost taking over through the simplification program; noted as hard to scale with a history of security issues | G98: =IF(OR($B98="",$D98="",$E98=""),"",IF(OR($C98="Target state",$C98="Exception"),"Out of scope",IF($D98="Low","No tranche",IF($E98="Low","Tranche 1",IF($E98="Medium","Tranche 2",IF($D98="High","Tranche 3","No tranche")))))) | O98: =IF(AND($B98<>"",$C98<>"Target state",$C98<>"Exception",$D98="High",$E98="Low"),$A98&" "&$B98,"") | P98: =IF(AND($B98<>"",$C98<>"Target state",$C98<>"Exception",$D98="High",$E98="Medium"),$A98&" "&$B98,"") | Q98: =IF(AND($B98<>"",$C98<>"Target state",$C98<>"Exception",$D98="High",$E98="High"),$A98&" "&$B98,"") | R98: =IF(AND($B98<>"",$C98<>"Target state",$C98<>"Exception",$D98="Medium",$E98="Low"),$A98&" "&$B98,"") | S98: =IF(AND($B98<>"",$C98<>"Target state",$C98<>"Exception",$D98="Medium",$E98="Medium"),$A98&" "&$B98,"") | T98: =IF(AND($B98<>"",$C98<>"Target state",$C98<>"Exception",$D98="Medium",$E98="High"),$A98&" "&$B98,"") | U98: =IF(AND($B98<>"",$C98<>"Target state",$C98<>"Exception",$D98="Low",$E98="Low"),$A98&" "&$B98,"") | V98: =IF(AND($B98<>"",$C98<>"Target state",$C98<>"Exception",$D98="Low",$E98="Medium"),$A98&" "&$B98,"") | W98: =IF(AND($B98<>"",$C98<>"Target state",$C98<>"Exception",$D98="Low",$E98="High"),$A98&" "&$B98,"")
A99: ④ | B99: Jarvis | C99: Non-target state | F99: Non-strategic Get Beyond underwriting and merchant maintenance tool integrating with TSYS and Fiserv; about $150K in yearly cost; on the decommission path | G99: =IF(OR($B99="",$D99="",$E99=""),"",IF(OR($C99="Target state",$C99="Exception"),"Out of scope",IF($D99="Low","No tranche",IF($E99="Low","Tranche 1",IF($E99="Medium","Tranche 2",IF($D99="High","Tranche 3","No tranche")))))) | O99: =IF(AND($B99<>"",$C99<>"Target state",$C99<>"Exception",$D99="High",$E99="Low"),$A99&" "&$B99,"") | P99: =IF(AND($B99<>"",$C99<>"Target state",$C99<>"Exception",$D99="High",$E99="Medium"),$A99&" "&$B99,"") | Q99: =IF(AND($B99<>"",$C99<>"Target state",$C99<>"Exception",$D99="High",$E99="High"),$A99&" "&$B99,"") | R99: =IF(AND($B99<>"",$C99<>"Target state",$C99<>"Exception",$D99="Medium",$E99="Low"),$A99&" "&$B99,"") | S99: =IF(AND($B99<>"",$C99<>"Target state",$C99<>"Exception",$D99="Medium",$E99="Medium"),$A99&" "&$B99,"") | T99: =IF(AND($B99<>"",$C99<>"Target state",$C99<>"Exception",$D99="Medium",$E99="High"),$A99&" "&$B99,"") | U99: =IF(AND($B99<>"",$C99<>"Target state",$C99<>"Exception",$D99="Low",$E99="Low"),$A99&" "&$B99,"") | V99: =IF(AND($B99<>"",$C99<>"Target state",$C99<>"Exception",$D99="Low",$E99="Medium"),$A99&" "&$B99,"") | W99: =IF(AND($B99<>"",$C99<>"Target state",$C99<>"Exception",$D99="Low",$E99="High"),$A99&" "&$B99,"")
A100: ⑤ | G100: =IF(OR($B100="",$D100="",$E100=""),"",IF(OR($C100="Target state",$C100="Exception"),"Out of scope",IF($D100="Low","No tranche",IF($E100="Low","Tranche 1",IF($E100="Medium","Tranche 2",IF($D100="High","Tranche 3","No tranche")))))) | J100: Medium | K100: ="Tranche 1"&CHAR(10)&_xlfn.TEXTJOIN(CHAR(10),TRUE,R$96:R$105) | L100: ="Tranche 2"&CHAR(10)&_xlfn.TEXTJOIN(CHAR(10),TRUE,S$96:S$105) | M100: =_xlfn.TEXTJOIN(CHAR(10),TRUE,T$96:T$105) | O100: =IF(AND($B100<>"",$C100<>"Target state",$C100<>"Exception",$D100="High",$E100="Low"),$A100&" "&$B100,"") | P100: =IF(AND($B100<>"",$C100<>"Target state",$C100<>"Exception",$D100="High",$E100="Medium"),$A100&" "&$B100,"") | Q100: =IF(AND($B100<>"",$C100<>"Target state",$C100<>"Exception",$D100="High",$E100="High"),$A100&" "&$B100,"") | R100: =IF(AND($B100<>"",$C100<>"Target state",$C100<>"Exception",$D100="Medium",$E100="Low"),$A100&" "&$B100,"") | S100: =IF(AND($B100<>"",$C100<>"Target state",$C100<>"Exception",$D100="Medium",$E100="Medium"),$A100&" "&$B100,"") | T100: =IF(AND($B100<>"",$C100<>"Target state",$C100<>"Exception",$D100="Medium",$E100="High"),$A100&" "&$B100,"") | U100: =IF(AND($B100<>"",$C100<>"Target state",$C100<>"Exception",$D100="Low",$E100="Low"),$A100&" "&$B100,"") | V100: =IF(AND($B100<>"",$C100<>"Target state",$C100<>"Exception",$D100="Low",$E100="Medium"),$A100&" "&$B100,"") | W100: =IF(AND($B100<>"",$C100<>"Target state",$C100<>"Exception",$D100="Low",$E100="High"),$A100&" "&$B100,"")
A101: ⑥ | G101: =IF(OR($B101="",$D101="",$E101=""),"",IF(OR($C101="Target state",$C101="Exception"),"Out of scope",IF($D101="Low","No tranche",IF($E101="Low","Tranche 1",IF($E101="Medium","Tranche 2",IF($D101="High","Tranche 3","No tranche")))))) | O101: =IF(AND($B101<>"",$C101<>"Target state",$C101<>"Exception",$D101="High",$E101="Low"),$A101&" "&$B101,"") | P101: =IF(AND($B101<>"",$C101<>"Target state",$C101<>"Exception",$D101="High",$E101="Medium"),$A101&" "&$B101,"") | Q101: =IF(AND($B101<>"",$C101<>"Target state",$C101<>"Exception",$D101="High",$E101="High"),$A101&" "&$B101,"") | R101: =IF(AND($B101<>"",$C101<>"Target state",$C101<>"Exception",$D101="Medium",$E101="Low"),$A101&" "&$B101,"") | S101: =IF(AND($B101<>"",$C101<>"Target state",$C101<>"Exception",$D101="Medium",$E101="Medium"),$A101&" "&$B101,"") | T101: =IF(AND($B101<>"",$C101<>"Target state",$C101<>"Exception",$D101="Medium",$E101="High"),$A101&" "&$B101,"") | U101: =IF(AND($B101<>"",$C101<>"Target state",$C101<>"Exception",$D101="Low",$E101="Low"),$A101&" "&$B101,"") | V101: =IF(AND($B101<>"",$C101<>"Target state",$C101<>"Exception",$D101="Low",$E101="Medium"),$A101&" "&$B101,"") | W101: =IF(AND($B101<>"",$C101<>"Target state",$C101<>"Exception",$D101="Low",$E101="High"),$A101&" "&$B101,"")
A102: ⑦ | G102: =IF(OR($B102="",$D102="",$E102=""),"",IF(OR($C102="Target state",$C102="Exception"),"Out of scope",IF($D102="Low","No tranche",IF($E102="Low","Tranche 1",IF($E102="Medium","Tranche 2",IF($D102="High","Tranche 3","No tranche")))))) | O102: =IF(AND($B102<>"",$C102<>"Target state",$C102<>"Exception",$D102="High",$E102="Low"),$A102&" "&$B102,"") | P102: =IF(AND($B102<>"",$C102<>"Target state",$C102<>"Exception",$D102="High",$E102="Medium"),$A102&" "&$B102,"") | Q102: =IF(AND($B102<>"",$C102<>"Target state",$C102<>"Exception",$D102="High",$E102="High"),$A102&" "&$B102,"") | R102: =IF(AND($B102<>"",$C102<>"Target state",$C102<>"Exception",$D102="Medium",$E102="Low"),$A102&" "&$B102,"") | S102: =IF(AND($B102<>"",$C102<>"Target state",$C102<>"Exception",$D102="Medium",$E102="Medium"),$A102&" "&$B102,"") | T102: =IF(AND($B102<>"",$C102<>"Target state",$C102<>"Exception",$D102="Medium",$E102="High"),$A102&" "&$B102,"") | U102: =IF(AND($B102<>"",$C102<>"Target state",$C102<>"Exception",$D102="Low",$E102="Low"),$A102&" "&$B102,"") | V102: =IF(AND($B102<>"",$C102<>"Target state",$C102<>"Exception",$D102="Low",$E102="Medium"),$A102&" "&$B102,"") | W102: =IF(AND($B102<>"",$C102<>"Target state",$C102<>"Exception",$D102="Low",$E102="High"),$A102&" "&$B102,"")
A103: ⑧ | G103: =IF(OR($B103="",$D103="",$E103=""),"",IF(OR($C103="Target state",$C103="Exception"),"Out of scope",IF($D103="Low","No tranche",IF($E103="Low","Tranche 1",IF($E103="Medium","Tranche 2",IF($D103="High","Tranche 3","No tranche")))))) | J103: Low | K103: =_xlfn.TEXTJOIN(CHAR(10),TRUE,U$96:U$105) | L103: =_xlfn.TEXTJOIN(CHAR(10),TRUE,V$96:V$105) | M103: =_xlfn.TEXTJOIN(CHAR(10),TRUE,W$96:W$105) | O103: =IF(AND($B103<>"",$C103<>"Target state",$C103<>"Exception",$D103="High",$E103="Low"),$A103&" "&$B103,"") | P103: =IF(AND($B103<>"",$C103<>"Target state",$C103<>"Exception",$D103="High",$E103="Medium"),$A103&" "&$B103,"") | Q103: =IF(AND($B103<>"",$C103<>"Target state",$C103<>"Exception",$D103="High",$E103="High"),$A103&" "&$B103,"") | R103: =IF(AND($B103<>"",$C103<>"Target state",$C103<>"Exception",$D103="Medium",$E103="Low"),$A103&" "&$B103,"") | S103: =IF(AND($B103<>"",$C103<>"Target state",$C103<>"Exception",$D103="Medium",$E103="Medium"),$A103&" "&$B103,"") | T103: =IF(AND($B103<>"",$C103<>"Target state",$C103<>"Exception",$D103="Medium",$E103="High"),$A103&" "&$B103,"") | U103: =IF(AND($B103<>"",$C103<>"Target state",$C103<>"Exception",$D103="Low",$E103="Low"),$A103&" "&$B103,"") | V103: =IF(AND($B103<>"",$C103<>"Target state",$C103<>"Exception",$D103="Low",$E103="Medium"),$A103&" "&$B103,"") | W103: =IF(AND($B103<>"",$C103<>"Target state",$C103<>"Exception",$D103="Low",$E103="High"),$A103&" "&$B103,"")
A104: ⑨ | G104: =IF(OR($B104="",$D104="",$E104=""),"",IF(OR($C104="Target state",$C104="Exception"),"Out of scope",IF($D104="Low","No tranche",IF($E104="Low","Tranche 1",IF($E104="Medium","Tranche 2",IF($D104="High","Tranche 3","No tranche")))))) | O104: =IF(AND($B104<>"",$C104<>"Target state",$C104<>"Exception",$D104="High",$E104="Low"),$A104&" "&$B104,"") | P104: =IF(AND($B104<>"",$C104<>"Target state",$C104<>"Exception",$D104="High",$E104="Medium"),$A104&" "&$B104,"") | Q104: =IF(AND($B104<>"",$C104<>"Target state",$C104<>"Exception",$D104="High",$E104="High"),$A104&" "&$B104,"") | R104: =IF(AND($B104<>"",$C104<>"Target state",$C104<>"Exception",$D104="Medium",$E104="Low"),$A104&" "&$B104,"") | S104: =IF(AND($B104<>"",$C104<>"Target state",$C104<>"Exception",$D104="Medium",$E104="Medium"),$A104&" "&$B104,"") | T104: =IF(AND($B104<>"",$C104<>"Target state",$C104<>"Exception",$D104="Medium",$E104="High"),$A104&" "&$B104,"") | U104: =IF(AND($B104<>"",$C104<>"Target state",$C104<>"Exception",$D104="Low",$E104="Low"),$A104&" "&$B104,"") | V104: =IF(AND($B104<>"",$C104<>"Target state",$C104<>"Exception",$D104="Low",$E104="Medium"),$A104&" "&$B104,"") | W104: =IF(AND($B104<>"",$C104<>"Target state",$C104<>"Exception",$D104="Low",$E104="High"),$A104&" "&$B104,"")
A105: ⑩ | G105: =IF(OR($B105="",$D105="",$E105=""),"",IF(OR($C105="Target state",$C105="Exception"),"Out of scope",IF($D105="Low","No tranche",IF($E105="Low","Tranche 1",IF($E105="Medium","Tranche 2",IF($D105="High","Tranche 3","No tranche")))))) | O105: =IF(AND($B105<>"",$C105<>"Target state",$C105<>"Exception",$D105="High",$E105="Low"),$A105&" "&$B105,"") | P105: =IF(AND($B105<>"",$C105<>"Target state",$C105<>"Exception",$D105="High",$E105="Medium"),$A105&" "&$B105,"") | Q105: =IF(AND($B105<>"",$C105<>"Target state",$C105<>"Exception",$D105="High",$E105="High"),$A105&" "&$B105,"") | R105: =IF(AND($B105<>"",$C105<>"Target state",$C105<>"Exception",$D105="Medium",$E105="Low"),$A105&" "&$B105,"") | S105: =IF(AND($B105<>"",$C105<>"Target state",$C105<>"Exception",$D105="Medium",$E105="Medium"),$A105&" "&$B105,"") | T105: =IF(AND($B105<>"",$C105<>"Target state",$C105<>"Exception",$D105="Medium",$E105="High"),$A105&" "&$B105,"") | U105: =IF(AND($B105<>"",$C105<>"Target state",$C105<>"Exception",$D105="Low",$E105="Low"),$A105&" "&$B105,"") | V105: =IF(AND($B105<>"",$C105<>"Target state",$C105<>"Exception",$D105="Low",$E105="Medium"),$A105&" "&$B105,"") | W105: =IF(AND($B105<>"",$C105<>"Target state",$C105<>"Exception",$D105="Low",$E105="High"),$A105&" "&$B105,"")
K106: Complexity
A110: CPQ / Quote-pricing | G110: =HYPERLINK("#'Boarding'!A4","▲ tracker") | K110: Assessment Outcome
A111: # | B111: Platform | C111: State | D111: Imperative to exit | E111: Exit complexity | F111: Supporting facts | G111: Tranche (auto) | K111: Low | L111: Medium | M111: High
A112: ① | B112: Fee Rule Manager | C112: Non-target state | F112: Non-strategic pricing manipulation tool for Heartland merchants with about 120 users; repository flags Keep & Enhance with selective migration — confirm with SPOC | G112: =IF(OR($B112="",$D112="",$E112=""),"",IF(OR($C112="Target state",$C112="Exception"),"Out of scope",IF($D112="Low","No tranche",IF($E112="Low","Tranche 1",IF($E112="Medium","Tranche 2",IF($D112="High","Tranche 3","No tranche")))))) | I112: Benefits | J112: High | K112: ="Tranche 1"&CHAR(10)&_xlfn.TEXTJOIN(CHAR(10),TRUE,O$112:O$121) | L112: ="Tranche 2"&CHAR(10)&_xlfn.TEXTJOIN(CHAR(10),TRUE,P$112:P$121) | M112: ="Tranche 3"&CHAR(10)&_xlfn.TEXTJOIN(CHAR(10),TRUE,Q$112:Q$121) | O112: =IF(AND($B112<>"",$C112<>"Target state",$C112<>"Exception",$D112="High",$E112="Low"),$A112&" "&$B112,"") | P112: =IF(AND($B112<>"",$C112<>"Target state",$C112<>"Exception",$D112="High",$E112="Medium"),$A112&" "&$B112,"") | Q112: =IF(AND($B112<>"",$C112<>"Target state",$C112<>"Exception",$D112="High",$E112="High"),$A112&" "&$B112,"") | R112: =IF(AND($B112<>"",$C112<>"Target state",$C112<>"Exception",$D112="Medium",$E112="Low"),$A112&" "&$B112,"") | S112: =IF(AND($B112<>"",$C112<>"Target state",$C112<>"Exception",$D112="Medium",$E112="Medium"),$A112&" "&$B112,"") | T112: =IF(AND($B112<>"",$C112<>"Target state",$C112<>"Exception",$D112="Medium",$E112="High"),$A112&" "&$B112,"") | U112: =IF(AND($B112<>"",$C112<>"Target state",$C112<>"Exception",$D112="Low",$E112="Low"),$A112&" "&$B112,"") | V112: =IF(AND($B112<>"",$C112<>"Target state",$C112<>"Exception",$D112="Low",$E112="Medium"),$A112&" "&$B112,"") | W112: =IF(AND($B112<>"",$C112<>"Target state",$C112<>"Exception",$D112="Low",$E112="High"),$A112&" "&$B112,"")
A113: ② | B113: Heartland Pricing Portal | C113: Non-target state | F113: Non-strategic pricing and retention tooling for Heartland merchants with about 220 users; repository flags Keep & Enhance with selective migration — confirm with SPOC | G113: =IF(OR($B113="",$D113="",$E113=""),"",IF(OR($C113="Target state",$C113="Exception"),"Out of scope",IF($D113="Low","No tranche",IF($E113="Low","Tranche 1",IF($E113="Medium","Tranche 2",IF($D113="High","Tranche 3","No tranche")))))) | O113: =IF(AND($B113<>"",$C113<>"Target state",$C113<>"Exception",$D113="High",$E113="Low"),$A113&" "&$B113,"") | P113: =IF(AND($B113<>"",$C113<>"Target state",$C113<>"Exception",$D113="High",$E113="Medium"),$A113&" "&$B113,"") | Q113: =IF(AND($B113<>"",$C113<>"Target state",$C113<>"Exception",$D113="High",$E113="High"),$A113&" "&$B113,"") | R113: =IF(AND($B113<>"",$C113<>"Target state",$C113<>"Exception",$D113="Medium",$E113="Low"),$A113&" "&$B113,"") | S113: =IF(AND($B113<>"",$C113<>"Target state",$C113<>"Exception",$D113="Medium",$E113="Medium"),$A113&" "&$B113,"") | T113: =IF(AND($B113<>"",$C113<>"Target state",$C113<>"Exception",$D113="Medium",$E113="High"),$A113&" "&$B113,"") | U113: =IF(AND($B113<>"",$C113<>"Target state",$C113<>"Exception",$D113="Low",$E113="Low"),$A113&" "&$B113,"") | V113: =IF(AND($B113<>"",$C113<>"Target state",$C113<>"Exception",$D113="Low",$E113="Medium"),$A113&" "&$B113,"") | W113: =IF(AND($B113<>"",$C113<>"Target state",$C113<>"Exception",$D113="Low",$E113="High"),$A113&" "&$B113,"")
A114: ③ | B114: Margin Service | C114: Non-target state | F114: Non-strategic margin calculator API for Heartland payments products; migration path agreed | G114: =IF(OR($B114="",$D114="",$E114=""),"",IF(OR($C114="Target state",$C114="Exception"),"Out of scope",IF($D114="Low","No tranche",IF($E114="Low","Tranche 1",IF($E114="Medium","Tranche 2",IF($D114="High","Tranche 3","No tranche")))))) | O114: =IF(AND($B114<>"",$C114<>"Target state",$C114<>"Exception",$D114="High",$E114="Low"),$A114&" "&$B114,"") | P114: =IF(AND($B114<>"",$C114<>"Target state",$C114<>"Exception",$D114="High",$E114="Medium"),$A114&" "&$B114,"") | Q114: =IF(AND($B114<>"",$C114<>"Target state",$C114<>"Exception",$D114="High",$E114="High"),$A114&" "&$B114,"") | R114: =IF(AND($B114<>"",$C114<>"Target state",$C114<>"Exception",$D114="Medium",$E114="Low"),$A114&" "&$B114,"") | S114: =IF(AND($B114<>"",$C114<>"Target state",$C114<>"Exception",$D114="Medium",$E114="Medium"),$A114&" "&$B114,"") | T114: =IF(AND($B114<>"",$C114<>"Target state",$C114<>"Exception",$D114="Medium",$E114="High"),$A114&" "&$B114,"") | U114: =IF(AND($B114<>"",$C114<>"Target state",$C114<>"Exception",$D114="Low",$E114="Low"),$A114&" "&$B114,"") | V114: =IF(AND($B114<>"",$C114<>"Target state",$C114<>"Exception",$D114="Low",$E114="Medium"),$A114&" "&$B114,"") | W114: =IF(AND($B114<>"",$C114<>"Target state",$C114<>"Exception",$D114="Low",$E114="High"),$A114&" "&$B114,"")
A115: ④ | G115: =IF(OR($B115="",$D115="",$E115=""),"",IF(OR($C115="Target state",$C115="Exception"),"Out of scope",IF($D115="Low","No tranche",IF($E115="Low","Tranche 1",IF($E115="Medium","Tranche 2",IF($D115="High","Tranche 3","No tranche")))))) | O115: =IF(AND($B115<>"",$C115<>"Target state",$C115<>"Exception",$D115="High",$E115="Low"),$A115&" "&$B115,"") | P115: =IF(AND($B115<>"",$C115<>"Target state",$C115<>"Exception",$D115="High",$E115="Medium"),$A115&" "&$B115,"") | Q115: =IF(AND($B115<>"",$C115<>"Target state",$C115<>"Exception",$D115="High",$E115="High"),$A115&" "&$B115,"") | R115: =IF(AND($B115<>"",$C115<>"Target state",$C115<>"Exception",$D115="Medium",$E115="Low"),$A115&" "&$B115,"") | S115: =IF(AND($B115<>"",$C115<>"Target state",$C115<>"Exception",$D115="Medium",$E115="Medium"),$A115&" "&$B115,"") | T115: =IF(AND($B115<>"",$C115<>"Target state",$C115<>"Exception",$D115="Medium",$E115="High"),$A115&" "&$B115,"") | U115: =IF(AND($B115<>"",$C115<>"Target state",$C115<>"Exception",$D115="Low",$E115="Low"),$A115&" "&$B115,"") | V115: =IF(AND($B115<>"",$C115<>"Target state",$C115<>"Exception",$D115="Low",$E115="Medium"),$A115&" "&$B115,"") | W115: =IF(AND($B115<>"",$C115<>"Target state",$C115<>"Exception",$D115="Low",$E115="High"),$A115&" "&$B115,"")
A116: ⑤ | G116: =IF(OR($B116="",$D116="",$E116=""),"",IF(OR($C116="Target state",$C116="Exception"),"Out of scope",IF($D116="Low","No tranche",IF($E116="Low","Tranche 1",IF($E116="Medium","Tranche 2",IF($D116="High","Tranche 3","No tranche")))))) | J116: Medium | K116: ="Tranche 1"&CHAR(10)&_xlfn.TEXTJOIN(CHAR(10),TRUE,R$112:R$121) | L116: ="Tranche 2"&CHAR(10)&_xlfn.TEXTJOIN(CHAR(10),TRUE,S$112:S$121) | M116: =_xlfn.TEXTJOIN(CHAR(10),TRUE,T$112:T$121) | O116: =IF(AND($B116<>"",$C116<>"Target state",$C116<>"Exception",$D116="High",$E116="Low"),$A116&" "&$B116,"") | P116: =IF(AND($B116<>"",$C116<>"Target state",$C116<>"Exception",$D116="High",$E116="Medium"),$A116&" "&$B116,"") | Q116: =IF(AND($B116<>"",$C116<>"Target state",$C116<>"Exception",$D116="High",$E116="High"),$A116&" "&$B116,"") | R116: =IF(AND($B116<>"",$C116<>"Target state",$C116<>"Exception",$D116="Medium",$E116="Low"),$A116&" "&$B116,"") | S116: =IF(AND($B116<>"",$C116<>"Target state",$C116<>"Exception",$D116="Medium",$E116="Medium"),$A116&" "&$B116,"") | T116: =IF(AND($B116<>"",$C116<>"Target state",$C116<>"Exception",$D116="Medium",$E116="High"),$A116&" "&$B116,"") | U116: =IF(AND($B116<>"",$C116<>"Target state",$C116<>"Exception",$D116="Low",$E116="Low"),$A116&" "&$B116,"") | V116: =IF(AND($B116<>"",$C116<>"Target state",$C116<>"Exception",$D116="Low",$E116="Medium"),$A116&" "&$B116,"") | W116: =IF(AND($B116<>"",$C116<>"Target state",$C116<>"Exception",$D116="Low",$E116="High"),$A116&" "&$B116,"")
A117: ⑥ | G117: =IF(OR($B117="",$D117="",$E117=""),"",IF(OR($C117="Target state",$C117="Exception"),"Out of scope",IF($D117="Low","No tranche",IF($E117="Low","Tranche 1",IF($E117="Medium","Tranche 2",IF($D117="High","Tranche 3","No tranche")))))) | O117: =IF(AND($B117<>"",$C117<>"Target state",$C117<>"Exception",$D117="High",$E117="Low"),$A117&" "&$B117,"") | P117: =IF(AND($B117<>"",$C117<>"Target state",$C117<>"Exception",$D117="High",$E117="Medium"),$A117&" "&$B117,"") | Q117: =IF(AND($B117<>"",$C117<>"Target state",$C117<>"Exception",$D117="High",$E117="High"),$A117&" "&$B117,"") | R117: =IF(AND($B117<>"",$C117<>"Target state",$C117<>"Exception",$D117="Medium",$E117="Low"),$A117&" "&$B117,"") | S117: =IF(AND($B117<>"",$C117<>"Target state",$C117<>"Exception",$D117="Medium",$E117="Medium"),$A117&" "&$B117,"") | T117: =IF(AND($B117<>"",$C117<>"Target state",$C117<>"Exception",$D117="Medium",$E117="High"),$A117&" "&$B117,"") | U117: =IF(AND($B117<>"",$C117<>"Target state",$C117<>"Exception",$D117="Low",$E117="Low"),$A117&" "&$B117,"") | V117: =IF(AND($B117<>"",$C117<>"Target state",$C117<>"Exception",$D117="Low",$E117="Medium"),$A117&" "&$B117,"") | W117: =IF(AND($B117<>"",$C117<>"Target state",$C117<>"Exception",$D117="Low",$E117="High"),$A117&" "&$B117,"")
...

Sheet Single-in
A1: Single-in — Platform Assessment
A2: =HYPERLINK("#'Summary'!A1","← Back to Summary") | C2: Pick a State, score High / Medium / Low — the tranche, the matrix and the Summary update automatically.
A4: Tracker — jump to a sub-capability:
A5: 1. | B5: =HYPERLINK("#'Single-in'!A11","Global API")
A6: 2. | B6: =HYPERLINK("#'Single-in'!A27","Payment Apps & SDKs")
A7: 3. | B7: =HYPERLINK("#'Single-in'!A56","Developer Experience")
A8: 4. | B8: =HYPERLINK("#'Single-in'!A72","Hosted Solutions")
A9: 5. | B9: =HYPERLINK("#'Single-in'!A88","Unified Proposition")
A11: Global API | G11: =HYPERLINK("#'Single-in'!A4","▲ tracker") | K11: Assessment Outcome
A12: # | B12: Platform | C12: State | D12: Imperative to exit | E12: Exit complexity | F12: Supporting facts | G12: Tranche (auto) | K12: Low | L12: Medium | M12: High
A13: ① | B13: Comercia Addon2.0 API | C13: Non-target state | F13: Non-strategic Addon 2.0 integration API for Comercia merchants offered as JavaScript or host-to-host; on the decommission path | G13: =IF(OR($B13="",$D13="",$E13=""),"",IF(OR($C13="Target state",$C13="Exception"),"Out of scope",IF($D13="Low","No tranche",IF($E13="Low","Tranche 1",IF($E13="Medium","Tranche 2",IF($D13="High","Tranche 3","No tranche")))))) | I13: Benefits | J13: High | K13: ="Tranche 1"&CHAR(10)&_xlfn.TEXTJOIN(CHAR(10),TRUE,O$13:O$22) | L13: ="Tranche 2"&CHAR(10)&_xlfn.TEXTJOIN(CHAR(10),TRUE,P$13:P$22) | M13: ="Tranche 3"&CHAR(10)&_xlfn.TEXTJOIN(CHAR(10),TRUE,Q$13:Q$22) | O13: =IF(AND($B13<>"",$C13<>"Target state",$C13<>"Exception",$D13="High",$E13="Low"),$A13&" "&$B13,"") | P13: =IF(AND($B13<>"",$C13<>"Target state",$C13<>"Exception",$D13="High",$E13="Medium"),$A13&" "&$B13,"") | Q13: =IF(AND($B13<>"",$C13<>"Target state",$C13<>"Exception",$D13="High",$E13="High"),$A13&" "&$B13,"") | R13: =IF(AND($B13<>"",$C13<>"Target state",$C13<>"Exception",$D13="Medium",$E13="Low"),$A13&" "&$B13,"") | S13: =IF(AND($B13<>"",$C13<>"Target state",$C13<>"Exception",$D13="Medium",$E13="Medium"),$A13&" "&$B13,"") | T13: =IF(AND($B13<>"",$C13<>"Target state",$C13<>"Exception",$D13="Medium",$E13="High"),$A13&" "&$B13,"") | U13: =IF(AND($B13<>"",$C13<>"Target state",$C13<>"Exception",$D13="Low",$E13="Low"),$A13&" "&$B13,"") | V13: =IF(AND($B13<>"",$C13<>"Target state",$C13<>"Exception",$D13="Low",$E13="Medium"),$A13&" "&$B13,"") | W13: =IF(AND($B13<>"",$C13<>"Target state",$C13<>"Exception",$D13="Low",$E13="High"),$A13&" "&$B13,"")
A14: ② | G14: =IF(OR($B14="",$D14="",$E14=""),"",IF(OR($C14="Target state",$C14="Exception"),"Out of scope",IF($D14="Low","No tranche",IF($E14="Low","Tranche 1",IF($E14="Medium","Tranche 2",IF($D14="High","Tranche 3","No tranche")))))) | O14: =IF(AND($B14<>"",$C14<>"Target state",$C14<>"Exception",$D14="High",$E14="Low"),$A14&" "&$B14,"") | P14: =IF(AND($B14<>"",$C14<>"Target state",$C14<>"Exception",$D14="High",$E14="Medium"),$A14&" "&$B14,"") | Q14: =IF(AND($B14<>"",$C14<>"Target state",$C14<>"Exception",$D14="High",$E14="High"),$A14&" "&$B14,"") | R14: =IF(AND($B14<>"",$C14<>"Target state",$C14<>"Exception",$D14="Medium",$E14="Low"),$A14&" "&$B14,"") | S14: =IF(AND($B14<>"",$C14<>"Target state",$C14<>"Exception",$D14="Medium",$E14="Medium"),$A14&" "&$B14,"") | T14: =IF(AND($B14<>"",$C14<>"Target state",$C14<>"Exception",$D14="Medium",$E14="High"),$A14&" "&$B14,"") | U14: =IF(AND($B14<>"",$C14<>"Target state",$C14<>"Exception",$D14="Low",$E14="Low"),$A14&" "&$B14,"") | V14: =IF(AND($B14<>"",$C14<>"Target state",$C14<>"Exception",$D14="Low",$E14="Medium"),$A14&" "&$B14,"") | W14: =IF(AND($B14<>"",$C14<>"Target state",$C14<>"Exception",$D14="Low",$E14="High"),$A14&" "&$B14,"")
A15: ③ | G15: =IF(OR($B15="",$D15="",$E15=""),"",IF(OR($C15="Target state",$C15="Exception"),"Out of scope",IF($D15="Low","No tranche",IF($E15="Low","Tranche 1",IF($E15="Medium","Tranche 2",IF($D15="High","Tranche 3","No tranche")))))) | O15: =IF(AND($B15<>"",$C15<>"Target state",$C15<>"Exception",$D15="High",$E15="Low"),$A15&" "&$B15,"") | P15: =IF(AND($B15<>"",$C15<>"Target state",$C15<>"Exception",$D15="High",$E15="Medium"),$A15&" "&$B15,"") | Q15: =IF(AND($B15<>"",$C15<>"Target state",$C15<>"Exception",$D15="High",$E15="High"),$A15&" "&$B15,"") | R15: =IF(AND($B15<>"",$C15<>"Target state",$C15<>"Exception",$D15="Medium",$E15="Low"),$A15&" "&$B15,"") | S15: =IF(AND($B15<>"",$C15<>"Target state",$C15<>"Exception",$D15="Medium",$E15="Medium"),$A15&" "&$B15,"") | T15: =IF(AND($B15<>"",$C15<>"Target state",$C15<>"Exception",$D15="Medium",$E15="High"),$A15&" "&$B15,"") | U15: =IF(AND($B15<>"",$C15<>"Target state",$C15<>"Exception",$D15="Low",$E15="Low"),$A15&" "&$B15,"") | V15: =IF(AND($B15<>"",$C15<>"Target state",$C15<>"Exception",$D15="Low",$E15="Medium"),$A15&" "&$B15,"") | W15: =IF(AND($B15<>"",$C15<>"Target state",$C15<>"Exception",$D15="Low",$E15="High"),$A15&" "&$B15,"")
A16: ④ | G16: =IF(OR($B16="",$D16="",$E16=""),"",IF(OR($C16="Target state",$C16="Exception"),"Out of scope",IF($D16="Low","No tranche",IF($E16="Low","Tranche 1",IF($E16="Medium","Tranche 2",IF($D16="High","Tranche 3","No tranche")))))) | O16: =IF(AND($B16<>"",$C16<>"Target state",$C16<>"Exception",$D16="High",$E16="Low"),$A16&" "&$B16,"") | P16: =IF(AND($B16<>"",$C16<>"Target state",$C16<>"Exception",$D16="High",$E16="Medium"),$A16&" "&$B16,"") | Q16: =IF(AND($B16<>"",$C16<>"Target state",$C16<>"Exception",$D16="High",$E16="High"),$A16&" "&$B16,"") | R16: =IF(AND($B16<>"",$C16<>"Target state",$C16<>"Exception",$D16="Medium",$E16="Low"),$A16&" "&$B16,"") | S16: =IF(AND($B16<>"",$C16<>"Target state",$C16<>"Exception",$D16="Medium",$E16="Medium"),$A16&" "&$B16,"") | T16: =IF(AND($B16<>"",$C16<>"Target state",$C16<>"Exception",$D16="Medium",$E16="High"),$A16&" "&$B16,"") | U16: =IF(AND($B16<>"",$C16<>"Target state",$C16<>"Exception",$D16="Low",$E16="Low"),$A16&" "&$B16,"") | V16: =IF(AND($B16<>"",$C16<>"Target state",$C16<>"Exception",$D16="Low",$E16="Medium"),$A16&" "&$B16,"") | W16: =IF(AND($B16<>"",$C16<>"Target state",$C16<>"Exception",$D16="Low",$E16="High"),$A16&" "&$B16,"")
A17: ⑤ | G17: =IF(OR($B17="",$D17="",$E17=""),"",IF(OR($C17="Target state",$C17="Exception"),"Out of scope",IF($D17="Low","No tranche",IF($E17="Low","Tranche 1",IF($E17="Medium","Tranche 2",IF($D17="High","Tranche 3","No tranche")))))) | J17: Medium | K17: ="Tranche 1"&CHAR(10)&_xlfn.TEXTJOIN(CHAR(10),TRUE,R$13:R$22) | L17: ="Tranche 2"&CHAR(10)&_xlfn.TEXTJOIN(CHAR(10),TRUE,S$13:S$22) | M17: =_xlfn.TEXTJOIN(CHAR(10),TRUE,T$13:T$22) | O17: =IF(AND($B17<>"",$C17<>"Target state",$C17<>"Exception",$D17="High",$E17="Low"),$A17&" "&$B17,"") | P17: =IF(AND($B17<>"",$C17<>"Target state",$C17<>"Exception",$D17="High",$E17="Medium"),$A17&" "&$B17,"") | Q17: =IF(AND($B17<>"",$C17<>"Target state",$C17<>"Exception",$D17="High",$E17="High"),$A17&" "&$B17,"") | R17: =IF(AND($B17<>"",$C17<>"Target state",$C17<>"Exception",$D17="Medium",$E17="Low"),$A17&" "&$B17,"") | S17: =IF(AND($B17<>"",$C17<>"Target state",$C17<>"Exception",$D17="Medium",$E17="Medium"),$A17&" "&$B17,"") | T17: =IF(AND($B17<>"",$C17<>"Target state",$C17<>"Exception",$D17="Medium",$E17="High"),$A17&" "&$B17,"") | U17: =IF(AND($B17<>"",$C17<>"Target state",$C17<>"Exception",$D17="Low",$E17="Low"),$A17&" "&$B17,"") | V17: =IF(AND($B17<>"",$C17<>"Target state",$C17<>"Exception",$D17="Low",$E17="Medium"),$A17&" "&$B17,"") | W17: =IF(AND($B17<>"",$C17<>"Target state",$C17<>"Exception",$D17="Low",$E17="High"),$A17&" "&$B17,"")
A18: ⑥ | G18: =IF(OR($B18="",$D18="",$E18=""),"",IF(OR($C18="Target state",$C18="Exception"),"Out of scope",IF($D18="Low","No tranche",IF($E18="Low","Tranche 1",IF($E18="Medium","Tranche 2",IF($D18="High","Tranche 3","No tranche")))))) | O18: =IF(AND($B18<>"",$C18<>"Target state",$C18<>"Exception",$D18="High",$E18="Low"),$A18&" "&$B18,"") | P18: =IF(AND($B18<>"",$C18<>"Target state",$C18<>"Exception",$D18="High",$E18="Medium"),$A18&" "&$B18,"") | Q18: =IF(AND($B18<>"",$C18<>"Target state",$C18<>"Exception",$D18="High",$E18="High"),$A18&" "&$B18,"") | R18: =IF(AND($B18<>"",$C18<>"Target state",$C18<>"Exception",$D18="Medium",$E18="Low"),$A18&" "&$B18,"") | S18: =IF(AND($B18<>"",$C18<>"Target state",$C18<>"Exception",$D18="Medium",$E18="Medium"),$A18&" "&$B18,"") | T18: =IF(AND($B18<>"",$C18<>"Target state",$C18<>"Exception",$D18="Medium",$E18="High"),$A18&" "&$B18,"") | U18: =IF(AND($B18<>"",$C18<>"Target state",$C18<>"Exception",$D18="Low",$E18="Low"),$A18&" "&$B18,"") | V18: =IF(AND($B18<>"",$C18<>"Target state",$C18<>"Exception",$D18="Low",$E18="Medium"),$A18&" "&$B18,"") | W18: =IF(AND($B18<>"",$C18<>"Target state",$C18<>"Exception",$D18="Low",$E18="High"),$A18&" "&$B18,"")
A19: ⑦ | G19: =IF(OR($B19="",$D19="",$E19=""),"",IF(OR($C19="Target state",$C19="Exception"),"Out of scope",IF($D19="Low","No tranche",IF($E19="Low","Tranche 1",IF($E19="Medium","Tranche 2",IF($D19="High","Tranche 3","No tranche")))))) | O19: =IF(AND($B19<>"",$C19<>"Target state",$C19<>"Exception",$D19="High",$E19="Low"),$A19&" "&$B19,"") | P19: =IF(AND($B19<>"",$C19<>"Target state",$C19<>"Exception",$D19="High",$E19="Medium"),$A19&" "&$B19,"") | Q19: =IF(AND($B19<>"",$C19<>"Target state",$C19<>"Exception",$D19="High",$E19="High"),$A19&" "&$B19,"") | R19: =IF(AND($B19<>"",$C19<>"Target state",$C19<>"Exception",$D19="Medium",$E19="Low"),$A19&" "&$B19,"") | S19: =IF(AND($B19<>"",$C19<>"Target state",$C19<>"Exception",$D19="Medium",$E19="Medium"),$A19&" "&$B19,"") | T19: =IF(AND($B19<>"",$C19<>"Target state",$C19<>"Exception",$D19="Medium",$E19="High"),$A19&" "&$B19,"") | U19: =IF(AND($B19<>"",$C19<>"Target state",$C19<>"Exception",$D19="Low",$E19="Low"),$A19&" "&$B19,"") | V19: =IF(AND($B19<>"",$C19<>"Target state",$C19<>"Exception",$D19="Low",$E19="Medium"),$A19&" "&$B19,"") | W19: =IF(AND($B19<>"",$C19<>"Target state",$C19<>"Exception",$D19="Low",$E19="High"),$A19&" "&$B19,"")
A20: ⑧ | G20: =IF(OR($B20="",$D20="",$E20=""),"",IF(OR($C20="Target state",$C20="Exception"),"Out of scope",IF($D20="Low","No tranche",IF($E20="Low","Tranche 1",IF($E20="Medium","Tranche 2",IF($D20="High","Tranche 3","No tranche")))))) | J20: Low | K20: =_xlfn.TEXTJOIN(CHAR(10),TRUE,U$13:U$22) | L20: =_xlfn.TEXTJOIN(CHAR(10),TRUE,V$13:V$22) | M20: =_xlfn.TEXTJOIN(CHAR(10),TRUE,W$13:W$22) | O20: =IF(AND($B20<>"",$C20<>"Target state",$C20<>"Exception",$D20="High",$E20="Low"),$A20&" "&$B20,"") | P20: =IF(AND($B20<>"",$C20<>"Target state",$C20<>"Exception",$D20="High",$E20="Medium"),$A20&" "&$B20,"") | Q20: =IF(AND($B20<>"",$C20<>"Target state",$C20<>"Exception",$D20="High",$E20="High"),$A20&" "&$B20,"") | R20: =IF(AND($B20<>"",$C20<>"Target state",$C20<>"Exception",$D20="Medium",$E20="Low"),$A20&" "&$B20,"") | S20: =IF(AND($B20<>"",$C20<>"Target state",$C20<>"Exception",$D20="Medium",$E20="Medium"),$A20&" "&$B20,"") | T20: =IF(AND($B20<>"",$C20<>"Target state",$C20<>"Exception",$D20="Medium",$E20="High"),$A20&" "&$B20,"") | U20: =IF(AND($B20<>"",$C20<>"Target state",$C20<>"Exception",$D20="Low",$E20="Low"),$A20&" "&$B20,"") | V20: =IF(AND($B20<>"",$C20<>"Target state",$C20<>"Exception",$D20="Low",$E20="Medium"),$A20&" "&$B20,"") | W20: =IF(AND($B20<>"",$C20<>"Target state",$C20<>"Exception",$D20="Low",$E20="High"),$A20&" "&$B20,"")
A21: ⑨ | G21: =IF(OR($B21="",$D21="",$E21=""),"",IF(OR($C21="Target state",$C21="Exception"),"Out of scope",IF($D21="Low","No tranche",IF($E21="Low","Tranche 1",IF($E21="Medium","Tranche 2",IF($D21="High","Tranche 3","No tranche")))))) | O21: =IF(AND($B21<>"",$C21<>"Target state",$C21<>"Exception",$D21="High",$E21="Low"),$A21&" "&$B21,"") | P21: =IF(AND($B21<>"",$C21<>"Target state",$C21<>"Exception",$D21="High",$E21="Medium"),$A21&" "&$B21,"") | Q21: =IF(AND($B21<>"",$C21<>"Target state",$C21<>"Exception",$D21="High",$E21="High"),$A21&" "&$B21,"") | R21: =IF(AND($B21<>"",$C21<>"Target state",$C21<>"Exception",$D21="Medium",$E21="Low"),$A21&" "&$B21,"") | S21: =IF(AND($B21<>"",$C21<>"Target state",$C21<>"Exception",$D21="Medium",$E21="Medium"),$A21&" "&$B21,"") | T21: =IF(AND($B21<>"",$C21<>"Target state",$C21<>"Exception",$D21="Medium",$E21="High"),$A21&" "&$B21,"") | U21: =IF(AND($B21<>"",$C21<>"Target state",$C21<>"Exception",$D21="Low",$E21="Low"),$A21&" "&$B21,"") | V21: =IF(AND($B21<>"",$C21<>"Target state",$C21<>"Exception",$D21="Low",$E21="Medium"),$A21&" "&$B21,"") | W21: =IF(AND($B21<>"",$C21<>"Target state",$C21<>"Exception",$D21="Low",$E21="High"),$A21&" "&$B21,"")
A22: ⑩ | G22: =IF(OR($B22="",$D22="",$E22=""),"",IF(OR($C22="Target state",$C22="Exception"),"Out of scope",IF($D22="Low","No tranche",IF($E22="Low","Tranche 1",IF($E22="Medium","Tranche 2",IF($D22="High","Tranche 3","No tranche")))))) | O22: =IF(AND($B22<>"",$C22<>"Target state",$C22<>"Exception",$D22="High",$E22="Low"),$A22&" "&$B22,"") | P22: =IF(AND($B22<>"",$C22<>"Target state",$C22<>"Exception",$D22="High",$E22="Medium"),$A22&" "&$B22,"") | Q22: =IF(AND($B22<>"",$C22<>"Target state",$C22<>"Exception",$D22="High",$E22="High"),$A22&" "&$B22,"") | R22: =IF(AND($B22<>"",$C22<>"Target state",$C22<>"Exception",$D22="Medium",$E22="Low"),$A22&" "&$B22,"") | S22: =IF(AND($B22<>"",$C22<>"Target state",$C22<>"Exception",$D22="Medium",$E22="Medium"),$A22&" "&$B22,"") | T22: =IF(AND($B22<>"",$C22<>"Target state",$C22<>"Exception",$D22="Medium",$E22="High"),$A22&" "&$B22,"") | U22: =IF(AND($B22<>"",$C22<>"Target state",$C22<>"Exception",$D22="Low",$E22="Low"),$A22&" "&$B22,"") | V22: =IF(AND($B22<>"",$C22<>"Target state",$C22<>"Exception",$D22="Low",$E22="Medium"),$A22&" "&$B22,"") | W22: =IF(AND($B22<>"",$C22<>"Target state",$C22<>"Exception",$D22="Low",$E22="High"),$A22&" "&$B22,"")
K23: Complexity
A27: Payment Apps & SDKs | G27: =HYPERLINK("#'Single-in'!A4","▲ tracker") | K27: Assessment Outcome
A28: # | B28: Platform | C28: State | D28: Imperative to exit | E28: Exit complexity | F28: Supporting facts | G28: Tranche (auto) | K28: Low | L28: Medium | M28: High
A29: ① | B29: Deployed Apps (XCharge, RCM) | C29: Non-target state | F29: Non-strategic legacy deployed applications tightly integrated with the Edge gateway; follow the Edge exit path | G29: =IF(OR($B29="",$D29="",$E29=""),"",IF(OR($C29="Target state",$C29="Exception"),"Out of scope",IF($D29="Low","No tranche",IF($E29="Low","Tranche 1",IF($E29="Medium","Tranche 2",IF($D29="High","Tranche 3","No tranche")))))) | I29: Benefits | J29: High | K29: ="Tranche 1"&CHAR(10)&_xlfn.TEXTJOIN(CHAR(10),TRUE,O$29:O$51) | L29: ="Tranche 2"&CHAR(10)&_xlfn.TEXTJOIN(CHAR(10),TRUE,P$29:P$51) | M29: ="Tranche 3"&CHAR(10)&_xlfn.TEXTJOIN(CHAR(10),TRUE,Q$29:Q$51) | O29: =IF(AND($B29<>"",$C29<>"Target state",$C29<>"Exception",$D29="High",$E29="Low"),$A29&" "&$B29,"") | P29: =IF(AND($B29<>"",$C29<>"Target state",$C29<>"Exception",$D29="High",$E29="Medium"),$A29&" "&$B29,"") | Q29: =IF(AND($B29<>"",$C29<>"Target state",$C29<>"Exception",$D29="High",$E29="High"),$A29&" "&$B29,"") | R29: =IF(AND($B29<>"",$C29<>"Target state",$C29<>"Exception",$D29="Medium",$E29="Low"),$A29&" "&$B29,"") | S29: =IF(AND($B29<>"",$C29<>"Target state",$C29<>"Exception",$D29="Medium",$E29="Medium"),$A29&" "&$B29,"") | T29: =IF(AND($B29<>"",$C29<>"Target state",$C29<>"Exception",$D29="Medium",$E29="High"),$A29&" "&$B29,"") | U29: =IF(AND($B29<>"",$C29<>"Target state",$C29<>"Exception",$D29="Low",$E29="Low"),$A29&" "&$B29,"") | V29: =IF(AND($B29<>"",$C29<>"Target state",$C29<>"Exception",$D29="Low",$E29="Medium"),$A29&" "&$B29,"") | W29: =IF(AND($B29<>"",$C29<>"Target state",$C29<>"Exception",$D29="Low",$E29="High"),$A29&" "&$B29,"")
A30: ② | B30: Middleware for Aloha & Symphony POS | C30: Non-target state | F30: Non-strategic middleware between the gateway and Aloha or Symphony POS across 1.4K merchants; meaningful margin contribution of about $4.5M; sustain in KTLO per the repository | G30: =IF(OR($B30="",$D30="",$E30=""),"",IF(OR($C30="Target state",$C30="Exception"),"Out of scope",IF($D30="Low","No tranche",IF($E30="Low","Tranche 1",IF($E30="Medium","Tranche 2",IF($D30="High","Tranche 3","No tranche")))))) | O30: =IF(AND($B30<>"",$C30<>"Target state",$C30<>"Exception",$D30="High",$E30="Low"),$A30&" "&$B30,"") | P30: =IF(AND($B30<>"",$C30<>"Target state",$C30<>"Exception",$D30="High",$E30="Medium"),$A30&" "&$B30,"") | Q30: =IF(AND($B30<>"",$C30<>"Target state",$C30<>"Exception",$D30="High",$E30="High"),$A30&" "&$B30,"") | R30: =IF(AND($B30<>"",$C30<>"Target state",$C30<>"Exception",$D30="Medium",$E30="Low"),$A30&" "&$B30,"") | S30: =IF(AND($B30<>"",$C30<>"Target state",$C30<>"Exception",$D30="Medium",$E30="Medium"),$A30&" "&$B30,"") | T30: =IF(AND($B30<>"",$C30<>"Target state",$C30<>"Exception",$D30="Medium",$E30="High"),$A30&" "&$B30,"") | U30: =IF(AND($B30<>"",$C30<>"Target state",$C30<>"Exception",$D30="Low",$E30="Low"),$A30&" "&$B30,"") | V30: =IF(AND($B30<>"",$C30<>"Target state",$C30<>"Exception",$D30="Low",$E30="Medium"),$A30&" "&$B30,"") | W30: =IF(AND($B30<>"",$C30<>"Target state",$C30<>"Exception",$D30="Low",$E30="High"),$A30&" "&$B30,"")
A31: ③ | B31: Spidr | C31: Non-target state | F31: Non-strategic Windows middleware used mainly in parking across 4.3K merchants; about 10M transactions and $150M processed; effectively no dedicated cost | G31: =IF(OR($B31="",$D31="",$E31=""),"",IF(OR($C31="Target state",$C31="Exception"),"Out of scope",IF($D31="Low","No tranche",IF($E31="Low","Tranche 1",IF($E31="Medium","Tranche 2",IF($D31="High","Tranche 3","No tranche")))))) | O31: =IF(AND($B31<>"",$C31<>"Target state",$C31<>"Exception",$D31="High",$E31="Low"),$A31&" "&$B31,"") | P31: =IF(AND($B31<>"",$C31<>"Target state",$C31<>"Exception",$D31="High",$E31="Medium"),$A31&" "&$B31,"") | Q31: =IF(AND($B31<>"",$C31<>"Target state",$C31<>"Exception",$D31="High",$E31="High"),$A31&" "&$B31,"") | R31: =IF(AND($B31<>"",$C31<>"Target state",$C31<>"Exception",$D31="Medium",$E31="Low"),$A31&" "&$B31,"") | S31: =IF(AND($B31<>"",$C31<>"Target state",$C31<>"Exception",$D31="Medium",$E31="Medium"),$A31&" "&$B31,"") | T31: =IF(AND($B31<>"",$C31<>"Target state",$C31<>"Exception",$D31="Medium",$E31="High"),$A31&" "&$B31,"") | U31: =IF(AND($B31<>"",$C31<>"Target state",$C31<>"Exception",$D31="Low",$E31="Low"),$A31&" "&$B31,"") | V31: =IF(AND($B31<>"",$C31<>"Target state",$C31<>"Exception",$D31="Low",$E31="Medium"),$A31&" "&$B31,"") | W31: =IF(AND($B31<>"",$C31<>"Target state",$C31<>"Exception",$D31="Low",$E31="High"),$A31&" "&$B31,"")
A32: ④ | B32: UK-Ingenico SDK | C32: Non-target state | F32: Non-strategic SDKs fronting legacy Ingenico applications for the UK ISV market; on the decommission path | G32: =IF(OR($B32="",$D32="",$E32=""),"",IF(OR($C32="Target state",$C32="Exception"),"Out of scope",IF($D32="Low","No tranche",IF($E32="Low","Tranche 1",IF($E32="Medium","Tranche 2",IF($D32="High","Tranche 3","No tranche")))))) | O32: =IF(AND($B32<>"",$C32<>"Target state",$C32<>"Exception",$D32="High",$E32="Low"),$A32&" "&$B32,"") | P32: =IF(AND($B32<>"",$C32<>"Target state",$C32<>"Exception",$D32="High",$E32="Medium"),$A32&" "&$B32,"") | Q32: =IF(AND($B32<>"",$C32<>"Target state",$C32<>"Exception",$D32="High",$E32="High"),$A32&" "&$B32,"") | R32: =IF(AND($B32<>"",$C32<>"Target state",$C32<>"Exception",$D32="Medium",$E32="Low"),$A32&" "&$B32,"") | S32: =IF(AND($B32<>"",$C32<>"Target state",$C32<>"Exception",$D32="Medium",$E32="Medium"),$A32&" "&$B32,"") | T32: =IF(AND($B32<>"",$C32<>"Target state",$C32<>"Exception",$D32="Medium",$E32="High"),$A32&" "&$B32,"") | U32: =IF(AND($B32<>"",$C32<>"Target state",$C32<>"Exception",$D32="Low",$E32="Low"),$A32&" "&$B32,"") | V32: =IF(AND($B32<>"",$C32<>"Target state",$C32<>"Exception",$D32="Low",$E32="Medium"),$A32&" "&$B32,"") | W32: =IF(AND($B32<>"",$C32<>"Target state",$C32<>"Exception",$D32="Low",$E32="High"),$A32&" "&$B32,"")
A33: ⑤ | B33: The Phoenix Group (TPG) | C33: Non-target state | F33: Third-party terminal deployment service sourcing hardware for Omaha, EVO, Canada and CPay across about 13K devices; repository flags initial disposition Keep & Enhance — confirm with SPOC | G33: =IF(OR($B33="",$D33="",$E33=""),"",IF(OR($C33="Target state",$C33="Exception"),"Out of scope",IF($D33="Low","No tranche",IF($E33="Low","Tranche 1",IF($E33="Medium","Tranche 2",IF($D33="High","Tranche 3","No tranche")))))) | O33: =IF(AND($B33<>"",$C33<>"Target state",$C33<>"Exception",$D33="High",$E33="Low"),$A33&" "&$B33,"") | P33: =IF(AND($B33<>"",$C33<>"Target state",$C33<>"Exception",$D33="High",$E33="Medium"),$A33&" "&$B33,"") | Q33: =IF(AND($B33<>"",$C33<>"Target state",$C33<>"Exception",$D33="High",$E33="High"),$A33&" "&$B33,"") | R33: =IF(AND($B33<>"",$C33<>"Target state",$C33<>"Exception",$D33="Medium",$E33="Low"),$A33&" "&$B33,"") | S33: =IF(AND($B33<>"",$C33<>"Target state",$C33<>"Exception",$D33="Medium",$E33="Medium"),$A33&" "&$B33,"") | T33: =IF(AND($B33<>"",$C33<>"Target state",$C33<>"Exception",$D33="Medium",$E33="High"),$A33&" "&$B33,"") | U33: =IF(AND($B33<>"",$C33<>"Target state",$C33<>"Exception",$D33="Low",$E33="Low"),$A33&" "&$B33,"") | V33: =IF(AND($B33<>"",$C33<>"Target state",$C33<>"Exception",$D33="Low",$E33="Medium"),$A33&" "&$B33,"") | W33: =IF(AND($B33<>"",$C33<>"Target state",$C33<>"Exception",$D33="Low",$E33="High"),$A33&" "&$B33,"")
A34: ⑥ | B34: POS Portal | C34: Non-target state | F34: Third-party terminal deployment service for Cayan, Omaha and Broomfield with about 100K devices shipped; repository flags initial disposition Keep & Enhance — confirm with SPOC | G34: =IF(OR($B34="",$D34="",$E34=""),"",IF(OR($C34="Target state",$C34="Exception"),"Out of scope",IF($D34="Low","No tranche",IF($E34="Low","Tranche 1",IF($E34="Medium","Tranche 2",IF($D34="High","Tranche 3","No tranche")))))) | O34: =IF(AND($B34<>"",$C34<>"Target state",$C34<>"Exception",$D34="High",$E34="Low"),$A34&" "&$B34,"") | P34: =IF(AND($B34<>"",$C34<>"Target state",$C34<>"Exception",$D34="High",$E34="Medium"),$A34&" "&$B34,"") | Q34: =IF(AND($B34<>"",$C34<>"Target state",$C34<>"Exception",$D34="High",$E34="High"),$A34&" "&$B34,"") | R34: =IF(AND($B34<>"",$C34<>"Target state",$C34<>"Exception",$D34="Medium",$E34="Low"),$A34&" "&$B34,"") | S34: =IF(AND($B34<>"",$C34<>"Target state",$C34<>"Exception",$D34="Medium",$E34="Medium"),$A34&" "&$B34,"") | T34: =IF(AND($B34<>"",$C34<>"Target state",$C34<>"Exception",$D34="Medium",$E34="High"),$A34&" "&$B34,"") | U34: =IF(AND($B34<>"",$C34<>"Target state",$C34<>"Exception",$D34="Low",$E34="Low"),$A34&" "&$B34,"") | V34: =IF(AND($B34<>"",$C34<>"Target state",$C34<>"Exception",$D34="Low",$E34="Medium"),$A34&" "&$B34,"") | W34: =IF(AND($B34<>"",$C34<>"Target state",$C34<>"Exception",$D34="Low",$E34="High"),$A34&" "&$B34,"")
A35: ⑦ | B35: EVO TMS | C35: Non-target state | F35: Non-strategic eService terminal management system supporting about 100K terminals across EU and UK; repository flags initial disposition Keep & Enhance — confirm with SPOC | G35: =IF(OR($B35="",$D35="",$E35=""),"",IF(OR($C35="Target state",$C35="Exception"),"Out of scope",IF($D35="Low","No tranche",IF($E35="Low","Tranche 1",IF($E35="Medium","Tranche 2",IF($D35="High","Tranche 3","No tranche")))))) | O35: =IF(AND($B35<>"",$C35<>"Target state",$C35<>"Exception",$D35="High",$E35="Low"),$A35&" "&$B35,"") | P35: =IF(AND($B35<>"",$C35<>"Target state",$C35<>"Exception",$D35="High",$E35="Medium"),$A35&" "&$B35,"") | Q35: =IF(AND($B35<>"",$C35<>"Target state",$C35<>"Exception",$D35="High",$E35="High"),$A35&" "&$B35,"") | R35: =IF(AND($B35<>"",$C35<>"Target state",$C35<>"Exception",$D35="Medium",$E35="Low"),$A35&" "&$B35,"") | S35: =IF(AND($B35<>"",$C35<>"Target state",$C35<>"Exception",$D35="Medium",$E35="Medium"),$A35&" "&$B35,"") | T35: =IF(AND($B35<>"",$C35<>"Target state",$C35<>"Exception",$D35="Medium",$E35="High"),$A35&" "&$B35,"") | U35: =IF(AND($B35<>"",$C35<>"Target state",$C35<>"Exception",$D35="Low",$E35="Low"),$A35&" "&$B35,"") | V35: =IF(AND($B35<>"",$C35<>"Target state",$C35<>"Exception",$D35="Low",$E35="Medium"),$A35&" "&$B35,"") | W35: =IF(AND($B35<>"",$C35<>"Target state",$C35<>"Exception",$D35="Low",$E35="High"),$A35&" "&$B35,"")
A36: ⑧ | B36: GPE TMS | C36: Non-target state | F36: Non-strategic GPE terminal management system covering about 91K terminals, tightly integrated with boarding; around $480K in yearly cost; repository flags initial disposition Keep & Enhance — confirm with SPOC | G36: =IF(OR($B36="",$D36="",$E36=""),"",IF(OR($C36="Target state",$C36="Exception"),"Out of scope",IF($D36="Low","No tranche",IF($E36="Low","Tranche 1",IF($E36="Medium","Tranche 2",IF($D36="High","Tranche 3","No tranche")))))) | O36: =IF(AND($B36<>"",$C36<>"Target state",$C36<>"Exception",$D36="High",$E36="Low"),$A36&" "&$B36,"") | P36: =IF(AND($B36<>"",$C36<>"Target state",$C36<>"Exception",$D36="High",$E36="Medium"),$A36&" "&$B36,"") | Q36: =IF(AND($B36<>"",$C36<>"Target state",$C36<>"Exception",$D36="High",$E36="High"),$A36&" "&$B36,"") | R36: =IF(AND($B36<>"",$C36<>"Target state",$C36<>"Exception",$D36="Medium",$E36="Low"),$A36&" "&$B36,"") | S36: =IF(AND($B36<>"",$C36<>"Target state",$C36<>"Exception",$D36="Medium",$E36="Medium"),$A36&" "&$B36,"") | T36: =IF(AND($B36<>"",$C36<>"Target state",$C36<>"Exception",$D36="Medium",$E36="High"),$A36&" "&$B36,"") | U36: =IF(AND($B36<>"",$C36<>"Target state",$C36<>"Exception",$D36="Low",$E36="Low"),$A36&" "&$B36,"") | V36: =IF(AND($B36<>"",$C36<>"Target state",$C36<>"Exception",$D36="Low",$E36="Medium"),$A36&" "&$B36,"") | W36: =IF(AND($B36<>"",$C36<>"Target state",$C36<>"Exception",$D36="Low",$E36="High"),$A36&" "&$B36,"")
A37: ⑨ | B37: Terminal Management Services (TMS) | C37: Non-target state | F37: Non-strategic terminal management supporting Genius across about 91K MIDs; repository flags initial disposition Keep & Enhance — confirm with SPOC | G37: =IF(OR($B37="",$D37="",$E37=""),"",IF(OR($C37="Target state",$C37="Exception"),"Out of scope",IF($D37="Low","No tranche",IF($E37="Low","Tranche 1",IF($E37="Medium","Tranche 2",IF($D37="High","Tranche 3","No tranche")))))) | J37: Medium | K37: ="Tranche 1"&CHAR(10)&_xlfn.TEXTJOIN(CHAR(10),TRUE,R$29:R$51) | L37: ="Tranche 2"&CHAR(10)&_xlfn.TEXTJOIN(CHAR(10),TRUE,S$29:S$51) | M37: =_xlfn.TEXTJOIN(CHAR(10),TRUE,T$29:T$51) | O37: =IF(AND($B37<>"",$C37<>"Target state",$C37<>"Exception",$D37="High",$E37="Low"),$A37&" "&$B37,"") | P37: =IF(AND($B37<>"",$C37<>"Target state",$C37<>"Exception",$D37="High",$E37="Medium"),$A37&" "&$B37,"") | Q37: =IF(AND($B37<>"",$C37<>"Target state",$C37<>"Exception",$D37="High",$E37="High"),$A37&" "&$B37,"") | R37: =IF(AND($B37<>"",$C37<>"Target state",$C37<>"Exception",$D37="Medium",$E37="Low"),$A37&" "&$B37,"") | S37: =IF(AND($B37<>"",$C37<>"Target state",$C37<>"Exception",$D37="Medium",$E37="Medium"),$A37&" "&$B37,"") | T37: =IF(AND($B37<>"",$C37<>"Target state",$C37<>"Exception",$D37="Medium",$E37="High"),$A37&" "&$B37,"") | U37: =IF(AND($B37<>"",$C37<>"Target state",$C37<>"Exception",$D37="Low",$E37="Low"),$A37&" "&$B37,"") | V37: =IF(AND($B37<>"",$C37<>"Target state",$C37<>"Exception",$D37="Low",$E37="Medium"),$A37&" "&$B37,"") | W37: =IF(AND($B37<>"",$C37<>"Target state",$C37<>"Exception",$D37="Low",$E37="High"),$A37&" "&$B37,"")
A38: ⑩ | B38: Aurora TMS | C38: Non-target state | F38: Non-strategic LATAM platform administering remote terminal application loads for POS and iAcepta across 93K MIDs; about 166M transactions and $10.6B processed; around $180K in yearly cost | G38: =IF(OR($B38="",$D38="",$E38=""),"",IF(OR($C38="Target state",$C38="Exception"),"Out of scope",IF($D38="Low","No tranche",IF($E38="Low","Tranche 1",IF($E38="Medium","Tranche 2",IF($D38="High","Tranche 3","No tranche")))))) | O38: =IF(AND($B38<>"",$C38<>"Target state",$C38<>"Exception",$D38="High",$E38="Low"),$A38&" "&$B38,"") | P38: =IF(AND($B38<>"",$C38<>"Target state",$C38<>"Exception",$D38="High",$E38="Medium"),$A38&" "&$B38,"") | Q38: =IF(AND($B38<>"",$C38<>"Target state",$C38<>"Exception",$D38="High",$E38="High"),$A38&" "&$B38,"") | R38: =IF(AND($B38<>"",$C38<>"Target state",$C38<>"Exception",$D38="Medium",$E38="Low"),$A38&" "&$B38,"") | S38: =IF(AND($B38<>"",$C38<>"Target state",$C38<>"Exception",$D38="Medium",$E38="Medium"),$A38&" "&$B38,"") | T38: =IF(AND($B38<>"",$C38<>"Target state",$C38<>"Exception",$D38="Medium",$E38="High"),$A38&" "&$B38,"") | U38: =IF(AND($B38<>"",$C38<>"Target state",$C38<>"Exception",$D38="Low",$E38="Low"),$A38&" "&$B38,"") | V38: =IF(AND($B38<>"",$C38<>"Target state",$C38<>"Exception",$D38="Low",$E38="Medium"),$A38&" "&$B38,"") | W38: =IF(AND($B38<>"",$C38<>"Target state",$C38<>"Exception",$D38="Low",$E38="High"),$A38&" "&$B38,"")
A39: ⑪ | B39: WebTops | C39: Non-target state | F39: Non-strategic Heartland terminal configuration platform across about 100K MIDs; around $1M in yearly cost; repository flags initial disposition Keep & Enhance — confirm with SPOC | G39: =IF(OR($B39="",$D39="",$E39=""),"",IF(OR($C39="Target state",$C39="Exception"),"Out of scope",IF($D39="Low","No tranche",IF($E39="Low","Tranche 1",IF($E39="Medium","Tranche 2",IF($D39="High","Tranche 3","No tranche")))))) | O39: =IF(AND($B39<>"",$C39<>"Target state",$C39<>"Exception",$D39="High",$E39="Low"),$A39&" "&$B39,"") | P39: =IF(AND($B39<>"",$C39<>"Target state",$C39<>"Exception",$D39="High",$E39="Medium"),$A39&" "&$B39,"") | Q39: =IF(AND($B39<>"",$C39<>"Target state",$C39<>"Exception",$D39="High",$E39="High"),$A39&" "&$B39,"") | R39: =IF(AND($B39<>"",$C39<>"Target state",$C39<>"Exception",$D39="Medium",$E39="Low"),$A39&" "&$B39,"") | S39: =IF(AND($B39<>"",$C39<>"Target state",$C39<>"Exception",$D39="Medium",$E39="Medium"),$A39&" "&$B39,"") | T39: =IF(AND($B39<>"",$C39<>"Target state",$C39<>"Exception",$D39="Medium",$E39="High"),$A39&" "&$B39,"") | U39: =IF(AND($B39<>"",$C39<>"Target state",$C39<>"Exception",$D39="Low",$E39="Low"),$A39&" "&$B39,"") | V39: =IF(AND($B39<>"",$C39<>"Target state",$C39<>"Exception",$D39="Low",$E39="Medium"),$A39&" "&$B39,"") | W39: =IF(AND($B39<>"",$C39<>"Target state",$C39<>"Exception",$D39="Low",$E39="High"),$A39&" "&$B39,"")
A40: ⑫ | B40: One Touch | C40: Non-target state | F40: Non-strategic internal UI managing terminal download files and parameters; no dedicated cost; on the decommission path | G40: =IF(OR($B40="",$D40="",$E40=""),"",IF(OR($C40="Target state",$C40="Exception"),"Out of scope",IF($D40="Low","No tranche",IF($E40="Low","Tranche 1",IF($E40="Medium","Tranche 2",IF($D40="High","Tranche 3","No tranche")))))) | O40: =IF(AND($B40<>"",$C40<>"Target state",$C40<>"Exception",$D40="High",$E40="Low"),$A40&" "&$B40,"") | P40: =IF(AND($B40<>"",$C40<>"Target state",$C40<>"Exception",$D40="High",$E40="Medium"),$A40&" "&$B40,"") | Q40: =IF(AND($B40<>"",$C40<>"Target state",$C40<>"Exception",$D40="High",$E40="High"),$A40&" "&$B40,"") | R40: =IF(AND($B40<>"",$C40<>"Target state",$C40<>"Exception",$D40="Medium",$E40="Low"),$A40&" "&$B40,"") | S40: =IF(AND($B40<>"",$C40<>"Target state",$C40<>"Exception",$D40="Medium",$E40="Medium"),$A40&" "&$B40,"") | T40: =IF(AND($B40<>"",$C40<>"Target state",$C40<>"Exception",$D40="Medium",$E40="High"),$A40&" "&$B40,"") | U40: =IF(AND($B40<>"",$C40<>"Target state",$C40<>"Exception",$D40="Low",$E40="Low"),$A40&" "&$B40,"") | V40: =IF(AND($B40<>"",$C40<>"Target state",$C40<>"Exception",$D40="Low",$E40="Medium"),$A40&" "&$B40,"") | W40: =IF(AND($B40<>"",$C40<>"Target state",$C40<>"Exception",$D40="Low",$E40="High"),$A40&" "&$B40,"")
A41: ⑬ | B41: AIMS | C41: Non-target state | F41: Non-strategic legacy Global US deployment system with about 190 users; around $130K in yearly cost; on the decommission path | G41: =IF(OR($B41="",$D41="",$E41=""),"",IF(OR($C41="Target state",$C41="Exception"),"Out of scope",IF($D41="Low","No tranche",IF($E41="Low","Tranche 1",IF($E41="Medium","Tranche 2",IF($D41="High","Tranche 3","No tranche")))))) | O41: =IF(AND($B41<>"",$C41<>"Target state",$C41<>"Exception",$D41="High",$E41="Low"),$A41&" "&$B41,"") | P41: =IF(AND($B41<>"",$C41<>"Target state",$C41<>"Exception",$D41="High",$E41="Medium"),$A41&" "&$B41,"") | Q41: =IF(AND($B41<>"",$C41<>"Target state",$C41<>"Exception",$D41="High",$E41="High"),$A41&" "&$B41,"") | R41: =IF(AND($B41<>"",$C41<>"Target state",$C41<>"Exception",$D41="Medium",$E41="Low"),$A41&" "&$B41,"") | S41: =IF(AND($B41<>"",$C41<>"Target state",$C41<>"Exception",$D41="Medium",$E41="Medium"),$A41&" "&$B41,"") | T41: =IF(AND($B41<>"",$C41<>"Target state",$C41<>"Exception",$D41="Medium",$E41="High"),$A41&" "&$B41,"") | U41: =IF(AND($B41<>"",$C41<>"Target state",$C41<>"Exception",$D41="Low",$E41="Low"),$A41&" "&$B41,"") | V41: =IF(AND($B41<>"",$C41<>"Target state",$C41<>"Exception",$D41="Low",$E41="Medium"),$A41&" "&$B41,"") | W41: =IF(AND($B41<>"",$C41<>"Target state",$C41<>"Exception",$D41="Low",$E41="High"),$A41&" "&$B41,"")
A42: ⑭ | B42: Deployment Manager | C42: Non-target state | F42: Non-strategic deployment web API used by ShipExec with warehouse printing services; modest annual cost; migration path agreed | G42: =IF(OR($B42="",$D42="",$E42=""),"",IF(OR($C42="Target state",$C42="Exception"),"Out of scope",IF($D42="Low","No tranche",IF($E42="Low","Tranche 1",IF($E42="Medium","Tranche 2",IF($D42="High","Tranche 3","No tranche")))))) | O42: =IF(AND($B42<>"",$C42<>"Target state",$C42<>"Exception",$D42="High",$E42="Low"),$A42&" "&$B42,"") | P42: =IF(AND($B42<>"",$C42<>"Target state",$C42<>"Exception",$D42="High",$E42="Medium"),$A42&" "&$B42,"") | Q42: =IF(AND($B42<>"",$C42<>"Target state",$C42<>"Exception",$D42="High",$E42="High"),$A42&" "&$B42,"") | R42: =IF(AND($B42<>"",$C42<>"Target state",$C42<>"Exception",$D42="Medium",$E42="Low"),$A42&" "&$B42,"") | S42: =IF(AND($B42<>"",$C42<>"Target state",$C42<>"Exception",$D42="Medium",$E42="Medium"),$A42&" "&$B42,"") | T42: =IF(AND($B42<>"",$C42<>"Target state",$C42<>"Exception",$D42="Medium",$E42="High"),$A42&" "&$B42,"") | U42: =IF(AND($B42<>"",$C42<>"Target state",$C42<>"Exception",$D42="Low",$E42="Low"),$A42&" "&$B42,"") | V42: =IF(AND($B42<>"",$C42<>"Target state",$C42<>"Exception",$D42="Low",$E42="Medium"),$A42&" "&$B42,"") | W42: =IF(AND($B42<>"",$C42<>"Target state",$C42<>"Exception",$D42="Low",$E42="High"),$A42&" "&$B42,"")
A43: ⑮ | B43: Inventory Manager | C43: Non-target state | F43: Non-strategic Canadian system tracking terminal physical locations with about 160 users; around $130K in yearly cost; repository flags initial disposition Keep & Enhance — confirm with SPOC | G43: =IF(OR($B43="",$D43="",$E43=""),"",IF(OR($C43="Target state",$C43="Exception"),"Out of scope",IF($D43="Low","No tranche",IF($E43="Low","Tranche 1",IF($E43="Medium","Tranche 2",IF($D43="High","Tranche 3","No tranche")))))) | O43: =IF(AND($B43<>"",$C43<>"Target state",$C43<>"Exception",$D43="High",$E43="Low"),$A43&" "&$B43,"") | P43: =IF(AND($B43<>"",$C43<>"Target state",$C43<>"Exception",$D43="High",$E43="Medium"),$A43&" "&$B43,"") | Q43: =IF(AND($B43<>"",$C43<>"Target state",$C43<>"Exception",$D43="High",$E43="High"),$A43&" "&$B43,"") | R43: =IF(AND($B43<>"",$C43<>"Target state",$C43<>"Exception",$D43="Medium",$E43="Low"),$A43&" "&$B43,"") | S43: =IF(AND($B43<>"",$C43<>"Target state",$C43<>"Exception",$D43="Medium",$E43="Medium"),$A43&" "&$B43,"") | T43: =IF(AND($B43<>"",$C43<>"Target state",$C43<>"Exception",$D43="Medium",$E43="High"),$A43&" "&$B43,"") | U43: =IF(AND($B43<>"",$C43<>"Target state",$C43<>"Exception",$D43="Low",$E43="Low"),$A43&" "&$B43,"") | V43: =IF(AND($B43<>"",$C43<>"Target state",$C43<>"Exception",$D43="Low",$E43="Medium"),$A43&" "&$B43,"") | W43: =IF(AND($B43<>"",$C43<>"Target state",$C43<>"Exception",$D43="Low",$E43="High"),$A43&" "&$B43,"")
A44: ⑯ | B44: VeriCentre (Canada) | C44: Non-target state | F44: Non-strategic Canadian instance of the Verifone terminal management system tracking about 111K terminal IDs; sustain in KTLO per the repository | G44: =IF(OR($B44="",$D44="",$E44=""),"",IF(OR($C44="Target state",$C44="Exception"),"Out of scope",IF($D44="Low","No tranche",IF($E44="Low","Tranche 1",IF($E44="Medium","Tranche 2",IF($D44="High","Tranche 3","No tranche")))))) | O44: =IF(AND($B44<>"",$C44<>"Target state",$C44<>"Exception",$D44="High",$E44="Low"),$A44&" "&$B44,"") | P44: =IF(AND($B44<>"",$C44<>"Target state",$C44<>"Exception",$D44="High",$E44="Medium"),$A44&" "&$B44,"") | Q44: =IF(AND($B44<>"",$C44<>"Target state",$C44<>"Exception",$D44="High",$E44="High"),$A44&" "&$B44,"") | R44: =IF(AND($B44<>"",$C44<>"Target state",$C44<>"Exception",$D44="Medium",$E44="Low"),$A44&" "&$B44,"") | S44: =IF(AND($B44<>"",$C44<>"Target state",$C44<>"Exception",$D44="Medium",$E44="Medium"),$A44&" "&$B44,"") | T44: =IF(AND($B44<>"",$C44<>"Target state",$C44<>"Exception",$D44="Medium",$E44="High"),$A44&" "&$B44,"") | U44: =IF(AND($B44<>"",$C44<>"Target state",$C44<>"Exception",$D44="Low",$E44="Low"),$A44&" "&$B44,"") | V44: =IF(AND($B44<>"",$C44<>"Target state",$C44<>"Exception",$D44="Low",$E44="Medium"),$A44&" "&$B44,"") | W44: =IF(AND($B44<>"",$C44<>"Target state",$C44<>"Exception",$D44="Low",$E44="High"),$A44&" "&$B44,"")
A45: ⑰ | B45: GPC Injection System | C45: Non-target state | F45: Non-strategic key injection system using Verifone secure modules for Canadian hosts and gateways; sustain in KTLO per the repository | G45: =IF(OR($B45="",$D45="",$E45=""),"",IF(OR($C45="Target state",$C45="Exception"),"Out of scope",IF($D45="Low","No tranche",IF($E45="Low","Tranche 1",IF($E45="Medium","Tranche 2",IF($D45="High","Tranche 3","No tranche")))))) | J45: Low | K45: =_xlfn.TEXTJOIN(CHAR(10),TRUE,U$29:U$51) | L45: =_xlfn.TEXTJOIN(CHAR(10),TRUE,V$29:V$51) | M45: =_xlfn.TEXTJOIN(CHAR(10),TRUE,W$29:W$51) | O45: =IF(AND($B45<>"",$C45<>"Target state",$C45<>"Exception",$D45="High",$E45="Low"),$A45&" "&$B45,"") | P45: =IF(AND($B45<>"",$C45<>"Target state",$C45<>"Exception",$D45="High",$E45="Medium"),$A45&" "&$B45,"") | Q45: =IF(AND($B45<>"",$C45<>"Target state",$C45<>"Exception",$D45="High",$E45="High"),$A45&" "&$B45,"") | R45: =IF(AND($B45<>"",$C45<>"Target state",$C45<>"Exception",$D45="Medium",$E45="Low"),$A45&" "&$B45,"") | S45: =IF(AND($B45<>"",$C45<>"Target state",$C45<>"Exception",$D45="Medium",$E45="Medium"),$A45&" "&$B45,"") | T45: =IF(AND($B45<>"",$C45<>"Target state",$C45<>"Exception",$D45="Medium",$E45="High"),$A45&" "&$B45,"") | U45: =IF(AND($B45<>"",$C45<>"Target state",$C45<>"Exception",$D45="Low",$E45="Low"),$A45&" "&$B45,"") | V45: =IF(AND($B45<>"",$C45<>"Target state",$C45<>"Exception",$D45="Low",$E45="Medium"),$A45&" "&$B45,"") | W45: =IF(AND($B45<>"",$C45<>"Target state",$C45<>"Exception",$D45="Low",$E45="High"),$A45&" "&$B45,"")
A46: ⑱ | B46: Logistics | C46: Non-target state | F46: Non-strategic Heartland equipment tracking system with about 110 users; modest annual cost; migration path agreed | G46: =IF(OR($B46="",$D46="",$E46=""),"",IF(OR($C46="Target state",$C46="Exception"),"Out of scope",IF($D46="Low","No tranche",IF($E46="Low","Tranche 1",IF($E46="Medium","Tranche 2",IF($D46="High","Tranche 3","No tranche")))))) | O46: =IF(AND($B46<>"",$C46<>"Target state",$C46<>"Exception",$D46="High",$E46="Low"),$A46&" "&$B46,"") | P46: =IF(AND($B46<>"",$C46<>"Target state",$C46<>"Exception",$D46="High",$E46="Medium"),$A46&" "&$B46,"") | Q46: =IF(AND($B46<>"",$C46<>"Target state",$C46<>"Exception",$D46="High",$E46="High"),$A46&" "&$B46,"") | R46: =IF(AND($B46<>"",$C46<>"Target state",$C46<>"Exception",$D46="Medium",$E46="Low"),$A46&" "&$B46,"") | S46: =IF(AND($B46<>"",$C46<>"Target state",$C46<>"Exception",$D46="Medium",$E46="Medium"),$A46&" "&$B46,"") | T46: =IF(AND($B46<>"",$C46<>"Target state",$C46<>"Exception",$D46="Medium",$E46="High"),$A46&" "&$B46,"") | U46: =IF(AND($B46<>"",$C46<>"Target state",$C46<>"Exception",$D46="Low",$E46="Low"),$A46&" "&$B46,"") | V46: =IF(AND($B46<>"",$C46<>"Target state",$C46<>"Exception",$D46="Low",$E46="Medium"),$A46&" "&$B46,"") | W46: =IF(AND($B46<>"",$C46<>"Target state",$C46<>"Exception",$D46="Low",$E46="High"),$A46&" "&$B46,"")
A47: ⑲ | B47: Order Management System | C47: Non-target state | F47: Non-strategic merchant equipment ordering and configuration system with about 230 users; modest annual cost; migration path agreed | G47: =IF(OR($B47="",$D47="",$E47=""),"",IF(OR($C47="Target state",$C47="Exception"),"Out of scope",IF($D47="Low","No tranche",IF($E47="Low","Tranche 1",IF($E47="Medium","Tranche 2",IF($D47="High","Tranche 3","No tranche")))))) | O47: =IF(AND($B47<>"",$C47<>"Target state",$C47<>"Exception",$D47="High",$E47="Low"),$A47&" "&$B47,"") | P47: =IF(AND($B47<>"",$C47<>"Target state",$C47<>"Exception",$D47="High",$E47="Medium"),$A47&" "&$B47,"") | Q47: =IF(AND($B47<>"",$C47<>"Target state",$C47<>"Exception",$D47="High",$E47="High"),$A47&" "&$B47,"") | R47: =IF(AND($B47<>"",$C47<>"Target state",$C47<>"Exception",$D47="Medium",$E47="Low"),$A47&" "&$B47,"") | S47: =IF(AND($B47<>"",$C47<>"Target state",$C47<>"Exception",$D47="Medium",$E47="Medium"),$A47&" "&$B47,"") | T47: =IF(AND($B47<>"",$C47<>"Target state",$C47<>"Exception",$D47="Medium",$E47="High"),$A47&" "&$B47,"") | U47: =IF(AND($B47<>"",$C47<>"Target state",$C47<>"Exception",$D47="Low",$E47="Low"),$A47&" "&$B47,"") | V47: =IF(AND($B47<>"",$C47<>"Target state",$C47<>"Exception",$D47="Low",$E47="Medium"),$A47&" "&$B47,"") | W47: =IF(AND($B47<>"",$C47<>"Target state",$C47<>"Exception",$D47="Low",$E47="High"),$A47&" "&$B47,"")
A48: ⑳ | G48: =IF(OR($B48="",$D48="",$E48=""),"",IF(OR($C48="Target state",$C48="Exception"),"Out of scope",IF($D48="Low","No tranche",IF($E48="Low","Tranche 1",IF($E48="Medium","Tranche 2",IF($D48="High","Tranche 3","No tranche")))))) | O48: =IF(AND($B48<>"",$C48<>"Target state",$C48<>"Exception",$D48="High",$E48="Low"),$A48&" "&$B48,"") | P48: =IF(AND($B48<>"",$C48<>"Target state",$C48<>"Exception",$D48="High",$E48="Medium"),$A48&" "&$B48,"") | Q48: =IF(AND($B48<>"",$C48<>"Target state",$C48<>"Exception",$D48="High",$E48="High"),$A48&" "&$B48,"") | R48: =IF(AND($B48<>"",$C48<>"Target state",$C48<>"Exception",$D48="Medium",$E48="Low"),$A48&" "&$B48,"") | S48: =IF(AND($B48<>"",$C48<>"Target state",$C48<>"Exception",$D48="Medium",$E48="Medium"),$A48&" "&$B48,"") | T48: =IF(AND($B48<>"",$C48<>"Target state",$C48<>"Exception",$D48="Medium",$E48="High"),$A48&" "&$B48,"") | U48: =IF(AND($B48<>"",$C48<>"Target state",$C48<>"Exception",$D48="Low",$E48="Low"),$A48&" "&$B48,"") | V48: =IF(AND($B48<>"",$C48<>"Target state",$C48<>"Exception",$D48="Low",$E48="Medium"),$A48&" "&$B48,"") | W48: =IF(AND($B48<>"",$C48<>"Target state",$C48<>"Exception",$D48="Low",$E48="High"),$A48&" "&$B48,"")
A49: ㉑ | G49: =IF(OR($B49="",$D49="",$E49=""),"",IF(OR($C49="Target state",$C49="Exception"),"Out of scope",IF($D49="Low","No tranche",IF($E49="Low","Tranche 1",IF($E49="Medium","Tranche 2",IF($D49="High","Tranche 3","No tranche")))))) | O49: =IF(AND($B49<>"",$C49<>"Target state",$C49<>"Exception",$D49="High",$E49="Low"),$A49&" "&$B49,"") | P49: =IF(AND($B49<>"",$C49<>"Target state",$C49<>"Exception",$D49="High",$E49="Medium"),$A49&" "&$B49,"") | Q49: =IF(AND($B49<>"",$C49<>"Target state",$C49<>"Exception",$D49="High",$E49="High"),$A49&" "&$B49,"") | R49: =IF(AND($B49<>"",$C49<>"Target state",$C49<>"Exception",$D49="Medium",$E49="Low"),$A49&" "&$B49,"") | S49: =IF(AND($B49<>"",$C49<>"Target state",$C49<>"Exception",$D49="Medium",$E49="Medium"),$A49&" "&$B49,"") | T49: =IF(AND($B49<>"",$C49<>"Target state",$C49<>"Exception",$D49="Medium",$E49="High"),$A49&" "&$B49,"") | U49: =IF(AND($B49<>"",$C49<>"Target state",$C49<>"Exception",$D49="Low",$E49="Low"),$A49&" "&$B49,"") | V49: =IF(AND($B49<>"",$C49<>"Target state",$C49<>"Exception",$D49="Low",$E49="Medium"),$A49&" "&$B49,"") | W49: =IF(AND($B49<>"",$C49<>"Target state",$C49<>"Exception",$D49="Low",$E49="High"),$A49&" "&$B49,"")
A50: ㉒ | G50: =IF(OR($B50="",$D50="",$E50=""),"",IF(OR($C50="Target state",$C50="Exception"),"Out of scope",IF($D50="Low","No tranche",IF($E50="Low","Tranche 1",IF($E50="Medium","Tranche 2",IF($D50="High","Tranche 3","No tranche")))))) | O50: =IF(AND($B50<>"",$C50<>"Target state",$C50<>"Exception",$D50="High",$E50="Low"),$A50&" "&$B50,"") | P50: =IF(AND($B50<>"",$C50<>"Target state",$C50<>"Exception",$D50="High",$E50="Medium"),$A50&" "&$B50,"") | Q50: =IF(AND($B50<>"",$C50<>"Target state",$C50<>"Exception",$D50="High",$E50="High"),$A50&" "&$B50,"") | R50: =IF(AND($B50<>"",$C50<>"Target state",$C50<>"Exception",$D50="Medium",$E50="Low"),$A50&" "&$B50,"") | S50: =IF(AND($B50<>"",$C50<>"Target state",$C50<>"Exception",$D50="Medium",$E50="Medium"),$A50&" "&$B50,"") | T50: =IF(AND($B50<>"",$C50<>"Target state",$C50<>"Exception",$D50="Medium",$E50="High"),$A50&" "&$B50,"") | U50: =IF(AND($B50<>"",$C50<>"Target state",$C50<>"Exception",$D50="Low",$E50="Low"),$A50&" "&$B50,"") | V50: =IF(AND($B50<>"",$C50<>"Target state",$C50<>"Exception",$D50="Low",$E50="Medium"),$A50&" "&$B50,"") | W50: =IF(AND($B50<>"",$C50<>"Target state",$C50<>"Exception",$D50="Low",$E50="High"),$A50&" "&$B50,"")
A51: ㉓ | G51: =IF(OR($B51="",$D51="",$E51=""),"",IF(OR($C51="Target state",$C51="Exception"),"Out of scope",IF($D51="Low","No tranche",IF($E51="Low","Tranche 1",IF($E51="Medium","Tranche 2",IF($D51="High","Tranche 3","No tranche")))))) | O51: =IF(AND($B51<>"",$C51<>"Target state",$C51<>"Exception",$D51="High",$E51="Low"),$A51&" "&$B51,"") | P51: =IF(AND($B51<>"",$C51<>"Target state",$C51<>"Exception",$D51="High",$E51="Medium"),$A51&" "&$B51,"") | Q51: =IF(AND($B51<>"",$C51<>"Target state",$C51<>"Exception",$D51="High",$E51="High"),$A51&" "&$B51,"") | R51: =IF(AND($B51<>"",$C51<>"Target state",$C51<>"Exception",$D51="Medium",$E51="Low"),$A51&" "&$B51,"") | S51: =IF(AND($B51<>"",$C51<>"Target state",$C51<>"Exception",$D51="Medium",$E51="Medium"),$A51&" "&$B51,"") | T51: =IF(AND($B51<>"",$C51<>"Target state",$C51<>"Exception",$D51="Medium",$E51="High"),$A51&" "&$B51,"") | U51: =IF(AND($B51<>"",$C51<>"Target state",$C51<>"Exception",$D51="Low",$E51="Low"),$A51&" "&$B51,"") | V51: =IF(AND($B51<>"",$C51<>"Target state",$C51<>"Exception",$D51="Low",$E51="Medium"),$A51&" "&$B51,"") | W51: =IF(AND($B51<>"",$C51<>"Target state",$C51<>"Exception",$D51="Low",$E51="High"),$A51&" "&$B51,"")
K52: Complexity
A56: Developer Experience | G56: =HYPERLINK("#'Single-in'!A4","▲ tracker") | K56: Assessment Outcome
A57: # | B57: Platform | C57: State | D57: Imperative to exit | E57: Exit complexity | F57: Supporting facts | G57: Tranche (auto) | K57: Low | L57: Medium | M57: High
A58: ① | B58: GPI Developer Portal | C58: Non-target state | F58: Non-strategic developer portal covering only GPI platforms with documentation and no sandbox; migration path agreed | G58: =IF(OR($B58="",$D58="",$E58=""),"",IF(OR($C58="Target state",$C58="Exception"),"Out of scope",IF($D58="Low","No tranche",IF($E58="Low","Tranche 1",IF($E58="Medium","Tranche 2",IF($D58="High","Tranche 3","No tranche")))))) | I58: Benefits | J58: High | K58: ="Tranche 1"&CHAR(10)&_xlfn.TEXTJOIN(CHAR(10),TRUE,O$58:O$67) | L58: ="Tranche 2"&CHAR(10)&_xlfn.TEXTJOIN(CHAR(10),TRUE,P$58:P$67) | M58: ="Tranche 3"&CHAR(10)&_xlfn.TEXTJOIN(CHAR(10),TRUE,Q$58:Q$67) | O58: =IF(AND($B58<>"",$C58<>"Target state",$C58<>"Exception",$D58="High",$E58="Low"),$A58&" "&$B58,"") | P58: =IF(AND($B58<>"",$C58<>"Target state",$C58<>"Exception",$D58="High",$E58="Medium"),$A58&" "&$B58,"") | Q58: =IF(AND($B58<>"",$C58<>"Target state",$C58<>"Exception",$D58="High",$E58="High"),$A58&" "&$B58,"") | R58: =IF(AND($B58<>"",$C58<>"Target state",$C58<>"Exception",$D58="Medium",$E58="Low"),$A58&" "&$B58,"") | S58: =IF(AND($B58<>"",$C58<>"Target state",$C58<>"Exception",$D58="Medium",$E58="Medium"),$A58&" "&$B58,"") | T58: =IF(AND($B58<>"",$C58<>"Target state",$C58<>"Exception",$D58="Medium",$E58="High"),$A58&" "&$B58,"") | U58: =IF(AND($B58<>"",$C58<>"Target state",$C58<>"Exception",$D58="Low",$E58="Low"),$A58&" "&$B58,"") | V58: =IF(AND($B58<>"",$C58<>"Target state",$C58<>"Exception",$D58="Low",$E58="Medium"),$A58&" "&$B58,"") | W58: =IF(AND($B58<>"",$C58<>"Target state",$C58<>"Exception",$D58="Low",$E58="High"),$A58&" "&$B58,"")
A59: ② | B59: Heartland Developer Portal | C59: Non-target state | F59: Non-strategic developer portal for credentials, SDK libraries and documentation with about 18.5K users; repository flags Further Input — confirm with SPOC | G59: =IF(OR($B59="",$D59="",$E59=""),"",IF(OR($C59="Target state",$C59="Exception"),"Out of scope",IF($D59="Low","No tranche",IF($E59="Low","Tranche 1",IF($E59="Medium","Tranche 2",IF($D59="High","Tranche 3","No tranche")))))) | O59: =IF(AND($B59<>"",$C59<>"Target state",$C59<>"Exception",$D59="High",$E59="Low"),$A59&" "&$B59,"") | P59: =IF(AND($B59<>"",$C59<>"Target state",$C59<>"Exception",$D59="High",$E59="Medium"),$A59&" "&$B59,"") | Q59: =IF(AND($B59<>"",$C59<>"Target state",$C59<>"Exception",$D59="High",$E59="High"),$A59&" "&$B59,"") | R59: =IF(AND($B59<>"",$C59<>"Target state",$C59<>"Exception",$D59="Medium",$E59="Low"),$A59&" "&$B59,"") | S59: =IF(AND($B59<>"",$C59<>"Target state",$C59<>"Exception",$D59="Medium",$E59="Medium"),$A59&" "&$B59,"") | T59: =IF(AND($B59<>"",$C59<>"Target state",$C59<>"Exception",$D59="Medium",$E59="High"),$A59&" "&$B59,"") | U59: =IF(AND($B59<>"",$C59<>"Target state",$C59<>"Exception",$D59="Low",$E59="Low"),$A59&" "&$B59,"") | V59: =IF(AND($B59<>"",$C59<>"Target state",$C59<>"Exception",$D59="Low",$E59="Medium"),$A59&" "&$B59,"") | W59: =IF(AND($B59<>"",$C59<>"Target state",$C59<>"Exception",$D59="Low",$E59="High"),$A59&" "&$B59,"")
A60: ③ | B60: TSYS Developer Portal | C60: Non-target state | F60: Developer portal through which issuing clients and partners access documentation and APIs; repository flags initial disposition Keep & Enhance — confirm with SPOC | G60: =IF(OR($B60="",$D60="",$E60=""),"",IF(OR($C60="Target state",$C60="Exception"),"Out of scope",IF($D60="Low","No tranche",IF($E60="Low","Tranche 1",IF($E60="Medium","Tranche 2",IF($D60="High","Tranche 3","No tranche")))))) | O60: =IF(AND($B60<>"",$C60<>"Target state",$C60<>"Exception",$D60="High",$E60="Low"),$A60&" "&$B60,"") | P60: =IF(AND($B60<>"",$C60<>"Target state",$C60<>"Exception",$D60="High",$E60="Medium"),$A60&" "&$B60,"") | Q60: =IF(AND($B60<>"",$C60<>"Target state",$C60<>"Exception",$D60="High",$E60="High"),$A60&" "&$B60,"") | R60: =IF(AND($B60<>"",$C60<>"Target state",$C60<>"Exception",$D60="Medium",$E60="Low"),$A60&" "&$B60,"") | S60: =IF(AND($B60<>"",$C60<>"Target state",$C60<>"Exception",$D60="Medium",$E60="Medium"),$A60&" "&$B60,"") | T60: =IF(AND($B60<>"",$C60<>"Target state",$C60<>"Exception",$D60="Medium",$E60="High"),$A60&" "&$B60,"") | U60: =IF(AND($B60<>"",$C60<>"Target state",$C60<>"Exception",$D60="Low",$E60="Low"),$A60&" "&$B60,"") | V60: =IF(AND($B60<>"",$C60<>"Target state",$C60<>"Exception",$D60="Low",$E60="Medium"),$A60&" "&$B60,"") | W60: =IF(AND($B60<>"",$C60<>"Target state",$C60<>"Exception",$D60="Low",$E60="High"),$A60&" "&$B60,"")
A61: ④ | B61: Comercia Developer Portal | C61: Non-target state | F61: Non-strategic documentation portal with SDKs and API explorer tools for the Spanish market | G61: =IF(OR($B61="",$D61="",$E61=""),"",IF(OR($C61="Target state",$C61="Exception"),"Out of scope",IF($D61="Low","No tranche",IF($E61="Low","Tranche 1",IF($E61="Medium","Tranche 2",IF($D61="High","Tranche 3","No tranche")))))) | O61: =IF(AND($B61<>"",$C61<>"Target state",$C61<>"Exception",$D61="High",$E61="Low"),$A61&" "&$B61,"") | P61: =IF(AND($B61<>"",$C61<>"Target state",$C61<>"Exception",$D61="High",$E61="Medium"),$A61&" "&$B61,"") | Q61: =IF(AND($B61<>"",$C61<>"Target state",$C61<>"Exception",$D61="High",$E61="High"),$A61&" "&$B61,"") | R61: =IF(AND($B61<>"",$C61<>"Target state",$C61<>"Exception",$D61="Medium",$E61="Low"),$A61&" "&$B61,"") | S61: =IF(AND($B61<>"",$C61<>"Target state",$C61<>"Exception",$D61="Medium",$E61="Medium"),$A61&" "&$B61,"") | T61: =IF(AND($B61<>"",$C61<>"Target state",$C61<>"Exception",$D61="Medium",$E61="High"),$A61&" "&$B61,"") | U61: =IF(AND($B61<>"",$C61<>"Target state",$C61<>"Exception",$D61="Low",$E61="Low"),$A61&" "&$B61,"") | V61: =IF(AND($B61<>"",$C61<>"Target state",$C61<>"Exception",$D61="Low",$E61="Medium"),$A61&" "&$B61,"") | W61: =IF(AND($B61<>"",$C61<>"Target state",$C61<>"Exception",$D61="Low",$E61="High"),$A61&" "&$B61,"")
A62: ⑤ | G62: =IF(OR($B62="",$D62="",$E62=""),"",IF(OR($C62="Target state",$C62="Exception"),"Out of scope",IF($D62="Low","No tranche",IF($E62="Low","Tranche 1",IF($E62="Medium","Tranche 2",IF($D62="High","Tranche 3","No tranche")))))) | J62: Medium | K62: ="Tranche 1"&CHAR(10)&_xlfn.TEXTJOIN(CHAR(10),TRUE,R$58:R$67) | L62: ="Tranche 2"&CHAR(10)&_xlfn.TEXTJOIN(CHAR(10),TRUE,S$58:S$67) | M62: =_xlfn.TEXTJOIN(CHAR(10),TRUE,T$58:T$67) | O62: =IF(AND($B62<>"",$C62<>"Target state",$C62<>"Exception",$D62="High",$E62="Low"),$A62&" "&$B62,"") | P62: =IF(AND($B62<>"",$C62<>"Target state",$C62<>"Exception",$D62="High",$E62="Medium"),$A62&" "&$B62,"") | Q62: =IF(AND($B62<>"",$C62<>"Target state",$C62<>"Exception",$D62="High",$E62="High"),$A62&" "&$B62,"") | R62: =IF(AND($B62<>"",$C62<>"Target state",$C62<>"Exception",$D62="Medium",$E62="Low"),$A62&" "&$B62,"") | S62: =IF(AND($B62<>"",$C62<>"Target state",$C62<>"Exception",$D62="Medium",$E62="Medium"),$A62&" "&$B62,"") | T62: =IF(AND($B62<>"",$C62<>"Target state",$C62<>"Exception",$D62="Medium",$E62="High"),$A62&" "&$B62,"") | U62: =IF(AND($B62<>"",$C62<>"Target state",$C62<>"Exception",$D62="Low",$E62="Low"),$A62&" "&$B62,"") | V62: =IF(AND($B62<>"",$C62<>"Target state",$C62<>"Exception",$D62="Low",$E62="Medium"),$A62&" "&$B62,"") | W62: =IF(AND($B62<>"",$C62<>"Target state",$C62<>"Exception",$D62="Low",$E62="High"),$A62&" "&$B62,"")
A63: ⑥ | G63: =IF(OR($B63="",$D63="",$E63=""),"",IF(OR($C63="Target state",$C63="Exception"),"Out of scope",IF($D63="Low","No tranche",IF($E63="Low","Tranche 1",IF($E63="Medium","Tranche 2",IF($D63="High","Tranche 3","No tranche")))))) | O63: =IF(AND($B63<>"",$C63<>"Target state",$C63<>"Exception",$D63="High",$E63="Low"),$A63&" "&$B63,"") | P63: =IF(AND($B63<>"",$C63<>"Target state",$C63<>"Exception",$D63="High",$E63="Medium"),$A63&" "&$B63,"") | Q63: =IF(AND($B63<>"",$C63<>"Target state",$C63<>"Exception",$D63="High",$E63="High"),$A63&" "&$B63,"") | R63: =IF(AND($B63<>"",$C63<>"Target state",$C63<>"Exception",$D63="Medium",$E63="Low"),$A63&" "&$B63,"") | S63: =IF(AND($B63<>"",$C63<>"Target state",$C63<>"Exception",$D63="Medium",$E63="Medium"),$A63&" "&$B63,"") | T63: =IF(AND($B63<>"",$C63<>"Target state",$C63<>"Exception",$D63="Medium",$E63="High"),$A63&" "&$B63,"") | U63: =IF(AND($B63<>"",$C63<>"Target state",$C63<>"Exception",$D63="Low",$E63="Low"),$A63&" "&$B63,"") | V63: =IF(AND($B63<>"",$C63<>"Target state",$C63<>"Exception",$D63="Low",$E63="Medium"),$A63&" "&$B63,"") | W63: =IF(AND($B63<>"",$C63<>"Target state",$C63<>"Exception",$D63="Low",$E63="High"),$A63&" "&$B63,"")
A64: ⑦ | G64: =IF(OR($B64="",$D64="",$E64=""),"",IF(OR($C64="Target state",$C64="Exception"),"Out of scope",IF($D64="Low","No tranche",IF($E64="Low","Tranche 1",IF($E64="Medium","Tranche 2",IF($D64="High","Tranche 3","No tranche")))))) | O64: =IF(AND($B64<>"",$C64<>"Target state",$C64<>"Exception",$D64="High",$E64="Low"),$A64&" "&$B64,"") | P64: =IF(AND($B64<>"",$C64<>"Target state",$C64<>"Exception",$D64="High",$E64="Medium"),$A64&" "&$B64,"") | Q64: =IF(AND($B64<>"",$C64<>"Target state",$C64<>"Exception",$D64="High",$E64="High"),$A64&" "&$B64,"") | R64: =IF(AND($B64<>"",$C64<>"Target state",$C64<>"Exception",$D64="Medium",$E64="Low"),$A64&" "&$B64,"") | S64: =IF(AND($B64<>"",$C64<>"Target state",$C64<>"Exception",$D64="Medium",$E64="Medium"),$A64&" "&$B64,"") | T64: =IF(AND($B64<>"",$C64<>"Target state",$C64<>"Exception",$D64="Medium",$E64="High"),$A64&" "&$B64,"") | U64: =IF(AND($B64<>"",$C64<>"Target state",$C64<>"Exception",$D64="Low",$E64="Low"),$A64&" "&$B64,"") | V64: =IF(AND($B64<>"",$C64<>"Target state",$C64<>"Exception",$D64="Low",$E64="Medium"),$A64&" "&$B64,"") | W64: =IF(AND($B64<>"",$C64<>"Target state",$C64<>"Exception",$D64="Low",$E64="High"),$A64&" "&$B64,"")
A65: ⑧ | G65: =IF(OR($B65="",$D65="",$E65=""),"",IF(OR($C65="Target state",$C65="Exception"),"Out of scope",IF($D65="Low","No tranche",IF($E65="Low","Tranche 1",IF($E65="Medium","Tranche 2",IF($D65="High","Tranche 3","No tranche")))))) | J65: Low | K65: =_xlfn.TEXTJOIN(CHAR(10),TRUE,U$58:U$67) | L65: =_xlfn.TEXTJOIN(CHAR(10),TRUE,V$58:V$67) | M65: =_xlfn.TEXTJOIN(CHAR(10),TRUE,W$58:W$67) | O65: =IF(AND($B65<>"",$C65<>"Target state",$C65<>"Exception",$D65="High",$E65="Low"),$A65&" "&$B65,"") | P65: =IF(AND($B65<>"",$C65<>"Target state",$C65<>"Exception",$D65="High",$E65="Medium"),$A65&" "&$B65,"") | Q65: =IF(AND($B65<>"",$C65<>"Target state",$C65<>"Exception",$D65="High",$E65="High"),$A65&" "&$B65,"") | R65: =IF(AND($B65<>"",$C65<>"Target state",$C65<>"Exception",$D65="Medium",$E65="Low"),$A65&" "&$B65,"") | S65: =IF(AND($B65<>"",$C65<>"Target state",$C65<>"Exception",$D65="Medium",$E65="Medium"),$A65&" "&$B65,"") | T65: =IF(AND($B65<>"",$C65<>"Target state",$C65<>"Exception",$D65="Medium",$E65="High"),$A65&" "&$B65,"") | U65: =IF(AND($B65<>"",$C65<>"Target state",$C65<>"Exception",$D65="Low",$E65="Low"),$A65&" "&$B65,"") | V65: =IF(AND($B65<>"",$C65<>"Target state",$C65<>"Exception",$D65="Low",$E65="Medium"),$A65&" "&$B65,"") | W65: =IF(AND($B65<>"",$C65<>"Target state",$C65<>"Exception",$D65="Low",$E65="High"),$A65&" "&$B65,"")
A66: ⑨ | G66: =IF(OR($B66="",$D66="",$E66=""),"",IF(OR($C66="Target state",$C66="Exception"),"Out of scope",IF($D66="Low","No tranche",IF($E66="Low","Tranche 1",IF($E66="Medium","Tranche 2",IF($D66="High","Tranche 3","No tranche")))))) | O66: =IF(AND($B66<>"",$C66<>"Target state",$C66<>"Exception",$D66="High",$E66="Low"),$A66&" "&$B66,"") | P66: =IF(AND($B66<>"",$C66<>"Target state",$C66<>"Exception",$D66="High",$E66="Medium"),$A66&" "&$B66,"") | Q66: =IF(AND($B66<>"",$C66<>"Target state",$C66<>"Exception",$D66="High",$E66="High"),$A66&" "&$B66,"") | R66: =IF(AND($B66<>"",$C66<>"Target state",$C66<>"Exception",$D66="Medium",$E66="Low"),$A66&" "&$B66,"") | S66: =IF(AND($B66<>"",$C66<>"Target state",$C66<>"Exception",$D66="Medium",$E66="Medium"),$A66&" "&$B66,"") | T66: =IF(AND($B66<>"",$C66<>"Target state",$C66<>"Exception",$D66="Medium",$E66="High"),$A66&" "&$B66,"") | U66: =IF(AND($B66<>"",$C66<>"Target state",$C66<>"Exception",$D66="Low",$E66="Low"),$A66&" "&$B66,"") | V66: =IF(AND($B66<>"",$C66<>"Target state",$C66<>"Exception",$D66="Low",$E66="Medium"),$A66&" "&$B66,"") | W66: =IF(AND($B66<>"",$C66<>"Target state",$C66<>"Exception",$D66="Low",$E66="High"),$A66&" "&$B66,"")
A67: ⑩ | G67: =IF(OR($B67="",$D67="",$E67=""),"",IF(OR($C67="Target state",$C67="Exception"),"Out of scope",IF($D67="Low","No tranche",IF($E67="Low","Tranche 1",IF($E67="Medium","Tranche 2",IF($D67="High","Tranche 3","No tranche")))))) | O67: =IF(AND($B67<>"",$C67<>"Target state",$C67<>"Exception",$D67="High",$E67="Low"),$A67&" "&$B67,"") | P67: =IF(AND($B67<>"",$C67<>"Target state",$C67<>"Exception",$D67="High",$E67="Medium"),$A67&" "&$B67,"") | Q67: =IF(AND($B67<>"",$C67<>"Target state",$C67<>"Exception",$D67="High",$E67="High"),$A67&" "&$B67,"") | R67: =IF(AND($B67<>"",$C67<>"Target state",$C67<>"Exception",$D67="Medium",$E67="Low"),$A67&" "&$B67,"") | S67: =IF(AND($B67<>"",$C67<>"Target state",$C67<>"Exception",$D67="Medium",$E67="Medium"),$A67&" "&$B67,"") | T67: =IF(AND($B67<>"",$C67<>"Target state",$C67<>"Exception",$D67="Medium",$E67="High"),$A67&" "&$B67,"") | U67: =IF(AND($B67<>"",$C67<>"Target state",$C67<>"Exception",$D67="Low",$E67="Low"),$A67&" "&$B67,"") | V67: =IF(AND($B67<>"",$C67<>"Target state",$C67<>"Exception",$D67="Low",$E67="Medium"),$A67&" "&$B67,"") | W67: =IF(AND($B67<>"",$C67<>"Target state",$C67<>"Exception",$D67="Low",$E67="High"),$A67&" "&$B67,"")
K68: Complexity
A72: Hosted Solutions | G72: =HYPERLINK("#'Single-in'!A4","▲ tracker") | K72: Assessment Outcome
A73: # | B73: Platform | C73: State | D73: Imperative to exit | E73: Exit complexity | F73: Supporting facts | G73: Tranche (auto) | K73: Low | L73: Medium | M73: High
A74: ① | G74: =IF(OR($B74="",$D74="",$E74=""),"",IF(OR($C74="Target state",$C74="Exception"),"Out of scope",IF($D74="Low","No tranche",IF($E74="Low","Tranche 1",IF($E74="Medium","Tranche 2",IF($D74="High","Tranche 3","No tranche")))))) | I74: Benefits | J74: High | K74: ="Tranche 1"&CHAR(10)&_xlfn.TEXTJOIN(CHAR(10),TRUE,O$74:O$83) | L74: ="Tranche 2"&CHAR(10)&_xlfn.TEXTJOIN(CHAR(10),TRUE,P$74:P$83) | M74: ="Tranche 3"&CHAR(10)&_xlfn.TEXTJOIN(CHAR(10),TRUE,Q$74:Q$83) | O74: =IF(AND($B74<>"",$C74<>"Target state",$C74<>"Exception",$D74="High",$E74="Low"),$A74&" "&$B74,"") | P74: =IF(AND($B74<>"",$C74<>"Target state",$C74<>"Exception",$D74="High",$E74="Medium"),$A74&" "&$B74,"") | Q74: =IF(AND($B74<>"",$C74<>"Target state",$C74<>"Exception",$D74="High",$E74="High"),$A74&" "&$B74,"") | R74: =IF(AND($B74<>"",$C74<>"Target state",$C74<>"Exception",$D74="Medium",$E74="Low"),$A74&" "&$B74,"") | S74: =IF(AND($B74<>"",$C74<>"Target state",$C74<>"Exception",$D74="Medium",$E74="Medium"),$A74&" "&$B74,"") | T74: =IF(AND($B74<>"",$C74<>"Target state",$C74<>"Exception",$D74="Medium",$E74="High"),$A74&" "&$B74,"") | U74: =IF(AND($B74<>"",$C74<>"Target state",$C74<>"Exception",$D74="Low",$E74="Low"),$A74&" "&$B74,"") | V74: =IF(AND($B74<>"",$C74<>"Target state",$C74<>"Exception",$D74="Low",$E74="Medium"),$A74&" "&$B74,"") | W74: =IF(AND($B74<>"",$C74<>"Target state",$C74<>"Exception",$D74="Low",$E74="High"),$A74&" "&$B74,"")
A75: ② | G75: =IF(OR($B75="",$D75="",$E75=""),"",IF(OR($C75="Target state",$C75="Exception"),"Out of scope",IF($D75="Low","No tranche",IF($E75="Low","Tranche 1",IF($E75="Medium","Tranche 2",IF($D75="High","Tranche 3","No tranche")))))) | O75: =IF(AND($B75<>"",$C75<>"Target state",$C75<>"Exception",$D75="High",$E75="Low"),$A75&" "&$B75,"") | P75: =IF(AND($B75<>"",$C75<>"Target state",$C75<>"Exception",$D75="High",$E75="Medium"),$A75&" "&$B75,"") | Q75: =IF(AND($B75<>"",$C75<>"Target state",$C75<>"Exception",$D75="High",$E75="High"),$A75&" "&$B75,"") | R75: =IF(AND($B75<>"",$C75<>"Target state",$C75<>"Exception",$D75="Medium",$E75="Low"),$A75&" "&$B75,"") | S75: =IF(AND($B75<>"",$C75<>"Target state",$C75<>"Exception",$D75="Medium",$E75="Medium"),$A75&" "&$B75,"") | T75: =IF(AND($B75<>"",$C75<>"Target state",$C75<>"Exception",$D75="Medium",$E75="High"),$A75&" "&$B75,"") | U75: =IF(AND($B75<>"",$C75<>"Target state",$C75<>"Exception",$D75="Low",$E75="Low"),$A75&" "&$B75,"") | V75: =IF(AND($B75<>"",$C75<>"Target state",$C75<>"Exception",$D75="Low",$E75="Medium"),$A75&" "&$B75,"") | W75: =IF(AND($B75<>"",$C75<>"Target state",$C75<>"Exception",$D75="Low",$E75="High"),$A75&" "&$B75,"")
A76: ③ | G76: =IF(OR($B76="",$D76="",$E76=""),"",IF(OR($C76="Target state",$C76="Exception"),"Out of scope",IF($D76="Low","No tranche",IF($E76="Low","Tranche 1",IF($E76="Medium","Tranche 2",IF($D76="High","Tranche 3","No tranche")))))) | O76: =IF(AND($B76<>"",$C76<>"Target state",$C76<>"Exception",$D76="High",$E76="Low"),$A76&" "&$B76,"") | P76: =IF(AND($B76<>"",$C76<>"Target state",$C76<>"Exception",$D76="High",$E76="Medium"),$A76&" "&$B76,"") | Q76: =IF(AND($B76<>"",$C76<>"Target state",$C76<>"Exception",$D76="High",$E76="High"),$A76&" "&$B76,"") | R76: =IF(AND($B76<>"",$C76<>"Target state",$C76<>"Exception",$D76="Medium",$E76="Low"),$A76&" "&$B76,"") | S76: =IF(AND($B76<>"",$C76<>"Target state",$C76<>"Exception",$D76="Medium",$E76="Medium"),$A76&" "&$B76,"") | T76: =IF(AND($B76<>"",$C76<>"Target state",$C76<>"Exception",$D76="Medium",$E76="High"),$A76&" "&$B76,"") | U76: =IF(AND($B76<>"",$C76<>"Target state",$C76<>"Exception",$D76="Low",$E76="Low"),$A76&" "&$B76,"") | V76: =IF(AND($B76<>"",$C76<>"Target state",$C76<>"Exception",$D76="Low",$E76="Medium"),$A76&" "&$B76,"") | W76: =IF(AND($B76<>"",$C76<>"Target state",$C76<>"Exception",$D76="Low",$E76="High"),$A76&" "&$B76,"")
A77: ④ | G77: =IF(OR($B77="",$D77="",$E77=""),"",IF(OR($C77="Target state",$C77="Exception"),"Out of scope",IF($D77="Low","No tranche",IF($E77="Low","Tranche 1",IF($E77="Medium","Tranche 2",IF($D77="High","Tranche 3","No tranche")))))) | O77: =IF(AND($B77<>"",$C77<>"Target state",$C77<>"Exception",$D77="High",$E77="Low"),$A77&" "&$B77,"") | P77: =IF(AND($B77<>"",$C77<>"Target state",$C77<>"Exception",$D77="High",$E77="Medium"),$A77&" "&$B77,"") | Q77: =IF(AND($B77<>"",$C77<>"Target state",$C77<>"Exception",$D77="High",$E77="High"),$A77&" "&$B77,"") | R77: =IF(AND($B77<>"",$C77<>"Target state",$C77<>"Exception",$D77="Medium",$E77="Low"),$A77&" "&$B77,"") | S77: =IF(AND($B77<>"",$C77<>"Target state",$C77<>"Exception",$D77="Medium",$E77="Medium"),$A77&" "&$B77,"") | T77: =IF(AND($B77<>"",$C77<>"Target state",$C77<>"Exception",$D77="Medium",$E77="High"),$A77&" "&$B77,"") | U77: =IF(AND($B77<>"",$C77<>"Target state",$C77<>"Exception",$D77="Low",$E77="Low"),$A77&" "&$B77,"") | V77: =IF(AND($B77<>"",$C77<>"Target state",$C77<>"Exception",$D77="Low",$E77="Medium"),$A77&" "&$B77,"") | W77: =IF(AND($B77<>"",$C77<>"Target state",$C77<>"Exception",$D77="Low",$E77="High"),$A77&" "&$B77,"")
A78: ⑤ | G78: =IF(OR($B78="",$D78="",$E78=""),"",IF(OR($C78="Target state",$C78="Exception"),"Out of scope",IF($D78="Low","No tranche",IF($E78="Low","Tranche 1",IF($E78="Medium","Tranche 2",IF($D78="High","Tranche 3","No tranche")))))) | J78: Medium | K78: ="Tranche 1"&CHAR(10)&_xlfn.TEXTJOIN(CHAR(10),TRUE,R$74:R$83) | L78: ="Tranche 2"&CHAR(10)&_xlfn.TEXTJOIN(CHAR(10),TRUE,S$74:S$83) | M78: =_xlfn.TEXTJOIN(CHAR(10),TRUE,T$74:T$83) | O78: =IF(AND($B78<>"",$C78<>"Target state",$C78<>"Exception",$D78="High",$E78="Low"),$A78&" "&$B78,"") | P78: =IF(AND($B78<>"",$C78<>"Target state",$C78<>"Exception",$D78="High",$E78="Medium"),$A78&" "&$B78,"") | Q78: =IF(AND($B78<>"",$C78<>"Target state",$C78<>"Exception",$D78="High",$E78="High"),$A78&" "&$B78,"") | R78: =IF(AND($B78<>"",$C78<>"Target state",$C78<>"Exception",$D78="Medium",$E78="Low"),$A78&" "&$B78,"") | S78: =IF(AND($B78<>"",$C78<>"Target state",$C78<>"Exception",$D78="Medium",$E78="Medium"),$A78&" "&$B78,"") | T78: =IF(AND($B78<>"",$C78<>"Target state",$C78<>"Exception",$D78="Medium",$E78="High"),$A78&" "&$B78,"") | U78: =IF(AND($B78<>"",$C78<>"Target state",$C78<>"Exception",$D78="Low",$E78="Low"),$A78&" "&$B78,"") | V78: =IF(AND($B78<>"",$C78<>"Target state",$C78<>"Exception",$D78="Low",$E78="Medium"),$A78&" "&$B78,"") | W78: =IF(AND($B78<>"",$C78<>"Target state",$C78<>"Exception",$D78="Low",$E78="High"),$A78&" "&$B78,"")
A79: ⑥ | G79: =IF(OR($B79="",$D79="",$E79=""),"",IF(OR($C79="Target state",$C79="Exception"),"Out of scope",IF($D79="Low","No tranche",IF($E79="Low","Tranche 1",IF($E79="Medium","Tranche 2",IF($D79="High","Tranche 3","No tranche")))))) | O79: =IF(AND($B79<>"",$C79<>"Target state",$C79<>"Exception",$D79="High",$E79="Low"),$A79&" "&$B79,"") | P79: =IF(AND($B79<>"",$C79<>"Target state",$C79<>"Exception",$D79="High",$E79="Medium"),$A79&" "&$B79,"") | Q79: =IF(AND($B79<>"",$C79<>"Target state",$C79<>"Exception",$D79="High",$E79="High"),$A79&" "&$B79,"") | R79: =IF(AND($B79<>"",$C79<>"Target state",$C79<>"Exception",$D79="Medium",$E79="Low"),$A79&" "&$B79,"") | S79: =IF(AND($B79<>"",$C79<>"Target state",$C79<>"Exception",$D79="Medium",$E79="Medium"),$A79&" "&$B79,"") | T79: =IF(AND($B79<>"",$C79<>"Target state",$C79<>"Exception",$D79="Medium",$E79="High"),$A79&" "&$B79,"") | U79: =IF(AND($B79<>"",$C79<>"Target state",$C79<>"Exception",$D79="Low",$E79="Low"),$A79&" "&$B79,"") | V79: =IF(AND($B79<>"",$C79<>"Target state",$C79<>"Exception",$D79="Low",$E79="Medium"),$A79&" "&$B79,"") | W79: =IF(AND($B79<>"",$C79<>"Target state",$C79<>"Exception",$D79="Low",$E79="High"),$A79&" "&$B79,"")
A80: ⑦ | G80: =IF(OR($B80="",$D80="",$E80=""),"",IF(OR($C80="Target state",$C80="Exception"),"Out of scope",IF($D80="Low","No tranche",IF($E80="Low","Tranche 1",IF($E80="Medium","Tranche 2",IF($D80="High","Tranche 3","No tranche")))))) | O80: =IF(AND($B80<>"",$C80<>"Target state",$C80<>"Exception",$D80="High",$E80="Low"),$A80&" "&$B80,"") | P80: =IF(AND($B80<>"",$C80<>"Target state",$C80<>"Exception",$D80="High",$E80="Medium"),$A80&" "&$B80,"") | Q80: =IF(AND($B80<>"",$C80<>"Target state",$C80<>"Exception",$D80="High",$E80="High"),$A80&" "&$B80,"") | R80: =IF(AND($B80<>"",$C80<>"Target state",$C80<>"Exception",$D80="Medium",$E80="Low"),$A80&" "&$B80,"") | S80: =IF(AND($B80<>"",$C80<>"Target state",$C80<>"Exception",$D80="Medium",$E80="Medium"),$A80&" "&$B80,"") | T80: =IF(AND($B80<>"",$C80<>"Target state",$C80<>"Exception",$D80="Medium",$E80="High"),$A80&" "&$B80,"") | U80: =IF(AND($B80<>"",$C80<>"Target state",$C80<>"Exception",$D80="Low",$E80="Low"),$A80&" "&$B80,"") | V80: =IF(AND($B80<>"",$C80<>"Target state",$C80<>"Exception",$D80="Low",$E80="Medium"),$A80&" "&$B80,"") | W80: =IF(AND($B80<>"",$C80<>"Target state",$C80<>"Exception",$D80="Low",$E80="High"),$A80&" "&$B80,"")
A81: ⑧ | G81: =IF(OR($B81="",$D81="",$E81=""),"",IF(OR($C81="Target state",$C81="Exception"),"Out of scope",IF($D81="Low","No tranche",IF($E81="Low","Tranche 1",IF($E81="Medium","Tranche 2",IF($D81="High","Tranche 3","No tranche")))))) | J81: Low | K81: =_xlfn.TEXTJOIN(CHAR(10),TRUE,U$74:U$83) | L81: =_xlfn.TEXTJOIN(CHAR(10),TRUE,V$74:V$83) | M81: =_xlfn.TEXTJOIN(CHAR(10),TRUE,W$74:W$83) | O81: =IF(AND($B81<>"",$C81<>"Target state",$C81<>"Exception",$D81="High",$E81="Low"),$A81&" "&$B81,"") | P81: =IF(AND($B81<>"",$C81<>"Target state",$C81<>"Exception",$D81="High",$E81="Medium"),$A81&" "&$B81,"") | Q81: =IF(AND($B81<>"",$C81<>"Target state",$C81<>"Exception",$D81="High",$E81="High"),$A81&" "&$B81,"") | R81: =IF(AND($B81<>"",$C81<>"Target state",$C81<>"Exception",$D81="Medium",$E81="Low"),$A81&" "&$B81,"") | S81: =IF(AND($B81<>"",$C81<>"Target state",$C81<>"Exception",$D81="Medium",$E81="Medium"),$A81&" "&$B81,"") | T81: =IF(AND($B81<>"",$C81<>"Target state",$C81<>"Exception",$D81="Medium",$E81="High"),$A81&" "&$B81,"") | U81: =IF(AND($B81<>"",$C81<>"Target state",$C81<>"Exception",$D81="Low",$E81="Low"),$A81&" "&$B81,"") | V81: =IF(AND($B81<>"",$C81<>"Target state",$C81<>"Exception",$D81="Low",$E81="Medium"),$A81&" "&$B81,"") | W81: =IF(AND($B81<>"",$C81<>"Target state",$C81<>"Exception",$D81="Low",$E81="High"),$A81&" "&$B81,"")
A82: ⑨ | G82: =IF(OR($B82="",$D82="",$E82=""),"",IF(OR($C82="Target state",$C82="Exception"),"Out of scope",IF($D82="Low","No tranche",IF($E82="Low","Tranche 1",IF($E82="Medium","Tranche 2",IF($D82="High","Tranche 3","No tranche")))))) | O82: =IF(AND($B82<>"",$C82<>"Target state",$C82<>"Exception",$D82="High",$E82="Low"),$A82&" "&$B82,"") | P82: =IF(AND($B82<>"",$C82<>"Target state",$C82<>"Exception",$D82="High",$E82="Medium"),$A82&" "&$B82,"") | Q82: =IF(AND($B82<>"",$C82<>"Target state",$C82<>"Exception",$D82="High",$E82="High"),$A82&" "&$B82,"") | R82: =IF(AND($B82<>"",$C82<>"Target state",$C82<>"Exception",$D82="Medium",$E82="Low"),$A82&" "&$B82,"") | S82: =IF(AND($B82<>"",$C82<>"Target state",$C82<>"Exception",$D82="Medium",$E82="Medium"),$A82&" "&$B82,"") | T82: =IF(AND($B82<>"",$C82<>"Target state",$C82<>"Exception",$D82="Medium",$E82="High"),$A82&" "&$B82,"") | U82: =IF(AND($B82<>"",$C82<>"Target state",$C82<>"Exception",$D82="Low",$E82="Low"),$A82&" "&$B82,"") | V82: =IF(AND($B82<>"",$C82<>"Target state",$C82<>"Exception",$D82="Low",$E82="Medium"),$A82&" "&$B82,"") | W82: =IF(AND($B82<>"",$C82<>"Target state",$C82<>"Exception",$D82="Low",$E82="High"),$A82&" "&$B82,"")
A83: ⑩ | G83: =IF(OR($B83="",$D83="",$E83=""),"",IF(OR($C83="Target state",$C83="Exception"),"Out of scope",IF($D83="Low","No tranche",IF($E83="Low","Tranche 1",IF($E83="Medium","Tranche 2",IF($D83="High","Tranche 3","No tranche")))))) | O83: =IF(AND($B83<>"",$C83<>"Target state",$C83<>"Exception",$D83="High",$E83="Low"),$A83&" "&$B83,"") | P83: =IF(AND($B83<>"",$C83<>"Target state",$C83<>"Exception",$D83="High",$E83="Medium"),$A83&" "&$B83,"") | Q83: =IF(AND($B83<>"",$C83<>"Target state",$C83<>"Exception",$D83="High",$E83="High"),$A83&" "&$B83,"") | R83: =IF(AND($B83<>"",$C83<>"Target state",$C83<>"Exception",$D83="Medium",$E83="Low"),$A83&" "&$B83,"") | S83: =IF(AND($B83<>"",$C83<>"Target state",$C83<>"Exception",$D83="Medium",$E83="Medium"),$A83&" "&$B83,"") | T83: =IF(AND($B83<>"",$C83<>"Target state",$C83<>"Exception",$D83="Medium",$E83="High"),$A83&" "&$B83,"") | U83: =IF(AND($B83<>"",$C83<>"Target state",$C83<>"Exception",$D83="Low",$E83="Low"),$A83&" "&$B83,"") | V83: =IF(AND($B83<>"",$C83<>"Target state",$C83<>"Exception",$D83="Low",$E83="Medium"),$A83&" "&$B83,"") | W83: =IF(AND($B83<>"",$C83<>"Target state",$C83<>"Exception",$D83="Low",$E83="High"),$A83&" "&$B83,"")
K84: Complexity
A88: Unified Proposition | G88: =HYPERLINK("#'Single-in'!A4","▲ tracker") | K88: Assessment Outcome
A89: # | B89: Platform | C89: State | D89: Imperative to exit | E89: Exit complexity | F89: Supporting facts | G89: Tranche (auto) | K89: Low | L89: Medium | M89: High
A90: ① | G90: =IF(OR($B90="",$D90="",$E90=""),"",IF(OR($C90="Target state",$C90="Exception"),"Out of scope",IF($D90="Low","No tranche",IF($E90="Low","Tranche 1",IF($E90="Medium","Tranche 2",IF($D90="High","Tranche 3","No tranche")))))) | I90: Benefits | J90: High | K90: ="Tranche 1"&CHAR(10)&_xlfn.TEXTJOIN(CHAR(10),TRUE,O$90:O$99) | L90: ="Tranche 2"&CHAR(10)&_xlfn.TEXTJOIN(CHAR(10),TRUE,P$90:P$99) | M90: ="Tranche 3"&CHAR(10)&_xlfn.TEXTJOIN(CHAR(10),TRUE,Q$90:Q$99) | O90: =IF(AND($B90<>"",$C90<>"Target state",$C90<>"Exception",$D90="High",$E90="Low"),$A90&" "&$B90,"") | P90: =IF(AND($B90<>"",$C90<>"Target state",$C90<>"Exception",$D90="High",$E90="Medium"),$A90&" "&$B90,"") | Q90: =IF(AND($B90<>"",$C90<>"Target state",$C90<>"Exception",$D90="High",$E90="High"),$A90&" "&$B90,"") | R90: =IF(AND($B90<>"",$C90<>"Target state",$C90<>"Exception",$D90="Medium",$E90="Low"),$A90&" "&$B90,"") | S90: =IF(AND($B90<>"",$C90<>"Target state",$C90<>"Exception",$D90="Medium",$E90="Medium"),$A90&" "&$B90,"") | T90: =IF(AND($B90<>"",$C90<>"Target state",$C90<>"Exception",$D90="Medium",$E90="High"),$A90&" "&$B90,"") | U90: =IF(AND($B90<>"",$C90<>"Target state",$C90<>"Exception",$D90="Low",$E90="Low"),$A90&" "&$B90,"") | V90: =IF(AND($B90<>"",$C90<>"Target state",$C90<>"Exception",$D90="Low",$E90="Medium"),$A90&" "&$B90,"") | W90: =IF(AND($B90<>"",$C90<>"Target state",$C90<>"Exception",$D90="Low",$E90="High"),$A90&" "&$B90,"")
A91: ② | G91: =IF(OR($B91="",$D91="",$E91=""),"",IF(OR($C91="Target state",$C91="Exception"),"Out of scope",IF($D91="Low","No tranche",IF($E91="Low","Tranche 1",IF($E91="Medium","Tranche 2",IF($D91="High","Tranche 3","No tranche")))))) | O91: =IF(AND($B91<>"",$C91<>"Target state",$C91<>"Exception",$D91="High",$E91="Low"),$A91&" "&$B91,"") | P91: =IF(AND($B91<>"",$C91<>"Target state",$C91<>"Exception",$D91="High",$E91="Medium"),$A91&" "&$B91,"") | Q91: =IF(AND($B91<>"",$C91<>"Target state",$C91<>"Exception",$D91="High",$E91="High"),$A91&" "&$B91,"") | R91: =IF(AND($B91<>"",$C91<>"Target state",$C91<>"Exception",$D91="Medium",$E91="Low"),$A91&" "&$B91,"") | S91: =IF(AND($B91<>"",$C91<>"Target state",$C91<>"Exception",$D91="Medium",$E91="Medium"),$A91&" "&$B91,"") | T91: =IF(AND($B91<>"",$C91<>"Target state",$C91<>"Exception",$D91="Medium",$E91="High"),$A91&" "&$B91,"") | U91: =IF(AND($B91<>"",$C91<>"Target state",$C91<>"Exception",$D91="Low",$E91="Low"),$A91&" "&$B91,"") | V91: =IF(AND($B91<>"",$C91<>"Target state",$C91<>"Exception",$D91="Low",$E91="Medium"),$A91&" "&$B91,"") | W91: =IF(AND($B91<>"",$C91<>"Target state",$C91<>"Exception",$D91="Low",$E91="High"),$A91&" "&$B91,"")
A92: ③ | G92: =IF(OR($B92="",$D92="",$E92=""),"",IF(OR($C92="Target state",$C92="Exception"),"Out of scope",IF($D92="Low","No tranche",IF($E92="Low","Tranche 1",IF($E92="Medium","Tranche 2",IF($D92="High","Tranche 3","No tranche")))))) | O92: =IF(AND($B92<>"",$C92<>"Target state",$C92<>"Exception",$D92="High",$E92="Low"),$A92&" "&$B92,"") | P92: =IF(AND($B92<>"",$C92<>"Target state",$C92<>"Exception",$D92="High",$E92="Medium"),$A92&" "&$B92,"") | Q92: =IF(AND($B92<>"",$C92<>"Target state",$C92<>"Exception",$D92="High",$E92="High"),$A92&" "&$B92,"") | R92: =IF(AND($B92<>"",$C92<>"Target state",$C92<>"Exception",$D92="Medium",$E92="Low"),$A92&" "&$B92,"") | S92: =IF(AND($B92<>"",$C92<>"Target state",$C92<>"Exception",$D92="Medium",$E92="Medium"),$A92&" "&$B92,"") | T92: =IF(AND($B92<>"",$C92<>"Target state",$C92<>"Exception",$D92="Medium",$E92="High"),$A92&" "&$B92,"") | U92: =IF(AND($B92<>"",$C92<>"Target state",$C92<>"Exception",$D92="Low",$E92="Low"),$A92&" "&$B92,"") | V92: =IF(AND($B92<>"",$C92<>"Target state",$C92<>"Exception",$D92="Low",$E92="Medium"),$A92&" "&$B92,"") | W92: =IF(AND($B92<>"",$C92<>"Target state",$C92<>"Exception",$D92="Low",$E92="High"),$A92&" "&$B92,"")
A93: ④ | G93: =IF(OR($B93="",$D93="",$E93=""),"",IF(OR($C93="Target state",$C93="Exception"),"Out of scope",IF($D93="Low","No tranche",IF($E93="Low","Tranche 1",IF($E93="Medium","Tranche 2",IF($D93="High","Tranche 3","No tranche")))))) | O93: =IF(AND($B93<>"",$C93<>"Target state",$C93<>"Exception",$D93="High",$E93="Low"),$A93&" "&$B93,"") | P93: =IF(AND($B93<>"",$C93<>"Target state",$C93<>"Exception",$D93="High",$E93="Medium"),$A93&" "&$B93,"") | Q93: =IF(AND($B93<>"",$C93<>"Target state",$C93<>"Exception",$D93="High",$E93="High"),$A93&" "&$B93,"") | R93: =IF(AND($B93<>"",$C93<>"Target state",$C93<>"Exception",$D93="Medium",$E93="Low"),$A93&" "&$B93,"") | S93: =IF(AND($B93<>"",$C93<>"Target state",$C93<>"Exception",$D93="Medium",$E93="Medium"),$A93&" "&$B93,"") | T93: =IF(AND($B93<>"",$C93<>"Target state",$C93<>"Exception",$D93="Medium",$E93="High"),$A93&" "&$B93,"") | U93: =IF(AND($B93<>"",$C93<>"Target state",$C93<>"Exception",$D93="Low",$E93="Low"),$A93&" "&$B93,"") | V93: =IF(AND($B93<>"",$C93<>"Target state",$C93<>"Exception",$D93="Low",$E93="Medium"),$A93&" "&$B93,"") | W93: =IF(AND($B93<>"",$C93<>"Target state",$C93<>"Exception",$D93="Low",$E93="High"),$A93&" "&$B93,"")
A94: ⑤ | G94: =IF(OR($B94="",$D94="",$E94=""),"",IF(OR($C94="Target state",$C94="Exception"),"Out of scope",IF($D94="Low","No tranche",IF($E94="Low","Tranche 1",IF($E94="Medium","Tranche 2",IF($D94="High","Tranche 3","No tranche")))))) | J94: Medium | K94: ="Tranche 1"&CHAR(10)&_xlfn.TEXTJOIN(CHAR(10),TRUE,R$90:R$99) | L94: ="Tranche 2"&CHAR(10)&_xlfn.TEXTJOIN(CHAR(10),TRUE,S$90:S$99) | M94: =_xlfn.TEXTJOIN(CHAR(10),TRUE,T$90:T$99) | O94: =IF(AND($B94<>"",$C94<>"Target state",$C94<>"Exception",$D94="High",$E94="Low"),$A94&" "&$B94,"") | P94: =IF(AND($B94<>"",$C94<>"Target state",$C94<>"Exception",$D94="High",$E94="Medium"),$A94&" "&$B94,"") | Q94: =IF(AND($B94<>"",$C94<>"Target state",$C94<>"Exception",$D94="High",$E94="High"),$A94&" "&$B94,"") | R94: =IF(AND($B94<>"",$C94<>"Target state",$C94<>"Exception",$D94="Medium",$E94="Low"),$A94&" "&$B94,"") | S94: =IF(AND($B94<>"",$C94<>"Target state",$C94<>"Exception",$D94="Medium",$E94="Medium"),$A94&" "&$B94,"") | T94: =IF(AND($B94<>"",$C94<>"Target state",$C94<>"Exception",$D94="Medium",$E94="High"),$A94&" "&$B94,"") | U94: =IF(AND($B94<>"",$C94<>"Target state",$C94<>"Exception",$D94="Low",$E94="Low"),$A94&" "&$B94,"") | V94: =IF(AND($B94<>"",$C94<>"Target state",$C94<>"Exception",$D94="Low",$E94="Medium"),$A94&" "&$B94,"") | W94: =IF(AND($B94<>"",$C94<>"Target state",$C94<>"Exception",$D94="Low",$E94="High"),$A94&" "&$B94,"")
